Workbook

Sheet 汇总
B2: 业绩奖金表（一人可多条，需写清类别）
B3: 序号 | C3: 机构 | D3: 年月 | E3: 工号 | F3: 姓名 | G3: 部门 | H3: 薪资项目 | I3: 金额
B4: 1 | C4: 北京中心 | D4: 2025.06 | E4: 238256 | F4: 赵星火 | G4: A级学习顾问 | H4: 月度绩效 | I4: =顾问绩效!R4 -> 800
B5: 2 | C5: 北京中心 | D5: 2025.06 | E5: 238256 | F5: 赵星火 | G5: A级学习顾问 | H5: 顾问签约奖金 | I5: =业绩汇总表!M8 -> 6519.6664
B6: 3 | C6: 北京中心 | D6: 2025.06 | E6: 238256 | F6: 赵星火 | G6: A级学习顾问 | H6: 组长绩效 | I6: 0
B7: 4 | C7: 北京中心 | D7: 2025.06 | E7: 341422 | F7: 谭悦 | G7: B级学习顾问 | H7: 月度绩效 | I7: =顾问绩效!R5 -> 2000
B8: 5 | C8: 北京中心 | D8: 2025.06 | E8: 341422 | F8: 谭悦 | G8: B级学习顾问 | H8: 顾问签约奖金 | I8: =业绩汇总表!M7 -> 38700.501
B9: 6 | C9: 北京中心 | D9: 2025.06 | E9: 341422 | F9: 谭悦 | G9: B级学习顾问 | H9: 组长绩效 | I9: 0

Sheet 业绩汇总表
B5: 2025.06个性化顾问业绩
B6: 序号 | C6: 顾问姓名 | D6: 月度目标 | E6: 地面业绩 | F6: 网课代售业绩 | G6: 业绩合计 | H6: 线下退费 | I6: 网课退费 | J6: 退费合计 | K6: 综合业绩 | L6: 完成率
B7: 1 | C7: 谭悦 | D7: 1100000 | E7: =GETPIVOTDATA("学费",'91签约明细'!$B$2,"代售标签",,"签约单录入人","谭悦") -> 1468317.2 | F7: =GETPIVOTDATA("学费",'91签约明细'!$B$2,"代售标签","在线网课","签约单录入人","谭悦") -> 41749.7 | G7: =E7+F7 -> 1510066.9 | H7: ='退费（取自钉钉客服退费表单）'!X19 -> 220050.2 | I7: 0 | J7: =H7+I7 -> 220050.2 | K7: =G7-J7 -> 1290016.7 | L7: =K7/D7 -> 1.1727425 | M7: =K7*3% -> 38700.501
B8: 2 | C8: 星火 | D8: 1150000 | E8: =GETPIVOTDATA("学费",'91签约明细'!$B$2,"代售标签",,"签约单录入人","赵星火") -> 922880.8 | F8: =GETPIVOTDATA("学费",'91签约明细'!$B$2,"代售标签","在线网课","签约单录入人","赵星火") -> 67148.9 | G8: =E8+F8 -> 990029.7 | H8: =SUM('退费（取自钉钉客服退费表单）'!X21:X34) -> 166607.4 | I8: ='退费（取自钉钉客服退费表单）'!X35 -> 8464 | J8: =H8+I8 -> 175071.4 | K8: =G8-J8 -> 814958.3 | L8: =K8/D8 -> 0.70865939 | M8: =K8*0.008 -> 6519.6664
B9: 合计 | D9: =SUM(D7:D8) -> 2250000 | E9: =SUM(E7:E8) -> 2391198 | F9: =SUM(F7:F8) -> 108898.6 | G9: =E9+F9 -> 2500096.6 | H9: =SUM(H7:H8) -> 386657.6 | I9: =SUM(I7:I8) -> 8464 | J9: =H9+I9 -> 395121.6 | K9: =G9-J9 -> 2104975 | L9: =K9/D9 -> 0.93554444

Sheet 数据表1
A1: 提交日期 | B1: 您所办理的业务类型 | C1: OA流水号 | D1: 学管姓名 | E1: 学管是否代办 | F1: 顾问姓名 | G1: 顾问是否代办 | H1: 91系统-最新报名二级渠道 | I1: 原班所属项目 | J1: 新报入班级所属项目 | K1: 退费阶段 | L1: 退费一级原因（开课前） | M1: 退费一级原因 (开课后) | N1: 退费二级原因（专业课师资匹配原因） | O1: 退费二级原因（学员意愿转变_开课前） | P1: 退费二级原因（计划冲突_开课前） | Q1: 退费二级原因（中心原因_开课前） | R1: 退费二级原因（签约话术） | S1: 退费二级原因（教师） | T1: 退费二级原因（教学） | U1: 退费二级原因（课程安排） | V1: 退费二级原因（配套服务） | W1: 退费二级原因（配套学习设施） | X1: 退费二级原因（中心原因_开课后） | Y1: 退费二级原因（计划冲突_开课后） | Z1: 退费二级原因（学员意愿转变_开课后） | AA1: 退费三级原因（完全匹配不上）-院校、学院、专业、专业课代码及名称 | AB1: 退费详细原因说明（与OA退费详细说明保持一致） | AC1: 预计报名新班学费金额 | AD1: 转班金额（请学管填写所在班级实际金额） | AE1: 转班详细原因说明 | AF1: 提交时间 | AG1: 提交人 | AH1: 退费类型 | AI1: 学员姓名 | AJ1: 学员编码 | AK1: 退费金额 | AL1: 办理日期-客服 | AM1: 退费方式-客服 | AN1: 需要跟进的顾问/学管 | AO1: 退费/转班特殊情况备注（若需要学管提供银行卡信息，可将需求填写在此处）-客服 | AP1: 是否完成退费/转班-客服 | AQ1: 父记录 | AR1: 父记录
A2: 2025/05/28 | B2: 退费 | C2: 18649504 | D2: 郑雪新 | F2: 钱雪冰 | H2: 巨量广告 | I2: 集训营项目 | K2: 开课后退费 | M2: 学员意愿转变_开课后 | Z2: 个人身体原因无法承受高强度学习 | AB2: 刘浩宇BJWY3212612620自报到后提出了3次退费，先后跟妈妈共同沟通挽单无效；主要是自报到后睡眠效果不好，经济上感觉家里有压力，最终执意回家先备考（7-8月份还有一个专业课面授班）挽单失败，强冲阶段的费用明细： 1】KYJS25006A0079 KYJS25006A 26考研数学全年集训营（强冲）课前全额退15860 2】KYJY25006A0061 KYJY25006A 26考研英语全年集训营（强冲/英语一）课前全额退17870 3】KYJZ25006A0070 KYJZ25006A 26考研政治全年集训营（强冲）课前全额退12500 | AF2: 2025-06-30 | AG2: 郑雪新 | AH2: 真实产生的退费 | AI2: 刘浩宇 | AJ2: BJWY3212612620 | AK2: 46230 | AL2: 2025/06/18 | AM2: 微信共退90521 [图片] [图片] | AP2: TRUE
A3: 2025/05/28 | B3: 退费 | C3: 18649547 | D3: 郑雪新 | F3: 钱雪冰 | H3: 巨量广告 | I3: 集训营项目 | K3: 开课后退费 | M3: 学员意愿转变_开课后 | Z3: 个人身体原因无法承受高强度学习 | AB3: 刘浩宇BJWY3212612620自报到后提出了3次退费，先后跟妈妈共同沟通挽单无效；主要是自报到后睡眠效果不好，经济上感觉家里有压力，最终执意回家先备考（7-8月份还有一个专业课面授班）挽单失败 KYJY250070042 KYJY25007 26考研英语全年集训营（基础/四月）实缴13070--总课时58；课耗22；恋练有词88元--扣费：（13870/58*22）+88=5349.0--退还：13070-5349=7721.0 | AF3: 2025-06-30 | AG3: 郑雪新 | AH3: 真实产生的退费 | AI3: 刘浩宇 | AJ3: BJWY3212612620 | AK3: 7721 | AL3: 2025/06/18 | AM3: 微信共退90521 [图片] [图片] | AP3: TRUE
A4: 2025/05/28 | B4: 退费 | C4: 18649542 | D4: 郑雪新 | F4: 钱雪冰 | H4: 巨量广告 | I4: 集训营项目 | K4: 开课后退费 | M4: 学员意愿转变_开课后 | Z4: 个人身体原因无法承受高强度学习 | AB4: 刘浩宇BJWY3212612620自报到后提出了3次退费，先后跟妈妈共同沟通挽单无效；主要是自报到后睡眠效果不好，经济上感觉家里有压力，最终执意回家先备考（7-8月份还有一个专业课面授班）挽单失败 KYJS250070026 KYJS25007 26考研数学全年集训营（基础/四月）实缴7670--总课时52；课耗16；资料费43.8元--扣费：（8340/52*16）+43.8=2610.0--退还：7670-2610=5060.0 | AF4: 2025-06-30 | AG4: 郑雪新 | AH4: 真实产生的退费 | AI4: 刘浩宇 | AJ4: BJWY3212612620 | AK4: 5060 | AL4: 2025/06/18 | AM4: 微信共退90521 [图片] [图片] | AP4: TRUE
A5: 2025/05/28 | B5: 退费 | C5: 18649549 | D5: 郑雪新 | F5: 钱雪冰 | H5: 巨量广告 | I5: 集训营项目 | K5: 开课后退费 | M5: 学员意愿转变_开课后 | Z5: 个人身体原因无法承受高强度学习 | AB5: 刘浩宇BJWY3212612620自报到后提出了3次退费，先后跟妈妈共同沟通挽单无效；主要是自报到后睡眠效果不好，经济上感觉家里有压力，最终执意回家先备考（7-8月份还有一个专业课面授班）挽单失败 KYJZ250070042 KYJZ25007 26考研政治全年集训营（基础/四月）实缴7630--总课时40；课耗16；不涉及书本费--扣费：8300/40*16=3320--退还：7630-3320=4310.0 | AF5: 2025-06-30 | AG5: 郑雪新 | AH5: 真实产生的退费 | AI5: 刘浩宇 | AJ5: BJWY3212612620 | AK5: 4310 | AL5: 2025/06/18 | AM5: 微信共退90521 [图片] [图片] | AP5: TRUE
A6: 2025/05/30 | B6: 退费 | C6: 2025052100094 | D6: 张子晗67-张子晗 | F6: 刘晓娟 | H6: 虚拟人 | I6: 四六级项目 | K6: 开课后退费 | M6: 学员意愿转变_开课后 | Z6: 认为课程用处不大/不适合自己 | AB6: 学生认为课程不适合自己 | AF6: 2025-06-30 | AG6: 张子晗67-张子晗 | AH6: 真实产生的退费 | AI6: 金立威 | AJ6: BJWY0665091701 | AK6: 8388 | AL6: 2025/06/01 | AM6: 微信退回[图片] | AP6: TRUE
A7: 2025/06/01 | B7: 退费 | C7: 18658679 | D7: 王立颖17-王立颖 | F7: 杨明43-杨明（北京在职mba考研） | H7: 公众号 | I7: 在职研项目 | K7: 开课后退费 | M7: 学员意愿转变_开课后 | Z7: 选择出国留学 | AB7: 姓名：张元正 电话：13520118637 学员编号：BJWY3510399937 产品名称：ZZYG26002 考研在职管理类综合全程班（26） 退费原因：计划有变，准备出国留学。 实际退费金额=总课时费-课时消耗金额-教材费用 课耗金额=21800/70*6=1868.6元 教材费用=100元 实际退费金额=21300-1868.6-100=19331.4元 | AF7: 2025-06-30 | AG7: 王立颖17-王立颖 | AH7: 真实产生的退费 | AI7: 张元正 | AJ7: BJWY3510399937 | AK7: 19331.4 | AL7: 2025/06/03 | AM7: 微信退回 | AO7: [图片] | AP7: TRUE
A8: 2025/06/02 | B8: 退费 | C8: 2025052903139 | D8: 张泽7-张泽 | F8: 赵星火 | H8: 学管续费推荐 | I8: VIP项目 | J8: 无忧项目 | K8: 开课后退费 | M8: 学员意愿转变_开课后 | Z8: 认为课程用处不大/不适合自己 | AB8: 投诉学员乔怡娜，处理方案：一对一剩余课时费4000元，特殊申请转入无忧走读班级（原价25600），无需补充差价；6.28开课：英语二强化+冲刺WYFE26007,WYFE26008 政治：WYFP26003,WYFP26004 姓名：乔怡娜 学员号：BJWY3184144484 课时包编码：LP1715735991942，考研一对一伴学班（25考季） 退费原因：公共课未考到目标学校分数线剩余5小时需要退费，报如无忧班课 退费金额=报名金额-课消金额=32000-800*35=4000元 | AC8: ¥4000.00 | AF8: 2025-06-30 | AG8: 张泽7-张泽 | AH8: 转项目/转班/退出重报等未产生实际退费 | AI8: 乔怡娜 | AJ8: BJWY3184144484 | AK8: 4000 | AL8: 2025/06/02 | AM8: 退至学员账户 | AP8: TRUE
A9: 2025/05/21 | B9: 退费 | C9: NO.7205759403793977957 | D9: 马一鸣16-马一鸣 | F9: 钱雪冰 | H9: 学管续费推荐 | I9: 无忧项目 | K9: 开课后退费 | M9: 学员意愿转变_开课后 | Z9: 认为课程用处不大/不适合自己 | AB9: 学生初级会计师考试结束，不需要课程了。询问是否学习其他内容，学生不需要，坚持退费。 | AF9: 2025-06-30 | AG9: 马一鸣16-马一鸣 | AH9: 真实产生的退费 | AI9: 毕嫣然 | AJ9: BJWY2440766155 | AK9: 32600 | AL9: 2025/06/03 | AM9: 6.10财务反馈退款失败，已重新提交新的银行卡：毕嫣然6214686200322381北京海淀北京银行新华支行 | AP9: TRUE
A10: 2025/06/03 | B10: 退费 | C10: NO.18656618 | D10: 高龙明 | F10: 高龙明 | H10: 顾问转介绍-老带新 | I10: 集训营项目 | K10: 开课前退费 | L10: 学员意愿转变_开课前 | O10: 找到工作 | AB10: 学生找到工作不考研了 | AF10: 2025-06-30 | AG10: 高龙明 | AH10: 真实产生的退费 | AI10: 王鹏 | AJ10: BJWY7229276582 | AK10: 95000 | AL10: 2025/06/03 | AM10: 支付宝退回 | AP10: TRUE
A11: 2025/06/03 | B11: 退费 | C11: 18656571 | D11: 高龙明 | F11: 高龙明 | H11: 内部工单推荐 | I11: 集训营项目 | K11: 开课前退费 | L11: 学员意愿转变_开课前 | O11: 去其他机构 | AB11: 孩子不来学习，家长沟通过了，尊重孩子想法 | AF11: 2025-06-30 | AG11: 高龙明 | AH11: 真实产生的退费 | AI11: 关子仁 | AJ11: XDF6597266200 | AK11: 75920 | AL11: 2025/06/05 | AM11: 已手工退款 | AP11: TRUE
A12: 2025/06/03 | B12: 退费 | C12: 8646911284552491678 | D12: 高龙明 | F12: 高龙明 | H12: 内部工单推荐 | I12: 集训营项目 | K12: 开课前退费 | L12: 学员意愿转变_开课前 | O12: 去其他机构 | AB12: 孩子不来学习，家长沟通过了，尊重孩子想法 | AF12: 2025-06-30 | AG12: 高龙明 | AH12: 真实产生的退费 | AI12: 关子仁 | AJ12: XDF6597266200 | AK12: 11000 | AL12: 2025/06/10 | AM12: 已手工退款 | AP12: TRUE
A13: 2025/06/03 | B13: 退费 | C13: 2025060301379 | D13: 李润基 | F13: 徐健坤1-徐健坤 | H13: 地推 | I13: VIP项目 | K13: 开课后退费 | M13: 学员意愿转变_开课后 | Z13: 认为课程用处不大/不适合自己 | AB13: 学生对两节课不满意，故退4H，（37000/50×4h=2960元） | AF13: 2025-06-30 | AG13: 李润基 | AH13: 真实产生的退费 | AI13: 张艺璇 | AJ13: BJWY0321441887 | AK13: 2960 | AL13: 2025/06/06 | AM13: 支付宝退回 | AP13: TRUE
A14: 2025/06/03 | B14: 退费 | C14: 2025052600102 | D14: 韦艺鑫 | F14: 高龙明 | H14: 公众号 | I14: VIP项目 | J14: 无忧项目 | K14: 开课前退费 | L14: 中心原因_开课前 | Q14: 退出重报（报错班级） | AB14: 课时包无法直接转产品到无忧，退出重报 退费金额=缴费金额=25500元 | AC14: ¥25500.00 | AF14: 2025-06-30 | AG14: 韦艺鑫 | AH14: 转项目/转班/退出重报等未产生实际退费 | AI14: 刘怡然 | AJ14: BJWY2674858025 | AK14: 25500 | AL14: 2025/06/03 | AM14: 退回账户余额 | AP14: TRUE
A15: 2025/06/03 | B15: 退费 | C15: 18664265 | D15: 郝琨 | F15: 刘创9-刘创（北京考研/四六级） | G15: TRUE | H15: 大众点评 | I15: 无忧项目 | K15: 开课后退费 | M15: 学员意愿转变_开课后 | Z15: 选择出国留学 | AB15: 学生姓名：邱浩嘉学员编号：BJWY9031976688退费方式：报英政数专退全科退费原因：学生考研留学两手准备，4.6号沟通转5月班级学习，最后出勤截止到4.6号，未到转班时间学生现在已经申请好英国的学校，提出退费退费班级：WYE26033、WYE26031、WYE26032、WYM26013、WYM26014、WYM26015、WYP26026、WYP26027、WYP26025退费明细：实缴金额：44800；课消费用：5301.8；教材费：198应退金额：实缴金额-课消-教材费=44800-5301.8-198=39300.2元 学生现金支付退回银行卡：6214 6800 8868 3543 北京银行田村支行 | AF15: 2025-06-30 | AG15: 郝琨 | AH15: 真实产生的退费 | AI15: 邱浩嘉 | AJ15: BJWY9031976688 | AK15: 2942.4 | AL15: 2025/06/04 | AM15: 6.11退款完成49300.2—————— ​原支付渠道为现金，6.10已转手工退至学员本人银行卡：邱浩嘉6214680088683543北京银行田村支行 | AP15: TRUE
A16: 2025/06/03 | B16: 退费 | C16: 18664327 | D16: 郝琨 | F16: 刘创9-刘创（北京考研/四六级） | G16: TRUE | H16: 大众点评 | I16: 无忧项目 | K16: 开课后退费 | M16: 学员意愿转变_开课后 | Z16: 选择出国留学 | AB16: 学生姓名：邱浩嘉学员编号：BJWY9031976688退费方式：报英政数专退全科退费原因：学生考研留学两手准备，4.6号沟通转5月班级学习，最后出勤截止到4.6号，未到转班时间学生现在已经申请好英国的学校，提出退费退费班级：WYE26033、WYE26031、WYE26032、WYM26013、WYM26014、WYM26015、WYP26026、WYP26027、WYP26025退费明细：实缴金额：44800；课消费用：5301.8；教材费：198应退金额：实缴金额-课消-教材费=44800-5301.8-198=39300.2元 学生现金支付退回银行卡：6214 6800 8868 3543 北京银行田村支行 | AF16: 2025-06-30 | AG16: 郝琨 | AH16: 真实产生的退费 | AI16: 邱浩嘉 | AJ16: BJWY9031976688 | AK16: 3445.6 | AL16: 2025/06/04 | AM16: 6.11退款完成49300.2—————— ​原支付渠道为现金，6.10已转手工退至学员本人银行卡：邱浩嘉6214680088683543北京银行田村支行 | AP16: TRUE
A17: 2025/06/03 | B17: 退费 | C17: 18664353 | D17: 郝琨 | F17: 刘创9-刘创（北京考研/四六级） | G17: TRUE | H17: 大众点评 | I17: 无忧项目 | K17: 开课后退费 | M17: 学员意愿转变_开课后 | Z17: 选择出国留学 | AB17: 学生姓名：邱浩嘉学员编号：BJWY9031976688退费方式：报英政数专退全科退费原因：学生考研留学两手准备，4.6号沟通转5月班级学习，最后出勤截止到4.6号，未到转班时间学生现在已经申请好英国的学校，提出退费退费班级：WYE26033、WYE26031、WYE26032、WYM26013、WYM26014、WYM26015、WYP26026、WYP26027、WYP26025退费明细：实缴金额：44800；课消费用：5301.8；教材费：198应退金额：实缴金额-课消-教材费=44800-5301.8-198=39300.2元 学生现金支付退回银行卡：6214 6800 8868 3543 北京银行田村支行 | AF17: 2025-06-30 | AG17: 郝琨 | AH17: 真实产生的退费 | AI17: 邱浩嘉 | AJ17: BJWY9031976688 | AK17: 4577.6 | AL17: 2025/06/04 | AM17: 6.11退款完成49300.2—————— ​原支付渠道为现金，6.10已转手工退至学员本人银行卡：邱浩嘉6214680088683543北京银行田村支行 | AP17: TRUE
A18: 2025/06/03 | B18: 退费 | C18: 18664390 | D18: 郝琨 | F18: 刘创9-刘创（北京考研/四六级） | G18: TRUE | H18: 大众点评 | I18: 无忧项目 | K18: 开课后退费 | M18: 学员意愿转变_开课后 | Z18: 选择出国留学 | AB18: 学生姓名：邱浩嘉学员编号：BJWY9031976688退费方式：报英政数专退全科退费原因：学生考研留学两手准备，4.6号沟通转5月班级学习，最后出勤截止到4.6号，未到转班时间学生现在已经申请好英国的学校，提出退费退费班级：WYE26033、WYE26031、WYE26032、WYM26013、WYM26014、WYM26015、WYP26026、WYP26027、WYP26025退费明细：实缴金额：44800；课消费用：5301.8；教材费：198应退金额：实缴金额-课消-教材费=44800-5301.8-198=39300.2元 学生现金支付退回银行卡：6214 6800 8868 3543 北京银行田村支行 | AF18: 2025-06-30 | AG18: 郝琨 | AH18: 真实产生的退费 | AI18: 邱浩嘉 | AJ18: BJWY9031976688 | AK18: 28334.6 | AL18: 2025/06/04 | AM18: 6.11退款完成49300.2—————— ​原支付渠道为现金，6.10已转手工退至学员本人银行卡：邱浩嘉6214680088683543北京银行田村支行 | AP18: TRUE
A19: 2025/06/03 | B19: 退费 | C19: 18664899 | D19: 葛铭 | F19: 刘海玲 | H19: 小红书 | I19: 无忧项目 | K19: 开课后退费 | M19: 学员意愿转变_开课后 | Z19: 选择出国留学 | AB19: 学员出国，放弃考研 | AF19: 2025-06-30 | AG19: 葛铭 | AH19: 真实产生的退费 | AI19: 李芊雨 | AJ19: BJWY2714713335 | AK19: 10528 | AL19: 2025/06/06 | AM19: 微信退13245.3 | AO19: [图片] | AP19: TRUE
A20: 2025/06/03 | B20: 退费 | C20: 18664846 | D20: 葛铭 | F20: 刘海玲 | H20: 小红书 | I20: 无忧项目 | K20: 开课后退费 | M20: 学员意愿转变_开课后 | Z20: 选择出国留学 | AB20: 学员出国，放弃考研 | AF20: 2025-06-30 | AG20: 葛铭 | AH20: 真实产生的退费 | AI20: 李芊雨 | AJ20: BJWY2714713335 | AK20: 2717.3 | AL20: 2025/06/06 | AM20: 微信退13245.3 | AO20: [图片] | AP20: TRUE
A21: 2025/06/03 | B21: 退费 | C21: NO.3746994889973389362 | D21: 陈猛飞 | F21: 李崇宇1-李崇宇（北京考研/四六级） | H21: 其他网络投放 | I21: 无忧项目 | K21: 开课后退费 | M21: 学员意愿转变_开课后 | Z21: 认为课程用处不大/不适合自己 | AB21: 学生上了一段时间专业课，由于家庭原因和学生觉得这部分内容自己可以自学解决，坚持退掉专业课 | AF21: 2025-06-30 | AG21: 陈猛飞 | AH21: 真实产生的退费 | AI21: 孟凡宇 | AJ21: BJWY5191841449 | AK21: 13588 | AL21: 2025/06/10 | AM21: 支付宝退回 | AP21: TRUE
A22: 2025/06/03 | B22: 退费 | C22: 18664589 | D22: 汤之然 | F22: 刘贵宁 | H22: 直访 | I22: 英语学习部 | K22: 开课后退费 | M22: 学员意愿转变_开课后 | Z22: 英学专用——不再需要此类课程 | AB22: 青少学员报名一对一课程进行考前冲刺，上完后未消耗课程已办理退费，现在考试结果出来了学员考试没过要投诉，咨询法务老师建议全额退款降低风险，申请已消耗的费用3600元全额退款。已走邮件申请 | AF22: 2025-06-30 | AG22: 汤之然 | AH22: 真实产生的退费 | AI22: 傅方静 | AJ22: BJWY5845279213 | AK22: 3600 | AL22: 2025/06/03 | AM22: 支付宝退3600 | AO22: [图片] | AP22: TRUE
A23: 2025/06/04 | B23: 退费 | C23: 18664187 | D23: 韦艺鑫 | F23: 刘创9-刘创（北京考研/四六级） | H23: 新东方在线员工推荐 | I23: 无忧项目 | K23: 开课后退费 | M23: 计划冲突_开课后 | Y23: 学校事务和新东方时间冲突 | AB23: 因为学校绩点原因再次延毕，需要重修20门课，无法参加26考研，也不考虑转到27考研，需要先处理学校毕业的事情 | AF23: 2025-06-30 | AG23: 韦艺鑫 | AH23: 真实产生的退费 | AI23: 史一博 | AJ23: BJWY4662945918 | AK23: 2055.6 | AL23: 2025/06/04 | AM23: 6.5已转手工退至学员本人银行卡：史一博6212260200196036251中国工商银行石景山玉泉路支行 | AP23: TRUE
A24: 2025/06/04 | B24: 退费 | C24: 18664211 | D24: 韦艺鑫 | F24: 刘创9-刘创（北京考研/四六级） | H24: 新东方在线员工推荐 | I24: 无忧项目 | K24: 开课前退费 | L24: 计划冲突_开课前 | P24: 学校事务和新东方时间冲突 | AB24: 因为学校绩点原因再次延毕，需要重修20门课，无法参加26考研，也不考虑转到27考研，需要先处理学校毕业的事情 | AF24: 2025-06-30 | AG24: 韦艺鑫 | AH24: 真实产生的退费 | AI24: 史一博 | AJ24: BJWY4662945918 | AK24: 10500 | AL24: 2025/06/04 | AM24: 6.5已转手工退至学员本人银行卡：史一博6212260200196036251中国工商银行石景山玉泉路支行 | AP24: TRUE
A25: 2025/06/03 | B25: 退费 | C25: NO.1166353 | D25: 马一鸣16-马一鸣 | F25: 周佳欣17-周佳欣-武汉考研四六级 | H25: 大众点评 | I25: 无忧项目 | K25: 开课前退费 | L25: 学员意愿转变_开课前 | O25: 选择出国留学 | AB25: 学生考研留学两手准备，3.30号学生沟通先暂停考研。学生现在已经申请好英国的学校，提出退费。 | AF25: 2025-06-30 | AG25: 马一鸣16-马一鸣 | AH25: 真实产生的退费 | AI25: 邱浩嘉 | AJ25: BJWY9031976688 | AK25: 10000 | AL25: 2025/06/10 | AM25: 6.11退款完成49300.2—————— ​原支付渠道为现金，6.10已转手工退至学员本人银行卡：邱浩嘉6214680088683543北京银行田村支行 | AP25: TRUE
A26: 2025/05/18 | B26: 退费 | C26: 18632485 | D26: 陈号东5-陈号东 | F26: 李崇宇1-李崇宇（北京考研/四六级） | H26: 小红书 | I26: 无忧项目 | K26: 开课后退费 | M26: 学员意愿转变_开课后 | Z26: 考研信心不足（因跟不上、基础薄弱、目标过高） | AB26: 学生和家长表示跨专业考试难度大，不计划考研 | AF26: 2025-06-30 | AG26: 陈号东5-陈号东 | AH26: 真实产生的退费 | AI26: 彭迦奥 | AJ26: XDF2736875298 | AK26: 4451.1 | AL26: 2025/06/04 | AM26: 支付宝退回 | AP26: TRUE
A27: 2025/05/18 | B27: 退费 | C27: 18632563 | D27: 陈号东5-陈号东 | F27: 李崇宇1-李崇宇（北京考研/四六级） | H27: 小红书 | I27: 无忧项目 | K27: 开课前退费 | L27: 学员意愿转变_开课前 | O27: 考研信心不足（因跟不上、基础薄弱、目标过高） | AB27: 学生和家长表示跨专业考试难度大，不计划考研 | AF27: 2025-06-30 | AG27: 陈号东5-陈号东 | AH27: 真实产生的退费 | AI27: 彭迦奥 | AJ27: XDF2736875298 | AK27: 17357.7 | AL27: 2025/06/04 | AM27: 支付宝退回 | AP27: TRUE
A28: 2025/06/18 | B28: 转班 | D28: 陈号东5-陈号东 | F28: 高龙明 | H28: 小红书 | I28: 无忧项目 | AD28: 11900 | AE28: 学生由英语一改考英语二 | AF28: 2025-06-30 | AG28: 陈号东5-陈号东 | AI28: 王朗芮 | AJ28: BJWY3327364490 | AL28: 2025/06/04 | AM28: 支付宝退回 | AP28: TRUE
A29: 2025/06/04 | B29: 退费 | C29: NO.5476377146883719625 | D29: 王士源13-王士源 | F29: 钱雪冰 | H29: 顾问转介绍-老带新 | I29: 集训营项目 | K29: 开课前退费 | L29: 学员意愿转变_开课前 | O29: 家人不支持考研/不支持跟班学习/意见不一致 | AB29: 学员报入后提供了择校服务，搜集了大量的相关资料,但学员近期说自己找到了研究生老师上课，询问后学员决定不在新东方学习专业课。 | AF29: 2025-06-30 | AG29: 王士源13-王士源 | AH29: 真实产生的退费 | AI29: 傅鑫昕 | AJ29: BJWY8658310322 | AK29: 23500 | AL29: 2025/06/10 | AM29: 支付宝退回 | AP29: TRUE
A30: 2025/06/04 | B30: 转班 | D30: 葛铭 | F30: 赵星火 | H30: 百度投放 | I30: 无忧项目 | AD30: 44800 | AE30: 学员时间冲突，申请转班 | AF30: 2025-06-30 | AG30: 葛铭 | AI30: 李尚烨 | AJ30: BJWY8264939203 | AL30: 2025/06/04 | AM30: 已转班 | AP30: TRUE
A31: 2025/06/04 | B31: 退费 | C31: NO.8358680908400807930 | D31: 郭又华 | F31: 谭悦9-谭悦 | H31: 代理商合作 | I31: 无忧项目 | K31: 开课后退费 | M31: 学员意愿转变_开课后 | Z31: 选择出国留学 | AB31: 学生今年计划出国，不打算考研了，目前也没有其他课程需求，后边有需要再联系。 | AF31: 2025-06-30 | AG31: 郭又华 | AH31: 真实产生的退费 | AI31: 何禹轩 | AJ31: BJWY2841652509 | AK31: 1979.6 | AL31: 2025/06/10 | AM31: 6.18退款完成22397.3—————— 6.17已经提交报账单 6.16转手工22397.3，待客户短信确认（@史文涵1 (史文涵)@郭又华）———————— 22397.3退回账户余额，原支付渠道微信超时失效，请提供学员本人银行卡手工退款：@谭悦9 (谭悦)@史文涵1 (史文涵)@郭又华 [图片] 暂退至学员账户，等无忧退费后一起提现 | AP31: TRUE
A32: 2025/06/04 | B32: 退费 | C32: 18668674 | D32: 葛铭 | F32: 赵星火 | H32: 新东方PC官网 | I32: 无忧项目 | K32: 开课后退费 | M32: 学员意愿转变_开课后 | Z32: 家人不支持考研/不支持跟班学习/意见不一致 | AB32: 学员家长生病，无法考研，申请退费 | AF32: 2025-06-30 | AG32: 葛铭 | AH32: 真实产生的退费 | AI32: 董菡 | AJ32: BJWY1429919607 | AK32: 25758.3 | AM32: 【作废】学管已重新提交OA | AP32: TRUE
A33: 2025/06/04 | B33: 退费 | C33: 18669053 | D33: 葛铭 | F33: 刘创9-刘创（北京考研/四六级） | H33: 新东方官网M站 | I33: 无忧项目 | K33: 开课后退费 | M33: 计划冲突_开课后 | Y33: 个人生活/工作事务和新东方时间冲突 | AB33: 学员怀孕，不能线下上课 | AF33: 2025-06-30 | AG33: 葛铭 | AH33: 真实产生的退费 | AI33: 李静 | AJ33: BJWY0432862919 | AK33: 11702 | AL33: 2025/06/16 | AM33: 6.22原路径支付宝退回 6.18强化班未申请新OA，等中—————— 6.16冲刺班已退，暂退账户4000，等强化班一起提现。 强化班需扣除198教材费，需单独申请OA，申请金额7900-198@葛铭[图片] | AP33: TRUE
A34: 2025/06/04 | B34: 退费 | C34: NO.3746994889973391167 | D34: 王嘉庆5-王嘉庆 | F34: 刘欢67-刘欢 | H34: 集团-百度品专 | I34: VIP项目 | K34: 开课后退费 | M34: 学员意愿转变_开课后 | Z34: 经济困难 | AB34: 学生家中出现变故，不打算继续考研，且不考虑转其他课程 | AF34: 2025-06-30 | AG34: 王嘉庆5-王嘉庆 | AH34: 真实产生的退费 | AI34: 孙畅 | AJ34: BJWY9068474562 | AK34: 4640 | AL34: 2025/06/10 | AM34: 微信退回 | AP34: TRUE
A35: 2025/06/04 | B35: 退费 | C35: 2025060402257 | D35: 黄小妹7-黄小妹 | F35: 谭悦9-谭悦 | H35: 学管续费推荐 | I35: VIP项目 | J35: 无忧项目 | K35: 开课前退费 | L35: 中心原因_开课前 | Q35: 退出重报（取消班/合班/延转/选班/扩科等） | AB35: 无课程消耗，需要退出报入 考研一对一VIP伴学(60小时/26考季)一对一-无忧 | AC35: ¥46800.00 | AF35: 2025-06-30 | AG35: 黄小妹7-黄小妹 | AH35: 转项目/转班/退出重报等未产生实际退费 | AI35: 孙洢妮 | AJ35: BJWY3739115067 | AK35: 46800 | AL35: 2025/06/10 | AM35: 退回账户余额 | AP35: TRUE
A36: 2025/06/04 | B36: 退费 | C36: 18668851 | D36: 李梦娇4-李梦娇 | F36: 刘贵宁 | H36: 学管续费推荐 | I36: 英语学习部 | K36: 开课后退费 | M36: 学员意愿转变_开课后 | Z36: 去其他机构 | AB36: 家长说家门口开了一个补习班，还是想要线下上课，申请退费 | AF36: 2025-06-30 | AG36: 李梦娇4-李梦娇 | AH36: 真实产生的退费 | AI36: 马荟坪 | AJ36: BJWY3479839951 | AK36: 38640 | AL36: 2025/06/04 | AM36: 支付宝退回 | AP36: TRUE
A37: 2025/06/04 | B37: 转班 | D37: 汤之然 | F37: 刘贵宁 | H37: 小红书 | I37: 英语学习部 | AD37: 6800 | AE37: 时间原因转班，原班未出勤 | AF37: 2025-06-30 | AG37: 汤之然 | AI37: 王玉雯 | AJ37: BJWY5216506845 | AL37: 2025/06/04 | AM37: 已转班 | AP37: TRUE
A38: 2025/06/04 | B38: 退费 | C38: 2025060403432 | D38: 刘畅778-刘畅 | F38: 刘文君6-刘文君(北京四六级/专四专八/大学预科) | H38: 学管续费推荐 | I38: 四六级项目 | J38: 四六级项目 | K38: 开课后退费 | M38: 教师 | S38: 教学能力 | AB38: 家长对老师授课不满意，要求换老师 | AC38: ¥2600.00 | AF38: 2025-06-30 | AG38: 刘畅778-刘畅 | AH38: 转项目/转班/退出重报等未产生实际退费 | AI38: 李奇霖 | AJ38: BJWY9604668618 | AK38: 1800 | AL38: 2025/06/05 | AM38: 退回学员账户余额 | AP38: TRUE
A39: 2025/06/05 | B39: 退费 | C39: 18666373 | D39: 刘爱馨-爱馨 | F39: 刘爱馨-爱馨 | H39: 小红书 | I39: 英语学习部 | K39: 开课后退费 | M39: 学员意愿转变_开课后 | Z39: 英学专用——不再需要此类课程 | AB39: 学生个人规划原因，无法安排后续学习。 | AF39: 2025-06-30 | AG39: 王宇乾16-王宇乾 | AH39: 真实产生的退费 | AI39: 周晓夏 | AJ39: BJWY3567803585 | AK39: 4500 | AL39: 2025/06/05 | AM39: 支付宝退回 | AP39: TRUE
A40: 2025/06/05 | B40: 退费 | C40: 18666347 | D40: 刘爱馨-爱馨 | F40: 刘爱馨-爱馨 | H40: 小红书 | I40: 英语学习部 | K40: 开课后退费 | M40: 学员意愿转变_开课后 | Z40: 英学专用——不再需要此类课程 | AB40: 学生个人规划原因，无法安排后续学习。 | AF40: 2025-06-30 | AG40: 王宇乾16-王宇乾 | AH40: 真实产生的退费 | AI40: 周晓夏 | AJ40: BJWY3567803585 | AK40: 5850 | AL40: 2025/06/05 | AM40: 支付宝退回 | AP40: TRUE
A41: 2025/06/06 | B41: 退费 | C41: 18668886 | D41: 李梦娇4-李梦娇 | F41: 刘贵宁 | H41: 公众号 | I41: 英语学习部 | K41: 开课前退费 | L41: 学员意愿转变_开课前 | O41: 认为课程用处不大/不适合自己 | AB41: 学生一直没有时间上课，说现在换工作了也不需要了，申请退款 | AF41: 2025-06-30 | AG41: 李梦娇4-李梦娇 | AH41: 真实产生的退费 | AI41: 刘佳 | AJ41: BJWY2769264382 | AK41: 12150 | AL41: 2025/06/06 | AM41: 支付宝退回12150，已开发票自动冲红@李梦娇4 (李梦娇) | AO41: [图片] | AP41: TRUE
A42: 2025/06/06 | B42: 退费 | C42: 18669286 | D42: 黄小妹7-黄小妹 | F42: 刘创9-刘创（北京考研/四六级） | H42: 社群、虚拟人 | I42: 无忧项目 | K42: 开课后退费 | M42: 学员意愿转变_开课后 | Z42: 考研信心不足（因跟不上、基础薄弱、目标过高） | AB42: 【已开课退费】学生持续对考研失去信心，多次调整无效，不考研了。 | AF42: 2025-06-30 | AG42: 黄小妹7-黄小妹 | AH42: 真实产生的退费 | AI42: 孙翰墨 | AJ42: BJWY4065010412 | AK42: 10015.4 | AL42: 2025/06/07 | AM42: 支付宝退回（6.7） [图片] | AP42: TRUE
A43: 2025/06/06 | B43: 退费 | C43: 18669157 | D43: 黄小妹7-黄小妹 | F43: 刘创9-刘创（北京考研/四六级） | H43: 社群、虚拟人 | I43: 无忧项目 | K43: 开课后退费 | M43: 学员意愿转变_开课后 | Z43: 考研信心不足（因跟不上、基础薄弱、目标过高） | AB43: 【已开课退费】学生持续对考研失去信心，多次调整无效，不考研了。 | AF43: 2025-06-30 | AG43: 黄小妹7-黄小妹 | AH43: 真实产生的退费 | AI43: 孙翰墨 | AJ43: BJWY4065010412 | AK43: 170.2 | AL43: 2025/06/07 | AM43: 支付宝退回（6.7） [图片] | AP43: TRUE
A44: 2025/06/06 | B44: 退费 | C44: 18669223 | D44: 黄小妹7-黄小妹 | F44: 刘创9-刘创（北京考研/四六级） | H44: 社群、虚拟人 | I44: 无忧项目 | K44: 开课后退费 | M44: 学员意愿转变_开课后 | Z44: 考研信心不足（因跟不上、基础薄弱、目标过高） | AB44: 【已开课退费】学生持续对考研失去信心，多次调整无效，不考研了。 | AF44: 2025-06-30 | AG44: 黄小妹7-黄小妹 | AH44: 真实产生的退费 | AI44: 孙翰墨 | AJ44: BJWY4065010412 | AK44: 9739.8 | AL44: 2025/06/07 | AM44: 支付宝退回（6.7） [图片] | AP44: TRUE
A45: 2025/06/06 | B45: 退费 | C45: 18668674 | D45: 葛铭 | F45: 赵星火 | H45: 新东方官网M站 | I45: 无忧项目 | K45: 开课后退费 | M45: 计划冲突_开课后 | Y45: 个人生活/工作事务和新东方时间冲突 | AB45: 学员 家长生病，放弃考研 | AF45: 2025-06-30 | AG45: 葛铭 | AH45: 真实产生的退费 | AI45: 董菡 | AJ45: BJWY1429919607 | AK45: 21026.2 | AL45: 2025/06/10 | AM45: 支付宝退回 | AP45: TRUE
A46: 2025/06/06 | B46: 退费 | C46: 18674781 | D46: 葛铭 | F46: 赵星火 | H46: 新东方官网M站 | I46: 无忧项目 | K46: 开课后退费 | M46: 计划冲突_开课后 | Y46: 个人生活/工作事务和新东方时间冲突 | AB46: 学员 家长生病，放弃考研 | AF46: 2025-06-30 | AG46: 葛铭 | AH46: 真实产生的退费 | AI46: 董菡 | AJ46: BJWY1429919607 | AK46: 4732.1 | AL46: 2025/06/10 | AM46: 支付宝退回 | AP46: TRUE
A47: 2025/06/06 | B47: 退费 | C47: NO.7782220156097415399 | D47: 刘佳林25-刘佳林 | F47: 高龙明,赵星火 | H47: 直访 | I47: 集训营项目 | K47: 开课后退费 | M47: 学员意愿转变_开课后 | Z47: 认为课程用处不大/不适合自己 | AB47: 学生目前三战，目前觉得专业课不符合预期，不适合自己，也不考虑其他课程，经挽单也坚持退费 | AF47: 2025-06-30 | AG47: 刘佳林25-刘佳林 | AH47: 真实产生的退费 | AI47: 王嘉祥 | AJ47: BJWY4539181865 | AK47: 6233.4 | AL47: 2025/06/15 | AM47: 6.25付款成功。退款待到账（6.25）,6.17转手工退 [图片] | AP47: TRUE
A48: 2025/06/06 | B48: 退费 | C48: NO.2882303761518315750 | D48: 刘佳林25-刘佳林 | F48: 刘创9-刘创（北京考研/四六级） | H48: 新东方PC官网 | I48: 集训营项目 | K48: 开课前退费 | L48: 专业课师资匹配原因 | N48: 完全匹配不上 | AA48: 清华清华大学 计算机科学与技术系 计算机科学与技术 (826)计算机专业基础综合 | AB48: 学生报考清华大学 计算机科学与技术专业，2月13日开始匹配，截止至当前6月4日，未匹配到研究生，5月提出退费，经挽单坚持退费，也不需要其他课程 | AF48: 2025-06-30 | AG48: 刘佳林25-刘佳林 | AH48: 真实产生的退费 | AI48: 芦煜博 | AJ48: BJWY6654700269 | AK48: 16000 | AL48: 2025/06/10 | AM48: 6.11退款完成16000—————— 原渠道为现金，6.10已转手工退至学员本人银行卡，待短信确认：芦煜博6217900800004444111中国银行上海市上海交通大学支行-[图片] | AP48: TRUE
A49: 2025/06/03 | B49: 退费 | C49: 2025060502030 | D49: 陈晶171-陈晶 | F49: 刘海玲,徐铁-徐铁(北京考研/四六级） | H49: 学管续费推荐 | I49: VIP项目 | K49: 开课后退费 | M49: 学员意愿转变_开课后 | Z49: 找到工作 | AB49: 学员24年下半年来到新东方集训营考研学习，8月中途妈妈退掉集训营给孩子报一对一，上一对一的途中多次因为家里矛盾停课复课，妈妈后又觉得孩子当年状态不好停课带着孩子回了黑龙江老家，我们沟通孩子自学数学一轮后开始26考研的学习；从24年底到今年的5月份我一直跟进孩子学习进度但是孩子回应很少，我担心孩子学习进度，一直联系的妈妈，5月份约好的开始学习，课程都已经安排好全年的了，孩子又和妈妈商量考不上了要找工作，妈妈又给找了工作着急的要退课，我和顾问劝说无果。 | AF49: 2025-06-30 | AG49: 陈晶171-陈晶 | AH49: 真实产生的退费 | AI49: 王艺斌 | AJ49: BJWY4503244188 | AK49: 265500 | AL49: 2025/06/10 | AM49: 6.18全部打款完成—————— 6.17打款失败，改分笔支付，已支付19w，———— [图片][图片] 6.16共享老师说金额太高改线下支付了，预计6点多或者明天上午提交，提交后张佳楠老师会告知—————— （6.15）手工退款退票@杨沫5 (杨沫) 240907.8转手工退款失败（6.14）[图片] | AP49: TRUE
A50: 2025/06/06 | B50: 退费 | C50: 2882303761518315441 | D50: 王天义56-王天义 | F50: 徐铁-徐铁(北京考研/四六级） | H50: 总部-百度投放 | I50: VIP项目 | K50: 开课前退费 | L50: 学员意愿转变_开课前 | O50: 自己找到老师复习 | AB50: 学员挂科较多，打算补大学课程，若有机会可考研。家长不让加孩子的微信，且对于专业课的考试用书不了解，所以未开启研究生匹配工作；后与家长确认开课时间，由于在校学习麻烦，打算暑期开始学习。退费原因为学员自己在校找到了学姐学长学习；学管挽单建议保留课时或者学习雅思托福等英语课程，保持英语口语、词汇学习，考研或者出国更好上手且选择会多一些，无果。目前着重解决毕业问题，再做打算，暂无考研、英语学习等需求。退费金额=报名金额-课消金额=31300-0=31300元 | AF50: 2025-06-30 | AG50: 王天义56-王天义 | AH50: 真实产生的退费 | AI50: 李佳蒙 | AJ50: BJWY9809019352 | AK50: 31300 | AL50: 2025/06/10 | AM50: 微信退回 | AP50: TRUE
A51: 2025/06/06 | B51: 退费 | C51: NO.5476377146883722288 | D51: 郭又华 | F51: 张乐33-张乐 | H51: 总部-百度投放 | I51: 无忧项目 | K51: 开课前退费 | L51: 学员意愿转变_开课前 | O51: 自己找到老师复习 | AB51: 学生考本专业，初联时就说专业课先看网课自学，暂时不用匹配研究生，现在突然表明家里人给找好研究生了，后面也不用再进行匹配了，目前也没有其他课程需求，坚持退掉。 | AF51: 2025-06-30 | AG51: 郭又华 | AH51: 真实产生的退费 | AI51: 赵匡磊 | AJ51: BJWY2336290390 | AK51: 10000 | AL51: 2025/06/12 | AM51: 6.18退款完成10000———————— 6.17报账单已提交 6.16转手工10000，待客户短信确认—————— 暂退账户10000，原支付渠道退费失败，需提供原支付截图+截图中银行卡信息或学员本人银行卡信息（6.16）@郭又华[图片] | AP51: TRUE
A52: 2025/06/07 | B52: 退费 | C52: 4611686018428519003 | D52: 王天义56-王天义 | F52: 张德天-张德天(小天) | H52: 内部工单推荐 | I52: VIP项目 | K52: 开课后退费 | M52: 学员意愿转变_开课后 | Z52: 认为课程用处不大/不适合自己 | AB52: 退费原因：二战学员初试没过分数线，无需雅思、三战，剩余课时费用需要退出 退费金额=实缴金额-课时单价×消耗课时数=8500-900*6=3100元 | AF52: 2025-06-30 | AG52: 王天义56-王天义 | AH52: 真实产生的退费 | AI52: 刘芷妤 | AJ52: BJWY1753410857 | AK52: 3100 | AL52: 2025/06/07 | AM52: 原渠道微信超时失效，6.9已转手工退至学员本人银行卡：刘芷妤6215582402000976995武汉宗关支行 | AO52: [图片] | AP52: TRUE
A53: 2025/06/06 | B53: 转班 | D53: 王立颖17-王立颖 | F53: 杨明43-杨明（北京在职mba考研） | H53: 大众点评 | I53: 在职研项目 | AD53: 5439.3 | AE53: 退费原因：目标学校央财取消提面，学生要求将费用转班到笔试一对一课程，退到学员账户。 | AF53: 2025-06-30 | AG53: 王立颖17-王立颖 | AI53: 刘司墨 | AJ53: BJWY4862121927 | AM53: 【作废】学管已重新提交OA | AP53: TRUE
A54: 2025/06/06 | B54: 转班 | D54: 王立颖17-王立颖 | F54: 杨明43-杨明（北京在职mba考研） | H54: 学管续费推荐 | I54: 在职研项目 | AD54: 7860.7 | AE54: 退费原因：目标学校央财取消提面，学生要求将费用转班到笔试一对一课程，请将学费退至学员账户。 | AF54: 2025-06-30 | AG54: 王立颖17-王立颖 | AI54: 刘司墨 | AJ54: BJWY4862121927 | AM54: 【作废】学管已重新提交OA | AP54: TRUE
A55: 2025/06/07 | B55: 转班 | D55: 韦艺鑫 | F55: 李婧2211-李婧（北京中心考研四六级） | H55: 顾问转介绍-老带新 | I55: 无忧项目 | AD55: 9349.7 | AE55: 学生英语二改考英语一 | AF55: 2025-06-30 | AG55: 韦艺鑫 | AI55: 王艺淳 | AJ55: BJWY8024898883 | AL55: 2025/06/07 | AM55: 已转班 | AP55: TRUE
A56: 2025/06/07 | B56: 转班 | D56: 葛铭 | F56: 钱雪冰 | H56: 大众点评 | I56: 无忧项目 | AD56: 9849.7 | AE56: 学员英一改考英二 | AF56: 2025-06-30 | AG56: 葛铭 | AI56: 王传铭 | AJ56: BJWY9783817271 | AL56: 2025/06/07 | AM56: 已转班 | AP56: TRUE
A57: 2025/06/06 | B57: 退费 | C57: NO.18676912 | D57: 王立颖17-王立颖 | F57: 杨明43-杨明（北京在职mba考研） | H57: 学管续费推荐 | I57: 在职研项目 | J57: 在职研项目 | K57: 开课前退费 | L57: 计划冲突_开课前 | P57: 学校事务和新东方时间冲突 | AB57: 目标学校央财取消提面，学生要求将费用转班到笔试一对一课程，退到学员账户。 | AC57: ¥5439.30 | AF57: 2025-06-30 | AG57: 王立颖17-王立颖 | AH57: 转项目/转班/退出重报等未产生实际退费 | AI57: 刘司墨 | AJ57: BJWY4862121927 | AK57: 5439.3 | AL57: 2025/06/09 | AM57: 退至学员账户(6.9)@王立颖17 (王立颖) | AP57: TRUE
A58: 2025/06/06 | B58: 退费 | C58: NO.2025060603303 | D58: 王立颖17-王立颖 | F58: 杨明43-杨明（北京在职mba考研） | H58: 学管续费推荐 | I58: 在职研项目 | J58: 在职研项目 | K58: 开课前退费 | L58: 计划冲突_开课前 | P58: 学校事务和新东方时间冲突 | AB58: 退费原因：目标学校央财取消提面，学生要求将费用转班到笔试一对一课程。退到学员账户 | AC58: ¥7860.70 | AF58: 2025-06-30 | AG58: 王立颖17-王立颖 | AH58: 转项目/转班/退出重报等未产生实际退费 | AI58: 刘司墨 | AJ58: BJWY4862121927 | AK58: 7860.7 | AL58: 2025/06/09 | AM58: 退至学员账户(6.9)@王立颖17 (王立颖) | AP58: TRUE
A59: 2025/06/07 | B59: 退费 | C59: 18678948 | D59: 史友娟 | F59: 李崇宇1-李崇宇（北京考研/四六级） | H59: 小红书 | I59: 无忧项目 | K59: 开课后退费 | M59: 学员意愿转变_开课后 | Z59: 考研信心不足（因跟不上、基础薄弱、目标过高） | AB59: 员在职考mba基础薄弱，跟不上工作也忙，建议转27或者在职研或者一对一学生坚持退费，今年不打算考了。 | AF59: 2025-06-30 | AG59: 史友娟 | AH59: 真实产生的退费 | AI59: 王继安 | AJ59: BJWY4387955867 | AK59: 594 | AL59: 2025/06/15 | AM59: 6.18退款完成12494—————— 6.17报账单已提交 6.16转手工退12494，待客户短信确认@史友娟—————— 退回账户余额，原支付宝支付渠道超时失效，请提供学员本人银行卡信息手工退款：（6.15）@史友娟 [图片] 未办理：缺少顾问老师挽单（6.14）@李崇宇1 (李崇宇（北京考研/四六级）) | AP59: TRUE
A60: 2025/06/07 | B60: 退费 | C60: 18679017 | D60: 史友娟 | F60: 李崇宇1-李崇宇（北京考研/四六级） | H60: 小红书 | I60: 无忧项目 | K60: 开课前退费 | L60: 学员意愿转变_开课前 | O60: 考研信心不足（因跟不上、基础薄弱、目标过高） | AB60: 员在职考mba基础薄弱，跟不上工作也忙，建议转27或者在职研或者一对一学生坚持退费，今年不打算考了。 | AF60: 2025-06-30 | AG60: 史友娟 | AH60: 真实产生的退费 | AI60: 王继安 | AJ60: BJWY4387955867 | AK60: 11900 | AL60: 2025/06/15 | AM60: 6.18退款完成12494—————— 6.17报账单已提交 6.16转手工退12494，待客户短信确认@史友娟—————— 退回账户余额，原支付宝支付渠道超时失效，请提供学员本人银行卡信息手工退款：（6.15）@史友娟 [图片] 未办理：缺少顾问老师挽单（6.14）@李崇宇1 (李崇宇（北京考研/四六级）) | AP60: TRUE
A61: 2025/06/08 | B61: 转班 | D61: 许庆典 | F61: 钱雪冰 | H61: 阿里本地通 | I61: 无忧项目 | AD61: 12250 | AE61: 学生想跟着指定老师上大班课，不在乎行课进度，所以更换班级。 | AF61: 2025-06-30 | AG61: 许庆典 | AI61: 白婧含 | AJ61: BJWY0721271953 | AL61: 2025/06/08 | AM61: 已转班 | AP61: TRUE
A62: 2025/06/08 | B62: 退费 | C62: 18681077 | D62: 郝琨 | F62: 王秋雨1-王秋雨 | H62: 顾问转介绍-老带新 | I62: 无忧项目 | K62: 开课后退费 | M62: 学员意愿转变_开课后 | Z62: 保研 | AB62: 学生姓名：王方正学员编号：BJWY8372787516退费方式：报英数退英数退费原因：学生本校直博，周六校区面谈不考研申请退出退费班级：WYE26033、WYE26036、WYE26032、WYM26013、WYM26014、WYM26015退费明细：实缴金额：36600；课消费用：9348.4；教材费：198应退金额：实缴金额-课消-教材费=36600-9348.4-198=27053.6元 | AF62: 2025-06-30 | AG62: 郝琨 | AH62: 真实产生的退费 | AI62: 王方正 | AJ62: BJWY8372787516 | AK62: 674.3 | AL62: 2025/06/20 | AM62: 6.25付款成功。 6.25学员短信确认 6.22转手工：王方正6217858000160185630中国银行周口分行沈丘支行 [图片] | AP62: TRUE
A63: 2025/06/08 | B63: 退费 | C63: 18681156 | D63: 郝琨 | F63: 王秋雨1-王秋雨 | H63: 顾问转介绍-老带新 | I63: 无忧项目 | K63: 开课后退费 | M63: 学员意愿转变_开课后 | Z63: 保研 | AB63: 学生姓名：王方正学员编号：BJWY8372787516退费方式：报英数退英数退费原因：学生本校直博，周六校区面谈不考研申请退出退费班级：WYE26033、WYE26036、WYE26032、WYM26013、WYM26014、WYM26015退费明细：实缴金额：36600；课消费用：9348.4；教材费：198应退金额：实缴金额-课消-教材费=36600-9348.4-198=27053.6元 | AF63: 2025-06-30 | AG63: 郝琨 | AH63: 真实产生的退费 | AI63: 王方正 | AJ63: BJWY8372787516 | AK63: 1316.9 | AL63: 2025/06/20 | AM63: 6.25付款成功。 6.25学员短信确认 6.22转手工：王方正6217858000160185630中国银行周口分行沈丘支行 [图片] | AP63: TRUE
A64: 2025/06/08 | B64: 退费 | C64: 18681298 | D64: 郝琨 | F64: 王秋雨1-王秋雨 | H64: 顾问转介绍-老带新 | I64: 无忧项目 | K64: 开课后退费 | M64: 学员意愿转变_开课后 | Z64: 保研 | AB64: 学生姓名：王方正学员编号：BJWY8372787516退费方式：报英数退英数退费原因：学生本校直博，周六校区面谈不考研申请退出退费班级：WYE26033、WYE26036、WYE26032、WYM26013、WYM26014、WYM26015退费明细：实缴金额：36600；课消费用：9348.4；教材费：198应退金额：实缴金额-课消-教材费=36600-9348.4-198=27053.6元 | AF64: 2025-06-30 | AG64: 郝琨 | AH64: 真实产生的退费 | AI64: 王方正 | AJ64: BJWY8372787516 | AK64: 25062.4 | AL64: 2025/06/22 | AM64: 6.25付款成功。 6.25学员短信确认 6.22转手工：王方正6217858000160185630中国银行周口分行沈丘支行 [图片] | AP64: TRUE
A65: 2025/06/08 | B65: 退费 | C65: NO.2882303761518315242 | D65: 王嘉庆5-王嘉庆 | F65: 赵星火 | H65: 新东方PC官网 | I65: 无忧项目 | K65: 开课后退费 | M65: 学员意愿转变_开课后 | Z65: 家人不支持考研/不支持跟班学习/意见不一致 | AB65: 学生家中有特殊情况，目前时间不支持继续考研，且不考虑转其他课程 | AF65: 2025-06-30 | AG65: 王嘉庆5-王嘉庆 | AH65: 真实产生的退费 | AI65: 董菡 | AJ65: BJWY1429919607 | AK65: 727 | AL65: 2025/06/14 | AM65: 支付宝原路退回 | AP65: TRUE
A66: 2025/06/08 | B66: 转班 | D66: 黄子琪3-黄子琪 | F66: 周佳欣17-周佳欣-武汉考研四六级 | H66: 巨量广告 | I66: 无忧项目 | AD66: 1552.8 | AE66: 姓名：杨天睿 电话：18510260519 学员编号：BJWY4587254525 转班原因：打算考专硕了 改为英二了 转班信息： WYHE26005转WYHE26006 | AF66: 2025-06-30 | AG66: 黄子琪3-黄子琪 | AI66: 杨天睿 | AJ66: BJWY4587254525 | AL66: 2025/06/08 | AM66: 已转班 | AP66: TRUE
A67: 2025/06/07 | B67: 退费 | C67: 4899916394580359697 | D67: 兰天惠 | F67: 刘津玲10-北京在职MBA刘津玲 | H67: 小红书 | I67: 在职研项目 | K67: 开课后退费 | M67: 计划冲突_开课后 | Y67: 个人生活/工作事务和新东方时间冲突 | AB67: 同学后面经常出差没有时间在安排课程了，剩余2小时退出，不考虑复试使用 | AF67: 2025-06-30 | AG67: 兰天惠 | AH67: 真实产生的退费 | AI67: 张圣鹤 | AJ67: BJWY8204516230 | AK67: 3000 | AL67: 2025/06/09 | AM67: 微信退回 | AO67: [图片] | AP67: TRUE
A68: 2025/06/09 | B68: 退费 | C68: 18683796 | D68: 刘爱馨-爱馨 | F68: 刘爱馨-爱馨 | H68: 大客服呼入 | I68: 英语学习部 | K68: 开课后退费 | M68: 学员意愿转变_开课后 | Z68: 英学专用——不再需要此类课程 | AB68: 学生觉得课程内容和课程模式不适合自己，不接受调整。申请退费。 | AF68: 2025-06-30 | AG68: 刘爱馨-爱馨 | AH68: 真实产生的退费 | AI68: 肖梦 | AJ68: XDF072103231218960 | AK68: 12150 | AL68: 2025/06/09 | AM68: 微信退回 | AO68: [图片] | AP68: TRUE
A69: 2025/06/09 | B69: 转班 | D69: 史友娟 | F69: 钱雪冰 | H69: 线下校代 | I69: 无忧项目 | AD69: 9959.6 | AE69: 转班原因：学生改考英语二 班级信息： WYE26038转WYE26040 WYE26039转WYE26041 | AF69: 2025-06-30 | AG69: 史友娟 | AI69: 樊欣钰 | AJ69: BJWY9476567744 | AL69: 2025/06/09 | AM69: 已转班 | AP69: TRUE
A70: 2025/06/09 | B70: 退费 | C70: 2025053101108 | D70: 罗志勇1-罗志勇 | F70: 张乐33-张乐 | H70: 京内毛坯数据 | I70: 四六级项目 | K70: 开课后退费 | M70: 计划冲突_开课后 | Y70: 个人生活/工作事务和新东方时间冲突 | AB70: 学生已经考完 有出国留学打算 无需求 要求退费 | AF70: 2025-06-30 | AG70: 罗志勇1-罗志勇 | AH70: 真实产生的退费 | AI70: 刘禹桐 | AJ70: BJWY8198803937 | AK70: 10100 | AL70: 2025/06/12 | AM70: 退款完成 6.14已转手工退，待用户短信自助确认 | AP70: TRUE
A71: 2025/06/09 | B71: 退费 | C71: NO.18684693 | D71: 罗志勇1-罗志勇 | F71: 徐健坤1-徐健坤 | H71: 公众号 | I71: 四六级项目 | K71: 开课前退费 | L71: 中心原因_开课前 | Q71: 特殊优惠 | AB71: 之前报错优惠 已经跟文君说明 6.7-6.9有活动优惠 需要把活动优惠返款到学生 | AF71: 2025-06-30 | AG71: 徐健坤1-徐健坤 | AH71: 真实产生的退费 | AI71: 邓一頔 | AJ71: BJWY8459557991 | AK71: 500 | AL71: 2025/06/13 | AM71: 已返款500 | AP71: TRUE
A72: 2025/06/09 | B72: 退费 | C72: 18685679 | D72: 史友娟 | F72: 刘创9-刘创（北京考研/四六级） | H72: 新东方在线员工推荐 | I72: 无忧项目 | K72: 开课前退费 | L72: 学员意愿转变_开课前 | O72: 选择出国留学 | AB72: 学生打算出国留学不考国内的研究生，基本已经定下来了，坚持退出 | AF72: 2025-06-30 | AG72: 史友娟 | AH72: 真实产生的退费 | AI72: 樊卓 | AJ72: BJWY1663491361 | AK72: 2999 | AL72: 2025/06/12 | AM72: 支付宝退2999[图片] | AP72: TRUE
A73: 2025/06/09 | B73: 退费 | C73: 18685740 | D73: 史友娟 | F73: 刘创9-刘创（北京考研/四六级） | H73: 新东方在线员工推荐 | I73: 无忧项目 | K73: 开课前退费 | L73: 学员意愿转变_开课前 | O73: 选择出国留学 | AB73: 学生打算出国留学不考国内的研究生，基本已经定下来了，坚持退出 | AF73: 2025-06-30 | AG73: 史友娟 | AH73: 真实产生的退费 | AI73: 樊卓 | AJ73: BJWY1663491361 | AK73: 5333.4 | AL73: 2025/06/12 | AM73: 支付宝退5333.4[图片] | AP73: TRUE
A74: 2025/06/09 | B74: 退费 | C74: 18685760 | D74: 史友娟 | F74: 刘创9-刘创（北京考研/四六级） | H74: 新东方在线员工推荐 | I74: 无忧项目 | K74: 开课前退费 | L74: 学员意愿转变_开课前 | O74: 选择出国留学 | AB74: 学生打算出国留学不考国内的研究生，基本已经定下来了，坚持退出 | AF74: 2025-06-30 | AG74: 史友娟 | AH74: 真实产生的退费 | AI74: 樊卓 | AJ74: BJWY1663491361 | AK74: 6800.7 | AL74: 2025/06/12 | AM74: 支付宝退6800.7[图片] | AP74: TRUE
A75: 2025/06/10 | B75: 转班 | D75: 郝琨 | F75: 刘晓娟 | H75: 学管续费推荐 | I75: 无忧项目 | AD75: 9849.7 | AE75: 姓名：刘加隆 电话：13141074310 学员编号：BJWY9975719936 转班原因：学生定好专业院校，考英二 英一转英二 转班信息：WYE26026、WYE26027转WYE26028、WYE26029 已登记表格，辛苦老师办理 | AF75: 2025-06-30 | AG75: 郝琨 | AI75: 刘加隆 | AJ75: BJWY9975719936 | AL75: 2025/06/10 | AM75: 已转班 | AP75: TRUE
A76: 2025/06/10 | B76: 转班 | D76: 郝琨 | F76: 徐铁-徐铁(北京考研/四六级） | H76: 新东方在线员工推荐 | I76: 无忧项目 | AD76: 9959.6 | AE76: 姓名：黄旭东 电话：18108159169 学员编号：BJWY6313353831 转班原因：学生定好专业院校，考英二 英一转英二 转班信息：WYE26032、WYE26033转WYE26034、WYE26035 已登记表格，辛苦老师办理 | AF76: 2025-06-30 | AG76: 郝琨 | AI76: 黄旭东 | AJ76: BJWY6313353831 | AL76: 2025/06/10 | AM76: 已转班 | AP76: TRUE
A77: 2025/06/10 | B77: 退费 | C77: NO.2025060401131 | D77: 谢仕为1-谢仕为 | F77: 钱雪冰 | H77: 新东方PC官网 | I77: 集训营项目 | K77: 开课前退费 | L77: 专业课师资匹配原因 | N77: 完全匹配不上 | AA77: 中国科学院大学 数学与系统科学研究院 070100 基础数学 | AB77: 学生2月份报名 3月份开始匹配专业课学长 学生报名的院校 无法匹配上研究生 学生自己找到了已毕业的学长 退费明细：全科实缴金额：51300 公共课原价32800 优惠1500 单独报入公共课价格；32800-1500=31300元 公共课优惠补款：31300-31300=0元 专业课消耗费用：0元 专业课实际退费：20000-0=20000元 退费金额：20000元 | AF77: 2025-06-30 | AG77: 谢仕为1-谢仕为 | AH77: 真实产生的退费 | AI77: 郑姝琳 | AJ77: BJWY0106132996 | AK77: 20000 | AL77: 2025/06/10 | AM77: 6.18退款完成20000—————— 6.16转手工20000，待客户短信确认@谢仕为1 (谢仕为)———— 暂退至学员账户，原渠道为汇款，需提供原汇款账户6231161700000029343的详细信息（6.14）[图片] @谢仕为1 (谢仕为) | AP77: TRUE
A78: 2025/06/08 | B78: 退费 | C78: NO.18682501 | D78: 王立颖17-王立颖 | F78: 刘津玲10-北京在职MBA刘津玲 | H78: 其他网络合作 | I78: 在职研项目 | K78: 开课后退费 | M78: 学员意愿转变_开课后 | Z78: 个人身体原因无法承受高强度学习 | AB78: 退费原因：身体一直不舒服，坚持工作都有些费劲，更没有精力学习，上周又查出抑郁症，决定暂时放弃考研。 | AF78: 2025-06-30 | AG78: 王立颖17-王立颖 | AH78: 真实产生的退费 | AI78: 刘海云 | AJ78: BJWY8365452755 | AK78: 9862.9 | AL78: 2025/06/11 | AM78: 退至学员账户 | AP78: TRUE
A79: 2025/06/08 | B79: 退费 | C79: NO.18682587 | D79: 王立颖17-王立颖 | F79: 刘津玲10-北京在职MBA刘津玲 | H79: 其他网络合作 | I79: 在职研项目 | K79: 开课后退费 | M79: 学员意愿转变_开课后 | Z79: 个人身体原因无法承受高强度学习 | AB79: 退费原因：身体一直不舒服，坚持工作都有些费劲，更没有精力学习，上周又查出抑郁症，决定暂时放弃考研。 | AF79: 2025-06-30 | AG79: 王立颖17-王立颖 | AH79: 真实产生的退费 | AI79: 刘海云 | AJ79: BJWY8365452755 | AK79: 2430 | AL79: 2025/06/11 | AM79: 退至学员账户 | AP79: TRUE
A80: 2025/06/10 | B80: 退费 | C80: NO.18682101 | D80: 王立颖17-王立颖 | F80: 刘津玲10-北京在职MBA刘津玲 | H80: 其他网络合作 | I80: 在职研项目 | K80: 开课后退费 | M80: 学员意愿转变_开课后 | Z80: 个人身体原因无法承受高强度学习 | AB80: 退费原因：身体一直不舒服，坚持工作都有些费劲，更没有精力学习，上周又查出抑郁症，决定暂时放弃考研。申请将学费退到学员账户。 | AF80: 2025-06-30 | AG80: 王立颖17-王立颖 | AH80: 真实产生的退费 | AI80: 刘海云 | AJ80: BJWY8365452755 | AK80: 8605.6 | AL80: 2025/06/11 | AM80: 退至学员账户 | AP80: TRUE
A81: 2025/06/10 | B81: 退费 | C81: 18688681 | D81: 汤之然 | F81: 刘贵宁 | H81: 小红书 | I81: 英语学习部 | K81: 开课后退费 | M81: 学员意愿转变_开课后 | Z81: 英学专用——不再需要此类课程 | AB81: 长期停课学员，之前因为工作比较忙没时间上课，现在个人原因不想学了申请退费。 | AF81: 2025-06-30 | AG81: 汤之然 | AH81: 真实产生的退费 | AI81: 孟雄飞 | AJ81: BJWY2279928430 | AK81: 6625 | AL81: 2025/06/11 | AM81: 支付宝退还 | AP81: TRUE
A82: 2025/06/10 | B82: 退费 | C82: 18688842 | D82: 张琦文6-张琦文 | F82: 高龙明 | H82: 百度投放 | I82: 集训营项目 | J82: 集训营项目 | K82: 开课前退费 | L82: 学员意愿转变_开课前 | O82: 考研信心不足（因跟不上、基础薄弱、目标过高） | AB82: 改考自命题，退408课程，原金额重新报入自命题专业课 | AC82: ¥17402.00 | AF82: 2025-06-30 | AG82: 张琦文6-张琦文 | AH82: 转项目/转班/退出重报等未产生实际退费 | AI82: 陈廷进 | AJ82: BJWY4776417923 | AK82: 17402 | AL82: 2025/06/11 | AM82: 退至学员账户 | AP82: TRUE
A83: 2025/06/10 | B83: 退费 | C83: 2025060300113 | D83: 李玉迪1-李玉迪 | F83: 刘晓娟 | H83: 学管续费推荐 | I83: 四六级项目 | K83: 开课前退费 | L83: 学员意愿转变_开课前 | O83: 认为课程用处不大/不适合自己 | AB83: 学员下半年报名出国交换，两年内都不会回国。已经考上岸目前没有别的课程需求 | AF83: 2025-06-30 | AG83: 李玉迪1-李玉迪 | AH83: 真实产生的退费 | AI83: 吴越 | AJ83: BJWY3961126498 | AK83: 9748 | AL83: 2025/06/11 | AM83: 微信退还 | AP83: TRUE
A84: 2025/06/11 | B84: 退费 | C84: 18689660 | D84: 罗志勇1-罗志勇 | F84: 钱雪冰 | H84: 代理商合作 | I84: 四六级项目 | K84: 开课前退费 | L84: 计划冲突_开课前 | P84: 学校事务和新东方时间冲突 | AB84: 学校暑假突然安排实验 时间冲突 拒绝转班 | AF84: 2025-06-30 | AG84: 罗志勇1-罗志勇 | AH84: 真实产生的退费 | AI84: 王博生 | AJ84: BJWY1301332362 | AK84: 15300 | AL84: 2025/06/11 | AM84: 微信退还 | AP84: TRUE
A85: 2025/06/11 | B85: 退费 | C85: 18691764 | D85: 王宇乾16-王宇乾 | F85: 王宇乾16-王宇乾 | H85: 小红书KOS | I85: 英语学习部 | K85: 开课后退费 | M85: 学员意愿转变_开课后 | Z85: 认为课程用处不大/不适合自己 | AB85: 家长感觉课程和孩子情况不匹配，不考虑调整课程难度或换老师，要求退费 | AF85: 2025-06-30 | AG85: 王宇乾16-王宇乾 | AH85: 真实产生的退费 | AI85: 邱俊涵 | AJ85: BJWY0710799039 | AK85: 15765 | AL85: 2025/06/11 | AM85: 微信退还 | AP85: TRUE
A86: 2025/06/11 | B86: 退费 | C86: 18692369 | D86: 汤之然 | F86: 刘贵宁 | H86: 大众点评 | I86: 英语学习部 | K86: 开课后退费 | M86: 学员意愿转变_开课后 | Z86: 英学专用——不再需要此类课程 | AB86: 长期停课学员，学生不想上一对一的课程，去年说要退费挽单成功了，然后家长改变学习需求给找了新的老师，但是一直不上课不回复，现在再次提出退费。 | AF86: 2025-06-30 | AG86: 汤之然 | AH86: 真实产生的退费 | AI86: Grace | AJ86: BJWY1299946649 | AK86: 18940 | AL86: 2025/06/11 | AM86: 6.25付款成功。退款待到账（6.25），6.20转手工退款[图片] | AP86: TRUE
A87: 2025/06/11 | B87: 转班 | D87: 徐铁-徐铁(北京考研/四六级） | F87: 徐铁-徐铁(北京考研/四六级） | H87: 学管续费推荐 | I87: 无忧项目 | AD87: 13300 | AE87: 报错班，转班 | AF87: 2025-06-30 | AG87: 徐铁-徐铁(北京考研/四六级） | AI87: 袁博 | AJ87: BJWY7526390970 | AL87: 2025/06/11 | AM87: 已转班 | AP87: TRUE
A88: 2025/06/11 | B88: 退费 | C88: NO.576460752304686542 | D88: 郭又华 | F88: 张德天-张德天(小天) | G88: TRUE | H88: 总部-百度投放 | I88: 无忧项目 | K88: 开课前退费 | L88: 学员意愿转变_开课前 | O88: 找到工作 | AB88: 学生是24年老生，专升本，基础不好，目前在职不打算考研了，目前也没有其他课程需求，坚持退掉。 | AF88: 2025-06-30 | AG88: 郭又华 | AH88: 真实产生的退费 | AI88: 李慧芳 | AJ88: BJWY2583116284 | AK88: 17800 | AL88: 2025/06/13 | AM88: 退款已完成 6.14已转手工退，待用户短信自助确认 | AP88: TRUE
A89: 2025/06/11 | B89: 转班 | D89: 王宇乾16-王宇乾 | F89: 王宇乾16-王宇乾 | H89: 小红书 | I89: 英语学习部 | AD89: 6800 | AE89: 个人原因一直没有时间上课，转到新开班级 班级信息：TBL250003转到TBL250005 | AF89: 2025-06-30 | AG89: 王宇乾16-王宇乾 | AI89: 会会 | AJ89: BJWY5096186852 | AL89: 2025/06/11 | AM89: 已转班 | AP89: TRUE
A90: 2025/06/11 | B90: 退费 | C90: 18692845 | D90: 刘爱馨-爱馨 | F90: 刘贵宁 | H90: 小红书KOS | I90: 英语学习部 | K90: 开课后退费 | M90: 学员意愿转变_开课后 | Z90: 认为课程用处不大/不适合自己 | AB90: 学员为准备国际会议报名课程，现在会议结束了，不需要课程和其他学习内容，申请退费。 | AF90: 2025-06-30 | AG90: 刘爱馨-爱馨 | AH90: 真实产生的退费 | AI90: 王一 | AJ90: BJWY7807479641 | AK90: 22915 | AL90: 2025/06/12 | AM90: 微信退22915 | AO90: [图片] | AP90: TRUE
A91: 2025/06/11 | B91: 退费 | C91: 18692523 | D91: 刘爱馨-爱馨 | F91: 刘贵宁 | H91: 学管转介绍 | I91: 英语学习部 | K91: 开课后退费 | M91: 学员意愿转变_开课后 | Z91: 认为课程用处不大/不适合自己 | AB91: 学员为准备国际会议报名课程，现在会议结束了，不需要课程和其他学习内容，申请退费。 | AF91: 2025-06-30 | AG91: 刘爱馨-爱馨 | AH91: 真实产生的退费 | AI91: 赵香玉 | AJ91: BJWY8125937055 | AK91: 22265 | AL91: 2025/06/12 | AM91: 支付宝退回22265[图片] | AP91: TRUE
A92: 2025/06/12 | B92: 退费 | C92: 18685930 | D92: 汤之然 | F92: 刘贵宁 | H92: 小红书 | I92: 英语学习部 | K92: 开课前退费 | L92: 学员意愿转变_开课前 | O92: 认为课程用处不大/不适合自己 | AB92: 学生转班时教材费留在原班，现在要退费，学生未上课，教材费返款退出 | AF92: 2025-06-30 | AG92: 汤之然 | AH92: 真实产生的退费 | AI92: 王玉雯 | AJ92: BJWY5216506845 | AK92: 76 | AL92: 2025/06/17 | AM92: 支付宝退回 | AP92: TRUE
A93: 2025/06/09 | B93: 退费 | C93: NO.18685914 | D93: 刘贵宁 | F93: 刘贵宁 | G93: TRUE | H93: 小红书 | I93: 英语学习部 | K93: 开课前退费 | L93: 计划冲突_开课前 | P93: 实习和新东方时间冲突 | AB93: 班课未开课，同学不想继续等待，报名了很久，一直没开成，不考虑插班 | AF93: 2025-06-30 | AG93: 刘贵宁 | AH93: 真实产生的退费 | AI93: 王潇 | AJ93: BJWY4904938231 | AK93: 6800 | AL93: 2025/06/12 | AM93: 支付宝退6800[图片] | AP93: TRUE
A94: 2025/06/09 | B94: 退费 | C94: NO.18685907 | D94: 刘贵宁 | F94: 刘贵宁 | G94: TRUE | H94: 小红书 | I94: 英语学习部 | K94: 开课前退费 | L94: 学员意愿转变_开课前 | O94: 个人身体原因无法承受高强度学习 | AB94: 班课未开课，同学不想继续等待，报名了很久，一直没开成，不考虑插班 | AF94: 2025-06-30 | AG94: 刘贵宁 | AH94: 真实产生的退费 | AI94: 王玉雯 | AJ94: BJWY5216506845 | AK94: 6724 | AL94: 2025/06/12 | AM94: 支付宝退回 | AP94: TRUE
A95: 2025/06/12 | B95: 退费 | C95: NO.1729382256911505473 | D95: 郭又华 | F95: 张乐33-张乐 | H95: 阿里本地通 | I95: 无忧项目 | K95: 开课前退费 | L95: 学员意愿转变_开课前 | O95: 自己找到老师复习 | AB95: 学生跨考，初联时就表明专业课只接受面授不考虑线上，告知学生可以先去匹配看看，学生不同意，现在家长表明学生自己找好研究生了，后面也不用再进行匹配了，目前也没有其他课程需求，坚持退掉。 | AF95: 2025-06-30 | AG95: 郭又华 | AH95: 真实产生的退费 | AI95: 岳硕 | AJ95: BJWY3023079064 | AK95: 21000 | AL95: 2025/06/17 | AM95: 6.25付款成功。 退款待到账（6.25），6.18转手工21000 [图片] | AP95: TRUE
A96: 2025/06/12 | B96: 退费 | C96: 18686243 | D96: 史文涵1-史文涵 | F96: 谭悦9-谭悦 | H96: 代理商合作 | I96: 无忧项目 | K96: 开课后退费 | M96: 学员意愿转变_开课后 | Z96: 选择出国留学 | AB96: 学生今年计划出国，不打算考研了 | AF96: 2025-06-30 | AG96: 史文涵1-史文涵 | AH96: 真实产生的退费 | AI96: 何禹轩 | AJ96: BJWY2841652509 | AK96: 0 | AL96: 2025/06/13 | AM96: 6.18退款完成22397.3———————— 6.17已提交报账单 6.16转手工22397.3，待客户短信确认（@史文涵1 (史文涵)@郭又华）———————— 22397.3退回账户余额，原支付渠道微信超时失效，请提供学员本人银行卡手工退款：@谭悦9 (谭悦)@史文涵1 (史文涵)@郭又华 [图片] 暂退至学员账户，等无忧退费后一起提现 | AP96: TRUE
A97: 2025/06/12 | B97: 退费 | C97: 18686291 | D97: 史文涵1-史文涵 | F97: 谭悦9-谭悦 | H97: 代理商合作 | I97: 无忧项目 | K97: 开课后退费 | M97: 学员意愿转变_开课后 | Z97: 选择出国留学 | AB97: 学生今年计划出国，不打算考研了 | AF97: 2025-06-30 | AG97: 史文涵1-史文涵 | AH97: 真实产生的退费 | AI97: 何禹轩 | AJ97: BJWY2841652509 | AK97: 3140.1 | AL97: 2025/06/13 | AM97: 6.18退款完成22397.3———————— 6.17已提交报账单 6.16转手工22397.3，待客户短信确认（@史文涵1 (史文涵)@郭又华）———————— 22397.3退回账户余额，原支付渠道微信超时失效，请提供学员本人银行卡手工退款：@谭悦9 (谭悦)@史文涵1 (史文涵)@郭又华 [图片] 暂退至学员账户，等无忧退费后一起提现 | AP97: TRUE
A98: 2025/06/12 | B98: 退费 | C98: 18686324 | D98: 史文涵1-史文涵 | F98: 谭悦9-谭悦 | H98: 代理商合作 | I98: 无忧项目 | K98: 开课后退费 | M98: 学员意愿转变_开课后 | Z98: 选择出国留学 | AB98: 学生今年计划出国，不打算考研了 | AF98: 2025-06-30 | AG98: 史文涵1-史文涵 | AH98: 真实产生的退费 | AI98: 何禹轩 | AJ98: BJWY2841652509 | AK98: 0 | AL98: 2025/06/13 | AM98: 6.18退款完成22397.3———————— 6.17已提交报账单 6.16转手工22397.3，待客户短信确认（@史文涵1 (史文涵)@郭又华）———————— 22397.3退回账户余额，原支付渠道微信超时失效，请提供学员本人银行卡手工退款：@谭悦9 (谭悦)@史文涵1 (史文涵)@郭又华 [图片] 暂退至学员账户，等无忧退费后一起提现 | AP98: TRUE
A99: 2025/06/12 | B99: 退费 | C99: 18686362 | D99: 史文涵1-史文涵 | F99: 谭悦9-谭悦 | H99: 代理商合作 | I99: 无忧项目 | K99: 开课后退费 | M99: 学员意愿转变_开课后 | Z99: 选择出国留学 | AB99: 学生今年计划出国，不打算考研了 | AF99: 2025-06-30 | AG99: 史文涵1-史文涵 | AH99: 真实产生的退费 | AI99: 何禹轩 | AJ99: BJWY2841652509 | AK99: 3595 | AL99: 2025/06/13 | AM99: 6.18退款完成22397.3———————— 6.17已提交报账单 6.16转手工22397.3，待客户短信确认（@史文涵1 (史文涵)@郭又华）———————— 22397.3退回账户余额，原支付渠道微信超时失效，请提供学员本人银行卡手工退款：@谭悦9 (谭悦)@史文涵1 (史文涵)@郭又华 [图片] 暂退至学员账户，等无忧退费后一起提现 | AP99: TRUE
A100: 2025/06/12 | B100: 退费 | C100: 18686450 | D100: 史文涵1-史文涵 | F100: 谭悦9-谭悦 | H100: 代理商合作 | I100: 无忧项目 | K100: 开课后退费 | M100: 学员意愿转变_开课后 | Z100: 选择出国留学 | AB100: 学生今年计划出国，不打算考研了 | AF100: 2025-06-30 | AG100: 史文涵1-史文涵 | AH100: 真实产生的退费 | AI100: 何禹轩 | AJ100: BJWY2841652509 | AK100: 0 | AL100: 2025/06/13 | AM100: 6.18退款完成22397.3———————— 6.17已提交报账单 6.16转手工22397.3，待客户短信确认（@史文涵1 (史文涵)@郭又华）———————— 22397.3退回账户余额，原支付渠道微信超时失效，请提供学员本人银行卡手工退款：@谭悦9 (谭悦)@史文涵1 (史文涵)@郭又华 [图片] 暂退至学员账户，等无忧退费后一起提现 | AP100: TRUE
...

Sheet 退费（取自钉钉客服退费表单）
A1: 提交日期 | B1: 您所办理的业务类型 | C1: OA流水号 | D1: 学管姓名 | E1: 学管是否代办 | F1: 顾问姓名 | G1: 顾问是否代办 | H1: 91系统-最新报名二级渠道 | I1: 原班所属项目 | J1: 新报入班级所属项目 | K1: 退费阶段 | L1: 退费一级原因（开课前） | M1: 退费二级原因（学员意愿转变_开课后） | N1: 退费三级原因（完全匹配不上）-院校、学院、专业、专业课代码及名称 | O1: 退费详细原因说明（与OA退费详细说明保持一致） | P1: 预计报名新班学费金额 | Q1: 转班金额（请学管填写所在班级实际金额） | R1: 转班详细原因说明 | S1: 提交时间 | T1: 提交人 | U1: 退费类型 | V1: 学员姓名 | W1: 学员编码 | X1: 退费金额 | Y1: 办理日期-客服 | Z1: 退费方式-客服 | AA1: 需要跟进的顾问/学管 | AB1: 退费/转班特殊情况备注（若需要学管提供银行卡信息，可将需求填写在此处）-客服 | AC1: 是否完成退费/转班-客服 | AD1: 父记录 | AE1: 父记录
A2: 2025/06/04 | B2: 退费 | C2: NO.8358680908400807930 | D2: 郭又华 | F2: 谭悦9-谭悦 | H2: 代理商合作 | I2: 无忧项目 | K2: 开课后退费 | M2: 选择出国留学 | O2: 学生今年计划出国，不打算考研了，目前也没有其他课程需求，后边有需要再联系。 | S2: 2025-06-30 | T2: 郭又华 | U2: 真实产生的退费 | V2: 何禹轩 | W2: BJWY2841652509 | X2: 1979.6 | Y2: 2025/06/10 | Z2: 6.18退款完成22397.3—————— 6.17已经提交报账单 6.16转手工22397.3，待客户短信确认（@史文涵1 (史文涵)@郭又华）———————— 22397.3退回账户余额，原支付渠道微信超时失效，请提供学员本人银行卡手工退款：@谭悦9 (谭悦)@史文涵1 (史文涵)@郭又华 [图片] 暂退至学员账户，等无忧退费后一起提现 | AC2: TRUE
A3: 2025/06/04 | B3: 退费 | C3: 2025060402257 | D3: 黄小妹7-黄小妹 | F3: 谭悦9-谭悦 | H3: 学管续费推荐 | I3: VIP项目 | J3: 无忧项目 | K3: 开课前退费 | L3: 中心原因_开课前 | O3: 无课程消耗，需要退出报入 考研一对一VIP伴学(60小时/26考季)一对一-无忧 | P3: ¥46800.00 | S3: 2025-06-30 | T3: 黄小妹7-黄小妹 | U3: 转项目/转班/退出重报等未产生实际退费 | V3: 孙洢妮 | W3: BJWY3739115067 | X3: 46800 | Y3: 2025/06/10 | Z3: 退回账户余额 | AC3: TRUE
A4: 2025/06/12 | B4: 退费 | C4: 18686243 | D4: 史文涵1-史文涵 | F4: 谭悦9-谭悦 | H4: 代理商合作 | I4: 无忧项目 | K4: 开课后退费 | M4: 选择出国留学 | O4: 学生今年计划出国，不打算考研了 | S4: 2025-06-30 | T4: 史文涵1-史文涵 | U4: 真实产生的退费 | V4: 何禹轩 | W4: BJWY2841652509 | X4: 0 | Y4: 2025/06/13 | Z4: 6.18退款完成22397.3———————— 6.17已提交报账单 6.16转手工22397.3，待客户短信确认（@史文涵1 (史文涵)@郭又华）———————— 22397.3退回账户余额，原支付渠道微信超时失效，请提供学员本人银行卡手工退款：@谭悦9 (谭悦)@史文涵1 (史文涵)@郭又华 [图片] 暂退至学员账户，等无忧退费后一起提现 | AC4: TRUE
A5: 2025/06/12 | B5: 退费 | C5: 18686291 | D5: 史文涵1-史文涵 | F5: 谭悦9-谭悦 | H5: 代理商合作 | I5: 无忧项目 | K5: 开课后退费 | M5: 选择出国留学 | O5: 学生今年计划出国，不打算考研了 | S5: 2025-06-30 | T5: 史文涵1-史文涵 | U5: 真实产生的退费 | V5: 何禹轩 | W5: BJWY2841652509 | X5: 3140.1 | Y5: 2025/06/13 | Z5: 6.18退款完成22397.3———————— 6.17已提交报账单 6.16转手工22397.3，待客户短信确认（@史文涵1 (史文涵)@郭又华）———————— 22397.3退回账户余额，原支付渠道微信超时失效，请提供学员本人银行卡手工退款：@谭悦9 (谭悦)@史文涵1 (史文涵)@郭又华 [图片] 暂退至学员账户，等无忧退费后一起提现 | AC5: TRUE
A6: 2025/06/12 | B6: 退费 | C6: 18686324 | D6: 史文涵1-史文涵 | F6: 谭悦9-谭悦 | H6: 代理商合作 | I6: 无忧项目 | K6: 开课后退费 | M6: 选择出国留学 | O6: 学生今年计划出国，不打算考研了 | S6: 2025-06-30 | T6: 史文涵1-史文涵 | U6: 真实产生的退费 | V6: 何禹轩 | W6: BJWY2841652509 | X6: 0 | Y6: 2025/06/13 | Z6: 6.18退款完成22397.3———————— 6.17已提交报账单 6.16转手工22397.3，待客户短信确认（@史文涵1 (史文涵)@郭又华）———————— 22397.3退回账户余额，原支付渠道微信超时失效，请提供学员本人银行卡手工退款：@谭悦9 (谭悦)@史文涵1 (史文涵)@郭又华 [图片] 暂退至学员账户，等无忧退费后一起提现 | AC6: TRUE
A7: 2025/06/12 | B7: 退费 | C7: 18686362 | D7: 史文涵1-史文涵 | F7: 谭悦9-谭悦 | H7: 代理商合作 | I7: 无忧项目 | K7: 开课后退费 | M7: 选择出国留学 | O7: 学生今年计划出国，不打算考研了 | S7: 2025-06-30 | T7: 史文涵1-史文涵 | U7: 真实产生的退费 | V7: 何禹轩 | W7: BJWY2841652509 | X7: 3595 | Y7: 2025/06/13 | Z7: 6.18退款完成22397.3———————— 6.17已提交报账单 6.16转手工22397.3，待客户短信确认（@史文涵1 (史文涵)@郭又华）———————— 22397.3退回账户余额，原支付渠道微信超时失效，请提供学员本人银行卡手工退款：@谭悦9 (谭悦)@史文涵1 (史文涵)@郭又华 [图片] 暂退至学员账户，等无忧退费后一起提现 | AC7: TRUE
A8: 2025/06/12 | B8: 退费 | C8: 18686450 | D8: 史文涵1-史文涵 | F8: 谭悦9-谭悦 | H8: 代理商合作 | I8: 无忧项目 | K8: 开课后退费 | M8: 选择出国留学 | O8: 学生今年计划出国，不打算考研了 | S8: 2025-06-30 | T8: 史文涵1-史文涵 | U8: 真实产生的退费 | V8: 何禹轩 | W8: BJWY2841652509 | X8: 0 | Y8: 2025/06/13 | Z8: 6.18退款完成22397.3———————— 6.17已提交报账单 6.16转手工22397.3，待客户短信确认（@史文涵1 (史文涵)@郭又华）———————— 22397.3退回账户余额，原支付渠道微信超时失效，请提供学员本人银行卡手工退款：@谭悦9 (谭悦)@史文涵1 (史文涵)@郭又华 [图片] 暂退至学员账户，等无忧退费后一起提现 | AC8: TRUE
A9: 2025/06/12 | B9: 退费 | C9: 18686483 | D9: 史文涵1-史文涵 | F9: 谭悦9-谭悦 | H9: 代理商合作 | I9: 无忧项目 | K9: 开课后退费 | M9: 选择出国留学 | O9: 学生今年计划出国，不打算考研了 | S9: 2025-06-30 | T9: 史文涵1-史文涵 | U9: 真实产生的退费 | V9: 何禹轩 | W9: BJWY2841652509 | X9: 2530.3 | Y9: 2025/06/13 | Z9: 6.18退款完成22397.3———————— 6.17已提交报账单 6.16转手工22397.3，待客户短信确认（@史文涵1 (史文涵)@郭又华）———————— 22397.3退回账户余额，原支付渠道微信超时失效，请提供学员本人银行卡手工退款：@谭悦9 (谭悦)@史文涵1 (史文涵)@郭又华 [图片] 暂退至学员账户，等无忧退费后一起提现 | AC9: TRUE
A10: 2025/06/12 | B10: 退费 | C10: 18686559 | D10: 史文涵1-史文涵 | F10: 谭悦9-谭悦 | H10: 代理商合作 | I10: 无忧项目 | K10: 开课后退费 | M10: 选择出国留学 | O10: 学生今年计划出国，不打算考研了 | S10: 2025-06-30 | T10: 史文涵1-史文涵 | U10: 真实产生的退费 | V10: 何禹轩 | W10: BJWY2841652509 | X10: 11152.3 | Y10: 2025/06/13 | Z10: 6.18退款完成22397.3———————— 6.17已提交报账单 6.16转手工22397.3，待客户短信确认（@史文涵1 (史文涵)@郭又华）———————— 22397.3退回账户余额，原支付渠道微信超时失效，请提供学员本人银行卡手工退款：@谭悦9 (谭悦)@史文涵1 (史文涵)@郭又华 [图片] 暂退至学员账户，等无忧退费后一起提现 | AC10: TRUE
A11: 2025/06/15 | B11: 转班 | D11: 史文涵1-史文涵 | F11: 谭悦9-谭悦 | H11: 代理商合作 | I11: 无忧项目 | R11: 退费需转班 | S11: 2025-06-30 | T11: 史文涵1-史文涵 | V11: 何禹轩 | W11: BJWY2841652509 | X11: 7890.6 | Y11: 2025/06/15 | Z11: 已转班 | AC11: TRUE
A12: 2025/06/18 | B12: 转班 | D12: 唐源曼 | F12: 谭悦9-谭悦 | G12: TRUE | H12: 知了好学 | I12: 集训营项目 | R12: 学生从英政经综班转到英政数班。价格一样，开课前转班。 | S12: 2025-06-30 | T12: 谭悦9-谭悦 | V12: 王英帆 | W12: BJWY4965756550 | X12: 94500 | Y12: 2025/06/19 | Z12: 已转班 | AC12: TRUE
A13: 2025/06/23 | B13: 转班 | D13: 郝琨 | F13: 谭悦9-谭悦 | H13: 阿里本地通 | I13: 无忧项目 | R13: 姓名：朱建金 电话：15910521973 学员编号：BJWY1520278143 转班原因：学生目前没定好院校，先按照英一准备 转班信息： WYE26028、WYE26029转WYE26026、WYE26027 已登记表格，辛苦老师办理 | S13: 2025-06-30 | T13: 郝琨 | V13: 朱建金 | W13: BJWY1520278143 | X13: 9959.6 | Y13: 2025/06/24 | Z13: 已转班 | AC13: TRUE
A14: 2025/06/24 | B14: 退费 | C14: 2882303761518362655 | D14: 王天义56-王天义 | E14: TRUE | F14: 谭悦9-谭悦 | H14: 学管续费推荐 | I14: VIP项目 | K14: 开课后退费 | M14: 认为课程用处不大/不适合自己 | O14: 25 考季复试学员，已上岸，交接时与学员电话沟通，剩余 2课时，学员要求退费，劝说保留四六级，学生 ok；5月 26 日与学员沟通上六级冲刺课程，学员不回复；目前要求退费，再次劝说课程报名时候应该用了一些优惠，退费的话课时可惜，推荐六级或雅思课，学员坚持退费。 退费核算：补专业课优惠：4800-4554=246 元；退费金额=总课时费-消耗课时费-补专业课优惠=9746-10*900-246 =500 元 | S14: 2025-06-30 | T14: 王天义56-王天义 | U14: 真实产生的退费 | V14: 张梓靖 | W14: BJWY8290701880 | X14: 500 | Y14: 2025/06/30 | Z14: 微信退回500元，账户246元补专业课优惠 | AC14: TRUE
A15: 2025/06/25 | B15: 转班 | D15: 葛铭 | F15: 谭悦9-谭悦 | H15: 大众点评 | I15: 无忧项目 | R15: 学员专业变化，需要转班 | S15: 2025-06-30 | T15: 葛铭 | V15: 付豪 | W15: BJWY0827309575 | X15: 9849.7 | Y15: 2025/06/25 | Z15: 已转班 | AC15: TRUE
A16: 2025/06/25 | B16: 退费 | C16: NO.1152921504608122823 | D16: 王嘉庆5-王嘉庆 | F16: 谭悦9-谭悦 | H16: 内部工单推荐 | I16: 无忧项目 | J16: 无忧项目 | K16: 开课后退费 | O16: 学生目标专业改考408，打算将专业课一对一课程改为408班课 | P16: ¥18800.00 | S16: 2025-06-30 | T16: 王嘉庆5-王嘉庆 | U16: 转项目/转班/退出重报等未产生实际退费 | V16: 林子策 | W16: BJWY0442645574 | X16: 8873 | Y16: 2025/06/28 | Z16: 退回学员账户余额 | AC16: TRUE
A17: 2025/06/27 | B17: 转班 | D17: 李小龙25-李小龙 | F17: 谭悦9-谭悦 | H17: 学管转介绍 | I17: 四六级项目 | R17: 学员暑期有事情，转到二期上课 | S17: 2025-06-30 | T17: 李小龙25-李小龙 | V17: 程悦 | W17: BJWY8477545262 | X17: 6480 | Y17: 2025/06/27 | Z17: 已转班 | AC17: TRUE
A18: 2025/06/30 | B18: 转班 | D18: 许庆典 | F18: 谭悦9-谭悦 | H18: 社群、虚拟人 | I18: 无忧项目 | R18: 学生英语一改考英语二。 | S18: 2025-06-30 | T18: 许庆典 | V18: 张霄翮 | W18: BJWY1043586545 | X18: 12800 | Y18: 2025/06/30 | Z18: 已转班 | AC18: TRUE
W19: 谭悦退费 | X19: =SUM(X2:X18) -> 220050.2
A20: 2025/06/02 | B20: 退费 | C20: 2025052903139 | D20: 张泽7-张泽 | F20: 赵星火 | H20: 学管续费推荐 | I20: VIP项目 | J20: 无忧项目 | K20: 开课后退费 | M20: 认为课程用处不大/不适合自己 | O20: 投诉学员乔怡娜，处理方案：一对一剩余课时费4000元，特殊申请转入无忧走读班级（原价25600），无需补充差价；6.28开课：英语二强化+冲刺WYFE26007,WYFE26008 政治：WYFP26003,WYFP26004 姓名：乔怡娜 学员号：BJWY3184144484 课时包编码：LP1715735991942，考研一对一伴学班（25考季） 退费原因：公共课未考到目标学校分数线剩余5小时需要退费，报如无忧班课 退费金额=报名金额-课消金额=32000-800*35=4000元 | P20: ¥4000.00 | S20: 2025-06-30 | T20: 张泽7-张泽 | U20: 转项目/转班/退出重报等未产生实际退费 | V20: 乔怡娜 | W20: BJWY3184144484 | Y20: 2025/06/02 | Z20: 退至学员账户 | AC20: TRUE | AD20: 特殊投诉学员，退转特批入班，换顾问跟进，新班级未绑定业绩， | AE20: 4000
A21: 2025/06/04 | B21: 转班 | D21: 葛铭 | F21: 赵星火 | H21: 百度投放 | I21: 无忧项目 | R21: 学员时间冲突，申请转班 | S21: 2025-06-30 | T21: 葛铭 | V21: 李尚烨 | W21: BJWY8264939203 | X21: 44800 | Y21: 2025/06/04 | Z21: 已转班 | AC21: TRUE
A22: 2025/06/04 | B22: 退费 | C22: 18668674 | D22: 葛铭 | F22: 赵星火 | H22: 新东方PC官网 | I22: 无忧项目 | K22: 开课后退费 | M22: 家人不支持考研/不支持跟班学习/意见不一致 | O22: 学员家长生病，无法考研，申请退费 | S22: 2025-06-30 | T22: 葛铭 | U22: 真实产生的退费 | V22: 董菡 | W22: BJWY1429919607 | X22: 25758.3 | Z22: 【作废】学管已重新提交OA | AC22: TRUE
A23: 2025/06/06 | B23: 退费 | C23: 18668674 | D23: 葛铭 | F23: 赵星火 | H23: 新东方官网M站 | I23: 无忧项目 | K23: 开课后退费 | O23: 学员 家长生病，放弃考研 | S23: 2025-06-30 | T23: 葛铭 | U23: 真实产生的退费 | V23: 董菡 | W23: BJWY1429919607 | X23: 21026.2 | Y23: 2025/06/10 | Z23: 支付宝退回 | AC23: TRUE
A24: 2025/06/06 | B24: 退费 | C24: 18674781 | D24: 葛铭 | F24: 赵星火 | H24: 新东方官网M站 | I24: 无忧项目 | K24: 开课后退费 | O24: 学员 家长生病，放弃考研 | S24: 2025-06-30 | T24: 葛铭 | U24: 真实产生的退费 | V24: 董菡 | W24: BJWY1429919607 | X24: 4732.1 | Y24: 2025/06/10 | Z24: 支付宝退回 | AC24: TRUE
A25: 2025/06/08 | B25: 退费 | C25: NO.2882303761518315242 | D25: 王嘉庆5-王嘉庆 | F25: 赵星火 | H25: 新东方PC官网 | I25: 无忧项目 | K25: 开课后退费 | M25: 家人不支持考研/不支持跟班学习/意见不一致 | O25: 学生家中有特殊情况，目前时间不支持继续考研，且不考虑转其他课程 | S25: 2025-06-30 | T25: 王嘉庆5-王嘉庆 | U25: 真实产生的退费 | V25: 董菡 | W25: BJWY1429919607 | X25: 727 | Y25: 2025/06/14 | Z25: 支付宝原路退回 | AC25: TRUE
A26: 2025/06/13 | B26: 退费 | C26: 2025060301380 | D26: 李玉迪1-李玉迪 | F26: 赵星火 | G26: TRUE | H26: 学管续费推荐 | I26: 四六级项目 | K26: 开课后退费 | M26: 自己找到老师复习 | O26: 学员觉得之后没有什么课程需要了。申请退费，学生有考研想法，确定在别的机构学习。这个学生只想上女老师的课，但是学数学专业，专业课数学部分只有曹超老师可以讲解，上过一次曹老师的课觉得不太喜欢，目前跟成小伟老师上课，成老师讲不了考研专业课部分。 | S26: 2025-06-30 | T26: 李玉迪1-李玉迪 | U26: 真实产生的退费 | V26: 潘雨时 | W26: BJWY2595990334 | X26: 20400 | Y26: 2025/06/14 | Z26: 6.17付款完成 6.14已转手工，等待用户短信自助确认 | AC26: TRUE
A27: 2025/06/10 | B27: 退费 | C27: NO.18688753 | D27: 王立颖17-王立颖 | F27: 赵星火 | H27: 内部工单推荐 | I27: 在职研项目 | K27: 开课后退费 | M27: 考研信心不足（因跟不上、基础薄弱、目标过高） | O27: 退费原因：学生目标是北大EMBA，不学习MBA 辅导课程，尝试学习过管综，觉得完全跟不上。 | S27: 2025-06-30 | T27: 王立颖17-王立颖 | U27: 真实产生的退费 | V27: 黄琳 | W27: BJWY4447076368 | X27: 11146.5 | Y27: 2025/06/14 | Z27: 微信退回28980.4（6.15） | AC27: TRUE
A28: 2025/06/10 | B28: 退费 | C28: NO.18688836 | D28: 王立颖17-王立颖 | F28: 赵星火 | H28: 内部工单推荐 | I28: 在职研项目 | K28: 开课后退费 | M28: 考研信心不足（因跟不上、基础薄弱、目标过高） | O28: 退费原因：学生目标是北大EMBA，不学习MBA 辅导课程，尝试学习过管综，觉得完全跟不上。 | S28: 2025-06-30 | T28: 王立颖17-王立颖 | U28: 真实产生的退费 | V28: 黄琳 | W28: BJWY4447076368 | X28: 10907 | Y28: 2025/06/15 | Z28: 微信退回28980.4（6.15） | AC28: TRUE
A29: 2025/06/10 | B29: 退费 | C29: NO.18688904 | D29: 王立颖17-王立颖 | F29: 赵星火 | H29: 内部工单推荐 | I29: 在职研项目 | K29: 开课后退费 | M29: 考研信心不足（因跟不上、基础薄弱、目标过高） | O29: 退费原因：学生目标是北大EMBA，不学习MBA 辅导课程，尝试学习过管综，觉得完全跟不上。 | S29: 2025-06-30 | T29: 王立颖17-王立颖 | U29: 真实产生的退费 | V29: 黄琳 | W29: BJWY4447076368 | X29: 4760.7 | Y29: 2025/06/14 | Z29: 微信退回28980.4（6.15） | AC29: TRUE
A30: 2025/06/10 | B30: 退费 | C30: NO.18688920 | D30: 王立颖17-王立颖 | F30: 赵星火 | H30: 内部工单推荐 | I30: 在职研项目 | K30: 开课后退费 | M30: 考研信心不足（因跟不上、基础薄弱、目标过高） | O30: 退费原因：学生目标是北大EMBA，不学习MBA 辅导课程，尝试学习过管综，觉得完全跟不上。 | S30: 2025-06-30 | T30: 王立颖17-王立颖 | U30: 真实产生的退费 | V30: 黄琳 | W30: BJWY4447076368 | X30: 2166.2 | Y30: 2025/06/14 | Z30: 微信退回28980.4（6.15） | AC30: TRUE
A31: 2025/06/22 | B31: 退费 | C31: 18724459 | D31: 黄小妹7-黄小妹 | F31: 赵星火 | H31: 学管续费推荐 | I31: 无忧项目 | K31: 开课后退费 | O31: 【开课后退费】学生毕业后北京无住宿条件，已经入营，退费班课。 | S31: 2025-06-30 | T31: 黄小妹7-黄小妹 | U31: 真实产生的退费 | V31: 赵祥辰 | W31: BJWY8097075006 | X31: 11623.1 | Y31: 2025/06/23 | Z31: 微信退回 | AC31: TRUE
A32: 2025/06/22 | B32: 退费 | C32: 18724348 | D32: 黄小妹7-黄小妹 | F32: 赵星火 | H32: 学管续费推荐 | I32: 无忧项目 | K32: 开课后退费 | O32: 【开课后退费】学生毕业后北京无住宿条件，已经入营，退费班课。 | S32: 2025-06-30 | T32: 黄小妹7-黄小妹 | U32: 真实产生的退费 | V32: 赵祥辰 | W32: BJWY8097075006 | X32: 443.6 | Y32: 2025/06/23 | Z32: 微信退回 | AC32: TRUE
A33: 2025/06/06 | B33: 退费 | C33: NO.7782220156097415399 | D33: 刘佳林25-刘佳林 | F33: 高龙明,赵星火 | H33: 直访 | I33: 集训营项目 | K33: 开课后退费 | M33: 认为课程用处不大/不适合自己 | O33: 学生目前三战，目前觉得专业课不符合预期，不适合自己，也不考虑其他课程，经挽单也坚持退费 | S33: 2025-06-30 | T33: 刘佳林25-刘佳林 | U33: 真实产生的退费 | V33: 王嘉祥 | W33: BJWY4539181865 | X33: =AE33/2 -> 3116.7 | Y33: 2025/06/15 | Z33: 6.25付款成功。退款待到账（6.25）,6.17转手工退 [图片] | AC33: TRUE | AD33: 高龙明分单 | AE33: 6233.4
C34: 18733849 | D34: 郝琨 | E34: FALSE | F34: 陈伟钰1-陈伟钰,苏乾楠-苏乾楠（北京考研四六级） | G34: FALSE | H34: 直访 | I34: 无忧项目 | J34: 无忧项目 | K34: 开课前退费 | L34: 中心原因_开课前 | Q34: 退出重报（取消班/合班/延转/选班/扩科等） | T34: 郝琨 | U34: 转项目/转班/退出重报等未产生实际退费 | V34: 张文 | W34: BJWY3211945534 | X34: =AE34/2 -> 5000 | Y34: 45836 | Z34: 账户余额 | AC34: TRUE | AD34: 高龙明分单 | AE34: 10000 | AM34: 退回学员账户余额
F35: 赵星火 | I35: 在线网课 | O35: 生姓名： 张文学员编号：BJWY3211945534退费方式：退出重报退费原因：学生要考自主命题院校，从408班课转专业课一对一退费班级：WYC26001退费明细：实缴价格=10000元，退出金额10000元 | V35: 学员1pg3r | W35: 108722739 | X35: 8464 | Y35: 2025/06/28
W36: 星火退费 | X36: =SUM(X20:X34:X35) -> 175071.4

Sheet 顾问绩效
B2: FY26-6月个性化顾问绩效核算
B3: 工号 | C3: 顾问 | D3: 转介绍工单目标 | E3: 转介绍工单完成 | F3: 顾问转介绍得分（50） | G3: 转介绍签约目标 | H3: 转介绍签约完成 | I3: 转介绍签约的份（30） | J3: 主动转化率目标 | K3: 主动转化率 | L3: 被动转化率目标 | M3: 被动转化率 | N3: 转化率得分（20） | O3: 合计得分 | P3: 发放比例 | Q3: 月度绩效标准 | R3: 月绩效应发
B4: 238256 | C4: 赵星火 | D4: 3 | E4: 3 | F4: 50 | G4: 1 | H4: 2 | I4: 30 | J4: 0.3 | K4: =39/135 -> 0.28888889 | L4: 0.1 | M4: =3/60 -> 0.05 | N4: 0 | O4: =F4+I4+N4 -> 80 | P4: =IF(AND(O4<70),0,IF(AND(O4>=70,O4<90),O4/100,1)) -> 0.8 | Q4: 1000 | R4: =Q4*P4 -> 800
B5: 341422 | C5: 谭悦 | D5: 3 | E5: 7 | F5: 50 | G5: 1 | H5: 2 | I5: 30 | J5: 0.3 | K5: =52/132 -> 0.39393939 | L5: 0.1 | M5: =8/51 -> 0.15686275 | N5: 20 | O5: =F5+I5+N5 -> 100 | P5: =IF(AND(O5<70),0,IF(AND(O5>=70,O5<90),O5/100,1)) -> 1 | Q5: 2000 | R5: =Q5*P5 -> 2000

Sheet 91签约明细
B2: 签约单录入人 | C2: 代售标签 | D2: 求和项:学费
B3: 谭悦 | C3: 在线网课 | D3: 41749.7
C4: (空白) | D4: 1468317.2
B5: 谭悦 汇总 | D5: 1510066.9
B6: 赵星火 | C6: 在线网课 | D6: 67148.9
C7: (空白) | D7: 922880.8
B8: 赵星火 汇总 | D8: 990029.7
B9: 总计 | D9: 2500096.6
A11: 代售标签 | B11: 序号 | C11: 学校 | D11: 部门 | E11: 资源姓名 | F11: 资源ID | G11: 资源录入人 | H11: 资源录入时间 | I11: 资源描述 | J11: 市场活动 | K11: 资源年级 | L11: 分配顾问/TMK | M11: 一级获取渠道 | N11: 二级获取渠道 | O11: 转介绍人 | P11: TMK激活人 | Q11: TMK激活处理时间 | R11: 工单姓名 | S11: 跟进顾问 | T11: 工单ID | U11: 工单类型 | V11: 工单录入时间 | W11: 工单等级 | X11: 咨询课程 | Y11: 工单年级 | Z11: 学校 | AA11: 院系 | AB11: 专业 | AC11: 签约学生姓名 | AD11: 签约单ID | AE11: 签约单录入人 | AF11: 签约单录入时间 | AG11: 签约单更新人 | AH11: 签约单更新时间 | AI11: 班号 | AJ11: 班级名称 | AK11: 面询表类型 | AL11: 订金 | AM11: 学费 | AN11: 续费类型 | AO11: 推荐人 | AP11: 类型 | AQ11: 是否交接 | AR11: 操作人编号 | AS11: 学员号 | AT11: 听课证号 | AU11: 报班日期 | AV11: 学员状态 | AW11: 回访记录 | AX11: 新老生类型 | AY11: 退费金额 | AZ11: 退费日期 | BA11: 课程类型 | BB11: 客户ID | BC11: 是否新东方在线签约 | BD11: 考季 | BE11: 报名产品 | BF11: 报名科目 | BG11: 意向报考专业 | BH11: 学校班型/类型 | BI11: 是否关联协议 | BJ11: 特殊备注 | BK11: 产品品类 | BL11: 业务类型 | BM11: 签约列表在线学员ID | BN11: 大学生源类型 | BO11: 资源来源
B12: 1 | C12: 北京大学部 | D12: 国内大学部 | E12: 同学 | F12: 116722017 | G12: 吴凯龙 | H12: 2025-06-30 13:56:56 | I12: 谭悦9的顾问转介绍工单 | K12: 大二 | L12: 谭悦 | M12: 转介绍 | N12: 顾问转介绍-老带新 | O12: 谭悦tanyue9@xdf.cn | R12: 姜源 | S12: 谭悦 | T12: 28724631 | U12: 正常工单 | V12: 2025-06-30 14:07 | W12: A（六个月内有报课意向工单） | X12: 六级 | Y12: 大二 | Z12: 西华大学 | AA12: 金融 | AB12: 金融 | AC12: 姜源 | AD12: 5461899 | AE12: 谭悦 | AF12: 2025-06-30 19:54 | AG12: 谭悦 | AH12: 2025-06-30 19:54 | AI12: ZVVB26001 | AJ12: 六级暑假集训营（24H冲刺直播） | AK12: 国内考试 | AM12: 15000 | AO12: 谭悦 | AP12: 新签 | AQ12: 已交接 | AR12: BJWY2011wXCx1W | AS12: BJWY7326008490 | AT12: ZVVB260010032 | AU12: 2025-06-30 | AW12: 回访人：谭悦，回访时间：2025-06-30 14:07，回访内容：准备报名六级集训营 ；|回访人：谭悦，回访时间：2025-06-30 19:54，回访内容：1 | BB12: 80739196 | BC12: 否 | BD12: 26上考季 | BE12: 六级无忧计划 | BH12: 国内高校-C9 | BI12: 是 | BL12: 报名 | BN12: 本地人外地大学(归巢) | BO12: 客服
A13: 在线网课 | B13: 2 | C13: 北京大学部 | D13: 国内大学部 | E13: 魏小姐 | F13: 115503604 | G13: 张亚男 | H13: 2025-06-20 19:56:01 | I13: 渠道录入来源：集团百度投放-基木鱼 账户名：baidu-大学-总部-A22KA00038 线索ID：250620465438808391 线索时间：2025-06-20 19:55:56 页面名称：新东方考研品专 姓名：魏小姐 城市：北京 IP：2409:8a00:8433:4f0:d0aa:bf9:75d3:a380 来源页：https://aisite.wejianzhan.com/site/wjzswa2z/73c5def5-883c-47c6-9bd9-9ce1d92bf9bf?wd=%E6%96%B0%E4%B8%9C%E6%96%B9%E8%80%83%E7%A0%94&utm_source=0_02_searchengine_Baidu_m_market&utm_medium=CPD&utm_campaign=DXSYB_XX_BD_DXPP-WY_M_240924&utm_1st_id=7&utm_2nd_id=63&xdf_source_channel_code=9ddc99f35fa8479d92b29f6c0ee04c33&wid=65437bc36a42436d8a6ec1e177ccb52f_0_0 | J13: 2026财年第1财月集团百度投放-基木鱼 | L13: 赵星火 | M13: 线上运营-投放 | N13: 集团-百度品专 | R13: 魏小姐 | S13: 赵星火 | T13: 28488427 | U13: 正常工单 | V13: 2025-06-20 20:27 | W13: A（六个月内有报课意向工单） | X13: MBA | Y13: 在职 | Z13: 北京工业大学 | AA13: 信息学部 | AB13: 信息安全（实验班） | AC13: 魏小姐 | AD13: 5433227 | AE13: 赵星火 | AF13: 2025-06-30 20:38 | AG13: 赵星火 | AH13: 2025-06-30 20:41 | AI13: 45374323934 | AJ13: 2026考研管综全科在职优学班（4期） | AK13: 国内考试 | AM13: 11385 | AP13: 新签 | AQ13: 无须交接 | AU13: 2025-06-30 | AW13: 回访人：赵星火，回访时间：2025-06-21 11:06，回访内容：回访学生现在了解情况跟进中，发送充足介绍内容；|回访人：赵星火，回访时间：2025-06-27 16:52，回访内容：感觉价格贵，在就是重读的话，没有择校服务这些要跟家里在沟通下。；|回访人：赵星火，回访时间：2025-06-30 17:10，回访内容：关注学生这边重读条件，跟进中，要过线不过线的问题。 | BA13: 长期班 | BB13: 80201508 | BC13: 是 | BD13: 26考季 | BE13: 考研在职管理类冲刺精讲班 | BF13: 英语 | BH13: 国内高校-211 | BI13: 否 | BM13: 110462239 | BO13: 集团百度投放-基木鱼
B14: 3 | C14: 北京大学部 | D14: 国内大学部 | E14: 郭宸宇 | F14: 116756538 | G14: 李润基 | H14: 2025-06-30 15:42:33 | I14: 续费原因：家长对数学没需求了，想了解六级班课，家长已主动联系谭悦老师（原来的顾问），很信任原顾问谭悦老师；该学生为保护期内续费，原顾问：国内大学部-谭悦(tanyue9@xdf.cn) | K14: 大一 | L14: 谭悦 | M14: 转介绍 | N14: 学管续费推荐 | O14: 李润基lirunji@xdf.cn | R14: 郭宸宇 | S14: 谭悦 | T14: 28737200 | U14: 续费工单 | V14: 2025-06-30 15:55 | W14: A（六个月内有报课意向工单） | X14: 六级 | Y14: 大一 | Z14: 北京工业大学 | AA14: 经济与管理学院 | AB14: 金融学 | AC14: 郭宸宇 | AD14: 5406309 | AE14: 谭悦 | AF14: 2025-06-30 19:42 | AG14: 谭悦 | AH14: 2025-06-30 19:42 | AI14: WYSJ25033 | AJ14: 六级无忧计划 | AK14: 国内考试 | AM14: 5180 | AN14: 同科续费 | AO14: 李润基 | AP14: 续班 | AQ14: 已交接 | AR14: WebReg | AS14: BJWY5305138836 | AT14: WYSJ250330038 | AU14: 2025-06-30 | AW14: 回访人：谭悦，回访时间：2025-06-30 15:55，回访内容：微信跟进中， 六级暑假班 ；|回访人：谭悦，回访时间：2025-06-30 19:42，回访内容：签约 | BB14: 59798822 | BC14: 否 | BD14: 25下考季 | BE14: 六级无忧计划 | BH14: 国内高校-211 | BI14: 是 | BL14: 报名 | BN14: 本地人本地大学(常规) | BO14: 学管续费推荐
A15: 在线网课 | B15: 4 | C15: 北京大学部 | D15: 国内大学部 | E15: 上海市4988 | F15: 116596886 | G15: 杨俊42(国内) | H15: 2025-06-28 18:59:51 | I15: 渠道录入来源：新东方PC官网-客服 意向城市：北京访客省/城市：上海市 访客静态ID：01000000034659110818227981814988 接待分组ID：70447 搜索引擎： 搜索词： 关键词： 设备类型：pc 访客IP：124.76.128.169 对话详细内容：AI-Lbo0rDBXCyBY 2025-06-28 18:56:22_x000D_ 您好同学,欢迎访问北京新东方考研四六级中心. 考研线下课程26/27考季【考研全年集训营】【考研半年集训营】【考研全科线下走读班】【考研寒/暑假集训营】【考研一对一】【考研专业课】【四/六级课程】，热门课程火热报名中,咨询即可领取专享优惠。 **【考研全年集训营】=ff761f# **【考研半年集训营】=ff6b6b# **【考研全科线下走读班】=ffc158# **【考研寒/暑假集训营】=ffc158# **【考研一对一】=ff761f# **【考研专业课】=ff6caa# **【四/六级课程】=ff6caa# **【考研冲刺班】=60e27e#_x000D_ _x000D_ AI-Lbo0rDBXCyBY 2025-06-28 18:56:25_x000D_ 您是想咨询【线下课程】【线上课程】【考研规划】还是【在职考研】呢？**【线下课程】# **【线上课程】#**【考研规划】#**【在职考研】#_x000D_ _x000D_ 01000000034659110818227981814988 2025-06-28 18:56:37_x000D_ 【线上课程】_x000D_ _x000D_ AI-Lbo0rDBXCyBY 2025-06-28 18:56:40_x000D_ 同学，你现在是在校还是在职呢？_x000D_ _x000D_ 01000000034659110818227981814988 2025-06-28 18:56:48_x000D_ 在校_x000D_ _x000D_ AI-Lbo0rDBXCyBY 2025-06-28 18:56:52_x000D_ 具体是想报考什么学校和专业呢？_x000D_ _x000D_ 01000000034659110818227981814988 2025-06-28 18:57:09_x000D_ 想报考上海财经大学的管理科学与工程专业_x000D_ _x000D_ AI-Lbo0rDBXCyBY 2025-06-28 18:57:12_x000D_ 好的，我这边安排专业老师给您回电，详细沟通一下，请问您的电话是多少呢？_x000D_ _x000D_ 01000000034659110818227981814988 2025-06-28 18:57:28_x000D_ 能不能微信，不方便电话_x000D_ _x000D_ AI-Lbo0rDBXCyBY 2025-06-28 18:57:32_x000D_ 那方便接收短信吗？您可以先留个电话，我安排顾问先给您发条短信介绍下，或者微信也可以。_x000D_ _x000D_ 01000000034659110818227981814988 2025-06-28 18:57:50_x000D_ 微信号是m17358738071_x000D_ _x000D_ AI-Lbo0rDBXCyBY 2025-06-28 18:57:54_x000D_ 好的，确认一下您的号码是否正确呢？_x000D_ _x000D_ 01000000034659110818227981814988 2025-06-28 18:58:16_x000D_ 正确_x000D_ _x000D_ AI-Lbo0rDBXCyBY 2025-06-28 18:58:20_x000D_ 同学怎么称呼呢？_x000D_ _x000D_ 01000000034659110818227981814988 2025-06-28 18:59:28_x000D_ 先加我微信再说别的_x000D_ _x000D_ AI-Lbo0rDBXCyBY 2025-06-28 18:59:31_x000D_ 这边马上安排顾问老师联系您，预计半个小时左右给您回电请注意接听~_x000D_ _x000D_ 来源页：https://www.xdf.cn/beijing/ 备注： | J15: 2026财年第1财月易聊新东方PC官网 | L15: 王静静 | M15: 新东方官网 | N15: 新东方PC官网 | P15: 王静静 | Q15: 2025-06-28 19:58:25 | R15: 上海市4988 | S15: 赵星火 | T15: 28693701 | U15: 正常工单 | V15: 2025-06-29 11:05 | W15: A（六个月内有报课意向工单） | X15: 考研专业课 | Y15: 大三 | Z15: 上海财经大学 | AA15: 信息管理与工程学院 | AB15: 管理科学与工程 | AC15: 上海市4988 | AD15: 5459675 | AE15: 赵星火 | AF15: 2025-06-29 20:10 | AG15: 赵星火 | AH15: 2025-06-29 20:14 | AI15: 10684230642 | AJ15: 2026考研管综全科在校直通车（3期） | AK15: 国内考试 | AM15: 10778 | AP15: 新签 | AQ15: 无须交接 | AU15: 2025-06-29 | AW15: 回访人：赵星火，回访时间：2025-06-29 11:05，回访内容：学生咨询专业课的考研辅导，开学大四考本校管理科技工程也想了解网课的英证数，已经推荐跟家里沟通 | BA15: 长期班 | BB15: 80705989 | BC15: 是 | BD15: 26考季 | BE15: 考研专业课150 | BF15: 专业课150 | BG15: 其他 | BH15: 国内高校-211 | BI15: 否 | BM15: 110457362 | BN15: 外地人外地大学(常规) | BO15: 新东方官网-易聊
B16: 5 | C16: 北京大学部 | D16: 国内大学部 | F16: 95537575 | H16: 2025-02-25 13:45:01 | I16: 知春路 赵星火(资源备注人:李雪68;资源备注时间:2025-02-25 13:46) | K16: 未知 | L16: 赵星火 | M16: 直访 | N16: 直访 | R16: 张文 | S16: 陈伟钰 | T16: 28714784 | U16: 续费工单 | V16: 2025-06-29 14:15 | W16: A（六个月内有报课意向工单） | X16: 考研专业课,考研无忧计划 | Y16: 大三 | Z16: 北京邮电大学世纪学院 | AA16: 计算机科学与技术系 | AB16: 计算机科学与技术（移动互联网应用方向） | AC16: 张文 | AD16: 5458743 | AE16: 赵星火 | AF16: 2025-06-29 14:17 | AG16: 陈伟钰 | AH16: 2025-06-29 15:39 | AK16: 国内考试 | AM16: 5000 | AP16: 分单 | AQ16: 已交接 | AS16: BJWY3211945534 | AW16: 回访人：陈伟钰，回访时间：2025-06-29 14:15，回访内容：1；|回访人：陈伟钰，回访时间：2025-06-29 14:17，回访内容：1 | BB16: 67265543 | BC16: 否 | BD16: 26考季 | BE16: 无忧计划-啄木鸟,考研专业课150 | BF16: 英语,政治,数学,专业课150 | BH16: 国内高校-双非 | BI16: 否 | BN16: 本地人本地大学(常规)
B17: 6 | C17: 北京大学部 | D17: 国内大学部 | E17: 罗宇航 | F17: 116618352 | G17: 马一鸣 | H17: 2025-06-29 13:03:33 | I17: 续费原因：交3000的升级费，辛苦老师收取一下，学生知道；该学生为保护期内续费，原顾问：国内大学部-谭悦(tanyue9@xdf.cn) | K17: 大三 | L17: 谭悦 | M17: 转介绍 | N17: 学管续费推荐 | O17: 马一鸣mayiming16@xdf.cn | R17: 罗宇航 | S17: 谭悦 | T17: 28714516 | U17: 续费工单 | V17: 2025-06-29 13:52 | W17: A（六个月内有报课意向工单） | X17: 考研专业课 | Y17: 大三 | Z17: 天津大学 | AA17: 化工学院 | AB17: 化学工程与工艺 | AC17: 罗宇航 | AD17: 5458704 | AE17: 谭悦 | AF17: 2025-06-29 14:03 | AG17: 谭悦 | AH17: 2025-07-01 10:11 | AI17: LP17511769792272 | AJ17: 985院校升级费-无忧 | AK17: 国内考试 | AM17: 3000 | AO17: 马一鸣 | AP17: 续班 | AQ17: 已交接 | AS17: BJWY7777555488 | AU17: 2025-06-29 | AW17: 回访人：谭悦，回访时间：2025-06-29 13:52，回访内容：1 | BB17: 65389384 | BC17: 否 | BD17: 26考季 | BE17: 考研专业课150 | BF17: 专业课150 | BG17: 其他 | BH17: 国内高校-985 | BI17: 否 | BN17: 本地人本地大学(常规) | BO17: 学管续费推荐
A18: 在线网课 | B18: 7 | C18: 北京大学部 | D18: 国内大学部 | E18: 刘菊 | F18: 102646871 | G18: 李雪68 | H18: 2025-05-15 15:14:16 | K18: 大三 | L18: 谭悦 | M18: 转介绍 | N18: 顾问转介绍-老带新 | O18: 吴嘉豪 | R18: 赵翔宇 | S18: 谭悦 | T18: 27898670 | U18: 正常工单 | V18: 2025-05-15 15:28 | W18: A（六个月内有报课意向工单） | X18: 线上考研产品 | Y18: 大三 | Z18: 北京理工大学 | AA18: 宇航学院 | AB18: 飞行器设计与工程 | AC18: 赵翔宇 | AD18: 5404397 | AE18: 谭悦 | AF18: 2025-06-28 12:46 | AG18: 谭悦 | AH18: 2025-06-28 12:46 | AI18: 31181722777 | AJ18: 2026考研政治直通车 6期 | AK18: 国内考试 | AM18: 3901.5 | AO18: 吴嘉豪 | AP18: 新签 | AQ18: 无须交接 | AU18: 2025-06-28 | AW18: 回访人：谭悦，回访时间：2025-06-23 15:56，回访内容：邀约来校区沟通 考研规划 ；|回访人：谭悦，回访时间：2025-06-28 12:46，回访内容：签约 | BA18: 长期班 | BB18: 30895369 | BC18: 是 | BD18: 26考季 | BE18: 线上直通车 | BF18: 政治 | BH18: 国内高校-985 | BI18: 否 | BM18: 104592631 | BN18: 本地人本地大学(常规) | BO18: 客服
A19: 在线网课 | B19: 8 | C19: 北京大学部 | D19: 国内大学部 | F19: 115078495 | H19: 2025-06-18 15:03:49 | I19: 【小红书资源】 一会儿到知春路面询 | K19: 未知 | L19: 赵星火 | M19: 线上运营-小红书 | N19: 小红书 | R19: 韩宜航 | S19: 赵星火 | T19: 28704683 | U19: 续费工单 | V19: 2025-06-28 14:12 | W19: A（六个月内有报课意向工单） | X19: 线上考研产品 | Y19: 大四 | Z19: 北京工业大学 | AA19: 环境与生命学部 | AB19: 化学生物学 | AC19: 韩宜航 | AD19: 5397207 | AE19: 赵星火 | AF19: 2025-06-28 14:13 | AG19: 赵星火 | AH19: 2025-06-28 14:13 | AI19: 27469816685 | AJ19: 2026考研英语直通车 6期,2026考研政治直通车 6期,2026考研数学无忧计划·7期 | AK19: 国内考试 | AM19: 18814.4 | AP19: 续班 | AQ19: 无须交接 | AU19: 2025-06-28 | AW19: 回访人：赵星火，回访时间：2025-06-28 14:12，回访内容：1；|回访人：赵星火，回访时间：2025-06-28 14:13，回访内容：1 | BA19: 长期班,长期班,长期班 | BB19: 80013959 | BC19: 是 | BD19: 26考季 | BE19: 线上直通车 | BF19: 英语,政治 | BH19: 国内高校-211 | BI19: 否 | BM19: 108722739 | BN19: 外地人本地大学(常规)
B20: 9 | C20: 北京大学部 | D20: 国内大学部 | F20: 100583092 | H20: 2025-04-24 09:32:59 | I20: 18705439787 毕业 想考北大医学或者首都医科大学 临床 咨询北京校区。辛苦老师建单 | K20: 未知 | L20: 谭悦 | M20: 线上运营-投放 | N20: 总部-百度投放 | R20: 刘紫乔 | S20: 谭悦 | T20: 28720818 | U20: 续费工单 | V20: 2025-06-29 22:22 | W20: A（六个月内有报课意向工单） | X20: 考研专业课,考研集训营 | Y20: 大学已毕业 | Z20: 山东大学 | AA20: 化学与化工学院 | AB20: 应用化学 | AC20: 刘紫乔 | AD20: 5459865 | AE20: 谭悦 | AF20: 2025-06-29 22:22 | AG20: 谭悦 | AH20: 2025-06-29 22:22 | AI20: KYJZ25007A | AJ20: 26考研政治全年集训营（强冲） | AK20: 国内考试 | AM20: 12577.6 | AN20: 同科续费 | AP20: 续班 | AQ20: 已交接 | AR20: BJWY24032w1g8X | AS20: BJWY4374635320 | AT20: KYJZ25007A0046 | AU20: 2025-06-27 | AW20: 回访人：谭悦，回访时间：2025-06-29 22:22，回访内容：1；|回访人：谭悦，回访时间：2025-06-29 22:22，回访内容：1 | BB20: 69612259 | BC20: 否 | BD20: 26考季 | BE20: 全年集训营,考研专业课300 | BF20: 英语,政治,专业课300 | BH20: 国内高校-985 | BI20: 否 | BL20: 转出
B21: 10 | C21: 北京大学部 | D21: 国内大学部 | F21: 98805854 | H21: 2025-04-04 10:21:21 | I21: 咨询考研线下课程（TMK主管分配TMK） 外呼主题：FY25-国内1月死单回访（2.3-2.9） | K21: 大学已毕业 | L21: 赵星火 | M21: 线上运营-本地生活平台 | N21: 地图标点 | R21: 刘云舒 | S21: 谭悦 | T21: 28701617 | U21: 续费工单 | V21: 2025-06-29 22:20 | W21: A（六个月内有报课意向工单） | X21: 考研专业课,考研集训营 | Y21: 在职 | Z21: 青岛科技大学 | AA21: 自动化与电子工程学院 | AB21: 电气工程及其自动化 | AC21: 刘云舒 | AD21: 5459863 | AE21: 谭悦 | AF21: 2025-06-29 22:21 | AG21: 谭悦 | AH21: 2025-06-29 22:21 | AI21: KYJZ25007A | AJ21: 26考研政治全年集训营（强冲） | AK21: 国内考试 | AM21: 5888.9 | AN21: 同科续费 | AP21: 续班 | AQ21: 已交接 | AR21: BJWY24032w1g8X | AS21: BJWY9006140904 | AT21: KYJZ25007A0045 | AU21: 2025-06-27 | AW21: 回访人：谭悦，回访时间：2025-06-29 22:20，回访内容：1；|回访人：谭悦，回访时间：2025-06-29 22:21，回访内容：1 | BB21: 65530077 | BC21: 否 | BD21: 26考季 | BE21: 全年集训营,考研专业课300 | BF21: 英语,政治,专业课300 | BH21: 国内高校-双非 | BI21: 否 | BL21: 转出
B22: 11 | C22: 北京大学部 | D22: 国内大学部 | F22: 95475458 | H22: 2025-02-24 16:56:33 | I22: 续费原因：调剂B 区学校 动物学专业 咨询调剂班 只要能上岸就行；该学生为保护期内续费，原顾问：国内大学部-赵星火(zhaoxinghuo@xdf.cn) | K22: 在职 | L22: 赵星火 | M22: 转介绍 | N22: 学管续费推荐 | R22: 都宣辰 | S22: 赵星火 | T22: 28720769 | U22: 续费工单 | V22: 2025-06-29 21:56 | W22: A（六个月内有报课意向工单） | X22: 考研集训营 | Y22: 在职 | Z22: 牡丹江大学 | AA22: 生物学 | AB22: 生物 | AC22: 都宣辰 | AD22: 5459836 | AE22: 赵星火 | AF22: 2025-06-29 21:57 | AG22: 赵星火 | AH22: 2025-06-29 21:57 | AI22: KYJZ25007A | AJ22: 26考研政治全年集训营（强冲） | AK22: 国内考试 | AM22: 12332.2 | AN22: 同科续费 | AP22: 续班 | AQ22: 无须交接 | AR22: BJWY24032w1g8X | AS22: BJWY0159234810 | AT22: KYJZ25007A0037 | AU22: 2025-06-27 | AW22: 回访人：赵星火，回访时间：2025-06-29 21:56，回访内容：1；|回访人：赵星火，回访时间：2025-06-29 21:57，回访内容：1 | BB22: 38708961 | BC22: 否 | BD22: 26考季 | BE22: 全年集训营 | BF22: 英语,政治 | BH22: 国内高校-双非 | BI22: 否 | BL22: 转出
B23: 12 | C23: 北京大学部 | D23: 国内大学部 | F23: 98805854 | H23: 2025-04-04 10:21:21 | I23: 咨询考研线下课程（TMK主管分配TMK） 外呼主题：FY25-国内1月死单回访（2.3-2.9） | K23: 大学已毕业 | L23: 赵星火 | M23: 线上运营-本地生活平台 | N23: 地图标点 | R23: 刘云舒 | S23: 谭悦 | T23: 28701617 | U23: 续费工单 | V23: 2025-06-29 22:20 | W23: A（六个月内有报课意向工单） | X23: 考研专业课,考研集训营 | Y23: 在职 | Z23: 青岛科技大学 | AA23: 自动化与电子工程学院 | AB23: 电气工程及其自动化 | AC23: 刘云舒 | AD23: 5405561 | AE23: 赵星火 | AF23: 2025-06-29 22:21 | AG23: 谭悦 | AH23: 2025-06-29 22:21 | AK23: 国内考试 | AM23: 5888.9 | AN23: 同科续费 | AP23: 分单 | AQ23: 已交接 | AS23: BJWY9006140904 | AW23: 回访人：谭悦，回访时间：2025-06-29 22:20，回访内容：1；|回访人：谭悦，回访时间：2025-06-29 22:21，回访内容：1 | BB23: 65530077 | BC23: 否 | BD23: 26考季 | BE23: 全年集训营,考研专业课300 | BF23: 英语,政治,专业课300 | BH23: 国内高校-双非 | BI23: 否
B24: 13 | C24: 北京大学部 | D24: 国内大学部 | F24: 95173408 | H24: 2025-02-20 16:07:50 | I24: 续费原因：如果今年成绩不理想，学员考虑再回来，细节已和顾问刘欢老师对接；该学生为保护期外续费，原顾问部门：国内大学部 | K24: 大学已毕业 | L24: 赵星火 | M24: 转介绍 | N24: 学管续费推荐 | R24: 张显 | S24: 赵星火 | T24: 28720746 | U24: 续费工单 | V24: 2025-06-29 21:50 | W24: A（六个月内有报课意向工单） | X24: 考研集训营 | Y24: 大学已毕业 | Z24: 天津财经大学 | AA24: 会计学院 | AB24: 财务管理 | AC24: 张显 | AD24: 5405545 | AE24: 赵星火 | AF24: 2025-06-29 21:51 | AG24: 赵星火 | AH24: 2025-06-29 21:51 | AI24: KYJZ25007A | AJ24: 26考研政治全年集训营（强冲） | AK24: 国内考试 | AM24: 10332.2 | AN24: 同科续费 | AP24: 续班 | AQ24: 无须交接 | AR24: BJWY24032w1g8X | AS24: BJWY3269678401 | AT24: KYJZ25007A0058 | AU24: 2025-06-27 | AW24: 回访人：赵星火，回访时间：2025-06-29 21:50，回访内容：1；|回访人：赵星火，回访时间：2025-06-29 21:51，回访内容：1 | BB24: 52965947 | BC24: 否 | BD24: 26考季 | BE24: 全年集训营 | BF24: 英语,政治 | BH24: 国内高校-C9 | BI24: 否 | BL24: 转出
A25: 在线网课 | B25: 14 | C25: 北京大学部 | D25: 国内大学部 | E25: grnv | F25: 115757231 | G25: 王静静 | H25: 2025-06-23 14:26:30 | I25: 渠道录入来源：集团百度投放-易聊 意向城市：北京市 访客省/城市：北京市 qq: 访客静态ID：01000000034718973185476658716548 接待分组ID：51266 搜索引擎： 搜索词： 关键词： 设备类型：pc 访客IP：111.192.103.219 对话详细内容：AI-KvNH7xJ0CD 2025-06-12 20:37:45_x000D_ 您好同学，欢迎访问新东方考研官网，【新东方考研】全新升级，课程灵活多样，【考研全年集训营】【考研半年集训营】【考研冲刺营】【线下走读班】【考研一对一】【在职考研】【四六级】火热报名中 ，现在报名更有高达3000元优惠！_x000D_ _x000D_ AI-KvNH7xJ0CD 2025-06-12 20:37:47_x000D_ 您是想咨询【考研走读班】【考研集训营】【考研规划】还是【在职考研】呢？_x000D_ _x000D_ 01000000034718973185476658716548 2025-06-12 20:38:28_x000D_ 在职考研_x000D_ _x000D_ AI-KvNH7xJ0CD 2025-06-12 20:38:32_x000D_ 您准备[在职读研] 还是[离职读研] ?**在职读研# **离职读研#_x000D_ _x000D_ 01000000034718973185476658716548 2025-06-12 20:38:38_x000D_ 在职读研_x000D_ _x000D_ AI-KvNH7xJ0CD 2025-06-12 20:38:42_x000D_ 具体是想报考什么学校和专业呢？_x000D_ _x000D_ 01000000034718973185476658716548 2025-06-12 20:38:54_x000D_ 想报考计算机相关专业_x000D_ _x000D_ AI-KvNH7xJ0CD 2025-06-12 20:38:57_x000D_ 同学，您可以留下您的联系方式，稍后顾问老师会给您进行专业的择校及专业选择的指导。_x000D_ _x000D_ 01000000034718973185476658716548 2025-06-12 20:39:08_x000D_ 15650706248_x000D_ _x000D_ 来源页：https://click.xdf.cn/ 备注：（TMK主管分配TMK） | J25: 2026财年第1财月百度投放总部-百度投放 | K25: 在职 | L25: 杨沫 | M25: 线上运营-投放 | N25: 总部-百度投放 | P25: 杨沫 | Q25: 2025-06-27 16:00:22 | R25: grnv | S25: 赵星火 | T25: 28677697 | U25: 正常工单 | V25: 2025-06-27 16:01 | W25: A（六个月内有报课意向工单） | X25: 线上考研产品 | Y25: 在职 | Z25: 北京物资学院 | AA25: 法学院 | AB25: 法学 | AC25: grnv | AD25: 5367500 | AE25: 赵星火 | AF25: 2025-06-27 16:01 | AG25: 赵星火 | AH25: 2025-06-27 16:01 | AI25: 80073851582 | AJ25: 2026考研政治全程班 6班,2026考研英语全程班 6班,2026考研数学全程班 6班,2026考研计算机全程班 | AK25: 国内考试 | AM25: 4547.5 | AP25: 新签 | AQ25: 无须交接 | AU25: 2025-06-27 | AW25: 回访人：赵星火，回访时间：2025-06-27 16:01，回访内容：1 | BA25: 长期班,长期班,长期班,长期班 | BB25: 79611103 | BC25: 是 | BD25: 26考季 | BE25: 线上全程班 | BF25: 英语 | BG25: 计算机 | BH25: 国内高校-双非 | BI25: 否 | BM25: 110448110
B26: 15 | C26: 北京大学部 | D26: 国内大学部 | F26: 86141900 | H26: 2024-10-11 10:31:47 | I26: 明天下午想到知春路校区面询，两位同学一起，尽快联系 渠道录入来源：大众点评 事件名称：在线咨询 大众点评门店名称：新东方考研四六级(知春路校区) 店铺绑定的校区：知春路校区 店铺管理员邮箱：lvmeng2@xdf.cn 备注：2024-10-11 10:31:45,用户在大众点评新东方考研四六级(知春路校区)在线咨询 | J26: 2025财年第5财月大众点评在线咨询 | K26: 大三 | L26: 邓谭(转岗) | M26: 线上运营-本地生活平台 | N26: 大众点评 | R26: 付豪 | S26: 谭悦 | T26: 28701601 | U26: 续费工单 | V26: 2025-06-29 22:13 | W26: B（需长时间跟单或只需要规划） | X26: 考研专业课,考研无忧计划 | Y26: 大三 | Z26: 北京工商学院 | AA26: 化学学院 | AB26: 化妆品工程 | AC26: 付豪 | AD26: 5459853 | AE26: 谭悦 | AF26: 2025-06-29 22:14 | AG26: 谭悦 | AH26: 2025-06-29 22:14 | AI26: WYE26034 | AJ26: 考研英语无忧计划（26考研/英二强化） | AK26: 国内考试 | AM26: 6672.4 | AN26: 同科续费 | AP26: 续班 | AQ26: 已交接 | AR26: BJWY25030q8UPI | AS26: BJWY0827309575 | AT26: WYE260340045 | AU26: 2025-06-25 | AW26: 回访人：谭悦，回访时间：2025-06-29 22:13，回访内容：1；|回访人：谭悦，回访时间：2025-06-29 22:14，回访内容：1 | BB26: 65076597 | BC26: 否 | BD26: 26考季 | BE26: 无忧计划-啄木鸟,考研专业课150 | BF26: 英语,政治,数学,专业课150 | BH26: 国内高校-双非 | BI26: 否 | BL26: 转出 | BN26: 本地人本地大学(常规)
B27: 16 | C27: 北京大学部 | D27: 国内大学部 | F27: 86141900 | H27: 2024-10-11 10:31:47 | I27: 明天下午想到知春路校区面询，两位同学一起，尽快联系 渠道录入来源：大众点评 事件名称：在线咨询 大众点评门店名称：新东方考研四六级(知春路校区) 店铺绑定的校区：知春路校区 店铺管理员邮箱：lvmeng2@xdf.cn 备注：2024-10-11 10:31:45,用户在大众点评新东方考研四六级(知春路校区)在线咨询 | J27: 2025财年第5财月大众点评在线咨询 | K27: 大三 | L27: 邓谭(转岗) | M27: 线上运营-本地生活平台 | N27: 大众点评 | R27: 付豪 | S27: 谭悦 | T27: 28701601 | U27: 续费工单 | V27: 2025-06-29 22:13 | W27: B（需长时间跟单或只需要规划） | X27: 考研专业课,考研无忧计划 | Y27: 大三 | Z27: 北京工商学院 | AA27: 化学学院 | AB27: 化妆品工程 | AC27: 付豪 | AD27: 5459853 | AE27: 谭悦 | AF27: 2025-06-29 22:14 | AG27: 谭悦 | AH27: 2025-06-29 22:14 | AI27: WYE26035 | AJ27: 考研英语无忧计划（26考研/英二冲刺） | AK27: 国内考试 | AM27: 3177.3 | AN27: 同科续费 | AP27: 续班 | AQ27: 已交接 | AR27: BJWY25030q8UPI | AS27: BJWY0827309575 | AT27: WYE260350045 | AU27: 2025-06-25 | AW27: 回访人：谭悦，回访时间：2025-06-29 22:13，回访内容：1；|回访人：谭悦，回访时间：2025-06-29 22:14，回访内容：1 | BB27: 65076597 | BC27: 否 | BD27: 26考季 | BE27: 无忧计划-啄木鸟,考研专业课150 | BF27: 英语,政治,数学,专业课150 | BH27: 国内高校-双非 | BI27: 否 | BL27: 转出 | BN27: 本地人本地大学(常规)
B28: 17 | C28: 北京大学部 | D28: 国内大学部 | F28: 94705727 | H28: 2025-02-15 15:43:36 | I28: 准备到知春路校区面询，尽快联系 | K28: 未知 | L28: 刘创 | M28: 线上运营-本地生活平台 | N28: 阿里本地通 | R28: 朱建金 | S28: 谭悦 | T28: 28575704 | U28: 续费工单 | V28: 2025-06-24 20:45 | W28: B（需长时间跟单或只需要规划） | X28: 考研专业课,考研无忧计划 | Y28: 在职 | Z28: 太原理工大学 | AA28: 土木工程学院 | AB28: 土木工程 | AC28: 朱建金 | AD28: 5402814 | AE28: 谭悦 | AF28: 2025-06-24 20:45 | AG28: 谭悦 | AH28: 2025-06-24 20:46 | AI28: WYE26026 | AJ28: 考研英语无忧计划（26考研/英一强化） | AK28: 国内考试 | AM28: 6746.8 | AN28: 同科续费 | AP28: 续班 | AQ28: 已交接 | AR28: BJWY2101498uW2 | AS28: BJWY1520278143 | AT28: WYE260260064 | AU28: 2025-06-24 | AW28: 回访人：谭悦，回访时间：2025-06-24 20:45，回访内容：1；|回访人：谭悦，回访时间：2025-06-24 20:45，回访内容：1 | BB28: 66984003 | BC28: 否 | BD28: 26考季 | BE28: 无忧计划-啄木鸟,考研专业课150 | BF28: 英语,政治,数学,专业课150 | BH28: 国内高校-211 | BI28: 否 | BL28: 转出
B29: 18 | C29: 北京大学部 | D29: 国内大学部 | F29: 94705727 | H29: 2025-02-15 15:43:36 | I29: 准备到知春路校区面询，尽快联系 | K29: 未知 | L29: 刘创 | M29: 线上运营-本地生活平台 | N29: 阿里本地通 | R29: 朱建金 | S29: 谭悦 | T29: 28575704 | U29: 续费工单 | V29: 2025-06-24 20:45 | W29: B（需长时间跟单或只需要规划） | X29: 考研专业课,考研无忧计划 | Y29: 在职 | Z29: 太原理工大学 | AA29: 土木工程学院 | AB29: 土木工程 | AC29: 朱建金 | AD29: 5402814 | AE29: 谭悦 | AF29: 2025-06-24 20:45 | AG29: 谭悦 | AH29: 2025-06-24 20:46 | AI29: WYE26027 | AJ29: 考研英语无忧计划（26考研/英一冲刺） | AK29: 国内考试 | AM29: 3212.8 | AN29: 同科续费 | AP29: 续班 | AQ29: 已交接 | AR29: BJWY2101498uW2 | AS29: BJWY1520278143 | AT29: WYE260270062 | AU29: 2025-06-24 | AW29: 回访人：谭悦，回访时间：2025-06-24 20:45，回访内容：1；|回访人：谭悦，回访时间：2025-06-24 20:45，回访内容：1 | BB29: 66984003 | BC29: 否 | BD29: 26考季 | BE29: 无忧计划-啄木鸟,考研专业课150 | BF29: 英语,政治,数学,专业课150 | BH29: 国内高校-211 | BI29: 否 | BL29: 转出
A30: 在线网课 | B30: 19 | C30: 北京大学部 | D30: 国内大学部 | E30: 胡家睿 | F30: 92377994 | G30: 张琦文 | H30: 2025-01-06 15:45:51 | I30: 续费原因：心脏不舒服去急诊没有考数学，要是成绩还好可能就报一个一对一在家复习了。老师可以跟进问一下；该学生为保护期内续费，原顾问：国内大学部-赵星火(zhaoxinghuo@xdf.cn) | K30: 大四 | L30: 赵星火 | M30: 转介绍 | N30: 学管续费推荐 | O30: 张琦文zhangqiwen6@xdf.cn | R30: 胡家睿 | S30: 赵星火 | T30: 26221646 | U30: 续费工单 | V30: 2025-01-06 16:21 | W30: A（六个月内有报课意向工单） | X30: 考研集训营 | Y30: 大四 | Z30: 北京信息科技大学 | AA30: 信息与通信工程学院 | AB30: 电子信息工程 | AC30: 胡家睿 | AD30: 5391072 | AE30: 赵星火 | AF30: 2025-06-22 17:15 | AG30: 赵星火 | AH30: 2025-06-22 17:15 | AI30: 52288160146 | AJ30: 2026考研英语直通车 6期,2026考研数学直通车 6期,2026考研政治直通车 6期 | AK30: 国内考试 | AM30: 11336 | AO30: 张琦文 | AP30: 续班 | AQ30: 无须交接 | AU30: 2025-06-22 | AW30: 回访人：赵星火，回访时间：2025-06-14 17:10，回访内容：电话呼出联系联系不上，微信没有回复；|回访人：赵星火，回访时间：2025-06-18 21:21，回访内容：跟进学生情况跟进学生考虑继续维护中。；|回访人：赵星火，回访时间：2025-06-21 20:31，回访内容：电话呼出联系不上学生微信跟进中继续维护。；|回访人：赵星火，回访时间：2025-06-22 17:15，回访内容：1 | BA30: 长期班,长期班,长期班 | BB30: 44083854 | BC30: 是 | BD30: 26考季 | BE30: 半年集训营 | BF30: 英语 | BG30: 计算机 | BH30: 国内高校-双非 | BI30: 否 | BM30: 105716491 | BN30: 本地人本地大学(常规) | BO30: 学管续费推荐
A31: 在线网课 | B31: 20 | C31: 北京大学部 | D31: 国内大学部 | E31: 白兰小字 | F31: 115078495 | G31: 康荧 | H31: 2025-06-18 15:03:49 | I31: 【小红书资源】 一会儿到知春路面询 | K31: 未知 | L31: 赵星火 | M31: 线上运营-小红书 | N31: 小红书 | R31: 韩宜航 | S31: 赵星火 | T31: 28434788 | U31: 正常工单 | V31: 2025-06-18 16:52 | W31: A（六个月内有报课意向工单） | X31: 线上考研产品 | Y31: 大四 | Z31: 北京工业大学 | AA31: 环境与生命学部 | AB31: 化学生物学 | AC31: 韩宜航 | AD31: 5400255 | AE31: 赵星火 | AF31: 2025-06-18 16:53 | AG31: 赵星火 | AH31: 2025-06-18 16:53 | AI31: 53494503643 | AJ31: 2026考研英语直通车 6期,2026考研政治直通车 6期 | AK31: 国内考试 | AM31: 8464 | AP31: 新签 | AQ31: 无须交接 | AU31: 2025-06-18 | AW31: 回访人：赵星火，回访时间：2025-06-18 16:53，回访内容：1 | AY31: 8464.0 | AZ31: 2025-06-28 | BA31: 长期班,长期班 | BB31: 80013959 | BC31: 是 | BD31: 26考季 | BE31: 线上直通车 | BF31: 英语,政治 | BG31: 其他 | BH31: 国内高校-211 | BI31: 否 | BM31: 108722739 | BN31: 外地人本地大学(常规) | BO31: 客服
A32: 在线网课 | B32: 21 | C32: 北京大学部 | D32: 国内大学部 | F32: 85549363 | H32: 2024-09-29 17:21:48 | I32: 续费原因：了解25考研对应课程，需要先看一下院校，学生家长先问的专业课，但是专业课每个学校考的不一样需要先看一下院校，说了公共课急救班还有一对一模式，孩子在老家可以上线上；该学生为保护期外续费，原顾问部门：国内大学部 | K32: 大学已毕业 | L32: 谭悦 | M32: 转介绍 | N32: 学管续费推荐 | R32: 张鸣政 | S32: 谭悦 | T32: 28387513 | U32: 续费工单 | V32: 2025-06-16 20:18 | W32: A（六个月内有报课意向工单） | X32: 教师资格证 | Y32: 大学已毕业 | Z32: 中国人民大学 | AA32: 马克思主义学院 | AB32: 中国共产党历史 | AC32: 张鸣政 | AD32: 5357256 | AE32: 谭悦 | AF32: 2025-06-16 20:21 | AG32: 谭悦 | AH32: 2025-06-16 20:21 | AI32: 15719805143 | AJ32: 【2025下】中学教资笔面直通车 | AK32: 国内考试 | AM32: 3930 | AP32: 续班 | AQ32: 无须交接 | AU32: 2025-06-16 | AW32: 回访人：谭悦，回访时间：2025-06-16 20:18，回访内容：教资网课 ；|回访人：谭悦，回访时间：2025-06-16 20:21，回访内容：1 | BA32: 长期班 | BB32: 39017583 | BC32: 是 | BD32: 25下考季 | BE32: 教师资格证笔试 | BH32: 国内高校-985 | BI32: 否 | BM32: 104315719
A33: 在线网课 | B33: 22 | C33: 北京大学部 | D33: 国内大学部 | F33: 112561935 | H33: 2025-06-06 12:20:44 | I33: 知春路直访，谭悦接待；销售主管分配TMK主管 外呼主题：寇源-等待工单库2025-05-23 | K33: 大三 | L33: 谭悦 | M33: 线上运营-投放 | N33: 百度投放 | R33: 曹玥 | S33: 谭悦 | T33: 28130808 | U33: 续费工单 | V33: 2025-06-10 15:07 | W33: A（六个月内有报课意向工单） | X33: 线上考研产品 | Y33: 大三 | Z33: 北京农学院 | AA33: 植物科学技术学院 | AB33: 农学 | AC33: 曹玥 | AD33: 5351875 | AE33: 谭悦 | AF33: 2025-06-10 15:07 | AG33: 谭悦 | AH33: 2025-06-10 15:07 | AI33: 06888906157 | AJ33: 2026考研专业课定制一对一（50h）-A班 | AK33: 国内考试 | AM33: 18615 | AP33: 续班 | AQ33: 无须交接 | AU33: 2025-06-10 | AW33: 回访人：谭悦，回访时间：2025-06-10 15:07，回访内容：1；|回访人：谭悦，回访时间：2025-06-10 15:07，回访内容：1 | BA33: 长期班 | BB33: 67470457 | BC33: 是 | BD33: 26考季 | BE33: 线上无忧计划 | BF33: 英语,政治,专业课300 | BH33: 国内高校-双非 | BI33: 否 | BM33: 107462026 | BN33: 本地人本地大学(常规)
A34: 在线网课 | B34: 23 | C34: 北京大学部 | D34: 国内大学部 | E34: 曹玥 | F34: 103546571 | G34: 杨俊 | H34: 2025-05-23 14:29:17 | I34: 销售主管分配TMK主管 | K34: 大三 | L34: 杨钰杰 | M34: 线上运营-投放 | N34: 百度投放 | P34: 杨钰杰 | Q34: 2025-06-06 12:20:44 | R34: 曹玥 | S34: 谭悦 | T34: 28176051 | U34: 正常工单 | V34: 2025-06-06 13:37 | W34: A（六个月内有报课意向工单） | X34: 线上考研产品 | Y34: 大三 | Z34: 北京农学院 | AA34: 植物科学技术学院 | AB34: 农学 | AC34: 曹玥 | AD34: 5277327 | AE34: 谭悦 | AF34: 2025-06-10 15:04 | AG34: 谭悦 | AH34: 2025-06-10 15:05 | AI34: 77410743517 | AJ34: 2026考研政治无忧计划·11期,2026考研英语一无忧计划·14期 | AK34: 国内考试 | AM34: 15303.2 | AP34: 新签 | AQ34: 无须交接 | AU34: 2025-06-10 | AW34: 回访人：谭悦，回访时间：2025-06-06 13:37，回访内容：26考研，植物保护，跟进中 ；|回访人：谭悦，回访时间：2025-06-07 16:44，回访内容：微信跟进中，菁英B计划 ；|回访人：谭悦，回访时间：2025-06-10 15:04，回访内容：签约 | BA34: 长期班,长期班 | BB34: 67470457 | BC34: 是 | BD34: 26考季 | BE34: 线上无忧计划 | BF34: 英语,政治,专业课300 | BG34: 其他 | BH34: 国内高校-双非 | BI34: 否 | BM34: 107462026 | BN34: 本地人本地大学(常规) | BO34: 市场
A35: 在线网课 | B35: 24 | C35: 北京大学部 | D35: 国内大学部 | F35: 87708587 | H35: 2024-11-05 14:17:45 | I35: 【考博】学生主动微信找的，毕业专业和院校是 大连医科大学 临床医学。咨询考博的英语辅导，线上大班网课，在上班，不方便电话，辛苦老师加微信，手机号是微信；【考博】毕业专业和院校是 大连医科大学 临床医学。咨询考博的英语辅导，线上大班网课，在上班，不方便电话，辛苦老师加微信 | K35: 在职 | L35: 赵星火 | M35: 直访 | N35: 直访 | R35: 1度 | S35: 赵星火 | T35: 28182825 | U35: 续费工单 | V35: 2025-06-07 13:05 | W35: A（六个月内有报课意向工单） | X35: 考博 | Y35: 在职 | Z35: 大连医科大学 | AA35: 临床学院 | AB35: 临床医学 | AC35: 1度 | AD35: 5377871 | AE35: 赵星火 | AF35: 2025-06-07 13:05 | AG35: 赵星火 | AH35: 2025-06-07 13:06 | AI35: 08181547771 | AJ35: 2026医学考博英语全程班【直播 + 录播】 | AK35: 国内考试 | AM35: 1824 | AP35: 续班 | AQ35: 无须交接 | AU35: 2025-06-07 | AW35: 回访人：赵星火，回访时间：2025-06-07 13:05，回访内容：1；|回访人：赵星火，回访时间：2025-06-07 13:05，回访内容：1 | BA35: 长期班 | BB35: 64038881 | BC35: 是 | BH35: 国内高校-双非 | BI35: 否 | BM35: 108979436
B36: 25 | C36: 北京大学部 | D36: 国内大学部 | F36: 95923932 | H36: 2025-03-01 15:57:49 | I36: 续费原因：咨询考研，辛苦流转赵星火；该学生为保护期内续费，原顾问：国内大学部-赵星火(zhaoxinghuo@xdf.cn) | K36: 大三 | L36: 赵星火 | M36: 转介绍 | N36: 学管续费推荐 | R36: 李尚烨 | S36: 赵星火 | T36: 28161284 | U36: 续费工单 | V36: 2025-06-05 14:42 | W36: A（六个月内有报课意向工单） | X36: 考研无忧计划 | Y36: 大三 | Z36: 北京航空航天大学 | AA36: 机械工程及自动化学院 | AB36: 材料成型及控制工程 | AC36: 李尚烨 | AD36: 5347627 | AE36: 赵星火 | AF36: 2025-06-05 14:42 | AG36: 赵星火 | AH36: 2025-06-05 15:14 | AI36: WYP26043 | AJ36: 考研政治无忧计划（26考研/基础） | AK36: 国内考试 | AM36: 6041.5 | AN36: 同科续费 | AP36: 续班 | AQ36: 无须交接 | AR36: BJWY25030q8UPI | AS36: BJWY8264939203 | AT36: WYP260430050 | AU36: 2025-06-04 | AW36: 回访人：赵星火，回访时间：2025-06-05 14:42，回访内容：1；|回访人：赵星火，回访时间：2025-06-05 14:42，回访内容：1 | BB36: 67086969 | BC36: 否 | BD36: 26考季 | BE36: 无忧计划-啄木鸟 | BF36: 英语,政治,数学 | BH36: 国内高校-985 | BI36: 否 | BL36: 转出 | BN36: 外地人本地大学(常规)
B37: 26 | C37: 北京大学部 | D37: 国内大学部 | F37: 95923932 | H37: 2025-03-01 15:57:49 | I37: 续费原因：咨询考研，辛苦流转赵星火；该学生为保护期内续费，原顾问：国内大学部-赵星火(zhaoxinghuo@xdf.cn) | K37: 大三 | L37: 赵星火 | M37: 转介绍 | N37: 学管续费推荐 | R37: 李尚烨 | S37: 赵星火 | T37: 28161284 | U37: 续费工单 | V37: 2025-06-05 14:42 | W37: A（六个月内有报课意向工单） | X37: 考研无忧计划 | Y37: 大三 | Z37: 北京航空航天大学 | AA37: 机械工程及自动化学院 | AB37: 材料成型及控制工程 | AC37: 李尚烨 | AD37: 5347627 | AE37: 赵星火 | AF37: 2025-06-05 14:42 | AG37: 赵星火 | AH37: 2025-06-05 15:14 | AI37: WYP26044 | AJ37: 考研政治无忧计划（26考研/强化） | AK37: 国内考试 | AM37: 3855.3 | AN37: 同科续费 | AP37: 续班 | AQ37: 无须交接 | AR37: BJWY25030q8UPI | AS37: BJWY8264939203 | AT37: WYP260440050 | AU37: 2025-06-04 | AW37: 回访人：赵星火，回访时间：2025-06-05 14:42，回访内容：1；|回访人：赵星火，回访时间：2025-06-05 14:42，回访内容：1 | BB37: 67086969 | BC37: 否 | BD37: 26考季 | BE37: 无忧计划-啄木鸟 | BF37: 英语,政治,数学 | BH37: 国内高校-985 | BI37: 否 | BL37: 转出 | BN37: 外地人本地大学(常规)
B38: 27 | C38: 北京大学部 | D38: 国内大学部 | F38: 95923932 | H38: 2025-03-01 15:57:49 | I38: 续费原因：咨询考研，辛苦流转赵星火；该学生为保护期内续费，原顾问：国内大学部-赵星火(zhaoxinghuo@xdf.cn) | K38: 大三 | L38: 赵星火 | M38: 转介绍 | N38: 学管续费推荐 | R38: 李尚烨 | S38: 赵星火 | T38: 28161284 | U38: 续费工单 | V38: 2025-06-05 14:42 | W38: A（六个月内有报课意向工单） | X38: 考研无忧计划 | Y38: 大三 | Z38: 北京航空航天大学 | AA38: 机械工程及自动化学院 | AB38: 材料成型及控制工程 | AC38: 李尚烨 | AD38: 5347627 | AE38: 赵星火 | AF38: 2025-06-05 14:42 | AG38: 赵星火 | AH38: 2025-06-05 15:14 | AI38: WYP26045 | AJ38: 考研政治无忧计划（26考研/冲刺） | AK38: 国内考试 | AM38: 4578.2 | AN38: 同科续费 | AP38: 续班 | AQ38: 无须交接 | AR38: BJWY25030q8UPI | AS38: BJWY8264939203 | AT38: WYP260450050 | AU38: 2025-06-04 | AW38: 回访人：赵星火，回访时间：2025-06-05 14:42，回访内容：1；|回访人：赵星火，回访时间：2025-06-05 14:42，回访内容：1 | BB38: 67086969 | BC38: 否 | BD38: 26考季 | BE38: 无忧计划-啄木鸟 | BF38: 英语,政治,数学 | BH38: 国内高校-985 | BI38: 否 | BL38: 转出 | BN38: 外地人本地大学(常规)
B39: 28 | C39: 北京大学部 | D39: 国内大学部 | F39: 95923932 | H39: 2025-03-01 15:57:49 | I39: 续费原因：咨询考研，辛苦流转赵星火；该学生为保护期内续费，原顾问：国内大学部-赵星火(zhaoxinghuo@xdf.cn) | K39: 大三 | L39: 赵星火 | M39: 转介绍 | N39: 学管续费推荐 | R39: 李尚烨 | S39: 赵星火 | T39: 28161284 | U39: 续费工单 | V39: 2025-06-05 14:42 | W39: A（六个月内有报课意向工单） | X39: 考研无忧计划 | Y39: 大三 | Z39: 北京航空航天大学 | AA39: 机械工程及自动化学院 | AB39: 材料成型及控制工程 | AC39: 李尚烨 | AD39: 5347627 | AE39: 赵星火 | AF39: 2025-06-05 14:42 | AG39: 赵星火 | AH39: 2025-06-05 15:14 | AI39: WYE26055 | AJ39: 考研英语无忧计划（26考研/基础） | AK39: 国内考试 | AM39: 4015.9 | AN39: 同科续费 | AP39: 续班 | AQ39: 无须交接 | AR39: BJWY25030q8UPI | AS39: BJWY8264939203 | AT39: WYE260550057 | AU39: 2025-06-04 | AW39: 回访人：赵星火，回访时间：2025-06-05 14:42，回访内容：1；|回访人：赵星火，回访时间：2025-06-05 14:42，回访内容：1 | BB39: 67086969 | BC39: 否 | BD39: 26考季 | BE39: 无忧计划-啄木鸟 | BF39: 英语,政治,数学 | BH39: 国内高校-985 | BI39: 否 | BL39: 转出 | BN39: 外地人本地大学(常规)
B40: 29 | C40: 北京大学部 | D40: 国内大学部 | F40: 95923932 | H40: 2025-03-01 15:57:49 | I40: 续费原因：咨询考研，辛苦流转赵星火；该学生为保护期内续费，原顾问：国内大学部-赵星火(zhaoxinghuo@xdf.cn) | K40: 大三 | L40: 赵星火 | M40: 转介绍 | N40: 学管续费推荐 | R40: 李尚烨 | S40: 赵星火 | T40: 28161284 | U40: 续费工单 | V40: 2025-06-05 14:42 | W40: A（六个月内有报课意向工单） | X40: 考研无忧计划 | Y40: 大三 | Z40: 北京航空航天大学 | AA40: 机械工程及自动化学院 | AB40: 材料成型及控制工程 | AC40: 李尚烨 | AD40: 5347627 | AE40: 赵星火 | AF40: 2025-06-05 14:42 | AG40: 赵星火 | AH40: 2025-06-05 15:14 | AI40: WYE26056 | AJ40: 考研英语无忧计划（26考研/英一强化） | AK40: 国内考试 | AM40: 6246.8 | AN40: 同科续费 | AP40: 续班 | AQ40: 无须交接 | AR40: BJWY25030q8UPI | AS40: BJWY8264939203 | AT40: WYE260560029 | AU40: 2025-06-04 | AW40: 回访人：赵星火，回访时间：2025-06-05 14:42，回访内容：1；|回访人：赵星火，回访时间：2025-06-05 14:42，回访内容：1 | BB40: 67086969 | BC40: 否 | BD40: 26考季 | BE40: 无忧计划-啄木鸟 | BF40: 英语,政治,数学 | BH40: 国内高校-985 | BI40: 否 | BL40: 转出 | BN40: 外地人本地大学(常规)
B41: 30 | C41: 北京大学部 | D41: 国内大学部 | F41: 95923932 | H41: 2025-03-01 15:57:49 | I41: 续费原因：咨询考研，辛苦流转赵星火；该学生为保护期内续费，原顾问：国内大学部-赵星火(zhaoxinghuo@xdf.cn) | K41: 大三 | L41: 赵星火 | M41: 转介绍 | N41: 学管续费推荐 | R41: 李尚烨 | S41: 赵星火 | T41: 28161284 | U41: 续费工单 | V41: 2025-06-05 14:42 | W41: A（六个月内有报课意向工单） | X41: 考研无忧计划 | Y41: 大三 | Z41: 北京航空航天大学 | AA41: 机械工程及自动化学院 | AB41: 材料成型及控制工程 | AC41: 李尚烨 | AD41: 5347627 | AE41: 赵星火 | AF41: 2025-06-05 14:42 | AG41: 赵星火 | AH41: 2025-06-05 15:14 | AI41: WYE26057 | AJ41: 考研英语无忧计划（26考研/英一冲刺） | AK41: 国内考试 | AM41: 3212.8 | AN41: 同科续费 | AP41: 续班 | AQ41: 无须交接 | AR41: BJWY25030q8UPI | AS41: BJWY8264939203 | AT41: WYE260570029 | AU41: 2025-06-04 | AW41: 回访人：赵星火，回访时间：2025-06-05 14:42，回访内容：1；|回访人：赵星火，回访时间：2025-06-05 14:42，回访内容：1 | BB41: 67086969 | BC41: 否 | BD41: 26考季 | BE41: 无忧计划-啄木鸟 | BF41: 英语,政治,数学 | BH41: 国内高校-985 | BI41: 否 | BL41: 转出 | BN41: 外地人本地大学(常规)
B42: 31 | C42: 北京大学部 | D42: 国内大学部 | F42: 95923932 | H42: 2025-03-01 15:57:49 | I42: 续费原因：咨询考研，辛苦流转赵星火；该学生为保护期内续费，原顾问：国内大学部-赵星火(zhaoxinghuo@xdf.cn) | K42: 大三 | L42: 赵星火 | M42: 转介绍 | N42: 学管续费推荐 | R42: 李尚烨 | S42: 赵星火 | T42: 28161284 | U42: 续费工单 | V42: 2025-06-05 14:42 | W42: A（六个月内有报课意向工单） | X42: 考研无忧计划 | Y42: 大三 | Z42: 北京航空航天大学 | AA42: 机械工程及自动化学院 | AB42: 材料成型及控制工程 | AC42: 李尚烨 | AD42: 5347627 | AE42: 赵星火 | AF42: 2025-06-05 14:42 | AG42: 赵星火 | AH42: 2025-06-05 15:14 | AI42: WYM26028 | AJ42: 考研数学无忧计划（26考研/基础） | AK42: 国内考试 | AM42: 4045.5 | AN42: 同科续费 | AP42: 续班 | AQ42: 无须交接 | AR42: BJWY25030q8UPI | AS42: BJWY8264939203 | AT42: WYM260280032 | AU42: 2025-06-04 | AW42: 回访人：赵星火，回访时间：2025-06-05 14:42，回访内容：1；|回访人：赵星火，回访时间：2025-06-05 14:42，回访内容：1 | BB42: 67086969 | BC42: 否 | BD42: 26考季 | BE42: 无忧计划-啄木鸟 | BF42: 英语,政治,数学 | BH42: 国内高校-985 | BI42: 否 | BL42: 转出 | BN42: 外地人本地大学(常规)
B43: 32 | C43: 北京大学部 | D43: 国内大学部 | F43: 95923932 | H43: 2025-03-01 15:57:49 | I43: 续费原因：咨询考研，辛苦流转赵星火；该学生为保护期内续费，原顾问：国内大学部-赵星火(zhaoxinghuo@xdf.cn) | K43: 大三 | L43: 赵星火 | M43: 转介绍 | N43: 学管续费推荐 | R43: 李尚烨 | S43: 赵星火 | T43: 28161284 | U43: 续费工单 | V43: 2025-06-05 14:42 | W43: A（六个月内有报课意向工单） | X43: 考研无忧计划 | Y43: 大三 | Z43: 北京航空航天大学 | AA43: 机械工程及自动化学院 | AB43: 材料成型及控制工程 | AC43: 李尚烨 | AD43: 5347627 | AE43: 赵星火 | AF43: 2025-06-05 14:42 | AG43: 赵星火 | AH43: 2025-06-05 15:14 | AI43: WYM26029 | AJ43: 考研数学无忧计划（26考研/强化） | AK43: 国内考试 | AM43: 7068.1 | AN43: 同科续费 | AP43: 续班 | AQ43: 无须交接 | AR43: BJWY25030q8UPI | AS43: BJWY8264939203 | AT43: WYM260290032 | AU43: 2025-06-04 | AW43: 回访人：赵星火，回访时间：2025-06-05 14:42，回访内容：1；|回访人：赵星火，回访时间：2025-06-05 14:42，回访内容：1 | BB43: 67086969 | BC43: 否 | BD43: 26考季 | BE43: 无忧计划-啄木鸟 | BF43: 英语,政治,数学 | BH43: 国内高校-985 | BI43: 否 | BL43: 转出 | BN43: 外地人本地大学(常规)
B44: 33 | C44: 北京大学部 | D44: 国内大学部 | F44: 95923932 | H44: 2025-03-01 15:57:49 | I44: 续费原因：咨询考研，辛苦流转赵星火；该学生为保护期内续费，原顾问：国内大学部-赵星火(zhaoxinghuo@xdf.cn) | K44: 大三 | L44: 赵星火 | M44: 转介绍 | N44: 学管续费推荐 | R44: 李尚烨 | S44: 赵星火 | T44: 28161284 | U44: 续费工单 | V44: 2025-06-05 14:42 | W44: A（六个月内有报课意向工单） | X44: 考研无忧计划 | Y44: 大三 | Z44: 北京航空航天大学 | AA44: 机械工程及自动化学院 | AB44: 材料成型及控制工程 | AC44: 李尚烨 | AD44: 5347627 | AE44: 赵星火 | AF44: 2025-06-05 14:42 | AG44: 赵星火 | AH44: 2025-06-05 15:14 | AI44: WYM26030 | AJ44: 考研数学无忧计划（26考研/冲刺） | AK44: 国内考试 | AM44: 3373.4 | AN44: 同科续费 | AP44: 续班 | AQ44: 无须交接 | AR44: BJWY25030q8UPI | AS44: BJWY8264939203 | AT44: WYM260300032 | AU44: 2025-06-04 | AW44: 回访人：赵星火，回访时间：2025-06-05 14:42，回访内容：1；|回访人：赵星火，回访时间：2025-06-05 14:42，回访内容：1 | BB44: 67086969 | BC44: 否 | BD44: 26考季 | BE44: 无忧计划-啄木鸟 | BF44: 英语,政治,数学 | BH44: 国内高校-985 | BI44: 否 | BL44: 转出 | BN44: 外地人本地大学(常规)
B45: 34 | C45: 北京大学部 | D45: 国内大学部 | E45: 章俊骐 | F45: 116868306 | G45: 刘佳林 | H45: 2025-07-01 10:33:35 | I45: 续费原因：学生更换研究生，需要缴纳500元师资重新匹配费；该学生为保护期内续费，原顾问：国内大学部-谭悦(tanyue9@xdf.cn) | K45: 大四 | L45: 谭悦 | M45: 转介绍 | N45: 学管续费推荐 | O45: 刘佳林liujialin25@xdf.cn | R45: 章俊骐 | S45: 谭悦 | T45: 28732371 | U45: 续费工单 | V45: 2025-07-01 10:46 | W45: A（六个月内有报课意向工单） | X45: 考研专业课 | Y45: 大四 | Z45: 福建师范大学 | AA45: 计算机与网络空间安全学院 | AB45: 网络空间安全 | AC45: 章俊骐 | AD45: 5406797 | AE45: 谭悦 | AF45: 2025-07-01 10:48 | AG45: 谭悦 | AH45: 2025-07-01 10:49 | AI45: LP175133809710126 | AJ45: 考研专业课匹配费-集训 | AK45: 国内考试 | AM45: 500 | AO45: 刘佳林 | AP45: 续班 | AQ45: 未交接 | AS45: BJWY4692076178 | AU45: 2025-07-01 | AW45: 回访人：谭悦，回访时间：2025-07-01 10:46，回访内容：升级费500 | BB45: 63993771 | BC45: 否 | BD45: 26考季 | BE45: 考研专业课150 | BF45: 专业课150 | BG45: 其他 | BH45: 国内高校-双非 | BI45: 否 | BN45: 外地人外地大学(常规) | BO45: 学管续费推荐
B46: 35 | C46: 北京大学部 | D46: 国内大学部 | F46: 83091320 | H46: 2024-08-23 10:52:44 | I46: 续费原因：四级考过了，秋季六级小班，辛苦流转；该学生为保护期外续费，原顾问部门：国内大学部 | K46: 大二 | L46: 谭悦 | M46: 转介绍 | N46: 学管续费推荐 | R46: 丁美希 | S46: 谭悦 | T46: 28541513 | U46: 续费工单 | V46: 2025-06-23 14:24 | W46: A（六个月内有报课意向工单） | X46: 考研专业课,考研无忧计划 | Y46: 大二 | Z46: 中央民族大学 | AA46: 经济学院 | AB46: 经济学 | AC46: 丁美希 | AD46: 5363227 | AE46: 谭悦 | AF46: 2025-06-23 14:26 | AI46: LP1750659982995 | AJ46: 985院校升级费-无忧 | AM46: 3000 | AP46: 续班 | AQ46: 未交接 | AS46: BJWY2338747100 | AU46: 2025-06-23 | AW46: 回访人：谭悦，回访时间：2025-06-23 14:24，回访内容：1 | BB46: 51402702 | BC46: 否 | BD46: 26考季 | BE46: 无忧计划-啄木鸟,考研专业课300 | BF46: 英语,政治,专业课300 | BG46: 其他 | BH46: 国内高校-985 | BI46: 否 | BN46: 本地人本地大学(常规)
B47: 36 | C47: 北京大学部 | D47: 国内大学部 | F47: 101206597 | H47: 2025-05-02 10:21:56 | I47: 13718108181，北京，一对一，家长 | K47: 未知 | L47: 谭悦 | M47: 线上运营-投放 | N47: 巨量广告 | R47: 高旭 | S47: 谭悦 | T47: 28636734 | U47: 续费工单 | V47: 2025-06-30 17:16 | W47: A（六个月内有报课意向工单） | X47: 考研专业课,考研集训营 | Y47: 大学已毕业 | Z47: 江西中医药大学 | AA47: 中医学院 | AB47: 中医学 | AC47: 高旭 | AD47: 5432382 | AE47: 谭悦 | AF47: 2025-06-30 17:18 | AG47: 谭悦 | AH47: 2025-06-30 17:18 | AI47: KYJY25005A | AJ47: 26考研英语全年集训营（强冲/英语一） | AK47: 国内考试 | AM47: 18083.8 | AN47: 同科续费 | AP47: 续班 | AQ47: 未交接 | AR47: BJWY24032w1g8X | AS47: BJWY1711738229 | AT47: KYJY25005A0051 | AU47: 2025-06-16 | AW47: 回访人：谭悦，回访时间：2025-06-30 17:16，回访内容：1；|回访人：谭悦，回访时间：2025-06-30 17:18，回访内容：1 | BB47: 69899313 | BC47: 否 | BD47: 26考季 | BE47: 全年集训营,考研专业课300 | BF47: 英语,政治,专业课300 | BH47: 国内高校-双非 | BI47: 否 | BL47: 转出
B48: 37 | C48: 北京大学部 | D48: 国内大学部 | F48: 93279543 | H48: 2025-01-17 15:26:42 | I48: 续费原因：【个性化项目】学生复试一对一需求/复试班课需求，学生专业课考的不错，政治和英语主观题不敢估计太高，给学生介绍了复试班课和一对一的时间，价格，优惠 学生说和家长商量一下 也要等等出分的情况（初试定制一对一+专业课+无忧班课）；该学生为保护期外续费，原顾问部门：国内大学部 | K48: 大四 | L48: 赵星火 | M48: 转介绍 | N48: 学管续费推荐 | R48: 邓子萱 | S48: 赵星火 | T48: 28329025 | U48: 续费工单 | V48: 2025-06-13 19:40 | W48: A（六个月内有报课意向工单） | X48: 考研复试班 | Y48: 大四 | Z48: 北京城市学院 | AA48: 经济管理学部 | AB48: 金融学 | AC48: 邓子萱 | AD48: 5398622 | AE48: 赵星火 | AF48: 2025-06-14 15:21 | AI48: LP17498856982112 | AJ48: 考研一对一伴学班（26考季） | AM48: 0 | AP48: 续班 | AQ48: 未交接 | AS48: BJWY6878369361 | AU48: 2025-06-14 | AW48: 回访人：赵星火，回访时间：2025-06-13 19:40，回访内容：1 | BB48: 53299500 | BC48: 否 | BD48: 25考季 | BE48: 考研复试班 | BF48: 英语 | BH48: 国内高校-双非 | BI48: 否 | BN48: 本地人本地大学(常规)
B49: 38 | C49: 北京大学部 | D49: 国内大学部 | F49: 82243811 | H49: 2024-08-13 11:59:07 | I49: 25考研，打算考法硕非法学，想了解下北京的半年集训营，也问了线下走读班，方便回电【死单激活】；渠道录入来源：集团百度投放-易聊 意向城市：北京 访客省/城市：淄博市 qq: 访客静态ID：01000000034718899556994789708966 接待分组ID：51266 搜索引擎： 搜索词： 关键词： 设备类型：pc 访客IP：218.58.131.6 对话详细内容：AI-KvNH7xJ0CD 2024-02-27 08:59:33_x000D_ 您好同学，欢迎访问新东方考研，【25考研】全新升级，考研线下课程【考研全年/半年集训营】【考研冲刺营】【考研线下走读冲刺班】【25无忧计划】【考研一对一】【在职考研】火热报名中 ，现在报名更有高达8000元优惠！_x000D_ 考研在线课程灵活多样，优惠高达3000元！**【考研全年/半年集训营】=019481# **【考研冲刺营】=019481# **【考研线下走读冲刺班】=019481# **【25无忧计划】=019481# **【考研一对一】=019481# **【在职考研】=019481#_x000D_ _x000D_ AI-KvNH7xJ0CD 2024-02-27 08:59:37_x000D_ 您是想咨询【线上课程】【线下课程】【考研规划】还是【在职考研】呢？_x000D_ **【线上课程】=019481# **【线下课程】=019481# **【考研规划】=019481# **【在职考研】=019481#_x000D_ _x000D_ 01000000034718899556994789708966 2024-02-27 09:02:28_x000D_ 你好，你们全年的学习环境图片是哪个省市的？_x000D_ _x000D_ AI-KvNH7xJ0CD 2024-02-27 09:02:32_x000D_ 同学，您是在校还是在职呢？_x000D_ _x000D_ 01000000034718899556994789708966 2024-02-27 09:02:46_x000D_ 我是家长，山东的_x000D_ _x000D_ AI-KvNH7xJ0CD 2024-02-27 09:02:50_x000D_ 具体是想报考什么学校和专业呢？_x000D_ _x000D_ 01000000034718899556994789708966 2024-02-27 09:02:57_x000D_ 法硕_x000D_ _x000D_ 01000000034718899556994789708966 2024-02-27 09:03:00_x000D_ 非法学_x000D_ _x000D_ AI-KvNH7xJ0CD 2024-02-27 09:03:04_x000D_ 好的，了解。我们新东方在全国32个城市都有校区，您倾向在哪个城市上课，或者希望哪里的老师给您介绍下呢？_x000D_ _x000D_ 01000000034718899556994789708966 2024-02-27 09:03:21_x000D_ 我在淄博_x000D_ _x000D_ AI-KvNH7xJ0CD 2024-02-27 09:03:25_x000D_ 您可以留下您的姓名和电话，我这边可以立刻安排对应校区顾问老师给您回电！_x000D_ _x000D_ 01000000034718899556994789708966 2024-02-27 09:03:37_x000D_ 先咨询下_x000D_ _x000D_ AI-KvNH7xJ0CD 2024-02-27 09:03:40_x000D_ 这样，您电话多少，我安排考研部的老师联系您，将课程的详细内容介绍给您_x000D_ _x000D_ 01000000034718899556994789708966 2024-02-27 09:03:55_x000D_ 是你们总部在哪，条件会好些吗_x000D_ _x000D_ AI-KvNH7xJ0CD 2024-02-27 09:03:58_x000D_ 我们在全国32个城市都有校区，您这边在哪个地区上课方便呢。_x000D_ _x000D_ 01000000034718899556994789708966 2024-02-27 09:04:01_x000D_ 是在北京吗_x000D_ _x000D_ AI-KvNH7xJ0CD 2024-02-27 09:04:05_x000D_ 这个可以具体安排老师跟您联系一下，同学这边觉得电话方便还是微信方便呢~_x000D_ _x000D_ 01000000034718899556994789708966 2024-02-27 09:04:10_x000D_ 都可以_x000D_ _x000D_ AI-KvNH7xJ0CD 2024-02-27 09:04:13_x000D_ 您这边方便留个联系方式吗？我们安排专业的老师跟您联系~_x000D_ _x000D_ 01000000034718899556994789708966 2024-02-27 09:04:20_x000D_ 可以推荐一下_x000D_ _x000D_ AI-KvNH7xJ0CD 2024-02-27 09:04:23_x000D_ 好的，您看您什么时候方便，资深老师给您介绍下，针对您的情况来给些匹配建议，给些适合您当前的规划准备，咨询也是免费的，你的电话或者微信是多少呢？_x000D_ _x000D_ 01000000034718899556994789708966 2024-02-27 09:04:38_x000D_ 18369916805_x000D_ _x000D_ 来源页：https://www.xdf.cn/market/360/index.html?utm_source=jituan_searchengine_360_PC_360PP&utm_medium=CPD&utm_campaign=JTQG_360_PP_PC_PP_230530&utm_term=biaoti&utm_1st_id=7&utm_2nd_id=64&xdf_source_channel_code=59fe761d6ffee3da399cdd0c64ce312b 备注：（TMK主管分配TMK） 外呼主题：FY24-国内2月死单回访（第四周）（TMK主管分配TMK） 外呼主题：FY24-英学5月死单回访（下旬） | J49: 2024财年第9财月集团百度投放集团百度投放 | K49: 大学已毕业 | L49: 谭悦 | M49: 线上运营-投放 | N49: 总部-百度投放 | R49: 孙艺鸣 | S49: 谭悦 | T49: 28146416 | U49: 续费工单 | V49: 2025-06-03 11:09 | W49: A（六个月内有报课意向工单） | X49: 考研专业课,考研集训营 | Y49: 大五 | Z49: 北京工商大学 | AA49: 法学院 | AB49: 法学 | AC49: 孙艺鸣 | AD49: 5345928 | AE49: 谭悦 | AF49: 2025-06-03 11:10 | AI49: LP1748920245661 | AJ49: 考研专业课匹配费-集训 | AM49: 500 | AP49: 续班 | AQ49: 未交接 | AS49: BJWY4215493869 | AU49: 2025-06-03 | AW49: 回访人：谭悦，回访时间：2025-06-03 11:09，回访内容：1 | BB49: 51534936 | BC49: 否 | BD49: 26考季 | BE49: 全年集训营,考研专业课300 | BF49: 英语,政治,专业课300 | BH49: 国内高校-双非 | BI49: 否 | BN49: 外地人本地大学(常规)
B50: 39 | C50: 北京大学部 | D50: 国内大学部 | F50: 116243253 | H50: 2025-06-25 20:31:12 | I50: 家长咨询，孩子本科东北大学，学的建筑，之前考过研，7月30号入职中冶京诚，想考非全日制，软件工程计算机之类的，考虑985的学校，想了解暑期集训和走读，简单介绍了下，现在可以回电，着急回电 | K50: 大四 | L50: 钱雪冰 | M50: 线上运营-私域中台 | N50: 社群、虚拟人 | R50: 张霄翮 | S50: 谭悦 | T50: 28741462 | U50: 续费工单 | V50: 2025-06-30 21:21 | W50: A（六个月内有报课意向工单） | X50: 考研专业课,考研无忧计划 | Y50: 大四 | Z50: 东北大学 | AA50: 江河建筑学院 | AB50: 建筑学 | AC50: 张霄翮 | AD50: 5462238 | AE50: 谭悦 | AF50: 2025-06-30 21:21 | AG50: 谭悦 | AH50: 2025-07-01 10:10 | AI50: WYFE26008 | AJ50: 考研英语无忧计划蜂鸟（26考研/英二冲刺） | AK50: 国内考试 | AM50: 3172.8 | AN50: 同科续费 | AP50: 续班 | AQ50: 已交接 | AR50: BJWY25030q8UPI | AS50: BJWY1043586545 | AT50: WYFE260080009 | AU50: 2025-06-30 | AW50: 回访人：谭悦，回访时间：2025-06-30 21:21，回访内容：1；|回访人：谭悦，回访时间：2025-06-30 21:21，回访内容：1 | BB50: 80558403 | BC50: 否 | BD50: 26考季 | BE50: 无忧计划-蜂鸟,考研专业课150 | BF50: 英语,政治,数学,专业课150 | BH50: 国内高校-985 | BI50: 是 | BL50: 转出 | BN50: 外地人外地大学(常规)
B51: 40 | C51: 北京大学部 | D51: 国内大学部 | F51: 116243253 | H51: 2025-06-25 20:31:12 | I51: 家长咨询，孩子本科东北大学，学的建筑，之前考过研，7月30号入职中冶京诚，想考非全日制，软件工程计算机之类的，考虑985的学校，想了解暑期集训和走读，简单介绍了下，现在可以回电，着急回电 | K51: 大四 | L51: 钱雪冰 | M51: 线上运营-私域中台 | N51: 社群、虚拟人 | R51: 张霄翮 | S51: 谭悦 | T51: 28741462 | U51: 续费工单 | V51: 2025-06-30 21:21 | W51: A（六个月内有报课意向工单） | X51: 考研专业课,考研无忧计划 | Y51: 大四 | Z51: 东北大学 | AA51: 江河建筑学院 | AB51: 建筑学 | AC51: 张霄翮 | AD51: 5462238 | AE51: 谭悦 | AF51: 2025-06-30 21:21 | AG51: 谭悦 | AH51: 2025-07-01 10:10 | AI51: WYFE26007 | AJ51: 考研英语无忧计划蜂鸟（26考研/英二强化） | AK51: 国内考试 | AM51: 6660.6 | AN51: 同科续费 | AP51: 续班 | AQ51: 已交接 | AR51: BJWY25030q8UPI | AS51: BJWY1043586545 | AT51: WYFE260070009 | AU51: 2025-06-30 | AW51: 回访人：谭悦，回访时间：2025-06-30 21:21，回访内容：1；|回访人：谭悦，回访时间：2025-06-30 21:21，回访内容：1 | BB51: 80558403 | BC51: 否 | BD51: 26考季 | BE51: 无忧计划-蜂鸟,考研专业课150 | BF51: 英语,政治,数学,专业课150 | BH51: 国内高校-985 | BI51: 是 | BL51: 转出 | BN51: 外地人外地大学(常规)
B52: 41 | C52: 北京大学部 | D52: 国内大学部 | F52: 91763456 | H52: 2024-12-29 12:04:05 | I52: 死单激活分配赵星火 | K52: 大一 | L52: 赵星火 | M52: 新东方官网 | N52: 新东方PC官网 | R52: 赵佳妮 | S52: 赵星火 | T52: 28729697 | U52: 续费工单 | V52: 2025-06-30 18:52 | W52: A（六个月内有报课意向工单） | X52: 六级 | Y52: 大二 | Z52: 北京林业大学 | AA52: 林学院 | AB52: 林学 | AC52: 赵佳妮 | AD52: 5461707 | AE52: 赵星火 | AF52: 2025-06-30 19:06 | AG52: 赵星火 | AH52: 2025-06-30 19:06 | AI52: WYS25035 | AJ52: 六级无忧计划 | AK52: 国内考试 | AM52: 5680 | AN52: 扩科续费 | AP52: 续班 | AQ52: 已交接 | AR52: WebReg | AS52: BJWY4527677924 | AT52: WYS250350018 | AU52: 2025-06-30 | AW52: 回访人：赵星火，回访时间：2025-06-30 18:52，回访内容：1；|回访人：赵星火，回访时间：2025-06-30 19:06，回访内容：1 | BB52: 59702269 | BC52: 否 | BD52: 25下考季 | BE52: 六级无忧计划 | BH52: 国内高校-211 | BI52: 是 | BL52: 报名 | BN52: 本地人本地大学(常规)
B53: 42 | C53: 北京大学部 | D53: 国内大学部 | E53: 未知 | F53: 116388103 | G53: 吕猛 | H53: 2025-06-27 00:18:50 | I53: 渠道录入来源：大众点评 事件名称：在线咨询 大众点评门店名称：新东方考研四六级(国贸校区) 店铺绑定的校区：临时教学校区 店铺管理员邮箱：lvmeng2@xdf.cn 备注：2025-06-27 00:18:49,用户在大众点评新东方考研四六级(国贸校区)在线咨询 | J53: 2026财年第1财月大众点评在线咨询 | L53: 谭悦 | M53: 线上运营-本地生活平台 | N53: 大众点评 | R53: 黄一诺 | S53: 谭悦 | T53: 28622758 | U53: 正常工单 | V53: 2025-06-27 15:30 | W53: A（六个月内有报课意向工单） | X53: 考研专业课,考研集训营 | Y53: 大四 | Z53: 北京服装学院 | AA53: 服装艺术与工程学院 | AB53: 服装设计与工程 | AC53: 黄一诺 | AD53: 5460668 | AE53: 谭悦 | AF53: 2025-06-30 14:38 | AG53: 谭悦 | AH53: 2025-06-30 14:39 | AI53: KYJY25012 | AJ53: 26考研英语半年集训营（基础/七月） | AK53: 国内考试 | AM53: 9724.1 | AP53: 新签 | AQ53: 已交接 | AR53: BJWY2101498uW2 | AS53: BJWY5556110989 | AT53: KYJY250120049 | AU53: 2025-06-30 | AW53: 回访人：谭悦，回访时间：2025-06-27 15:30，回访内容：26考研，大四毕业，二战，家住在朝阳大悦城，考虑走读班或者住宿集训，；|回访人：谭悦，回访时间：2025-06-29 19:59，回访内容：微信跟进中，明天来营地参观沟通 ；|回访人：谭悦，回访时间：2025-06-30 14:38，回访内容：签约 | BB53: 80739300 | BC53: 否 | BD53: 26考季 | BE53: 半年集训营,考研专业课150 | BF53: 英语,政治,经综,专业课150 | BG53: 其他 | BH53: 国内高校-双非 | BI53: 是 | BL53: 报名 | BN53: 本地人本地大学(常规) | BO53: 新媒体管家-点评
B54: 43 | C54: 北京大学部 | D54: 国内大学部 | E54: 未知 | F54: 116388103 | G54: 吕猛 | H54: 2025-06-27 00:18:50 | I54: 渠道录入来源：大众点评 事件名称：在线咨询 大众点评门店名称：新东方考研四六级(国贸校区) 店铺绑定的校区：临时教学校区 店铺管理员邮箱：lvmeng2@xdf.cn 备注：2025-06-27 00:18:49,用户在大众点评新东方考研四六级(国贸校区)在线咨询 | J54: 2026财年第1财月大众点评在线咨询 | L54: 谭悦 | M54: 线上运营-本地生活平台 | N54: 大众点评 | R54: 黄一诺 | S54: 谭悦 | T54: 28622758 | U54: 正常工单 | V54: 2025-06-27 15:30 | W54: A（六个月内有报课意向工单） | X54: 考研专业课,考研集训营 | Y54: 大四 | Z54: 北京服装学院 | AA54: 服装艺术与工程学院 | AB54: 服装设计与工程 | AC54: 黄一诺 | AD54: 5460668 | AE54: 谭悦 | AF54: 2025-06-30 14:38 | AG54: 谭悦 | AH54: 2025-06-30 14:39 | AI54: KYJZ25012 | AJ54: 26考研政治半年集训营（基础/七月） | AK54: 国内考试 | AM54: 6864.8 | AP54: 新签 | AQ54: 已交接 | AR54: BJWY2101498uW2 | AS54: BJWY5556110989 | AT54: KYJZ250120041 | AU54: 2025-06-30 | AW54: 回访人：谭悦，回访时间：2025-06-27 15:30，回访内容：26考研，大四毕业，二战，家住在朝阳大悦城，考虑走读班或者住宿集训，；|回访人：谭悦，回访时间：2025-06-29 19:59，回访内容：微信跟进中，明天来营地参观沟通 ；|回访人：谭悦，回访时间：2025-06-30 14:38，回访内容：签约 | BB54: 80739300 | BC54: 否 | BD54: 26考季 | BE54: 半年集训营,考研专业课150 | BF54: 英语,政治,经综,专业课150 | BG54: 其他 | BH54: 国内高校-双非 | BI54: 是 | BL54: 报名 | BN54: 本地人本地大学(常规) | BO54: 新媒体管家-点评
B55: 44 | C55: 北京大学部 | D55: 国内大学部 | E55: 未知 | F55: 116388103 | G55: 吕猛 | H55: 2025-06-27 00:18:50 | I55: 渠道录入来源：大众点评 事件名称：在线咨询 大众点评门店名称：新东方考研四六级(国贸校区) 店铺绑定的校区：临时教学校区 店铺管理员邮箱：lvmeng2@xdf.cn 备注：2025-06-27 00:18:49,用户在大众点评新东方考研四六级(国贸校区)在线咨询 | J55: 2026财年第1财月大众点评在线咨询 | L55: 谭悦 | M55: 线上运营-本地生活平台 | N55: 大众点评 | R55: 黄一诺 | S55: 谭悦 | T55: 28622758 | U55: 正常工单 | V55: 2025-06-27 15:30 | W55: A（六个月内有报课意向工单） | X55: 考研专业课,考研集训营 | Y55: 大四 | Z55: 北京服装学院 | AA55: 服装艺术与工程学院 | AB55: 服装设计与工程 | AC55: 黄一诺 | AD55: 5460668 | AE55: 谭悦 | AF55: 2025-06-30 14:38 | AG55: 谭悦 | AH55: 2025-06-30 14:39 | AI55: KYJJZ2501 | AJ55: 26考研经综半年集训营 | AK55: 国内考试 | AM55: 25000 | AP55: 新签 | AQ55: 已交接 | AR55: BJWY2101498uW2 | AS55: BJWY5556110989 | AT55: KYJJZ25010010 | AU55: 2025-06-30 | AW55: 回访人：谭悦，回访时间：2025-06-27 15:30，回访内容：26考研，大四毕业，二战，家住在朝阳大悦城，考虑走读班或者住宿集训，；|回访人：谭悦，回访时间：2025-06-29 19:59，回访内容：微信跟进中，明天来营地参观沟通 ；|回访人：谭悦，回访时间：2025-06-30 14:38，回访内容：签约 | BB55: 80739300 | BC55: 否 | BD55: 26考季 | BE55: 半年集训营,考研专业课150 | BF55: 英语,政治,经综,专业课150 | BG55: 其他 | BH55: 国内高校-双非 | BI55: 是 | BL55: 报名 | BN55: 本地人本地大学(常规) | BO55: 新媒体管家-点评
B56: 45 | C56: 北京大学部 | D56: 国内大学部 | E56: 未知 | F56: 116388103 | G56: 吕猛 | H56: 2025-06-27 00:18:50 | I56: 渠道录入来源：大众点评 事件名称：在线咨询 大众点评门店名称：新东方考研四六级(国贸校区) 店铺绑定的校区：临时教学校区 店铺管理员邮箱：lvmeng2@xdf.cn 备注：2025-06-27 00:18:49,用户在大众点评新东方考研四六级(国贸校区)在线咨询 | J56: 2026财年第1财月大众点评在线咨询 | L56: 谭悦 | M56: 线上运营-本地生活平台 | N56: 大众点评 | R56: 黄一诺 | S56: 谭悦 | T56: 28622758 | U56: 正常工单 | V56: 2025-06-27 15:30 | W56: A（六个月内有报课意向工单） | X56: 考研专业课,考研集训营 | Y56: 大四 | Z56: 北京服装学院 | AA56: 服装艺术与工程学院 | AB56: 服装设计与工程 | AC56: 黄一诺 | AD56: 5460668 | AE56: 谭悦 | AF56: 2025-06-30 14:38 | AG56: 谭悦 | AH56: 2025-06-30 14:39 | AI56: KYZ25011 | AJ56: 26考研半年集训营（住宿费/七月） | AK56: 国内考试 | AM56: 24800 | AP56: 新签 | AQ56: 已交接 | AR56: BJWY2101498uW2 | AS56: BJWY5556110989 | AT56: KYZ250110047 | AU56: 2025-06-30 | AW56: 回访人：谭悦，回访时间：2025-06-27 15:30，回访内容：26考研，大四毕业，二战，家住在朝阳大悦城，考虑走读班或者住宿集训，；|回访人：谭悦，回访时间：2025-06-29 19:59，回访内容：微信跟进中，明天来营地参观沟通 ；|回访人：谭悦，回访时间：2025-06-30 14:38，回访内容：签约 | BB56: 80739300 | BC56: 否 | BD56: 26考季 | BE56: 半年集训营,考研专业课150 | BF56: 英语,政治,经综,专业课150 | BG56: 其他 | BH56: 国内高校-双非 | BI56: 是 | BL56: 报名 | BN56: 本地人本地大学(常规) | BO56: 新媒体管家-点评
B57: 46 | C57: 北京大学部 | D57: 国内大学部 | E57: 未知 | F57: 116388103 | G57: 吕猛 | H57: 2025-06-27 00:18:50 | I57: 渠道录入来源：大众点评 事件名称：在线咨询 大众点评门店名称：新东方考研四六级(国贸校区) 店铺绑定的校区：临时教学校区 店铺管理员邮箱：lvmeng2@xdf.cn 备注：2025-06-27 00:18:49,用户在大众点评新东方考研四六级(国贸校区)在线咨询 | J57: 2026财年第1财月大众点评在线咨询 | L57: 谭悦 | M57: 线上运营-本地生活平台 | N57: 大众点评 | R57: 黄一诺 | S57: 谭悦 | T57: 28622758 | U57: 正常工单 | V57: 2025-06-27 15:30 | W57: A（六个月内有报课意向工单） | X57: 考研专业课,考研集训营 | Y57: 大四 | Z57: 北京服装学院 | AA57: 服装艺术与工程学院 | AB57: 服装设计与工程 | AC57: 黄一诺 | AD57: 5460668 | AE57: 谭悦 | AF57: 2025-06-30 14:38 | AG57: 谭悦 | AH57: 2025-06-30 14:39 | AI57: KYJY25013A | AJ57: 26考研英语半年集训营（强冲/英语二） | AK57: 国内考试 | AM57: 14825.9 | AP57: 新签 | AQ57: 已交接 | AR57: BJWY2101498uW2 | AS57: BJWY5556110989 | AT57: KYJY25013A0060 | AU57: 2025-06-30 | AW57: 回访人：谭悦，回访时间：2025-06-27 15:30，回访内容：26考研，大四毕业，二战，家住在朝阳大悦城，考虑走读班或者住宿集训，；|回访人：谭悦，回访时间：2025-06-29 19:59，回访内容：微信跟进中，明天来营地参观沟通 ；|回访人：谭悦，回访时间：2025-06-30 14:38，回访内容：签约 | BB57: 80739300 | BC57: 否 | BD57: 26考季 | BE57: 半年集训营,考研专业课150 | BF57: 英语,政治,经综,专业课150 | BG57: 其他 | BH57: 国内高校-双非 | BI57: 是 | BL57: 报名 | BN57: 本地人本地大学(常规) | BO57: 新媒体管家-点评
B58: 47 | C58: 北京大学部 | D58: 国内大学部 | E58: 未知 | F58: 116388103 | G58: 吕猛 | H58: 2025-06-27 00:18:50 | I58: 渠道录入来源：大众点评 事件名称：在线咨询 大众点评门店名称：新东方考研四六级(国贸校区) 店铺绑定的校区：临时教学校区 店铺管理员邮箱：lvmeng2@xdf.cn 备注：2025-06-27 00:18:49,用户在大众点评新东方考研四六级(国贸校区)在线咨询 | J58: 2026财年第1财月大众点评在线咨询 | L58: 谭悦 | M58: 线上运营-本地生活平台 | N58: 大众点评 | R58: 黄一诺 | S58: 谭悦 | T58: 28622758 | U58: 正常工单 | V58: 2025-06-27 15:30 | W58: A（六个月内有报课意向工单） | X58: 考研专业课,考研集训营 | Y58: 大四 | Z58: 北京服装学院 | AA58: 服装艺术与工程学院 | AB58: 服装设计与工程 | AC58: 黄一诺 | AD58: 5460668 | AE58: 谭悦 | AF58: 2025-06-30 14:38 | AG58: 谭悦 | AH58: 2025-06-30 14:39 | AI58: KYJZ25013A | AJ58: 26考研政治半年集训营（强冲） | AK58: 国内考试 | AM58: 9685.2 | AP58: 新签 | AQ58: 已交接 | AR58: BJWY2101498uW2 | AS58: BJWY5556110989 | AT58: KYJZ25013A0045 | AU58: 2025-06-30 | AW58: 回访人：谭悦，回访时间：2025-06-27 15:30，回访内容：26考研，大四毕业，二战，家住在朝阳大悦城，考虑走读班或者住宿集训，；|回访人：谭悦，回访时间：2025-06-29 19:59，回访内容：微信跟进中，明天来营地参观沟通 ；|回访人：谭悦，回访时间：2025-06-30 14:38，回访内容：签约 | BB58: 80739300 | BC58: 否 | BD58: 26考季 | BE58: 半年集训营,考研专业课150 | BF58: 英语,政治,经综,专业课150 | BG58: 其他 | BH58: 国内高校-双非 | BI58: 是 | BL58: 报名 | BN58: 本地人本地大学(常规) | BO58: 新媒体管家-点评
B59: 48 | C59: 北京大学部 | D59: 国内大学部 | E59: 未知 | F59: 116388103 | G59: 吕猛 | H59: 2025-06-27 00:18:50 | I59: 渠道录入来源：大众点评 事件名称：在线咨询 大众点评门店名称：新东方考研四六级(国贸校区) 店铺绑定的校区：临时教学校区 店铺管理员邮箱：lvmeng2@xdf.cn 备注：2025-06-27 00:18:49,用户在大众点评新东方考研四六级(国贸校区)在线咨询 | J59: 2026财年第1财月大众点评在线咨询 | L59: 谭悦 | M59: 线上运营-本地生活平台 | N59: 大众点评 | R59: 黄一诺 | S59: 谭悦 | T59: 28622758 | U59: 正常工单 | V59: 2025-06-27 15:30 | W59: A（六个月内有报课意向工单） | X59: 考研专业课,考研集训营 | Y59: 大四 | Z59: 北京服装学院 | AA59: 服装艺术与工程学院 | AB59: 服装设计与工程 | AC59: 黄一诺 | AD59: 5460668 | AE59: 谭悦 | AF59: 2025-06-30 14:38 | AG59: 谭悦 | AH59: 2025-06-30 14:39 | AI59: LP17512614561757 | AJ59: 考研初试专业课一对一（26考研/集训30小时） | AK59: 国内考试 | AM59: 11300 | AP59: 新签 | AQ59: 已交接 | AR59: BJWY2101498uW2 | AS59: BJWY5556110989 | AU59: 2025-06-30 | AW59: 回访人：谭悦，回访时间：2025-06-27 15:30，回访内容：26考研，大四毕业，二战，家住在朝阳大悦城，考虑走读班或者住宿集训，；|回访人：谭悦，回访时间：2025-06-29 19:59，回访内容：微信跟进中，明天来营地参观沟通 ；|回访人：谭悦，回访时间：2025-06-30 14:38，回访内容：签约 | BB59: 80739300 | BC59: 否 | BD59: 26考季 | BE59: 半年集训营,考研专业课150 | BF59: 英语,政治,经综,专业课150 | BG59: 其他 | BH59: 国内高校-双非 | BI59: 是 | BN59: 本地人本地大学(常规) | BO59: 新媒体管家-点评
B60: 49 | C60: 北京大学部 | D60: 国内大学部 | E60: 张家长 | F60: 102473626 | G60: 杨沫 | H60: 2025-05-14 14:34:40 | I60: 杨莹莹+yangyingying18@xdf.cn+ID+北京学校-运营管理部-东南区-刘家窑角门分中心 谭悦 | K60: 大一 | L60: 谭悦 | M60: 转介绍 | N60: 内部员工推荐 | O60: 杨莹莹+yangyingying18@xdf.cn+ID+北京学校-运营管理部-东南区-刘家窑角门分中心 | R60: 张雅琦 | S60: 谭悦 | T60: 27893786 | U60: 正常工单 | V60: 2025-06-30 17:07 | W60: A（六个月内有报课意向工单） | X60: 四级 | Y60: 大一 | Z60: 衡水学院 | AA60: 外国语学院 | AB60: 英语 | AC60: 张雅琦 | AD60: 5433340 | AE60: 谭悦 | AF60: 2025-06-30 21:12 | AG60: 谭悦 | AH60: 2025-07-01 10:10 | AI60: ZVVA26001 | AJ60: 四级暑假集训营（24H冲刺直播） | AK60: 国内考试 | AM60: 15000 | AO60: 杨莹莹+yangyingying18@xdf.cn+ID+北京学校-运营管理部-东南区-刘家窑角门分中心 | AP60: 新签 | AQ60: 已交接 | AR60: WebReg | AS60: BJWY4095691646 | AT60: ZVVA260010028 | AU60: 2025-06-30 | AW60: 回访人：谭悦，回访时间：2025-06-23 19:05，回访内容：不回复 ；|回访人：程远，回访时间：2025-06-30 17:07，回访内容：程远恢复工单, 系统自动生成回访记录!；|回访人：谭悦，回访时间：2025-06-30 21:12，回访内容：准备报名 | BB60: 70439422 | BC60: 否 | BD60: 25下考季 | BE60: 四级无忧计划 | BH60: 国内高校-双非 | BI60: 是 | BL60: 报名 | BN60: 外地人外地大学(常规) | BO60: 客服
B61: 50 | C61: 北京大学部 | D61: 国内大学部 | E61: 未告知 | F61: 116595589 | G61: 赵秋侠 | H61: 2025-06-28 18:10:08 | K61: 高三 | L61: 赵星火 | M61: 转介绍 | N61: 内部员工推荐 | O61: 王佳琦+wangjiaqi65@xdf.cn+ID+产业机构-大学事业部-大学沈阳中心-考研项目部-销售管理部 | R61: 邵春晖 | S61: 赵星火 | T61: 28690651 | U61: 正常工单 | V61: 2025-06-28 18:23 | W61: A（六个月内有报课意向工单） | X61: 大学预科 | Y61: 高三 | Z61: 鞍山市鞍钢高中 | AA61: 新大一 | AB61: 新大一 | AC61: 邵春晖 | AD61: 5433321 | AE61: 赵星火 | AF61: 2025-06-30 21:08 | AG61: 赵星火 | AH61: 2025-06-30 21:08 | AI61: ZVVA26001 | AJ61: 四级暑假集训营（24H冲刺直播） | AK61: 国内考试 | AM61: 15000 | AO61: 王佳琦+wangjiaqi65@xdf.cn+ID+产业机构-大学事业部-大学沈阳中心-考研项目部-销售管理部 | AP61: 新签 | AQ61: 已交接 | AR61: WebReg | AS61: BJWY5696578429 | AT61: ZVVA260010027 | AU61: 2025-06-30 | AW61: 回访人：赵星火，回访时间：2025-06-28 18:23，回访内容：想要集训学习，北京这边也有地方住，就比较远，想要学习听说和背单词，关注学习管理给到四级集训介绍；|回访人：赵星火，回访时间：2025-06-30 16:49，回访内容：跟进学生担心不放心，跟进学生情况继续维护中。；|回访人：赵星火，回访时间：2025-06-30 21:08，回访内容：1 | BB61: 80705238 | BC61: 否 | BH61: 国内高校-双非 | BI61: 是 | BL61: 报名 | BO61: 客服
B62: 51 | C62: 北京大学部 | D62: 国内大学部 | F62: 100254299 | H62: 2025-04-20 11:16:06 | I62: 死单激活分配赵星火 外呼主题：FY25-英学1-4月无效资源回访（1.1-4.13） | K62: 大三 | L62: 赵星火 | M62: 线上运营-本地生活平台 | N62: 知了好学 | R62: 王英帆 | S62: 谭悦 | T62: 28730425 | U62: 续费工单 | V62: 2025-06-30 20:33 | W62: A（六个月内有报课意向工单） | X62: 考研集训营 | Y62: 大四 | Z62: 北京邮电大学 | AA62: 电子工程学院 | AB62: 电子信息科学与技术 | AC62: 王英帆 | AD62: 5433214 | AE62: 赵星火 | AF62: 2025-06-30 20:34 | AG62: 谭悦 | AH62: 2025-06-30 20:34 | AK62: 国内考试 | AM62: 45450 | AN62: 同科续费 | AP62: 分单 | AQ62: 已交接 | AS62: BJWY4965756550 | AW62: 回访人：谭悦，回访时间：2025-06-30 20:33，回访内容：1；|回访人：谭悦，回访时间：2025-06-30 20:34，回访内容：签约 | BB62: 64203758 | BC62: 否 | BD62: 26考季 | BE62: 半年集训营 | BF62: 英语,政治,经综 | BH62: 国内高校-211 | BI62: 否 | BN62: 外地人本地大学(常规)
B63: 52 | C63: 北京大学部 | D63: 国内大学部 | E63: 孙亚静 | F63: 116530527 | G63: 赵秋侠 | H63: 2025-06-28 13:56:04 | I63: 魏公村直访 | K63: 大三 | L63: 谭悦 | M63: 直访 | N63: 直访 | R63: 李星仪 | S63: 谭悦 | T63: 28705832 | U63: 正常工单 | V63: 2025-06-28 15:16 | W63: A（六个月内有报课意向工单） | X63: 考研专业课,考研无忧计划 | Y63: 大三 | Z63: 北京林业大学 | AA63: 信息学院 | AB63: 计算机科学与技术 | AC63: 李星仪 | AD63: 5433070 | AE63: 谭悦 | AF63: 2025-06-30 19:59 | AG63: 谭悦 | AH63: 2025-06-30 20:00 | AI63: WYE26074 | AJ63: 考研英语无忧计划（26考研/英一强化） | AK63: 国内考试 | AM63: 3160.65 | AP63: 新签 | AQ63: 已交接 | AR63: BJWY2101498uW2 | AS63: BJWY2280140260 | AT63: WYE260740058 | AU63: 2025-06-30 | AW63: 回访人：谭悦，回访时间：2025-06-28 15:16，回访内容：学生：李星仪 专业：电子信息 院校：北京林业大学 年级：大三 四六级 都过 数学有基础 目标院校 没有定现在复习进度就是英语背单词了 数学还可以 专业课刚学完 规划 北交 ，北京科技大学 推荐啄木鸟 也考虑候鸟 已经发送试听课；|回访人：谭悦，回访时间：2025-06-29 22:29，回访内容：跟进中 逼单 ；|回访人：谭悦，回访时间：2025-06-30 19:59，回访内容：签约 | BB63: 74492611 | BC63: 否 | BD63: 26考季 | BE63: 无忧计划-啄木鸟,考研专业课150 | BF63: 英语,政治,数学,专业课150 | BG63: 其他 | BH63: 国内高校-211 | BI63: 是 | BL63: 报名 | BN63: 本地人本地大学(常规) | BO63: 客服
B64: 53 | C64: 北京大学部 | D64: 国内大学部 | E64: 孙亚静 | F64: 116530527 | G64: 赵秋侠 | H64: 2025-06-28 13:56:04 | I64: 魏公村直访 | K64: 大三 | L64: 谭悦 | M64: 直访 | N64: 直访 | R64: 李星仪 | S64: 谭悦 | T64: 28705832 | U64: 正常工单 | V64: 2025-06-28 15:16 | W64: A（六个月内有报课意向工单） | X64: 考研专业课,考研无忧计划 | Y64: 大三 | Z64: 北京林业大学 | AA64: 信息学院 | AB64: 计算机科学与技术 | AC64: 李星仪 | AD64: 5433070 | AE64: 谭悦 | AF64: 2025-06-30 19:59 | AG64: 谭悦 | AH64: 2025-06-30 20:00 | AI64: WYM26033 | AJ64: 考研数学无忧计划（26考研/冲刺） | AK64: 国内考试 | AM64: 1705.3 | AP64: 新签 | AQ64: 已交接 | AR64: BJWY2101498uW2 | AS64: BJWY2280140260 | AT64: WYM260330037 | AU64: 2025-06-30 | AW64: 回访人：谭悦，回访时间：2025-06-28 15:16，回访内容：学生：李星仪 专业：电子信息 院校：北京林业大学 年级：大三 四六级 都过 数学有基础 目标院校 没有定现在复习进度就是英语背单词了 数学还可以 专业课刚学完 规划 北交 ，北京科技大学 推荐啄木鸟 也考虑候鸟 已经发送试听课；|回访人：谭悦，回访时间：2025-06-29 22:29，回访内容：跟进中 逼单 ；|回访人：谭悦，回访时间：2025-06-30 19:59，回访内容：签约 | BB64: 74492611 | BC64: 否 | BD64: 26考季 | BE64: 无忧计划-啄木鸟,考研专业课150 | BF64: 英语,政治,数学,专业课150 | BG64: 其他 | BH64: 国内高校-211 | BI64: 是 | BL64: 报名 | BN64: 本地人本地大学(常规) | BO64: 客服
B65: 54 | C65: 北京大学部 | D65: 国内大学部 | E65: 孙亚静 | F65: 116530527 | G65: 赵秋侠 | H65: 2025-06-28 13:56:04 | I65: 魏公村直访 | K65: 大三 | L65: 谭悦 | M65: 直访 | N65: 直访 | R65: 李星仪 | S65: 谭悦 | T65: 28705832 | U65: 正常工单 | V65: 2025-06-28 15:16 | W65: A（六个月内有报课意向工单） | X65: 考研专业课,考研无忧计划 | Y65: 大三 | Z65: 北京林业大学 | AA65: 信息学院 | AB65: 计算机科学与技术 | AC65: 李星仪 | AD65: 5433070 | AE65: 谭悦 | AF65: 2025-06-30 19:59 | AG65: 谭悦 | AH65: 2025-06-30 20:00 | AI65: WYP26065 | AJ65: 考研政治无忧计划（26考研/强化） | AK65: 国内考试 | AM65: 1948.95 | AP65: 新签 | AQ65: 已交接 | AR65: BJWY2101498uW2 | AS65: BJWY2280140260 | AT65: WYP260650010 | AU65: 2025-06-30 | AW65: 回访人：谭悦，回访时间：2025-06-28 15:16，回访内容：学生：李星仪 专业：电子信息 院校：北京林业大学 年级：大三 四六级 都过 数学有基础 目标院校 没有定现在复习进度就是英语背单词了 数学还可以 专业课刚学完 规划 北交 ，北京科技大学 推荐啄木鸟 也考虑候鸟 已经发送试听课；|回访人：谭悦，回访时间：2025-06-29 22:29，回访内容：跟进中 逼单 ；|回访人：谭悦，回访时间：2025-06-30 19:59，回访内容：签约 | BB65: 74492611 | BC65: 否 | BD65: 26考季 | BE65: 无忧计划-啄木鸟,考研专业课150 | BF65: 英语,政治,数学,专业课150 | BG65: 其他 | BH65: 国内高校-211 | BI65: 是 | BL65: 报名 | BN65: 本地人本地大学(常规) | BO65: 客服
B66: 55 | C66: 北京大学部 | D66: 国内大学部 | E66: 孙亚静 | F66: 116530527 | G66: 赵秋侠 | H66: 2025-06-28 13:56:04 | I66: 魏公村直访 | K66: 大三 | L66: 谭悦 | M66: 直访 | N66: 直访 | R66: 李星仪 | S66: 谭悦 | T66: 28705832 | U66: 正常工单 | V66: 2025-06-28 15:16 | W66: A（六个月内有报课意向工单） | X66: 考研专业课,考研无忧计划 | Y66: 大三 | Z66: 北京林业大学 | AA66: 信息学院 | AB66: 计算机科学与技术 | AC66: 李星仪 | AD66: 5433070 | AE66: 谭悦 | AF66: 2025-06-30 19:59 | AG66: 谭悦 | AH66: 2025-06-30 20:00 | AI66: WYM26032 | AJ66: 考研数学无忧计划（26考研/强化） | AK66: 国内考试 | AM66: 3573.05 | AP66: 新签 | AQ66: 已交接 | AR66: BJWY2101498uW2 | AS66: BJWY2280140260 | AT66: WYM260320036 | AU66: 2025-06-30 | AW66: 回访人：谭悦，回访时间：2025-06-28 15:16，回访内容：学生：李星仪 专业：电子信息 院校：北京林业大学 年级：大三 四六级 都过 数学有基础 目标院校 没有定现在复习进度就是英语背单词了 数学还可以 专业课刚学完 规划 北交 ，北京科技大学 推荐啄木鸟 也考虑候鸟 已经发送试听课；|回访人：谭悦，回访时间：2025-06-29 22:29，回访内容：跟进中 逼单 ；|回访人：谭悦，回访时间：2025-06-30 19:59，回访内容：签约 | BB66: 74492611 | BC66: 否 | BD66: 26考季 | BE66: 无忧计划-啄木鸟,考研专业课150 | BF66: 英语,政治,数学,专业课150 | BG66: 其他 | BH66: 国内高校-211 | BI66: 是 | BL66: 报名 | BN66: 本地人本地大学(常规) | BO66: 客服
B67: 56 | C67: 北京大学部 | D67: 国内大学部 | E67: 孙亚静 | F67: 116530527 | G67: 赵秋侠 | H67: 2025-06-28 13:56:04 | I67: 魏公村直访 | K67: 大三 | L67: 谭悦 | M67: 直访 | N67: 直访 | R67: 李星仪 | S67: 谭悦 | T67: 28705832 | U67: 正常工单 | V67: 2025-06-28 15:16 | W67: A（六个月内有报课意向工单） | X67: 考研专业课,考研无忧计划 | Y67: 大三 | Z67: 北京林业大学 | AA67: 信息学院 | AB67: 计算机科学与技术 | AC67: 李星仪 | AD67: 5433070 | AE67: 谭悦 | AF67: 2025-06-30 19:59 | AG67: 谭悦 | AH67: 2025-06-30 20:00 | AI67: WYM26031 | AJ67: 考研数学无忧计划（26考研/基础） | AK67: 国内考试 | AM67: 2354.95 | AP67: 新签 | AQ67: 已交接 | AR67: BJWY2101498uW2 | AS67: BJWY2280140260 | AT67: WYM260310036 | AU67: 2025-06-30 | AW67: 回访人：谭悦，回访时间：2025-06-28 15:16，回访内容：学生：李星仪 专业：电子信息 院校：北京林业大学 年级：大三 四六级 都过 数学有基础 目标院校 没有定现在复习进度就是英语背单词了 数学还可以 专业课刚学完 规划 北交 ，北京科技大学 推荐啄木鸟 也考虑候鸟 已经发送试听课；|回访人：谭悦，回访时间：2025-06-29 22:29，回访内容：跟进中 逼单 ；|回访人：谭悦，回访时间：2025-06-30 19:59，回访内容：签约 | BB67: 74492611 | BC67: 否 | BD67: 26考季 | BE67: 无忧计划-啄木鸟,考研专业课150 | BF67: 英语,政治,数学,专业课150 | BG67: 其他 | BH67: 国内高校-211 | BI67: 是 | BL67: 报名 | BN67: 本地人本地大学(常规) | BO67: 客服
B68: 57 | C68: 北京大学部 | D68: 国内大学部 | E68: 孙亚静 | F68: 116530527 | G68: 赵秋侠 | H68: 2025-06-28 13:56:04 | I68: 魏公村直访 | K68: 大三 | L68: 谭悦 | M68: 直访 | N68: 直访 | R68: 李星仪 | S68: 谭悦 | T68: 28705832 | U68: 正常工单 | V68: 2025-06-28 15:16 | W68: A（六个月内有报课意向工单） | X68: 考研专业课,考研无忧计划 | Y68: 大三 | Z68: 北京林业大学 | AA68: 信息学院 | AB68: 计算机科学与技术 | AC68: 李星仪 | AD68: 5433070 | AE68: 谭悦 | AF68: 2025-06-30 19:59 | AG68: 谭悦 | AH68: 2025-06-30 20:00 | AI68: WYP26066 | AJ68: 考研政治无忧计划（26考研/冲刺） | AK68: 国内考试 | AM68: 2314.35 | AP68: 新签 | AQ68: 已交接 | AR68: BJWY2101498uW2 | AS68: BJWY2280140260 | AT68: WYP260660010 | AU68: 2025-06-30 | AW68: 回访人：谭悦，回访时间：2025-06-28 15:16，回访内容：学生：李星仪 专业：电子信息 院校：北京林业大学 年级：大三 四六级 都过 数学有基础 目标院校 没有定现在复习进度就是英语背单词了 数学还可以 专业课刚学完 规划 北交 ，北京科技大学 推荐啄木鸟 也考虑候鸟 已经发送试听课；|回访人：谭悦，回访时间：2025-06-29 22:29，回访内容：跟进中 逼单 ；|回访人：谭悦，回访时间：2025-06-30 19:59，回访内容：签约 | BB68: 74492611 | BC68: 否 | BD68: 26考季 | BE68: 无忧计划-啄木鸟,考研专业课150 | BF68: 英语,政治,数学,专业课150 | BG68: 其他 | BH68: 国内高校-211 | BI68: 是 | BL68: 报名 | BN68: 本地人本地大学(常规) | BO68: 客服
B69: 58 | C69: 北京大学部 | D69: 国内大学部 | E69: 孙亚静 | F69: 116530527 | G69: 赵秋侠 | H69: 2025-06-28 13:56:04 | I69: 魏公村直访 | K69: 大三 | L69: 谭悦 | M69: 直访 | N69: 直访 | R69: 李星仪 | S69: 谭悦 | T69: 28705832 | U69: 正常工单 | V69: 2025-06-28 15:16 | W69: A（六个月内有报课意向工单） | X69: 考研专业课,考研无忧计划 | Y69: 大三 | Z69: 北京林业大学 | AA69: 信息学院 | AB69: 计算机科学与技术 | AC69: 李星仪 | AD69: 5433070 | AE69: 谭悦 | AF69: 2025-06-30 19:59 | AG69: 谭悦 | AH69: 2025-06-30 20:00 | AI69: WYE26078 | AJ69: 考研英语无忧计划（26考研/基础） | AK69: 国内考试 | AM69: 2598.6 | AP69: 新签 | AQ69: 已交接 | AR69: BJWY2101498uW2 | AS69: BJWY2280140260 | AT69: WYE260780014 | AU69: 2025-06-30 | AW69: 回访人：谭悦，回访时间：2025-06-28 15:16，回访内容：学生：李星仪 专业：电子信息 院校：北京林业大学 年级：大三 四六级 都过 数学有基础 目标院校 没有定现在复习进度就是英语背单词了 数学还可以 专业课刚学完 规划 北交 ，北京科技大学 推荐啄木鸟 也考虑候鸟 已经发送试听课；|回访人：谭悦，回访时间：2025-06-29 22:29，回访内容：跟进中 逼单 ；|回访人：谭悦，回访时间：2025-06-30 19:59，回访内容：签约 | BB69: 74492611 | BC69: 否 | BD69: 26考季 | BE69: 无忧计划-啄木鸟,考研专业课150 | BF69: 英语,政治,数学,专业课150 | BG69: 其他 | BH69: 国内高校-211 | BI69: 是 | BL69: 报名 | BN69: 本地人本地大学(常规) | BO69: 客服
B70: 59 | C70: 北京大学部 | D70: 国内大学部 | E70: 孙亚静 | F70: 116530527 | G70: 赵秋侠 | H70: 2025-06-28 13:56:04 | I70: 魏公村直访 | K70: 大三 | L70: 谭悦 | M70: 直访 | N70: 直访 | R70: 李星仪 | S70: 谭悦 | T70: 28705832 | U70: 正常工单 | V70: 2025-06-28 15:16 | W70: A（六个月内有报课意向工单） | X70: 考研专业课,考研无忧计划 | Y70: 大三 | Z70: 北京林业大学 | AA70: 信息学院 | AB70: 计算机科学与技术 | AC70: 李星仪 | AD70: 5433070 | AE70: 谭悦 | AF70: 2025-06-30 19:59 | AG70: 谭悦 | AH70: 2025-06-30 20:00 | AI70: WYE26075 | AJ70: 考研英语无忧计划（26考研/英一冲刺） | AK70: 国内考试 | AM70: 1624.1 | AP70: 新签 | AQ70: 已交接 | AR70: BJWY2101498uW2 | AS70: BJWY2280140260 | AT70: WYE260750058 | AU70: 2025-06-30 | AW70: 回访人：谭悦，回访时间：2025-06-28 15:16，回访内容：学生：李星仪 专业：电子信息 院校：北京林业大学 年级：大三 四六级 都过 数学有基础 目标院校 没有定现在复习进度就是英语背单词了 数学还可以 专业课刚学完 规划 北交 ，北京科技大学 推荐啄木鸟 也考虑候鸟 已经发送试听课；|回访人：谭悦，回访时间：2025-06-29 22:29，回访内容：跟进中 逼单 ；|回访人：谭悦，回访时间：2025-06-30 19:59，回访内容：签约 | BB70: 74492611 | BC70: 否 | BD70: 26考季 | BE70: 无忧计划-啄木鸟,考研专业课150 | BF70: 英语,政治,数学,专业课150 | BG70: 其他 | BH70: 国内高校-211 | BI70: 是 | BL70: 报名 | BN70: 本地人本地大学(常规) | BO70: 客服
B71: 60 | C71: 北京大学部 | D71: 国内大学部 | E71: 孙亚静 | F71: 116530527 | G71: 赵秋侠 | H71: 2025-06-28 13:56:04 | I71: 魏公村直访 | K71: 大三 | L71: 谭悦 | M71: 直访 | N71: 直访 | R71: 李星仪 | S71: 谭悦 | T71: 28705832 | U71: 正常工单 | V71: 2025-06-28 15:16 | W71: A（六个月内有报课意向工单） | X71: 考研专业课,考研无忧计划 | Y71: 大三 | Z71: 北京林业大学 | AA71: 信息学院 | AB71: 计算机科学与技术 | AC71: 李星仪 | AD71: 5433070 | AE71: 谭悦 | AF71: 2025-06-30 19:59 | AG71: 谭悦 | AH71: 2025-06-30 20:00 | AI71: WYP26064 | AJ71: 考研政治无忧计划（26考研/基础） | AK71: 国内考试 | AM71: 3370.05 | AP71: 新签 | AQ71: 已交接 | AR71: BJWY2101498uW2 | AS71: BJWY2280140260 | AT71: WYP260640010 | AU71: 2025-06-30 | AW71: 回访人：谭悦，回访时间：2025-06-28 15:16，回访内容：学生：李星仪 专业：电子信息 院校：北京林业大学 年级：大三 四六级 都过 数学有基础 目标院校 没有定现在复习进度就是英语背单词了 数学还可以 专业课刚学完 规划 北交 ，北京科技大学 推荐啄木鸟 也考虑候鸟 已经发送试听课；|回访人：谭悦，回访时间：2025-06-29 22:29，回访内容：跟进中 逼单 ；|回访人：谭悦，回访时间：2025-06-30 19:59，回访内容：签约 | BB71: 74492611 | BC71: 否 | BD71: 26考季 | BE71: 无忧计划-啄木鸟,考研专业课150 | BF71: 英语,政治,数学,专业课150 | BG71: 其他 | BH71: 国内高校-211 | BI71: 是 | BL71: 报名 | BN71: 本地人本地大学(常规) | BO71: 客服
B72: 61 | C72: 北京大学部 | D72: 国内大学部 | E72: 孙亚静 | F72: 116530527 | G72: 赵秋侠 | H72: 2025-06-28 13:56:04 | I72: 魏公村直访 | K72: 大三 | L72: 谭悦 | M72: 直访 | N72: 直访 | R72: 李星仪 | S72: 谭悦 | T72: 28705832 | U72: 正常工单 | V72: 2025-06-28 15:16 | W72: A（六个月内有报课意向工单） | X72: 考研专业课,考研无忧计划 | Y72: 大三 | Z72: 北京林业大学 | AA72: 信息学院 | AB72: 计算机科学与技术 | AC72: 李星仪 | AD72: 5433070 | AE72: 谭悦 | AF72: 2025-06-30 19:59 | AG72: 谭悦 | AH72: 2025-06-30 20:00 | AI72: LP17512816676211 | AJ72: 考研初试专业课一对一（26考研/无忧30小时） | AK72: 国内考试 | AM72: 5250 | AP72: 新签 | AQ72: 已交接 | AR72: BJWY2101498uW2 | AS72: BJWY2280140260 | AU72: 2025-06-30 | AW72: 回访人：谭悦，回访时间：2025-06-28 15:16，回访内容：学生：李星仪 专业：电子信息 院校：北京林业大学 年级：大三 四六级 都过 数学有基础 目标院校 没有定现在复习进度就是英语背单词了 数学还可以 专业课刚学完 规划 北交 ，北京科技大学 推荐啄木鸟 也考虑候鸟 已经发送试听课；|回访人：谭悦，回访时间：2025-06-29 22:29，回访内容：跟进中 逼单 ；|回访人：谭悦，回访时间：2025-06-30 19:59，回访内容：签约 | BB72: 74492611 | BC72: 否 | BD72: 26考季 | BE72: 无忧计划-啄木鸟,考研专业课150 | BF72: 英语,政治,数学,专业课150 | BG72: 其他 | BH72: 国内高校-211 | BI72: 是 | BN72: 本地人本地大学(常规) | BO72: 客服
B73: 62 | C73: 北京大学部 | D73: 国内大学部 | F73: 78869656 | H73: 2024-07-04 11:22:02 | I73: 刚高考完，咨询英语四级方面的辅导，现在方便电话联系；刚高考完，咨询英语四级方面的辅导，现在方便电话联系 | K73: 大一 | L73: 王若飞(离职) | M73: 线上运营-本地生活平台 | N73: 大众点评 | R73: 阮江 | S73: 谭悦 | T73: 27663688 | U73: 续费工单 | V73: 2025-04-24 18:03 | W73: A（六个月内有报课意向工单） | X73: 四级 | Y73: 大一 | Z73: 北京工业大学 | AA73: 信息学部 | AB73: 物联网工程 | AC73: 阮江 | AD73: 5433040 | AE73: 谭悦 | AF73: 2025-06-30 19:50 | AG73: 谭悦 | AH73: 2025-06-30 19:50 | AI73: ZVVA26001 | AJ73: 四级暑假集训营（24H冲刺直播） | AK73: 国内考试 | AM73: 15000 | AN73: 同科续费 | AP73: 续班 | AQ73: 已交接 | AR73: BJWY2011wXCx1W | AS73: BJWY4575112970 | AT73: ZVVA260010026 | AU73: 2025-06-30 | AW73: 回访人：谭悦，回访时间：2025-06-28 20:57，回访内容：微信跟进中，考研学习 ；|回访人：谭悦，回访时间：2025-06-30 14:06，回访内容：准备报名暑假集训 ；|回访人：谭悦，回访时间：2025-06-30 19:50，回访内容：1 | BB73: 59834457 | BC73: 否 | BD73: 25下考季 | BE73: 四级无忧计划 | BH73: 国内高校-211 | BI73: 是 | BL73: 报名 | BN73: 本地人本地大学(常规)
B74: 63 | C74: 北京大学部 | D74: 国内大学部 | E74: 陈政宇同学 | F74: 98581283 | G74: 吴凯龙 | H74: 2025-04-01 14:19:49 | I74: 谭悦老师内部员工推荐工单 | K74: 大三 | L74: 谭悦 | M74: 转介绍 | N74: 内部员工推荐 | O74: 杨莹莹+yangyingying18@xdf.cn+ID+北京学校-运营管理部 | R74: 陈政宇 | S74: 谭悦 | T74: 27417879 | U74: 续费工单 | V74: 2025-04-01 14:38 | W74: A（六个月内有报课意向工单） | X74: 考研VIP | Y74: 大三 | Z74: 中央音乐学院 | AA74: 音乐学系 | AB74: 音乐学 | AC74: 陈政宇 | AD74: 5432904 | AE74: 谭悦 | AF74: 2025-06-30 19:13 | AG74: 谭悦 | AH74: 2025-06-30 19:17 | AI74: LP17512820076320 | AJ74: 26考研一对一伴学（50h/无忧） | AK74: 国内考试 | AM74: 40000 | AO74: 杨莹莹+yangyingying18@xdf.cn+ID+北京学校-运营管理部 | AP74: 续班 | AQ74: 已交接 | AS74: BJWY1881829500 | AU74: 2025-06-30 | AW74: 回访人：谭悦，回访时间：2025-06-24 18:08，回访内容：微信跟进 一对一续费 ；|回访人：谭悦，回访时间：2025-06-30 15:23，回访内容：微信跟进中，半年营 一直没报 | BB74: 51892257 | BC74: 否 | BD74: 26考季 | BE74: VIP - 伴学 | BF74: 英语,政治 | BG74: 其他 | BH74: 国内高校-211 | BI74: 是 | BN74: 本地人本地大学(常规) | BO74: 客服
B75: 64 | C75: 北京大学部 | D75: 国内大学部 | E75: 李同学 | F75: 116621997 | G75: 杨沫 | H75: 2025-06-29 15:39:34 | I75: 知春路直访 | K75: 大三 | L75: 张俊旺 | M75: 直访 | N75: 直访 | R75: 李广地 | S75: 谭悦 | T75: 28716368 | U75: 正常工单 | V75: 2025-06-29 20:28 | W75: A（六个月内有报课意向工单） | X75: 考研无忧计划 | Y75: 大三 | Z75: 北京工业大学 | AA75: 信息学部 | AB75: 通信工程 | AC75: 李广地 | AD75: 5431884 | AE75: 谭悦 | AF75: 2025-06-30 14:55 | AG75: 谭悦 | AH75: 2025-06-30 14:56 | AI75: WYHM2604 | AJ75: 考研数学无忧计划候鸟（26考研/基础强化） | AK75: 国内考试 | AM75: 5502.55 | AP75: 新签 | AQ75: 已交接 | AR75: BJWY25030q8UPI | AS75: BJWY6311842248 | AT75: WYHM26040030 | AU75: 2025-06-30 | AW75: 回访人：张俊旺，回访时间：2025-06-29 15:49，回访内容：校区面谈中；|回访人：张俊旺，回访时间：2025-06-29 19:04，回访内容：谭悦老师沟通，晚上决定；|回访人：谭悦，回访时间：2025-06-29 20:56，回访内容：准备报名 ；|回访人：谭悦，回访时间：2025-06-30 14:55，回访内容：签约 | BB75: 80723875 | BC75: 否 | BD75: 26考季 | BE75: 无忧计划-候鸟 | BF75: 英语,政治,数学 | BG75: 其他 | BH75: 国内高校-211 | BI75: 是 | BL75: 报名 | BN75: 本地人本地大学(常规) | BO75: 客服
B76: 65 | C76: 北京大学部 | D76: 国内大学部 | E76: 李同学 | F76: 116621997 | G76: 杨沫 | H76: 2025-06-29 15:39:34 | I76: 知春路直访 | K76: 大三 | L76: 张俊旺 | M76: 直访 | N76: 直访 | R76: 李广地 | S76: 谭悦 | T76: 28716368 | U76: 正常工单 | V76: 2025-06-29 20:28 | W76: A（六个月内有报课意向工单） | X76: 考研无忧计划 | Y76: 大三 | Z76: 北京工业大学 | AA76: 信息学部 | AB76: 通信工程 | AC76: 李广地 | AD76: 5431884 | AE76: 谭悦 | AF76: 2025-06-30 14:55 | AG76: 谭悦 | AH76: 2025-06-30 14:56 | AI76: WYHP26002 | AJ76: 考研政治无忧计划候鸟（26考研/冲刺） | AK76: 国内考试 | AM76: 797.45 | AP76: 新签 | AQ76: 已交接 | AR76: BJWY25030q8UPI | AS76: BJWY6311842248 | AT76: WYHP260020097 | AU76: 2025-06-30 | AW76: 回访人：张俊旺，回访时间：2025-06-29 15:49，回访内容：校区面谈中；|回访人：张俊旺，回访时间：2025-06-29 19:04，回访内容：谭悦老师沟通，晚上决定；|回访人：谭悦，回访时间：2025-06-29 20:56，回访内容：准备报名 ；|回访人：谭悦，回访时间：2025-06-30 14:55，回访内容：签约 | BB76: 80723875 | BC76: 否 | BD76: 26考季 | BE76: 无忧计划-候鸟 | BF76: 英语,政治,数学 | BG76: 其他 | BH76: 国内高校-211 | BI76: 是 | BL76: 报名 | BN76: 本地人本地大学(常规) | BO76: 客服
B77: 66 | C77: 北京大学部 | D77: 国内大学部 | E77: 李同学 | F77: 116621997 | G77: 杨沫 | H77: 2025-06-29 15:39:34 | I77: 知春路直访 | K77: 大三 | L77: 张俊旺 | M77: 直访 | N77: 直访 | R77: 李广地 | S77: 谭悦 | T77: 28716368 | U77: 正常工单 | V77: 2025-06-29 20:28 | W77: A（六个月内有报课意向工单） | X77: 考研无忧计划 | Y77: 大三 | Z77: 北京工业大学 | AA77: 信息学部 | AB77: 通信工程 | AC77: 李广地 | AD77: 5431884 | AE77: 谭悦 | AF77: 2025-06-30 14:55 | AG77: 谭悦 | AH77: 2025-06-30 14:56 | AI77: WYHE26005 | AJ77: 考研英语无忧计划候鸟（26考研/英一冲刺） | AK77: 国内考试 | AM77: 797.45 | AP77: 新签 | AQ77: 已交接 | AR77: BJWY25030q8UPI | AS77: BJWY6311842248 | AT77: WYHE260050090 | AU77: 2025-06-30 | AW77: 回访人：张俊旺，回访时间：2025-06-29 15:49，回访内容：校区面谈中；|回访人：张俊旺，回访时间：2025-06-29 19:04，回访内容：谭悦老师沟通，晚上决定；|回访人：谭悦，回访时间：2025-06-29 20:56，回访内容：准备报名 ；|回访人：谭悦，回访时间：2025-06-30 14:55，回访内容：签约 | BB77: 80723875 | BC77: 否 | BD77: 26考季 | BE77: 无忧计划-候鸟 | BF77: 英语,政治,数学 | BG77: 其他 | BH77: 国内高校-211 | BI77: 是 | BL77: 报名 | BN77: 本地人本地大学(常规) | BO77: 客服
B78: 67 | C78: 北京大学部 | D78: 国内大学部 | E78: 李同学 | F78: 116621997 | G78: 杨沫 | H78: 2025-06-29 15:39:34 | I78: 知春路直访 | K78: 大三 | L78: 张俊旺 | M78: 直访 | N78: 直访 | R78: 李广地 | S78: 谭悦 | T78: 28716368 | U78: 正常工单 | V78: 2025-06-29 20:28 | W78: A（六个月内有报课意向工单） | X78: 考研无忧计划 | Y78: 大三 | Z78: 北京工业大学 | AA78: 信息学部 | AB78: 通信工程 | AC78: 李广地 | AD78: 5431884 | AE78: 谭悦 | AF78: 2025-06-30 14:55 | AG78: 谭悦 | AH78: 2025-06-30 14:56 | AI78: WYHE26007 | AJ78: 考研英语无忧计划候鸟（26考研/基础强化） | AK78: 国内考试 | AM78: 5502.55 | AP78: 新签 | AQ78: 已交接 | AR78: BJWY25030q8UPI | AS78: BJWY6311842248 | AT78: WYHE260070006 | AU78: 2025-06-30 | AW78: 回访人：张俊旺，回访时间：2025-06-29 15:49，回访内容：校区面谈中；|回访人：张俊旺，回访时间：2025-06-29 19:04，回访内容：谭悦老师沟通，晚上决定；|回访人：谭悦，回访时间：2025-06-29 20:56，回访内容：准备报名 ；|回访人：谭悦，回访时间：2025-06-30 14:55，回访内容：签约 | BB78: 80723875 | BC78: 否 | BD78: 26考季 | BE78: 无忧计划-候鸟 | BF78: 英语,政治,数学 | BG78: 其他 | BH78: 国内高校-211 | BI78: 是 | BL78: 报名 | BN78: 本地人本地大学(常规) | BO78: 客服
B79: 68 | C79: 北京大学部 | D79: 国内大学部 | E79: 李同学 | F79: 116621997 | G79: 杨沫 | H79: 2025-06-29 15:39:34 | I79: 知春路直访 | K79: 大三 | L79: 张俊旺 | M79: 直访 | N79: 直访 | R79: 李广地 | S79: 谭悦 | T79: 28716368 | U79: 正常工单 | V79: 2025-06-29 20:28 | W79: A（六个月内有报课意向工单） | X79: 考研无忧计划 | Y79: 大三 | Z79: 北京工业大学 | AA79: 信息学部 | AB79: 通信工程 | AC79: 李广地 | AD79: 5431884 | AE79: 谭悦 | AF79: 2025-06-30 14:55 | AG79: 谭悦 | AH79: 2025-06-30 14:56 | AI79: WYHP2605 | AJ79: 考研政治无忧计划候鸟（26考研/基础强化） | AK79: 国内考试 | AM79: 5502.55 | AP79: 新签 | AQ79: 已交接 | AR79: BJWY25030q8UPI | AS79: BJWY6311842248 | AT79: WYHP26050048 | AU79: 2025-06-30 | AW79: 回访人：张俊旺，回访时间：2025-06-29 15:49，回访内容：校区面谈中；|回访人：张俊旺，回访时间：2025-06-29 19:04，回访内容：谭悦老师沟通，晚上决定；|回访人：谭悦，回访时间：2025-06-29 20:56，回访内容：准备报名 ；|回访人：谭悦，回访时间：2025-06-30 14:55，回访内容：签约 | BB79: 80723875 | BC79: 否 | BD79: 26考季 | BE79: 无忧计划-候鸟 | BF79: 英语,政治,数学 | BG79: 其他 | BH79: 国内高校-211 | BI79: 是 | BL79: 报名 | BN79: 本地人本地大学(常规) | BO79: 客服
B80: 69 | C80: 北京大学部 | D80: 国内大学部 | E80: 李同学 | F80: 116621997 | G80: 杨沫 | H80: 2025-06-29 15:39:34 | I80: 知春路直访 | K80: 大三 | L80: 张俊旺 | M80: 直访 | N80: 直访 | R80: 李广地 | S80: 谭悦 | T80: 28716368 | U80: 正常工单 | V80: 2025-06-29 20:28 | W80: A（六个月内有报课意向工单） | X80: 考研无忧计划 | Y80: 大三 | Z80: 北京工业大学 | AA80: 信息学部 | AB80: 通信工程 | AC80: 李广地 | AD80: 5431884 | AE80: 谭悦 | AF80: 2025-06-30 14:55 | AG80: 谭悦 | AH80: 2025-06-30 14:56 | AI80: WYHM26002 | AJ80: 考研数学无忧计划候鸟（26考研/冲刺） | AK80: 国内考试 | AM80: 547.45 | AP80: 新签 | AQ80: 已交接 | AR80: BJWY25030q8UPI | AS80: BJWY6311842248 | AT80: WYHM260020069 | AU80: 2025-06-30 | AW80: 回访人：张俊旺，回访时间：2025-06-29 15:49，回访内容：校区面谈中；|回访人：张俊旺，回访时间：2025-06-29 19:04，回访内容：谭悦老师沟通，晚上决定；|回访人：谭悦，回访时间：2025-06-29 20:56，回访内容：准备报名 ；|回访人：谭悦，回访时间：2025-06-30 14:55，回访内容：签约 | BB80: 80723875 | BC80: 否 | BD80: 26考季 | BE80: 无忧计划-候鸟 | BF80: 英语,政治,数学 | BG80: 其他 | BH80: 国内高校-211 | BI80: 是 | BL80: 报名 | BN80: 本地人本地大学(常规) | BO80: 客服
B81: 70 | C81: 北京大学部 | D81: 国内大学部 | F81: 100254299 | H81: 2025-04-20 11:16:06 | I81: 死单激活分配赵星火 外呼主题：FY25-英学1-4月无效资源回访（1.1-4.13） | K81: 大三 | L81: 赵星火 | M81: 线上运营-本地生活平台 | N81: 知了好学 | R81: 王英帆 | S81: 谭悦 | T81: 28730425 | U81: 续费工单 | V81: 2025-06-30 20:33 | W81: A（六个月内有报课意向工单） | X81: 考研集训营 | Y81: 大四 | Z81: 北京邮电大学 | AA81: 电子工程学院 | AB81: 电子信息科学与技术 | AC81: 王英帆 | AD81: 5406395 | AE81: 谭悦 | AF81: 2025-06-30 20:34 | AG81: 谭悦 | AH81: 2025-06-30 20:34 | AI81: KYJZ25012 | AJ81: 26考研政治半年集训营（基础/七月） | AK81: 国内考试 | AM81: 3432.3 | AN81: 同科续费 | AP81: 续班 | AQ81: 已交接 | AR81: BJWY2101498uW2 | AS81: BJWY4965756550 | AT81: KYJZ250120042 | AU81: 2025-06-30 | AW81: 回访人：谭悦，回访时间：2025-06-30 20:33，回访内容：1；|回访人：谭悦，回访时间：2025-06-30 20:34，回访内容：签约 | BB81: 64203758 | BC81: 否 | BD81: 26考季 | BE81: 半年集训营 | BF81: 英语,政治,经综 | BH81: 国内高校-211 | BI81: 是 | BL81: 报名 | BN81: 外地人本地大学(常规)
B82: 71 | C82: 北京大学部 | D82: 国内大学部 | F82: 100254299 | H82: 2025-04-20 11:16:06 | I82: 死单激活分配赵星火 外呼主题：FY25-英学1-4月无效资源回访（1.1-4.13） | K82: 大三 | L82: 赵星火 | M82: 线上运营-本地生活平台 | N82: 知了好学 | R82: 王英帆 | S82: 谭悦 | T82: 28730425 | U82: 续费工单 | V82: 2025-06-30 20:33 | W82: A（六个月内有报课意向工单） | X82: 考研集训营 | Y82: 大四 | Z82: 北京邮电大学 | AA82: 电子工程学院 | AB82: 电子信息科学与技术 | AC82: 王英帆 | AD82: 5406395 | AE82: 谭悦 | AF82: 2025-06-30 20:34 | AG82: 谭悦 | AH82: 2025-06-30 20:34 | AI82: KYJY25012 | AJ82: 26考研英语半年集训营（基础/七月） | AK82: 国内考试 | AM82: 4862.15 | AN82: 同科续费 | AP82: 续班 | AQ82: 已交接 | AR82: BJWY2101498uW2 | AS82: BJWY4965756550 | AT82: KYJY250120050 | AU82: 2025-06-30 | AW82: 回访人：谭悦，回访时间：2025-06-30 20:33，回访内容：1；|回访人：谭悦，回访时间：2025-06-30 20:34，回访内容：签约 | BB82: 64203758 | BC82: 否 | BD82: 26考季 | BE82: 半年集训营 | BF82: 英语,政治,经综 | BH82: 国内高校-211 | BI82: 是 | BL82: 报名 | BN82: 外地人本地大学(常规)
B83: 72 | C83: 北京大学部 | D83: 国内大学部 | F83: 100254299 | H83: 2025-04-20 11:16:06 | I83: 死单激活分配赵星火 外呼主题：FY25-英学1-4月无效资源回访（1.1-4.13） | K83: 大三 | L83: 赵星火 | M83: 线上运营-本地生活平台 | N83: 知了好学 | R83: 王英帆 | S83: 谭悦 | T83: 28730425 | U83: 续费工单 | V83: 2025-06-30 20:33 | W83: A（六个月内有报课意向工单） | X83: 考研集训营 | Y83: 大四 | Z83: 北京邮电大学 | AA83: 电子工程学院 | AB83: 电子信息科学与技术 | AC83: 王英帆 | AD83: 5406395 | AE83: 谭悦 | AF83: 2025-06-30 20:34 | AG83: 谭悦 | AH83: 2025-06-30 20:34 | AI83: KYJJZ2501 | AJ83: 26考研经综半年集训营 | AK83: 国内考试 | AM83: 12250 | AN83: 同科续费 | AP83: 续班 | AQ83: 已交接 | AR83: BJWY2101498uW2 | AS83: BJWY4965756550 | AT83: KYJJZ25010011 | AU83: 2025-06-30 | AW83: 回访人：谭悦，回访时间：2025-06-30 20:33，回访内容：1；|回访人：谭悦，回访时间：2025-06-30 20:34，回访内容：签约 | BB83: 64203758 | BC83: 否 | BD83: 26考季 | BE83: 半年集训营 | BF83: 英语,政治,经综 | BH83: 国内高校-211 | BI83: 是 | BL83: 报名 | BN83: 外地人本地大学(常规)
B84: 73 | C84: 北京大学部 | D84: 国内大学部 | F84: 100254299 | H84: 2025-04-20 11:16:06 | I84: 死单激活分配赵星火 外呼主题：FY25-英学1-4月无效资源回访（1.1-4.13） | K84: 大三 | L84: 赵星火 | M84: 线上运营-本地生活平台 | N84: 知了好学 | R84: 王英帆 | S84: 谭悦 | T84: 28730425 | U84: 续费工单 | V84: 2025-06-30 20:33 | W84: A（六个月内有报课意向工单） | X84: 考研集训营 | Y84: 大四 | Z84: 北京邮电大学 | AA84: 电子工程学院 | AB84: 电子信息科学与技术 | AC84: 王英帆 | AD84: 5406395 | AE84: 谭悦 | AF84: 2025-06-30 20:34 | AG84: 谭悦 | AH84: 2025-06-30 20:34 | AI84: KYZ25011 | AJ84: 26考研半年集训营（住宿费/七月） | AK84: 国内考试 | AM84: 12400 | AN84: 同科续费 | AP84: 续班 | AQ84: 已交接 | AR84: BJWY2101498uW2 | AS84: BJWY4965756550 | AT84: KYZ250110048 | AU84: 2025-06-30 | AW84: 回访人：谭悦，回访时间：2025-06-30 20:33，回访内容：1；|回访人：谭悦，回访时间：2025-06-30 20:34，回访内容：签约 | BB84: 64203758 | BC84: 否 | BD84: 26考季 | BE84: 半年集训营 | BF84: 英语,政治,经综 | BH84: 国内高校-211 | BI84: 是 | BL84: 报名 | BN84: 外地人本地大学(常规)
B85: 74 | C85: 北京大学部 | D85: 国内大学部 | F85: 100254299 | H85: 2025-04-20 11:16:06 | I85: 死单激活分配赵星火 外呼主题：FY25-英学1-4月无效资源回访（1.1-4.13） | K85: 大三 | L85: 赵星火 | M85: 线上运营-本地生活平台 | N85: 知了好学 | R85: 王英帆 | S85: 谭悦 | T85: 28730425 | U85: 续费工单 | V85: 2025-06-30 20:33 | W85: A（六个月内有报课意向工单） | X85: 考研集训营 | Y85: 大四 | Z85: 北京邮电大学 | AA85: 电子工程学院 | AB85: 电子信息科学与技术 | AC85: 王英帆 | AD85: 5406395 | AE85: 谭悦 | AF85: 2025-06-30 20:34 | AG85: 谭悦 | AH85: 2025-06-30 20:34 | AI85: KYJY25013A | AJ85: 26考研英语半年集训营（强冲/英语二） | AK85: 国内考试 | AM85: 7662.95 | AN85: 同科续费 | AP85: 续班 | AQ85: 已交接 | AR85: BJWY2101498uW2 | AS85: BJWY4965756550 | AT85: KYJY25013A0061 | AU85: 2025-06-30 | AW85: 回访人：谭悦，回访时间：2025-06-30 20:33，回访内容：1；|回访人：谭悦，回访时间：2025-06-30 20:34，回访内容：签约 | BB85: 64203758 | BC85: 否 | BD85: 26考季 | BE85: 半年集训营 | BF85: 英语,政治,经综 | BH85: 国内高校-211 | BI85: 是 | BL85: 报名 | BN85: 外地人本地大学(常规)
B86: 75 | C86: 北京大学部 | D86: 国内大学部 | F86: 100254299 | H86: 2025-04-20 11:16:06 | I86: 死单激活分配赵星火 外呼主题：FY25-英学1-4月无效资源回访（1.1-4.13） | K86: 大三 | L86: 赵星火 | M86: 线上运营-本地生活平台 | N86: 知了好学 | R86: 王英帆 | S86: 谭悦 | T86: 28730425 | U86: 续费工单 | V86: 2025-06-30 20:33 | W86: A（六个月内有报课意向工单） | X86: 考研集训营 | Y86: 大四 | Z86: 北京邮电大学 | AA86: 电子工程学院 | AB86: 电子信息科学与技术 | AC86: 王英帆 | AD86: 5406395 | AE86: 谭悦 | AF86: 2025-06-30 20:34 | AG86: 谭悦 | AH86: 2025-06-30 20:34 | AI86: KYJZ25013A | AJ86: 26考研政治半年集训营（强冲） | AK86: 国内考试 | AM86: 4842.6 | AN86: 同科续费 | AP86: 续班 | AQ86: 已交接 | AR86: BJWY2101498uW2 | AS86: BJWY4965756550 | AT86: KYJZ25013A0046 | AU86: 2025-06-30 | AW86: 回访人：谭悦，回访时间：2025-06-30 20:33，回访内容：1；|回访人：谭悦，回访时间：2025-06-30 20:34，回访内容：签约 | BB86: 64203758 | BC86: 否 | BD86: 26考季 | BE86: 半年集训营 | BF86: 英语,政治,经综 | BH86: 国内高校-211 | BI86: 是 | BL86: 报名 | BN86: 外地人本地大学(常规)
B87: 76 | C87: 北京大学部 | D87: 国内大学部 | E87: 未知 | F87: 116588102 | G87: 李雪68 | H87: 2025-06-28 14:23:29 | I87: 李娜78+lina78@xdf.cn+ID+产业机构-国际教育培训事业部-国际教育北京中心-美研部-服务管理中心-班课项目 | K87: 大三 | L87: 谭悦 | M87: 转介绍 | N87: 内部员工推荐 | O87: 李娜78+lina78@xdf.cn+ID+产业机构-国际教育培训事业部-国际教育北京中心-美研部-服务管理中心-班课项目 | R87: 孙凌飞 | S87: 谭悦 | T87: 28704919 | U87: 正常工单 | V87: 2025-06-28 14:28 | W87: A（六个月内有报课意向工单） | X87: 考研无忧计划 | Y87: 大三 | Z87: 天津大学 | AA87: 生命科学学院 | AB87: 生物科学 | AC87: 孙凌飞 | AD87: 5405910 | AE87: 谭悦 | AF87: 2025-06-30 14:44 | AG87: 谭悦 | AH87: 2025-06-30 14:44 | AI87: WYHP2605 | AJ87: 考研政治无忧计划候鸟（26考研/基础强化） | AK87: 国内考试 | AM87: 10330.4 | AO87: 李娜78+lina78@xdf.cn+ID+产业机构-国际教育培训事业部-国际教育北京中心-美研部-服务管理中心-班课项目 | AP87: 新签 | AQ87: 已交接 | AR87: BJWY25030q8UPI | AS87: BJWY1285019618 | AT87: WYHP26050047 | AU87: 2025-06-30 | AW87: 回访人：谭悦，回访时间：2025-06-28 14:28，回访内容：咨询英语班课 ；|回访人：谭悦，回访时间：2025-06-29 21:17，回访内容：微信跟进中 考研学习规划 ；|回访人：谭悦，回访时间：2025-06-29 21:41，回访内容：准备报名 候鸟英政 ；|回访人：谭悦，回访时间：2025-06-30 14:44，回访内容：签约 | BB87: 30897544 | BC87: 否 | BD87: 26考季 | BE87: 无忧计划-候鸟 | BF87: 英语,政治 | BG87: 其他 | BH87: 国内高校-985 | BI87: 是 | BL87: 报名 | BN87: 外地人外地大学(常规) | BO87: 客服
B88: 77 | C88: 北京大学部 | D88: 国内大学部 | E88: 未知 | F88: 116588102 | G88: 李雪68 | H88: 2025-06-28 14:23:29 | I88: 李娜78+lina78@xdf.cn+ID+产业机构-国际教育培训事业部-国际教育北京中心-美研部-服务管理中心-班课项目 | K88: 大三 | L88: 谭悦 | M88: 转介绍 | N88: 内部员工推荐 | O88: 李娜78+lina78@xdf.cn+ID+产业机构-国际教育培训事业部-国际教育北京中心-美研部-服务管理中心-班课项目 | R88: 孙凌飞 | S88: 谭悦 | T88: 28704919 | U88: 正常工单 | V88: 2025-06-28 14:28 | W88: A（六个月内有报课意向工单） | X88: 考研无忧计划 | Y88: 大三 | Z88: 天津大学 | AA88: 生命科学学院 | AB88: 生物科学 | AC88: 孙凌飞 | AD88: 5405910 | AE88: 谭悦 | AF88: 2025-06-30 14:44 | AG88: 谭悦 | AH88: 2025-06-30 14:44 | AI88: WYHP26002 | AJ88: 考研政治无忧计划候鸟（26考研/冲刺） | AK88: 国内考试 | AM88: 1569.6 | AO88: 李娜78+lina78@xdf.cn+ID+产业机构-国际教育培训事业部-国际教育北京中心-美研部-服务管理中心-班课项目 | AP88: 新签 | AQ88: 已交接 | AR88: BJWY25030q8UPI | AS88: BJWY1285019618 | AT88: WYHP260020096 | AU88: 2025-06-30 | AW88: 回访人：谭悦，回访时间：2025-06-28 14:28，回访内容：咨询英语班课 ；|回访人：谭悦，回访时间：2025-06-29 21:17，回访内容：微信跟进中 考研学习规划 ；|回访人：谭悦，回访时间：2025-06-29 21:41，回访内容：准备报名 候鸟英政 ；|回访人：谭悦，回访时间：2025-06-30 14:44，回访内容：签约 | BB88: 30897544 | BC88: 否 | BD88: 26考季 | BE88: 无忧计划-候鸟 | BF88: 英语,政治 | BG88: 其他 | BH88: 国内高校-985 | BI88: 是 | BL88: 报名 | BN88: 外地人外地大学(常规) | BO88: 客服
B89: 78 | C89: 北京大学部 | D89: 国内大学部 | E89: 未知 | F89: 116588102 | G89: 李雪68 | H89: 2025-06-28 14:23:29 | I89: 李娜78+lina78@xdf.cn+ID+产业机构-国际教育培训事业部-国际教育北京中心-美研部-服务管理中心-班课项目 | K89: 大三 | L89: 谭悦 | M89: 转介绍 | N89: 内部员工推荐 | O89: 李娜78+lina78@xdf.cn+ID+产业机构-国际教育培训事业部-国际教育北京中心-美研部-服务管理中心-班课项目 | R89: 孙凌飞 | S89: 谭悦 | T89: 28704919 | U89: 正常工单 | V89: 2025-06-28 14:28 | W89: A（六个月内有报课意向工单） | X89: 考研无忧计划 | Y89: 大三 | Z89: 天津大学 | AA89: 生命科学学院 | AB89: 生物科学 | AC89: 孙凌飞 | AD89: 5405910 | AE89: 谭悦 | AF89: 2025-06-30 14:44 | AG89: 谭悦 | AH89: 2025-06-30 14:44 | AI89: WYHE26007 | AJ89: 考研英语无忧计划候鸟（26考研/基础强化） | AK89: 国内考试 | AM89: 10830.4 | AO89: 李娜78+lina78@xdf.cn+ID+产业机构-国际教育培训事业部-国际教育北京中心-美研部-服务管理中心-班课项目 | AP89: 新签 | AQ89: 已交接 | AR89: BJWY25030q8UPI | AS89: BJWY1285019618 | AT89: WYHE260070005 | AU89: 2025-06-30 | AW89: 回访人：谭悦，回访时间：2025-06-28 14:28，回访内容：咨询英语班课 ；|回访人：谭悦，回访时间：2025-06-29 21:17，回访内容：微信跟进中 考研学习规划 ；|回访人：谭悦，回访时间：2025-06-29 21:41，回访内容：准备报名 候鸟英政 ；|回访人：谭悦，回访时间：2025-06-30 14:44，回访内容：签约 | BB89: 30897544 | BC89: 否 | BD89: 26考季 | BE89: 无忧计划-候鸟 | BF89: 英语,政治 | BG89: 其他 | BH89: 国内高校-985 | BI89: 是 | BL89: 报名 | BN89: 外地人外地大学(常规) | BO89: 客服
B90: 79 | C90: 北京大学部 | D90: 国内大学部 | E90: 未知 | F90: 116588102 | G90: 李雪68 | H90: 2025-06-28 14:23:29 | I90: 李娜78+lina78@xdf.cn+ID+产业机构-国际教育培训事业部-国际教育北京中心-美研部-服务管理中心-班课项目 | K90: 大三 | L90: 谭悦 | M90: 转介绍 | N90: 内部员工推荐 | O90: 李娜78+lina78@xdf.cn+ID+产业机构-国际教育培训事业部-国际教育北京中心-美研部-服务管理中心-班课项目 | R90: 孙凌飞 | S90: 谭悦 | T90: 28704919 | U90: 正常工单 | V90: 2025-06-28 14:28 | W90: A（六个月内有报课意向工单） | X90: 考研无忧计划 | Y90: 大三 | Z90: 天津大学 | AA90: 生命科学学院 | AB90: 生物科学 | AC90: 孙凌飞 | AD90: 5405910 | AE90: 谭悦 | AF90: 2025-06-30 14:44 | AG90: 谭悦 | AH90: 2025-06-30 14:44 | AI90: WYHE26005 | AJ90: 考研英语无忧计划候鸟（26考研/英一冲刺） | AK90: 国内考试 | AM90: 1569.6 | AO90: 李娜78+lina78@xdf.cn+ID+产业机构-国际教育培训事业部-国际教育北京中心-美研部-服务管理中心-班课项目 | AP90: 新签 | AQ90: 已交接 | AR90: BJWY25030q8UPI | AS90: BJWY1285019618 | AT90: WYHE260050089 | AU90: 2025-06-30 | AW90: 回访人：谭悦，回访时间：2025-06-28 14:28，回访内容：咨询英语班课 ；|回访人：谭悦，回访时间：2025-06-29 21:17，回访内容：微信跟进中 考研学习规划 ；|回访人：谭悦，回访时间：2025-06-29 21:41，回访内容：准备报名 候鸟英政 ；|回访人：谭悦，回访时间：2025-06-30 14:44，回访内容：签约 | BB90: 30897544 | BC90: 否 | BD90: 26考季 | BE90: 无忧计划-候鸟 | BF90: 英语,政治 | BG90: 其他 | BH90: 国内高校-985 | BI90: 是 | BL90: 报名 | BN90: 外地人外地大学(常规) | BO90: 客服
B91: 80 | C91: 北京大学部 | D91: 国内大学部 | E91: 肖咏茜 | F91: 116647541 | G91: 赵秋侠 | H91: 2025-06-29 16:27:15 | I91: 魏公村直访 | K91: 未知 | L91: 赵星火 | M91: 直访 | N91: 直访 | R91: 肖咏茜 | S91: 赵星火 | T91: 28700257 | U91: 正常工单 | V91: 2025-06-29 18:39 | W91: A（六个月内有报课意向工单） | X91: 考研专业课,考研无忧计划 | Y91: 大二 | Z91: 首都师范大学 | AA91: 美术学院 | AB91: 美术学 | AC91: 肖咏茜 | AD91: 5430845 | AE91: 赵星火 | AF91: 2025-06-29 20:15 | AG91: 赵星火 | AH91: 2025-06-29 20:15 | AI91: WYE27029 | AJ91: 考研英语无忧计划（27考研/英一冲刺） | AK91: 国内考试 | AM91: 2141.05 | AP91: 新签 | AQ91: 已交接 | AR91: BJWY25030q8UPI | AS91: BJWY1992073878 | AT91: WYE270290007 | AU91: 2025-06-29 | AW91: 回访人：赵星火，回访时间：2025-06-29 18:39，回访内容：1；|回访人：赵星火，回访时间：2025-06-29 19:33，回访内容：预计缴费跟进学生情况中 首都师范大学美术师范大二的学生考美术，学这个专业都可以，他们是公费师范生，不允许考其他的专业。了解了北京这边的院校还有考试科目课程，介绍了27无忧计划；|回访人：赵星火，回访时间：2025-06-29 20:15，回访内容：1 | BB91: 80714734 | BC91: 否 | BD91: 27考季 | BE91: 无忧计划-啄木鸟,考研专业课300 | BF91: 英语,政治,专业课300 | BG91: 其他 | BH91: 国内高校-双一流(非985/211) | BI91: 是 | BL91: 报名 | BN91: 本地人本地大学(常规) | BO91: 客服
B92: 81 | C92: 北京大学部 | D92: 国内大学部 | E92: 肖咏茜 | F92: 116647541 | G92: 赵秋侠 | H92: 2025-06-29 16:27:15 | I92: 魏公村直访 | K92: 未知 | L92: 赵星火 | M92: 直访 | N92: 直访 | R92: 肖咏茜 | S92: 赵星火 | T92: 28700257 | U92: 正常工单 | V92: 2025-06-29 18:39 | W92: A（六个月内有报课意向工单） | X92: 考研专业课,考研无忧计划 | Y92: 大二 | Z92: 首都师范大学 | AA92: 美术学院 | AB92: 美术学 | AC92: 肖咏茜 | AD92: 5430845 | AE92: 赵星火 | AF92: 2025-06-29 20:15 | AG92: 赵星火 | AH92: 2025-06-29 20:15 | AI92: WYS25035 | AJ92: 六级无忧计划 | AK92: 国内考试 | AM92: 1982 | AP92: 新签 | AQ92: 已交接 | AR92: BJWY25030q8UPI | AS92: BJWY1992073878 | AT92: WYS250350015 | AU92: 2025-06-29 | AW92: 回访人：赵星火，回访时间：2025-06-29 18:39，回访内容：1；|回访人：赵星火，回访时间：2025-06-29 19:33，回访内容：预计缴费跟进学生情况中 首都师范大学美术师范大二的学生考美术，学这个专业都可以，他们是公费师范生，不允许考其他的专业。了解了北京这边的院校还有考试科目课程，介绍了27无忧计划；|回访人：赵星火，回访时间：2025-06-29 20:15，回访内容：1 | BB92: 80714734 | BC92: 否 | BD92: 27考季 | BE92: 无忧计划-啄木鸟,考研专业课300 | BF92: 英语,政治,专业课300 | BG92: 其他 | BH92: 国内高校-双一流(非985/211) | BI92: 是 | BL92: 报名 | BN92: 本地人本地大学(常规) | BO92: 客服
B93: 82 | C93: 北京大学部 | D93: 国内大学部 | E93: 肖咏茜 | F93: 116647541 | G93: 赵秋侠 | H93: 2025-06-29 16:27:15 | I93: 魏公村直访 | K93: 未知 | L93: 赵星火 | M93: 直访 | N93: 直访 | R93: 肖咏茜 | S93: 赵星火 | T93: 28700257 | U93: 正常工单 | V93: 2025-06-29 18:39 | W93: A（六个月内有报课意向工单） | X93: 考研专业课,考研无忧计划 | Y93: 大二 | Z93: 首都师范大学 | AA93: 美术学院 | AB93: 美术学 | AC93: 肖咏茜 | AD93: 5430845 | AE93: 赵星火 | AF93: 2025-06-29 20:15 | AG93: 赵星火 | AH93: 2025-06-29 20:15 | AI93: WYE27014 | AJ93: 考研英语无忧计划（27考研/英一强化） | AK93: 国内考试 | AM93: 2569.25 | AP93: 新签 | AQ93: 已交接 | AR93: BJWY25030q8UPI | AS93: BJWY1992073878 | AT93: WYE270140016 | AU93: 2025-06-29 | AW93: 回访人：赵星火，回访时间：2025-06-29 18:39，回访内容：1；|回访人：赵星火，回访时间：2025-06-29 19:33，回访内容：预计缴费跟进学生情况中 首都师范大学美术师范大二的学生考美术，学这个专业都可以，他们是公费师范生，不允许考其他的专业。了解了北京这边的院校还有考试科目课程，介绍了27无忧计划；|回访人：赵星火，回访时间：2025-06-29 20:15，回访内容：1 | BB93: 80714734 | BC93: 否 | BD93: 27考季 | BE93: 无忧计划-啄木鸟,考研专业课300 | BF93: 英语,政治,专业课300 | BG93: 其他 | BH93: 国内高校-双一流(非985/211) | BI93: 是 | BL93: 报名 | BN93: 本地人本地大学(常规) | BO93: 客服
B94: 83 | C94: 北京大学部 | D94: 国内大学部 | E94: 肖咏茜 | F94: 116647541 | G94: 赵秋侠 | H94: 2025-06-29 16:27:15 | I94: 魏公村直访 | K94: 未知 | L94: 赵星火 | M94: 直访 | N94: 直访 | R94: 肖咏茜 | S94: 赵星火 | T94: 28700257 | U94: 正常工单 | V94: 2025-06-29 18:39 | W94: A（六个月内有报课意向工单） | X94: 考研专业课,考研无忧计划 | Y94: 大二 | Z94: 首都师范大学 | AA94: 美术学院 | AB94: 美术学 | AC94: 肖咏茜 | AD94: 5430845 | AE94: 赵星火 | AF94: 2025-06-29 20:15 | AG94: 赵星火 | AH94: 2025-06-29 20:15 | AI94: WYP27011 | AJ94: 考研政治无忧计划（27考研/强化） | AK94: 国内考试 | AM94: 1468.15 | AP94: 新签 | AQ94: 已交接 | AR94: BJWY25030q8UPI | AS94: BJWY1992073878 | AT94: WYP270110034 | AU94: 2025-06-29 | AW94: 回访人：赵星火，回访时间：2025-06-29 18:39，回访内容：1；|回访人：赵星火，回访时间：2025-06-29 19:33，回访内容：预计缴费跟进学生情况中 首都师范大学美术师范大二的学生考美术，学这个专业都可以，他们是公费师范生，不允许考其他的专业。了解了北京这边的院校还有考试科目课程，介绍了27无忧计划；|回访人：赵星火，回访时间：2025-06-29 20:15，回访内容：1 | BB94: 80714734 | BC94: 否 | BD94: 27考季 | BE94: 无忧计划-啄木鸟,考研专业课300 | BF94: 英语,政治,专业课300 | BG94: 其他 | BH94: 国内高校-双一流(非985/211) | BI94: 是 | BL94: 报名 | BN94: 本地人本地大学(常规) | BO94: 客服
B95: 84 | C95: 北京大学部 | D95: 国内大学部 | E95: 肖咏茜 | F95: 116647541 | G95: 赵秋侠 | H95: 2025-06-29 16:27:15 | I95: 魏公村直访 | K95: 未知 | L95: 赵星火 | M95: 直访 | N95: 直访 | R95: 肖咏茜 | S95: 赵星火 | T95: 28700257 | U95: 正常工单 | V95: 2025-06-29 18:39 | W95: A（六个月内有报课意向工单） | X95: 考研专业课,考研无忧计划 | Y95: 大二 | Z95: 首都师范大学 | AA95: 美术学院 | AB95: 美术学 | AC95: 肖咏茜 | AD95: 5430845 | AE95: 赵星火 | AF95: 2025-06-29 20:15 | AG95: 赵星火 | AH95: 2025-06-29 20:15 | AI95: WYE27013 | AJ95: 考研英语无忧计划（27考研/基础） | AK95: 国内考试 | AM95: 1957.5 | AP95: 新签 | AQ95: 已交接 | AR95: BJWY25030q8UPI | AS95: BJWY1992073878 | AT95: WYE270130041 | AU95: 2025-06-29 | AW95: 回访人：赵星火，回访时间：2025-06-29 18:39，回访内容：1；|回访人：赵星火，回访时间：2025-06-29 19:33，回访内容：预计缴费跟进学生情况中 首都师范大学美术师范大二的学生考美术，学这个专业都可以，他们是公费师范生，不允许考其他的专业。了解了北京这边的院校还有考试科目课程，介绍了27无忧计划；|回访人：赵星火，回访时间：2025-06-29 20:15，回访内容：1 | BB95: 80714734 | BC95: 否 | BD95: 27考季 | BE95: 无忧计划-啄木鸟,考研专业课300 | BF95: 英语,政治,专业课300 | BG95: 其他 | BH95: 国内高校-双一流(非985/211) | BI95: 是 | BL95: 报名 | BN95: 本地人本地大学(常规) | BO95: 客服
B96: 85 | C96: 北京大学部 | D96: 国内大学部 | E96: 肖咏茜 | F96: 116647541 | G96: 赵秋侠 | H96: 2025-06-29 16:27:15 | I96: 魏公村直访 | K96: 未知 | L96: 赵星火 | M96: 直访 | N96: 直访 | R96: 肖咏茜 | S96: 赵星火 | T96: 28700257 | U96: 正常工单 | V96: 2025-06-29 18:39 | W96: A（六个月内有报课意向工单） | X96: 考研专业课,考研无忧计划 | Y96: 大二 | Z96: 首都师范大学 | AA96: 美术学院 | AB96: 美术学 | AC96: 肖咏茜 | AD96: 5430845 | AE96: 赵星火 | AF96: 2025-06-29 20:15 | AG96: 赵星火 | AH96: 2025-06-29 20:15 | AI96: WYP27012 | AJ96: 考研政治无忧计划（27考研/冲刺） | AK96: 国内考试 | AM96: 1743.4 | AP96: 新签 | AQ96: 已交接 | AR96: BJWY25030q8UPI | AS96: BJWY1992073878 | AT96: WYP270120034 | AU96: 2025-06-29 | AW96: 回访人：赵星火，回访时间：2025-06-29 18:39，回访内容：1；|回访人：赵星火，回访时间：2025-06-29 19:33，回访内容：预计缴费跟进学生情况中 首都师范大学美术师范大二的学生考美术，学这个专业都可以，他们是公费师范生，不允许考其他的专业。了解了北京这边的院校还有考试科目课程，介绍了27无忧计划；|回访人：赵星火，回访时间：2025-06-29 20:15，回访内容：1 | BB96: 80714734 | BC96: 否 | BD96: 27考季 | BE96: 无忧计划-啄木鸟,考研专业课300 | BF96: 英语,政治,专业课300 | BG96: 其他 | BH96: 国内高校-双一流(非985/211) | BI96: 是 | BL96: 报名 | BN96: 本地人本地大学(常规) | BO96: 客服
B97: 86 | C97: 北京大学部 | D97: 国内大学部 | E97: 肖咏茜 | F97: 116647541 | G97: 赵秋侠 | H97: 2025-06-29 16:27:15 | I97: 魏公村直访 | K97: 未知 | L97: 赵星火 | M97: 直访 | N97: 直访 | R97: 肖咏茜 | S97: 赵星火 | T97: 28700257 | U97: 正常工单 | V97: 2025-06-29 18:39 | W97: A（六个月内有报课意向工单） | X97: 考研专业课,考研无忧计划 | Y97: 大二 | Z97: 首都师范大学 | AA97: 美术学院 | AB97: 美术学 | AC97: 肖咏茜 | AD97: 5430845 | AE97: 赵星火 | AF97: 2025-06-29 20:15 | AG97: 赵星火 | AH97: 2025-06-29 20:15 | AI97: WYP27010 | AJ97: 考研政治无忧计划（27考研/基础） | AK97: 国内考试 | AM97: 2288.65 | AP97: 新签 | AQ97: 已交接 | AR97: BJWY25030q8UPI | AS97: BJWY1992073878 | AT97: WYP270100034 | AU97: 2025-06-29 | AW97: 回访人：赵星火，回访时间：2025-06-29 18:39，回访内容：1；|回访人：赵星火，回访时间：2025-06-29 19:33，回访内容：预计缴费跟进学生情况中 首都师范大学美术师范大二的学生考美术，学这个专业都可以，他们是公费师范生，不允许考其他的专业。了解了北京这边的院校还有考试科目课程，介绍了27无忧计划；|回访人：赵星火，回访时间：2025-06-29 20:15，回访内容：1 | BB97: 80714734 | BC97: 否 | BD97: 27考季 | BE97: 无忧计划-啄木鸟,考研专业课300 | BF97: 英语,政治,专业课300 | BG97: 其他 | BH97: 国内高校-双一流(非985/211) | BI97: 是 | BL97: 报名 | BN97: 本地人本地大学(常规) | BO97: 客服
B98: 87 | C98: 北京大学部 | D98: 国内大学部 | E98: 肖咏茜 | F98: 116647541 | G98: 赵秋侠 | H98: 2025-06-29 16:27:15 | I98: 魏公村直访 | K98: 未知 | L98: 赵星火 | M98: 直访 | N98: 直访 | R98: 肖咏茜 | S98: 赵星火 | T98: 28700257 | U98: 正常工单 | V98: 2025-06-29 18:39 | W98: A（六个月内有报课意向工单） | X98: 考研专业课,考研无忧计划 | Y98: 大二 | Z98: 首都师范大学 | AA98: 美术学院 | AB98: 美术学 | AC98: 肖咏茜 | AD98: 5430845 | AE98: 赵星火 | AF98: 2025-06-29 20:15 | AG98: 赵星火 | AH98: 2025-06-29 20:15 | AI98: LP17511988705598 | AJ98: 考研初试专业课一对一（27考研/无忧50小时） | AK98: 国内考试 | AM98: 10500 | AP98: 新签 | AQ98: 已交接 | AR98: BJWY25030q8UPI | AS98: BJWY1992073878 | AU98: 2025-06-29 | AW98: 回访人：赵星火，回访时间：2025-06-29 18:39，回访内容：1；|回访人：赵星火，回访时间：2025-06-29 19:33，回访内容：预计缴费跟进学生情况中 首都师范大学美术师范大二的学生考美术，学这个专业都可以，他们是公费师范生，不允许考其他的专业。了解了北京这边的院校还有考试科目课程，介绍了27无忧计划；|回访人：赵星火，回访时间：2025-06-29 20:15，回访内容：1 | BB98: 80714734 | BC98: 否 | BD98: 27考季 | BE98: 无忧计划-啄木鸟,考研专业课300 | BF98: 英语,政治,专业课300 | BG98: 其他 | BH98: 国内高校-双一流(非985/211) | BI98: 是 | BN98: 本地人本地大学(常规) | BO98: 客服
B99: 88 | C99: 北京大学部 | D99: 国内大学部 | E99: 未知 | F99: 116359782 | G99: 李雪68 | H99: 2025-06-26 20:06:28 | I99: 激活 | K99: 大三 | L99: 谭悦 | M99: 毛坯数据 | N99: 毛坯数据 | R99: 孙钰宸 | S99: 谭悦 | T99: 28610085 | U99: 续费工单 | V99: 2025-06-26 20:34 | W99: A（六个月内有报课意向工单） | X99: 考研专业课,考研集训营 | Y99: 大三 | Z99: 辽宁大学 | AA99: 商学院 | AB99: 会计学1 | AC99: 孙钰宸 | AD99: 5430405 | AE99: 谭悦 | AF99: 2025-06-29 17:20 | AG99: 谭悦 | AH99: 2025-06-29 21:00 | AI99: KYZ25017 | AJ99: 26考研OMO全程集训营（住宿费/英管） | AK99: 国内考试 | AM99: 6240 | AP99: 续班 | AQ99: 已交接 | AR99: BJWY25030q8UPI | AS99: BJWY6660576687 | AT99: KYZ250170020 | AU99: 2025-06-29 | AW99: 回访人：谭悦，回访时间：2025-06-26 20:34，回访内容：跟进会计专硕，暑假集训营 ；|回访人：谭悦，回访时间：2025-06-28 16:12，回访内容：微信不回复 联系不上 ；|回访人：谭悦，回访时间：2025-06-29 17:20，回访内容：准备报名 | BB99: 30886307 | BC99: 否 | BD99: 26考季 | BE99: 暑假集训营,考研专业课管综 | BF99: 英语,管综 | BG99: 其他 | BH99: 国内高校-211 | BI99: 是 | BL99: 报名 | BN99: 外地人外地大学(常规) | BO99: 客服
B100: 89 | C100: 北京大学部 | D100: 国内大学部 | E100: 未知 | F100: 116359782 | G100: 李雪68 | H100: 2025-06-26 20:06:28 | I100: 激活 | K100: 大三 | L100: 谭悦 | M100: 毛坯数据 | N100: 毛坯数据 | R100: 孙钰宸 | S100: 谭悦 | T100: 28610085 | U100: 续费工单 | V100: 2025-06-26 20:34 | W100: A（六个月内有报课意向工单） | X100: 考研专业课,考研集训营 | Y100: 大三 | Z100: 辽宁大学 | AA100: 商学院 | AB100: 会计学1 | AC100: 孙钰宸 | AD100: 5430405 | AE100: 谭悦 | AF100: 2025-06-29 17:20 | AG100: 谭悦 | AH100: 2025-06-29 21:00 | AI100: KYJY25017 | AJ100: 26考研英语OMO全程集训营（政英二联报） | AK100: 国内考试 | AM100: 14029.4 | AP100: 续班 | AQ100: 已交接 | AR100: BJWY25030q8UPI | AS100: BJWY6660576687 | AT100: KYJY250170063 | AU100: 2025-06-29 | AW100: 回访人：谭悦，回访时间：2025-06-26 20:34，回访内容：跟进会计专硕，暑假集训营 ；|回访人：谭悦，回访时间：2025-06-28 16:12，回访内容：微信不回复 联系不上 ；|回访人：谭悦，回访时间：2025-06-29 17:20，回访内容：准备报名 | BB100: 30886307 | BC100: 否 | BD100: 26考季 | BE100: 暑假集训营,考研专业课管综 | BF100: 英语,管综 | BG100: 其他 | BH100: 国内高校-211 | BI100: 是 | BL100: 报名 | BN100: 外地人外地大学(常规) | BO100: 客服
B101: 90 | C101: 北京大学部 | D101: 国内大学部 | E101: 未知 | F101: 116359782 | G101: 李雪68 | H101: 2025-06-26 20:06:28 | I101: 激活 | K101: 大三 | L101: 谭悦 | M101: 毛坯数据 | N101: 毛坯数据 | R101: 孙钰宸 | S101: 谭悦 | T101: 28610085 | U101: 续费工单 | V101: 2025-06-26 20:34 | W101: A（六个月内有报课意向工单） | X101: 考研专业课,考研集训营 | Y101: 大三 | Z101: 辽宁大学 | AA101: 商学院 | AB101: 会计学1 | AC101: 孙钰宸 | AD101: 5430405 | AE101: 谭悦 | AF101: 2025-06-29 17:20 | AG101: 谭悦 | AH101: 2025-06-29 21:00 | AI101: KYJGZ2502 | AJ101: 26考研管综OMO全程集训营 | AK101: 国内考试 | AM101: 15030.6 | AP101: 续班 | AQ101: 已交接 | AR101: BJWY25030q8UPI | AS101: BJWY6660576687 | AT101: KYJGZ25020020 | AU101: 2025-06-29 | AW101: 回访人：谭悦，回访时间：2025-06-26 20:34，回访内容：跟进会计专硕，暑假集训营 ；|回访人：谭悦，回访时间：2025-06-28 16:12，回访内容：微信不回复 联系不上 ；|回访人：谭悦，回访时间：2025-06-29 17:20，回访内容：准备报名 | BB101: 30886307 | BC101: 否 | BD101: 26考季 | BE101: 暑假集训营,考研专业课管综 | BF101: 英语,管综 | BG101: 其他 | BH101: 国内高校-211 | BI101: 是 | BL101: 报名 | BN101: 外地人外地大学(常规) | BO101: 客服
B102: 91 | C102: 北京大学部 | D102: 国内大学部 | E102: 顾安诺 | F102: 114416731 | G102: 陈晶 | H102: 2025-06-16 10:55:32 | I102: 续费原因：就差政治了，需要续费课时，我在沟通课时中；该学生为保护期内续费，原顾问：国内大学部-谭悦(tanyue9@xdf.cn) | K102: 大学已毕业 | L102: 谭悦 | M102: 转介绍 | N102: 学管续费推荐 | O102: 陈晶chenjing171@xdf.cn | R102: 顾安诺 | S102: 谭悦 | T102: 28405745 | U102: 续费工单 | V102: 2025-06-16 17:36 | W102: A（六个月内有报课意向工单） | X102: 考研VIP | Y102: 大学已毕业 | Z102: 上海理工大学 | AA102: 管理学院 | AB102: 金融学 | AC102: 顾安诺 | AD102: 5429948 | AE102: 谭悦 | AF102: 2025-06-29 14:12 | AG102: 谭悦 | AH102: 2025-06-29 14:14 | AI102: LP17511775212368 | AJ102: 考研一对一伴学班（定制/26考季） | AK102: 国内考试 | AM102: 45000 | AO102: 陈晶 | AP102: 续班 | AQ102: 已交接 | AS102: BJWY1221102855 | AU102: 2025-06-29 | AW102: 回访人：谭悦，回访时间：2025-06-21 12:45，回访内容：陈晶跟进中 ；|回访人：谭悦，回访时间：2025-06-28 15:01，回访内容：准备报名中 | BB102: 45380621 | BC102: 否 | BD102: 26考季 | BE102: VIP - 伴学 | BF102: 英语,政治 | BG102: 法硕 | BH102: 国内高校-双非 | BI102: 是 | BO102: 学管续费推荐
...

Sheet 7月绩效目标
B2: 序号 | C2: 年月 | D2: 部门 | E2: 工号 | F2: 姓名 | G2: 岗位 | H2: 考核指标1 | I2: 目标值1 | J2: 考核指标2 | K2: 目标值2 | L2: 考核指标3 | M2: 目标值3 | N2: 考核指标4 | O2: 目标值4
B3: 1 | C3: 202506 | D3: 个性化项目部 | E3: 238256 | F3: 赵星火 | G3: 学习顾问 | H3: 签约业绩（考研线上+线下净现金） | I3: 1100000 | J3: 老带新签约人头 | K3: 2 | L3: 老带新工单 | M3: 6 | N3: 转化率 | O3: 满分
B4: 3 | C4: 202506 | D4: 个性化项目部 | E4: 341422 | F4: 谭悦 | G4: 学习顾问 | H4: 签约业绩（考研线上+线下净现金） | I4: 1100000 | J4: 老带新签约人头 | K4: 2 | L4: 老带新工单 | M4: 6 | N4: 转化率 | O4: 满分
