Workbook

Sheet 汇总
B2: 业绩奖金表（一人可多条，需写清类别）
B3: 序号 | C3: 机构 | D3: 年月 | E3: 工号 | F3: 姓名 | G3: 部门 | H3: 薪资项目 | I3: 金额 | J3: 备注
B4: 1 | C4: 北京中心 | D4: 45931 | E4: 238256 | F4: 赵星火 | G4: O2级学习顾问 | H4: 月度绩效 | I4: ='10月绩效核算'!AD4 -> 600
B5: 2 | C5: 北京中心 | D5: 45932 | E5: 238256 | F5: 赵星火 | G5: O2级学习顾问 | H5: 顾问签约奖金 | I5: =业绩核算!P5 -> 48633.241
B6: 3 | C6: 北京中心 | D6: 45933 | E6: 238256 | F6: 赵星火 | G6: O2级学习顾问 | H6: 组长绩效 | I6: 2000 | J6: 新人满3月留存带教费
B7: 4 | C7: 北京中心 | D7: 45934 | E7: 341422 | F7: 谭悦 | G7: O3级学习顾问 | H7: 月度绩效 | I7: 0 | J7: O3无绩效
B8: 5 | C8: 北京中心 | D8: 45935 | E8: 341422 | F8: 谭悦 | G8: O3级学习顾问 | H8: 顾问签约奖金 | I8: =业绩核算!P4 -> 56041.305
B9: 6 | C9: 北京中心 | D9: 45936 | E9: 404905 | F9: 李涛 | G9: O1级学习顾问 | H9: 月度绩效 | I9: ='10月绩效核算'!AD5 -> 1200
B10: 7 | C10: 北京中心 | D10: 45937 | E10: 404905 | F10: 李涛 | G10: O1级学习顾问 | H10: 顾问签约奖金 | I10: =业绩核算!P6 -> 28491.419 | J10: 2025.10结束保护期
B11: 8 | C11: 北京中心 | D11: 45933 | E11: 238256 | F11: 赵星火 | G11: O2级学习顾问 | H11: 转介绍负激励 | I11: =-0.2%*(19303.2+50180) -> -138.9664 | J11: 九月老带新业绩50180十月老带新业绩19303.2
B12: 9 | C12: 北京中心 | D12: 45934 | E12: 341422 | F12: 谭悦 | G12: O3级学习顾问 | H12: 转介绍负激励 | I12: =-0.2%*(25040+17586.2) -> -85.2524 | J12: 九月老带新业绩25040十月老带新业绩17586.2

Sheet 业绩核算
B2: 2025.10个性化顾问业绩
B3: 序号 | C3: 顾问姓名 | D3: 地面目标 | E3: 网课目标 | F3: 综合目标 | G3: 四六级签约 | H3: 网课签约 | I3: 无忧签约 | J3: 集训签约 | K3: 个性化 | L3: 业绩合计 | M3: 退费合计 | N3: 综合业绩 | O3: 完成率
B4: 1 | C4: 谭悦 | D4: 650000 | E4: 20000 | F4: =D4+E4 -> 670000 | G4: =GETPIVOTDATA("学费",签约单明细!$C$2,"签约单录入人","谭悦","项目类别","四六级") -> 53661.1 | H4: =GETPIVOTDATA("学费",签约单明细!$C$2,"签约单录入人","谭悦","项目类别","网课") -> 59354.7 | I4: =GETPIVOTDATA("学费",签约单明细!$C$2,"签约单录入人","谭悦","项目类别","无忧") -> 421119.5 | J4: =GETPIVOTDATA("学费",签约单明细!$C$2,"签约单录入人","谭悦","项目类别","集训营") -> 71628.9 | K4: =GETPIVOTDATA("学费",签约单明细!$C$2,"签约单录入人","谭悦","项目类别","个性化") -> 584850 | L4: =SUM(G4:K4) -> 1190614.2 | M4: =退费明细!AO26 -> 69788.1 | N4: =L4-M4 -> 1120826.1 | O4: =N4/D4 -> 1.7243478 | P4: =N4*5% -> 56041.305
B5: 2 | C5: 赵星火 | D5: 650000 | E5: 20000 | F5: =D5+E5 -> 670000 | G5: =GETPIVOTDATA("学费",签约单明细!$C$2,"签约单录入人","赵星火","项目类别","四六级") -> 117950 | H5: =GETPIVOTDATA("学费",签约单明细!$C$2,"签约单录入人","赵星火","项目类别","网课") -> 35003.13 | I5: =GETPIVOTDATA("学费",签约单明细!$C$2,"签约单录入人","赵星火","项目类别","无忧") -> 391300 | J5: =GETPIVOTDATA("学费",签约单明细!$C$2,"签约单录入人","赵星火","项目类别","集训营") -> 103968.15 | K5: =GETPIVOTDATA("学费",签约单明细!$C$2,"签约单录入人","赵星火","项目类别","个性化")+GETPIVOTDATA("学费",签约单明细!$C$2,"签约单录入人","赵星火","项目类别","在职") -> 350544 | L5: =SUM(G5:K5) -> 998765.28 | M5: =退费明细!AO36 -> 26100.45 | N5: =L5-M5 -> 972664.83 | O5: =N5/D5 -> 1.4964074 | P5: =N5*5% -> 48633.241
B6: 3 | C6: 李涛 | D6: 325000 | E6: 20000 | F6: =D6+E6 -> 345000 | G6: =GETPIVOTDATA("学费",签约单明细!$C$2,"签约单录入人","李涛","项目类别","四六级") -> 81939 | H6: =GETPIVOTDATA("学费",签约单明细!$C$2,"签约单录入人","李涛","项目类别","网课") -> 53229.38 | I6: =GETPIVOTDATA("学费",签约单明细!$C$2,"签约单录入人","李涛","项目类别","无忧") -> 124700 | K6: =GETPIVOTDATA("学费",签约单明细!$C$2,"签约单录入人","李涛","项目类别","个性化") -> 328500 | L6: =SUM(G6:K6) -> 588368.38 | M6: =退费明细!AO5 -> 18540 | N6: =L6-M6 -> 569828.38 | O6: =N6/D6 -> 1.7533181 | P6: =N6*5% -> 28491.419
B7: 合计 | D7: =SUM(D4:D6) -> 1625000 | E7: 60000 | F7: =D7+E7 -> 1685000 | G7: =SUM(G4:G6) -> 253550.1 | H7: =SUM(H4:H6) -> 147587.21 | I7: =SUM(I4:I6) -> 937119.5 | J7: =SUM(J4:J6) -> 175597.05 | K7: =SUM(K4:K6) -> 1263894 | L7: =SUM(L4:L6) -> 2777747.9 | M7: 587442.07 | N7: =SUM(N4:N6) -> 2663319.3 | O7: =N7/D7 -> 1.6389657
E8: 签约占比 | F8: 谭悦 | G8: =G4/$L4 -> 0.045070099 | H8: =H4/$L4 -> 0.049852169 | I8: =I4/$L4 -> 0.35369938 | J8: =J4/$L4 -> 0.060161302 | K8: =K4/$L4 -> 0.49121705 | L8: =L4/$L4 -> 1
F9: 赵星火 | G9: =G5/$L5 -> 0.11809582 | H9: =H5/$L5 -> 0.035046402 | I9: =I5/$L5 -> 0.39178374 | J9: =J5/$L5 -> 0.10409668 | K9: =K5/$L5 -> 0.35097736 | L9: =L5/$L5 -> 1
F10: 李涛 | G10: =G6/$L6 -> 0.13926479 | H10: =H6/$L6 -> 0.090469478 | I10: =I6/$L6 -> 0.21194205 | J10: =J6/$L6 -> 0 | K10: =K6/$L6 -> 0.55832368 | L10: =L6/$L6 -> 1

Sheet 签约单明细
C2: 求和项:学费 | D2: 项目类别
C3: 签约单录入人 | D3: 个性化 | E3: 集训营 | F3: 四六级 | G3: 网课 | H3: 无忧 | I3: 在职 | J3: 总计
C4: 李涛 | D4: 328500 | F4: 81939 | G4: 53229.38 | H4: 124700 | J4: 588368.38
C5: 谭悦 | D5: 584850 | E5: 71628.9 | F5: 53661.1 | G5: 59354.7 | H5: 421119.5 | J5: 1190614.2
C6: 赵星火 | D6: 343800 | E6: 103968.15 | F6: 117950 | G6: 35003.13 | H6: 391300 | I6: 6744 | J6: 998765.28
C7: 总计 | D7: 1257150 | E7: 175597.05 | F7: 253550.1 | G7: 147587.21 | H7: 937119.5 | I7: 6744 | J7: 2777747.9
A10: 序号 | B10: 学校 | C10: 部门 | D10: 资源姓名 | E10: 资源ID | F10: 资源录入人 | G10: 资源录入时间 | H10: 资源描述 | I10: 市场活动 | J10: 资源年级 | K10: 分配顾问/TMK | L10: 一级获取渠道 | M10: 二级获取渠道 | N10: 转介绍人 | O10: TMK激活人 | P10: TMK激活处理时间 | Q10: 工单姓名 | R10: 跟进顾问 | S10: 工单ID | T10: 工单类型 | U10: 工单录入时间 | V10: 工单等级 | W10: 咨询课程 | X10: 工单年级 | Y10: 学校 | Z10: 院系 | AA10: 专业 | AB10: 签约学生姓名 | AC10: 签约单ID | AD10: 签约单录入人 | AE10: 签约单录入时间 | AF10: 签约单更新人 | AG10: 签约单更新时间 | AH10: 项目类别 | AI10: 班号 | AJ10: 班级名称 | AK10: 面询表类型 | AL10: 订金 | AM10: 学费 | AN10: 续费类型 | AO10: 推荐人 | AP10: 类型 | AQ10: 是否交接 | AR10: 操作人编号 | AS10: 学员号 | AT10: 听课证号 | AU10: 报班日期 | AV10: 学员状态 | AW10: 回访记录 | AX10: 新老生类型 | AY10: 退费金额 | AZ10: 退费日期 | BA10: 课程类型 | BB10: 客户ID | BC10: 是否新东方在线签约 | BD10: 考季 | BE10: 报名产品 | BF10: 报名科目 | BG10: 意向报考专业 | BH10: 学校班型/类型 | BI10: 是否关联协议 | BJ10: 特殊备注 | BK10: 产品品类 | BL10: 业务类型 | BM10: 签约列表在线学员ID | BN10: 大学生源类型 | BO10: 资源来源
A11: 157 | B11: 北京大学部 | C11: 国内大学部 | D11: 白宗翰 | E11: 131188287 | F11: 王天义 | G11: 2025-10-18 10:23:18 | H11: 续费原因：续费专业课 12h；该学生为保护期内续费，原顾问：国内大学部-谭悦(tanyue9@xdf.cn) | J11: 大四 | K11: 谭悦 | L11: 转介绍 | M11: 学管续费推荐 | N11: 王天义wangtianyi56@xdf.cn | Q11: 白宗翰 | R11: 谭悦 | S11: 30429586 | T11: 续费工单 | U11: 2025-10-18 10:38 | V11: A（六个月内有报课意向工单） | W11: 考研专业课 | X11: 大四 | Y11: 首都师范大学 | Z11: 物理系 | AA11: 物理学 | AB11: 白宗翰 | AC11: 5566241 | AD11: 谭悦 | AE11: 2025-10-18 11:40 | AF11: 谭悦 | AG11: 2025-10-18 11:43 | AH11: 个性化 | AI11: LP1760758837490 | AJ11: 985院校升级费（26考季/12小时） | AK11: 国内考试 | AM11: 1200 | AO11: 王天义 | AP11: 续班 | AQ11: 已交接 | AS11: BJWY9470173972 | AU11: 2025-10-18 | AW11: 回访人：谭悦，回访时间：2025-10-18 10:38，回访内容：1；|回访人：谭悦，回访时间：2025-10-18 10:41，回访内容：系统自动签约；|回访人：谭悦，回访时间：2025-10-18 11:39，回访内容：谭悦进行了退单操作!(本条回访记录由系统自动记录)；|回访人：谭悦，回访时间：2025-10-18 11:40，回访内容：系统自动签约 | BB11: 85872093 | BC11: 否 | BD11: 26考季 | BE11: 考研专业课150 | BF11: 专业课150 | BG11: 其他 | BH11: 国内高校-双一流(非985/211) | BI11: 是 | BN11: 本地人本地大学(常规) | BO11: 学管续费推荐
A12: 158 | B12: 北京大学部 | C12: 国内大学部 | D12: 白宗翰 | E12: 131188287 | F12: 王天义 | G12: 2025-10-18 10:23:18 | H12: 续费原因：续费专业课 12h；该学生为保护期内续费，原顾问：国内大学部-谭悦(tanyue9@xdf.cn) | J12: 大四 | K12: 谭悦 | L12: 转介绍 | M12: 学管续费推荐 | N12: 王天义wangtianyi56@xdf.cn | Q12: 白宗翰 | R12: 谭悦 | S12: 30429586 | T12: 续费工单 | U12: 2025-10-18 10:38 | V12: A（六个月内有报课意向工单） | W12: 考研专业课 | X12: 大四 | Y12: 首都师范大学 | Z12: 物理系 | AA12: 物理学 | AB12: 白宗翰 | AC12: 5566241 | AD12: 谭悦 | AE12: 2025-10-18 11:40 | AF12: 谭悦 | AG12: 2025-10-18 11:43 | AH12: 个性化 | AI12: LP1760755301231 | AJ12: 考研专业课一对一伴学班（12h/26考季） | AK12: 国内考试 | AM12: 7200 | AO12: 王天义 | AP12: 续班 | AQ12: 已交接 | AS12: BJWY9470173972 | AU12: 2025-10-18 | AW12: 回访人：谭悦，回访时间：2025-10-18 10:38，回访内容：1；|回访人：谭悦，回访时间：2025-10-18 10:41，回访内容：系统自动签约；|回访人：谭悦，回访时间：2025-10-18 11:39，回访内容：谭悦进行了退单操作!(本条回访记录由系统自动记录)；|回访人：谭悦，回访时间：2025-10-18 11:40，回访内容：系统自动签约 | BB12: 85872093 | BC12: 否 | BD12: 26考季 | BE12: 考研专业课150 | BF12: 专业课150 | BG12: 其他 | BH12: 国内高校-双一流(非985/211) | BI12: 是 | BN12: 本地人本地大学(常规) | BO12: 学管续费推荐
A13: 211 | B13: 北京大学部 | C13: 国内大学部 | D13: 天生有两个口的白羊 | E13: 130137792 | F13: 崔佳慧 | G13: 2025-10-10 19:12:28 | H13: 渠道录入来源：小红书 事件名称：私信留资 小红书账号id：659bd1020000000022000003 小红书账号名称：北京新东方考研一对一咨询 广告投放账号名称：北京新东方考研一对一咨询 活动所属学校id：108 活动所属学校名称：北京大学事业部 统一活动id：2822543 统一活动名称：北京大学事业部25年10月小红书专业号投放 渠道名称：网络营销-小红书-专业号投放 线索创建人邮箱：cuijiahui2@xdf.cn 资源跟进人邮箱：cuijiahui2@xdf.cn 备注：用户地区是【北京市北京市】，在【2025-10-10 19:10:23】留资，私信通线索标签为【留客资】，来源于【北京新东方考研一对一咨询】投放账户，意向项目是【考研/考博】，留资笔记是【】，备注【-】 | I13: 2026财年第5财月小红书 | J13: 未知 | K13: 谭悦 | L13: 线上运营-小红书 | M13: 小红书 | Q13: 白宗翰 | R13: 谭悦 | S13: 30394190 | T13: 正常工单 | U13: 2025-10-10 19:58 | V13: A（六个月内有报课意向工单） | W13: 考研VIP | X13: 大四 | Y13: 首都师范大学 | Z13: 物理系 | AA13: 物理学 | AB13: 白宗翰 | AC13: 5673871 | AD13: 谭悦 | AE13: 2025-10-11 12:57 | AF13: 谭悦 | AG13: 2025-10-11 13:03 | AH13: 个性化 | AI13: LP1760158666473 | AJ13: 考研一对一伴学班（26考季） | AK13: 国内考试 | AM13: 63200 | AP13: 新签 | AQ13: 已交接 | AS13: BJWY9470173972 | AU13: 2025-10-11 | AW13: 回访人：谭悦，回访时间：2025-10-10 19:58，回访内容：一对一辅导，首师大 今年考 ，想学数学，孩子心气高，想考985；|回访人：谭悦，回访时间：2025-10-11 12:57，回访内容：系统自动签约 | BB13: 85872093 | BC13: 否 | BD13: 26考季 | BE13: VIP - 伴学 | BF13: 英语,政治,数学 | BG13: 其他 | BH13: 国内高校-双一流(非985/211) | BI13: 是 | BN13: 本地人本地大学(常规) | BO13: 小红书
A14: 201 | B14: 北京大学部 | C14: 国内大学部 | D14: jxm | E14: 129186213 | F14: 王朝群 | G14: 2025-09-27 15:07:14 | H14: 【王朝群】咨询考研政治线下课程 | J14: 大四 | K14: 赵星火 | L14: 线上运营-小红书 | M14: 小红书KOS | Q14: 包淳鑫 | R14: 赵星火 | S14: 30259600 | T14: 正常工单 | U14: 2025-09-27 17:58 | V14: A（六个月内有报课意向工单） | W14: 考研无忧计划 | X14: 大四 | Y14: 北京化工大学 | Z14: 信息科学与技术学院 | AA14: 人工智能 | AB14: 包淳鑫 | AC14: 5648748 | AD14: 赵星火 | AE14: 2025-10-12 20:20 | AF14: 赵星火 | AG14: 2025-10-12 20:20 | AH14: 无忧 | AI14: GWYP26001 | AJ14: 考研政治无忧计划考前突破班（26考研/刷题带背） | AK14: 国内考试 | AM14: 9800 | AP14: 新签 | AQ14: 已交接 | AR14: WebReg | AS14: XDF8949218256 | AT14: GWYP260010070 | AU14: 2025-10-12 | AW14: 回访人：赵星火，回访时间：2025-10-04 22:27，回访内容：假期休息上班回访；|回访人：赵星火，回访时间：2025-10-06 16:45，回访内容：表示孩子要等孩子回京之后校区沟通下继续维护中；|回访人：赵星火，回访时间：2025-10-09 17:03，回访内容：跟进学生情况中继续维护中看下沟通中；|回访人：赵星火，回访时间：2025-10-11 18:13，回访内容：表示回京之后联系这边还没确定跟进中；|回访人：赵星火，回访时间：2025-10-12 20:20，回访内容：1 | BB14: 85516485 | BC14: 否 | BD14: 26考季 | BE14: 无忧计划-蜂鸟 | BF14: 政治 | BG14: 其他 | BH14: 国内高校-211 | BI14: 是 | BL14: 报名 | BN14: 本地人本地大学(常规) | BO14: 市场
A15: 21 | B15: 北京大学部 | C15: 国内大学部 | D15: 北京市5538 | E15: 130489672 | F15: 杨俊42(国内) | G15: 2025-10-13 12:51:26 | H15: 渠道录入来源：新东方官网M站-客服 意向城市：北京访客省/城市：北京市 访客静态ID：01000000034659033093629490515538 接待分组ID：70455 搜索引擎： 搜索词： 关键词： 设备类型：phone 访客IP：39.155.141.180 对话详细内容：AI-Lbo0rDBXCyBY 2025-10-13 12:48:59 您好同学,欢迎访问北京新东方考研四六级中心. 考研线下课程26/27考季【考研全年集训营】【考研半年集训营】【考研全科线下走读班】【考研寒/暑假集训营】【考研一对一】【考研专业课】【四/六级课程】，热门课程火热报名中,咨询即可领取专享优惠。 **【考研全年集训营】=ff761f# **【考研半年集训营】=ff6b6b# **【考研全科线下走读班】=ffc158# **【考研寒/暑假集训营】=ffc158# **【考研一对一】=ff761f# **【考研专业课】=ff6caa# **【四/六级课程】=ff6caa# **【考研冲刺班】=60e27e# AI-Lbo0rDBXCyBY 2025-10-13 12:49:02 您是想咨询【线下课程】【线上课程】【考研规划】还是【在职考研】呢？**【线下课程】# **【线上课程】#**【考研规划】#**【在职考研】# 01000000034659033093629490515538 2025-10-13 12:49:04 catti二级 AI-Lbo0rDBXCyBY 2025-10-13 12:49:08 同学，你现在是在校还是在职呢？ 01000000034659033093629490515538 2025-10-13 12:49:08 【线下课程】 01000000034659033093629490515538 2025-10-13 12:49:11 在校 AI-Lbo0rDBXCyBY 2025-10-13 12:49:11 具体是想报考什么学校和专业呢？ AI-Lbo0rDBXCyBY 2025-10-13 12:49:15 好的，我这边安排专业老师给您回电，详细沟通一下，请问您的电话是多少呢？ 01000000034659033093629490515538 2025-10-13 12:49:24 15830975316 AI-Lbo0rDBXCyBY 2025-10-13 12:49:28 好的，确认一下你的号码是否正确呢~ 01000000034659033093629490515538 2025-10-13 12:49:33 正确 AI-Lbo0rDBXCyBY 2025-10-13 12:49:37 同学怎么称呼呢？ 01000000034659033093629490515538 2025-10-13 12:49:44 韩 AI-Lbo0rDBXCyBY 2025-10-13 12:49:47 这边马上安排顾问老师联系您，预计半个小时左右给您回电请注意接听~ 来源页：https://bj.xdf.cn/ 备注： | I15: 2026财年第5财月易聊新东方官网M站 | K15: 徐树萌 | L15: 新东方官网 | M15: 新东方官网M站 | O15: 徐树萌 | P15: 2025-10-13 13:13:39 | Q15: 北京市5538 | R15: 赵星火 | S15: 30379360 | T15: 正常工单 | U15: 2025-10-13 15:34 | V15: A（六个月内有报课意向工单） | W15: 英语学习 | X15: 在职 | Y15: 北京物资学院 | Z15: 法学院 | AA15: 法学 | AB15: 北京市5538 | AC15: 5680022 | AD15: 赵星火 | AE15: 2025-10-20 20:24 | AF15: 赵星火 | AG15: 2025-10-20 20:28 | AH15: 网课 | AI15: 97809271276 | AJ15: 【26年考】CATTI二级笔译全程班 | AK15: 国内考试 | AM15: 2934.13 | AP15: 新签 | AQ15: 无须交接 | AU15: 2025-10-20 | AW15: 回访人：赵星火，回访时间：2025-10-13 15:34，回访内容：看下是考虑线下的，表示没有，然后看下这个线上介绍；|回访人：赵星火，回访时间：2025-10-16 15:02，回访内容：联系不上学生情况这边继续维我和中，看下课程考虑；|回访人：赵星火，回访时间：2025-10-19 17:31，回访内容：表示是不是有黄培辰老师，其次没有纸质版教材在就是具体价格；|回访人：赵星火，回访时间：2025-10-20 20:24，回访内容：系统自动签约 | BA15: 长期班 | BB15: 86005371 | BC15: 是 | BH15: 国内高校-双非 | BI15: 否 | BM15: 109418058 | BO15: 易聊在线咨询
A16: 122 | B16: 北京大学部 | C16: 国内大学部 | D16: 蔡哲 | E16: 131883958 | F16: 陈晶 | G16: 2025-10-22 14:30:22 | H16: 续费原因：续费课时，个性化谭悦；该学生为保护期内续费，原顾问：国内大学部-谭悦(tanyue9@xdf.cn) | J16: 大学已毕业 | K16: 谭悦 | L16: 转介绍 | M16: 学管续费推荐 | N16: 陈晶chenjing171@xdf.cn | Q16: 蔡哲 | R16: 谭悦 | S16: 30538237 | T16: 续费工单 | U16: 2025-10-22 15:16 | V16: A（六个月内有报课意向工单） | W16: 考研VIP | X16: 大学已毕业 | Y16: 北京邮电大学 | Z16: 信息与通信工程学院 | AA16: 电子信息工程 | AB16: 蔡哲 | AC16: 5567368 | AD16: 谭悦 | AE16: 2025-10-22 15:59 | AF16: 谭悦 | AG16: 2025-10-22 16:55 | AH16: 个性化 | AI16: LP17611199461015 | AJ16: 考研一对一伴学班（26考季） | AK16: 国内考试 | AM16: 29900 | AO16: 陈晶 | AP16: 续班 | AQ16: 已交接 | AS16: BJWY0874092650 | AU16: 2025-10-22 | AW16: 回访人：谭悦，回访时间：2025-10-22 15:16，回访内容：跟进一对一 ；|回访人：谭悦，回访时间：2025-10-22 15:59，回访内容：系统自动签约 | BB16: 33569231 | BC16: 否 | BD16: 26考季 | BE16: VIP - 伴学 | BF16: 英语,数学 | BG16: 其他 | BH16: 国内高校-211 | BI16: 是 | BO16: 学管续费推荐
A17: 129 | B17: 北京大学部 | C17: 国内大学部 | E17: 125413803 | G17: 2025-08-29 10:27:41 | H17: 续费原因：学生咨询续费一对一价格，老师建议续费 20h；该学生为保护期内续费，原顾问：国内大学部-赵星火(zhaoxinghuo@xdf.cn) | J17: 大学已毕业 | K17: 赵星火 | L17: 转介绍 | M17: 学管续费推荐 | Q17: 曹泽恒 | R17: 赵星火 | S17: 30470659 | T17: 续费工单 | U17: 2025-10-19 18:09 | V17: A（六个月内有报课意向工单） | W17: 考研VIP | X17: 大学已毕业 | Y17: 北京工业大学 | Z17: 城市建设学部 | AA17: 土木工程 | AB17: 曹泽恒 | AC17: 5679654 | AD17: 赵星火 | AE17: 2025-10-20 09:53 | AF17: 赵星火 | AG17: 2025-10-20 11:12 | AH17: 集训营 | AI17: LP176092519905 | AJ17: 26考研一对一伴学（集训） | AK17: 国内考试 | AM17: 16000 | AP17: 续班 | AQ17: 已交接 | AS17: BJWY4116308585 | AU17: 2025-10-20 | AW17: 回访人：赵星火，回访时间：2025-10-19 18:09，回访内容：1；|回访人：赵星火，回访时间：2025-10-20 09:53，回访内容：系统自动签约 | BB17: 33140368 | BC17: 否 | BD17: 26考季 | BE17: VIP - 伴学 | BF17: 英语 | BH17: 国内高校-211 | BI17: 是
A18: 42 | B18: 北京大学部 | C18: 国内大学部 | D18: 家长 | E18: 129593843 | F18: 吕猛 | G18: 2025-10-02 13:08:01 | H18: 咨询英语一对一，尽快联系 | J18: 大四 | K18: 谭悦 | L18: 线上运营-本地生活平台 | M18: 阿里本地通 | Q18: 曾行健 | R18: 谭悦 | S18: 30336781 | T18: 续费工单 | U18: 2025-10-02 14:36 | V18: A（六个月内有报课意向工单） | W18: 考研VIP | X18: 大四 | Y18: 大连海事大学 | Z18: 法学院 | AA18: 法学（海商法） | AB18: 曾行健 | AC18: 5570137 | AD18: 谭悦 | AE18: 2025-10-30 16:17 | AF18: 谭悦 | AG18: 2025-10-30 16:18 | AH18: 个性化 | AI18: LP175954480098 | AJ18: 考研一对一伴学班（定制/26考季） | AK18: 国内考试 | AM18: 0 | AP18: 新签 | AQ18: 无须交接 | AS18: BJWY3312305782 | AU18: 2025-10-04 | AW18: 回访人：谭悦，回访时间：2025-10-02 14:36，回访内容：加微信，建群，跟进中一对一英语 ；|回访人：谭悦，回访时间：2025-10-19 15:05，回访内容：谭悦进行了退单操作!(本条回访记录由系统自动记录)；|回访人：谭悦，回访时间：2025-10-19 16:39，回访内容：学生退费了， 看看考试成绩吧，跟进二战 ；|回访人：谭悦，回访时间：2025-10-26 13:55，回访内容：跟进集训营，还没回复 ；|回访人：谭悦，回访时间：2025-10-30 16:17，回访内容：1 | BB18: 85687580 | BC18: 否 | BD18: 26考季 | BE18: VIP - 伴学 | BF18: 英语,政治 | BG18: 其他 | BH18: 国内高校-211 | BI18: 否 | BN18: 外地人外地大学(常规) | BO18: 客服
A19: 53 | B19: 北京大学部 | C19: 国内大学部 | E19: 132605684 | G19: 2025-10-28 20:22:28 | H19: 【小红书资源】 咨询考研一对一，IP地址在北京 | J19: 大三 | K19: 李涛 | L19: 线上运营-小红书 | M19: 小红书 | Q19: 陈靓怡 | R19: 李涛 | S19: 30642337 | T19: 续费工单 | U19: 2025-10-31 20:48 | V19: A（六个月内有报课意向工单） | W19: 考研VIP | X19: 大三 | Y19: 北京信息科技大学 | Z19: 计算机学院 | AA19: 计算机科学与技术 | AB19: 陈靓怡 | AC19: 5663041 | AD19: 李涛 | AE19: 2025-10-31 20:51 | AF19: 李涛 | AG19: 2025-10-31 21:44 | AH19: 无忧 | AI19: WYE27047 | AJ19: 考研英语无忧计划（27考研/英一冲刺） | AK19: 国内考试 | AM19: 5137.6 | AP19: 新签 | AQ19: 已交接 | AR19: BJWY22035556hl | AS19: BJWY7173848231 | AT19: WYE270470043 | AU19: 2025-10-31 | AW19: 回访人：李涛，回访时间：2025-10-31 20:48，回访内容：续费；|回访人：李涛，回访时间：2025-10-31 20:51，回访内容：系统自动签约 | BB19: 86751591 | BC19: 否 | BD19: 27考季 | BE19: VIP - 伴学 | BF19: 英语,政治,数学,计算机 | BH19: 国内高校-双非 | BI19: 是 | BL19: 报名 | BN19: 本地人本地大学(常规)
A20: 54 | B20: 北京大学部 | C20: 国内大学部 | E20: 132605684 | G20: 2025-10-28 20:22:28 | H20: 【小红书资源】 咨询考研一对一，IP地址在北京 | J20: 大三 | K20: 李涛 | L20: 线上运营-小红书 | M20: 小红书 | Q20: 陈靓怡 | R20: 李涛 | S20: 30642337 | T20: 续费工单 | U20: 2025-10-31 20:48 | V20: A（六个月内有报课意向工单） | W20: 考研VIP | X20: 大三 | Y20: 北京信息科技大学 | Z20: 计算机学院 | AA20: 计算机科学与技术 | AB20: 陈靓怡 | AC20: 5663041 | AD20: 李涛 | AE20: 2025-10-31 20:51 | AF20: 李涛 | AG20: 2025-10-31 21:44 | AH20: 无忧 | AI20: WYP27034 | AJ20: 考研政治无忧计划（27考研/基础） | AK20: 国内考试 | AM20: 6092.2 | AP20: 新签 | AQ20: 已交接 | AR20: BJWY22035556hl | AS20: BJWY7173848231 | AT20: WYP270340039 | AU20: 2025-10-31 | AW20: 回访人：李涛，回访时间：2025-10-31 20:48，回访内容：续费；|回访人：李涛，回访时间：2025-10-31 20:51，回访内容：系统自动签约 | BB20: 86751591 | BC20: 否 | BD20: 27考季 | BE20: VIP - 伴学 | BF20: 英语,政治,数学,计算机 | BH20: 国内高校-双非 | BI20: 是 | BL20: 报名 | BN20: 本地人本地大学(常规)
A21: 55 | B21: 北京大学部 | C21: 国内大学部 | E21: 132605684 | G21: 2025-10-28 20:22:28 | H21: 【小红书资源】 咨询考研一对一，IP地址在北京 | J21: 大三 | K21: 李涛 | L21: 线上运营-小红书 | M21: 小红书 | Q21: 陈靓怡 | R21: 李涛 | S21: 30642337 | T21: 续费工单 | U21: 2025-10-31 20:48 | V21: A（六个月内有报课意向工单） | W21: 考研VIP | X21: 大三 | Y21: 北京信息科技大学 | Z21: 计算机学院 | AA21: 计算机科学与技术 | AB21: 陈靓怡 | AC21: 5663041 | AD21: 李涛 | AE21: 2025-10-31 20:51 | AF21: 李涛 | AG21: 2025-10-31 21:44 | AH21: 无忧 | AI21: WYP27036 | AJ21: 考研政治无忧计划（27考研/冲刺） | AK21: 国内考试 | AM21: 4183.8 | AP21: 新签 | AQ21: 已交接 | AR21: BJWY22035556hl | AS21: BJWY7173848231 | AT21: WYP270360039 | AU21: 2025-10-31 | AW21: 回访人：李涛，回访时间：2025-10-31 20:48，回访内容：续费；|回访人：李涛，回访时间：2025-10-31 20:51，回访内容：系统自动签约 | BB21: 86751591 | BC21: 否 | BD21: 27考季 | BE21: VIP - 伴学 | BF21: 英语,政治,数学,计算机 | BH21: 国内高校-双非 | BI21: 是 | BL21: 报名 | BN21: 本地人本地大学(常规)
A22: 56 | B22: 北京大学部 | C22: 国内大学部 | E22: 132605684 | G22: 2025-10-28 20:22:28 | H22: 【小红书资源】 咨询考研一对一，IP地址在北京 | J22: 大三 | K22: 李涛 | L22: 线上运营-小红书 | M22: 小红书 | Q22: 陈靓怡 | R22: 李涛 | S22: 30642337 | T22: 续费工单 | U22: 2025-10-31 20:48 | V22: A（六个月内有报课意向工单） | W22: 考研VIP | X22: 大三 | Y22: 北京信息科技大学 | Z22: 计算机学院 | AA22: 计算机科学与技术 | AB22: 陈靓怡 | AC22: 5663041 | AD22: 李涛 | AE22: 2025-10-31 20:51 | AF22: 李涛 | AG22: 2025-10-31 21:44 | AH22: 无忧 | AI22: WYP27035 | AJ22: 考研政治无忧计划（27考研/强化） | AK22: 国内考试 | AM22: 3523.2 | AP22: 新签 | AQ22: 已交接 | AR22: BJWY22035556hl | AS22: BJWY7173848231 | AT22: WYP270350039 | AU22: 2025-10-31 | AW22: 回访人：李涛，回访时间：2025-10-31 20:48，回访内容：续费；|回访人：李涛，回访时间：2025-10-31 20:51，回访内容：系统自动签约 | BB22: 86751591 | BC22: 否 | BD22: 27考季 | BE22: VIP - 伴学 | BF22: 英语,政治,数学,计算机 | BH22: 国内高校-双非 | BI22: 是 | BL22: 报名 | BN22: 本地人本地大学(常规)
A23: 57 | B23: 北京大学部 | C23: 国内大学部 | E23: 132605684 | G23: 2025-10-28 20:22:28 | H23: 【小红书资源】 咨询考研一对一，IP地址在北京 | J23: 大三 | K23: 李涛 | L23: 线上运营-小红书 | M23: 小红书 | Q23: 陈靓怡 | R23: 李涛 | S23: 30642337 | T23: 续费工单 | U23: 2025-10-31 20:48 | V23: A（六个月内有报课意向工单） | W23: 考研VIP | X23: 大三 | Y23: 北京信息科技大学 | Z23: 计算机学院 | AA23: 计算机科学与技术 | AB23: 陈靓怡 | AC23: 5663041 | AD23: 李涛 | AE23: 2025-10-31 20:51 | AF23: 李涛 | AG23: 2025-10-31 21:44 | AH23: 无忧 | AI23: WYE27046 | AJ23: 考研英语无忧计划（27考研/英一强化） | AK23: 国内考试 | AM23: 6165.6 | AP23: 新签 | AQ23: 已交接 | AR23: BJWY22035556hl | AS23: BJWY7173848231 | AT23: WYE270460043 | AU23: 2025-10-31 | AW23: 回访人：李涛，回访时间：2025-10-31 20:48，回访内容：续费；|回访人：李涛，回访时间：2025-10-31 20:51，回访内容：系统自动签约 | BB23: 86751591 | BC23: 否 | BD23: 27考季 | BE23: VIP - 伴学 | BF23: 英语,政治,数学,计算机 | BH23: 国内高校-双非 | BI23: 是 | BL23: 报名 | BN23: 本地人本地大学(常规)
A24: 58 | B24: 北京大学部 | C24: 国内大学部 | E24: 132605684 | G24: 2025-10-28 20:22:28 | H24: 【小红书资源】 咨询考研一对一，IP地址在北京 | J24: 大三 | K24: 李涛 | L24: 线上运营-小红书 | M24: 小红书 | Q24: 陈靓怡 | R24: 李涛 | S24: 30642337 | T24: 续费工单 | U24: 2025-10-31 20:48 | V24: A（六个月内有报课意向工单） | W24: 考研VIP | X24: 大三 | Y24: 北京信息科技大学 | Z24: 计算机学院 | AA24: 计算机科学与技术 | AB24: 陈靓怡 | AC24: 5663041 | AD24: 李涛 | AE24: 2025-10-31 20:51 | AF24: 李涛 | AG24: 2025-10-31 21:44 | AH24: 无忧 | AI24: WYE27048 | AJ24: 考研英语无忧计划（27考研/基础） | AK24: 国内考试 | AM24: 4697.6 | AP24: 新签 | AQ24: 已交接 | AR24: BJWY22035556hl | AS24: BJWY7173848231 | AT24: WYE270480013 | AU24: 2025-10-31 | AW24: 回访人：李涛，回访时间：2025-10-31 20:48，回访内容：续费；|回访人：李涛，回访时间：2025-10-31 20:51，回访内容：系统自动签约 | BB24: 86751591 | BC24: 否 | BD24: 27考季 | BE24: VIP - 伴学 | BF24: 英语,政治,数学,计算机 | BH24: 国内高校-双非 | BI24: 是 | BL24: 报名 | BN24: 本地人本地大学(常规)
A25: 59 | B25: 北京大学部 | C25: 国内大学部 | E25: 132605684 | G25: 2025-10-28 20:22:28 | H25: 【小红书资源】 咨询考研一对一，IP地址在北京 | J25: 大三 | K25: 李涛 | L25: 线上运营-小红书 | M25: 小红书 | Q25: 陈靓怡 | R25: 李涛 | S25: 30642337 | T25: 续费工单 | U25: 2025-10-31 20:48 | V25: A（六个月内有报课意向工单） | W25: 考研VIP | X25: 大三 | Y25: 北京信息科技大学 | Z25: 计算机学院 | AA25: 计算机科学与技术 | AB25: 陈靓怡 | AC25: 5663041 | AD25: 李涛 | AE25: 2025-10-31 20:51 | AF25: 李涛 | AG25: 2025-10-31 21:44 | AH25: 四六级 | AI25: WYF25046 | AJ25: 四级无忧冲刺 | AK25: 国内考试 | AM25: 3180 | AP25: 新签 | AQ25: 已交接 | AR25: BJWY2201F8pC6h | AS25: BJWY7173848231 | AT25: WYF250460015 | AU25: 2025-10-31 | AW25: 回访人：李涛，回访时间：2025-10-31 20:48，回访内容：续费；|回访人：李涛，回访时间：2025-10-31 20:51，回访内容：系统自动签约 | BB25: 86751591 | BC25: 否 | BD25: 27考季 | BE25: VIP - 伴学 | BF25: 英语,政治,数学,计算机 | BH25: 国内高校-双非 | BI25: 是 | BL25: 报名 | BN25: 本地人本地大学(常规)
A26: 60 | B26: 北京大学部 | C26: 国内大学部 | E26: 132605684 | G26: 2025-10-28 20:22:28 | H26: 【小红书资源】 咨询考研一对一，IP地址在北京 | J26: 大三 | K26: 李涛 | L26: 线上运营-小红书 | M26: 小红书 | Q26: 陈靓怡 | R26: 李涛 | S26: 30642337 | T26: 续费工单 | U26: 2025-10-31 20:48 | V26: A（六个月内有报课意向工单） | W26: 考研VIP | X26: 大三 | Y26: 北京信息科技大学 | Z26: 计算机学院 | AA26: 计算机科学与技术 | AB26: 陈靓怡 | AC26: 5663041 | AD26: 李涛 | AE26: 2025-10-31 20:51 | AF26: 李涛 | AG26: 2025-10-31 21:44 | AH26: 无忧 | AI26: LP17619151162350 | AJ26: 27考研一对一伴学(无忧) | AK26: 国内考试 | AM26: 80000 | AP26: 新签 | AQ26: 已交接 | AR26: BJWY22035556hl | AS26: BJWY7173848231 | AU26: 2025-10-31 | AW26: 回访人：李涛，回访时间：2025-10-31 20:48，回访内容：续费；|回访人：李涛，回访时间：2025-10-31 20:51，回访内容：系统自动签约 | BB26: 86751591 | BC26: 否 | BD26: 27考季 | BE26: VIP - 伴学 | BF26: 英语,政治,数学,计算机 | BH26: 国内高校-双非 | BI26: 是 | BN26: 本地人本地大学(常规)
A27: 104 | B27: 北京大学部 | C27: 国内大学部 | D27: 许昌苦瓜 | E27: 129687286 | F27: 张亚男 | G27: 2025-10-04 11:26:07 | H27: 渠道录入来源：集团百度投放-基木鱼 账户名：baidu-大学-总部-A22KA00038 线索ID：251004481825693103 线索时间：2025-10-04 11:25:47 页面名称：新东方考研集训营 姓名：许昌苦瓜 城市：北京 IP：2408:8207:7824:a5d0:718f:6e6c:26a9:cc7b 来源页：https://aisite.wejianzhan.com/site/wjzswa2z/a8dbbce4-c4ec-438e-922c-14344008843f?utm_source=jituan_searchengine_douyin__M_douyin_PP&utm_medium=CPD&utm_campaign=jituanpinzhuanjuheye&utm_term=daxuekaoshi_banwei_1&wid=a842d1130c6e4394afaede8ccb14d579_0_0 | I27: 2026财年第5财月集团百度投放-基木鱼 | K27: 谭悦 | L27: 线上运营-投放 | M27: 集团-抖音品专 | Q27: 陈立峰 | R27: 谭悦 | S27: 30355465 | T27: 正常工单 | U27: 2025-10-19 18:27 | V27: A（六个月内有报课意向工单） | W27: 考研专业课,考研无忧计划 | X27: 大三 | Y27: 北京工业大学 | Z27: 信息学部 | AA27: 通信工程 | AB27: 陈立峰 | AC27: 5681454 | AD27: 谭悦 | AE27: 2025-10-23 10:54 | AF27: 谭悦 | AG27: 2025-10-23 10:55 | AH27: 无忧 | AI27: WYE27101 | AJ27: 考研英语无忧计划啄木鸟（27考研/基础） | AK27: 国内考试 | AM27: 5300 | AP27: 新签 | AQ27: 已交接 | AR27: BJWY2201F8pC6h | AS27: BJWY5487120372 | AT27: WYE271010007 | AU27: 2025-10-23 | AW27: 回访人：谭悦，回访时间：2025-10-17 18:42，回访内容：长期不回我消息 ；|回访人：陈伟钰，回访时间：2025-10-19 18:27，回访内容：陈伟钰恢复工单, 系统自动生成回访记录!；|回访人：谭悦，回访时间：2025-10-19 18:43，回访内容：面谈过了， 跟进中，走读班 ；|回访人：谭悦，回访时间：2025-10-22 18:03，回访内容：已出订单；|回访人：谭悦，回访时间：2025-10-23 10:54，回访内容：1 | BB27: 43431314 | BC27: 否 | BD27: 27考季 | BE27: 考研专业课150,无忧计划-啄木鸟 | BF27: 专业课150,英语,政治,数学 | BG27: 其他 | BH27: 国内高校-211 | BI27: 是 | BL27: 报名 | BN27: 本地人本地大学(常规) | BO27: 集团百度投放-基木鱼
A28: 105 | B28: 北京大学部 | C28: 国内大学部 | D28: 许昌苦瓜 | E28: 129687286 | F28: 张亚男 | G28: 2025-10-04 11:26:07 | H28: 渠道录入来源：集团百度投放-基木鱼 账户名：baidu-大学-总部-A22KA00038 线索ID：251004481825693103 线索时间：2025-10-04 11:25:47 页面名称：新东方考研集训营 姓名：许昌苦瓜 城市：北京 IP：2408:8207:7824:a5d0:718f:6e6c:26a9:cc7b 来源页：https://aisite.wejianzhan.com/site/wjzswa2z/a8dbbce4-c4ec-438e-922c-14344008843f?utm_source=jituan_searchengine_douyin__M_douyin_PP&utm_medium=CPD&utm_campaign=jituanpinzhuanjuheye&utm_term=daxuekaoshi_banwei_1&wid=a842d1130c6e4394afaede8ccb14d579_0_0 | I28: 2026财年第5财月集团百度投放-基木鱼 | K28: 谭悦 | L28: 线上运营-投放 | M28: 集团-抖音品专 | Q28: 陈立峰 | R28: 谭悦 | S28: 30355465 | T28: 正常工单 | U28: 2025-10-19 18:27 | V28: A（六个月内有报课意向工单） | W28: 考研专业课,考研无忧计划 | X28: 大三 | Y28: 北京工业大学 | Z28: 信息学部 | AA28: 通信工程 | AB28: 陈立峰 | AC28: 5681454 | AD28: 谭悦 | AE28: 2025-10-23 10:54 | AF28: 谭悦 | AG28: 2025-10-23 10:55 | AH28: 无忧 | AI28: WYM27101 | AJ28: 考研数学无忧计划啄木鸟（27考研/基础） | AK28: 国内考试 | AM28: 4300 | AP28: 新签 | AQ28: 已交接 | AR28: BJWY2201F8pC6h | AS28: BJWY5487120372 | AT28: WYM271010002 | AU28: 2025-10-23 | AW28: 回访人：谭悦，回访时间：2025-10-17 18:42，回访内容：长期不回我消息 ；|回访人：陈伟钰，回访时间：2025-10-19 18:27，回访内容：陈伟钰恢复工单, 系统自动生成回访记录!；|回访人：谭悦，回访时间：2025-10-19 18:43，回访内容：面谈过了， 跟进中，走读班 ；|回访人：谭悦，回访时间：2025-10-22 18:03，回访内容：已出订单；|回访人：谭悦，回访时间：2025-10-23 10:54，回访内容：1 | BB28: 43431314 | BC28: 否 | BD28: 27考季 | BE28: 考研专业课150,无忧计划-啄木鸟 | BF28: 专业课150,英语,政治,数学 | BG28: 其他 | BH28: 国内高校-211 | BI28: 是 | BL28: 报名 | BN28: 本地人本地大学(常规) | BO28: 集团百度投放-基木鱼
A29: 106 | B29: 北京大学部 | C29: 国内大学部 | D29: 许昌苦瓜 | E29: 129687286 | F29: 张亚男 | G29: 2025-10-04 11:26:07 | H29: 渠道录入来源：集团百度投放-基木鱼 账户名：baidu-大学-总部-A22KA00038 线索ID：251004481825693103 线索时间：2025-10-04 11:25:47 页面名称：新东方考研集训营 姓名：许昌苦瓜 城市：北京 IP：2408:8207:7824:a5d0:718f:6e6c:26a9:cc7b 来源页：https://aisite.wejianzhan.com/site/wjzswa2z/a8dbbce4-c4ec-438e-922c-14344008843f?utm_source=jituan_searchengine_douyin__M_douyin_PP&utm_medium=CPD&utm_campaign=jituanpinzhuanjuheye&utm_term=daxuekaoshi_banwei_1&wid=a842d1130c6e4394afaede8ccb14d579_0_0 | I29: 2026财年第5财月集团百度投放-基木鱼 | K29: 谭悦 | L29: 线上运营-投放 | M29: 集团-抖音品专 | Q29: 陈立峰 | R29: 谭悦 | S29: 30355465 | T29: 正常工单 | U29: 2025-10-19 18:27 | V29: A（六个月内有报课意向工单） | W29: 考研专业课,考研无忧计划 | X29: 大三 | Y29: 北京工业大学 | Z29: 信息学部 | AA29: 通信工程 | AB29: 陈立峰 | AC29: 5681454 | AD29: 谭悦 | AE29: 2025-10-23 10:54 | AF29: 谭悦 | AG29: 2025-10-23 10:55 | AH29: 无忧 | AI29: WYM27103 | AJ29: 考研数学无忧计划啄木鸟（27考研/冲刺） | AK29: 国内考试 | AM29: 3900 | AP29: 新签 | AQ29: 已交接 | AR29: BJWY2201F8pC6h | AS29: BJWY5487120372 | AT29: WYM271030002 | AU29: 2025-10-23 | AW29: 回访人：谭悦，回访时间：2025-10-17 18:42，回访内容：长期不回我消息 ；|回访人：陈伟钰，回访时间：2025-10-19 18:27，回访内容：陈伟钰恢复工单, 系统自动生成回访记录!；|回访人：谭悦，回访时间：2025-10-19 18:43，回访内容：面谈过了， 跟进中，走读班 ；|回访人：谭悦，回访时间：2025-10-22 18:03，回访内容：已出订单；|回访人：谭悦，回访时间：2025-10-23 10:54，回访内容：1 | BB29: 43431314 | BC29: 否 | BD29: 27考季 | BE29: 考研专业课150,无忧计划-啄木鸟 | BF29: 专业课150,英语,政治,数学 | BG29: 其他 | BH29: 国内高校-211 | BI29: 是 | BL29: 报名 | BN29: 本地人本地大学(常规) | BO29: 集团百度投放-基木鱼
A30: 107 | B30: 北京大学部 | C30: 国内大学部 | D30: 许昌苦瓜 | E30: 129687286 | F30: 张亚男 | G30: 2025-10-04 11:26:07 | H30: 渠道录入来源：集团百度投放-基木鱼 账户名：baidu-大学-总部-A22KA00038 线索ID：251004481825693103 线索时间：2025-10-04 11:25:47 页面名称：新东方考研集训营 姓名：许昌苦瓜 城市：北京 IP：2408:8207:7824:a5d0:718f:6e6c:26a9:cc7b 来源页：https://aisite.wejianzhan.com/site/wjzswa2z/a8dbbce4-c4ec-438e-922c-14344008843f?utm_source=jituan_searchengine_douyin__M_douyin_PP&utm_medium=CPD&utm_campaign=jituanpinzhuanjuheye&utm_term=daxuekaoshi_banwei_1&wid=a842d1130c6e4394afaede8ccb14d579_0_0 | I30: 2026财年第5财月集团百度投放-基木鱼 | K30: 谭悦 | L30: 线上运营-投放 | M30: 集团-抖音品专 | Q30: 陈立峰 | R30: 谭悦 | S30: 30355465 | T30: 正常工单 | U30: 2025-10-19 18:27 | V30: A（六个月内有报课意向工单） | W30: 考研专业课,考研无忧计划 | X30: 大三 | Y30: 北京工业大学 | Z30: 信息学部 | AA30: 通信工程 | AB30: 陈立峰 | AC30: 5681454 | AD30: 谭悦 | AE30: 2025-10-23 10:54 | AF30: 谭悦 | AG30: 2025-10-23 10:55 | AH30: 无忧 | AI30: WYE27105 | AJ30: 考研英语无忧计划啄木鸟（27考研/英二强化） | AK30: 国内考试 | AM30: 6600 | AP30: 新签 | AQ30: 已交接 | AR30: BJWY2201F8pC6h | AS30: BJWY5487120372 | AT30: WYE271050003 | AU30: 2025-10-23 | AW30: 回访人：谭悦，回访时间：2025-10-17 18:42，回访内容：长期不回我消息 ；|回访人：陈伟钰，回访时间：2025-10-19 18:27，回访内容：陈伟钰恢复工单, 系统自动生成回访记录!；|回访人：谭悦，回访时间：2025-10-19 18:43，回访内容：面谈过了， 跟进中，走读班 ；|回访人：谭悦，回访时间：2025-10-22 18:03，回访内容：已出订单；|回访人：谭悦，回访时间：2025-10-23 10:54，回访内容：1 | BB30: 43431314 | BC30: 否 | BD30: 27考季 | BE30: 考研专业课150,无忧计划-啄木鸟 | BF30: 专业课150,英语,政治,数学 | BG30: 其他 | BH30: 国内高校-211 | BI30: 是 | BL30: 报名 | BN30: 本地人本地大学(常规) | BO30: 集团百度投放-基木鱼
A31: 108 | B31: 北京大学部 | C31: 国内大学部 | D31: 许昌苦瓜 | E31: 129687286 | F31: 张亚男 | G31: 2025-10-04 11:26:07 | H31: 渠道录入来源：集团百度投放-基木鱼 账户名：baidu-大学-总部-A22KA00038 线索ID：251004481825693103 线索时间：2025-10-04 11:25:47 页面名称：新东方考研集训营 姓名：许昌苦瓜 城市：北京 IP：2408:8207:7824:a5d0:718f:6e6c:26a9:cc7b 来源页：https://aisite.wejianzhan.com/site/wjzswa2z/a8dbbce4-c4ec-438e-922c-14344008843f?utm_source=jituan_searchengine_douyin__M_douyin_PP&utm_medium=CPD&utm_campaign=jituanpinzhuanjuheye&utm_term=daxuekaoshi_banwei_1&wid=a842d1130c6e4394afaede8ccb14d579_0_0 | I31: 2026财年第5财月集团百度投放-基木鱼 | K31: 谭悦 | L31: 线上运营-投放 | M31: 集团-抖音品专 | Q31: 陈立峰 | R31: 谭悦 | S31: 30355465 | T31: 正常工单 | U31: 2025-10-19 18:27 | V31: A（六个月内有报课意向工单） | W31: 考研专业课,考研无忧计划 | X31: 大三 | Y31: 北京工业大学 | Z31: 信息学部 | AA31: 通信工程 | AB31: 陈立峰 | AC31: 5681454 | AD31: 谭悦 | AE31: 2025-10-23 10:54 | AF31: 谭悦 | AG31: 2025-10-23 10:55 | AH31: 无忧 | AI31: WYM27102 | AJ31: 考研数学无忧计划啄木鸟（27考研/强化） | AK31: 国内考试 | AM31: 7100 | AP31: 新签 | AQ31: 已交接 | AR31: BJWY2201F8pC6h | AS31: BJWY5487120372 | AT31: WYM271020002 | AU31: 2025-10-23 | AW31: 回访人：谭悦，回访时间：2025-10-17 18:42，回访内容：长期不回我消息 ；|回访人：陈伟钰，回访时间：2025-10-19 18:27，回访内容：陈伟钰恢复工单, 系统自动生成回访记录!；|回访人：谭悦，回访时间：2025-10-19 18:43，回访内容：面谈过了， 跟进中，走读班 ；|回访人：谭悦，回访时间：2025-10-22 18:03，回访内容：已出订单；|回访人：谭悦，回访时间：2025-10-23 10:54，回访内容：1 | BB31: 43431314 | BC31: 否 | BD31: 27考季 | BE31: 考研专业课150,无忧计划-啄木鸟 | BF31: 专业课150,英语,政治,数学 | BG31: 其他 | BH31: 国内高校-211 | BI31: 是 | BL31: 报名 | BN31: 本地人本地大学(常规) | BO31: 集团百度投放-基木鱼
A32: 109 | B32: 北京大学部 | C32: 国内大学部 | D32: 许昌苦瓜 | E32: 129687286 | F32: 张亚男 | G32: 2025-10-04 11:26:07 | H32: 渠道录入来源：集团百度投放-基木鱼 账户名：baidu-大学-总部-A22KA00038 线索ID：251004481825693103 线索时间：2025-10-04 11:25:47 页面名称：新东方考研集训营 姓名：许昌苦瓜 城市：北京 IP：2408:8207:7824:a5d0:718f:6e6c:26a9:cc7b 来源页：https://aisite.wejianzhan.com/site/wjzswa2z/a8dbbce4-c4ec-438e-922c-14344008843f?utm_source=jituan_searchengine_douyin__M_douyin_PP&utm_medium=CPD&utm_campaign=jituanpinzhuanjuheye&utm_term=daxuekaoshi_banwei_1&wid=a842d1130c6e4394afaede8ccb14d579_0_0 | I32: 2026财年第5财月集团百度投放-基木鱼 | K32: 谭悦 | L32: 线上运营-投放 | M32: 集团-抖音品专 | Q32: 陈立峰 | R32: 谭悦 | S32: 30355465 | T32: 正常工单 | U32: 2025-10-19 18:27 | V32: A（六个月内有报课意向工单） | W32: 考研专业课,考研无忧计划 | X32: 大三 | Y32: 北京工业大学 | Z32: 信息学部 | AA32: 通信工程 | AB32: 陈立峰 | AC32: 5681454 | AD32: 谭悦 | AE32: 2025-10-23 10:54 | AF32: 谭悦 | AG32: 2025-10-23 10:55 | AH32: 无忧 | AI32: WYE27106 | AJ32: 考研英语无忧计划啄木鸟（27考研/英二冲刺） | AK32: 国内考试 | AM32: 2900 | AP32: 新签 | AQ32: 已交接 | AR32: BJWY2201F8pC6h | AS32: BJWY5487120372 | AT32: WYE271060003 | AU32: 2025-10-23 | AW32: 回访人：谭悦，回访时间：2025-10-17 18:42，回访内容：长期不回我消息 ；|回访人：陈伟钰，回访时间：2025-10-19 18:27，回访内容：陈伟钰恢复工单, 系统自动生成回访记录!；|回访人：谭悦，回访时间：2025-10-19 18:43，回访内容：面谈过了， 跟进中，走读班 ；|回访人：谭悦，回访时间：2025-10-22 18:03，回访内容：已出订单；|回访人：谭悦，回访时间：2025-10-23 10:54，回访内容：1 | BB32: 43431314 | BC32: 否 | BD32: 27考季 | BE32: 考研专业课150,无忧计划-啄木鸟 | BF32: 专业课150,英语,政治,数学 | BG32: 其他 | BH32: 国内高校-211 | BI32: 是 | BL32: 报名 | BN32: 本地人本地大学(常规) | BO32: 集团百度投放-基木鱼
A33: 110 | B33: 北京大学部 | C33: 国内大学部 | D33: 许昌苦瓜 | E33: 129687286 | F33: 张亚男 | G33: 2025-10-04 11:26:07 | H33: 渠道录入来源：集团百度投放-基木鱼 账户名：baidu-大学-总部-A22KA00038 线索ID：251004481825693103 线索时间：2025-10-04 11:25:47 页面名称：新东方考研集训营 姓名：许昌苦瓜 城市：北京 IP：2408:8207:7824:a5d0:718f:6e6c:26a9:cc7b 来源页：https://aisite.wejianzhan.com/site/wjzswa2z/a8dbbce4-c4ec-438e-922c-14344008843f?utm_source=jituan_searchengine_douyin__M_douyin_PP&utm_medium=CPD&utm_campaign=jituanpinzhuanjuheye&utm_term=daxuekaoshi_banwei_1&wid=a842d1130c6e4394afaede8ccb14d579_0_0 | I33: 2026财年第5财月集团百度投放-基木鱼 | K33: 谭悦 | L33: 线上运营-投放 | M33: 集团-抖音品专 | Q33: 陈立峰 | R33: 谭悦 | S33: 30355465 | T33: 正常工单 | U33: 2025-10-19 18:27 | V33: A（六个月内有报课意向工单） | W33: 考研专业课,考研无忧计划 | X33: 大三 | Y33: 北京工业大学 | Z33: 信息学部 | AA33: 通信工程 | AB33: 陈立峰 | AC33: 5681454 | AD33: 谭悦 | AE33: 2025-10-23 10:54 | AF33: 谭悦 | AG33: 2025-10-23 10:55 | AH33: 无忧 | AI33: WYP27035 | AJ33: 考研政治无忧计划（27考研/强化） | AK33: 国内考试 | AM33: 4000 | AP33: 新签 | AQ33: 已交接 | AR33: BJWY2201F8pC6h | AS33: BJWY5487120372 | AT33: WYP270350033 | AU33: 2025-10-23 | AW33: 回访人：谭悦，回访时间：2025-10-17 18:42，回访内容：长期不回我消息 ；|回访人：陈伟钰，回访时间：2025-10-19 18:27，回访内容：陈伟钰恢复工单, 系统自动生成回访记录!；|回访人：谭悦，回访时间：2025-10-19 18:43，回访内容：面谈过了， 跟进中，走读班 ；|回访人：谭悦，回访时间：2025-10-22 18:03，回访内容：已出订单；|回访人：谭悦，回访时间：2025-10-23 10:54，回访内容：1 | BB33: 43431314 | BC33: 否 | BD33: 27考季 | BE33: 考研专业课150,无忧计划-啄木鸟 | BF33: 专业课150,英语,政治,数学 | BG33: 其他 | BH33: 国内高校-211 | BI33: 是 | BL33: 报名 | BN33: 本地人本地大学(常规) | BO33: 集团百度投放-基木鱼
A34: 111 | B34: 北京大学部 | C34: 国内大学部 | D34: 许昌苦瓜 | E34: 129687286 | F34: 张亚男 | G34: 2025-10-04 11:26:07 | H34: 渠道录入来源：集团百度投放-基木鱼 账户名：baidu-大学-总部-A22KA00038 线索ID：251004481825693103 线索时间：2025-10-04 11:25:47 页面名称：新东方考研集训营 姓名：许昌苦瓜 城市：北京 IP：2408:8207:7824:a5d0:718f:6e6c:26a9:cc7b 来源页：https://aisite.wejianzhan.com/site/wjzswa2z/a8dbbce4-c4ec-438e-922c-14344008843f?utm_source=jituan_searchengine_douyin__M_douyin_PP&utm_medium=CPD&utm_campaign=jituanpinzhuanjuheye&utm_term=daxuekaoshi_banwei_1&wid=a842d1130c6e4394afaede8ccb14d579_0_0 | I34: 2026财年第5财月集团百度投放-基木鱼 | K34: 谭悦 | L34: 线上运营-投放 | M34: 集团-抖音品专 | Q34: 陈立峰 | R34: 谭悦 | S34: 30355465 | T34: 正常工单 | U34: 2025-10-19 18:27 | V34: A（六个月内有报课意向工单） | W34: 考研专业课,考研无忧计划 | X34: 大三 | Y34: 北京工业大学 | Z34: 信息学部 | AA34: 通信工程 | AB34: 陈立峰 | AC34: 5681454 | AD34: 谭悦 | AE34: 2025-10-23 10:54 | AF34: 谭悦 | AG34: 2025-10-23 10:55 | AH34: 无忧 | AI34: WYP27034 | AJ34: 考研政治无忧计划（27考研/基础） | AK34: 国内考试 | AM34: 6100 | AP34: 新签 | AQ34: 已交接 | AR34: BJWY2201F8pC6h | AS34: BJWY5487120372 | AT34: WYP270340033 | AU34: 2025-10-23 | AW34: 回访人：谭悦，回访时间：2025-10-17 18:42，回访内容：长期不回我消息 ；|回访人：陈伟钰，回访时间：2025-10-19 18:27，回访内容：陈伟钰恢复工单, 系统自动生成回访记录!；|回访人：谭悦，回访时间：2025-10-19 18:43，回访内容：面谈过了， 跟进中，走读班 ；|回访人：谭悦，回访时间：2025-10-22 18:03，回访内容：已出订单；|回访人：谭悦，回访时间：2025-10-23 10:54，回访内容：1 | BB34: 43431314 | BC34: 否 | BD34: 27考季 | BE34: 考研专业课150,无忧计划-啄木鸟 | BF34: 专业课150,英语,政治,数学 | BG34: 其他 | BH34: 国内高校-211 | BI34: 是 | BL34: 报名 | BN34: 本地人本地大学(常规) | BO34: 集团百度投放-基木鱼
A35: 112 | B35: 北京大学部 | C35: 国内大学部 | D35: 许昌苦瓜 | E35: 129687286 | F35: 张亚男 | G35: 2025-10-04 11:26:07 | H35: 渠道录入来源：集团百度投放-基木鱼 账户名：baidu-大学-总部-A22KA00038 线索ID：251004481825693103 线索时间：2025-10-04 11:25:47 页面名称：新东方考研集训营 姓名：许昌苦瓜 城市：北京 IP：2408:8207:7824:a5d0:718f:6e6c:26a9:cc7b 来源页：https://aisite.wejianzhan.com/site/wjzswa2z/a8dbbce4-c4ec-438e-922c-14344008843f?utm_source=jituan_searchengine_douyin__M_douyin_PP&utm_medium=CPD&utm_campaign=jituanpinzhuanjuheye&utm_term=daxuekaoshi_banwei_1&wid=a842d1130c6e4394afaede8ccb14d579_0_0 | I35: 2026财年第5财月集团百度投放-基木鱼 | K35: 谭悦 | L35: 线上运营-投放 | M35: 集团-抖音品专 | Q35: 陈立峰 | R35: 谭悦 | S35: 30355465 | T35: 正常工单 | U35: 2025-10-19 18:27 | V35: A（六个月内有报课意向工单） | W35: 考研专业课,考研无忧计划 | X35: 大三 | Y35: 北京工业大学 | Z35: 信息学部 | AA35: 通信工程 | AB35: 陈立峰 | AC35: 5681454 | AD35: 谭悦 | AE35: 2025-10-23 10:54 | AF35: 谭悦 | AG35: 2025-10-23 10:55 | AH35: 无忧 | AI35: WYP27036 | AJ35: 考研政治无忧计划（27考研/冲刺） | AK35: 国内考试 | AM35: 4100 | AP35: 新签 | AQ35: 已交接 | AR35: BJWY2201F8pC6h | AS35: BJWY5487120372 | AT35: WYP270360033 | AU35: 2025-10-23 | AW35: 回访人：谭悦，回访时间：2025-10-17 18:42，回访内容：长期不回我消息 ；|回访人：陈伟钰，回访时间：2025-10-19 18:27，回访内容：陈伟钰恢复工单, 系统自动生成回访记录!；|回访人：谭悦，回访时间：2025-10-19 18:43，回访内容：面谈过了， 跟进中，走读班 ；|回访人：谭悦，回访时间：2025-10-22 18:03，回访内容：已出订单；|回访人：谭悦，回访时间：2025-10-23 10:54，回访内容：1 | BB35: 43431314 | BC35: 否 | BD35: 27考季 | BE35: 考研专业课150,无忧计划-啄木鸟 | BF35: 专业课150,英语,政治,数学 | BG35: 其他 | BH35: 国内高校-211 | BI35: 是 | BL35: 报名 | BN35: 本地人本地大学(常规) | BO35: 集团百度投放-基木鱼
A36: 113 | B36: 北京大学部 | C36: 国内大学部 | D36: 许昌苦瓜 | E36: 129687286 | F36: 张亚男 | G36: 2025-10-04 11:26:07 | H36: 渠道录入来源：集团百度投放-基木鱼 账户名：baidu-大学-总部-A22KA00038 线索ID：251004481825693103 线索时间：2025-10-04 11:25:47 页面名称：新东方考研集训营 姓名：许昌苦瓜 城市：北京 IP：2408:8207:7824:a5d0:718f:6e6c:26a9:cc7b 来源页：https://aisite.wejianzhan.com/site/wjzswa2z/a8dbbce4-c4ec-438e-922c-14344008843f?utm_source=jituan_searchengine_douyin__M_douyin_PP&utm_medium=CPD&utm_campaign=jituanpinzhuanjuheye&utm_term=daxuekaoshi_banwei_1&wid=a842d1130c6e4394afaede8ccb14d579_0_0 | I36: 2026财年第5财月集团百度投放-基木鱼 | K36: 谭悦 | L36: 线上运营-投放 | M36: 集团-抖音品专 | Q36: 陈立峰 | R36: 谭悦 | S36: 30355465 | T36: 正常工单 | U36: 2025-10-19 18:27 | V36: A（六个月内有报课意向工单） | W36: 考研专业课,考研无忧计划 | X36: 大三 | Y36: 北京工业大学 | Z36: 信息学部 | AA36: 通信工程 | AB36: 陈立峰 | AC36: 5681454 | AD36: 谭悦 | AE36: 2025-10-23 10:54 | AF36: 谭悦 | AG36: 2025-10-23 10:55 | AH36: 无忧 | AI36: LP1761186112116 | AJ36: 考研初试专业课一对一（27考研/无忧30小时） | AK36: 国内考试 | AM36: 10000 | AP36: 新签 | AQ36: 已交接 | AR36: BJWY2201F8pC6h | AS36: BJWY5487120372 | AU36: 2025-10-23 | AW36: 回访人：谭悦，回访时间：2025-10-17 18:42，回访内容：长期不回我消息 ；|回访人：陈伟钰，回访时间：2025-10-19 18:27，回访内容：陈伟钰恢复工单, 系统自动生成回访记录!；|回访人：谭悦，回访时间：2025-10-19 18:43，回访内容：面谈过了， 跟进中，走读班 ；|回访人：谭悦，回访时间：2025-10-22 18:03，回访内容：已出订单；|回访人：谭悦，回访时间：2025-10-23 10:54，回访内容：1 | BB36: 43431314 | BC36: 否 | BD36: 27考季 | BE36: 考研专业课150,无忧计划-啄木鸟 | BF36: 专业课150,英语,政治,数学 | BG36: 其他 | BH36: 国内高校-211 | BI36: 是 | BN36: 本地人本地大学(常规) | BO36: 集团百度投放-基木鱼
A37: 172 | B37: 北京大学部 | C37: 国内大学部 | D37: 北京市7303 | E37: 130801054 | F37: 杨俊42(国内) | G37: 2025-10-15 12:38:47 | H37: AI-37815-492 2025-10-15 12:36:12 您好同学，欢迎访问新东方考研官网，【新东方考研】全新升级，课程灵活多样，【考研全年集训营】【考研半年集训营】【考研冲刺营】【线下走读班】【考研一对一】【在职考研】【四六级】火热报名中 ，现在报名更有高达3000元优惠！ AI-37815-492 2025-10-15 12:36:14 您是想咨询【考研走读班】【考研集训营】【考研规划】还是【在职考研】呢？ 01000000037815050295739111827303 2025-10-15 12:36:29 考研咨询 AI-37815-492 2025-10-15 12:36:32 同学，你现在是在校还是在职呢？ 01000000037815050295739111827303 2025-10-15 12:36:38 刚毕业 AI-37815-492 2025-10-15 12:36:41 具体是想报考什么学校和专业呢？ 01000000037815050295739111827303 2025-10-15 12:36:47 有电话吗 AI-37815-492 2025-10-15 12:36:50 有的，您现在方便接电话吗，说下的电话号码，我跟老师说下您的情况，让这边考研课程老师联系一下您，您看可以么？ 01000000037815050295739111827303 2025-10-15 12:37:12 我打过去咨询一下 AI-37815-492 2025-10-15 12:37:15 好的，了解。我们新东方在全国32个城市都有校区，您倾向在哪个城市上课，或者希望哪里的老师给您介绍下呢？ 01000000037815050295739111827303 2025-10-15 12:37:21 北京 AI-37815-492 2025-10-15 12:37:25 您可以留下您的姓名和电话，我这边可以立刻安排对应校区顾问老师给您回电！ 01000000037815050295739111827303 2025-10-15 12:37:45 18122856609 AI-37815-492 2025-10-15 12:37:49 好的，确认一下你的号码是否正确呢~ 01000000037815050295739111827303 2025-10-15 12:38:02 大概什么时间打过来 AI-37815-492 2025-10-15 12:38:06 这个手机号是您的微信吗？如果不是您可以留一下您的微信号 01000000037815050295739111827303 2025-10-15 12:38:06 对的 AI-37815-492 2025-10-15 12:38:09 同学怎么称呼呢？ 01000000037815050295739111827303 2025-10-15 12:38:14 陈 AI-37815-492 2025-10-15 12:38:18 这边马上安排顾问老师联系您，预计半个小时左右给您回电请注意接听~ | I37: 2026财年第5财月百度投放新东方官网小程序 | K37: 杨欢欢 | L37: 新东方官网 | M37: 新东方官网小程序 | O37: 杨欢欢 | P37: 2025-10-15 12:45:55 | Q37: 陈杞荣 | R37: 李涛 | S37: 30448384 | T37: 正常工单 | U37: 2025-10-15 13:26 | V37: A（六个月内有报课意向工单） | W37: 考研VIP | X37: 大学已毕业 | Y37: 北京师范大学 | Z37: 艺术与传媒学院 | AA37: 舞蹈学 | AB37: 陈杞荣 | AC37: 5650748 | AD37: 李涛 | AE37: 2025-10-16 11:16 | AF37: 李涛 | AG37: 2025-10-16 11:17 | AH37: 个性化 | AI37: LP1760584615310 | AJ37: 考研一对一伴学班（26考季） | AK37: 国内考试 | AM37: 50200 | AP37: 新签 | AQ37: 已交接 | AS37: BJWY8687315134 | AU37: 2025-10-16 | AW37: 回访人：李涛，回访时间：2025-10-15 13:26，回访内容：今年考北师大 舞蹈专业！ 本科是北京体育大学，4-6级没有考！ 有学过雅思 5分左右！ 学习时间每天 专业课是在魏公村！下午到学校面谈！；|回访人：李涛，回访时间：2025-10-16 11:16，回访内容：系统自动签约 | BB37: 86079300 | BC37: 否 | BD37: 26考季 | BE37: VIP - 伴学 | BF37: 英语 | BG37: 其他 | BH37: 国内高校-985 | BI37: 是 | BO37: 百度投放
A38: 214 | B38: 北京大学部 | C38: 国内大学部 | E38: 91185805 | G38: 2024-12-20 19:49:46 | H38: 续费原因：学员咨询接下来的考研课程，辛苦流转；该学生为保护期外续费，原顾问部门：国内大学部 | J38: 大二 | K38: 谭悦 | L38: 转介绍 | M38: 学管续费推荐 | Q38: 陈若瑜 | R38: 谭悦 | S38: 30415504 | T38: 续费工单 | U38: 2025-10-11 10:08 | V38: A（六个月内有报课意向工单） | W38: 考研集训营 | X38: 大三 | Y38: 中北大学 | Z38: 机械工程学院 | AA38: 机械设计制造及其自动化 | AB38: 陈若瑜 | AC38: 5647188 | AD38: 谭悦 | AE38: 2025-10-11 10:13 | AF38: 谭悦 | AG38: 2025-10-11 10:24 | AH38: 个性化 | AI38: LP1760148823102 | AJ38: 考研初试专业课一对一（26考研/30小时） | AK38: 国内考试 | AM38: 18300 | AP38: 续班 | AQ38: 已交接 | AS38: XDF072214235615410 | AU38: 2025-10-11 | AW38: 回访人：谭悦，回访时间：2025-10-11 10:08，回访内容：1；|回访人：谭悦，回访时间：2025-10-11 10:13，回访内容：系统自动签约 | BB38: 33338537 | BC38: 否 | BD38: 26考季 | BE38: 寒暑假集训营（春秋OMO） | BF38: 英语,政治 | BH38: 国内高校-双非 | BI38: 是 | BN38: 外地人外地大学(常规)
A39: 24 | B39: 北京大学部 | C39: 国内大学部 | E39: 92994255 | G39: 2025-01-13 16:06:45 | H39: 赵星火老师死单激活资源；赵星火老师死单激活资源 外呼主题：FY24-国内9月死单回访（第四周） 赵星火老师死单激活资源(资源备注人:吴凯龙;资源备注时间:2025-01-13 16:07) | J39: 大三 | K39: 赵星火 | L39: 线上运营-投放 | M39: 百度投放 | Q39: 陈廷进 | R39: 高龙明 | S39: 30469649 | T39: 续费工单 | U39: 2025-10-19 15:47 | V39: A（六个月内有报课意向工单） | W39: 考研VIP | X39: 大学已毕业 | Y39: 吉林大学 | Z39: 物理学院 | AA39: 物理学 | AB39: 陈廷进 | AC39: 5653215 | AD39: 赵星火 | AE39: 2025-10-19 15:47 | AF39: 高龙明 | AG39: 2025-10-19 15:48 | AH39: 集训营 | AK39: 国内考试 | AM39: 9018.15 | AN39: 同科续费 | AP39: 分单 | AQ39: 无须交接 | AS39: BJWY4776417923 | AW39: 回访人：高龙明，回访时间：2025-10-19 15:47，回访内容：1；|回访人：高龙明，回访时间：2025-10-19 15:47，回访内容：1 | BB39: 62316553 | BC39: 否 | BD39: 26考季 | BE39: VIP - 伴学 | BF39: 数学 | BH39: 国内高校-985 | BI39: 否 | BN39: 外地人外地大学(常规)
A40: 44 | B40: 北京大学部 | C40: 国内大学部 | E40: 101338732 | G40: 2025-05-05 17:07:28 | H40: 渠道录入来源：集团百度投放-基木鱼 账户名：baidu-大学-总部-A22KA00038 线索ID：250505456599343480 线索时间：2025-05-05 17:07:25 页面名称：表单单页 姓名：李女士 城市：北京 IP：106.39.151.230 来源页：https://aisite.wejianzhan.com/site/wjzswa2z/ae4b1107-66a0-456e-a487-5b127e799c11?fid=nHcLnjcsPW6zn1fvnHb4PWRLP7tznWPxn6&ch=4&bd_vid=nHcLnjcsPW6zn1fvnHb4PWRLP7tznWPxn-tknjKxP7tknjnkPWf3nWRdn10&bd_bxst=EiaKZ_Blwva8CKZx00cD05kyisFDg0f000000KQfsopoVeLRv_OxEe1wYnoqYpTSm-z800000aFAPbFDrH6zPbRvPHmvPYFKnD7AwH-arHIKfbDvnjKKrZsscDc1f1uawH6znj6sPbPjPHbvf16drRu7PYfswWb3rjIDt1QcFitgly3a00008btpKw6000KgrKHSef0000D0xsDcEe1wYnoqYpTmEe1wYnoqYpTVYn2vJeXqEe1wYnL3dU39000005OOOOOOOOOOEDq7r6 描述：VIP课程 | I40: 2025财年第12财月集团百度投放-基木鱼 | K40: 谭悦 | L40: 线上运营-投放 | M40: 总部-百度投放 | Q40: 陈翔 | R40: 谭悦 | S40: 30223170 | T40: 续费工单 | U40: 2025-09-30 17:20 | V40: A（六个月内有报课意向工单） | W40: 线上考研产品 | X40: 大学已毕业 | Y40: 北京电子科技学院 | Z40: 电子与通信工程系 | AA40: 电子信息工程 | AB40: 陈翔 | AC40: 5642275 | AD40: 谭悦 | AE40: 2025-09-30 17:20 | AF40: 谭悦 | AG40: 2025-10-01 17:50 | AH40: 网课 | AI40: 94083352139 | AJ40: 2026考研英语大纲冲刺班,2026考研政治大纲冲刺班,2026考研数学直通车 5期 | AK40: 国内考试 | AM40: 5686.8 | AP40: 续班 | AQ40: 无须交接 | AU40: 2025-10-01 | AW40: 回访人：谭悦，回访时间：2025-09-30 17:20，回访内容：1；|回访人：谭悦，回访时间：2025-09-30 17:20，回访内容：1 | BA40: 长期班,长期班,长期班 | BB40: 69951253 | BC40: 是 | BD40: 26考季 | BE40: 线上直通车 | BF40: 数学 | BH40: 国内高校-双非 | BI40: 否 | BM40: 110159583
A41: 15 | B41: 北京大学部 | C41: 国内大学部 | E41: 132519662 | G41: 2025-10-28 11:15:27 | H41: 续费原因：学生27考研，需要一对一，辛苦谭悦老师跟进；该学生为保护期内续费，原顾问：国内大学部-谭悦(tanyue9@xdf.cn) | J41: 大四 | K41: 谭悦 | L41: 转介绍 | M41: 学管续费推荐 | Q41: 陈一凡 | R41: 谭悦 | S41: 30609934 | T41: 续费工单 | U41: 2025-10-30 16:10 | V41: A（六个月内有报课意向工单） | W41: 考研VIP | X41: 大四 | Y41: 北方工业大学 | Z41: 信息学院 | AA41: 数据科学与大数据技术 | AB41: 陈一凡 | AC41: 5687773 | AD41: 谭悦 | AE41: 2025-10-30 16:10 | AF41: 谭悦 | AG41: 2025-10-30 16:12 | AH41: 四六级 | AI41: WYFBK25060 | AJ41: 四级无忧计划（补优惠/ 陈一凡 ） | AK41: 国内考试 | AM41: 1481.1 | AP41: 续班 | AQ41: 已交接 | AR41: BJWY24032w1g8X | AS41: BJWY8503976521 | AT41: WYFBK250600001 | AU41: 2025-10-30 | AW41: 回访人：谭悦，回访时间：2025-10-30 16:10，回访内容：1；|回访人：谭悦，回访时间：2025-10-30 16:10，回访内容：补四六级班级优惠入班 | BB41: 58815635 | BC41: 否 | BD41: 26考季 | BE41: VIP - 伴学 | BF41: 英语,政治 | BH41: 国内高校-211 | BI41: 否 | BL41: 报名 | BN41: 本地人本地大学(常规)
A42: 16 | B42: 北京大学部 | C42: 国内大学部 | E42: 132519662 | G42: 2025-10-28 11:15:27 | H42: 续费原因：学生27考研，需要一对一，辛苦谭悦老师跟进；该学生为保护期内续费，原顾问：国内大学部-谭悦(tanyue9@xdf.cn) | J42: 大四 | K42: 谭悦 | L42: 转介绍 | M42: 学管续费推荐 | Q42: 陈一凡 | R42: 谭悦 | S42: 30609934 | T42: 续费工单 | U42: 2025-10-30 16:10 | V42: A（六个月内有报课意向工单） | W42: 考研VIP | X42: 大四 | Y42: 北方工业大学 | Z42: 信息学院 | AA42: 数据科学与大数据技术 | AB42: 陈一凡 | AC42: 5687773 | AD42: 谭悦 | AE42: 2025-10-30 16:10 | AF42: 谭悦 | AG42: 2025-10-30 16:12 | AH42: 无忧 | AI42: WYM26009 | AJ42: 考研数学无忧计划（26考研/冲刺） | AK42: 国内考试 | AM42: 4200 | AP42: 续班 | AQ42: 已交接 | AR42: BJWY22035556hl | AS42: BJWY8503976521 | AT42: WYM260090062 | AU42: 2025-10-26 | AW42: 回访人：谭悦，回访时间：2025-10-30 16:10，回访内容：1；|回访人：谭悦，回访时间：2025-10-30 16:10，回访内容：补四六级班级优惠入班 | BB42: 58815635 | BC42: 否 | BD42: 26考季 | BE42: VIP - 伴学 | BF42: 英语,政治 | BH42: 国内高校-211 | BI42: 否 | BL42: 转出 | BN42: 本地人本地大学(常规)
A43: 17 | B43: 北京大学部 | C43: 国内大学部 | E43: 132519662 | G43: 2025-10-28 11:15:27 | H43: 续费原因：学生27考研，需要一对一，辛苦谭悦老师跟进；该学生为保护期内续费，原顾问：国内大学部-谭悦(tanyue9@xdf.cn) | J43: 大四 | K43: 谭悦 | L43: 转介绍 | M43: 学管续费推荐 | Q43: 陈一凡 | R43: 谭悦 | S43: 30609934 | T43: 续费工单 | U43: 2025-10-30 16:10 | V43: A（六个月内有报课意向工单） | W43: 考研VIP | X43: 大四 | Y43: 北方工业大学 | Z43: 信息学院 | AA43: 数据科学与大数据技术 | AB43: 陈一凡 | AC43: 5687773 | AD43: 谭悦 | AE43: 2025-10-30 16:10 | AF43: 谭悦 | AG43: 2025-10-30 16:12 | AH43: 无忧 | AI43: WYP26021 | AJ43: 考研政治无忧计划（26考研/冲刺） | AK43: 国内考试 | AM43: 5700 | AP43: 续班 | AQ43: 已交接 | AR43: BJWY22035556hl | AS43: BJWY8503976521 | AT43: WYP260210063 | AU43: 2025-10-26 | AW43: 回访人：谭悦，回访时间：2025-10-30 16:10，回访内容：1；|回访人：谭悦，回访时间：2025-10-30 16:10，回访内容：补四六级班级优惠入班 | BB43: 58815635 | BC43: 否 | BD43: 26考季 | BE43: VIP - 伴学 | BF43: 英语,政治 | BH43: 国内高校-211 | BI43: 否 | BL43: 转出 | BN43: 本地人本地大学(常规)
A44: 80 | B44: 北京大学部 | C44: 国内大学部 | D44: 陈一凡 | E44: 132519662 | F44: 郝琨 | G44: 2025-10-28 11:15:27 | H44: 续费原因：学生27考研，需要一对一，辛苦谭悦老师跟进；该学生为保护期内续费，原顾问：国内大学部-谭悦(tanyue9@xdf.cn) | J44: 大四 | K44: 谭悦 | L44: 转介绍 | M44: 学管续费推荐 | N44: 郝琨haokun@xdf.cn | Q44: 陈一凡 | R44: 谭悦 | S44: 30624983 | T44: 续费工单 | U44: 2025-10-28 11:22 | V44: A（六个月内有报课意向工单） | W44: 考研VIP | X44: 大四 | Y44: 北方工业大学 | Z44: 信息学院 | AA44: 数据科学与大数据技术 | AB44: 陈一凡 | AC44: 5569255 | AD44: 谭悦 | AE44: 2025-10-28 11:29 | AF44: 谭悦 | AG44: 2025-10-28 11:43 | AH44: 无忧 | AI44: LP1761622149221 | AJ44: 26考研一对一伴学（无忧） | AK44: 国内考试 | AM44: 20400 | AO44: 郝琨 | AP44: 续班 | AQ44: 已交接 | AS44: BJWY8503976521 | AU44: 2025-10-28 | AW44: 回访人：谭悦，回访时间：2025-10-28 11:22，回访内容：续费一对一；|回访人：谭悦，回访时间：2025-10-28 11:29，回访内容：系统自动签约 | BB44: 58815635 | BC44: 否 | BD44: 26考季 | BE44: VIP - 伴学 | BF44: 英语,政治 | BG44: 其他 | BH44: 国内高校-211 | BI44: 是 | BN44: 本地人本地大学(常规) | BO44: 学管续费推荐
A45: 22 | B45: 北京大学部 | C45: 国内大学部 | D45: 学生 | E45: 131485564 | F45: 乔文娇 | G45: 2025-10-20 10:42:19 | J45: 研三 | K45: 乔文娇 | L45: 电话 | M45: 大客服呼入 | O45: 乔文娇 | P45: 2025-10-20 10:44:59 | Q45: 陈玉昆 | R45: 谭悦 | S45: 30499061 | T45: 正常工单 | U45: 2025-10-20 11:57 | V45: A（六个月内有报课意向工单） | W45: 考博 | X45: 在职 | Y45: 北京大学医学部 | Z45: 医学 | AA45: 医学 | AB45: 陈玉昆 | AC45: 5679797 | AD45: 谭悦 | AE45: 2025-10-20 14:10 | AF45: 谭悦 | AG45: 2025-10-20 15:15 | AH45: 网课 | AI45: 97505185768 | AJ45: 2026医学考博英语全程班【直播 + 录播】 | AK45: 国内考试 | AM45: 1938 | AP45: 新签 | AQ45: 无须交接 | AU45: 2025-10-20 | AW45: 回访人：谭悦，回访时间：2025-10-20 11:57，回访内容：在职工作，医学考博，明年考试，推荐网课和一对一 ；|回访人：谭悦，回访时间：2025-10-20 14:10，回访内容：系统自动签约；|回访人：谭悦，回访时间：2025-10-20 15:14，回访内容：签约 | BA45: 长期班 | BB45: 86345434 | BC45: 是 | BH45: 国内高校-985 | BI45: 否 | BM45: 111037098 | BO45: 客服
A46: 231 | B46: 北京大学部 | C46: 国内大学部 | D46: 崔毓轩 | E46: 129648353 | F46: 北京国内管理员 | G46: 2025-10-05 10:29:53 | H46: 资源录入来源：小表单 城市：张家口市 市场活动id：412422 市场活动名称：新东方集团官微【新东方】资源 活动所属学校id：10000 活动所属学校名称：总公司 线索接收人邮箱：yangjun42@xdf.cn 线索接受人类型：自定义 表单信息：表单id81512、表单名(对内)：新东方集团官微【新东方】资源、表单名（对外）：新东方课程报名、创建人邮箱：wuyue38@xdf.cn、表单链接：pages/index/index.html?scene=81512,,ucwVUGil 备注：来源:小表单;姓名:崔毓轩;意向课程: 【课程】考研、四六级、专升本、成人英语/北京/北京; 新老生: 新生; 提交链接:pages/index/index.html?scene=81512,,ucwVUGil;地理位置:河北省张家口市怀来县官厅镇珠园村;渠道:新媒体运营/集团品牌官微 | I46: 2026财年小表单-新东方集团官微【新东方】资源 | J46: 未知 | K46: 王静静 | L46: 线上运营-私域中台 | M46: 集团官微 | O46: 王静静 | P46: 2025-10-05 11:00:15 | Q46: 崔毓轩 | R46: 李涛 | S46: 30315057 | T46: 正常工单 | U46: 2025-10-05 12:15 | V46: A（六个月内有报课意向工单） | W46: 考研专业课,考研VIP,考研无忧计划,线上考研产品 | X46: 大四 | Y46: 中央财经大学 | Z46: 金融学院 | AA46: 金融学 | AB46: 崔毓轩 | AC46: 5563678 | AD46: 李涛 | AE46: 2025-10-09 11:20 | AF46: 李涛 | AG46: 2025-10-09 11:21 | AH46: 个性化 | AI46: LP1759980029184 | AJ46: 考研一对一伴学班（26考季） | AK46: 国内考试 | AM46: 50200 | AP46: 新签 | AQ46: 已交接 | AS46: BJWY3662221602 | AU46: 2025-10-09 | AW46: 回访人：李涛，回访时间：2025-10-05 12:15，回访内容：现在不是很方便 晚点电话联系 微信通过了！；|回访人：李涛，回访时间：2025-10-05 16:42，回访内容：详细介绍一对一课程 家在东城住 这俩天考虑一下 给回复！ | BB46: 85728867 | BC46: 否 | BD46: 26考季 | BE46: VIP - 伴学 | BF46: 英语,政治,数学,专业课150 | BG46: 其他 | BH46: 国内高校-211 | BI46: 是 | BN46: 外地人外地大学(常规) | BO46: 小表单
A47: 62 | B47: 北京大学部 | C47: 国内大学部 | D47: 翟羽轩 | E47: 120027670 | F47: 王天义 | G47: 2025-07-21 13:29:55 | H47: 续费原因：续费 1一对一；该学生为保护期外续费，原顾问部门：国内大学部 | J47: 大学已毕业 | K47: 赵星火 | L47: 转介绍 | M47: 学管续费推荐 | N47: 王天义wangtianyi56@xdf.cn | Q47: 翟羽轩 | R47: 赵星火 | S47: 29231960 | T47: 续费工单 | U47: 2025-07-21 14:18 | V47: A（六个月内有报课意向工单） | W47: 考研VIP | X47: 大学已毕业 | Y47: 国际关系学院 | Z47: 国际安全学院 | AA47: 国际政治 | AB47: 翟羽轩 | AC47: 5661321 | AD47: 赵星火 | AE47: 2025-10-30 11:12 | AF47: 赵星火 | AG47: 2025-10-30 11:17 | AH47: 个性化 | AI47: LP1761793973312 | AJ47: 考研一对一伴学班（定制/26考季） | AK47: 国内考试 | AM47: 18700 | AO47: 王天义 | AP47: 续班 | AQ47: 已交接 | AS47: BJWY0621194005 | AU47: 2025-10-30 | AW47: 回访人：赵星火，回访时间：2025-10-24 18:50，回访内容：还没确定时间这边继续维护跟进中这边继续维护中；|回访人：赵星火，回访时间：2025-10-29 17:03，回访内容：给到课程计划和这个收费以及上课时间跟进中；|回访人：赵星火，回访时间：2025-10-30 11:12，回访内容：系统自动签约 | BB47: 20908795 | BC47: 否 | BD47: 26考季 | BE47: VIP - 伴学 | BF47: 政治 | BG47: 其他 | BH47: 国内高校-双非 | BI47: 是 | BO47: 学管续费推荐
A48: 170 | B48: 北京大学部 | C48: 国内大学部 | D48: 范围 | E48: 130939619 | F48: 王天义 | G48: 2025-10-15 15:57:24 | H48: 续费原因：数学补充 12 次课，英语补充 5 次课，共 34h；该学生为保护期内续费，原顾问：国内大学部-赵星火(zhaoxinghuo@xdf.cn) | J48: 大四 | K48: 赵星火 | L48: 转介绍 | M48: 学管续费推荐 | N48: 王天义wangtianyi56@xdf.cn | Q48: 范围 | R48: 赵星火 | S48: 30479815 | T48: 续费工单 | U48: 2025-10-15 21:43 | V48: A（六个月内有报课意向工单） | W48: 考研VIP | X48: 大四 | Y48: 北京建筑大学 | Z48: 土木与交通工程学院 | AA48: 土木工程 | AB48: 范围 | AC48: 5676974 | AD48: 赵星火 | AE48: 2025-10-16 11:30 | AF48: 赵星火 | AG48: 2025-10-16 13:02 | AH48: 个性化 | AI48: LP1760585419343 | AJ48: 考研一对一伴学班（26考季） | AK48: 国内考试 | AM48: 26700 | AO48: 王天义 | AP48: 续班 | AQ48: 已交接 | AS48: BJWY1871741452 | AU48: 2025-10-16 | AW48: 回访人：赵星火，回访时间：2025-10-15 21:43，回访内容：明天缴费；|回访人：赵星火，回访时间：2025-10-16 11:30，回访内容：系统自动签约 | BB48: 25333257 | BC48: 否 | BD48: 26考季 | BE48: VIP - 伴学 | BF48: 英语 | BG48: 其他 | BH48: 国内高校-双非 | BI48: 是 | BN48: 本地人本地大学(常规) | BO48: 学管续费推荐
A49: 237 | B49: 北京大学部 | C49: 国内大学部 | E49: 91630350 | G49: 2024-12-26 18:40:02 | H49: 激活 | J49: 大二 | K49: 赵星火 | L49: 线上运营-投放 | M49: 百度投放 | Q49: 方越 | R49: 赵星火 | S49: 30317217 | T49: 续费工单 | U49: 2025-10-06 11:29 | V49: A（六个月内有报课意向工单） | W49: 考研专业课,考研无忧计划 | X49: 大三 | Y49: 北京联合大学 | Z49: 艺术学院 | AA49: 绘画 | AB49: 方越 | AC49: 5563119 | AD49: 赵星火 | AE49: 2025-10-06 14:22 | AF49: 赵星火 | AG49: 2025-10-06 14:22 | AH49: 无忧 | AI49: WYE27010 | AJ49: 考研英语无忧计划（27考研/英二强化） | AK49: 国内考试 | AM49: 5165.2 | AN49: 扩科续费 | AP49: 续班 | AQ49: 已交接 | AR49: WebReg | AS49: BJWY2391065562 | AT49: WYE270100014 | AU49: 2025-10-06 | AW49: 回访人：赵星火，回访时间：2025-10-06 11:29，回访内容：1；|回访人：赵星火，回访时间：2025-10-06 14:22，回访内容：1 | BB49: 62011352 | BC49: 否 | BD49: 27考季 | BE49: 无忧计划-早鸟,考研专业课300 | BF49: 英语,政治,专业课300 | BH49: 国内高校-双非 | BI49: 是 | BL49: 报名 | BN49: 本地人本地大学(常规)
A50: 238 | B50: 北京大学部 | C50: 国内大学部 | E50: 91630350 | G50: 2024-12-26 18:40:02 | H50: 激活 | J50: 大二 | K50: 赵星火 | L50: 线上运营-投放 | M50: 百度投放 | Q50: 方越 | R50: 赵星火 | S50: 30317217 | T50: 续费工单 | U50: 2025-10-06 11:29 | V50: A（六个月内有报课意向工单） | W50: 考研专业课,考研无忧计划 | X50: 大三 | Y50: 北京联合大学 | Z50: 艺术学院 | AA50: 绘画 | AB50: 方越 | AC50: 5563119 | AD50: 赵星火 | AE50: 2025-10-06 14:22 | AF50: 赵星火 | AG50: 2025-10-06 14:22 | AH50: 无忧 | AI50: WYE27012 | AJ50: 考研英语无忧计划（27考研/基础） | AK50: 国内考试 | AM50: 4697.6 | AN50: 扩科续费 | AP50: 续班 | AQ50: 已交接 | AR50: WebReg | AS50: BJWY2391065562 | AT50: WYE270120037 | AU50: 2025-10-06 | AW50: 回访人：赵星火，回访时间：2025-10-06 11:29，回访内容：1；|回访人：赵星火，回访时间：2025-10-06 14:22，回访内容：1 | BB50: 62011352 | BC50: 否 | BD50: 27考季 | BE50: 无忧计划-早鸟,考研专业课300 | BF50: 英语,政治,专业课300 | BH50: 国内高校-双非 | BI50: 是 | BL50: 报名 | BN50: 本地人本地大学(常规)
A51: 239 | B51: 北京大学部 | C51: 国内大学部 | E51: 91630350 | G51: 2024-12-26 18:40:02 | H51: 激活 | J51: 大二 | K51: 赵星火 | L51: 线上运营-投放 | M51: 百度投放 | Q51: 方越 | R51: 赵星火 | S51: 30317217 | T51: 续费工单 | U51: 2025-10-06 11:29 | V51: A（六个月内有报课意向工单） | W51: 考研专业课,考研无忧计划 | X51: 大三 | Y51: 北京联合大学 | Z51: 艺术学院 | AA51: 绘画 | AB51: 方越 | AC51: 5563119 | AD51: 赵星火 | AE51: 2025-10-06 14:22 | AF51: 赵星火 | AG51: 2025-10-06 14:22 | AH51: 无忧 | AI51: WYE27011 | AJ51: 考研英语无忧计划（27考研/英二冲刺） | AK51: 国内考试 | AM51: 5138 | AN51: 扩科续费 | AP51: 续班 | AQ51: 已交接 | AR51: WebReg | AS51: BJWY2391065562 | AT51: WYE270110014 | AU51: 2025-10-06 | AW51: 回访人：赵星火，回访时间：2025-10-06 11:29，回访内容：1；|回访人：赵星火，回访时间：2025-10-06 14:22，回访内容：1 | BB51: 62011352 | BC51: 否 | BD51: 27考季 | BE51: 无忧计划-早鸟,考研专业课300 | BF51: 英语,政治,专业课300 | BH51: 国内高校-双非 | BI51: 是 | BL51: 报名 | BN51: 本地人本地大学(常规)
A52: 240 | B52: 北京大学部 | C52: 国内大学部 | E52: 91630350 | G52: 2024-12-26 18:40:02 | H52: 激活 | J52: 大二 | K52: 赵星火 | L52: 线上运营-投放 | M52: 百度投放 | Q52: 方越 | R52: 赵星火 | S52: 30317217 | T52: 续费工单 | U52: 2025-10-06 11:29 | V52: A（六个月内有报课意向工单） | W52: 考研专业课,考研无忧计划 | X52: 大三 | Y52: 北京联合大学 | Z52: 艺术学院 | AA52: 绘画 | AB52: 方越 | AC52: 5563119 | AD52: 赵星火 | AE52: 2025-10-06 14:22 | AF52: 赵星火 | AG52: 2025-10-06 14:22 | AH52: 无忧 | AI52: WYP27034 | AJ52: 考研政治无忧计划（27考研/基础） | AK52: 国内考试 | AM52: 6092.2 | AN52: 扩科续费 | AP52: 续班 | AQ52: 已交接 | AR52: WebReg | AS52: BJWY2391065562 | AT52: WYP270340009 | AU52: 2025-10-06 | AW52: 回访人：赵星火，回访时间：2025-10-06 11:29，回访内容：1；|回访人：赵星火，回访时间：2025-10-06 14:22，回访内容：1 | BB52: 62011352 | BC52: 否 | BD52: 27考季 | BE52: 无忧计划-早鸟,考研专业课300 | BF52: 英语,政治,专业课300 | BH52: 国内高校-双非 | BI52: 是 | BL52: 报名 | BN52: 本地人本地大学(常规)
A53: 241 | B53: 北京大学部 | C53: 国内大学部 | E53: 91630350 | G53: 2024-12-26 18:40:02 | H53: 激活 | J53: 大二 | K53: 赵星火 | L53: 线上运营-投放 | M53: 百度投放 | Q53: 方越 | R53: 赵星火 | S53: 30317217 | T53: 续费工单 | U53: 2025-10-06 11:29 | V53: A（六个月内有报课意向工单） | W53: 考研专业课,考研无忧计划 | X53: 大三 | Y53: 北京联合大学 | Z53: 艺术学院 | AA53: 绘画 | AB53: 方越 | AC53: 5563119 | AD53: 赵星火 | AE53: 2025-10-06 14:22 | AF53: 赵星火 | AG53: 2025-10-06 14:22 | AH53: 无忧 | AI53: WYP27036 | AJ53: 考研政治无忧计划（27考研/冲刺） | AK53: 国内考试 | AM53: 4183.8 | AN53: 扩科续费 | AP53: 续班 | AQ53: 已交接 | AR53: WebReg | AS53: BJWY2391065562 | AT53: WYP270360009 | AU53: 2025-10-06 | AW53: 回访人：赵星火，回访时间：2025-10-06 11:29，回访内容：1；|回访人：赵星火，回访时间：2025-10-06 14:22，回访内容：1 | BB53: 62011352 | BC53: 否 | BD53: 27考季 | BE53: 无忧计划-早鸟,考研专业课300 | BF53: 英语,政治,专业课300 | BH53: 国内高校-双非 | BI53: 是 | BL53: 报名 | BN53: 本地人本地大学(常规)
A54: 242 | B54: 北京大学部 | C54: 国内大学部 | E54: 91630350 | G54: 2024-12-26 18:40:02 | H54: 激活 | J54: 大二 | K54: 赵星火 | L54: 线上运营-投放 | M54: 百度投放 | Q54: 方越 | R54: 赵星火 | S54: 30317217 | T54: 续费工单 | U54: 2025-10-06 11:29 | V54: A（六个月内有报课意向工单） | W54: 考研专业课,考研无忧计划 | X54: 大三 | Y54: 北京联合大学 | Z54: 艺术学院 | AA54: 绘画 | AB54: 方越 | AC54: 5563119 | AD54: 赵星火 | AE54: 2025-10-06 14:22 | AF54: 赵星火 | AG54: 2025-10-06 14:22 | AH54: 无忧 | AI54: WYP27035 | AJ54: 考研政治无忧计划（27考研/强化） | AK54: 国内考试 | AM54: 3523.2 | AN54: 扩科续费 | AP54: 续班 | AQ54: 已交接 | AR54: WebReg | AS54: BJWY2391065562 | AT54: WYP270350009 | AU54: 2025-10-06 | AW54: 回访人：赵星火，回访时间：2025-10-06 11:29，回访内容：1；|回访人：赵星火，回访时间：2025-10-06 14:22，回访内容：1 | BB54: 62011352 | BC54: 否 | BD54: 27考季 | BE54: 无忧计划-早鸟,考研专业课300 | BF54: 英语,政治,专业课300 | BH54: 国内高校-双非 | BI54: 是 | BL54: 报名 | BN54: 本地人本地大学(常规)
A55: 243 | B55: 北京大学部 | C55: 国内大学部 | E55: 91630350 | G55: 2024-12-26 18:40:02 | H55: 激活 | J55: 大二 | K55: 赵星火 | L55: 线上运营-投放 | M55: 百度投放 | Q55: 方越 | R55: 赵星火 | S55: 30317217 | T55: 续费工单 | U55: 2025-10-06 11:29 | V55: A（六个月内有报课意向工单） | W55: 考研专业课,考研无忧计划 | X55: 大三 | Y55: 北京联合大学 | Z55: 艺术学院 | AA55: 绘画 | AB55: 方越 | AC55: 5563119 | AD55: 赵星火 | AE55: 2025-10-06 14:22 | AF55: 赵星火 | AG55: 2025-10-06 14:22 | AH55: 无忧 | AI55: LP1759730731334 | AJ55: 考研初试专业课一对一（27考研/无忧50小时） | AK55: 国内考试 | AM55: 21000 | AN55: 扩科续费 | AP55: 续班 | AQ55: 已交接 | AR55: WebReg | AS55: BJWY2391065562 | AU55: 2025-10-06 | AW55: 回访人：赵星火，回访时间：2025-10-06 11:29，回访内容：1；|回访人：赵星火，回访时间：2025-10-06 14:22，回访内容：1 | BB55: 62011352 | BC55: 否 | BD55: 27考季 | BE55: 无忧计划-早鸟,考研专业课300 | BF55: 英语,政治,专业课300 | BH55: 国内高校-双非 | BI55: 是 | BN55: 本地人本地大学(常规)
A56: 209 | B56: 北京大学部 | C56: 国内大学部 | E56: 129222635 | G56: 2025-09-28 10:27:12 | H56: 家长咨询四级线下课课程地点及收费情况 | J56: 大一 | K56: 李涛 | L56: 转介绍 | M56: 内部员工推荐 | Q56: 冯文玥 | R56: 李涛 | S56: 30422642 | T56: 续费工单 | U56: 2025-10-14 17:17 | V56: A（六个月内有报课意向工单） | W56: 四级 | X56: 六年级 | Y56: 北京化工大学 | Z56: 机电工程学院 | AA56: 机械设计制造及其自动化 | AB56: 冯文玥 | AC56: 5676089 | AD56: 李涛 | AE56: 2025-10-14 17:18 | AF56: 李涛 | AG56: 2025-10-14 17:18 | AH56: 四六级 | AI56: WYF25043 | AJ56: 四级无忧计划 | AK56: 国内考试 | AM56: 6180 | AN56: 同科续费 | AO56: 姚明明+yaomingming@xdf.cn+新东方教育科技集团有限公司-培训学校-北京学校-高中一对一部-西南区-玉泉路分中心 | 学习顾问 | AP56: 续班 | AQ56: 已交接 | AR56: BJWY2101498uW2 | AS56: BJWY3141371973 | AT56: WYF250430058 | AU56: 2025-10-11 | AW56: 回访人：李涛，回访时间：2025-10-14 17:17，回访内容：转班 重新弄一下；|回访人：李涛，回访时间：2025-10-14 17:18，回访内容：报名！ | BB56: 74931274 | BC56: 否 | BD56: 25下考季 | BE56: 四级无忧计划 | BH56: 国内高校-211 | BI56: 是 | BL56: 转出 | BN56: 本地人本地大学(常规)
A57: 46 | B57: 北京大学部 | C57: 国内大学部 | D57: 刘书明 | E57: 114767021 | F57: 赵秋侠 | G57: 2025-06-17 11:25:47 | J57: 在职 | K57: 赵秋侠 | L57: 线上运营-抖音 | M57: 抖音 | O57: 赵秋侠 | P57: 2025-06-17 11:27:46 | Q57: 冯义卿 | R57: 赵星火 | S57: 28390043 | T57: 正常工单 | U57: 2025-06-17 11:42 | V57: A（六个月内有报课意向工单） | W57: 考研集训营 | X57: 在职 | Y57: 首都医科大学 | Z57: 临床医学院 | AA57: 临床医学 | AB57: 冯义卿 | AC57: 5689064 | AD57: 赵星火 | AE57: 2025-10-31 18:42 | AF57: 赵星火 | AG57: 2025-10-31 19:04 | AH57: 集训营 | AI57: KYQNJXY2701B | AJ57: 27考研全年集训营英语（强冲/英语一） | AK57: 国内考试 | AM57: 7633.75 | AP57: 新签 | AQ57: 已交接 | AR57: BJWY25030q8UPI | AS57: BJWY5373463335 | AT57: KYQNJXY2701B0004 | AU57: 2025-10-31 | AW57: 回访人：赵星火，回访时间：2025-10-28 16:53，回访内容：给到课程辅导合同跟进中继续维护学生。；|回访人：赵星火，回访时间：2025-10-31 18:42，回访内容：1 | BB57: 64239584 | BC57: 否 | BD57: 27考季 | BE57: 全年集训营 | BF57: 英语,政治 | BG57: 其他 | BH57: 国内高校-双非 | BI57: 是 | BL57: 报名
A58: 47 | B58: 北京大学部 | C58: 国内大学部 | D58: 刘书明 | E58: 114767021 | F58: 赵秋侠 | G58: 2025-06-17 11:25:47 | J58: 在职 | K58: 赵秋侠 | L58: 线上运营-抖音 | M58: 抖音 | O58: 赵秋侠 | P58: 2025-06-17 11:27:46 | Q58: 冯义卿 | R58: 赵星火 | S58: 28390043 | T58: 正常工单 | U58: 2025-06-17 11:42 | V58: A（六个月内有报课意向工单） | W58: 考研集训营 | X58: 在职 | Y58: 首都医科大学 | Z58: 临床医学院 | AA58: 临床医学 | AB58: 冯义卿 | AC58: 5689064 | AD58: 赵星火 | AE58: 2025-10-31 18:42 | AF58: 赵星火 | AG58: 2025-10-31 19:04 | AH58: 集训营 | AI58: KYQNJX2703Z | AJ58: 27考研全年集训营（住宿费/三月） | AK58: 国内考试 | AM58: 19950 | AP58: 新签 | AQ58: 已交接 | AR58: BJWY25030q8UPI | AS58: BJWY5373463335 | AT58: KYQNJX2703Z0005 | AU58: 2025-10-31 | AW58: 回访人：赵星火，回访时间：2025-10-28 16:53，回访内容：给到课程辅导合同跟进中继续维护学生。；|回访人：赵星火，回访时间：2025-10-31 18:42，回访内容：1 | BB58: 64239584 | BC58: 否 | BD58: 27考季 | BE58: 全年集训营 | BF58: 英语,政治 | BG58: 其他 | BH58: 国内高校-双非 | BI58: 是 | BL58: 报名
A59: 48 | B59: 北京大学部 | C59: 国内大学部 | D59: 刘书明 | E59: 114767021 | F59: 赵秋侠 | G59: 2025-06-17 11:25:47 | J59: 在职 | K59: 赵秋侠 | L59: 线上运营-抖音 | M59: 抖音 | O59: 赵秋侠 | P59: 2025-06-17 11:27:46 | Q59: 冯义卿 | R59: 赵星火 | S59: 28390043 | T59: 正常工单 | U59: 2025-06-17 11:42 | V59: A（六个月内有报课意向工单） | W59: 考研集训营 | X59: 在职 | Y59: 首都医科大学 | Z59: 临床医学院 | AA59: 临床医学 | AB59: 冯义卿 | AC59: 5689064 | AD59: 赵星火 | AE59: 2025-10-31 18:42 | AF59: 赵星火 | AG59: 2025-10-31 19:04 | AH59: 集训营 | AI59: KYHJJXY2701 | AJ59: 27考研寒假集训营英语 | AK59: 国内考试 | AM59: 2400 | AP59: 新签 | AQ59: 已交接 | AR59: BJWY25030q8UPI | AS59: BJWY5373463335 | AT59: KYHJJXY27010004 | AU59: 2025-10-31 | AW59: 回访人：赵星火，回访时间：2025-10-28 16:53，回访内容：给到课程辅导合同跟进中继续维护学生。；|回访人：赵星火，回访时间：2025-10-31 18:42，回访内容：1 | BB59: 64239584 | BC59: 否 | BD59: 27考季 | BE59: 全年集训营 | BF59: 英语,政治 | BG59: 其他 | BH59: 国内高校-双非 | BI59: 是 | BL59: 报名
A60: 49 | B60: 北京大学部 | C60: 国内大学部 | D60: 刘书明 | E60: 114767021 | F60: 赵秋侠 | G60: 2025-06-17 11:25:47 | J60: 在职 | K60: 赵秋侠 | L60: 线上运营-抖音 | M60: 抖音 | O60: 赵秋侠 | P60: 2025-06-17 11:27:46 | Q60: 冯义卿 | R60: 赵星火 | S60: 28390043 | T60: 正常工单 | U60: 2025-06-17 11:42 | V60: A（六个月内有报课意向工单） | W60: 考研集训营 | X60: 在职 | Y60: 首都医科大学 | Z60: 临床医学院 | AA60: 临床医学 | AB60: 冯义卿 | AC60: 5689064 | AD60: 赵星火 | AE60: 2025-10-31 18:42 | AF60: 赵星火 | AG60: 2025-10-31 19:04 | AH60: 集训营 | AI60: KYQNJXZ2702A | AJ60: 27考研全年集训营政治（基础） | AK60: 国内考试 | AM60: 2693.75 | AP60: 新签 | AQ60: 已交接 | AR60: BJWY25030q8UPI | AS60: BJWY5373463335 | AT60: KYQNJXZ2702A0004 | AU60: 2025-10-31 | AW60: 回访人：赵星火，回访时间：2025-10-28 16:53，回访内容：给到课程辅导合同跟进中继续维护学生。；|回访人：赵星火，回访时间：2025-10-31 18:42，回访内容：1 | BB60: 64239584 | BC60: 否 | BD60: 27考季 | BE60: 全年集训营 | BF60: 英语,政治 | BG60: 其他 | BH60: 国内高校-双非 | BI60: 是 | BL60: 报名
A61: 50 | B61: 北京大学部 | C61: 国内大学部 | D61: 刘书明 | E61: 114767021 | F61: 赵秋侠 | G61: 2025-06-17 11:25:47 | J61: 在职 | K61: 赵秋侠 | L61: 线上运营-抖音 | M61: 抖音 | O61: 赵秋侠 | P61: 2025-06-17 11:27:46 | Q61: 冯义卿 | R61: 赵星火 | S61: 28390043 | T61: 正常工单 | U61: 2025-06-17 11:42 | V61: A（六个月内有报课意向工单） | W61: 考研集训营 | X61: 在职 | Y61: 首都医科大学 | Z61: 临床医学院 | AA61: 临床医学 | AB61: 冯义卿 | AC61: 5689064 | AD61: 赵星火 | AE61: 2025-10-31 18:42 | AF61: 赵星火 | AG61: 2025-10-31 19:04 | AH61: 集训营 | AI61: KYQNJXZ2702B | AJ61: 27考研全年集训营政治（强冲） | AK61: 国内考试 | AM61: 5813.75 | AP61: 新签 | AQ61: 已交接 | AR61: BJWY25030q8UPI | AS61: BJWY5373463335 | AT61: KYQNJXZ2702B0004 | AU61: 2025-10-31 | AW61: 回访人：赵星火，回访时间：2025-10-28 16:53，回访内容：给到课程辅导合同跟进中继续维护学生。；|回访人：赵星火，回访时间：2025-10-31 18:42，回访内容：1 | BB61: 64239584 | BC61: 否 | BD61: 27考季 | BE61: 全年集训营 | BF61: 英语,政治 | BG61: 其他 | BH61: 国内高校-双非 | BI61: 是 | BL61: 报名
A62: 51 | B62: 北京大学部 | C62: 国内大学部 | D62: 刘书明 | E62: 114767021 | F62: 赵秋侠 | G62: 2025-06-17 11:25:47 | J62: 在职 | K62: 赵秋侠 | L62: 线上运营-抖音 | M62: 抖音 | O62: 赵秋侠 | P62: 2025-06-17 11:27:46 | Q62: 冯义卿 | R62: 赵星火 | S62: 28390043 | T62: 正常工单 | U62: 2025-06-17 11:42 | V62: A（六个月内有报课意向工单） | W62: 考研集训营 | X62: 在职 | Y62: 首都医科大学 | Z62: 临床医学院 | AA62: 临床医学 | AB62: 冯义卿 | AC62: 5689064 | AD62: 赵星火 | AE62: 2025-10-31 18:42 | AF62: 赵星火 | AG62: 2025-10-31 19:04 | AH62: 集训营 | AI62: KYHJJX2701Z | AJ62: 27考研寒假集训营（住宿费） | AK62: 国内考试 | AM62: 1125 | AP62: 新签 | AQ62: 已交接 | AR62: BJWY25030q8UPI | AS62: BJWY5373463335 | AT62: KYHJJX2701Z0004 | AU62: 2025-10-31 | AW62: 回访人：赵星火，回访时间：2025-10-28 16:53，回访内容：给到课程辅导合同跟进中继续维护学生。；|回访人：赵星火，回访时间：2025-10-31 18:42，回访内容：1 | BB62: 64239584 | BC62: 否 | BD62: 27考季 | BE62: 全年集训营 | BF62: 英语,政治 | BG62: 其他 | BH62: 国内高校-双非 | BI62: 是 | BL62: 报名
A63: 52 | B63: 北京大学部 | C63: 国内大学部 | D63: 刘书明 | E63: 114767021 | F63: 赵秋侠 | G63: 2025-06-17 11:25:47 | J63: 在职 | K63: 赵秋侠 | L63: 线上运营-抖音 | M63: 抖音 | O63: 赵秋侠 | P63: 2025-06-17 11:27:46 | Q63: 冯义卿 | R63: 赵星火 | S63: 28390043 | T63: 正常工单 | U63: 2025-06-17 11:42 | V63: A（六个月内有报课意向工单） | W63: 考研集训营 | X63: 在职 | Y63: 首都医科大学 | Z63: 临床医学院 | AA63: 临床医学 | AB63: 冯义卿 | AC63: 5689064 | AD63: 赵星火 | AE63: 2025-10-31 18:42 | AF63: 赵星火 | AG63: 2025-10-31 19:04 | AH63: 集训营 | AI63: KYQNJXY2701A | AJ63: 27考研全年集训营英语（基础） | AK63: 国内考试 | AM63: 5033.75 | AP63: 新签 | AQ63: 已交接 | AR63: BJWY25030q8UPI | AS63: BJWY5373463335 | AT63: KYQNJXY2701A0004 | AU63: 2025-10-31 | AW63: 回访人：赵星火，回访时间：2025-10-28 16:53，回访内容：给到课程辅导合同跟进中继续维护学生。；|回访人：赵星火，回访时间：2025-10-31 18:42，回访内容：1 | BB63: 64239584 | BC63: 否 | BD63: 27考季 | BE63: 全年集训营 | BF63: 英语,政治 | BG63: 其他 | BH63: 国内高校-双非 | BI63: 是 | BL63: 报名
A64: 208 | B64: 北京大学部 | C64: 国内大学部 | E64: 126945275 | G64: 2025-09-10 14:30:02 | H64: 【考博】 考季：26年 年级：在职 课程形式：线下考博一对一或者六级线下班课 女士在职，当老师，咨询考博英语一对一，考博英语包含六级内容，去年已经在新东方报了六级无忧计划线下学过，还想再报六级线下班和考博一对一，现在准备上课不方便接听，让加微信介绍，手机号是本人微信号。 ！！！辛苦前台客服查重分配，有去年的签约单-谢仕为；考博一对一和六级线下班课都要了解 | J64: 在职 | K64: 李涛 | L64: 线上运营-私域中台 | M64: 公众号 | Q64: 高原 | R64: 李涛 | S64: 30422639 | T64: 续费工单 | U64: 2025-10-14 17:16 | V64: A（六个月内有报课意向工单） | W64: 考博 | X64: 在职 | Y64: 毕业/在职 | Z64: 询问院系未告知 | AA64: 其他 | AB64: 高原 | AC64: 5676095 | AD64: 李涛 | AE64: 2025-10-14 17:21 | AF64: 李涛 | AG64: 2025-10-14 17:21 | AH64: 四六级 | AI64: WYS25047 | AJ64: 六级无忧计划 | AK64: 国内考试 | AM64: 6180 | AN64: 同科续费 | AP64: 续班 | AQ64: 已交接 | AR64: BJWY2101498uW2 | AS64: BJWY2095765425 | AT64: WYS250470040 | AU64: 2025-10-11 | AW64: 回访人：李涛，回访时间：2025-10-14 17:16，回访内容：转班 重新弄一下；|回访人：李涛，回访时间：2025-10-14 17:21，回访内容：报名 | BB64: 84749213 | BC64: 否 | BH64: 国内高校-双非 | BI64: 是 | BL64: 转出
A65: 247 | B65: 北京大学部 | C65: 国内大学部 | D65: 龚依萌 | E65: 129414910 | F65: 北京国内管理员 | G65: 2025-09-29 17:12:39 | H65: 资源录入来源：小表单 城市：北京市 市场活动id：412422 市场活动名称：新东方集团官微【新东方】资源 活动所属学校id：10000 活动所属学校名称：总公司 线索接收人邮箱：yangjun42@xdf.cn 线索接受人类型：自定义 表单信息：表单id81512、表单名(对内)：新东方集团官微【新东方】资源、表单名（对外）：新东方课程报名、创建人邮箱：wuyue38@xdf.cn、表单链接：pages/index/index.html?scene=81512,,ucwVUGil 备注：来源:小表单;姓名:龚依萌;意向课程: 【课程】考研、四六级、专升本、成人英语/北京/北京; 新老生: 在读老生; 提交链接:pages/index/index.html?scene=81512,,ucwVUGil;地理位置:北京市西城区什刹海街道1901 Cafe(西四店)西什库大街37号小区;渠道:新媒体运营/集团品牌官微 | I65: 2026财年小表单-新东方集团官微【新东方】资源 | J65: 未知 | K65: 杨欢欢 | L65: 线上运营-私域中台 | M65: 集团官微 | O65: 杨欢欢 | P65: 2025-09-29 18:54:45 | Q65: 龚依萌 | R65: 李涛 | S65: 30302946 | T65: 正常工单 | U65: 2025-09-30 15:21 | V65: A（六个月内有报课意向工单） | W65: 考研VIP,考研无忧计划,ACCA | X65: 大学已毕业 | Y65: 询问院校未告知 | Z65: 询问院系未告知 | AA65: 询问专业未告知 | AB65: 龚依萌 | AC65: 5643489 | AD65: 李涛 | AE65: 2025-10-03 14:00 | AF65: 李涛 | AG65: 2025-10-03 14:26 | AH65: 个性化 | AI65: LP1759471258459 | AJ65: 考研一对一伴学班（26考季） | AK65: 国内考试 | AM65: 18000 | AP65: 新签 | AQ65: 已交接 | AS65: XDF082105131725317 | AU65: 2025-10-03 | AW65: 回访人：李涛，回访时间：2025-09-30 15:21，回访内容：主要英语 去年英语65分，希望找经验丰富的老师，倾向一对一 推荐老师 想要10.1假期上课 微信发送试听课！；|回访人：李涛，回访时间：2025-10-01 16:31，回访内容：微信跟进中 ；|回访人：李涛，回访时间：2025-10-02 16:37，回访内容：选老师中 继续跟进！ | BB65: 51110842 | BC65: 否 | BD65: 26考季 | BE65: VIP - 伴学 | BF65: 英语 | BG65: 其他 | BH65: 国内高校-双非 | BI65: 是 | BO65: 小表单
A66: 115 | B66: 北京大学部 | C66: 国内大学部 | D66: 小谷 | E66: 131792932 | F66: 王朝群 | G66: 2025-10-22 00:53:48 | H66: 【王朝群】咨询考研英语辅导，今年考研 | J66: 大四 | K66: 谭悦 | L66: 线上运营-小红书 | M66: 小红书KOS | Q66: 谷子博 | R66: 谭悦 | S66: 30540435 | T66: 正常工单 | U66: 2025-10-22 19:26 | V66: A（六个月内有报课意向工单） | W66: 考研VIP | X66: 在职 | Y66: 中国社会科学院大学 | Z66: 社会学院 | AA66: 社会学 | AB66: 谷子博 | AC66: 5681185 | AD66: 谭悦 | AE66: 2025-10-22 20:12 | AF66: 谭悦 | AG66: 2025-10-22 20:17 | AH66: 个性化 | AI66: LP17611351751543 | AJ66: 考研一对一伴学班（26考季） | AK66: 国内考试 | AM66: 17500 | AP66: 新签 | AQ66: 已交接 | AS66: BJWY4469528121 | AU66: 2025-10-22 | AW66: 回访人：谭悦，回访时间：2025-10-22 19:26，回访内容：今年考，MPA，去年考过，社科大，164分， 英语一对一20小时，；|回访人：谭悦，回访时间：2025-10-22 20:12，回访内容：系统自动签约 | BB66: 86418545 | BC66: 否 | BD66: 26考季 | BE66: VIP - 伴学 | BF66: 英语 | BG66: 其他 | BH66: 国内高校-双非 | BI66: 是 | BO66: 市场
A67: 37 | B67: 北京大学部 | C67: 国内大学部 | D67: 未知 | E67: 129657037 | F67: 吕猛 | G67: 2025-10-07 15:41:56 | H67: 渠道录入来源：大众点评 事件名称：400电话 大众点评门店名称：新东方考研四六级(良乡大学城校区) 店铺绑定的校区：临时教学校区 店铺管理员邮箱：lvmeng2@xdf.cn 备注：2025-10-07 15:41:54,用户在大众点评新东方考研四六级(良乡大学城校区)呼入400电话 未接 | I67: 2026财年第5财月大众点评在线咨询 | K67: 赵星火 | L67: 线上运营-本地生活平台 | M67: 大众点评 | Q67: 管综水 | R67: 赵星火 | S67: 30352792 | T67: 正常工单 | U67: 2025-10-08 17:52 | V67: A（六个月内有报课意向工单） | W67: 考研VIP | X67: 在职 | Y67: 北京物资学院 | Z67: 外国语言与文化学院 | AA67: 商务英语 | AB67: 管综水 | AC67: 5645630 | AD67: 赵星火 | AE67: 2025-10-09 11:01 | AF67: 赵星火 | AG67: 2025-10-09 11:11 | AH67: 网课 | AI67: 17325106600 | AJ67: 考研规划（择校）热线Pro | AK67: 国内考试 | AM67: 399 | AP67: 新签 | AQ67: 无须交接 | AU67: 2025-10-09 | AW67: 回访人：赵星火，回访时间：2025-10-08 17:52，回访内容：表示关注择校跟进中继续维护学生情况 | BA67: 长期班 | BB67: 83933443 | BC67: 是 | BD67: 26考季 | BE67: VIP - 伴学 | BF67: 英语 | BG67: 其他 | BH67: 国内高校-双非 | BI67: 否 | BM67: 110966340 | BO67: 新媒体管家-点评
A68: 146 | B68: 北京大学部 | C68: 国内大学部 | D68: 无 | E68: 131289612 | F68: 程远 | G68: 2025-10-18 11:42:44 | H68: 花园桥直访； | J68: 未知 | K68: 赵星火 | L68: 直访 | M68: 直访 | Q68: 郭凯航 | R68: 赵星火 | S68: 30464118 | T68: 正常工单 | U68: 2025-10-18 13:27 | V68: A（六个月内有报课意向工单） | W68: 考研无忧计划 | X68: 大三 | Y68: 首都经济贸易大学 | Z68: 劳动经济学院 | AA68: 人力资源管理 | AB68: 郭凯航 | AC68: 5652324 | AD68: 赵星火 | AE68: 2025-10-18 13:57 | AF68: 赵星火 | AG68: 2025-10-18 13:57 | AH68: 无忧 | AI68: WYP27017 | AJ68: 考研政治无忧计划（27考研/强化） | AK68: 国内考试 | AM68: 3676.5 | AP68: 新签 | AQ68: 已交接 | AR68: WebReg | AS68: BJWY4033041835 | AT68: WYP270170031 | AU68: 2025-10-18 | AW68: 回访人：赵星火，回访时间：2025-10-18 13:27，回访内容：1；|回访人：赵星火，回访时间：2025-10-18 13:57，回访内容：1 | BB68: 86298103 | BC68: 否 | BD68: 27考季 | BE68: 无忧计划-早鸟 | BF68: 英语,政治,数学,专业课150 | BG68: 其他 | BH68: 国内高校-C9 | BI68: 是 | BL68: 报名 | BN68: 外地人本地大学(常规) | BO68: 客服
A69: 147 | B69: 北京大学部 | C69: 国内大学部 | D69: 无 | E69: 131289612 | F69: 程远 | G69: 2025-10-18 11:42:44 | H69: 花园桥直访； | J69: 未知 | K69: 赵星火 | L69: 直访 | M69: 直访 | Q69: 郭凯航 | R69: 赵星火 | S69: 30464118 | T69: 正常工单 | U69: 2025-10-18 13:27 | V69: A（六个月内有报课意向工单） | W69: 考研无忧计划 | X69: 大三 | Y69: 首都经济贸易大学 | Z69: 劳动经济学院 | AA69: 人力资源管理 | AB69: 郭凯航 | AC69: 5652324 | AD69: 赵星火 | AE69: 2025-10-18 13:57 | AF69: 赵星火 | AG69: 2025-10-18 13:57 | AH69: 无忧 | AI69: WYP27018 | AJ69: 考研政治无忧计划（27考研/冲刺） | AK69: 国内考试 | AM69: 4366.4 | AP69: 新签 | AQ69: 已交接 | AR69: WebReg | AS69: BJWY4033041835 | AT69: WYP270180031 | AU69: 2025-10-18 | AW69: 回访人：赵星火，回访时间：2025-10-18 13:27，回访内容：1；|回访人：赵星火，回访时间：2025-10-18 13:57，回访内容：1 | BB69: 86298103 | BC69: 否 | BD69: 27考季 | BE69: 无忧计划-早鸟 | BF69: 英语,政治,数学,专业课150 | BG69: 其他 | BH69: 国内高校-C9 | BI69: 是 | BL69: 报名 | BN69: 外地人本地大学(常规) | BO69: 客服
A70: 148 | B70: 北京大学部 | C70: 国内大学部 | D70: 无 | E70: 131289612 | F70: 程远 | G70: 2025-10-18 11:42:44 | H70: 花园桥直访； | J70: 未知 | K70: 赵星火 | L70: 直访 | M70: 直访 | Q70: 郭凯航 | R70: 赵星火 | S70: 30464118 | T70: 正常工单 | U70: 2025-10-18 13:27 | V70: A（六个月内有报课意向工单） | W70: 考研无忧计划 | X70: 大三 | Y70: 首都经济贸易大学 | Z70: 劳动经济学院 | AA70: 人力资源管理 | AB70: 郭凯航 | AC70: 5652324 | AD70: 赵星火 | AE70: 2025-10-18 13:57 | AF70: 赵星火 | AG70: 2025-10-18 13:57 | AH70: 无忧 | AI70: WYP27016 | AJ70: 考研政治无忧计划（27考研/基础） | AK70: 国内考试 | AM70: 6358.1 | AP70: 新签 | AQ70: 已交接 | AR70: WebReg | AS70: BJWY4033041835 | AT70: WYP270160031 | AU70: 2025-10-18 | AW70: 回访人：赵星火，回访时间：2025-10-18 13:27，回访内容：1；|回访人：赵星火，回访时间：2025-10-18 13:57，回访内容：1 | BB70: 86298103 | BC70: 否 | BD70: 27考季 | BE70: 无忧计划-早鸟 | BF70: 英语,政治,数学,专业课150 | BG70: 其他 | BH70: 国内高校-C9 | BI70: 是 | BL70: 报名 | BN70: 外地人本地大学(常规) | BO70: 客服
A71: 149 | B71: 北京大学部 | C71: 国内大学部 | D71: 无 | E71: 131289612 | F71: 程远 | G71: 2025-10-18 11:42:44 | H71: 花园桥直访； | J71: 未知 | K71: 赵星火 | L71: 直访 | M71: 直访 | Q71: 郭凯航 | R71: 赵星火 | S71: 30464118 | T71: 正常工单 | U71: 2025-10-18 13:27 | V71: A（六个月内有报课意向工单） | W71: 考研无忧计划 | X71: 大三 | Y71: 首都经济贸易大学 | Z71: 劳动经济学院 | AA71: 人力资源管理 | AB71: 郭凯航 | AC71: 5652324 | AD71: 赵星火 | AE71: 2025-10-18 13:57 | AF71: 赵星火 | AG71: 2025-10-18 13:57 | AH71: 无忧 | AI71: WYM27020 | AJ71: 考研数学无忧计划（27考研/强化） | AK71: 国内考试 | AM71: 6741.1 | AP71: 新签 | AQ71: 已交接 | AR71: WebReg | AS71: BJWY4033041835 | AT71: WYM270200012 | AU71: 2025-10-18 | AW71: 回访人：赵星火，回访时间：2025-10-18 13:27，回访内容：1；|回访人：赵星火，回访时间：2025-10-18 13:57，回访内容：1 | BB71: 86298103 | BC71: 否 | BD71: 27考季 | BE71: 无忧计划-早鸟 | BF71: 英语,政治,数学,专业课150 | BG71: 其他 | BH71: 国内高校-C9 | BI71: 是 | BL71: 报名 | BN71: 外地人本地大学(常规) | BO71: 客服
A72: 150 | B72: 北京大学部 | C72: 国内大学部 | D72: 无 | E72: 131289612 | F72: 程远 | G72: 2025-10-18 11:42:44 | H72: 花园桥直访； | J72: 未知 | K72: 赵星火 | L72: 直访 | M72: 直访 | Q72: 郭凯航 | R72: 赵星火 | S72: 30464118 | T72: 正常工单 | U72: 2025-10-18 13:27 | V72: A（六个月内有报课意向工单） | W72: 考研无忧计划 | X72: 大三 | Y72: 首都经济贸易大学 | Z72: 劳动经济学院 | AA72: 人力资源管理 | AB72: 郭凯航 | AC72: 5652324 | AD72: 赵星火 | AE72: 2025-10-18 13:57 | AF72: 赵星火 | AG72: 2025-10-18 13:57 | AH72: 无忧 | AI72: WYM27019 | AJ72: 考研数学无忧计划（27考研/基础） | AK72: 国内考试 | AM72: 4443 | AP72: 新签 | AQ72: 已交接 | AR72: WebReg | AS72: BJWY4033041835 | AT72: WYM270190012 | AU72: 2025-10-18 | AW72: 回访人：赵星火，回访时间：2025-10-18 13:27，回访内容：1；|回访人：赵星火，回访时间：2025-10-18 13:57，回访内容：1 | BB72: 86298103 | BC72: 否 | BD72: 27考季 | BE72: 无忧计划-早鸟 | BF72: 英语,政治,数学,专业课150 | BG72: 其他 | BH72: 国内高校-C9 | BI72: 是 | BL72: 报名 | BN72: 外地人本地大学(常规) | BO72: 客服
A73: 151 | B73: 北京大学部 | C73: 国内大学部 | D73: 无 | E73: 131289612 | F73: 程远 | G73: 2025-10-18 11:42:44 | H73: 花园桥直访； | J73: 未知 | K73: 赵星火 | L73: 直访 | M73: 直访 | Q73: 郭凯航 | R73: 赵星火 | S73: 30464118 | T73: 正常工单 | U73: 2025-10-18 13:27 | V73: A（六个月内有报课意向工单） | W73: 考研无忧计划 | X73: 大三 | Y73: 首都经济贸易大学 | Z73: 劳动经济学院 | AA73: 人力资源管理 | AB73: 郭凯航 | AC73: 5652324 | AD73: 赵星火 | AE73: 2025-10-18 13:57 | AF73: 赵星火 | AG73: 2025-10-18 13:57 | AH73: 无忧 | AI73: WYE27021 | AJ73: 考研英语无忧计划（27考研/英一冲刺） | AK73: 国内考试 | AM73: 4862.2 | AP73: 新签 | AQ73: 已交接 | AR73: WebReg | AS73: BJWY4033041835 | AT73: WYE270210016 | AU73: 2025-10-18 | AW73: 回访人：赵星火，回访时间：2025-10-18 13:27，回访内容：1；|回访人：赵星火，回访时间：2025-10-18 13:57，回访内容：1 | BB73: 86298103 | BC73: 否 | BD73: 27考季 | BE73: 无忧计划-早鸟 | BF73: 英语,政治,数学,专业课150 | BG73: 其他 | BH73: 国内高校-C9 | BI73: 是 | BL73: 报名 | BN73: 外地人本地大学(常规) | BO73: 客服
A74: 152 | B74: 北京大学部 | C74: 国内大学部 | D74: 无 | E74: 131289612 | F74: 程远 | G74: 2025-10-18 11:42:44 | H74: 花园桥直访； | J74: 未知 | K74: 赵星火 | L74: 直访 | M74: 直访 | Q74: 郭凯航 | R74: 赵星火 | S74: 30464118 | T74: 正常工单 | U74: 2025-10-18 13:27 | V74: A（六个月内有报课意向工单） | W74: 考研无忧计划 | X74: 大三 | Y74: 首都经济贸易大学 | Z74: 劳动经济学院 | AA74: 人力资源管理 | AB74: 郭凯航 | AC74: 5652324 | AD74: 赵星火 | AE74: 2025-10-18 13:57 | AF74: 赵星火 | AG74: 2025-10-18 13:57 | AH74: 无忧 | AI74: WYE27020 | AJ74: 考研英语无忧计划（27考研/英一强化） | AK74: 国内考试 | AM74: 6434.7 | AP74: 新签 | AQ74: 已交接 | AR74: WebReg | AS74: BJWY4033041835 | AT74: WYE270200016 | AU74: 2025-10-18 | AW74: 回访人：赵星火，回访时间：2025-10-18 13:27，回访内容：1；|回访人：赵星火，回访时间：2025-10-18 13:57，回访内容：1 | BB74: 86298103 | BC74: 否 | BD74: 27考季 | BE74: 无忧计划-早鸟 | BF74: 英语,政治,数学,专业课150 | BG74: 其他 | BH74: 国内高校-C9 | BI74: 是 | BL74: 报名 | BN74: 外地人本地大学(常规) | BO74: 客服
A75: 153 | B75: 北京大学部 | C75: 国内大学部 | D75: 无 | E75: 131289612 | F75: 程远 | G75: 2025-10-18 11:42:44 | H75: 花园桥直访； | J75: 未知 | K75: 赵星火 | L75: 直访 | M75: 直访 | Q75: 郭凯航 | R75: 赵星火 | S75: 30464118 | T75: 正常工单 | U75: 2025-10-18 13:27 | V75: A（六个月内有报课意向工单） | W75: 考研无忧计划 | X75: 大三 | Y75: 首都经济贸易大学 | Z75: 劳动经济学院 | AA75: 人力资源管理 | AB75: 郭凯航 | AC75: 5652324 | AD75: 赵星火 | AE75: 2025-10-18 13:57 | AF75: 赵星火 | AG75: 2025-10-18 13:57 | AH75: 无忧 | AI75: WYE27019 | AJ75: 考研英语无忧计划（27考研/基础） | AK75: 国内考试 | AM75: 4902.6 | AP75: 新签 | AQ75: 已交接 | AR75: WebReg | AS75: BJWY4033041835 | AT75: WYE270190037 | AU75: 2025-10-18 | AW75: 回访人：赵星火，回访时间：2025-10-18 13:27，回访内容：1；|回访人：赵星火，回访时间：2025-10-18 13:57，回访内容：1 | BB75: 86298103 | BC75: 否 | BD75: 27考季 | BE75: 无忧计划-早鸟 | BF75: 英语,政治,数学,专业课150 | BG75: 其他 | BH75: 国内高校-C9 | BI75: 是 | BL75: 报名 | BN75: 外地人本地大学(常规) | BO75: 客服
A76: 154 | B76: 北京大学部 | C76: 国内大学部 | D76: 无 | E76: 131289612 | F76: 程远 | G76: 2025-10-18 11:42:44 | H76: 花园桥直访； | J76: 未知 | K76: 赵星火 | L76: 直访 | M76: 直访 | Q76: 郭凯航 | R76: 赵星火 | S76: 30464118 | T76: 正常工单 | U76: 2025-10-18 13:27 | V76: A（六个月内有报课意向工单） | W76: 考研无忧计划 | X76: 大三 | Y76: 首都经济贸易大学 | Z76: 劳动经济学院 | AA76: 人力资源管理 | AB76: 郭凯航 | AC76: 5652324 | AD76: 赵星火 | AE76: 2025-10-18 13:57 | AF76: 赵星火 | AG76: 2025-10-18 13:57 | AH76: 无忧 | AI76: WYM27021 | AJ76: 考研数学无忧计划（27考研/冲刺） | AK76: 国内考试 | AM76: 5515.4 | AP76: 新签 | AQ76: 已交接 | AR76: WebReg | AS76: BJWY4033041835 | AT76: WYM270210012 | AU76: 2025-10-18 | AW76: 回访人：赵星火，回访时间：2025-10-18 13:27，回访内容：1；|回访人：赵星火，回访时间：2025-10-18 13:57，回访内容：1 | BB76: 86298103 | BC76: 否 | BD76: 27考季 | BE76: 无忧计划-早鸟 | BF76: 英语,政治,数学,专业课150 | BG76: 其他 | BH76: 国内高校-C9 | BI76: 是 | BL76: 报名 | BN76: 外地人本地大学(常规) | BO76: 客服
A77: 155 | B77: 北京大学部 | C77: 国内大学部 | D77: 无 | E77: 131289612 | F77: 程远 | G77: 2025-10-18 11:42:44 | H77: 花园桥直访； | J77: 未知 | K77: 赵星火 | L77: 直访 | M77: 直访 | Q77: 郭凯航 | R77: 赵星火 | S77: 30464118 | T77: 正常工单 | U77: 2025-10-18 13:27 | V77: A（六个月内有报课意向工单） | W77: 考研无忧计划 | X77: 大三 | Y77: 首都经济贸易大学 | Z77: 劳动经济学院 | AA77: 人力资源管理 | AB77: 郭凯航 | AC77: 5652324 | AD77: 赵星火 | AE77: 2025-10-18 13:57 | AF77: 赵星火 | AG77: 2025-10-18 13:57 | AH77: 无忧 | AI77: LP1760766045876 | AJ77: 考研初试专业课一对一（27考研/无忧30小时） | AK77: 国内考试 | AM77: 9000 | AP77: 新签 | AQ77: 已交接 | AR77: WebReg | AS77: BJWY4033041835 | AU77: 2025-10-18 | AW77: 回访人：赵星火，回访时间：2025-10-18 13:27，回访内容：1；|回访人：赵星火，回访时间：2025-10-18 13:57，回访内容：1 | BB77: 86298103 | BC77: 否 | BD77: 27考季 | BE77: 无忧计划-早鸟 | BF77: 英语,政治,数学,专业课150 | BG77: 其他 | BH77: 国内高校-C9 | BI77: 是 | BN77: 外地人本地大学(常规) | BO77: 客服
A78: 137 | B78: 北京大学部 | C78: 国内大学部 | D78: 酸酸 | E78: 131168343 | F78: 王朝群 | G78: 2025-10-17 09:33:19 | H78: 【王朝群】咨询考研英语➕政治 专业课一对一，全科【微信联系，不要电话】 | J78: 大四 | K78: 赵星火 | L78: 线上运营-小红书 | M78: 小红书KOS | Q78: 郭畑畑 | R78: 赵星火 | S78: 30459740 | T78: 正常工单 | U78: 2025-10-17 14:43 | V78: A（六个月内有报课意向工单） | W78: 考研专业课,考研无忧计划 | X78: 大四 | Y78: 中国矿业大学(北京) | Z78: 管理学院 | AA78: 行政管理 | AB78: 郭畑畑 | AC78: 5678833 | AD78: 赵星火 | AE78: 2025-10-18 19:39 | AF78: 赵星火 | AG78: 2025-10-18 19:40 | AH78: 无忧 | AI78: WYE27101 | AJ78: 考研英语无忧计划啄木鸟（27考研/基础） | AK78: 国内考试 | AM78: 4684 | AP78: 新签 | AQ78: 已交接 | AR78: BJWY22035556hl | AS78: BJWY1312993478 | AT78: WYE271010004 | AU78: 2025-10-18 | AW78: 回访人：赵星火，回访时间：2025-10-17 14:43，回访内容：明年考本校本专业，这边想要线上网课，都推荐中邀约面谈跟进中；|回访人：赵星火，回访时间：2025-10-18 16:10，回访内容：郭畑畑校区试听课沟通了，跟进学生情况看下课程考虑推荐知春路走读班中，关注人数和授课进度分班。；|回访人：赵星火，回访时间：2025-10-18 19:39，回访内容：1 | BB78: 86107632 | BC78: 否 | BD78: 27考季 | BE78: 无忧计划-啄木鸟 | BF78: 英语,政治,专业课300 | BH78: 国内高校-211 | BI78: 是 | BL78: 报名 | BN78: 本地人本地大学(常规) | BO78: 市场
A79: 138 | B79: 北京大学部 | C79: 国内大学部 | D79: 酸酸 | E79: 131168343 | F79: 王朝群 | G79: 2025-10-17 09:33:19 | H79: 【王朝群】咨询考研英语➕政治 专业课一对一，全科【微信联系，不要电话】 | J79: 大四 | K79: 赵星火 | L79: 线上运营-小红书 | M79: 小红书KOS | Q79: 郭畑畑 | R79: 赵星火 | S79: 30459740 | T79: 正常工单 | U79: 2025-10-17 14:43 | V79: A（六个月内有报课意向工单） | W79: 考研专业课,考研无忧计划 | X79: 大四 | Y79: 中国矿业大学(北京) | Z79: 管理学院 | AA79: 行政管理 | AB79: 郭畑畑 | AC79: 5678833 | AD79: 赵星火 | AE79: 2025-10-18 19:39 | AF79: 赵星火 | AG79: 2025-10-18 19:40 | AH79: 无忧 | AI79: WYE27104 | AJ79: 考研英语无忧计划啄木鸟（27考研/英一冲刺） | AK79: 国内考试 | AM79: 2284 | AP79: 新签 | AQ79: 已交接 | AR79: BJWY22035556hl | AS79: BJWY1312993478 | AT79: WYE271040003 | AU79: 2025-10-18 | AW79: 回访人：赵星火，回访时间：2025-10-17 14:43，回访内容：明年考本校本专业，这边想要线上网课，都推荐中邀约面谈跟进中；|回访人：赵星火，回访时间：2025-10-18 16:10，回访内容：郭畑畑校区试听课沟通了，跟进学生情况看下课程考虑推荐知春路走读班中，关注人数和授课进度分班。；|回访人：赵星火，回访时间：2025-10-18 19:39，回访内容：1 | BB79: 86107632 | BC79: 否 | BD79: 27考季 | BE79: 无忧计划-啄木鸟 | BF79: 英语,政治,专业课300 | BH79: 国内高校-211 | BI79: 是 | BL79: 报名 | BN79: 本地人本地大学(常规) | BO79: 市场
A80: 139 | B80: 北京大学部 | C80: 国内大学部 | D80: 酸酸 | E80: 131168343 | F80: 王朝群 | G80: 2025-10-17 09:33:19 | H80: 【王朝群】咨询考研英语➕政治 专业课一对一，全科【微信联系，不要电话】 | J80: 大四 | K80: 赵星火 | L80: 线上运营-小红书 | M80: 小红书KOS | Q80: 郭畑畑 | R80: 赵星火 | S80: 30459740 | T80: 正常工单 | U80: 2025-10-17 14:43 | V80: A（六个月内有报课意向工单） | W80: 考研专业课,考研无忧计划 | X80: 大四 | Y80: 中国矿业大学(北京) | Z80: 管理学院 | AA80: 行政管理 | AB80: 郭畑畑 | AC80: 5678833 | AD80: 赵星火 | AE80: 2025-10-18 19:39 | AF80: 赵星火 | AG80: 2025-10-18 19:40 | AH80: 无忧 | AI80: WYP27035 | AJ80: 考研政治无忧计划（27考研/强化） | AK80: 国内考试 | AM80: 3084 | AP80: 新签 | AQ80: 已交接 | AR80: BJWY22035556hl | AS80: BJWY1312993478 | AT80: WYP270350027 | AU80: 2025-10-18 | AW80: 回访人：赵星火，回访时间：2025-10-17 14:43，回访内容：明年考本校本专业，这边想要线上网课，都推荐中邀约面谈跟进中；|回访人：赵星火，回访时间：2025-10-18 16:10，回访内容：郭畑畑校区试听课沟通了，跟进学生情况看下课程考虑推荐知春路走读班中，关注人数和授课进度分班。；|回访人：赵星火，回访时间：2025-10-18 19:39，回访内容：1 | BB80: 86107632 | BC80: 否 | BD80: 27考季 | BE80: 无忧计划-啄木鸟 | BF80: 英语,政治,专业课300 | BH80: 国内高校-211 | BI80: 是 | BL80: 报名 | BN80: 本地人本地大学(常规) | BO80: 市场
A81: 140 | B81: 北京大学部 | C81: 国内大学部 | D81: 酸酸 | E81: 131168343 | F81: 王朝群 | G81: 2025-10-17 09:33:19 | H81: 【王朝群】咨询考研英语➕政治 专业课一对一，全科【微信联系，不要电话】 | J81: 大四 | K81: 赵星火 | L81: 线上运营-小红书 | M81: 小红书KOS | Q81: 郭畑畑 | R81: 赵星火 | S81: 30459740 | T81: 正常工单 | U81: 2025-10-17 14:43 | V81: A（六个月内有报课意向工单） | W81: 考研专业课,考研无忧计划 | X81: 大四 | Y81: 中国矿业大学(北京) | Z81: 管理学院 | AA81: 行政管理 | AB81: 郭畑畑 | AC81: 5678833 | AD81: 赵星火 | AE81: 2025-10-18 19:39 | AF81: 赵星火 | AG81: 2025-10-18 19:40 | AH81: 无忧 | AI81: WYP27034 | AJ81: 考研政治无忧计划（27考研/基础） | AK81: 国内考试 | AM81: 6584 | AP81: 新签 | AQ81: 已交接 | AR81: BJWY22035556hl | AS81: BJWY1312993478 | AT81: WYP270340027 | AU81: 2025-10-18 | AW81: 回访人：赵星火，回访时间：2025-10-17 14:43，回访内容：明年考本校本专业，这边想要线上网课，都推荐中邀约面谈跟进中；|回访人：赵星火，回访时间：2025-10-18 16:10，回访内容：郭畑畑校区试听课沟通了，跟进学生情况看下课程考虑推荐知春路走读班中，关注人数和授课进度分班。；|回访人：赵星火，回访时间：2025-10-18 19:39，回访内容：1 | BB81: 86107632 | BC81: 否 | BD81: 27考季 | BE81: 无忧计划-啄木鸟 | BF81: 英语,政治,专业课300 | BH81: 国内高校-211 | BI81: 是 | BL81: 报名 | BN81: 本地人本地大学(常规) | BO81: 市场
A82: 141 | B82: 北京大学部 | C82: 国内大学部 | D82: 酸酸 | E82: 131168343 | F82: 王朝群 | G82: 2025-10-17 09:33:19 | H82: 【王朝群】咨询考研英语➕政治 专业课一对一，全科【微信联系，不要电话】 | J82: 大四 | K82: 赵星火 | L82: 线上运营-小红书 | M82: 小红书KOS | Q82: 郭畑畑 | R82: 赵星火 | S82: 30459740 | T82: 正常工单 | U82: 2025-10-17 14:43 | V82: A（六个月内有报课意向工单） | W82: 考研专业课,考研无忧计划 | X82: 大四 | Y82: 中国矿业大学(北京) | Z82: 管理学院 | AA82: 行政管理 | AB82: 郭畑畑 | AC82: 5678833 | AD82: 赵星火 | AE82: 2025-10-18 19:39 | AF82: 赵星火 | AG82: 2025-10-18 19:40 | AH82: 无忧 | AI82: WYP27036 | AJ82: 考研政治无忧计划（27考研/冲刺） | AK82: 国内考试 | AM82: 3984 | AP82: 新签 | AQ82: 已交接 | AR82: BJWY22035556hl | AS82: BJWY1312993478 | AT82: WYP270360027 | AU82: 2025-10-18 | AW82: 回访人：赵星火，回访时间：2025-10-17 14:43，回访内容：明年考本校本专业，这边想要线上网课，都推荐中邀约面谈跟进中；|回访人：赵星火，回访时间：2025-10-18 16:10，回访内容：郭畑畑校区试听课沟通了，跟进学生情况看下课程考虑推荐知春路走读班中，关注人数和授课进度分班。；|回访人：赵星火，回访时间：2025-10-18 19:39，回访内容：1 | BB82: 86107632 | BC82: 否 | BD82: 27考季 | BE82: 无忧计划-啄木鸟 | BF82: 英语,政治,专业课300 | BH82: 国内高校-211 | BI82: 是 | BL82: 报名 | BN82: 本地人本地大学(常规) | BO82: 市场
A83: 142 | B83: 北京大学部 | C83: 国内大学部 | D83: 酸酸 | E83: 131168343 | F83: 王朝群 | G83: 2025-10-17 09:33:19 | H83: 【王朝群】咨询考研英语➕政治 专业课一对一，全科【微信联系，不要电话】 | J83: 大四 | K83: 赵星火 | L83: 线上运营-小红书 | M83: 小红书KOS | Q83: 郭畑畑 | R83: 赵星火 | S83: 30459740 | T83: 正常工单 | U83: 2025-10-17 14:43 | V83: A（六个月内有报课意向工单） | W83: 考研专业课,考研无忧计划 | X83: 大四 | Y83: 中国矿业大学(北京) | Z83: 管理学院 | AA83: 行政管理 | AB83: 郭畑畑 | AC83: 5678833 | AD83: 赵星火 | AE83: 2025-10-18 19:39 | AF83: 赵星火 | AG83: 2025-10-18 19:40 | AH83: 无忧 | AI83: WYE27103 | AJ83: 考研英语无忧计划啄木鸟（27考研/英一强化） | AK83: 国内考试 | AM83: 6680 | AP83: 新签 | AQ83: 已交接 | AR83: BJWY22035556hl | AS83: BJWY1312993478 | AT83: WYE271030003 | AU83: 2025-10-18 | AW83: 回访人：赵星火，回访时间：2025-10-17 14:43，回访内容：明年考本校本专业，这边想要线上网课，都推荐中邀约面谈跟进中；|回访人：赵星火，回访时间：2025-10-18 16:10，回访内容：郭畑畑校区试听课沟通了，跟进学生情况看下课程考虑推荐知春路走读班中，关注人数和授课进度分班。；|回访人：赵星火，回访时间：2025-10-18 19:39，回访内容：1 | BB83: 86107632 | BC83: 否 | BD83: 27考季 | BE83: 无忧计划-啄木鸟 | BF83: 英语,政治,专业课300 | BH83: 国内高校-211 | BI83: 是 | BL83: 报名 | BN83: 本地人本地大学(常规) | BO83: 市场
A84: 169 | B84: 北京大学部 | C84: 国内大学部 | E84: 77791747 | G84: 2024-06-19 11:34:43 | H84: 13552721008死单激活 | J84: 未知 | K84: 谭悦 | L84: 线上运营-投放 | M84: 百度投放 | Q84: 贺其永歌 | R84: 谭悦 | S84: 30362493 | T84: 续费工单 | U84: 2025-10-10 13:23 | V84: A（六个月内有报课意向工单） | W84: 六级 | X84: 大四 | Y84: 首都师范大学 | Z84: 文学院 | AA84: 汉语言文学 | AB84: 贺其永歌 | AC84: 5676995 | AD84: 谭悦 | AE84: 2025-10-16 11:47 | AF84: 谭悦 | AG84: 2025-10-16 11:49 | AH84: 四六级 | AI84: LP1760586462394 | AJ84: 六级一对一伴学班 | AK84: 国内考试 | AM84: 8500 | AP84: 续班 | AQ84: 已交接 | AS84: BJWY9822893615 | AU84: 2025-10-16 | AW84: 回访人：谭悦，回访时间：2025-10-10 13:23，回访内容：续费一对一；|回访人：谭悦，回访时间：2025-10-10 19:17，回访内容：微信跟进中，一对一续费 ；|回访人：谭悦，回访时间：2025-10-13 12:42，回访内容：孩子不想上课呢， 再等等吧 ；|回访人：谭悦，回访时间：2025-10-16 11:47，回访内容：系统自动签约 | BB84: 53001132 | BC84: 否 | BD84: 25上考季 | BE84: 六级无忧计划 | BH84: 国内高校-双一流(非985/211) | BI84: 是 | BN84: 本地人本地大学(常规)
A85: 131 | B85: 北京大学部 | C85: 国内大学部 | D85: 贺暄恒 | E85: 131492196 | F85: 余韵 | G85: 2025-10-20 12:37:19 | H85: 续费原因：老师好，学员正在和家长沟通续费；该学生为保护期内续费，原顾问：国内大学部-谭悦(tanyue9@xdf.cn) | J85: 大四 | K85: 谭悦 | L85: 转介绍 | M85: 学管续费推荐 | N85: 余韵yuyun7@xdf.cn | Q85: 贺暄恒 | R85: 谭悦 | S85: 30434200 | T85: 续费工单 | U85: 2025-10-20 17:39 | V85: A（六个月内有报课意向工单） | W85: 考研VIP | X85: 大四 | Y85: 北京建筑大学 | Z85: 建筑与城市规划学院 | AA85: 建筑学 | AB85: 贺暄恒 | AC85: 5653926 | AD85: 谭悦 | AE85: 2025-10-20 19:26 | AF85: 谭悦 | AG85: 2025-10-20 19:28 | AH85: 无忧 | AI85: LP1760959607903 | AJ85: 26考研一对一伴学（无忧） | AK85: 国内考试 | AM85: 15500 | AO85: 余韵 | AP85: 续班 | AQ85: 已交接 | AS85: BJWY9142571360 | AU85: 2025-10-20 | AW85: 回访人：谭悦，回访时间：2025-10-20 17:39，回访内容：续费跟进 ；|回访人：谭悦，回访时间：2025-10-20 19:26，回访内容：系统自动签约 | BB85: 66477823 | BC85: 否 | BD85: 26考季 | BE85: VIP - 伴学 | BF85: 英语,数学 | BG85: 其他 | BH85: 国内高校-双非 | BI85: 是 | BN85: 本地人本地大学(常规) | BO85: 学管续费推荐
A86: 183 | B86: 北京大学部 | C86: 国内大学部 | D86: Gyjymms戒赌版 | E86: 130323622 | F86: 崔佳慧 | G86: 2025-10-11 19:50:44 | H86: 渠道录入来源：小红书 事件名称：私信留资 小红书账号id：659bd1020000000022000003 小红书账号名称：北京新东方考研一对一咨询 广告投放账号名称：北京新东方考研一对一咨询 活动所属学校id：108 活动所属学校名称：北京大学事业部 统一活动id：2822543 统一活动名称：北京大学事业部25年10月小红书专业号投放 渠道名称：网络营销-小红书-专业号投放 线索创建人邮箱：cuijiahui2@xdf.cn 资源跟进人邮箱：cuijiahui2@xdf.cn 备注：用户地区是【北京市北京市】，在【2025-10-11 19:48:39】留资，私信通线索标签为【留客资】，来源于【北京新东方考研一对一咨询】投放账户，意向项目是【考研/考博】，留资笔记是【】，备注【-】 | I86: 2026财年第5财月小红书 | J86: 未知 | K86: 李涛 | L86: 线上运营-小红书 | M86: 小红书 | Q86: 胡钰彬 | R86: 李涛 | S86: 30372903 | T86: 正常工单 | U86: 2025-10-12 11:30 | V86: B（需长时间跟单或只需要规划） | W86: 考研VIP | X86: 大四 | Y86: 陕西师范大学 | Z86: 化学与材料科学学院 | AA86: 材料化学 | AB86: 胡钰彬 | AC86: 5649336 | AD86: 李涛 | AE86: 2025-10-13 18:42 | AF86: 李涛 | AG86: 2025-10-13 18:44 | AH86: 个性化 | AI86: LP1760352166829 | AJ86: 考研一对一伴学班（26考季） | AK86: 国内考试 | AM86: 33200 | AP86: 新签 | AQ86: 已交接 | AS86: BJWY6319169391 | AU86: 2025-10-13 | AW86: 回访人：李涛，回访时间：2025-10-12 11:30，回访内容：国科大 化学专硕！ 材料与化工！现在临时换的专业 现在比较着急 主要是补习数学2 微信发老师介绍 资料！；|回访人：李涛，回访时间：2025-10-13 15:49，回访内容：下午来魏公村校区面谈！；|回访人：李涛，回访时间：2025-10-13 18:42，回访内容：系统自动签约 | BB86: 85922702 | BC86: 否 | BD86: 26考季 | BE86: VIP - 伴学 | BF86: 英语 | BG86: 其他 | BH86: 国内高校-211 | BI86: 是 | BN86: 本地人本地大学(常规) | BO86: 小红书
A87: 27 | B87: 北京大学部 | C87: 国内大学部 | E87: 121258774 | G87: 2025-07-30 12:45:19 | H87: 续费原因：学生决定考浙江大学，辛苦联系黄禹淇的妈妈收取一下升级费3000；该学生为保护期内续费，原顾问：国内大学部-谭悦(tanyue9@xdf.cn) | J87: 大四 | K87: 谭悦 | L87: 转介绍 | M87: 学管续费推荐 | Q87: 黄禹淇 | R87: 谭悦 | S87: 30447223 | T87: 续费工单 | U87: 2025-10-15 10:37 | V87: A（六个月内有报课意向工单） | W87: 考研无忧计划 | X87: 大四 | Y87: 北京交通大学 | Z87: 机械与电子控制工程学院 | AA87: 机械工程 | AB87: 黄禹淇 | AC87: 5676319 | AD87: 谭悦 | AE87: 2025-10-15 10:54 | AF87: 谭悦 | AG87: 2025-10-15 11:10 | AH87: 无忧 | AI87: WYB250052 | AJ87: 考研无忧计划（黄禹淇） | AK87: 国内考试 | AM87: 296.5 | AN87: 同科续费 | AP87: 续班 | AQ87: 无须交接 | AR87: BJWY2011wXCx1W | AS87: BJWY4049653605 | AT87: WYB2500520001 | AU87: 2025-10-15 | AW87: 回访人：谭悦，回访时间：2025-10-15 10:37，回访内容：1；|回访人：谭悦，回访时间：2025-10-15 10:54，回访内容：1 | BB87: 60647114 | BC87: 否 | BD87: 26考季 | BE87: 无忧计划-啄木鸟 | BF87: 英语 | BH87: 国内高校-211 | BI87: 否 | BL87: 报名 | BN87: 本地人本地大学(常规)
A88: 120 | B88: 北京大学部 | C88: 国内大学部 | E88: 116226230 | G88: 2025-06-25 16:30:11 | H88: 续费原因：咨询考研课程 ；该学生为保护期内续费，原顾问：国内大学部-赵星火(zhaoxinghuo@xdf.cn) | J88: 大三 | K88: 赵星火 | L88: 转介绍 | M88: 学管续费推荐 | Q88: 霍盈杉 | R88: 赵星火 | S88: 30437092 | T88: 续费工单 | U88: 2025-10-22 13:54 | V88: A（六个月内有报课意向工单） | W88: 考研VIP | X88: 大四 | Y88: 保定理工学院 | Z88: 资源与工程技术学院 | AA88: 土地资源管理 | AB88: 霍盈杉 | AC88: 5654858 | AD88: 赵星火 | AE88: 2025-10-22 14:38 | AF88: 赵星火 | AG88: 2025-10-22 14:41 | AH88: 集训营 | AI88: LP1761115120730 | AJ88: 26考研一对一伴学（定制/集训） | AK88: 国内考试 | AM88: 7200 | AP88: 续班 | AQ88: 已交接 | AS88: BJWY9038592627 | AU88: 2025-10-22 | AW88: 回访人：赵星火，回访时间：2025-10-22 13:54，回访内容：1；|回访人：赵星火，回访时间：2025-10-22 14:38，回访内容：系统自动签约 | BB88: 38346789 | BC88: 否 | BD88: 26考季 | BE88: VIP - 伴学 | BF88: 英语 | BH88: 国内高校-双非 | BI88: 是 | BN88: 外地人外地大学(常规)
A89: 229 | B89: 北京大学部 | C89: 国内大学部 | D89: 姜钰峰 | E89: 104049670 | F89: 李小龙(离职) | G89: 2025-05-28 16:47:43 | H89: 续费原因：学生想咨询四级翻译部分，辛苦转给星火老师；该学生为保护期内续费，原顾问：国内大学部-赵星火(zhaoxinghuo@xdf.cn) | J89: 大二 | K89: 赵星火 | L89: 转介绍 | M89: 学管续费推荐 | N89: 李小龙(离职)lixiaolong25_lz@xdf.cn | Q89: 姜钰峰 | R89: 赵星火 | S89: 27949111 | T89: 续费工单 | U89: 2025-05-28 17:18 | V89: A（六个月内有报课意向工单） | W89: 四级 | X89: 大二 | Y89: 首都师范大学科德学院 | Z89: 传媒学院 | AA89: 广播电视编导（新闻编导） | AB89: 姜钰峰 | AC89: 5645653 | AD89: 赵星火 | AE89: 2025-10-09 11:16 | AF89: 赵星火 | AG89: 2025-10-11 18:41 | AH89: 四六级 | AI89: LP1759979789177 | AJ89: 四级一对一（30H） | AK89: 国内考试 | AM89: 24800 | AO89: 李小龙(离职) | AP89: 续班 | AQ89: 已交接 | AS89: BJWY1772110556 | AU89: 2025-10-09 | AW89: 回访人：赵星火，回访时间：2025-10-03 21:33，回访内容：假期休息上班回访；|回访人：赵星火，回访时间：2025-10-05 22:43，回访内容：假期休息上班回放；|回访人：赵星火，回访时间：2025-10-06 17:04，回访内容：回访学生现在的课程考虑给到节假日祝福 | BB89: 45460659 | BC89: 否 | BD89: 25上考季 | BE89: 四级一对一 | BH89: 国内高校-双非 | BI89: 是 | BN89: 本地人本地大学(常规) | BO89: 学管续费推荐
A90: 204 | B90: 北京大学部 | C90: 国内大学部 | E90: 103700641 | G90: 2025-05-25 18:57:40 | H90: 李文萱+liwenxuan3@xdf.cn+ID+国际教育培训事业部-国际教育北京中心-运营管理部-运营中心-魏公村分中心 | J90: 大三 | K90: 谭悦 | L90: 转介绍 | M90: 内部员工推荐 | Q90: 焦新婷 | R90: 谭悦 | S90: 30373516 | T90: 续费工单 | U90: 2025-10-12 13:33 | V90: A（六个月内有报课意向工单） | W90: 考研VIP | X90: 大四 | Y90: 北京信息科技大学 | Z90: 经济管理学院 | AA90: 质量管理工程 | AB90: 焦新婷 | AC90: 5648200 | AD90: 谭悦 | AE90: 2025-10-12 13:38 | AF90: 谭悦 | AG90: 2025-10-12 13:38 | AH90: 个性化 | AI90: LP1760247512788 | AJ90: 考研一对一伴学班（26考季） | AK90: 国内考试 | AM90: 17500 | AO90: 李文萱+liwenxuan3@xdf.cn+ID+国际教育培训事业部-国际教育北京中心-运营管理部-运营中心-魏公村分中心 | AP90: 续班 | AQ90: 已交接 | AS90: BJWY6585769297 | AU90: 2025-10-12 | AW90: 回访人：谭悦，回访时间：2025-10-12 13:33，回访内容：1；|回访人：谭悦，回访时间：2025-10-12 13:38，回访内容：系统自动签约 | BB90: 30893093 | BC90: 否 | BD90: 26考季 | BE90: VIP - 伴学 | BF90: 英语,管综 | BH90: 国内高校-双非 | BI90: 是 | BN90: 本地人本地大学(常规)
A91: 102 | B91: 北京大学部 | C91: 国内大学部 | D91: 未知 | E91: 132001704 | F91: 吕猛 | G91: 2025-10-23 10:26:16 | H91: 准备考博，了解考研英语和考博英语 渠道录入来源：大众点评 事件名称：400电话 大众点评门店名称：新东方考研四六级(魏公村校区) 店铺绑定的校区：魏公村北京国际大厦校区 店铺管理员邮箱：lvmeng2@xdf.cn 备注：2025-10-23 10:26:08,用户在大众点评新东方考研四六级(魏公村校区)呼入400电话 已接 | I91: 2026财年第5财月大众点评在线咨询 | J91: 研究生以上 | K91: 李涛 | L91: 线上运营-本地生活平台 | M91: 大众点评 | Q91: 柯宇 | R91: 李涛 | S91: 30541910 | T91: 正常工单 | U91: 2025-10-23 11:50 | V91: A（六个月内有报课意向工单） | W91: 考博,考研VIP | X91: 研究生以上 | Y91: 中央戏剧学院 | Z91: 表演系 | AA91: 话剧影视表演 | AB91: 柯宇 | AC91: 5681787 | AD91: 李涛 | AE91: 2025-10-23 15:50 | AF91: 李涛 | AG91: 2025-10-23 15:59 | AH91: 四六级 | AI91: WYS25043 | AJ91: 六级无忧计划 | AK91: 国内考试 | AM91: 6180 | AP91: 新签 | AQ91: 已交接 | AR91: WebReg | AS91: BJWY2838541819 | AT91: WYS250430059 | AU91: 2025-10-23 | AW91: 回访人：李涛，回访时间：2025-10-23 11:50，回访内容：计划明年博士考试 英语基础不好 英国留学回来的，学艺术的，托福前年考试98分，近一年没有学过阅读写作，考本科院校的博士，完型，写作，阅读，听学姐说考博英语和国内英一难度差不多！中央戏剧大学 本科，研究生在国外！；|回访人：李涛，回访时间：2025-10-23 15:50，回访内容：报名了 | BB91: 86536689 | BC91: 否 | BD91: 25考季 | BE91: VIP - 伴学 | BF91: 英语 | BG91: 其他 | BH91: 国内高校-双一流(非985/211) | BI91: 是 | BL91: 报名 | BO91: 新媒体管家-点评
A92: 127 | B92: 北京大学部 | C92: 国内大学部 | D92: 雷才利 | E92: 131536389 | F92: 陈晶 | G92: 2025-10-21 09:25:41 | H92: 续费原因：二战一对一，个性化谭悦；该学生为保护期外续费，原顾问部门：国内大学部 | J92: 大学已毕业 | K92: 谭悦 | L92: 转介绍 | M92: 学管续费推荐 | N92: 陈晶chenjing171@xdf.cn | Q92: 雷才利 | R92: 谭悦 | S92: 30502255 | T92: 续费工单 | U92: 2025-10-21 10:40 | V92: A（六个月内有报课意向工单） | W92: 考研VIP | X92: 大学已毕业 | Y92: 华中农业大学 | Z92: 园艺林学学院 | AA92: 风景园林 | AB92: 雷才利 | AC92: 5567033 | AD92: 谭悦 | AE92: 2025-10-21 11:33 | AF92: 谭悦 | AG92: 2025-10-21 11:40 | AH92: 个性化 | AI92: LP1761017597211 | AJ92: 考研一对一伴学班（定制/26考季） | AK92: 国内考试 | AM92: 12000 | AO92: 陈晶 | AP92: 续班 | AQ92: 已交接 | AS92: BJWY7202042206 | AU92: 2025-10-21 | AW92: 回访人：谭悦，回访时间：2025-10-21 10:40，回访内容：1；|回访人：谭悦，回访时间：2025-10-21 11:33，回访内容：系统自动签约 | BB92: 46040906 | BC92: 否 | BD92: 26考季 | BE92: VIP - 伴学 | BF92: 英语 | BG92: 其他 | BH92: 国内高校-211 | BI92: 是 | BO92: 学管续费推荐
A93: 181 | B93: 北京大学部 | C93: 国内大学部 | D93: 黎桐钰 | E93: 130659730 | F93: 黄小妹 | G93: 2025-10-14 11:44:11 | H93: 续费原因：续一对一；该学生为保护期内续费，原顾问：国内大学部-张乐(zhangle33@xdf.cn) | J93: 大四 | K93: 张乐 | L93: 转介绍 | M93: 学管续费推荐 | N93: 黄小妹huangxiaomei7@xdf.cn | Q93: 黎桐钰 | R93: 张乐 | S93: 30473214 | T93: 续费工单 | U93: 2025-10-14 17:01 | V93: A（六个月内有报课意向工单） | W93: 考研VIP | X93: 大四 | Y93: 中央财经大学 | Z93: 金融学院 | AA93: 金融学 | AB93: 黎桐钰 | AC93: 5565240 | AD93: 赵星火 | AE93: 2025-10-14 17:05 | AF93: 张乐 | AG93: 2025-10-14 17:06 | AH93: 无忧 | AK93: 国内考试 | AM93: 5750 | AO93: 黄小妹 | AP93: 分单 | AQ93: 已交接 | AS93: BJWY8528951390 | AW93: 回访人：张乐，回访时间：2025-10-14 17:01，回访内容：续费一对一；|回访人：张乐，回访时间：2025-10-14 17:05，回访内容：系统自动签约 | BB93: 41763277 | BC93: 否 | BD93: 26考季 | BE93: VIP - 伴学 | BF93: 英语 | BG93: 其他 | BH93: 国内高校-211 | BI93: 否 | BJ93: 辛苦黄小妹老师排课 | BN93: 本地人本地大学(常规) | BO93: 学管续费推荐
A94: 180 | B94: 北京大学部 | C94: 国内大学部 | D94: 李嘉译 | E94: 130536818 | F94: 余韵 | G94: 2025-10-13 17:09:35 | H94: 续费原因：老师好，学生有政治英语的续费意向~；该学生为保护期内续费，原顾问：国内大学部-谭悦(tanyue9@xdf.cn) | J94: 大学已毕业 | K94: 谭悦 | L94: 转介绍 | M94: 学管续费推荐 | N94: 余韵yuyun7@xdf.cn | Q94: 李嘉译 | R94: 谭悦 | S94: 30381433 | T94: 续费工单 | U94: 2025-10-13 21:59 | V94: A（六个月内有报课意向工单） | W94: 考研VIP | X94: 大学已毕业 | Y94: 天津音乐学院 | Z94: 舞蹈学系 | AA94: 舞蹈表演 | AB94: 李嘉译 | AC94: 5649663 | AD94: 谭悦 | AE94: 2025-10-14 14:38 | AF94: 谭悦 | AG94: 2025-10-14 14:39 | AH94: 无忧 | AI94: LP1760423926563 | AJ94: 26考研一对一伴学（20h/无忧） | AK94: 国内考试 | AM94: 16500 | AO94: 余韵 | AP94: 续班 | AQ94: 已交接 | AS94: BJWY6350503751 | AU94: 2025-10-14 | AW94: 回访人：谭悦，回访时间：2025-10-13 21:59，回访内容：续费 ；|回访人：谭悦，回访时间：2025-10-14 14:38，回访内容：系统自动签约 | BB94: 64770845 | BC94: 否 | BD94: 26考季 | BE94: VIP - 伴学 | BF94: 英语,政治 | BG94: 其他 | BH94: 国内高校-双非 | BI94: 是 | BO94: 学管续费推荐
A95: 88 | B95: 北京大学部 | C95: 国内大学部 | D95: 句号 | E95: 131836011 | F95: 王朝群 | G95: 2025-10-22 12:00:39 | H95: 【王朝群】咨询计算机考研辅导，22408，一对一 | J95: 大四 | K95: 李涛 | L95: 线上运营-小红书 | M95: 小红书KOS | Q95: 李书范 | R95: 李涛 | S95: 30510750 | T95: 正常工单 | U95: 2025-10-22 13:10 | V95: A（六个月内有报课意向工单） | W95: 考研VIP | X95: 大四 | Y95: 齐鲁工业大学 | Z95: 计算机科学与技术学院 | AA95: 计算机科学与技术 | AB95: 李书范 | AC95: 5657048 | AD95: 李涛 | AE95: 2025-10-25 12:35 | AF95: 李涛 | AG95: 2025-10-25 12:37 | AH95: 个性化 | AI95: LP1761366955652 | AJ95: 考研一对一伴学班（26考季） | AK95: 国内考试 | AM95: 10300 | AP95: 新签 | AQ95: 已交接 | AS95: BJWY7826064927 | AU95: 2025-10-25 | AW95: 回访人：李涛，回访时间：2025-10-22 13:10，回访内容：给哥哥咨询 考安徽工业大学 电科！想要线上授课 需要辅导一下英语和408 加微信沟通！；|回访人：李涛，回访时间：2025-10-23 16:26，回访内容：电话沟通 给新的课程方案！跟家里人在沟通一下！；|回访人：李涛，回访时间：2025-10-24 14:20，回访内容：明天早上来校区沟通一下！；|回访人：李涛，回访时间：2025-10-25 12:35，回访内容：系统自动签约 | BB95: 86447793 | BC95: 否 | BD95: 26考季 | BE95: VIP - 伴学 | BF95: 计算机 | BG95: 计算机 | BH95: 国内高校-211 | BI95: 是 | BN95: 本地人本地大学(常规) | BO95: 市场
A96: 89 | B96: 北京大学部 | C96: 国内大学部 | D96: 句号 | E96: 131836011 | F96: 王朝群 | G96: 2025-10-22 12:00:39 | H96: 【王朝群】咨询计算机考研辅导，22408，一对一 | J96: 大四 | K96: 李涛 | L96: 线上运营-小红书 | M96: 小红书KOS | Q96: 李书范 | R96: 李涛 | S96: 30510750 | T96: 正常工单 | U96: 2025-10-22 13:10 | V96: A（六个月内有报课意向工单） | W96: 考研VIP | X96: 大四 | Y96: 齐鲁工业大学 | Z96: 计算机科学与技术学院 | AA96: 计算机科学与技术 | AB96: 李书范 | AC96: 5657048 | AD96: 李涛 | AE96: 2025-10-25 12:35 | AF96: 李涛 | AG96: 2025-10-25 12:37 | AH96: 个性化 | AI96: LP1761366967655 | AJ96: 考研初试专业课一对一（26考研/30小时） | AK96: 国内考试 | AM96: 18800 | AP96: 新签 | AQ96: 已交接 | AS96: BJWY7826064927 | AU96: 2025-10-25 | AW96: 回访人：李涛，回访时间：2025-10-22 13:10，回访内容：给哥哥咨询 考安徽工业大学 电科！想要线上授课 需要辅导一下英语和408 加微信沟通！；|回访人：李涛，回访时间：2025-10-23 16:26，回访内容：电话沟通 给新的课程方案！跟家里人在沟通一下！；|回访人：李涛，回访时间：2025-10-24 14:20，回访内容：明天早上来校区沟通一下！；|回访人：李涛，回访时间：2025-10-25 12:35，回访内容：系统自动签约 | BB96: 86447793 | BC96: 否 | BD96: 26考季 | BE96: VIP - 伴学 | BF96: 计算机 | BG96: 计算机 | BH96: 国内高校-211 | BI96: 是 | BN96: 本地人本地大学(常规) | BO96: 市场
A97: 23 | B97: 北京大学部 | C97: 国内大学部 | E97: 59580329 | G97: 2023-09-05 07:09:00 | H97: 性别：女 院校：北华大学 年级：大三 生源渠道：顾问转介绍 推荐人：星星 咨询课程：四级班课 辛苦老师流转赵星火 | J97: 大三 | K97: 赵星火 | L97: 转介绍 | M97: 顾问转介绍-其他(不返现) | Q97: 李蔚彤 | R97: 赵星火 | S97: 30464456 | T97: 续费工单 | U97: 2025-10-18 14:25 | V97: A（六个月内有报课意向工单） | W97: 考研VIP | X97: 大学已毕业 | Y97: 北华大学 | Z97: 经济管理学院 | AA97: 会计学 | AB97: 李蔚彤 | AC97: 5678441 | AD97: 赵星火 | AE97: 2025-10-18 14:25 | AF97: 赵星火 | AG97: 2025-10-18 14:26 | AH97: 网课 | AI97: 83044292813 | AJ97: 2026考研专业课定制一对一（10h）A班 | AK97: 国内考试 | AM97: 4000 | AO97: 星星 | AP97: 续班 | AQ97: 无须交接 | AU97: 2025-10-18 | AW97: 回访人：赵星火，回访时间：2025-10-18 14:25，回访内容：1；|回访人：赵星火，回访时间：2025-10-18 14:25，回访内容：1 | BA97: 长期班 | BB97: 48178531 | BC97: 是 | BD97: 26考季 | BE97: VIP - 伴学 | BH97: 国内高校-C9 | BI97: 否 | BM97: 105463129 | BN97: 本地人本地大学(常规)
A98: 28 | B98: 北京大学部 | C98: 国内大学部 | D98: shady | E98: 130647915 | F98: 王朝群 | G98: 2025-10-14 12:48:36 | H98: 【王朝群】咨询考研一对一，今年考研 | J98: 大四 | K98: 李涛 | L98: 线上运营-小红书 | M98: 小红书KOS | Q98: 李宇超 | R98: 李涛 | S98: 30421917 | T98: 正常工单 | U98: 2025-10-14 13:55 | V98: A（六个月内有报课意向工单） | W98: 考研VIP | X98: 大学已毕业 | Y98: 保定学院 | Z98: 外语教育与国际商务学院 | AA98: 英语 | AB98: 李宇超 | AC98: 5650139 | AD98: 李涛 | AE98: 2025-10-15 13:41 | AF98: 李涛 | AG98: 2025-10-15 14:00 | AH98: 网课 | AI98: 65843816174 | AJ98: 2026考研专业课定制一对一（20h）-A班 | AK98: 国内考试 | AM98: 9450 | AP98: 新签 | AQ98: 无须交接 | AU98: 2025-10-15 | AW98: 回访人：李涛，回访时间：2025-10-14 13:55，回访内容：今年是二战了，目标是武汉工程大学！专8，65左右！ 去年翻译基础100初头，现在主要辅导(357)翻译基础（英语） (448)汉语写作与百科知识 ，加微信！；|回访人：李涛，回访时间：2025-10-15 13:41，回访内容：系统自动签约 | BA98: 长期班 | BB98: 86057560 | BC98: 是 | BD98: 26考季 | BE98: VIP - 伴学 | BF98: 专业课300 | BG98: 其他 | BH98: 国内高校-双非 | BI98: 否 | BM98: 111002726 | BO98: 市场
A99: 125 | B99: 北京大学部 | C99: 国内大学部 | D99: 练玙婷 | E99: 131619631 | F99: 陈号东 | G99: 2025-10-20 20:42:47 | H99: 续费原因：学生续费政治一对一；该学生为保护期内续费，原顾问：国内大学部-赵星火(zhaoxinghuo@xdf.cn) | J99: 大三 | K99: 赵星火 | L99: 转介绍 | M99: 学管续费推荐 | N99: 陈号东chenhaodong5@xdf.cn | Q99: 练玙婷 | R99: 赵星火 | S99: 30501970 | T99: 续费工单 | U99: 2025-10-21 09:44 | V99: A（六个月内有报课意向工单） | W99: 考研VIP | X99: 大三 | Y99: 陕西科技大学 | Z99: 设计与艺术学院 | AA99: 播音与主持艺术 | AB99: 练玙婷 | AC99: 5680120 | AD99: 赵星火 | AE99: 2025-10-21 09:49 | AF99: 赵星火 | AG99: 2025-10-21 11:44 | AH99: 无忧 | AI99: LP17610113741208 | AJ99: 26考研一对一伴学（20h/无忧） | AK99: 国内考试 | AM99: 16500 | AO99: 陈号东 | AP99: 续班 | AQ99: 已交接 | AS99: BJWY0421882534 | AU99: 2025-10-21 | AW99: 回访人：赵星火，回访时间：2025-10-21 09:44，回访内容：1；|回访人：赵星火，回访时间：2025-10-21 09:49，回访内容：系统自动签约 | BB99: 81005349 | BC99: 否 | BD99: 26考季 | BE99: VIP - 伴学 | BF99: 英语 | BG99: 其他 | BH99: 国内高校-双非 | BI99: 是 | BN99: 外地人外地大学(常规) | BO99: 学管续费推荐
A100: 31 | B100: 北京大学部 | C100: 国内大学部 | D100: 北京市1529 | E100: 130265445 | F100: 杨俊42(国内) | G100: 2025-10-11 15:15:04 | H100: 渠道录入来源：新东方官网M站-客服 意向城市：北京访客省/城市：北京市 访客静态ID：01000003465900016672500183911529 接待分组ID：70455 搜索引擎： 搜索词： 关键词： 设备类型：phone 访客IP：125.34.45.240 对话详细内容：AI-Lbo0rDBXCyBY 2025-10-11 15:12:06 您好同学,欢迎访问北京新东方考研四六级中心. 考研线下课程26/27考季【考研全年集训营】【考研半年集训营】【考研全科线下走读班】【考研寒/暑假集训营】【考研一对一】【考研专业课】【四/六级课程】，热门课程火热报名中,咨询即可领取专享优惠。 **【考研全年集训营】=ff761f# **【考研半年集训营】=ff6b6b# **【考研全科线下走读班】=ffc158# **【考研寒/暑假集训营】=ffc158# **【考研一对一】=ff761f# **【考研专业课】=ff6caa# **【四/六级课程】=ff6caa# **【考研冲刺班】=60e27e# AI-Lbo0rDBXCyBY 2025-10-11 15:12:09 您是想咨询【线下课程】【线上课程】【考研规划】还是【在职考研】呢？**【线下课程】# **【线上课程】#**【考研规划】#**【在职考研】# 01000003465900016672500183911529 2025-10-11 15:12:19 线上课程 AI-Lbo0rDBXCyBY 2025-10-11 15:12:22 同学，你现在是在校还是在职呢？ 01000003465900016672500183911529 2025-10-11 15:12:28 在校 AI-Lbo0rDBXCyBY 2025-10-11 15:12:32 具体是想报考什么学校和专业呢？ 01000003465900016672500183911529 2025-10-11 15:12:44 山东大学 通信工程 AI-Lbo0rDBXCyBY 2025-10-11 15:12:48 好的，我这边安排专业老师给您回电，详细沟通一下，请问您的电话是多少呢？ 01000003465900016672500183911529 2025-10-11 15:13:03 17710780856 AI-Lbo0rDBXCyBY 2025-10-11 15:13:06 好的，确认一下你的号码是否正确呢~ 01000003465900016672500183911529 2025-10-11 15:13:50 正确 AI-Lbo0rDBXCyBY 2025-10-11 15:13:53 同学怎么称呼呢？ 01000003465900016672500183911529 2025-10-11 15:14:05 刘琛 AI-Lbo0rDBXCyBY 2025-10-11 15:14:08 这边马上安排顾问老师联系您，预计半个小时左右给您回电请注意接听~ 来源页：https://group-live2.easyliao.com/live/chat.do?c=34659&g=70455&config=102466 备注： | I100: 2026财年第5财月易聊新东方官网M站 | K100: 杨欢欢 | L100: 新东方官网 | M100: 新东方官网M站 | O100: 杨欢欢 | P100: 2025-10-11 15:23:32 | Q100: 刘琛 | R100: 谭悦 | S100: 30397776 | T100: 正常工单 | U100: 2025-10-11 15:59 | V100: A（六个月内有报课意向工单） | W100: 线上考研产品 | X100: 大学已毕业 | Y100: 合肥工业大学翡翠湖校区 | Z100: 通信学院 | AA100: 通信 | AB100: 刘琛 | AC100: 5648090 | AD100: 谭悦 | AE100: 2025-10-12 11:39 | AF100: 谭悦 | AG100: 2025-10-12 11:39 | AH100: 网课 | AI100: 67127006658 | AJ100: 2026考研英语大纲冲刺VIP班,2026考研数学大纲冲刺VIP班 | AK100: 国内考试 | AM100: 6224 | AP100: 新签 | AQ100: 无须交接 | AU100: 2025-10-12 | AW100: 回访人：谭悦，回访时间：2025-10-11 15:59，回访内容：考虑英语和数学的网课学习， 推荐一对一 ；|回访人：谭悦，回访时间：2025-10-12 11:39，回访内容：签约网课 | BA100: 长期班,长期班 | BB100: 85916962 | BC100: 是 | BD100: 26考季 | BE100: 线上全程班 | BF100: 英语,数学 | BG100: 其他 | BH100: 国内高校-211 | BI100: 否 | BM100: 72387208 | BO100: 易聊在线咨询
A101: 39 | B101: 北京大学部 | C101: 国内大学部 | D101: 北京5f4a | E101: 129718547 | F101: 张亚男 | G101: 2025-10-05 18:07:14 | H101: 渠道录入来源：百度基木鱼 意向城市：北京访客省/城市：北京 访客静态ID：63a3390afc481be80ab7f432dec05f4a 接待分组ID：50795 搜索引擎：www.baidu.com 搜索词：东方新东方考研校区北京 关键词：北京新东方27考研 设备类型：phone 访客IP：117.128.97.69 对话详细内容：AI-Lbo0rDBXCy 2025-10-05 18:04:23 您好同学,欢迎访问北京新东方考研四六级中心. 考研线下课程26/27考季【考研全年集训营】【考研半年集训营】【考研全科线下走读班】【考研寒/暑假集训营】【考研一对一】【考研专业课】【四/六级课程】，热门课程火热报名中,咨询即可领取专享优惠。 **【考研全年集训营】=ff761f# **【考研半年集训营】=ff6b6b# **【考研全科线下走读班】=ffc158# **【考研寒/暑假集训营】=ffc158# **【考研一对一】=ff761f# **【考研专业课】=ff6caa# **【四/六级课程】=ff6caa# **【考研冲刺班】=60e27e# AI-Lbo0rDBXCy 2025-10-05 18:04:27 您是想咨询【线下课程】【线上课程】【考研规划】还是【在职考研】呢？**【线下课程】# **【线上课程】#**【考研规划】#**【在职考研】# 63a3390afc481be80ab7f432dec05f4a 2025-10-05 18:04:35 27考研线上课程 AI-Lbo0rDBXCy 2025-10-05 18:04:39 同学，你现在是在校还是在职呢？ 63a3390afc481be80ab7f432dec05f4a 2025-10-05 18:04:42 百度系统消息-行为轨迹:该访客在咨询页点击了内容为"在校"的按钮 63a3390afc481be80ab7f432dec05f4a 2025-10-05 18:04:42 在校 AI-Lbo0rDBXCy 2025-10-05 18:04:45 具体是想报考什么学校和专业呢？ 63a3390afc481be80ab7f432dec05f4a 2025-10-05 18:04:57 还没想好什么学校，护理专业 AI-Lbo0rDBXCy 2025-10-05 18:05:01 好的，我这边安排专业老师给您回电，详细沟通一下，请问您的电话是多少呢？ 63a3390afc481be80ab7f432dec05f4a 2025-10-05 18:05:10 18811628020 63a3390afc481be80ab7f432dec05f4a 2025-10-05 18:05:11 百度系统消息-行为轨迹:【百度】用户已留联，通过聆音回访获得实时无效返款：https://aisite.wejianzhan.com/site/wjz2tdly/5f6d3d18-a30c-41e9-9d39-6be046109511?reqCode=LYST-46LTA1P0DO8AEP1VO38V2JBQ8M AI-Lbo0rDBXCy 2025-10-05 18:05:14 好的，确认一下你的号码是否正确呢~ 63a3390afc481be80ab7f432dec05f4a 2025-10-05 18:05:17 百度系统消息-行为轨迹:该访客在咨询页点击了内容为"正确"的按钮 63a3390afc481be80ab7f432dec05f4a 2025-10-05 18:05:17 正确 AI-Lbo0rDBXCy 2025-10-05 18:05:21 同学怎么称呼呢？ 63a3390afc481be80ab7f432dec05f4a 2025-10-05 18:05:33 刘淙予 AI-Lbo0rDBXCy 2025-10-05 18:05:37 这边马上安排顾问老师联系您，预计半个小时左右给您回电请注意接听~ 来源页：http://www.baidu.com/bcp 备注： | I101: 2026财年第5财月易聊百度投放 | K101: 李涛 | L101: 线上运营-投放 | M101: 百度投放 | Q101: 刘淙予 | R101: 李涛 | S101: 30345155 | T101: 正常工单 | U101: 2025-10-05 19:04 | V101: A（六个月内有报课意向工单） | W101: 考研VIP | X101: 大三 | Y101: 北京中医药大学 | Z101: 护理学院 | AA101: 护理学 | AB101: 刘淙予 | AC101: 5644957 | AD101: 李涛 | AE101: 2025-10-08 10:46 | AF101: 李涛 | AG101: 2025-10-08 10:47 | AH101: 网课 | AI101: 61110850073 | AJ101: 2027考研英语一无忧计划·6期,2027考研护理（护综308）VIP直通车,2027考研政治无忧计划·5期 | AK101: 国内考试 | AM101: 20724.28 | AP101: 新签 | AQ101: 无须交接 | AU101: 2025-10-08 | AW101: 回访人：李涛，回访时间：2025-10-05 19:04，回访内容：今年大三，护理专业，北京中医药大学， 现在有医院践习 时间不是很好固定！推荐封闭营，一对一 走读！ 要考虑一下！继续跟进！ | BA101: 长期班,长期班,长期班 | BB101: 85717645 | BC101: 是 | BD101: 26考季 | BE101: VIP - 伴学 | BF101: 英语,政治,专业课300 | BG101: 其他 | BH101: 国内高校-中外合作办学 | BI101: 否 | BM101: 110960627 | BN101: 本地人本地大学(常规) | BO101: 易聊在线咨询
A102: 117 | B102: 北京大学部 | C102: 国内大学部 | D102: 刘浩妈妈 | E102: 131598663 | F102: 吴凯龙 | G102: 2025-10-20 20:37:01 | H102: 谭悦9的内部员工推荐工单 | J102: 大三 | K102: 谭悦 | L102: 转介绍 | M102: 内部员工推荐 | N102: 陈华锐+chenhuarui1@xdf.cn+陈华锐1(新东方教育科技集团有限公司-产业机构-前途出国-前途欧亚北京中心-语培业务部-销售部 | 销售部副总监) | Q102: 刘浩 | R102: 谭悦 | S102: 30505100 | T102: 正常工单 | U102: 2025-10-20 22:09 | V102: A（六个月内有报课意向工单） | W102: 考研集训营 | X102: 大三 | Y102: 山东艺术学院 | Z102: 美术学院 | AA102: 美术学 | AB102: 刘浩 | AC102: 5654987 | AD102: 谭悦 | AE102: 2025-10-22 16:30 | AF102: 谭悦 | AG102: 2025-10-22 16:32 | AH102: 集训营 | AI102: KYHSJXY2702 | AJ102: 27考研寒暑集训营英语 | AK102: 国内考试 | AM102: 16050 | AO102: 陈华锐+chenhuarui1@xdf.cn+陈华锐1(新东方教育科技集团有限公司-产业机构-前途出国-前途欧亚北京中心-语培业务部-销售部 | 销售部副总监) | AP102: 新签 | AQ102: 已交接 | AR102: BJWY2201F8pC6h | AS102: BJWY0994996158 | AT102: KYHSJXY27020044 | AU102: 2025-10-22 | AW102: 回访人：谭悦，回访时间：2025-10-20 22:09，回访内容：内推的学生家长 ；|回访人：谭悦，回访时间：2025-10-21 19:17，回访内容：微信跟进中， 寒暑集训营 优惠 ；|回访人：谭悦，回访时间：2025-10-22 16:30，回访内容：签约 | BB102: 86362270 | BC102: 否 | BD102: 27考季 | BE102: 寒暑假集训营（春秋OMO） | BF102: 英语,政治 | BH102: 国内高校-双非 | BI102: 是 | BL102: 报名 | BN102: 外地人外地大学(常规) | BO102: 客服
A103: 118 | B103: 北京大学部 | C103: 国内大学部 | D103: 刘浩妈妈 | E103: 131598663 | F103: 吴凯龙 | G103: 2025-10-20 20:37:01 | H103: 谭悦9的内部员工推荐工单 | J103: 大三 | K103: 谭悦 | L103: 转介绍 | M103: 内部员工推荐 | N103: 陈华锐+chenhuarui1@xdf.cn+陈华锐1(新东方教育科技集团有限公司-产业机构-前途出国-前途欧亚北京中心-语培业务部-销售部 | 销售部副总监) | Q103: 刘浩 | R103: 谭悦 | S103: 30505100 | T103: 正常工单 | U103: 2025-10-20 22:09 | V103: A（六个月内有报课意向工单） | W103: 考研集训营 | X103: 大三 | Y103: 山东艺术学院 | Z103: 美术学院 | AA103: 美术学 | AB103: 刘浩 | AC103: 5654987 | AD103: 谭悦 | AE103: 2025-10-22 16:30 | AF103: 谭悦 | AG103: 2025-10-22 16:32 | AH103: 集训营 | AI103: KYHSJXZ2702 | AJ103: 27考研寒暑集训营政治 | AK103: 国内考试 | AM103: 10850 | AO103: 陈华锐+chenhuarui1@xdf.cn+陈华锐1(新东方教育科技集团有限公司-产业机构-前途出国-前途欧亚北京中心-语培业务部-销售部 | 销售部副总监) | AP103: 新签 | AQ103: 已交接 | AR103: BJWY2201F8pC6h | AS103: BJWY0994996158 | AT103: KYHSJXZ27020038 | AU103: 2025-10-22 | AW103: 回访人：谭悦，回访时间：2025-10-20 22:09，回访内容：内推的学生家长 ；|回访人：谭悦，回访时间：2025-10-21 19:17，回访内容：微信跟进中， 寒暑集训营 优惠 ；|回访人：谭悦，回访时间：2025-10-22 16:30，回访内容：签约 | BB103: 86362270 | BC103: 否 | BD103: 27考季 | BE103: 寒暑假集训营（春秋OMO） | BF103: 英语,政治 | BH103: 国内高校-双非 | BI103: 是 | BL103: 报名 | BN103: 外地人外地大学(常规) | BO103: 客服
...

Sheet 退费明细
A1: 提交日期 | B1: OA流水号 | C1: 学管姓名 | D1: 学管是否代办 | E1: 顾问姓名 | F1: 顾问是否代办 | G1: 91系统-最新报名二级渠道 | H1: 原班所属项目 | I1: 新报入班级所属项目 | J1: 退费阶段 | K1: 退费一级原因（开课前） | L1: 退费一级原因 (开课后) | M1: 退费二级原因（专业课师资匹配原因） | N1: 退费二级原因（学员意愿转变_开课前） | O1: 退费二级原因（计划冲突_开课前） | P1: 退费二级原因（中心原因_开课前） | Q1: 退费二级原因（签约话术） | R1: 退费二级原因（教师） | S1: 退费二级原因（教学） | T1: 退费二级原因（课程安排） | U1: 退费二级原因（配套服务） | V1: 退费二级原因（配套学习设施） | W1: 退费二级原因（中心原因_开课后） | X1: 退费二级原因（计划冲突_开课后） | Y1: 退费二级原因（学员意愿转变_开课后） | Z1: 退费三级原因（完全匹配不上）-院校、学院、专业、专业课代码及名称 | AA1: 退费详细原因说明（与OA退费详细说明保持一致） | AB1: 预计报名新班学费金额 | AC1: 转班金额（请学管填写所在班级实际金额） | AD1: 转班详细原因说明 | AE1: 提交时间 | AF1: 学校 | AG1: 学院 | AH1: 年级 | AI1: 专业 | AJ1: 您所办理的业务类型 | AK1: 提交人 | AL1: 退费类型 | AM1: 学员姓名 | AN1: 学员编码 | AO1: 退费金额 | AP1: 办理日期-客服 | AQ1: 退费方式-客服 | AR1: 需要跟进的顾问/学管 | AS1: 退费/转班特殊情况备注（若需要学管提供银行卡信息，可将需求填写在此处）-客服 | AT1: 是否完成退费/转班-客服 | AU1: 父记录 | AV1: 备注
A2: 2025/10/11 | C2: 罗志勇1 | E2: 李涛48 | G2: 京内毛坯数据 | H2: 四六级项目-班课 | AC2: ¥6180.00 | AD2: 上下午班 | AE2: 2025-10-11 | AJ2: 转班 | AK2: 罗志勇1 | AM2: 冯文玥 | AN2: BJWY3141371973 | AO2: 6180 | AP2: 2025/10/11 | AQ2: 已转班 | AT2: TRUE
A3: 2025/10/11 | C3: 罗志勇1 | E3: 李涛48 | G3: 公众号 | H3: 四六级项目-班课 | AC3: ¥6180.00 | AD3: 转魏公村 花园桥太远 | AE3: 2025-10-11 | AJ3: 转班 | AK3: 罗志勇1 | AM3: 张腾 | AN3: BJWY4523927820 | AO3: 6180 | AP3: 2025/10/11 | AQ3: 已转班 | AT3: TRUE
A4: 2025/10/11 | C4: 罗志勇1 | E4: 李涛48 | G4: 公众号 | H4: 四六级项目-班课 | AC4: ¥6180.00 | AD4: 花园桥远 转入魏公村 | AE4: 2025-10-11 | AJ4: 转班 | AK4: 罗志勇1 | AM4: 高原 | AN4: BJWY2095765425 | AO4: 6180 | AP4: 2025/10/11 | AQ4: 已转班 | AT4: TRUE
AN5: 李涛合计 | AO5: =SUM(AO2:AO4) -> 18540
A6: 2025/09/26 | B6: NO.18929128 | C6: 寇颖 | E6: 谭悦9 | G6: 顾问转介绍-老带新 | H6: 无忧项目-班课 | J6: 开课后退费 | L6: 学员意愿转变_开课后 | Y6: 保研 | AA6: 退费原因：学生基本确定保研，后面课程不需要了，申请退出。【此退费为投诉退费，已走特殊申请】 | AE6: 2025-09-26 | AF6: 中央民族大学 | AG6: 音乐学院 | AH6: 大四 | AI6: 音乐表演（声乐） | AJ6: 退费 | AK6: 寇颖 | AL6: 真实产生的退费 | AM6: 官智贤 | AN6: BJWY6283856593 | AO6: 2709.6 | AP6: 2025/10/02 | AQ6: 原路径微信退回 | AT6: TRUE
A7: 2025/09/26 | B7: NO.18929111 | C7: 寇颖 | E7: 谭悦9 | G7: 顾问转介绍-老带新 | H7: 无忧项目-班课 | J7: 开课后退费 | L7: 学员意愿转变_开课后 | Y7: 保研 | AA7: 学生基本确定保研，后面课程不需要了，申请退出。【此退费为投诉退费，已走特殊申请】 | AE7: 2025-09-26 | AF7: 中央民族大学 | AG7: 音乐学院 | AH7: 大四 | AI7: 音乐表演（声乐） | AJ7: 退费 | AK7: 寇颖 | AL7: 真实产生的退费 | AM7: 官智贤 | AN7: BJWY6283856593 | AO7: 3652.8 | AP7: 2025/10/02 | AQ7: 原路径微信退回 | AT7: TRUE
A8: 2025/10/06 | C8: 寇颖 | E8: 谭悦9 | G8: 学管续费推荐 | H8: 无忧项目-班课 | AC8: ¥3038.30 | AD8: 转班信息如下： WYZ26001转WYZ26002 转班原因：学生时间冲突，需转班 | AE8: 2025-10-06 | AJ8: 转班 | AK8: 寇颖 | AM8: 孙雨涵 | AN8: BJWY6398433958 | AO8: 2531.9 | AP8: 2025/10/06 | AQ8: 10.6已转班 | AT8: TRUE | AV8: 系统实际绑单2531.9
A9: 2025/10/08 | B9: 18940587 | C9: 黄小妹7 | E9: 谭悦9 | G9: 集团-百度品专 | H9: 无忧项目-班课 | J9: 开课后退费 | L9: 学员意愿转变_开课后 | Y9: 个人身体原因无法承受高强度学习 | AA9: 【已开课退费】上课环境太远，无力兼顾来回跑 | AE9: 2025-10-08 | AF9: 中国石油大学昌平校区 | AG9: 工学院 | AH9: 大四 | AI9: 环境工程 | AJ9: 退费 | AK9: 黄小妹7 | AL9: 真实产生的退费 | AM9: 赵一泽 | AN9: BJWY5334447793 | AO9: 5725 | AP9: 2025/10/11 | AQ9: 微信退13958.3（账户6800为专业课补优惠金额）——————[图片] 20758.3暂退至学员账户，专业课确定退出后才能全部提现退回，若专业课不退需补优惠6800@刘佳林25 (刘佳林) [图片][图片] 未办理：OA未到前台（10.10） 未办理：OA未到前台（10.9） 未办理：OA未到前台（10.8） | AT9: TRUE
A10: 2025/10/08 | B10: 18940539 | C10: 黄小妹7 | E10: 谭悦9 | G10: 集团-百度品专 | H10: 无忧项目-班课 | J10: 开课后退费 | L10: 学员意愿转变_开课后 | Y10: 个人身体原因无法承受高强度学习 | AA10: 【已开课退费】上课环境太远，无力兼顾来回跑 | AE10: 2025-10-08 | AF10: 中国石油大学 | AG10: 工学院 | AH10: 大四 | AI10: 环境工程 | AJ10: 退费 | AK10: 黄小妹7 | AL10: 真实产生的退费 | AM10: 赵一泽 | AN10: BJWY5334447793 | AO10: 15033.3 | AP10: 2025/10/11 | AQ10: 微信退13958.3（账户6800为专业课补优惠金额）@黄小妹7 (黄小妹)——————[图片] 20758.3暂退至学员账户，专业课确定退出后才能全部提现退回，若专业课不退需补优惠6800@刘佳林25 (刘佳林) [图片][图片] 未办理：OA未到前台（10.10） 未办理：OA未到前台（10.9） 未办理：OA未到前台（10.8） | AT10: TRUE
A11: 2025/10/09 | B11: NO.8358680908401152856 | C11: 谭悦9 | E11: 谭悦9 | F11: TRUE | G11: 直访 | H11: VIP项目-VIP | J11: 开课前退费 | K11: 学员意愿转变_开课前 | N11: 家人不支持考研/不支持跟班学习/意见不一致 | AA11: 家长直访，汪宇萌老师帮忙接待，给学生报名的10小时一对一，学生坚持不学，意见不一致，确定要退费。 | AE11: 2025-10-09 | AF11: 吉林大学 | AG11: 能源动力 | AH11: 在职 | AI11: 能源动力 | AJ11: 退费 | AK11: 谭悦9 | AL11: 真实产生的退费 | AM11: 于潇 | AN11: BJWY3517193451 | AO11: 0 | AP11: 2025/10/13 | AQ11: 10.16原路径退费失败，改手工账号:6212264200017221013开户行:中国工商银行长春二区支行开户姓名:于宏伟，顾问汪宇萌提供信息 银联扫码退回：微信133636826509978376 未办理：OA未到前台（10.12） 未办理：OA未到前台（10.11） 未办理：OA未到前台（10.10） | AT11: TRUE | AV11: 当月退费签约退费都不算
A12: 2025/10/12 | C12: 唐源曼 | E12: 谭悦9 | G12: 总部-百度投放 | H12: 集训营项目-班课 | AC12: ¥15281.60 | AD12: 学员因换院校转成英二 | AE12: 2025-10-12 | AJ12: 转班 | AK12: 唐源曼 | AM12: 张梓桐 | AN12: BJWY2669115733 | AO12: 8404.9 | AP12: 2025/10/12 | AQ12: 已转班 | AT12: TRUE | AV12: 系统实际绑单8404.9
A13: 2025/10/14 | B13: 18947384 | C13: 郝琨 | E13: 谭悦9 | G13: 学管续费推荐 | H13: 无忧项目-班课 | I13: VIP项目 | J13: 开课后退费 | L13: 中心原因_开课后 | W13: 退出重报（取消班/合班/延转/选班/扩科等） | AA13: 学生姓名：陈一凡学员编号：BJWY8503976521退费方式：报名英政数专退英政数专退费原因：学生心理状态问题，今年不打算考研，想把公共课和专业课剩余金额转成一对一后续学习班课退费班级：、WYE26007、WYE26008、WYP26005、WYP26006、WYM26005、WYM26006应退金额：12250.7，其中1481.1元保留给六级班，总计退出给学生10769.6元最后出勤日期：6.28 | AB13: ¥2948.90 | AE13: 2025-10-14 | AF13: 北方工业大学 | AG13: 信息学院 | AH13: 大四 | AI13: 数据科学与大数据技术 | AJ13: 退费 | AK13: 郝琨 | AL13: 转项目/转班/退出重报等未产生实际退费 | AM13: 陈一凡 | AN13: BJWY8503976521 | AO13: 0 | AP13: 2025/10/26 | AQ13: 10.27 已退回账户余额 10.26 这个已经退回账户余额啦 10.24 未办理，退回后的oa未到前台 10.23学管要求退回oa，已回退@郝琨 未办理：补给四六级的1481.1从哪个办理退出（10.23）@郝琨 未办理：补给四六级的1481.1从哪个办理退出（10.22）@郝琨 未办理：补给四六级的1481.1从哪个办理退出（10.20）@郝琨[图片] 未办理，OA未到前台（10.19）@郝琨 未办理，OA未到前台（10.18） 未办理，OA未到前台（10.17） 未办理，OA未到前台（10.16） 未办理，OA未到前台（10.15） | AT13: TRUE | AV13: 代离职顾问办理，栗晓环 | AX13: 2948.9
A14: 2025/10/14 | B14: 18947393 | C14: 郝琨 | E14: 谭悦9 | G14: 学管续费推荐 | H14: 无忧项目-班课 | I14: VIP项目 | J14: 开课后退费 | L14: 中心原因_开课后 | W14: 退出重报（取消班/合班/延转/选班/扩科等） | AA14: 学生姓名：陈一凡学员编号：BJWY8503976521退费方式：报名英政数专退英政数专退费原因：学生心理状态问题，今年不打算考研，想把公共课和专业课剩余金额转成一对一后续学习班课退费班级：、WYE26007、WYE26008、WYP26005、WYP26006、WYM26005、WYM26006应退金额：12250.7，其中1481.1元保留给六级班，总计退出给学生10769.6元最后出勤日期：6.28 | AB14: ¥20000.00 | AE14: 2025-10-14 | AF14: 北方工业大学 | AG14: 信息学院 | AH14: 大四 | AI14: 数据科学与大数据技术 | AJ14: 退费 | AK14: 郝琨 | AL14: 转项目/转班/退出重报等未产生实际退费 | AM14: 陈一凡 | AN14: BJWY8503976521 | AO14: 0 | AP14: 2025/10/26 | AQ14: 10.27已退回账户余额 10.26，救命啊😱，WYP26006 退费的时候发现课次变化了，先转班一下老师，转班之后再退：@郝琨 [图片] 10.24 未办理，退回后的oa未到前台 10.23学管要求退回oa，已回退@郝琨 未办理：补给四六级的1481.1从哪个办理退出（10.23）@郝琨 未办理：补给四六级的1481.1从哪个办理退出（10.22）@郝琨 未办理：补给四六级的1481.1从哪个办理退出（10.20）@郝琨[图片] 未办理，OA未到前台（10.19）@郝琨 未办理，OA未到前台（10.18） 未办理，OA未到前台（10.17） 未办理，OA未到前台（10.16） 未办理，OA未到前台（10.15） | AT14: TRUE | AV14: 代离职顾问办理，栗晓环 | AX14: 4774.6
A15: 2025/10/14 | B15: 18947405 | C15: 郝琨 | E15: 谭悦9 | G15: 学管续费推荐 | H15: 无忧项目-班课 | I15: VIP项目 | J15: 开课后退费 | L15: 中心原因_开课后 | W15: 退出重报（取消班/合班/延转/选班/扩科等） | AA15: 学生姓名：陈一凡学员编号：BJWY8503976521退费方式：报名英政数专退英政数专退费原因：学生心理状态问题，今年不打算考研，想把公共课和专业课剩余金额转成一对一后续学习班课退费班级：、WYE26007、WYE26008、WYP26005、WYP26006、WYM26005、WYM26006应退金额：12250.7，其中1481.1元保留给六级班，总计退出给学生10769.6元最后出勤日期：6.28 | AB15: ¥20000.00 | AE15: 2025-10-14 | AF15: 北方工业大学 | AG15: 信息学院 | AH15: 大四 | AI15: 数据科学与大数据技术 | AJ15: 退费 | AK15: 郝琨 | AL15: 转项目/转班/退出重报等未产生实际退费 | AM15: 陈一凡 | AN15: BJWY8503976521 | AO15: 0 | AP15: 2025/10/26 | AQ15: 10.27已退回账户余额 10.26，救命啊，这个WYM26006也要转班：@郝琨 [图片] 10.24 未办理，退回后的oa未到前台 10.23学管要求退回oa，已回退@郝琨 未办理：补给四六级的1481.1从哪个办理退出（10.23）@郝琨 未办理：补给四六级的1481.1从哪个办理退出（10.22）@郝琨 未办理：补给四六级的1481.1从哪个办理退出（10.20）@郝琨[图片] 未办理，OA未到前台（10.19）@郝琨 未办理，OA未到前台（10.18） 未办理，OA未到前台（10.17） 未办理，OA未到前台（10.16） 未办理，OA未到前台（10.15） | AT15: TRUE | AV15: 代离职顾问办理，栗晓环 | AX15: 3370.3
A16: 2025/10/24 | B16: 18959033 | C16: 郝琨 | E16: 谭悦9 | G16: 学管续费推荐 | H16: 无忧项目-班课 | I16: VIP项目 | J16: 开课后退费 | L16: 中心原因_开课后 | W16: 退出重报（取消班/合班/延转/选班/扩科等） | AA16: 学生姓名：陈一凡学员编号：BJWY8503976521退费方式：报名英政数专退英政数专退费原因：学生心理状态问题，今年不打算考研，想把公共课和专业课剩余金额转成一对一后续学习班课退费班级：、WYE26007、WYE26008、WYP26005、WYP26006、WYM26005、WYM26006应退金额：12250.7，其中1481.1元保留给六级班，总计退出给学生10769.6元最后出勤日期：6.28 应退金额：12250.7，其中1481.1元保留给六级班，英语冲刺班退出2948.9元，政治冲刺班退出4774.6元 数学冲刺班退出3370.3，政治强化班退出1156.9元，金额保留在学员账户，公共课部分10769.6元，后续入一对一 | AB16: ¥20000.00 | AE16: 2025-10-24 | AF16: 北方工业大学 | AG16: 计算机学院 | AH16: 大四 | AI16: 大数据技术 | AJ16: 退费 | AK16: 郝琨 | AL16: 转项目/转班/退出重报等未产生实际退费 | AM16: 陈一凡 | AN16: BJWY8503976521 | AO16: 0 | AP16: 2025/10/26 | AQ16: 10.27已退回账户余额 10.26，这个OA已经退回账户余额啦，等等上面那俩转班的@郝琨 | AT16: TRUE | AV16: 代离职顾问办理，栗晓环 | AX16: 1156.9
A17: 2025/10/18 | B17: NO.864691128456653152 | C17: 刘佳林25 | E17: 谭悦9 | G17: 学管续费推荐 | H17: 集训营项目-专业课 | J17: 开课前退费 | K17: 学员意愿转变_开课前 | N17: 家人不支持考研/不支持跟班学习/意见不一致 | AA17: 学生是中石油的，来花园桥距离太远来回奔波，家长要求退费，专业课也要一同退费；经过挽单，原本是等学生专业课测试成绩出来后，再决定专业课这边是否退费，但是目前学生对考本校专业课比较有信心，孩子坚持不需要，需要办理退费 | AE17: 2025-10-18 | AF17: 中国石油大学 | AG17: 环境工程 | AH17: 大四 | AI17: 环境工程 | AJ17: 退费 | AK17: 刘佳林25 | AL17: 真实产生的退费 | AM17: 赵一泽 | AN17: BJWY5334447793 | AO17: 5500 | AP17: 2025/10/18 | AQ17: 原路径微信退回 | AT17: TRUE
A18: 2025/10/18 | C18: 黄小妹7 | E18: 谭悦9 | G18: 巨量广告 | H18: 无忧项目-班课 | AC18: ¥3891.10 | AD18: 学生需要往后转班3月上课，目前花园桥没有新班，需要先转到知春路避免学生看回放形成客诉 | AE18: 2025-10-18 | AJ18: 转班 | AK18: 黄小妹7 | AM18: 郑雅洁 | AN18: BJWY5564317069 | AO18: 3891.1 | AP18: 2025/10/18 | AQ18: 已转班 | AT18: TRUE
A19: 2025/10/14 | B19: 2025101402418 | C19: 陈晶171 | E19: 谭悦9 | G19: 阿里本地通 | H19: 无忧项目-VIP | J19: 开课前退费 | K19: 学员意愿转变_开课前 | N19: 找到工作 | AA19: 得知孩子退费的消息第一时间联系了孩子，主要是从尝试和老师接触开始第一次的课程学习，工作后就再也没时间考研了，以及以后的工作学历要求高几个方面说起，孩子态度比较坚决，说是和家长商量好了决定工作，详细的不愿意多说。 但是问到孩子我还要发后续的学习资料吗，孩子还是要发，今年可能还要考，但要把课程费用退出，我后续会继续跟进服务，最好是能再让孩子报一些课时考前冲刺用 | AE19: 2025-10-18 | AF19: 大连海事大学 | AG19: 法学院 | AH19: 大三 | AI19: 法律 | AJ19: 退费 | AK19: 陈晶171 | AL19: 真实产生的退费 | AM19: 曾行健 | AN19: BJWY3312305782 | AO19: 0 | AP19: 2025/10/19 | AQ19: 10.19原渠道微信已退回@陈晶171 (陈晶) | AT19: TRUE | AV19: 当月退费签约退费都不算
A20: 2025/10/26 | C20: 郝琨 | E20: 谭悦9 | G20: 学管续费推荐 | H20: 无忧项目-班课 | AC20: ¥8144.90 | AD20: 姓名：陈一凡 电话：18322094303 学员编号： BJWY8503976521 转班原因：退费转班 转班信息： WYM26006转WYM26009，WYP26006转WYP26021 已登记表格，辛苦老师办理 | AE20: 2025-10-26 | AJ20: 转班 | AK20: 郝琨 | AM20: 陈一凡 | AN20: BJWY8503976521 | AO20: 8144.9 | AP20: 2025/10/26 | AQ20: 已转班，新班已退 | AT20: TRUE
A21: 2025/10/27 | C21: 葛铭 | E21: 谭悦9 | G21: 线下校代 | H21: 无忧项目-班课 | AC21: ¥9000.00 | AD21: 学员更换专业，申请转班 | AE21: 2025-10-27 | AJ21: 转班 | AK21: 葛铭 | AM21: 汤世瑞 | AN21: BJWY7703355611 | AO21: 9000 | AP21: 2025/10/27 | AQ21: 已转班 | AT21: TRUE
A22: 2025/10/30 | B22: 18967999 | C22: 余韵7 | E22: 谭悦9 | G22: 大众点评 | H22: 无忧项目-班课 | J22: 开课后退费 | L22: 学员意愿转变_开课后 | Y22: 认为课程用处不大/不适合自己 | AA22: 学生姓名：许凯贤 学员编号：BJWY0058842315 报名班级：无忧英语政治 报名手机号：18611288017 考勤截至日期：10月19号 实际课消：英语2次课共4课时 退费明细：资料费用68.2元 其中已开课班次WYE27019退4184-（2/108）*21800-68.2元=3712.1元 其他未开课班次WYP27016，WYP27017，WYP27018，WYE27022，WYE27023退23116元 总退费金额：3712.1+23116=26828.1元 | AE22: 2025-10-30 | AF22: 首都体育学院 | AG22: 体育教育训练学院 | AH22: 在职 | AI22: 体育教育 | AJ22: 退费 | AK22: 余韵7 | AL22: 真实产生的退费 | AM22: 许凯贤 | AN22: BJWY0058842315 | AO22: 0 | AP22: 2025/10/31 | AQ22: 11.1已提交退款，目前显示退款失败商户头寸不足，原因如下图，辛苦老师确认@余韵7 (余韵)[图片] 10.31暂退学生账户，学生另一个班级课消有误@余韵7 (余韵) 10.30未办理，oa未到前台@余韵7 (余韵) | AV22: 魏公村班取消，不扣除业绩
E23: 谭悦9 | AL23: 网课退费 | AM23: 学员9ljko | AN23: 110139778 | AO23: 100 | AP23: 45961
E24: 谭悦9 | AL24: 网课退费 | AM24: DLS_5125394710 | AN24: 110976963 | AO24: 399 | AP24: 45943
E25: 谭悦9 | AL25: 网课退费 | AM25: DLS_4437884727 | AN25: 110159583 | AO25: 4695.6 | AP25: 45931
AN26: 谭悦合计 | AO26: =SUM(AO6:AO25) -> 69788.1
A27: 2025/10/17 | B27: 18950454 | C27: 罗志勇1 | E27: 赵星火 | G27: 直访 | H27: 四六级项目-班课 | J27: 开课前退费 | K27: 学员意愿转变_开课前 | N27: 个人身体原因无法承受高强度学习 | AA27: 【开课前退费】学生因为身体原因，无法参与学习，多次沟通不愿意转班或者是线上，申请退费。 | AE27: 2025-10-17 | AF27: 北京联合大学 | AG27: 历史 | AH27: 大二 | AI27: 历史学 | AJ27: 退费 | AK27: 罗志勇1 | AL27: 真实产生的退费 | AM27: 薛绍钧 | AN27: BJWY0461942484 | AO27: =6180/2 -> 3090 | AP27: 2025/10/30 | AQ27: 10.30已办理，原渠道是微信支付，已到账@罗志勇1 (罗志勇) [图片] 10.29未办理，oa未到前台@罗志勇1 (罗志勇) 未办理，OA未到前台（10.28）已经在群内同步提醒@罗志勇1 (罗志勇) 未办理，OA未到前台（10.27）@罗志勇1 (罗志勇) 未办理，OA未到前台（10.26）@罗志勇1 (罗志勇) 未办理，OA未到前台（10.24）@罗志勇1 (罗志勇) 未办理，OA未到前台（10.23）@罗志勇1 (罗志勇) 未办理，OA未到前台（10.22）@罗志勇1 (罗志勇) 未办理，OA未到前台（10.21） 未办理，OA未到前台（10.20） 未办理，OA未到前台（10.19） 未办理，OA未到前台（10.18） 未办理，OA未到前台（10.17） | AT27: TRUE | AV27: 和高龙明分单6180
A28: 2025/10/22 | B28: NO.2025102100844 | C28: 谢仕为1 | E28: 赵星火 | G28: 学管续费推荐 | H28: 集训营项目-专业课 | J28: 开课后退费 | L28: 计划冲突_开课后 | X28: 专业课学习时间和新东方时间冲突 | AA28: 学生觉得专业课内容太多 学不完 要调整一部分到公共课一对一上 | AE28: 2025-10-22 | AF28: 保定理工学院 | AG28: 资源与工程技术学院 | AH28: 大四 | AI28: 土地资源管理 | AJ28: 退费 | AK28: 谢仕为1 | AL28: 真实产生的退费 | AM28: 霍盈杉 | AN28: BJWY9038592627 | AO28: 6476 | AP28: 2025/10/22 | AQ28: 退至学员账户 | AT28: TRUE
A29: 2025/10/23 | B29: 18956851 | C29: 葛铭 | E29: 赵星火 | G29: 百度投放 | H29: 无忧项目-班课 | I29: 无忧项目 | J29: 开课后退费 | L29: 计划冲突_开课后 | X29: 个人生活/工作事务和新东方时间冲突 | AA29: 学员开学大三，明年正式考研，在报名蜂鸟英数班，报名时已确定后续冲刺班退出 | AB29: ¥18300.00 | AE29: 2025-10-23 | AF29: 北京电子科技大学 | AG29: 电子信息 | AH29: 大三 | AI29: 电子信息 | AJ29: 退费 | AK29: 葛铭 | AL29: 转项目/转班/退出重报等未产生实际退费 | AM29: 杨欣 | AN29: XDF3140342751 | AO29: 4121.2 | AP29: 2025/10/23 | AQ29: 已退回账户余额（10.23）@葛铭@赵星火 | AT29: TRUE
A30: 2025/10/23 | B30: 18956753 | C30: 葛铭 | E30: 赵星火 | G30: 百度投放 | H30: 无忧项目-班课 | I30: 无忧项目 | J30: 开课后退费 | L30: 计划冲突_开课后 | X30: 个人生活/工作事务和新东方时间冲突 | AA30: 学员开学大三，明年正式考研，在报名蜂鸟英数班，报名时已确定后续冲刺班退出。 | AB30: ¥18300.00 | AE30: 2025-10-23 | AF30: 北京电子科技大学 | AG30: 电子信息 | AH30: 大三 | AI30: 电子信息 | AJ30: 退费 | AK30: 葛铭 | AL30: 转项目/转班/退出重报等未产生实际退费 | AM30: 杨欣 | AN30: XDF3140342751 | AO30: 3978.9 | AP30: 2025/10/23 | AQ30: 已退回账户余额（10.23）@葛铭@赵星火 | AT30: TRUE
A31: 2025/10/23 | B31: 18956887 | C31: 葛铭 | E31: 赵星火 | G31: 百度投放 | H31: 无忧项目-班课 | J31: 开课后退费 | L31: 计划冲突_开课后 | X31: 个人生活/工作事务和新东方时间冲突 | AA31: 学员开学大三，明年正式考研，在报名蜂鸟英数班，报名时已确定后续冲刺班退出。 | AE31: 2025-10-23 | AF31: 北京信息科技大学 | AG31: 电子信息 | AH31: 大三 | AI31: 电子信息 | AJ31: 退费 | AK31: 葛铭 | AL31: 真实产生的退费 | AM31: 杨欣 | AN31: XDF3140342751 | AO31: 92.55 | AP31: 2025/10/26 | AQ31: 10.28顾问已确认，留在账户余额，已办理完成@赵星火@葛铭 10.28账户余额192.6元，需要怎么处理么？@葛铭@赵星火 10.26 退回账户余额92.5@葛铭@赵星火，这点零钱是要退回给家长吗？ 10.24未办理，退回后的oa未到前台@葛铭@赵星火 未办理：（10.23）OA金额有误，92.5不是92.55，OA已回退@葛铭 | AT31: TRUE
A32: 2025/10/27 | B32: 2025101702316 | C32: 徐岩91 | E32: 赵星火 | G32: 百度地图 | H32: 四六级项目-VIP | J32: 开课后退费 | L32: 学员意愿转变_开课后 | Y32: 认为课程用处不大/不适合自己 | AA32: 目前孩子比较抗拒上课，家长也没有办法，之前上六级没过，不想在上课了，已经说了可以上其他的科目，但家长还是坚持退费 | AE32: 2025-10-27 | AF32: 北京大学 | AG32: 物理学院 | AH32: 大二 | AI32: 物理学 | AJ32: 退费 | AK32: 徐岩91 | AL32: 真实产生的退费 | AM32: 田浩天 | AN32: BJWY9272845607 | AO32: 775 | AP32: 2025/10/29 | AQ32: 11.1显示已退款@徐岩91 (徐岩)[图片] 10.31用户已确认，退款中@徐岩91 (徐岩) 10.30用户已确认，退款中@徐岩91 (徐岩) [图片] 10.29微信支付的775元已经原路返回已经到账，700元渠道是支付宝，已失效，已提交手工退款，已发送确认短信到139****0325，需要用户短信确认@徐岩91 (徐岩)[图片] [图片] [图片] 10.28未办理，缺少顾问和学管老师的挽单截图@徐岩91 (徐岩) 未办理：缺少顾问和学管老师的挽单截图（10.27）@徐岩91 (徐岩) | AT32: TRUE | AV32: 两笔退费，第一笔700代离职顾问杨阳办理
AM33: 学员0wg6u | AN33: 100806138 | AO33: 100 | AQ33: 45960
AM34: DLS_0044058589 | AN34: 111045497 | AO34: 100 | AQ34: 45951
AM35: 学员7x9u_ | AN35: 104236314 | AO35: 7366.8 | AQ35: 45940
AN36: 赵星火合计 | AO36: =SUM(AO27:AO35) -> 26100.45

Sheet 10月绩效核算
B2: 顾问 | E2: 转介绍 | M2: 签约率 | U2: 日常管理 | AA2: 总计
B3: 工号 | C3: 顾问姓名 | D3: 备注 | E3: 工单目标 | F3: 工单实际 | G3: 完成率 | H3: 签约目标 | I3: 签约实际 | J3: 完成率 | K3: 占比 | L3: 得分 | M3: 主动目标 | N3: 主动实际 | O3: 完成情况 | P3: 被动目标 | Q3: 被动实际 | R3: 完成情况 | S3: 占比 | T3: 得分 | U3: 自签占比目标比 | V3: 实际 | W3: 占比 | X3: 回访时效 | Y3: 占比 | Z3: 得分 | AA3: 得分合计 | AB3: 绩效标准 | AC3: 发放比例 | AD3: 实发绩效
B4: 238256 | C4: 赵星火 | E4: 6 | F4: 0 | G4: =F4/E4 -> 0 | H4: 6 | I4: 1.9 | J4: =I4/H4 -> 0.31666667 | K4: 0.3 | L4: 0 | M4: 0.25 | N4: 0.42 | O4: 完成 | P4: 0.1 | Q4: 0.15 | R4: 完成 | S4: 0.4 | T4: 40 | U4: 0.3 | V4: 0.38 | W4: 0.2 | X4: 合格 | Y4: 0.1 | Z4: 30 | AA4: =L4+T4+Z4 -> 70 | AB4: 1000 | AC4: =(100-(90-AA4)*2)% -> 0.6 | AD4: =AB4*AC4 -> 600
B5: 404905 | C5: 李涛 | D5: 结束保护期 | E5: 2 | F5: 1 | G5: =F5/E5 -> 0.5 | H5: 2 | I5: 0 | J5: =I5/H5 -> 0 | K5: 0.3 | L5: 0 | M5: 0.1 | N5: 0.23 | O5: 完成 | P5: 0.1 | Q5: 0.26 | R5: 完成 | S5: 0.4 | T5: 40 | U5: 0.3 | V5: 0.69 | W5: 0.2 | X5: 合格 | Y5: 0.1 | Z5: =W5*100+10 -> 30 | AA5: =L5+T5+Z5 -> 70 | AB5: 2000 | AC5: =(100-(90-AA5)*2)% -> 0.6 | AD5: =AB5*AC5 -> 1200
B6: 341422 | C6: 谭悦 | D6: O3无考核指标 | E6: 6 | F6: 0 | G6: =F6/E6 -> 0 | H6: 6 | I6: 1.7587 | J6: =I6/H6 -> 0.29311667 | K6: 0.3 | L6: 0 | M6: 0.25 | N6: 0.45 | O6: 完成 | P6: 0.1 | Q6: 0.26 | R6: 完成 | S6: 0.4 | T6: 40 | U6: 0.3 | V6: 0.5 | W6: 0.2 | X6: 合格 | Y6: 0.1 | Z6: =W6*100+10 -> 30 | AA6: =L6+T6+Z6 -> 70 | AB6: 0 | AD6: =AB6*AA6% -> 0

Sheet 11月绩效目标
B2: 序号 | C2: 年月 | D2: 部门 | E2: 工号 | F2: 姓名 | G2: 岗位 | H2: 绩效考核项
H3: 1.签约业绩 | I3: 2.主被动转化率 | J3: 3.老带新工单/人头/金额 | K3: 4.项目自签占比 | L3: 5.回访时效
B4: 1 | C4: 202511 | D4: 个性化项目部 | E4: 238256 | F4: 赵星火 | G4: 学习顾问 | H4: 51.5w（含在线代售5000） | I4: 主动25%、被动10% | J4: 工单6/人头2/金额5 | K4: 0.35 | L4: 不低于中心75分位值
B5: 2 | C5: 202511 | E5: 341422 | F5: 谭悦 | H5: 51.5w（含在线代售5000） | I5: 主动25%、被动10% | J5: 工单6/人头2/金额5 | K5: 0.35 | L5: 不低于中心75分位值
B6: 3 | C6: 202511 | E6: 404905 | F6: 李涛 | H6: 51.4w（含在线代售4000） | I6: 主动20%、被动10% | J6: 工单4/人头2/金额4 | K6: 0.35 | L6: 不低于中心75分位值
I7: 占比40% | J7: 占比30% | K7: 占比30%

Sheet Sheet1
AM1: 学员0wg6u | AN1: 100806138 | AP1: 45960 | AV1: 100
AM2: DLS_0044058589 | AN2: 111045497 | AP2: 45951 | AV2: 100
AM3: 学员7x9u_ | AN3: 104236314 | AP3: 45940 | AV3: 7366.8
