Workbook

Sheet 绩效汇总
B2: 业绩奖金表（一人可多条，需写清类别）
B3: 序号 | C3: 机构 | D3: 年月 | E3: 工号 | F3: 姓名 | G3: 部门 | H3: 薪资项目 | I3: 金额
B4: 1 | C4: 北京中心 | D4: 2025.07 | E4: 238256 | F4: 赵星火 | G4: O2级学习顾问 | H4: 月度绩效 | I4: ='7月绩效核算'!T4 -> 920
B5: 2 | C5: 北京中心 | D5: 2026.07 | E5: 238256 | F5: 赵星火 | G5: O2级学习顾问 | H5: 顾问签约奖金 | I5: ='业绩汇总'!N5 -> 53861.437
B6: 3 | C6: 北京中心 | D6: 2028.07 | E6: 341422 | F6: 谭悦 | G6: O3级学习顾问 | H6: 月度绩效 | I6: 0 | J6: 新财年按照O3发放顾问底薪
B7: 4 | C7: 北京中心 | D7: 2029.07 | E7: 341422 | F7: 谭悦 | G7: O3级学习顾问 | H7: 顾问签约奖金 | I7: ='业绩汇总'!N4 -> 94270.822
B8: 5 | C8: 北京中心 | D8: 2030.07 | E8: 341422 | F8: 谭悦 | G8: O3级学习顾问 | H8: PK赛奖金 | I8: 4000 | J8: 前两周第一名
B9: 6 | C9: 北京中心 | D9: 2030.07 | E9: 341422 | F9: 李涛 | G9: O1级学习顾问 | H9: 月度绩效 | I9: =2000*(24/31) -> 1548.3871 | J9: 2025/7/8入职

Sheet 业绩汇总
B2: 2025.07个性化顾问业绩
B3: 序号 | C3: 顾问姓名 | D3: 月度目标 | E3: 地面业绩 | F3: 网课代售业绩 | G3: 业绩合计 | H3: 线下退费 | I3: 网课退费 | J3: 退费合计 | K3: 综合业绩 | L3: 完成率
B4: 1 | C4: 谭悦 | D4: 1100000 | E4: =GETPIVOTDATA("学费",'7月签约班级明细导出'!$C$1,"标签","地面业绩","签约单录入人","谭悦") -> 2167026.9 | F4: =GETPIVOTDATA("学费",'7月签约班级明细导出'!$C$1,"标签","代售网课","签约单录入人","谭悦") -> 104102.6 | G4: =E4+F4 -> 2271129.5 | H4: ='7月钉钉退费共享表明细'!AP39-'7月钉钉退费共享表明细'!AP38-'7月钉钉退费共享表明细'!AP37-'7月钉钉退费共享表明细'!AP36 -> 385463.05 | I4: ='7月钉钉退费共享表明细'!AP36+'7月钉钉退费共享表明细'!AP37+'7月钉钉退费共享表明细'!AP38 -> 250 | J4: =H4+I4 -> 385713.05 | K4: =G4-J4 -> 1885416.4 | L4: =K4/D4 -> 1.714015 | N4: =K4*0.05 -> 94270.822
B5: 2 | C5: 星火 | D5: 1100000 | E5: =GETPIVOTDATA("学费",'7月签约班级明细导出'!$C$1,"标签","地面业绩","签约单录入人","赵星火") -> 1478651.6 | F5: =GETPIVOTDATA("学费",'7月签约班级明细导出'!$C$1,"标签","代售网课","签约单录入人","赵星火") -> 71792.8 | G5: =E5+F5 -> 1550444.4 | H5: ='7月钉钉退费共享表明细'!AP64-'7月钉钉退费共享表明细'!AP63-'7月钉钉退费共享表明细'!AP62 -> 196501.85 | I5: ='7月钉钉退费共享表明细'!AP62+'7月钉钉退费共享表明细'!AP63 -> 7406.63 | J5: =H5+I5 -> 203908.48 | K5: =G5-J5 -> 1346535.9 | L5: =K5/D5 -> 1.2241236 | N5: =K5*0.04 -> 53861.437
B6: 合计 | D6: =SUM(D4:D5) -> 2200000 | E6: =SUM(E4:E5) -> 3645678.5 | F6: 108898.6 | G6: =E6+F6 -> 3754577.1 | H6: ¥386,657.60 | I6: 8464 | J6: =SUM(J4:J5) -> 589621.53 | K6: =SUM(K4:K5) -> 3231952.4 | L6: =K6/D6 -> 1.4690693

Sheet 7月签约班级明细导出
D1: 标签 | E1: 求和项:学费
C2: 谭悦 | E2: 2271129.5
D3: 代售网课 | E3: 104102.6
D4: 地面业绩 | E4: 2167026.9
C5: 赵星火 | E5: 1550444.4
D6: 代售网课 | E6: 71792.8
D7: 地面业绩 | E7: 1478651.6
C8: Grand Total | E8: 3821573.9
A10: 标签 | B10: 序号 | C10: 学校 | D10: 部门 | E10: 资源姓名 | F10: 资源ID | G10: 资源录入人 | H10: 资源录入时间 | I10: 资源描述 | J10: 市场活动 | K10: 资源年级 | L10: 分配顾问/TMK | M10: 一级获取渠道 | N10: 二级获取渠道 | O10: 转介绍人 | P10: TMK激活人 | Q10: TMK激活处理时间 | R10: 工单姓名 | S10: 跟进顾问 | T10: 工单ID | U10: 工单类型 | V10: 工单录入时间 | W10: 工单等级 | X10: 咨询课程 | Y10: 工单年级 | Z10: 学校 | AA10: 院系 | AB10: 专业 | AC10: 签约学生姓名 | AD10: 签约单ID | AE10: 签约单录入人 | AF10: 签约单录入时间 | AG10: 签约单更新人 | AH10: 签约单更新时间 | AI10: 班号 | AJ10: 班级名称 | AK10: 面询表类型 | AL10: 订金 | AM10: 学费 | AN10: 续费类型 | AO10: 推荐人 | AP10: 类型 | AQ10: 是否交接 | AR10: 操作人编号 | AS10: 学员号 | AT10: 听课证号 | AU10: 报班日期 | AV10: 学员状态 | AW10: 回访记录 | AX10: 新老生类型 | AY10: 退费金额 | AZ10: 退费日期 | BA10: 课程类型 | BB10: 客户ID | BC10: 是否新东方在线签约 | BD10: 考季 | BE10: 报名产品 | BF10: 报名科目 | BG10: 意向报考专业 | BH10: 学校班型/类型 | BI10: 是否关联协议 | BJ10: 特殊备注 | BK10: 产品品类 | BL10: 业务类型 | BM10: 签约列表在线学员ID | BN10: 大学生源类型 | BO10: 资源来源
A11: 地面业绩 | B11: 1 | C11: 北京大学部 | D11: 国内大学部 | E11: 杨显婷 | F11: 121602812 | G11: 许庆典 | H11: 2025-07-31 19:54:31 | I11: 续费原因：续费27考研；该学生为保护期内续费，原顾问：国内大学部-谭悦(tanyue9@xdf.cn) | K11: 大二 | L11: 谭悦 | M11: 转介绍 | N11: 学管续费推荐 | O11: 许庆典xuqingdian@xdf.cn | R11: 杨显婷 | S11: 谭悦 | T11: 29440654 | U11: 续费工单 | V11: 2025-07-31 20:06 | W11: A（六个月内有报课意向工单） | X11: 考研专业课,考研无忧计划 | Y11: 大二 | Z11: 北京物资学院 | AA11: 信息学院 | AB11: 应用统计学 | AC11: 杨显婷 | AD11: 5528120 | AE11: 谭悦 | AF11: 2025-07-31 20:06 | AG11: 谭悦 | AH11: 2025-07-31 20:06 | AI11: WYM27002 | AJ11: 考研数学无忧计划（27考研/强化） | AK11: 国内考试 | AM11: 6100 | AN11: 同科续费 | AO11: 许庆典 | AP11: 续班 | AQ11: 已交接 | AR11: BJWY2101498uW2 | AS11: BJWY5113272165 | AT11: WYM270020036 | AU11: 2025-07-31 | AW11: 回访人：谭悦，回访时间：2025-07-31 20:06，回访内容：27考研 | BB11: 44495810 | BC11: 否 | BD11: 27考季 | BE11: 无忧计划-啄木鸟,考研专业课150 | BF11: 英语,政治,数学,专业课150 | BG11: 其他 | BH11: 国内高校-双非 | BI11: 是 | BL11: 报名 | BN11: 本地人本地大学(常规) | BO11: 学管续费推荐
A12: 地面业绩 | B12: 2 | C12: 北京大学部 | D12: 国内大学部 | E12: 杨显婷 | F12: 121602812 | G12: 许庆典 | H12: 2025-07-31 19:54:31 | I12: 续费原因：续费27考研；该学生为保护期内续费，原顾问：国内大学部-谭悦(tanyue9@xdf.cn) | K12: 大二 | L12: 谭悦 | M12: 转介绍 | N12: 学管续费推荐 | O12: 许庆典xuqingdian@xdf.cn | R12: 杨显婷 | S12: 谭悦 | T12: 29440654 | U12: 续费工单 | V12: 2025-07-31 20:06 | W12: A（六个月内有报课意向工单） | X12: 考研专业课,考研无忧计划 | Y12: 大二 | Z12: 北京物资学院 | AA12: 信息学院 | AB12: 应用统计学 | AC12: 杨显婷 | AD12: 5528120 | AE12: 谭悦 | AF12: 2025-07-31 20:06 | AG12: 谭悦 | AH12: 2025-07-31 20:06 | AI12: WYP27005 | AJ12: 考研政治无忧计划（27考研/强化） | AK12: 国内考试 | AM12: 3600 | AN12: 同科续费 | AO12: 许庆典 | AP12: 续班 | AQ12: 已交接 | AR12: BJWY2101498uW2 | AS12: BJWY5113272165 | AT12: WYP270050012 | AU12: 2025-07-31 | AW12: 回访人：谭悦，回访时间：2025-07-31 20:06，回访内容：27考研 | BB12: 44495810 | BC12: 否 | BD12: 27考季 | BE12: 无忧计划-啄木鸟,考研专业课150 | BF12: 英语,政治,数学,专业课150 | BG12: 其他 | BH12: 国内高校-双非 | BI12: 是 | BL12: 报名 | BN12: 本地人本地大学(常规) | BO12: 学管续费推荐
A13: 地面业绩 | B13: 3 | C13: 北京大学部 | D13: 国内大学部 | E13: 杨显婷 | F13: 121602812 | G13: 许庆典 | H13: 2025-07-31 19:54:31 | I13: 续费原因：续费27考研；该学生为保护期内续费，原顾问：国内大学部-谭悦(tanyue9@xdf.cn) | K13: 大二 | L13: 谭悦 | M13: 转介绍 | N13: 学管续费推荐 | O13: 许庆典xuqingdian@xdf.cn | R13: 杨显婷 | S13: 谭悦 | T13: 29440654 | U13: 续费工单 | V13: 2025-07-31 20:06 | W13: A（六个月内有报课意向工单） | X13: 考研专业课,考研无忧计划 | Y13: 大二 | Z13: 北京物资学院 | AA13: 信息学院 | AB13: 应用统计学 | AC13: 杨显婷 | AD13: 5528120 | AE13: 谭悦 | AF13: 2025-07-31 20:06 | AG13: 谭悦 | AH13: 2025-07-31 20:06 | AI13: WYP27006 | AJ13: 考研政治无忧计划（27考研/冲刺） | AK13: 国内考试 | AM13: 4275 | AN13: 同科续费 | AO13: 许庆典 | AP13: 续班 | AQ13: 已交接 | AR13: BJWY2101498uW2 | AS13: BJWY5113272165 | AT13: WYP270060012 | AU13: 2025-07-31 | AW13: 回访人：谭悦，回访时间：2025-07-31 20:06，回访内容：27考研 | BB13: 44495810 | BC13: 否 | BD13: 27考季 | BE13: 无忧计划-啄木鸟,考研专业课150 | BF13: 英语,政治,数学,专业课150 | BG13: 其他 | BH13: 国内高校-双非 | BI13: 是 | BL13: 报名 | BN13: 本地人本地大学(常规) | BO13: 学管续费推荐
A14: 地面业绩 | B14: 4 | C14: 北京大学部 | D14: 国内大学部 | E14: 杨显婷 | F14: 121602812 | G14: 许庆典 | H14: 2025-07-31 19:54:31 | I14: 续费原因：续费27考研；该学生为保护期内续费，原顾问：国内大学部-谭悦(tanyue9@xdf.cn) | K14: 大二 | L14: 谭悦 | M14: 转介绍 | N14: 学管续费推荐 | O14: 许庆典xuqingdian@xdf.cn | R14: 杨显婷 | S14: 谭悦 | T14: 29440654 | U14: 续费工单 | V14: 2025-07-31 20:06 | W14: A（六个月内有报课意向工单） | X14: 考研专业课,考研无忧计划 | Y14: 大二 | Z14: 北京物资学院 | AA14: 信息学院 | AB14: 应用统计学 | AC14: 杨显婷 | AD14: 5528120 | AE14: 谭悦 | AF14: 2025-07-31 20:06 | AG14: 谭悦 | AH14: 2025-07-31 20:06 | AI14: WYE27026 | AJ14: 考研英语无忧计划（27考研/英二冲刺） | AK14: 国内考试 | AM14: 5250 | AN14: 同科续费 | AO14: 许庆典 | AP14: 续班 | AQ14: 已交接 | AR14: BJWY2101498uW2 | AS14: BJWY5113272165 | AT14: WYE270260019 | AU14: 2025-07-31 | AW14: 回访人：谭悦，回访时间：2025-07-31 20:06，回访内容：27考研 | BB14: 44495810 | BC14: 否 | BD14: 27考季 | BE14: 无忧计划-啄木鸟,考研专业课150 | BF14: 英语,政治,数学,专业课150 | BG14: 其他 | BH14: 国内高校-双非 | BI14: 是 | BL14: 报名 | BN14: 本地人本地大学(常规) | BO14: 学管续费推荐
A15: 地面业绩 | B15: 5 | C15: 北京大学部 | D15: 国内大学部 | E15: 杨显婷 | F15: 121602812 | G15: 许庆典 | H15: 2025-07-31 19:54:31 | I15: 续费原因：续费27考研；该学生为保护期内续费，原顾问：国内大学部-谭悦(tanyue9@xdf.cn) | K15: 大二 | L15: 谭悦 | M15: 转介绍 | N15: 学管续费推荐 | O15: 许庆典xuqingdian@xdf.cn | R15: 杨显婷 | S15: 谭悦 | T15: 29440654 | U15: 续费工单 | V15: 2025-07-31 20:06 | W15: A（六个月内有报课意向工单） | X15: 考研专业课,考研无忧计划 | Y15: 大二 | Z15: 北京物资学院 | AA15: 信息学院 | AB15: 应用统计学 | AC15: 杨显婷 | AD15: 5528120 | AE15: 谭悦 | AF15: 2025-07-31 20:06 | AG15: 谭悦 | AH15: 2025-07-31 20:06 | AI15: WYE27004 | AJ15: 考研英语无忧计划（27考研/英二强化） | AK15: 国内考试 | AM15: 6300 | AN15: 同科续费 | AO15: 许庆典 | AP15: 续班 | AQ15: 已交接 | AR15: BJWY2101498uW2 | AS15: BJWY5113272165 | AT15: WYE270040026 | AU15: 2025-07-31 | AW15: 回访人：谭悦，回访时间：2025-07-31 20:06，回访内容：27考研 | BB15: 44495810 | BC15: 否 | BD15: 27考季 | BE15: 无忧计划-啄木鸟,考研专业课150 | BF15: 英语,政治,数学,专业课150 | BG15: 其他 | BH15: 国内高校-双非 | BI15: 是 | BL15: 报名 | BN15: 本地人本地大学(常规) | BO15: 学管续费推荐
A16: 地面业绩 | B16: 6 | C16: 北京大学部 | D16: 国内大学部 | E16: 杨显婷 | F16: 121602812 | G16: 许庆典 | H16: 2025-07-31 19:54:31 | I16: 续费原因：续费27考研；该学生为保护期内续费，原顾问：国内大学部-谭悦(tanyue9@xdf.cn) | K16: 大二 | L16: 谭悦 | M16: 转介绍 | N16: 学管续费推荐 | O16: 许庆典xuqingdian@xdf.cn | R16: 杨显婷 | S16: 谭悦 | T16: 29440654 | U16: 续费工单 | V16: 2025-07-31 20:06 | W16: A（六个月内有报课意向工单） | X16: 考研专业课,考研无忧计划 | Y16: 大二 | Z16: 北京物资学院 | AA16: 信息学院 | AB16: 应用统计学 | AC16: 杨显婷 | AD16: 5528120 | AE16: 谭悦 | AF16: 2025-07-31 20:06 | AG16: 谭悦 | AH16: 2025-07-31 20:06 | AI16: WYM27010 | AJ16: 考研数学无忧计划（27考研/冲刺） | AK16: 国内考试 | AM16: 5400 | AN16: 同科续费 | AO16: 许庆典 | AP16: 续班 | AQ16: 已交接 | AR16: BJWY2101498uW2 | AS16: BJWY5113272165 | AT16: WYM270100025 | AU16: 2025-07-31 | AW16: 回访人：谭悦，回访时间：2025-07-31 20:06，回访内容：27考研 | BB16: 44495810 | BC16: 否 | BD16: 27考季 | BE16: 无忧计划-啄木鸟,考研专业课150 | BF16: 英语,政治,数学,专业课150 | BG16: 其他 | BH16: 国内高校-双非 | BI16: 是 | BL16: 报名 | BN16: 本地人本地大学(常规) | BO16: 学管续费推荐
A17: 地面业绩 | B17: 7 | C17: 北京大学部 | D17: 国内大学部 | E17: 杨显婷 | F17: 121602812 | G17: 许庆典 | H17: 2025-07-31 19:54:31 | I17: 续费原因：续费27考研；该学生为保护期内续费，原顾问：国内大学部-谭悦(tanyue9@xdf.cn) | K17: 大二 | L17: 谭悦 | M17: 转介绍 | N17: 学管续费推荐 | O17: 许庆典xuqingdian@xdf.cn | R17: 杨显婷 | S17: 谭悦 | T17: 29440654 | U17: 续费工单 | V17: 2025-07-31 20:06 | W17: A（六个月内有报课意向工单） | X17: 考研专业课,考研无忧计划 | Y17: 大二 | Z17: 北京物资学院 | AA17: 信息学院 | AB17: 应用统计学 | AC17: 杨显婷 | AD17: 5528120 | AE17: 谭悦 | AF17: 2025-07-31 20:06 | AG17: 谭悦 | AH17: 2025-07-31 20:06 | AI17: WYE27006 | AJ17: 考研英语无忧计划（27考研/基础） | AK17: 国内考试 | AM17: 4800 | AN17: 同科续费 | AO17: 许庆典 | AP17: 续班 | AQ17: 已交接 | AR17: BJWY2101498uW2 | AS17: BJWY5113272165 | AT17: WYE270060023 | AU17: 2025-07-31 | AW17: 回访人：谭悦，回访时间：2025-07-31 20:06，回访内容：27考研 | BB17: 44495810 | BC17: 否 | BD17: 27考季 | BE17: 无忧计划-啄木鸟,考研专业课150 | BF17: 英语,政治,数学,专业课150 | BG17: 其他 | BH17: 国内高校-双非 | BI17: 是 | BL17: 报名 | BN17: 本地人本地大学(常规) | BO17: 学管续费推荐
A18: 地面业绩 | B18: 8 | C18: 北京大学部 | D18: 国内大学部 | E18: 杨显婷 | F18: 121602812 | G18: 许庆典 | H18: 2025-07-31 19:54:31 | I18: 续费原因：续费27考研；该学生为保护期内续费，原顾问：国内大学部-谭悦(tanyue9@xdf.cn) | K18: 大二 | L18: 谭悦 | M18: 转介绍 | N18: 学管续费推荐 | O18: 许庆典xuqingdian@xdf.cn | R18: 杨显婷 | S18: 谭悦 | T18: 29440654 | U18: 续费工单 | V18: 2025-07-31 20:06 | W18: A（六个月内有报课意向工单） | X18: 考研专业课,考研无忧计划 | Y18: 大二 | Z18: 北京物资学院 | AA18: 信息学院 | AB18: 应用统计学 | AC18: 杨显婷 | AD18: 5528120 | AE18: 谭悦 | AF18: 2025-07-31 20:06 | AG18: 谭悦 | AH18: 2025-07-31 20:06 | AI18: WYP27004 | AJ18: 考研政治无忧计划（27考研/基础） | AK18: 国内考试 | AM18: 6225 | AN18: 同科续费 | AO18: 许庆典 | AP18: 续班 | AQ18: 已交接 | AR18: BJWY2101498uW2 | AS18: BJWY5113272165 | AT18: WYP270040012 | AU18: 2025-07-31 | AW18: 回访人：谭悦，回访时间：2025-07-31 20:06，回访内容：27考研 | BB18: 44495810 | BC18: 否 | BD18: 27考季 | BE18: 无忧计划-啄木鸟,考研专业课150 | BF18: 英语,政治,数学,专业课150 | BG18: 其他 | BH18: 国内高校-双非 | BI18: 是 | BL18: 报名 | BN18: 本地人本地大学(常规) | BO18: 学管续费推荐
A19: 地面业绩 | B19: 9 | C19: 北京大学部 | D19: 国内大学部 | E19: 杨显婷 | F19: 121602812 | G19: 许庆典 | H19: 2025-07-31 19:54:31 | I19: 续费原因：续费27考研；该学生为保护期内续费，原顾问：国内大学部-谭悦(tanyue9@xdf.cn) | K19: 大二 | L19: 谭悦 | M19: 转介绍 | N19: 学管续费推荐 | O19: 许庆典xuqingdian@xdf.cn | R19: 杨显婷 | S19: 谭悦 | T19: 29440654 | U19: 续费工单 | V19: 2025-07-31 20:06 | W19: A（六个月内有报课意向工单） | X19: 考研专业课,考研无忧计划 | Y19: 大二 | Z19: 北京物资学院 | AA19: 信息学院 | AB19: 应用统计学 | AC19: 杨显婷 | AD19: 5528120 | AE19: 谭悦 | AF19: 2025-07-31 20:06 | AG19: 谭悦 | AH19: 2025-07-31 20:06 | AI19: WYM27001 | AJ19: 考研数学无忧计划（27考研/基础） | AK19: 国内考试 | AM19: 4350 | AN19: 同科续费 | AO19: 许庆典 | AP19: 续班 | AQ19: 已交接 | AR19: BJWY2101498uW2 | AS19: BJWY5113272165 | AT19: WYM270010036 | AU19: 2025-07-31 | AW19: 回访人：谭悦，回访时间：2025-07-31 20:06，回访内容：27考研 | BB19: 44495810 | BC19: 否 | BD19: 27考季 | BE19: 无忧计划-啄木鸟,考研专业课150 | BF19: 英语,政治,数学,专业课150 | BG19: 其他 | BH19: 国内高校-双非 | BI19: 是 | BL19: 报名 | BN19: 本地人本地大学(常规) | BO19: 学管续费推荐
A20: 地面业绩 | B20: 10 | C20: 北京大学部 | D20: 国内大学部 | E20: 杨显婷 | F20: 121602812 | G20: 许庆典 | H20: 2025-07-31 19:54:31 | I20: 续费原因：续费27考研；该学生为保护期内续费，原顾问：国内大学部-谭悦(tanyue9@xdf.cn) | K20: 大二 | L20: 谭悦 | M20: 转介绍 | N20: 学管续费推荐 | O20: 许庆典xuqingdian@xdf.cn | R20: 杨显婷 | S20: 谭悦 | T20: 29440654 | U20: 续费工单 | V20: 2025-07-31 20:06 | W20: A（六个月内有报课意向工单） | X20: 考研专业课,考研无忧计划 | Y20: 大二 | Z20: 北京物资学院 | AA20: 信息学院 | AB20: 应用统计学 | AC20: 杨显婷 | AD20: 5528120 | AE20: 谭悦 | AF20: 2025-07-31 20:06 | AG20: 谭悦 | AH20: 2025-07-31 20:06 | AI20: LP17539617712673 | AJ20: 考研初试专业课一对一（27考研/无忧30小时） | AK20: 国内考试 | AM20: 9000 | AN20: 同科续费 | AO20: 许庆典 | AP20: 续班 | AQ20: 已交接 | AR20: BJWY2101498uW2 | AS20: BJWY5113272165 | AU20: 2025-07-31 | AW20: 回访人：谭悦，回访时间：2025-07-31 20:06，回访内容：27考研 | BB20: 44495810 | BC20: 否 | BD20: 27考季 | BE20: 无忧计划-啄木鸟,考研专业课150 | BF20: 英语,政治,数学,专业课150 | BG20: 其他 | BH20: 国内高校-双非 | BI20: 是 | BN20: 本地人本地大学(常规) | BO20: 学管续费推荐
A21: 地面业绩 | B21: 11 | C21: 北京大学部 | D21: 国内大学部 | E21: 杨希恒 | F21: 121517724 | G21: 段同飞 | H21: 2025-07-30 22:05:58 | I21: 同学介绍的，转谭悦 | K21: 大四 | L21: 谭悦 | M21: 转介绍 | N21: 顾问转介绍-老带新 | O21: 谭悦tanyue9@xdf.cn | R21: 杨希恒 | S21: 谭悦 | T21: 29435689 | U21: 正常工单 | V21: 2025-07-31 12:15 | W21: A（六个月内有报课意向工单） | X21: 考研无忧计划 | Y21: 大四 | Z21: 北京化工大学 | AA21: 材料科学与工程学院 | AB21: 高分子材料与工程精英班 | AC21: 杨希恒 | AD21: 5528086 | AE21: 谭悦 | AF21: 2025-07-31 19:51 | AG21: 谭悦 | AH21: 2025-07-31 19:51 | AI21: GWYM26001 | AJ21: 考研数学无忧计划考前突破班（26考研/专项突破） | AK21: 国内考试 | AM21: 7600 | AO21: 谭悦 | AP21: 新签 | AQ21: 已交接 | AR21: BJWY2101498uW2 | AS21: BJWY2409130365 | AT21: GWYM260010002 | AU21: 2025-07-31 | AW21: 回访人：谭悦，回访时间：2025-07-31 12:15，回访内容：26考研，英语政治刚开始备考，考虑上课学习 ；|回访人：谭悦，回访时间：2025-07-31 19:51，回访内容：签约 | BB21: 30795044 | BC21: 否 | BD21: 26考季 | BE21: 无忧计划-蜂鸟 | BF21: 英语,政治,数学 | BG21: 其他 | BH21: 国内高校-211 | BI21: 是 | BL21: 报名 | BN21: 外地人本地大学(常规) | BO21: 客服
A22: 地面业绩 | B22: 12 | C22: 北京大学部 | D22: 国内大学部 | E22: 杨希恒 | F22: 121517724 | G22: 段同飞 | H22: 2025-07-30 22:05:58 | I22: 同学介绍的，转谭悦 | K22: 大四 | L22: 谭悦 | M22: 转介绍 | N22: 顾问转介绍-老带新 | O22: 谭悦tanyue9@xdf.cn | R22: 杨希恒 | S22: 谭悦 | T22: 29435689 | U22: 正常工单 | V22: 2025-07-31 12:15 | W22: A（六个月内有报课意向工单） | X22: 考研无忧计划 | Y22: 大四 | Z22: 北京化工大学 | AA22: 材料科学与工程学院 | AB22: 高分子材料与工程精英班 | AC22: 杨希恒 | AD22: 5528086 | AE22: 谭悦 | AF22: 2025-07-31 19:51 | AG22: 谭悦 | AH22: 2025-07-31 19:51 | AI22: GWYP26001 | AJ22: 考研政治无忧计划考前突破班（26考研/刷题带背） | AK22: 国内考试 | AM22: 7100 | AO22: 谭悦 | AP22: 新签 | AQ22: 已交接 | AR22: BJWY2101498uW2 | AS22: BJWY2409130365 | AT22: GWYP260010005 | AU22: 2025-07-31 | AW22: 回访人：谭悦，回访时间：2025-07-31 12:15，回访内容：26考研，英语政治刚开始备考，考虑上课学习 ；|回访人：谭悦，回访时间：2025-07-31 19:51，回访内容：签约 | BB22: 30795044 | BC22: 否 | BD22: 26考季 | BE22: 无忧计划-蜂鸟 | BF22: 英语,政治,数学 | BG22: 其他 | BH22: 国内高校-211 | BI22: 是 | BL22: 报名 | BN22: 外地人本地大学(常规) | BO22: 客服
A23: 地面业绩 | B23: 13 | C23: 北京大学部 | D23: 国内大学部 | E23: 杨希恒 | F23: 121517724 | G23: 段同飞 | H23: 2025-07-30 22:05:58 | I23: 同学介绍的，转谭悦 | K23: 大四 | L23: 谭悦 | M23: 转介绍 | N23: 顾问转介绍-老带新 | O23: 谭悦tanyue9@xdf.cn | R23: 杨希恒 | S23: 谭悦 | T23: 29435689 | U23: 正常工单 | V23: 2025-07-31 12:15 | W23: A（六个月内有报课意向工单） | X23: 考研无忧计划 | Y23: 大四 | Z23: 北京化工大学 | AA23: 材料科学与工程学院 | AB23: 高分子材料与工程精英班 | AC23: 杨希恒 | AD23: 5528086 | AE23: 谭悦 | AF23: 2025-07-31 19:51 | AG23: 谭悦 | AH23: 2025-07-31 19:51 | AI23: GWYE26001 | AJ23: 考研英语无忧计划考前突破班（26考研/英语一） | AK23: 国内考试 | AM23: 7100 | AO23: 谭悦 | AP23: 新签 | AQ23: 已交接 | AR23: BJWY2101498uW2 | AS23: BJWY2409130365 | AT23: GWYE260010003 | AU23: 2025-07-31 | AW23: 回访人：谭悦，回访时间：2025-07-31 12:15，回访内容：26考研，英语政治刚开始备考，考虑上课学习 ；|回访人：谭悦，回访时间：2025-07-31 19:51，回访内容：签约 | BB23: 30795044 | BC23: 否 | BD23: 26考季 | BE23: 无忧计划-蜂鸟 | BF23: 英语,政治,数学 | BG23: 其他 | BH23: 国内高校-211 | BI23: 是 | BL23: 报名 | BN23: 外地人本地大学(常规) | BO23: 客服
A24: 地面业绩 | B24: 14 | C24: 北京大学部 | D24: 国内大学部 | F24: 92994255 | H24: 2025-01-13 16:06:45 | I24: 赵星火老师死单激活资源；赵星火老师死单激活资源 外呼主题：FY24-国内9月死单回访（第四周） 赵星火老师死单激活资源(资源备注人:吴凯龙;资源备注时间:2025-01-13 16:07) | K24: 大三 | L24: 赵星火 | M24: 线上运营-投放 | N24: 百度投放 | R24: 陈廷进 | S24: 高龙明 | T24: 29460345 | U24: 续费工单 | V24: 2025-07-31 18:11 | W24: A（六个月内有报课意向工单） | X24: 考研集训营 | Y24: 大学已毕业 | Z24: 吉林大学 | AA24: 物理学院 | AB24: 物理学 | AC24: 陈廷进 | AD24: 5527877 | AE24: 赵星火 | AF24: 2025-07-31 18:24 | AG24: 高龙明 | AH24: 2025-07-31 18:25 | AK24: 国内考试 | AM24: 1417.5 | AP24: 分单 | AQ24: 无须交接 | AS24: BJWY4776417923 | AW24: 回访人：高龙明，回访时间：2025-07-31 18:11，回访内容：转；|回访人：高龙明，回访时间：2025-07-31 18:11，回访内容：报；|回访人：高龙明，回访时间：2025-07-31 18:19，回访内容：高龙明进行了退单操作!(本条回访记录由系统自动记录) | BB24: 62316553 | BC24: 否 | BD24: 26考季 | BE24: 半年集训营 | BF24: 英语 | BH24: 国内高校-985 | BI24: 否 | BN24: 外地人外地大学(常规)
A25: 代售网课 | B25: 15 | C25: 北京大学部 | D25: 国内大学部 | E25: 北京市5435 | F25: 120078696 | G25: 张亚男 | H25: 2025-07-21 16:45:27 | I25: 渠道录入来源：集团百度投放-易聊 意向城市：北京市 访客省/城市：北京市 qq: 访客静态ID：01000000034718308740867391835435 接待分组ID：51266 搜索引擎： 搜索词： 关键词： 设备类型：pc 访客IP：117.133.62.42 对话详细内容：AI-KvNH7xJ0CD 2025-07-21 16:44:01 您好同学，欢迎访问新东方考研官网，【新东方考研】全新升级，课程灵活多样，【考研全年集训营】【考研半年集训营】【考研冲刺营】【线下走读班】【考研一对一】【在职考研】【四六级】火热报名中 ，现在报名更有高达3000元优惠！ AI-KvNH7xJ0CD 2025-07-21 16:44:03 您是想咨询【考研走读班】【考研集训营】【考研规划】还是【在职考研】呢？ 01000000034718308740867391835435 2025-07-21 16:44:27 【在职考研】 AI-KvNH7xJ0CD 2025-07-21 16:44:31 您准备[在职读研] 还是[离职读研] ?**在职读研# **离职读研# 01000000034718308740867391835435 2025-07-21 16:44:36 在职读研 AI-KvNH7xJ0CD 2025-07-21 16:44:40 具体是想报考什么学校和专业呢？ 01000000034718308740867391835435 2025-07-21 16:44:53 人民大学 应用心理学 AI-KvNH7xJ0CD 2025-07-21 16:44:57 好的，了解。我们新东方在全国32个城市都有校区，您倾向在哪个城市上课，或者希望哪里的老师给您介绍下呢？ 01000000034718308740867391835435 2025-07-21 16:45:07 北京 AI-KvNH7xJ0CD 2025-07-21 16:45:11 您可以留下您的姓名和电话，我这边可以立刻安排对应校区顾问老师给您回电！ 01000000034718308740867391835435 2025-07-21 16:45:26 张惠晴 13716251966 来源页：https://click.xdf.cn/ 备注： | J25: 2026财年第2财月百度投放总部-百度投放 | L25: 谭悦 | M25: 线上运营-投放 | N25: 总部-百度投放 | R25: grace | S25: 谭悦 | T25: 29254778 | U25: 正常工单 | V25: 2025-07-31 13:30 | W25: A（六个月内有报课意向工单） | X25: 线上考研产品 | Y25: 在职 | Z25: 中国人民大学 | AA25: 社会与人口学院 | AB25: 社会工作 | AC25: grace | AD25: 5527161 | AE25: 谭悦 | AF25: 2025-07-31 14:11 | AG25: 谭悦 | AH25: 2025-07-31 14:12 | AI25: 33782039713 | AJ25: 2026考研英语直通车 6期 | AK25: 国内考试 | AM25: 6791.5 | AP25: 新签 | AQ25: 无须交接 | AU25: 2025-07-31 | AW25: 回访人：谭悦，回访时间：2025-07-24 21:34，回访内容：微信跟进中 考研学习 ；|回访人：谭悦，回访时间：2025-07-30 16:42，回访内容：不回复消息 ；|回访人：吴凯龙，回访时间：2025-07-31 13:30，回访内容：吴凯龙恢复工单, 系统自动生成回访记录!；|回访人：谭悦，回访时间：2025-07-31 14:11，回访内容：1 | BA25: 长期班 | BB25: 82103592 | BC25: 是 | BD25: 26考季 | BE25: 线上直通车 | BF25: 英语 | BG25: 其他 | BH25: 国内高校-985 | BI25: 否 | BM25: 110624761 | BO25: 百度投放
A26: 代售网课 | B26: 16 | C26: 北京大学部 | D26: 国内大学部 | E26: 未知 | F26: 121602784 | G26: 李雪68 | H26: 2025-07-31 19:33:50 | I26: 激活 | K26: 大四 | L26: 赵星火 | M26: 毛坯数据 | N26: 毛坯数据 | R26: 韩月鹏 | S26: 赵星火 | T26: 29460986 | U26: 正常工单 | V26: 2025-07-31 20:01 | W26: A（六个月内有报课意向工单） | X26: 线上考研产品 | Y26: 大四 | Z26: 北京工业大学 | AA26: 北京-都柏林国际学院 | AB26: 电子信息工程1 | AC26: 韩月鹏 | AD26: 5500336 | AE26: 赵星火 | AF26: 2025-07-31 20:01 | AG26: 赵星火 | AH26: 2025-07-31 20:02 | AI26: 01384944814 | AJ26: 2026考研直通车VIP【计算机】,2026考研英语直通车 6期,2026考研数学直通车 6期,2026考研政治直通车 6期 | AK26: 国内考试 | AM26: 17136 | AP26: 新签 | AQ26: 无须交接 | AU26: 2025-07-31 | AW26: 回访人：赵星火，回访时间：2025-07-31 20:01，回访内容：签约 | BA26: 长期班,长期班,长期班,长期班 | BB26: 30923959 | BC26: 是 | BD26: 26考季 | BE26: 线上直通车 | BF26: 计算机 | BG26: 计算机 | BH26: 国内高校-211 | BI26: 否 | BM26: 109947422 | BN26: 本地人本地大学(常规) | BO26: 客服
A27: 地面业绩 | B27: 17 | C27: 北京大学部 | D27: 国内大学部 | F27: 121258774 | H27: 2025-07-30 12:45:19 | I27: 续费原因：学生决定考浙江大学，辛苦联系黄禹淇的妈妈收取一下升级费3000；该学生为保护期内续费，原顾问：国内大学部-谭悦(tanyue9@xdf.cn) | K27: 大四 | L27: 谭悦 | M27: 转介绍 | N27: 学管续费推荐 | R27: 黄禹淇 | S27: 谭悦 | T27: 29422728 | U27: 续费工单 | V27: 2025-07-30 18:55 | W27: A（六个月内有报课意向工单） | X27: 考研无忧计划 | Y27: 大四 | Z27: 北京交通大学 | AA27: 机械与电子控制工程学院 | AB27: 机械工程 | AC27: 黄禹淇 | AD27: 5526455 | AE27: 谭悦 | AF27: 2025-07-30 18:55 | AG27: 谭悦 | AH27: 2025-07-30 18:56 | AI27: WYE26003 | AJ27: 考研英语无忧计划（26考研/英一冲刺） | AK27: 国内考试 | AM27: 2965.2 | AN27: 同科续费 | AP27: 续班 | AQ27: 无须交接 | AR27: BJWY24032w1g8X | AS27: BJWY4049653605 | AT27: WYE260030072 | AU27: 2025-07-30 | AW27: 回访人：谭悦，回访时间：2025-07-30 18:55，回访内容：转班；|回访人：谭悦，回访时间：2025-07-30 18:55，回访内容：1 | BB27: 60647114 | BC27: 否 | BD27: 26考季 | BE27: 无忧计划-啄木鸟 | BF27: 英语 | BH27: 国内高校-211 | BI27: 否 | BL27: 转出 | BN27: 本地人本地大学(常规)
A28: 地面业绩 | B28: 18 | C28: 北京大学部 | D28: 国内大学部 | F28: 121258774 | H28: 2025-07-30 12:45:19 | I28: 续费原因：学生决定考浙江大学，辛苦联系黄禹淇的妈妈收取一下升级费3000；该学生为保护期内续费，原顾问：国内大学部-谭悦(tanyue9@xdf.cn) | K28: 大四 | L28: 谭悦 | M28: 转介绍 | N28: 学管续费推荐 | R28: 黄禹淇 | S28: 谭悦 | T28: 29422728 | U28: 续费工单 | V28: 2025-07-30 18:55 | W28: A（六个月内有报课意向工单） | X28: 考研无忧计划 | Y28: 大四 | Z28: 北京交通大学 | AA28: 机械与电子控制工程学院 | AB28: 机械工程 | AC28: 黄禹淇 | AD28: 5526455 | AE28: 谭悦 | AF28: 2025-07-30 18:55 | AG28: 谭悦 | AH28: 2025-07-30 18:56 | AI28: WYE26002 | AJ28: 考研英语无忧计划（26考研/英一强化） | AK28: 国内考试 | AM28: 2732.2 | AN28: 同科续费 | AP28: 续班 | AQ28: 无须交接 | AR28: BJWY24032w1g8X | AS28: BJWY4049653605 | AT28: WYE260020071 | AU28: 2025-07-30 | AW28: 回访人：谭悦，回访时间：2025-07-30 18:55，回访内容：转班；|回访人：谭悦，回访时间：2025-07-30 18:55，回访内容：1 | BB28: 60647114 | BC28: 否 | BD28: 26考季 | BE28: 无忧计划-啄木鸟 | BF28: 英语 | BH28: 国内高校-211 | BI28: 否 | BL28: 转出 | BN28: 本地人本地大学(常规)
A29: 地面业绩 | B29: 19 | C29: 北京大学部 | D29: 国内大学部 | F29: 90288454 | H29: 2024-12-09 20:46:29 | I29: 在校，考中国科学院大学 遥感方面的都行 IP：北京 | K29: 未知 | L29: 赵星火 | M29: 线上运营-投放 | N29: 其他网络投放 | R29: 朱博政 | S29: 赵星火 | T29: 29421355 | U29: 续费工单 | V29: 2025-07-30 17:05 | W29: A（六个月内有报课意向工单） | X29: 考研专业课,考研无忧计划 | Y29: 大四 | Z29: 中国传媒大学 | AA29: 信息与通信工程学院 | AB29: 通信工程 | AC29: 朱博政 | AD29: 5526266 | AE29: 赵星火 | AF29: 2025-07-30 17:06 | AG29: 赵星火 | AH29: 2025-07-30 17:07 | AI29: WYE26026 | AJ29: 考研英语无忧计划（26考研/英一强化） | AK29: 国内考试 | AM29: 3812.8 | AN29: 同科续费 | AP29: 续班 | AQ29: 无须交接 | AR29: BJWY2101498uW2 | AS29: BJWY5552920417 | AT29: WYE260260066 | AU29: 2025-07-30 | AW29: 回访人：赵星火，回访时间：2025-07-30 17:05，回访内容：1；|回访人：赵星火，回访时间：2025-07-30 17:06，回访内容：1 | BB29: 65132392 | BC29: 否 | BD29: 26考季 | BE29: 无忧计划-啄木鸟,考研专业课150 | BF29: 英语,政治,数学,专业课150 | BH29: 国内高校-211 | BI29: 否 | BL29: 转出 | BN29: 本地人本地大学(常规)
A30: 地面业绩 | B30: 20 | C30: 北京大学部 | D30: 国内大学部 | F30: 90288454 | H30: 2024-12-09 20:46:29 | I30: 在校，考中国科学院大学 遥感方面的都行 IP：北京 | K30: 未知 | L30: 赵星火 | M30: 线上运营-投放 | N30: 其他网络投放 | R30: 朱博政 | S30: 赵星火 | T30: 29421355 | U30: 续费工单 | V30: 2025-07-30 17:05 | W30: A（六个月内有报课意向工单） | X30: 考研专业课,考研无忧计划 | Y30: 大四 | Z30: 中国传媒大学 | AA30: 信息与通信工程学院 | AB30: 通信工程 | AC30: 朱博政 | AD30: 5526266 | AE30: 赵星火 | AF30: 2025-07-30 17:06 | AG30: 赵星火 | AH30: 2025-07-30 17:07 | AI30: WYE26027 | AJ30: 考研英语无忧计划（26考研/英一冲刺） | AK30: 国内考试 | AM30: 3177.3 | AN30: 同科续费 | AP30: 续班 | AQ30: 无须交接 | AR30: BJWY2101498uW2 | AS30: BJWY5552920417 | AT30: WYE260270064 | AU30: 2025-07-30 | AW30: 回访人：赵星火，回访时间：2025-07-30 17:05，回访内容：1；|回访人：赵星火，回访时间：2025-07-30 17:06，回访内容：1 | BB30: 65132392 | BC30: 否 | BD30: 26考季 | BE30: 无忧计划-啄木鸟,考研专业课150 | BF30: 英语,政治,数学,专业课150 | BH30: 国内高校-211 | BI30: 否 | BL30: 转出 | BN30: 本地人本地大学(常规)
A31: 地面业绩 | B31: 21 | C31: 北京大学部 | D31: 国内大学部 | E31: 黄禹淇 | F31: 121258774 | G31: 马一鸣 | H31: 2025-07-30 12:45:19 | I31: 续费原因：学生决定考浙江大学，辛苦联系黄禹淇的妈妈收取一下升级费3000；该学生为保护期内续费，原顾问：国内大学部-谭悦(tanyue9@xdf.cn) | K31: 大四 | L31: 谭悦 | M31: 转介绍 | N31: 学管续费推荐 | O31: 马一鸣mayiming16@xdf.cn | R31: 黄禹淇 | S31: 谭悦 | T31: 29428581 | U31: 续费工单 | V31: 2025-07-30 13:38 | W31: A（六个月内有报课意向工单） | X31: 考研专业课 | Y31: 大四 | Z31: 北京交通大学 | AA31: 机械与电子控制工程学院 | AB31: 机械工程 | AC31: 黄禹淇 | AD31: 5420608 | AE31: 谭悦 | AF31: 2025-07-30 13:40 | AG31: 谭悦 | AH31: 2025-07-30 14:11 | AI31: LP1753854023771 | AJ31: 985院校升级费-无忧 | AK31: 国内考试 | AM31: 3000 | AO31: 马一鸣 | AP31: 续班 | AQ31: 无须交接 | AS31: BJWY4049653605 | AU31: 2025-07-30 | AW31: 回访人：谭悦，回访时间：2025-07-30 13:38，回访内容：1 | BB31: 60647114 | BC31: 否 | BD31: 26考季 | BE31: 考研专业课150 | BF31: 专业课150 | BG31: 其他 | BH31: 国内高校-211 | BI31: 否 | BN31: 本地人本地大学(常规) | BO31: 学管续费推荐
A32: 代售网课 | B32: 22 | C32: 北京大学部 | D32: 国内大学部 | E32: 同学 | F32: 120882682 | G32: 方勃文 | H32: 2025-07-26 13:43:34 | I32: 咨询英语一一对一【已在群内反馈】 | K32: 大四 | L32: 赵星火 | M32: 线上运营-私域中台 | N32: 社群、虚拟人 | R32: Merih | S32: 赵星火 | T32: 29342786 | U32: 正常工单 | V32: 2025-07-27 14:45 | W32: A（六个月内有报课意向工单） | X32: 线上考研产品 | Y32: 大四 | Z32: 河北大学 | AA32: 管理学院 | AB32: 图书馆学 | AC32: Merih | AD32: 5420588 | AE32: 赵星火 | AF32: 2025-07-30 12:47 | AG32: 赵星火 | AH32: 2025-07-30 12:47 | AI32: 96565840801 | AJ32: 2026考研英语全程班 6班 | AK32: 国内考试 | AM32: 1096.5 | AP32: 新签 | AQ32: 无须交接 | AU32: 2025-07-30 | AW32: 回访人：赵星火，回访时间：2025-07-27 14:45，回访内容：联系不上学生微信上问下给到课程介绍跟进中；|回访人：赵星火，回访时间：2025-07-28 14:49，回访内容：跟进学生情况这边继续维护学生跟进中。；|回访人：赵星火，回访时间：2025-07-30 12:47，回访内容：1 | BA32: 长期班 | BB32: 82421047 | BC32: 是 | BD32: 26考季 | BE32: 线上全程班 | BH32: 国内高校-双非 | BI32: 否 | BM32: 110614822 | BN32: 本地人本地大学(常规) | BO32: 市场
A33: 代售网课 | B33: 23 | C33: 北京大学部 | D33: 国内大学部 | E33: 北京市6271 | F33: 120932120 | G33: 杨俊42(国内) | H33: 2025-07-28 08:56:20 | I33: 渠道录入来源：新东方官网M站-客服 意向城市：北京访客省/城市：北京市 访客静态ID：01000000034659366398395471906271 接待分组ID：70455 搜索引擎： 搜索词： 关键词： 设备类型：phone 访客IP：221.217.26.141 对话详细内容：AI-Lbo0rDBXCyBY 2025-07-28 08:53:08 您好同学,欢迎访问北京新东方考研四六级中心. 考研线下课程26/27考季【考研全年集训营】【考研半年集训营】【考研全科线下走读班】【考研寒/暑假集训营】【考研一对一】【考研专业课】【四/六级课程】，热门课程火热报名中,咨询即可领取专享优惠。 **【考研全年集训营】=ff761f# **【考研半年集训营】=ff6b6b# **【考研全科线下走读班】=ffc158# **【考研寒/暑假集训营】=ffc158# **【考研一对一】=ff761f# **【考研专业课】=ff6caa# **【四/六级课程】=ff6caa# **【考研冲刺班】=60e27e# AI-Lbo0rDBXCyBY 2025-07-28 08:53:11 您是想咨询【线下课程】【线上课程】【考研规划】还是【在职考研】呢？**【线下课程】# **【线上课程】#**【考研规划】#**【在职考研】# 01000000034659366398395471906271 2025-07-28 08:53:19 【在职考研】 AI-Lbo0rDBXCyBY 2025-07-28 08:53:23 您准备【边工作边读研]】还是【脱产读研】 ?**边工作边读研# **脱产读研# 01000000034659366398395471906271 2025-07-28 08:53:27 脱产读研 AI-Lbo0rDBXCyBY 2025-07-28 08:53:31 具体是想报考什么学校和专业呢？ 01000000034659366398395471906271 2025-07-28 08:53:46 北京理工大学软件工程硕士 AI-Lbo0rDBXCyBY 2025-07-28 08:53:50 好的，我这边安排专业老师给您回电，详细沟通一下，请问您的电话是多少呢？ 01000000034659366398395471906271 2025-07-28 08:54:18 18500224563 AI-Lbo0rDBXCyBY 2025-07-28 08:54:21 好的，确认一下你的号码是否正确呢~ 来源页：https://bj.xdf.cn/ 备注： | J33: 2026财年第2财月易聊新东方官网M站 | L33: 徐树萌 | M33: 新东方官网 | N33: 新东方官网M站 | P33: 徐树萌 | Q33: 2025-07-28 09:32:37 | R33: 北京市6271 | S33: 赵星火 | T33: 29345437 | U33: 正常工单 | V33: 2025-07-28 14:14 | W33: A（六个月内有报课意向工单） | X33: 线上考研产品 | Y33: 在职 | Z33: 北京工业大学耿丹学院 | AA33: 工学院 | AB33: 计算机科学与技术 | AC33: 北京市6271 | AD33: 5524661 | AE33: 赵星火 | AF33: 2025-07-29 10:09 | AG33: 赵星火 | AH33: 2025-07-29 10:11 | AI33: 58407124528 | AJ33: 2026考研英语一无忧计划·16期,2026考研政治无忧计划·13期,2026考研数学无忧计划·7期 | AK33: 国内考试 | AM33: 24471 | AP33: 新签 | AQ33: 无须交接 | AU33: 2025-07-29 | AW33: 回访人：赵星火，回访时间：2025-07-28 14:14，回访内容：基础薄弱这边想要考研，刚才开始准备，集训价格高，推荐线上小班课程继续维护中。 | BA33: 长期班,长期班,长期班 | BB33: 82475627 | BC33: 是 | BD33: 26考季 | BE33: 线上无忧计划 | BF33: 英语 | BG33: 计算机 | BH33: 国内高校-双非 | BI33: 否 | BM33: 110610561 | BO33: 易聊在线咨询
A34: 地面业绩 | B34: 24 | C34: 北京大学部 | D34: 国内大学部 | F34: 92994255 | H34: 2025-01-13 16:06:45 | I34: 赵星火老师死单激活资源；赵星火老师死单激活资源 外呼主题：FY24-国内9月死单回访（第四周） 赵星火老师死单激活资源(资源备注人:吴凯龙;资源备注时间:2025-01-13 16:07) | K34: 大三 | L34: 赵星火 | M34: 线上运营-投放 | N34: 百度投放 | R34: 陈廷进 | S34: 高龙明 | T34: 29432626 | U34: 续费工单 | V34: 2025-07-30 18:41 | W34: A（六个月内有报课意向工单） | X34: 考研集训营 | Y34: 大学已毕业 | Z34: 吉林大学 | AA34: 物理学院 | AB34: 物理学 | AC34: 陈廷进 | AD34: 5498616 | AE34: 赵星火 | AF34: 2025-07-30 18:41 | AG34: 高龙明 | AH34: 2025-07-30 18:43 | AK34: 国内考试 | AM34: 10855.2 | AN34: 同科续费 | AP34: 分单 | AQ34: 无须交接 | AS34: BJWY4776417923 | AW34: 回访人：高龙明，回访时间：2025-07-30 18:41，回访内容：转；|回访人：高龙明，回访时间：2025-07-30 18:41，回访内容：报 | BB34: 62316553 | BC34: 否 | BD34: 26考季 | BE34: 半年集训营 | BF34: 英语 | BH34: 国内高校-985 | BI34: 否 | BN34: 外地人外地大学(常规)
A35: 代售网课 | B35: 25 | C35: 北京大学部 | D35: 国内大学部 | E35: 叶宸羽 | F35: 119043886 | G35: 北京国内管理员 | H35: 2025-07-14 17:09:37 | I35: 渠道录入来源：SCRM-客服推送 商机ID：5009267870 商机编码：XSJ20250714027807 针对人群：大学 学生学校：不详 咨询课程：英语一 创建人邮箱：wangguibing@xdf.cn 创建时间：2025-07-14 17:09:33 资源类型：单个资源 跟进记录：商机备注：学员妈妈咨询考研课程，天津理工大学，咨询线上课程，27年考研，辛苦老师沟通;接触点：呼入； | K35: 大三 | L35: 赵星火 | M35: 新东方官网 | N35: 新东方PC官网 | R35: 叶宸羽 | S35: 赵星火 | T35: 29084490 | U35: 正常工单 | V35: 2025-07-14 18:32 | W35: A（六个月内有报课意向工单） | X35: 线上考研产品 | Y35: 大三 | Z35: 天津理工大学 | AA35: 管理学院 | AB35: 工商管理 | AC35: 叶宸羽 | AD35: 5494164 | AE35: 赵星火 | AF35: 2025-07-26 13:57 | AG35: 赵星火 | AH35: 2025-07-26 13:57 | AI35: 53555637604 | AJ35: 2027考研政治直通车 长线2期,2027考研数学直通车 长线2期,2027考研英语直通车 长线2期 | AK35: 国内考试 | AM35: 11902.8 | AP35: 新签 | AQ35: 无须交接 | AU35: 2025-07-26 | AW35: 回访人：赵星火，回访时间：2025-07-17 19:43，回访内容：电话呼出联系不上，微信继续问一下情况；|回访人：赵星火，回访时间：2025-07-20 16:04，回访内容：表示还没确定确定了这边再说跟进中。；|回访人：赵星火，回访时间：2025-07-23 16:16，回访内容：对比海文和新东方跟进学生情况中继续维护学生；|回访人：赵星火，回访时间：2025-07-25 19:43，回访内容：表示明后天这边确定一下跟进中继续维护中。；|回访人：赵星火，回访时间：2025-07-26 13:57，回访内容：1 | BA35: 长期班,长期班,长期班 | BB35: 81577565 | BC35: 是 | BD35: 27考季 | BE35: 线上直通车 | BF35: 英语 | BG35: 其他 | BH35: 国内高校-双非 | BI35: 否 | BM35: 110601979 | BN35: 外地人外地大学(常规) | BO35: SCRM-客服推送
A36: 地面业绩 | B36: 26 | C36: 北京大学部 | D36: 国内大学部 | E36: 蔡哲 | F36: 118843591 | G36: 陈晶 | H36: 2025-07-13 12:08:52 | I36: 续费原因：续费一对一；该学生为保护期内续费，原顾问：国内大学部-谭悦(tanyue9@xdf.cn) | K36: 大学已毕业 | L36: 谭悦 | M36: 转介绍 | N36: 学管续费推荐 | O36: 陈晶chenjing171@xdf.cn | R36: 蔡哲 | S36: 谭悦 | T36: 29060027 | U36: 续费工单 | V36: 2025-07-13 19:11 | W36: A（六个月内有报课意向工单） | X36: 考研VIP | Y36: 大学已毕业 | Z36: 北京邮电大学 | AA36: 信息与通信工程学院 | AB36: 电子信息工程 | AC36: 蔡哲 | AD36: 5418288 | AE36: 谭悦 | AF36: 2025-07-24 18:36 | AG36: 谭悦 | AH36: 2025-07-24 19:10 | AI36: LP17533534131898 | AJ36: 考研一对一伴学班（26考季） | AK36: 国内考试 | AM36: 15600 | AO36: 陈晶 | AP36: 续班 | AQ36: 已交接 | AS36: BJWY0874092650 | AU36: 2025-07-24 | AW36: 回访人：谭悦，回访时间：2025-07-20 18:25，回访内容：跟进续费中 | BB36: 33569231 | BC36: 否 | BD36: 26考季 | BE36: VIP - 伴学 | BF36: 英语,政治 | BG36: 其他 | BH36: 国内高校-211 | BI36: 是 | BO36: 学管续费推荐
A37: 地面业绩 | B37: 27 | C37: 北京大学部 | D37: 国内大学部 | F37: 115849673 | H37: 2025-06-23 15:33:28 | I37: 【考研】学生本人，北京农学院，大三，食品专业，想考中国农业大学，食品加工与安全专业，问士兵计划的分数，也要了解课程，线上还是线下课程没说，想先确定了解好学校分数，或者查北林，北农的分数加微信介绍；渠道录入来源：抖音新东方考研直播间 koouserID：110429453 城市：北京 产品分组：考研 线索来源：直播间小风车收资-大学生-线下面授 市场人员： 是否兼职： 备注信息：请选择当前所属阶段：:大三;请选择倾向的备考方式：:线下面授;请选择备考城市：:北京 外呼主题：2026财年第1财月抖音新东方考研直播间 | J37: 2026财年第1财月抖音新东方考研直播间 | K37: 大三 | L37: 谭悦 | M37: 线上运营-抖音 | N37: 抖音新东方考研直播间 | R37: 周靖程 | S37: 谭悦 | T37: 29252280 | U37: 续费工单 | V37: 2025-07-21 16:03 | W37: A（六个月内有报课意向工单） | X37: 考研专业课,考研集训营 | Y37: 大四 | Z37: 北京农学院 | AA37: 食品科学与工程学院 | AB37: 食品科学与工程 | AC37: 周靖程 | AD37: 5487404 | AE37: 谭悦 | AF37: 2025-07-21 16:14 | AG37: 谭悦 | AH37: 2025-07-21 16:16 | AI37: LP17530856811511 | AJ37: 985院校升级费-集训 | AK37: 国内考试 | AM37: 1500 | AP37: 续班 | AQ37: 已交接 | AS37: BJWY0787829408 | AU37: 2025-07-21 | AW37: 回访人：谭悦，回访时间：2025-07-21 16:03，回访内容：1 | BB37: 82087801 | BC37: 否 | BD37: 26考季 | BE37: 半年集训营,考研专业课300 | BF37: 英语,政治,专业课300 | BH37: 国内高校-双非 | BI37: 是 | BN37: 本地人本地大学(常规)
A38: 代售网课 | B38: 28 | C38: 北京大学部 | D38: 国内大学部 | E38: 杨 | F38: 119920344 | G38: 北京客服部 | H38: 2025-07-20 09:16:56 | I38: 政治和英语 | J38: 2026财年第2财月代理商 | L38: 乔文娇 | M38: 线上运营-商务合作 | N38: 米化 | P38: 乔文娇 | Q38: 2025-07-20 10:55:29 | R38: 王喆 | S38: 谭悦 | T38: 29212534 | U38: 正常工单 | V38: 2025-07-20 15:00 | W38: A（六个月内有报课意向工单） | X38: 线上考研产品 | Y38: 大四 | Z38: 北京物资学院 | AA38: 商学院 | AB38: 财务管理 | AC38: 王喆 | AD38: 5416998 | AE38: 谭悦 | AF38: 2025-07-21 16:02 | AG38: 谭悦 | AH38: 2025-07-21 16:02 | AI38: 69208835259 | AJ38: 2026考研英语一无忧计划·16期,2026考研政治无忧计划·12期 | AK38: 国内考试 | AM38: 15651 | AP38: 新签 | AQ38: 无须交接 | AU38: 2025-07-21 | AW38: 回访人：谭悦，回访时间：2025-07-20 15:00，回访内容：打电话非常强势，问英语政治，加微信叫温柔 ；|回访人：谭悦，回访时间：2025-07-21 16:02，回访内容：1 | BA38: 长期班,长期班 | BB38: 82071259 | BC38: 是 | BD38: 26考季 | BE38: 线上无忧计划 | BF38: 英语,政治 | BG38: 其他 | BH38: 国内高校-双非 | BI38: 否 | BM38: 107965657 | BN38: 本地人本地大学(常规) | BO38: 线下代理商
A39: 代售网课 | B39: 29 | C39: 北京大学部 | D39: 国内大学部 | E39: 赵家长 | F39: 119930462 | G39: 北京客服部 | H39: 2025-07-20 15:11:56 | I39: 赵家长 13601221052 首都经贸大学 马上大三 考研辅导 会计专硕 无意向机构 | J39: 2026财年第2财月代理商 | L39: 乔文娇 | M39: 线上运营-商务合作 | N39: 坦途网 | P39: 乔文娇 | Q39: 2025-07-20 15:26:41 | R39: 赵嘉华 | S39: 谭悦 | T39: 29212948 | U39: 正常工单 | V39: 2025-07-20 15:31 | W39: A（六个月内有报课意向工单） | X39: 线上考研产品 | Y39: 大三 | Z39: 首都经济贸易大学 | AA39: 会计学院 | AB39: 会计学1 | AC39: 赵嘉华 | AD39: 5486586 | AE39: 谭悦 | AF39: 2025-07-20 18:20 | AG39: 谭悦 | AH39: 2025-07-20 18:21 | AI39: 45051853639 | AJ39: 2026考研管综全科在校全程班（3期） | AK39: 国内考试 | AM39: 4139.5 | AP39: 新签 | AQ39: 无须交接 | AU39: 2025-07-20 | AW39: 回访人：谭悦，回访时间：2025-07-20 15:31，回访内容：马上过来面谈 ；|回访人：谭悦，回访时间：2025-07-20 18:20，回访内容：签约 | BA39: 长期班 | BB39: 82058266 | BC39: 是 | BD39: 26考季 | BE39: 线上全程班 | BF39: 英语,管综 | BG39: 其他 | BH39: 国内高校-双非 | BI39: 否 | BM39: 110572419 | BN39: 本地人本地大学(常规) | BO39: 线下代理商
A40: 代售网课 | B40: 30 | C40: 北京大学部 | D40: 国内大学部 | E40: 赵泽阳 | F40: 119012024 | G40: 北京国内管理员 | H40: 2025-07-14 17:08:22 | I40: 渠道录入来源：SCRM-客服推送 商机ID：5009282307 商机编码：XSJ20250714027730 针对人群：大学 学员号：BJ1221164274 学生学校：不详 咨询课程：不区分 创建人邮箱：liuxinyi91@xdf.cn 创建时间：2025-07-14 17:08:16 资源类型：单个资源 跟进记录：商机备注：孩子妈妈来电，孩子开学大三，想了解线上的考研公共课和专业课，四级过了，六级还没出分，辛苦顾问老师联系手机号2介绍，手机号2是学员自己的电话;接触点：呼入； | K40: 大三 | L40: 谭悦 | M40: 新东方官网 | N40: 新东方PC官网 | R40: 赵泽阳 | S40: 赵星火 | T40: 29084286 | U40: 续费工单 | V40: 2025-07-18 13:55 | W40: A（六个月内有报课意向工单） | X40: 线上考研产品 | Y40: 大三 | Z40: 北京物资学院 | AA40: 信息学院 | AB40: 信息工程 | AC40: 赵泽阳 | AD40: 5483935 | AE40: 赵星火 | AF40: 2025-07-18 13:57 | AG40: 赵星火 | AH40: 2025-07-18 13:57 | AI40: 17320768233 | AJ40: 2027考研政治直通车 长线2期,2027考研英语直通车 长线2期 | AK40: 国内考试 | AM40: 4443.6 | AP40: 续班 | AQ40: 无须交接 | AU40: 2025-07-18 | AW40: 回访人：谭悦，回访时间：2025-07-14 18:14，回访内容：人工智能，电子信息，27考研，学生想上网课 ；|回访人：谭悦，回访时间：2025-07-15 16:50，回访内容：考虑网课学习 ；|回访人：赵星火，回访时间：2025-07-18 13:57，回访内容：1 | BA40: 长期班,长期班 | BB40: 50793454 | BC40: 是 | BD40: 26考季 | BE40: 线上直通车 | BF40: 英语,政治 | BG40: 其他 | BH40: 国内高校-双非 | BI40: 否 | BM40: 107425955 | BN40: 本地人本地大学(常规) | BO40: SCRM-客服推送
A41: 地面业绩 | B41: 31 | C41: 北京大学部 | D41: 国内大学部 | E41: 赵泽阳 | F41: 119012024 | G41: 北京国内管理员 | H41: 2025-07-14 17:08:22 | I41: 渠道录入来源：SCRM-客服推送 商机ID：5009282307 商机编码：XSJ20250714027730 针对人群：大学 学员号：BJ1221164274 学生学校：不详 咨询课程：不区分 创建人邮箱：liuxinyi91@xdf.cn 创建时间：2025-07-14 17:08:16 资源类型：单个资源 跟进记录：商机备注：孩子妈妈来电，孩子开学大三，想了解线上的考研公共课和专业课，四级过了，六级还没出分，辛苦顾问老师联系手机号2介绍，手机号2是学员自己的电话;接触点：呼入； | K41: 大三 | L41: 谭悦 | M41: 新东方官网 | N41: 新东方PC官网 | R41: 赵泽阳 | S41: 赵星火 | T41: 29084286 | U41: 续费工单 | V41: 2025-07-18 13:55 | W41: A（六个月内有报课意向工单） | X41: 线上考研产品 | Y41: 大三 | Z41: 北京物资学院 | AA41: 信息学院 | AB41: 信息工程 | AC41: 赵泽阳 | AD41: 5455920 | AE41: 谭悦 | AF41: 2025-07-18 13:57 | AG41: 赵星火 | AH41: 2025-07-18 13:57 | AK41: 国内考试 | AM41: 4443.6 | AP41: 分单 | AQ41: 无须交接 | AW41: 回访人：谭悦，回访时间：2025-07-14 18:14，回访内容：人工智能，电子信息，27考研，学生想上网课 ；|回访人：谭悦，回访时间：2025-07-15 16:50，回访内容：考虑网课学习 ；|回访人：赵星火，回访时间：2025-07-18 13:57，回访内容：1 | BB41: 50793454 | BC41: 是 | BD41: 26考季 | BE41: 线上直通车 | BF41: 英语,政治 | BG41: 其他 | BH41: 国内高校-双非 | BI41: 否 | BN41: 本地人本地大学(常规) | BO41: SCRM-客服推送
A42: 地面业绩 | B42: 32 | C42: 北京大学部 | D42: 国内大学部 | F42: 90288454 | H42: 2024-12-09 20:46:29 | I42: 在校，考中国科学院大学 遥感方面的都行 IP：北京 | K42: 未知 | L42: 赵星火 | M42: 线上运营-投放 | N42: 其他网络投放 | R42: 朱博政 | S42: 赵星火 | T42: 29280070 | U42: 续费工单 | V42: 2025-07-23 14:21 | W42: A（六个月内有报课意向工单） | X42: 考研专业课,考研无忧计划 | Y42: 大四 | Z42: 中国传媒大学 | AA42: 信息与通信工程学院 | AB42: 通信工程 | AC42: 朱博政 | AD42: 5519037 | AE42: 赵星火 | AF42: 2025-07-23 14:21 | AG42: 赵星火 | AH42: 2025-07-23 14:21 | AI42: WYE26029 | AJ42: 考研英语无忧计划（26考研/英二冲刺） | AK42: 国内考试 | AM42: 3177.3 | AN42: 同科续费 | AP42: 续班 | AQ42: 无须交接 | AR42: BJWY24032w1g8X | AS42: BJWY5552920417 | AT42: WYE260290065 | AU42: 2025-07-16 | AW42: 回访人：赵星火，回访时间：2025-07-23 14:21，回访内容：1；|回访人：赵星火，回访时间：2025-07-23 14:21，回访内容：1 | BB42: 65132392 | BC42: 否 | BD42: 26考季 | BE42: 无忧计划-啄木鸟,考研专业课150 | BF42: 英语,政治,数学,专业课150 | BH42: 国内高校-211 | BI42: 否 | BL42: 转出 | BN42: 本地人本地大学(常规)
A43: 地面业绩 | B43: 33 | C43: 北京大学部 | D43: 国内大学部 | F43: 90288454 | H43: 2024-12-09 20:46:29 | I43: 在校，考中国科学院大学 遥感方面的都行 IP：北京 | K43: 未知 | L43: 赵星火 | M43: 线上运营-投放 | N43: 其他网络投放 | R43: 朱博政 | S43: 赵星火 | T43: 29280070 | U43: 续费工单 | V43: 2025-07-23 14:21 | W43: A（六个月内有报课意向工单） | X43: 考研专业课,考研无忧计划 | Y43: 大四 | Z43: 中国传媒大学 | AA43: 信息与通信工程学院 | AB43: 通信工程 | AC43: 朱博政 | AD43: 5519037 | AE43: 赵星火 | AF43: 2025-07-23 14:21 | AG43: 赵星火 | AH43: 2025-07-23 14:21 | AI43: WYE26028 | AJ43: 考研英语无忧计划（26考研/英二强化） | AK43: 国内考试 | AM43: 5083.7 | AN43: 同科续费 | AP43: 续班 | AQ43: 无须交接 | AR43: BJWY2101498uW2 | AS43: BJWY5552920417 | AT43: WYE260280066 | AU43: 2025-07-17 | AW43: 回访人：赵星火，回访时间：2025-07-23 14:21，回访内容：1；|回访人：赵星火，回访时间：2025-07-23 14:21，回访内容：1 | BB43: 65132392 | BC43: 否 | BD43: 26考季 | BE43: 无忧计划-啄木鸟,考研专业课150 | BF43: 英语,政治,数学,专业课150 | BH43: 国内高校-211 | BI43: 否 | BL43: 转出 | BN43: 本地人本地大学(常规)
A44: 代售网课 | B44: 34 | C44: 北京大学部 | D44: 国内大学部 | F44: 115551597 | H44: 2025-06-22 11:33:30 | I44: 渠道录入来源：总部-巨量广告 意向城市：北京市 访客省/城市：北京市 qq: 访客静态ID：01000003781500056303567923947307 接待分组ID：78500 搜索引擎： 搜索词： 关键词： 设备类型：phone 访客IP：111.196.228.49 对话详细内容：AI-37815-01a 2025-06-22 11:30:37 AI-37815-01a 2025-06-22 11:30:39 您好同学，欢迎访问新东方考研官网，【新东方考研】全新升级，课程灵活多样，【考研全年集训营】【考研半年集训营】【考研冲刺营】【线下走读班】【考研一对一】【在职考研】【四六级】火热报名中 ，现在报名更有高达3000元优惠！ AI-37815-01a 2025-06-22 11:30:41 您是想咨询【考研走读班】【考研集训营】【考研规划】还是【在职考研】呢？ 01000003781500056303567923947307 2025-06-22 11:31:10 老师，你好，专业课有培训吗？ AI-37815-01a 2025-06-22 11:31:14 同学，你现在是在校还是在职呢？ 01000003781500056303567923947307 2025-06-22 11:31:30 在校 AI-37815-01a 2025-06-22 11:31:34 具体是想报考什么学校和专业呢？ 01000003781500056303567923947307 2025-06-22 11:31:56 北理，人工智能 AI-37815-01a 2025-06-22 11:31:59 好的，了解。我们新东方在全国32个城市都有校区，您倾向在哪个城市上课，或者希望哪里的老师给您介绍下呢？ 01000003781500056303567923947307 2025-06-22 11:32:09 北京 AI-37815-01a 2025-06-22 11:32:13 您可以留下您的姓名和电话，我这边可以立刻安排对应校区顾问老师给您回电！ 01000003781500056303567923947307 2025-06-22 11:32:29 13661283905 AI-37815-01a 2025-06-22 11:32:33 好的，确认一下你的号码是否正确呢~ 01000003781500056303567923947307 2025-06-22 11:32:45 周女士 AI-37815-01a 2025-06-22 11:32:49 这个手机号是您的微信吗？如果不是您可以留一下您的微信号 01000003781500056303567923947307 2025-06-22 11:32:58 都是 AI-37815-01a 2025-06-22 11:33:01 同学怎么称呼呢？ 01000003781500056303567923947307 2025-06-22 11:33:02 一个号 AI-37815-01a 2025-06-22 11:33:06 这边马上安排顾问老师联系您，预计半个小时左右给您回电请注意接听~ 01000003781500056303567923947307 2025-06-22 11:33:14 周小英 AI-37815-01a 2025-06-22 11:33:17 稍后老师会联系哈 来源页：https://c-37815.p.easyliao.com/ 备注： | J44: 2026财年第1财月总部巨量投放-易聊 | L44: 谭悦 | M44: 线上运营-投放 | N44: 总部-巨量广告 | R44: 刘泽宇 | S44: 谭悦 | T44: 29115599 | U44: 续费工单 | V44: 2025-07-16 13:22 | W44: A（六个月内有报课意向工单） | X44: 考研无忧计划 | Y44: 大学已毕业 | Z44: 北京交通大学 | AA44: 计算机与信息技术学院 | AB44: 人工智能 | AC44: 刘泽宇 | AD44: 5453615 | AE44: 谭悦 | AF44: 2025-07-16 13:25 | AG44: 谭悦 | AH44: 2025-07-16 13:27 | AI44: 46130652007 | AJ44: 2026考研直通车VIP【计算机】 | AK44: 国内考试 | AM44: 5941.5 | AP44: 续班 | AQ44: 无须交接 | AU44: 2025-07-16 | AW44: 回访人：谭悦，回访时间：2025-07-16 13:22，回访内容：1；|回访人：谭悦，回访时间：2025-07-16 13:25，回访内容：1 | BA44: 长期班 | BB44: 80249839 | BC44: 是 | BD44: 26考季 | BE44: 无忧计划-啄木鸟 | BF44: 计算机 | BH44: 国内高校-211 | BI44: 否 | BM44: 110549227 | BN44: 本地人本地大学(常规)
A45: 地面业绩 | B45: 35 | C45: 北京大学部 | D45: 国内大学部 | E45: 可爱的小翠翠 | F45: 119210700 | G45: 杨钰杰 | H45: 2025-07-15 16:20:36 | K45: 大学已毕业 | L45: 杨钰杰 | M45: 直访 | N45: 直访 | P45: 杨钰杰 | Q45: 2025-07-15 16:32:09 | R45: 可爱的小翠翠 | S45: 刘欢 | T45: 29129653 | U45: 正常工单 | V45: 2025-07-16 21:17 | W45: A（六个月内有报课意向工单） | X45: 线上考研产品 | Y45: 大学已毕业 | Z45: 北京工业大学 | AA45: 城市建设学部 | AB45: 建筑学 | AC45: 可爱的小翠翠 | AD45: 5414954 | AE45: 谭悦 | AF45: 2025-07-16 21:21 | AG45: 刘欢 | AH45: 2025-07-16 21:22 | AK45: 国内考试 | AM45: 4232 | AP45: 分单 | AQ45: 无须交接 | AW45: 回访人：谭悦，回访时间：2025-07-16 14:28，回访内容：朋友推荐的直通车，觉得不划算，想要暑假自学，秋季报线下课 ；|回访人：谭悦，回访时间：2025-07-16 21:13，回访内容：1；|回访人：谭悦，回访时间：2025-07-16 21:14，回访内容：谭悦进行了退单操作!(本条回访记录由系统自动记录)；|回访人：刘欢，回访时间：2025-07-16 21:21，回访内容：1 | BB45: 81747257 | BC45: 否 | BD45: 26考季 | BE45: 线上直通车 | BF45: 英语,政治 | BG45: 其他 | BH45: 国内高校-211 | BI45: 否 | BO45: 客服
A46: 代售网课 | B46: 36 | C46: 北京大学部 | D46: 国内大学部 | E46: 向日葵5 | F46: 116967534 | G46: 王静静 | H46: 2025-07-01 14:41:06 | I46: 26考研想要了解学前教育专业，线上网课【已在群内反馈】（TMK主管分配TMK） | K46: 大学已毕业 | L46: 段同飞 | M46: 线上运营-私域中台 | N46: 社群、虚拟人 | P46: 段同飞 | Q46: 2025-07-16 16:24:30 | R46: 张键溪 | S46: 谭悦 | T46: 29132252 | U46: 正常工单 | V46: 2025-07-16 16:26 | W46: A（六个月内有报课意向工单） | X46: 线上考研产品 | Y46: 大四 | Z46: 首都师范大学 | AA46: 学前教育学院 | AB46: 学前教育 | AC46: 张键溪 | AD46: 5414774 | AE46: 谭悦 | AF46: 2025-07-16 16:27 | AG46: 谭悦 | AH46: 2025-07-16 16:27 | AI46: 01501936809 | AJ46: 2026考研英语直通车 6期,2026考研政治直通车 6期,2026考研教育硕士（333）直通车VIP 暑期班 | AK46: 国内考试 | AM46: 10931 | AP46: 新签 | AQ46: 无须交接 | AU46: 2025-07-16 | AW46: 回访人：谭悦，回访时间：2025-07-16 16:26，回访内容：1；|回访人：谭悦，回访时间：2025-07-16 16:27，回访内容：1 | BA46: 长期班,长期班,长期班 | BB46: 80468395 | BC46: 是 | BD46: 26考季 | BE46: 线上直通车 | BF46: 英语,政治,教育硕士 | BG46: 其他 | BH46: 国内高校-双一流(非985/211) | BI46: 否 | BM46: 109081890 | BN46: 本地人本地大学(常规)
A47: 地面业绩 | B47: 37 | C47: 北京大学部 | D47: 国内大学部 | F47: 118847129 | H47: 2025-07-13 15:38:24 | I47: 魏公村直访 | K47: 未知 | L47: 谭悦 | M47: 直访 | N47: 直访 | R47: 李宇 | S47: 谭悦 | T47: 29086171 | U47: 续费工单 | V47: 2025-07-15 10:14 | W47: A（六个月内有报课意向工单） | X47: 考研专业课 | Y47: 在职 | Z47: 广州商学院 | AA47: 会计学院 | AB47: 会计学1 | AC47: 李宇 | AD47: 5452254 | AE47: 谭悦 | AF47: 2025-07-15 11:57 | AG47: 谭悦 | AH47: 2025-07-15 11:58 | AI47: LP1752549599710 | AJ47: 考研初试专业课一对一（26考研/集训50小时） | AK47: 国内考试 | AM47: 10500 | AP47: 续班 | AQ47: 已交接 | AR47: BJWY24032w1g8X | AS47: BJWY2831358062 | AU47: 2025-07-15 | AW47: 回访人：谭悦，回访时间：2025-07-15 10:14，回访内容：1；|回访人：谭悦，回访时间：2025-07-15 11:57，回访内容：1 | BB47: 67283110 | BC47: 否 | BD47: 26考季 | BE47: 考研专业课300 | BF47: 英语,政治 | BH47: 国内高校-双非 | BI47: 是
A48: 代售网课 | B48: 38 | C48: 北京大学部 | D48: 国内大学部 | E48: 张奕鸽 | F48: 118842170 | G48: 李雪68 | H48: 2025-07-13 11:21:25 | I48: 司明霞+simingxia@xdf.cn+ID+ 产业机构-前途出国-前途北京公司-行政总经办 | K48: 未知 | L48: 谭悦 | M48: 转介绍 | N48: 内部员工推荐 | O48: 司明霞+simingxia@xdf.cn+ID+ 产业机构-前途出国-前途北京公司-行政总经办 | R48: 张奕鸽 | S48: 谭悦 | T48: 29069950 | U48: 正常工单 | V48: 2025-07-13 11:51 | W48: A（六个月内有报课意向工单） | X48: 线上考研产品 | Y48: 大三 | Z48: 菏泽学院 | AA48: 人文与新闻传播学院 | AB48: 汉语言文学（师范类） | AC48: 张奕鸽 | AD48: 5451463 | AE48: 谭悦 | AF48: 2025-07-14 16:00 | AG48: 谭悦 | AH48: 2025-07-14 16:30 | AI48: 60003912989 | AJ48: 2027考研教育硕士（333）直通车VIP,2027考研政治无忧计划·3期,2027考研英语二无忧计划·2期 | AK48: 国内考试 | AM48: 18805.6 | AO48: 司明霞+simingxia@xdf.cn+ID+ 产业机构-前途出国-前途北京公司-行政总经办 | AP48: 新签 | AQ48: 无须交接 | AU48: 2025-07-14 | AW48: 回访人：谭悦，回访时间：2025-07-13 11:51，回访内容：微信跟进中 准备报在线课，沟通优惠方案 ；|回访人：谭悦，回访时间：2025-07-14 11:00，回访内容：微信跟进中，考研学习 准备报名在线班 | BA48: 长期班,长期班,长期班 | BB48: 81570635 | BC48: 是 | BD48: 27考季 | BE48: 线上直通车,线上无忧计划 | BF48: 英语,政治,教育硕士 | BG48: 其他 | BH48: 国内高校-双非 | BI48: 否 | BM48: 110538582 | BN48: 外地人外地大学(常规) | BO48: 客服
A49: 代售网课 | B49: 39 | C49: 北京大学部 | D49: 国内大学部 | E49: 张奕鸽 | F49: 118842170 | G49: 李雪68 | H49: 2025-07-13 11:21:25 | I49: 司明霞+simingxia@xdf.cn+ID+ 产业机构-前途出国-前途北京公司-行政总经办 | K49: 未知 | L49: 谭悦 | M49: 转介绍 | N49: 内部员工推荐 | O49: 司明霞+simingxia@xdf.cn+ID+ 产业机构-前途出国-前途北京公司-行政总经办 | R49: 张奕鸽 | S49: 谭悦 | T49: 29069950 | U49: 正常工单 | V49: 2025-07-13 11:51 | W49: A（六个月内有报课意向工单） | X49: 线上考研产品 | Y49: 大三 | Z49: 菏泽学院 | AA49: 人文与新闻传播学院 | AB49: 汉语言文学（师范类） | AC49: 张奕鸽 | AD49: 5451463 | AE49: 谭悦 | AF49: 2025-07-14 16:00 | AG49: 谭悦 | AH49: 2025-07-14 16:30 | AI49: 65047887659 | AJ49: 2027考研专业课定制一对一（30h）-A班 | AK49: 国内考试 | AM49: 11160 | AO49: 司明霞+simingxia@xdf.cn+ID+ 产业机构-前途出国-前途北京公司-行政总经办 | AP49: 新签 | AQ49: 无须交接 | AU49: 2025-07-14 | AW49: 回访人：谭悦，回访时间：2025-07-13 11:51，回访内容：微信跟进中 准备报在线课，沟通优惠方案 ；|回访人：谭悦，回访时间：2025-07-14 11:00，回访内容：微信跟进中，考研学习 准备报名在线班 | BA49: 长期班 | BB49: 81570635 | BC49: 是 | BD49: 27考季 | BE49: 线上直通车,线上无忧计划 | BF49: 英语,政治,教育硕士 | BG49: 其他 | BH49: 国内高校-双非 | BI49: 否 | BM49: 110538582 | BN49: 外地人外地大学(常规) | BO49: 客服
A50: 代售网课 | B50: 40 | C50: 北京大学部 | D50: 国内大学部 | E50: 北京dbbb | F50: 114553861 | G50: 张亚男 | H50: 2025-06-16 11:36:00 | I50: 渠道录入来源：集团百度投放-易聊 意向城市：北京 访客省/城市：北京 qq: 访客静态ID：1577afd511d3f43a4a0b5ebe233cdbbb 接待分组ID：10101749 搜索引擎：www.baidu.com 搜索词：北京考研比较厉害的培训机构 关键词：考研 设备类型：phone 访客IP：1.203.67.98 对话详细内容：AI-KvNH7xJ0CDBY 2025-06-16 11:33:53 您好同学，欢迎访问新东方考研官网，【新东方考研】全新升级，课程灵活多样，【考研全年集训营】【考研半年集训营】【考研冲刺营】【线下走读班】【考研一对一】【在职考研】【四六级】火热报名中 ，现在报名更有高达3000元优惠！ AI-KvNH7xJ0CDBY 2025-06-16 11:33:54 您是想咨询【考研走读班】【考研集训营】【考研规划】还是【在职考研】呢？ 1577afd511d3f43a4a0b5ebe233cdbbb 2025-06-16 11:34:39 都想咨询 AI-KvNH7xJ0CDBY 2025-06-16 11:34:42 同学，你现在是在校还是在职呢？ 1577afd511d3f43a4a0b5ebe233cdbbb 2025-06-16 11:34:45 百度系统消息-行为轨迹:该访客在咨询页点击了内容为"在校"的按钮 1577afd511d3f43a4a0b5ebe233cdbbb 2025-06-16 11:34:45 在校 AI-KvNH7xJ0CDBY 2025-06-16 11:34:49 具体是想报考什么学校和专业呢？ 1577afd511d3f43a4a0b5ebe233cdbbb 2025-06-16 11:35:05 北京邮电大学 人工智能 AI-KvNH7xJ0CDBY 2025-06-16 11:35:09 好的，了解。我们新东方在全国32个城市都有校区，您倾向在哪个城市上课，或者希望哪里的老师给您介绍下呢？ 1577afd511d3f43a4a0b5ebe233cdbbb 2025-06-16 11:35:16 北京 AI-KvNH7xJ0CDBY 2025-06-16 11:35:20 您可以留下您的姓名和电话，我这边可以立刻安排对应校区顾问老师给您回电！ AI-KvNH7xJ0CDBY 2025-06-16 11:35:57 您好，能看到我的对话吗？如有疑问，可以在此留电咨询！ 1577afd511d3f43a4a0b5ebe233cdbbb 2025-06-16 11:35:58 13901399177 1577afd511d3f43a4a0b5ebe233cdbbb 2025-06-16 11:35:58 百度系统消息-行为轨迹:【百度】用户已留联，通过聆音回访获得实时无效返款：https://aisite.wejianzhan.com/site/wjz2tdly/5f6d3d18-a30c-41e9-9d39-6be046109511?reqCode=LYST-TE38BR7G1871RT2IQTUCS94K8 来源页：http://www.baidu.com/bcp 备注： | J50: 2026财年第1财月百度投放总部-百度投放 | L50: 谭悦 | M50: 线上运营-投放 | N50: 总部-百度投放 | R50: 费皓卿 | S50: 谭悦 | T50: 28381447 | U50: 正常工单 | V50: 2025-07-10 11:00 | W50: A（六个月内有报课意向工单） | X50: 线上考研产品 | Y50: 大三 | Z50: 北京邮电大学 | AA50: 电子工程学院 | AB50: 电子信息科学与技术 | AC50: 费皓卿 | AD50: 5474503 | AE50: 谭悦 | AF50: 2025-07-10 11:02 | AG50: 谭悦 | AH50: 2025-07-10 11:02 | AI50: 91203708310 | AJ50: 2026考研政治全程班 6班,2026考研英语全程班 6班,2026考研数学全程班 6班,2026考研政英数管综全程班重读权益（标准版） | AK50: 国内考试 | AM50: 3348.5 | AP50: 新签 | AQ50: 无须交接 | AU50: 2025-07-09 | AW50: 回访人：谭悦，回访时间：2025-07-04 21:56，回访内容：不回消息 ；|回访人：杨沫，回访时间：2025-07-10 11:00，回访内容：杨沫恢复工单, 系统自动生成回访记录!；|回访人：谭悦，回访时间：2025-07-10 11:02，回访内容：1报网课 | BA50: 长期班,长期班,长期班,重读保障 | BB50: 67544838 | BC50: 是 | BD50: 26考季 | BE50: 线上全程班 | BF50: 英语,政治,数学 | BG50: 其他 | BH50: 国内高校-211 | BI50: 否 | BM50: 110512915 | BN50: 本地人本地大学(常规) | BO50: 百度投放
A51: 代售网课 | B51: 41 | C51: 北京大学部 | D51: 国内大学部 | E51: 考研 | F51: 117808650 | G51: 杨欢欢 | H51: 2025-07-06 14:13:57 | I51: 学生想来校区面询考研辅导， | K51: 大三 | L51: 杨欢欢 | M51: 电话 | N51: 大客服呼入 | P51: 杨欢欢 | Q51: 2025-07-06 14:20:16 | R51: 考研 | S51: 赵星火 | T51: 28892060 | U51: 正常工单 | V51: 2025-07-06 16:45 | W51: A（六个月内有报课意向工单） | X51: 线上考研产品 | Y51: 大三 | Z51: 北京化工大学 | AA51: 生命科学与技术学院 | AB51: 生物工程 | AC51: 考研 | AD51: 5471244 | AE51: 赵星火 | AF51: 2025-07-07 14:44 | AG51: 赵星火 | AH51: 2025-07-07 14:46 | AI51: 42332373685 | AJ51: 2027考研政治直通车 长线2期,2027考研数学直通车 长线2期,2027考研英语直通车 长线2期 | AK51: 国内考试 | AM51: 5951.4 | AP51: 新签 | AQ51: 无须交接 | AU51: 2025-07-07 | AW51: 回访人：赵星火，回访时间：2025-07-06 16:45，回访内容：下载内蒙，现在是中外核办，后期很多学生想要出国，但自己计划考研，关注就业比较好的，以考研为主就行，倾向于本校推荐冲刺高一点的学校院校专业建议在下学校导师课程推荐直通车，专业课暂时不考虑7月19号 | BA51: 长期班,长期班,长期班 | BB51: 81188674 | BC51: 是 | BD51: 27考季 | BE51: 线上直通车 | BF51: 英语 | BG51: 其他 | BH51: 国内高校-211 | BI51: 否 | BM51: 109848410 | BN51: 本地人本地大学(常规) | BO51: 客服
A52: 代售网课 | B52: 42 | C52: 北京大学部 | D52: 国内大学部 | E52: 小菠萝 | F52: 107420758 | G52: 王静静 | H52: 2025-06-02 09:00:49 | I52: 加微信，北京文科想考研，咨询初步考虑心理学、教育学、管理学、马理论、法学几个方向 18235447322加微信（TMK主管分配TMK） | K52: 在职 | L52: 王静静 | M52: 线上运营-小红书 | N52: 小红书 | P52: 王静静 | Q52: 2025-06-10 19:28:10 | R52: 小菠萝 | S52: 谭悦 | T52: 28260575 | U52: 正常工单 | V52: 2025-06-10 19:54 | W52: A（六个月内有报课意向工单） | X52: 线上考研产品 | Y52: 在职 | Z52: 山西农业大学 | AA52: 农学院 | AB52: 农学 | AC52: 小菠萝 | AD52: 5470810 | AE52: 谭悦 | AF52: 2025-07-07 10:10 | AG52: 谭悦 | AH52: 2025-07-07 10:25 | AI52: 91694064302 | AJ52: 2026考研管综全科在职畅学班（4期） | AK52: 国内考试 | AM52: 5992.5 | AP52: 新签 | AQ52: 无须交接 | AU52: 2025-07-07 | BA52: 长期班 | BB52: 69060590 | BC52: 是 | BD52: 26考季 | BE52: 线上直通车 | BF52: 英语,政治 | BG52: 管综 | BH52: 国内高校-双非 | BI52: 否 | BM52: 75211762
A53: 地面业绩 | B53: 43 | C53: 北京大学部 | D53: 国内大学部 | E53: 考研 | F53: 117808650 | G53: 杨欢欢 | H53: 2025-07-06 14:13:57 | I53: 学生想来校区面询考研辅导， | K53: 大三 | L53: 杨欢欢 | M53: 电话 | N53: 大客服呼入 | P53: 杨欢欢 | Q53: 2025-07-06 14:20:16 | R53: 考研 | S53: 赵星火 | T53: 28892060 | U53: 正常工单 | V53: 2025-07-06 16:45 | W53: A（六个月内有报课意向工单） | X53: 线上考研产品 | Y53: 大三 | Z53: 北京化工大学 | AA53: 生命科学与技术学院 | AB53: 生物工程 | AC53: 考研 | AD53: 5442502 | AE53: 谭悦 | AF53: 2025-07-07 14:44 | AG53: 赵星火 | AH53: 2025-07-07 14:46 | AK53: 国内考试 | AM53: 5951.4 | AP53: 分单 | AQ53: 无须交接 | AW53: 回访人：赵星火，回访时间：2025-07-06 16:45，回访内容：下载内蒙，现在是中外核办，后期很多学生想要出国，但自己计划考研，关注就业比较好的，以考研为主就行，倾向于本校推荐冲刺高一点的学校院校专业建议在下学校导师课程推荐直通车，专业课暂时不考虑7月19号 | BB53: 81188674 | BC53: 是 | BD53: 27考季 | BE53: 线上直通车 | BF53: 英语 | BG53: 其他 | BH53: 国内高校-211 | BI53: 否 | BN53: 本地人本地大学(常规) | BO53: 客服
A54: 代售网课 | B54: 44 | C54: 北京大学部 | D54: 国内大学部 | E54: 董佳易 | F54: 117385583 | G54: 吴凯龙 | H54: 2025-07-03 12:49:56 | I54: 谭悦9的内部员工推荐工单 | K54: 大四 | L54: 谭悦 | M54: 转介绍 | N54: 内部员工推荐 | O54: 杨莹莹+yangyingying18@xdf.cn+ID+北京学校-运营管理部-东南区-刘家窑角门分中心 | R54: 董佳易 | S54: 谭悦 | T54: 28785861 | U54: 正常工单 | V54: 2025-07-03 13:10 | W54: A（六个月内有报课意向工单） | X54: 线上考研产品 | Y54: 大四 | Z54: 中国政法大学 | AA54: 法学院 | AB54: 法学（法学人才培养模式改革实验班） | AC54: 董佳易 | AD54: 5465643 | AE54: 谭悦 | AF54: 2025-07-03 13:11 | AG54: 谭悦 | AH54: 2025-07-03 13:12 | AI54: 90261548033 | AJ54: 2026考研英语直通车 6期,2026考研政治直通车 6期 | AK54: 国内考试 | AM54: 8464 | AO54: 杨莹莹+yangyingying18@xdf.cn+ID+北京学校-运营管理部-东南区-刘家窑角门分中心 | AP54: 新签 | AQ54: 无须交接 | AU54: 2025-07-03 | AW54: 回访人：谭悦，回访时间：2025-07-03 13:10，回访内容：签约 ；|回访人：谭悦，回访时间：2025-07-03 13:11，回访内容：1 | BA54: 长期班,长期班 | BB54: 81056684 | BC54: 是 | BD54: 26考季 | BE54: 线上直通车 | BF54: 英语,政治 | BG54: 其他 | BH54: 国内高校-211 | BI54: 否 | BM54: 107230195 | BN54: 本地人本地大学(常规) | BO54: 客服
A55: 地面业绩 | B55: 45 | C55: 北京大学部 | D55: 国内大学部 | E55: 魏亚桐 | F55: 116713488 | G55: 程远 | H55: 2025-06-30 11:16:41 | I55: 李文萱+liwenxuan3@xdf.cn+国际教育培训事业部-国际教育北京中心-运营管理部-运营中心-魏公村分中心，徐健坤； | K55: 大三 | L55: 徐健坤 | M55: 转介绍 | N55: 内部员工推荐 | O55: 李文萱+liwenxuan3@xdf.cn+国际教育培训事业部-国际教育北京中心-运营管理部-运营中心-魏公村分中心 | R55: 陈晨 | S55: 徐健坤 | T55: 28731103 | U55: 正常工单 | V55: 2025-06-30 23:20 | W55: A（六个月内有报课意向工单） | X55: 四级 | Y55: 大二 | Z55: 淮北师范大学 | AA55: 数学科学学院 | AB55: 数学与应用数学（师范） | AC55: 陈晨 | AD55: 5465207 | AE55: 谭悦 | AF55: 2025-07-02 22:46 | AG55: 徐健坤 | AH55: 2025-07-06 10:13 | AK55: 国内考试 | AM55: 2840 | AO55: 李文萱+liwenxuan3@xdf.cn+国际教育培训事业部-国际教育北京中心-运营管理部-运营中心-魏公村分中心 | AP55: 分单 | AQ55: 无须交接 | AS55: BJWY2672207145 | AW55: 回访人：徐健坤，回访时间：2025-06-30 23:20，回访内容：基础不好 自制性一般 家长想让孩子稳妥的通过四级 明后天决定；|回访人：徐健坤，回访时间：2025-07-02 22:46，回访内容：签约 | BB55: 80737003 | BC55: 否 | BD55: 25下考季 | BE55: 四级无忧计划 | BH55: 国内高校-双非 | BI55: 否 | BN55: 外地人外地大学(常规) | BO55: 客服
A56: 地面业绩 | B56: 46 | C56: 北京大学部 | D56: 国内大学部 | F56: 100771442 | H56: 2025-04-26 17:13:31 | I56: 续费原因：加一对一，5月中旬之前确定所需课时。辛苦转谭悦老师；该学生为保护期内续费，原顾问：国内大学部-谭悦(tanyue9@xdf.cn) | K56: 大三 | L56: 谭悦 | M56: 转介绍 | N56: 学管续费推荐 | R56: 黄禹淇 | S56: 谭悦 | T56: 28853577 | U56: 续费工单 | V56: 2025-07-03 23:12 | W56: A（六个月内有报课意向工单） | X56: 考研VIP | Y56: 大四 | Z56: 北京交通大学 | AA56: 机械与电子控制工程学院 | AB56: 机械工程 | AC56: 黄禹淇 | AD56: 5437764 | AE56: 谭悦 | AF56: 2025-07-03 23:13 | AG56: 谭悦 | AH56: 2025-07-03 23:13 | AI56: WYE26004 | AJ56: 考研英语无忧计划（26考研/英二强化） | AK56: 国内考试 | AM56: 3946.5 | AN56: 同科续费 | AP56: 续班 | AQ56: 已交接 | AR56: BJWY2306SVFgG7 | AS56: BJWY4049653605 | AT56: WYE260040069 | AU56: 2025-07-02 | AW56: 回访人：谭悦，回访时间：2025-07-03 23:12，回访内容：1；|回访人：谭悦，回访时间：2025-07-03 23:13，回访内容：1 | BB56: 60647114 | BC56: 否 | BD56: 26考季 | BE56: VIP - 伴学 | BF56: 英语,政治,数学 | BH56: 国内高校-211 | BI56: 否 | BL56: 转出 | BN56: 本地人本地大学(常规)
A57: 地面业绩 | B57: 47 | C57: 北京大学部 | D57: 国内大学部 | F57: 100771442 | H57: 2025-04-26 17:13:31 | I57: 续费原因：加一对一，5月中旬之前确定所需课时。辛苦转谭悦老师；该学生为保护期内续费，原顾问：国内大学部-谭悦(tanyue9@xdf.cn) | K57: 大三 | L57: 谭悦 | M57: 转介绍 | N57: 学管续费推荐 | R57: 黄禹淇 | S57: 谭悦 | T57: 28853577 | U57: 续费工单 | V57: 2025-07-03 23:12 | W57: A（六个月内有报课意向工单） | X57: 考研VIP | Y57: 大四 | Z57: 北京交通大学 | AA57: 机械与电子控制工程学院 | AB57: 机械工程 | AC57: 黄禹淇 | AD57: 5437764 | AE57: 谭悦 | AF57: 2025-07-03 23:13 | AG57: 谭悦 | AH57: 2025-07-03 23:13 | AI57: WYE26005 | AJ57: 考研英语无忧计划（26考研/英二冲刺） | AK57: 国内考试 | AM57: 2965.2 | AN57: 同科续费 | AP57: 续班 | AQ57: 已交接 | AR57: BJWY2306SVFgG7 | AS57: BJWY4049653605 | AT57: WYE260050071 | AU57: 2025-07-02 | AW57: 回访人：谭悦，回访时间：2025-07-03 23:12，回访内容：1；|回访人：谭悦，回访时间：2025-07-03 23:13，回访内容：1 | BB57: 60647114 | BC57: 否 | BD57: 26考季 | BE57: VIP - 伴学 | BF57: 英语,政治,数学 | BH57: 国内高校-211 | BI57: 否 | BL57: 转出 | BN57: 本地人本地大学(常规)
A58: 地面业绩 | B58: 48 | C58: 北京大学部 | D58: 国内大学部 | F58: 98945287 | H58: 2025-04-07 10:03:48 | I58: 续费原因：离职学管彭航的学生，已上6h,更换西北师范大学，需要缴纳500匹配费；该学生为保护期内续费，原顾问：国内大学部-赵星火(zhaoxinghuo@xdf.cn) | K58: 大三 | L58: 赵星火 | M58: 转介绍 | N58: 学管续费推荐 | R58: 王舒桐 | S58: 赵星火 | T58: 28806820 | U58: 续费工单 | V58: 2025-07-05 10:54 | W58: A（六个月内有报课意向工单） | X58: 考研专业课 | Y58: 大四 | Z58: 烟台理工学院 | AA58: 信息工程学院 | AB58: 计算机科学与技术 | AC58: 王舒桐 | AD58: 5467838 | AE58: 赵星火 | AF58: 2025-07-05 10:55 | AG58: 赵星火 | AH58: 2025-07-05 10:55 | AI58: KYJZ25004 | AJ58: 26考研政治全程集训营（寒暑） | AK58: 国内考试 | AM58: 9096.4 | AN58: 同科续费 | AP58: 续班 | AQ58: 无须交接 | AR58: BJWY2011wXCx1W | AS58: BJWY1749565978 | AT58: KYJZ250040053 | AU58: 2025-07-01 | AW58: 回访人：赵星火，回访时间：2025-07-05 10:54，回访内容：1；|回访人：赵星火，回访时间：2025-07-05 10:55，回访内容：1 | BB58: 53063270 | BC58: 否 | BD58: 26考季 | BE58: 考研专业课150 | BF58: 专业课150 | BH58: 国内高校-双非 | BI58: 否 | BL58: 转出 | BN58: 外地人外地大学(常规)
A59: 地面业绩 | B59: 49 | C59: 北京大学部 | D59: 国内大学部 | F59: 98945287 | H59: 2025-04-07 10:03:48 | I59: 续费原因：离职学管彭航的学生，已上6h,更换西北师范大学，需要缴纳500匹配费；该学生为保护期内续费，原顾问：国内大学部-赵星火(zhaoxinghuo@xdf.cn) | K59: 大三 | L59: 赵星火 | M59: 转介绍 | N59: 学管续费推荐 | R59: 王舒桐 | S59: 赵星火 | T59: 28806820 | U59: 续费工单 | V59: 2025-07-05 10:54 | W59: A（六个月内有报课意向工单） | X59: 考研专业课 | Y59: 大四 | Z59: 烟台理工学院 | AA59: 信息工程学院 | AB59: 计算机科学与技术 | AC59: 王舒桐 | AD59: 5467838 | AE59: 赵星火 | AF59: 2025-07-05 10:55 | AG59: 赵星火 | AH59: 2025-07-05 10:55 | AI59: KYJY25004 | AJ59: 26考研英语全程集训营（寒暑） | AK59: 国内考试 | AM59: 5141.3 | AN59: 同科续费 | AP59: 续班 | AQ59: 无须交接 | AR59: BJWY2011wXCx1W | AS59: BJWY1749565978 | AT59: KYJY250040053 | AU59: 2025-07-01 | AW59: 回访人：赵星火，回访时间：2025-07-05 10:54，回访内容：1；|回访人：赵星火，回访时间：2025-07-05 10:55，回访内容：1 | BB59: 53063270 | BC59: 否 | BD59: 26考季 | BE59: 考研专业课150 | BF59: 专业课150 | BH59: 国内高校-双非 | BI59: 否 | BL59: 转出 | BN59: 外地人外地大学(常规)
A60: 地面业绩 | B60: 50 | C60: 北京大学部 | D60: 国内大学部 | F60: 90730818 | H60: 2024-12-16 08:29:31 | I60: 渠道录入来源：SCRM-客服推送 商机ID：5007627536 商机编码：XSJ20241216000122 针对人群：大学 学生学校：不详 咨询课程：英语一 创建人邮箱：zhengxiaoyue@xdf.cn 创建时间：2024-12-16 08:29:26 资源类型：单个资源 跟进记录：商机备注：【呼入组+62605555】学生妈妈帮孩子咨询考研课程，英语底子不好，想了解寒假集训班，走读和住宿都行，大三，辛苦老师跟进联系介绍，谢谢;接触点：呼入； | K60: 大三 | L60: 谭悦 | M60: 新东方官网 | N60: 新东方PC官网 | R60: 谌蕙荃 | S60: 谭悦 | T60: 28844417 | U60: 续费工单 | V60: 2025-07-04 18:25 | W60: A（六个月内有报课意向工单） | X60: 考研专业课,考研集训营 | Y60: 大四 | Z60: 甘肃农业大学 | AA60: 资源与环境学院 | AB60: 生态学 | AC60: 谌蕙荃 | AD60: 5467489 | AE60: 谭悦 | AF60: 2025-07-04 18:29 | AG60: 谭悦 | AH60: 2025-07-04 18:29 | AI60: KYJZ25015 | AJ60: 26考研政治全程集训营（寒暑） | AK60: 国内考试 | AM60: 11497.4 | AN60: 同科续费 | AP60: 续班 | AQ60: 无须交接 | AR60: BJWY2011wXCx1W | AS60: BJWY1059344174 | AT60: KYJZ250150045 | AU60: 2025-07-01 | AW60: 回访人：谭悦，回访时间：2025-07-04 18:25，回访内容：1；|回访人：谭悦，回访时间：2025-07-04 18:29，回访内容：1 | BB60: 65286884 | BC60: 否 | BD60: 26考季 | BE60: 寒暑假集训营（春秋OMO）,考研专业课300 | BF60: 政治,英语,专业课300 | BH60: 国内高校-双非 | BI60: 否 | BL60: 转出 | BN60: 外地人外地大学(常规)
A61: 地面业绩 | B61: 51 | C61: 北京大学部 | D61: 国内大学部 | F61: 90730818 | H61: 2024-12-16 08:29:31 | I61: 渠道录入来源：SCRM-客服推送 商机ID：5007627536 商机编码：XSJ20241216000122 针对人群：大学 学生学校：不详 咨询课程：英语一 创建人邮箱：zhengxiaoyue@xdf.cn 创建时间：2024-12-16 08:29:26 资源类型：单个资源 跟进记录：商机备注：【呼入组+62605555】学生妈妈帮孩子咨询考研课程，英语底子不好，想了解寒假集训班，走读和住宿都行，大三，辛苦老师跟进联系介绍，谢谢;接触点：呼入； | K61: 大三 | L61: 谭悦 | M61: 新东方官网 | N61: 新东方PC官网 | R61: 谌蕙荃 | S61: 谭悦 | T61: 28844417 | U61: 续费工单 | V61: 2025-07-04 18:25 | W61: A（六个月内有报课意向工单） | X61: 考研专业课,考研集训营 | Y61: 大四 | Z61: 甘肃农业大学 | AA61: 资源与环境学院 | AB61: 生态学 | AC61: 谌蕙荃 | AD61: 5467489 | AE61: 谭悦 | AF61: 2025-07-04 18:29 | AG61: 谭悦 | AH61: 2025-07-04 18:29 | AI61: KYJY25015 | AJ61: 26考研英语全程集训营（寒暑） | AK61: 国内考试 | AM61: 7131.3 | AN61: 同科续费 | AP61: 续班 | AQ61: 无须交接 | AR61: BJWY2011wXCx1W | AS61: BJWY1059344174 | AT61: KYJY250150044 | AU61: 2025-07-01 | AW61: 回访人：谭悦，回访时间：2025-07-04 18:25，回访内容：1；|回访人：谭悦，回访时间：2025-07-04 18:29，回访内容：1 | BB61: 65286884 | BC61: 否 | BD61: 26考季 | BE61: 寒暑假集训营（春秋OMO）,考研专业课300 | BF61: 政治,英语,专业课300 | BH61: 国内高校-双非 | BI61: 否 | BL61: 转出 | BN61: 外地人外地大学(常规)
A62: 地面业绩 | B62: 52 | C62: 北京大学部 | D62: 国内大学部 | F62: 92162314 | H62: 2025-01-04 09:27:49 | I62: 乔子恒推荐，转谭悦 | K62: 大三 | L62: 谭悦 | M62: 转介绍 | N62: 顾问转介绍-老带新 | R62: 白恩宁 | S62: 谭悦 | T62: 28863646 | U62: 续费工单 | V62: 2025-07-04 18:25 | W62: A（六个月内有报课意向工单） | X62: 考研专业课,考研集训营 | Y62: 大四 | Z62: 对外经济贸易大学 | AA62: 金融学院 | AB62: 金融学 | AC62: 白恩宁 | AD62: 5467485 | AE62: 谭悦 | AF62: 2025-07-04 18:26 | AG62: 谭悦 | AH62: 2025-07-04 18:26 | AI62: KYJZ25003 | AJ62: 26考研政治全程集训营（寒暑） | AK62: 国内考试 | AM62: 11867.7 | AN62: 同科续费 | AO62: 乔子恒 | AP62: 续班 | AQ62: 无须交接 | AR62: BJWY2011wXCx1W | AS62: BJWY6892607576 | AT62: KYJZ250030088 | AU62: 2025-07-01 | AW62: 回访人：谭悦，回访时间：2025-07-04 18:25，回访内容：1；|回访人：谭悦，回访时间：2025-07-04 18:26，回访内容：1 | BB62: 65878928 | BC62: 否 | BD62: 26考季 | BE62: 考研专业课150,寒暑假集训营（春秋OMO） | BF62: 专业课150,数学,政治,英语 | BH62: 国内高校-211 | BI62: 否 | BL62: 转出 | BN62: 外地人本地大学(常规)
A63: 地面业绩 | B63: 53 | C63: 北京大学部 | D63: 国内大学部 | F63: 92162314 | H63: 2025-01-04 09:27:49 | I63: 乔子恒推荐，转谭悦 | K63: 大三 | L63: 谭悦 | M63: 转介绍 | N63: 顾问转介绍-老带新 | R63: 白恩宁 | S63: 谭悦 | T63: 28863646 | U63: 续费工单 | V63: 2025-07-04 18:25 | W63: A（六个月内有报课意向工单） | X63: 考研专业课,考研集训营 | Y63: 大四 | Z63: 对外经济贸易大学 | AA63: 金融学院 | AB63: 金融学 | AC63: 白恩宁 | AD63: 5467485 | AE63: 谭悦 | AF63: 2025-07-04 18:26 | AG63: 谭悦 | AH63: 2025-07-04 18:26 | AI63: KYJY25003 | AJ63: 26考研英语全程集训营（寒暑） | AK63: 国内考试 | AM63: 7101.4 | AN63: 同科续费 | AO63: 乔子恒 | AP63: 续班 | AQ63: 无须交接 | AR63: BJWY2011wXCx1W | AS63: BJWY6892607576 | AT63: KYJY250030089 | AU63: 2025-07-01 | AW63: 回访人：谭悦，回访时间：2025-07-04 18:25，回访内容：1；|回访人：谭悦，回访时间：2025-07-04 18:26，回访内容：1 | BB63: 65878928 | BC63: 否 | BD63: 26考季 | BE63: 考研专业课150,寒暑假集训营（春秋OMO） | BF63: 专业课150,数学,政治,英语 | BH63: 国内高校-211 | BI63: 否 | BL63: 转出 | BN63: 外地人本地大学(常规)
A64: 地面业绩 | B64: 54 | C64: 北京大学部 | D64: 国内大学部 | F64: 66558773 | H64: 2024-02-27 12:06:39 | I64: 咨询四级课程以及考研线下课程 IP：北京 搜索词：考研辅导班哪家机构好 | K64: 未知 | L64: 曹婧(离职) | M64: 线上运营-投放 | N64: 百度投放 | R64: 李兆同 | S64: 谭悦 | T64: 28844402 | U64: 续费工单 | V64: 2025-07-04 18:24 | W64: A（六个月内有报课意向工单） | X64: 考研专业课,考研集训营 | Y64: 大四 | Z64: 中国石油大学（华东） | AA64: 新能源学院 | AB64: 过程装备与控制工程 | AC64: 李兆同 | AD64: 5438819 | AE64: 谭悦 | AF64: 2025-07-04 18:31 | AG64: 谭悦 | AH64: 2025-07-04 18:31 | AI64: KYJZ25004 | AJ64: 26考研政治全程集训营（寒暑） | AK64: 国内考试 | AM64: 9096.4 | AN64: 同科续费 | AP64: 续班 | AQ64: 无须交接 | AR64: BJWY2011wXCx1W | AS64: BJWY7087471752 | AT64: KYJZ250040054 | AU64: 2025-07-01 | AW64: 回访人：谭悦，回访时间：2025-07-04 18:24，回访内容：1；|回访人：谭悦，回访时间：2025-07-04 18:31，回访内容：1 | BB64: 33529072 | BC64: 否 | BD64: 26考季 | BE64: 寒暑假集训营（春秋OMO）,暑假集训营 | BF64: 英语,政治,数学,专业课150 | BH64: 国内高校-211 | BI64: 否 | BL64: 转出
A65: 地面业绩 | B65: 55 | C65: 北京大学部 | D65: 国内大学部 | F65: 66558773 | H65: 2024-02-27 12:06:39 | I65: 咨询四级课程以及考研线下课程 IP：北京 搜索词：考研辅导班哪家机构好 | K65: 未知 | L65: 曹婧(离职) | M65: 线上运营-投放 | N65: 百度投放 | R65: 李兆同 | S65: 谭悦 | T65: 28844402 | U65: 续费工单 | V65: 2025-07-04 18:24 | W65: A（六个月内有报课意向工单） | X65: 考研专业课,考研集训营 | Y65: 大四 | Z65: 中国石油大学（华东） | AA65: 新能源学院 | AB65: 过程装备与控制工程 | AC65: 李兆同 | AD65: 5438819 | AE65: 谭悦 | AF65: 2025-07-04 18:31 | AG65: 谭悦 | AH65: 2025-07-04 18:31 | AI65: KYJY25004 | AJ65: 26考研英语全程集训营（寒暑） | AK65: 国内考试 | AM65: 5141.3 | AN65: 同科续费 | AP65: 续班 | AQ65: 无须交接 | AR65: BJWY2011wXCx1W | AS65: BJWY7087471752 | AT65: KYJY250040054 | AU65: 2025-07-01 | AW65: 回访人：谭悦，回访时间：2025-07-04 18:24，回访内容：1；|回访人：谭悦，回访时间：2025-07-04 18:31，回访内容：1 | BB65: 33529072 | BC65: 否 | BD65: 26考季 | BE65: 寒暑假集训营（春秋OMO）,暑假集训营 | BF65: 英语,政治,数学,专业课150 | BH65: 国内高校-211 | BI65: 否 | BL65: 转出
A66: 地面业绩 | B66: 56 | C66: 北京大学部 | D66: 国内大学部 | F66: 77096516 | H66: 2024-06-11 11:24:15 | I66: 【六级】家长给孩子咨询，大二，在北京上学，要了解六级的学习，说是今年还没报呢，应该是12月份考试，下午2点后方便电话；渠道录入来源：新东方PC官网-客服 意向城市：北京访客省/城市：北京市 访客静态ID：01000000034659807507282021972472 接待分组ID：70447 搜索引擎：www.baidu.com 搜索词： 关键词： 设备类型：pc 访客IP：42.99.63.51 对话详细内容：AI-Lbo0rDBXCyBY 2024-06-11 11:04:36 您好同学,欢迎访问北京新东方考研四六级中心. 考研线下课程【考研全年/半年集训营】【暑假集训营】【考研线下走读班】【考研一对一】【四六级课程】，火热报名中,咨询即可领取专享优惠.**【考研全年/半年集训营】# **【暑假集训营】# **【考研线下走读班】# **【考研一对一】# **【四六级课程】# AI-Lbo0rDBXCyBY 2024-06-11 11:04:38 您是想咨询【线下课程】【线上课程】【考研规划】还是【在职考研】呢？**【线下课程】# **【线上课程】#**【考研规划】#**【在职考研】# 01000000034659807507282021972472 2024-06-11 11:05:22 方地 AI-Lbo0rDBXCyBY 2024-06-11 11:05:25 同学，您是在校还是在职呢？**在校# **在职# 01000000034659807507282021972472 2024-06-11 11:05:35 六级 AI-Lbo0rDBXCyBY 2024-06-11 11:05:39 您目前在学的院校是哪所呢？ 01000000034659807507282021972472 2024-06-11 11:05:56 北京 AI-Lbo0rDBXCyBY 2024-06-11 11:05:59 您目前英语基础如何呢？ AI-Lbo0rDBXCyBY 2024-06-11 11:06:36 您好，能看到我的对话吗？如有疑问，可以在此留电咨询！ AI-Lbo0rDBXCyBY 2024-06-11 11:06:56 如果打字不方便，可以在此输入电话或者微信，这边安排老师与您联系，为您详细解答！ AI-Lbo0rDBXCyBY 2024-06-11 11:07:56 同学您好，目前处于咨询的高峰期，如需咨询25/26考研【复习规划、择校择专业】【课程详情】等问题，您可以留下您的【姓名电话方便接听电话的时间】，我们会安排老师第一时间为您回电免费咨询！ 01000000034659807507282021972472 2024-06-11 11:08:19 13301161922 AI-Lbo0rDBXCyBY 2024-06-11 11:08:22 好的，确认一下你的号码是否正确呢~ 01000000034659807507282021972472 2024-06-11 11:08:33 正确 AI-Lbo0rDBXCyBY 2024-06-11 11:08:37 同学怎么称呼呢？ 01000000034659807507282021972472 2024-06-11 11:08:47 王，我是家长 AI-Lbo0rDBXCyBY 2024-06-11 11:08:51 这边马上安排顾问老师联系您，预计半个小时左右给您回电请注意接听~ 来源页：https://www.baidu.com/link?url=KTO9Aa3PzFHJO4cBSmiAkshr3HwvMjgEfHVctTJmoQu&wd=&eqid=fbd6285e0005268b000000036667bea4 备注： 外呼主题：2025财年第1财月易聊新东方PC官网 | J66: 2025财年第1财月易聊新东方PC官网 | K66: 大二 | L66: 谭悦 | M66: 新东方官网 | N66: 新东方PC官网 | R66: 张思远 | S66: 谭悦 | T66: 28805720 | U66: 续费工单 | V66: 2025-07-04 18:25 | W66: A（六个月内有报课意向工单） | X66: 六级,考研专业课,考研集训营 | Y66: 大四 | Z66: 北京工业大学 | AA66: 信息学部 | AB66: 通信工程 | AC66: 张思远 | AD66: 5438817 | AE66: 谭悦 | AF66: 2025-07-04 18:30 | AG66: 谭悦 | AH66: 2025-07-04 18:30 | AI66: KYJZ25004 | AJ66: 26考研政治全程集训营（寒暑） | AK66: 国内考试 | AM66: 9096.5 | AN66: 同科续费 | AP66: 续班 | AQ66: 无须交接 | AR66: BJWY2011wXCx1W | AS66: BJWY7257773805 | AT66: KYJZ250040055 | AU66: 2025-07-01 | AW66: 回访人：谭悦，回访时间：2025-07-04 18:25，回访内容：1；|回访人：谭悦，回访时间：2025-07-04 18:30，回访内容：1 | BB66: 58864973 | BC66: 否 | BD66: 26考季 | BE66: 六级无忧计划,考研专业课150,寒暑假集训营（春秋OMO） | BF66: 英语,政治,数学,专业课150 | BH66: 国内高校-211 | BI66: 否 | BL66: 转出 | BN66: 本地人本地大学(常规)
A67: 地面业绩 | B67: 57 | C67: 北京大学部 | D67: 国内大学部 | F67: 77096516 | H67: 2024-06-11 11:24:15 | I67: 【六级】家长给孩子咨询，大二，在北京上学，要了解六级的学习，说是今年还没报呢，应该是12月份考试，下午2点后方便电话；渠道录入来源：新东方PC官网-客服 意向城市：北京访客省/城市：北京市 访客静态ID：01000000034659807507282021972472 接待分组ID：70447 搜索引擎：www.baidu.com 搜索词： 关键词： 设备类型：pc 访客IP：42.99.63.51 对话详细内容：AI-Lbo0rDBXCyBY 2024-06-11 11:04:36 您好同学,欢迎访问北京新东方考研四六级中心. 考研线下课程【考研全年/半年集训营】【暑假集训营】【考研线下走读班】【考研一对一】【四六级课程】，火热报名中,咨询即可领取专享优惠.**【考研全年/半年集训营】# **【暑假集训营】# **【考研线下走读班】# **【考研一对一】# **【四六级课程】# AI-Lbo0rDBXCyBY 2024-06-11 11:04:38 您是想咨询【线下课程】【线上课程】【考研规划】还是【在职考研】呢？**【线下课程】# **【线上课程】#**【考研规划】#**【在职考研】# 01000000034659807507282021972472 2024-06-11 11:05:22 方地 AI-Lbo0rDBXCyBY 2024-06-11 11:05:25 同学，您是在校还是在职呢？**在校# **在职# 01000000034659807507282021972472 2024-06-11 11:05:35 六级 AI-Lbo0rDBXCyBY 2024-06-11 11:05:39 您目前在学的院校是哪所呢？ 01000000034659807507282021972472 2024-06-11 11:05:56 北京 AI-Lbo0rDBXCyBY 2024-06-11 11:05:59 您目前英语基础如何呢？ AI-Lbo0rDBXCyBY 2024-06-11 11:06:36 您好，能看到我的对话吗？如有疑问，可以在此留电咨询！ AI-Lbo0rDBXCyBY 2024-06-11 11:06:56 如果打字不方便，可以在此输入电话或者微信，这边安排老师与您联系，为您详细解答！ AI-Lbo0rDBXCyBY 2024-06-11 11:07:56 同学您好，目前处于咨询的高峰期，如需咨询25/26考研【复习规划、择校择专业】【课程详情】等问题，您可以留下您的【姓名电话方便接听电话的时间】，我们会安排老师第一时间为您回电免费咨询！ 01000000034659807507282021972472 2024-06-11 11:08:19 13301161922 AI-Lbo0rDBXCyBY 2024-06-11 11:08:22 好的，确认一下你的号码是否正确呢~ 01000000034659807507282021972472 2024-06-11 11:08:33 正确 AI-Lbo0rDBXCyBY 2024-06-11 11:08:37 同学怎么称呼呢？ 01000000034659807507282021972472 2024-06-11 11:08:47 王，我是家长 AI-Lbo0rDBXCyBY 2024-06-11 11:08:51 这边马上安排顾问老师联系您，预计半个小时左右给您回电请注意接听~ 来源页：https://www.baidu.com/link?url=KTO9Aa3PzFHJO4cBSmiAkshr3HwvMjgEfHVctTJmoQu&wd=&eqid=fbd6285e0005268b000000036667bea4 备注： 外呼主题：2025财年第1财月易聊新东方PC官网 | J67: 2025财年第1财月易聊新东方PC官网 | K67: 大二 | L67: 谭悦 | M67: 新东方官网 | N67: 新东方PC官网 | R67: 张思远 | S67: 谭悦 | T67: 28805720 | U67: 续费工单 | V67: 2025-07-04 18:25 | W67: A（六个月内有报课意向工单） | X67: 六级,考研专业课,考研集训营 | Y67: 大四 | Z67: 北京工业大学 | AA67: 信息学部 | AB67: 通信工程 | AC67: 张思远 | AD67: 5438817 | AE67: 谭悦 | AF67: 2025-07-04 18:30 | AG67: 谭悦 | AH67: 2025-07-04 18:30 | AI67: KYJY25004 | AJ67: 26考研英语全程集训营（寒暑） | AK67: 国内考试 | AM67: 5141.3 | AN67: 同科续费 | AP67: 续班 | AQ67: 无须交接 | AR67: BJWY2011wXCx1W | AS67: BJWY7257773805 | AT67: KYJY250040055 | AU67: 2025-07-01 | AW67: 回访人：谭悦，回访时间：2025-07-04 18:25，回访内容：1；|回访人：谭悦，回访时间：2025-07-04 18:30，回访内容：1 | BB67: 58864973 | BC67: 否 | BD67: 26考季 | BE67: 六级无忧计划,考研专业课150,寒暑假集训营（春秋OMO） | BF67: 英语,政治,数学,专业课150 | BH67: 国内高校-211 | BI67: 否 | BL67: 转出 | BN67: 本地人本地大学(常规)
A68: 地面业绩 | B68: 58 | C68: 北京大学部 | D68: 国内大学部 | F68: 116868306 | H68: 2025-07-01 10:33:35 | I68: 续费原因：学生更换研究生，需要缴纳500元师资重新匹配费；该学生为保护期内续费，原顾问：国内大学部-谭悦(tanyue9@xdf.cn) | K68: 大四 | L68: 谭悦 | M68: 转介绍 | N68: 学管续费推荐 | R68: 章俊骐 | S68: 谭悦 | T68: 28844381 | U68: 续费工单 | V68: 2025-07-04 18:23 | W68: A（六个月内有报课意向工单） | X68: 考研专业课 | Y68: 大四 | Z68: 福建师范大学 | AA68: 计算机与网络空间安全学院 | AB68: 网络空间安全 | AC68: 章俊骐 | AD68: 5438803 | AE68: 谭悦 | AF68: 2025-07-04 18:23 | AG68: 谭悦 | AH68: 2025-07-04 18:24 | AI68: KYJZ25004 | AJ68: 26考研政治全程集训营（寒暑） | AK68: 国内考试 | AM68: 11729.9 | AN68: 同科续费 | AP68: 续班 | AQ68: 无须交接 | AR68: BJWY2011wXCx1W | AS68: BJWY4692076178 | AT68: KYJZ250040047 | AU68: 2025-07-01 | AW68: 回访人：谭悦，回访时间：2025-07-04 18:23，回访内容：1；|回访人：谭悦，回访时间：2025-07-04 18:23，回访内容：1 | BB68: 63993771 | BC68: 否 | BD68: 26考季 | BE68: 考研专业课150 | BF68: 专业课150 | BH68: 国内高校-双非 | BI68: 否 | BL68: 转出 | BN68: 外地人外地大学(常规)
A69: 地面业绩 | B69: 59 | C69: 北京大学部 | D69: 国内大学部 | F69: 116868306 | H69: 2025-07-01 10:33:35 | I69: 续费原因：学生更换研究生，需要缴纳500元师资重新匹配费；该学生为保护期内续费，原顾问：国内大学部-谭悦(tanyue9@xdf.cn) | K69: 大四 | L69: 谭悦 | M69: 转介绍 | N69: 学管续费推荐 | R69: 章俊骐 | S69: 谭悦 | T69: 28844381 | U69: 续费工单 | V69: 2025-07-04 18:23 | W69: A（六个月内有报课意向工单） | X69: 考研专业课 | Y69: 大四 | Z69: 福建师范大学 | AA69: 计算机与网络空间安全学院 | AB69: 网络空间安全 | AC69: 章俊骐 | AD69: 5438803 | AE69: 谭悦 | AF69: 2025-07-04 18:23 | AG69: 谭悦 | AH69: 2025-07-04 18:24 | AI69: KYJY25004 | AJ69: 26考研英语全程集训营（寒暑） | AK69: 国内考试 | AM69: 7269.5 | AN69: 同科续费 | AP69: 续班 | AQ69: 无须交接 | AR69: BJWY2011wXCx1W | AS69: BJWY4692076178 | AT69: KYJY250040047 | AU69: 2025-07-01 | AW69: 回访人：谭悦，回访时间：2025-07-04 18:23，回访内容：1；|回访人：谭悦，回访时间：2025-07-04 18:23，回访内容：1 | BB69: 63993771 | BC69: 否 | BD69: 26考季 | BE69: 考研专业课150 | BF69: 专业课150 | BH69: 国内高校-双非 | BI69: 否 | BL69: 转出 | BN69: 外地人外地大学(常规)
A70: 地面业绩 | B70: 60 | C70: 北京大学部 | D70: 国内大学部 | F70: 116868306 | H70: 2025-07-01 10:33:35 | I70: 续费原因：学生更换研究生，需要缴纳500元师资重新匹配费；该学生为保护期内续费，原顾问：国内大学部-谭悦(tanyue9@xdf.cn) | K70: 大四 | L70: 谭悦 | M70: 转介绍 | N70: 学管续费推荐 | R70: 章俊骐 | S70: 谭悦 | T70: 28844381 | U70: 续费工单 | V70: 2025-07-04 18:23 | W70: A（六个月内有报课意向工单） | X70: 考研专业课 | Y70: 大四 | Z70: 福建师范大学 | AA70: 计算机与网络空间安全学院 | AB70: 网络空间安全 | AC70: 章俊骐 | AD70: 5438803 | AE70: 谭悦 | AF70: 2025-07-04 18:23 | AG70: 谭悦 | AH70: 2025-07-04 18:24 | AI70: KYJY25003 | AJ70: 26考研英语全程集训营（寒暑） | AK70: 国内考试 | AM70: 7269.5 | AN70: 同科续费 | AP70: 续班 | AQ70: 无须交接 | AR70: BJWY2101498uW2 | AS70: BJWY4692076178 | AT70: KYJY250030101 | AU70: 2025-07-01 | AW70: 回访人：谭悦，回访时间：2025-07-04 18:23，回访内容：1；|回访人：谭悦，回访时间：2025-07-04 18:23，回访内容：1 | BB70: 63993771 | BC70: 否 | BD70: 26考季 | BE70: 考研专业课150 | BF70: 专业课150 | BH70: 国内高校-双非 | BI70: 否 | BL70: 转出 | BN70: 外地人外地大学(常规)
A71: 地面业绩 | B71: 61 | C71: 北京大学部 | D71: 国内大学部 | F71: 116868306 | H71: 2025-07-01 10:33:35 | I71: 续费原因：学生更换研究生，需要缴纳500元师资重新匹配费；该学生为保护期内续费，原顾问：国内大学部-谭悦(tanyue9@xdf.cn) | K71: 大四 | L71: 谭悦 | M71: 转介绍 | N71: 学管续费推荐 | R71: 章俊骐 | S71: 谭悦 | T71: 28844381 | U71: 续费工单 | V71: 2025-07-04 18:23 | W71: A（六个月内有报课意向工单） | X71: 考研专业课 | Y71: 大四 | Z71: 福建师范大学 | AA71: 计算机与网络空间安全学院 | AB71: 网络空间安全 | AC71: 章俊骐 | AD71: 5438803 | AE71: 谭悦 | AF71: 2025-07-04 18:23 | AG71: 谭悦 | AH71: 2025-07-04 18:24 | AI71: KYJZ25003 | AJ71: 26考研政治全程集训营（寒暑） | AK71: 国内考试 | AM71: 11729.9 | AN71: 同科续费 | AP71: 续班 | AQ71: 无须交接 | AR71: BJWY2101498uW2 | AS71: BJWY4692076178 | AT71: KYJZ250030100 | AU71: 2025-07-01 | AW71: 回访人：谭悦，回访时间：2025-07-04 18:23，回访内容：1；|回访人：谭悦，回访时间：2025-07-04 18:23，回访内容：1 | BB71: 63993771 | BC71: 否 | BD71: 26考季 | BE71: 考研专业课150 | BF71: 专业课150 | BH71: 国内高校-双非 | BI71: 否 | BL71: 转出 | BN71: 外地人外地大学(常规)
A72: 代售网课 | B72: 62 | C72: 北京大学部 | D72: 国内大学部 | E72: 未知 | F72: 120674124 | G72: 李雪68 | H72: 2025-07-25 09:19:49 | I72: 激活 | K72: 大四 | L72: 谭悦 | M72: 线上运营-投放 | N72: 巨量广告 | R72: 周舟6 | S72: 谭悦 | T72: 29315777 | U72: 正常工单 | V72: 2025-07-25 09:42 | W72: A（六个月内有报课意向工单） | X72: 线上考研产品 | Y72: 大四 | Z72: 北京石油化工学院 | AA72: 材料科学与工程学院 | AB72: 高分子材料与工程 | AC72: 周舟6 | AD72: 5494745 | AE72: 谭悦 | AF72: 2025-07-26 21:06 | AI72: 87475099999 | AJ72: 2026考研数学直通车 6期,2026考研政治直通车 6期 | AM72: 6953 | AP72: 新签 | AQ72: 未交接 | AU72: 2025-07-26 | AW72: 回访人：谭悦，回访时间：2025-07-25 09:42，回访内容：1；|回访人：谭悦，回访时间：2025-07-26 15:14，回访内容：微信跟进中，考研学校 | BA72: 长期班,长期班 | BB72: 74099200 | BC72: 是 | BD72: 26考季 | BE72: 线上全程班 | BF72: 英语 | BG72: 其他 | BH72: 国内高校-双非 | BI72: 否 | BM72: 103009134 | BN72: 本地人本地大学(常规) | BO72: 客服
A73: 地面业绩 | B73: 63 | C73: 北京大学部 | D73: 国内大学部 | F73: 96709233 | H73: 2025-03-11 08:48:05 | I73: 15911140519，北京，一对一，家长 | K73: 未知 | L73: 谭悦 | M73: 线上运营-投放 | N73: 巨量广告 | R73: 郑雅洁 | S73: 谭悦 | T73: 29325048 | U73: 续费工单 | V73: 2025-07-25 20:47 | W73: A（六个月内有报课意向工单） | X73: 六级,考研专业课,考研无忧计划 | Y73: 大三 | Z73: 首都师范大学 | AA73: 物理系 | AB73: 物理学 | AC73: 郑雅洁 | AD73: 5521655 | AE73: 谭悦 | AF73: 2025-07-25 20:47 | AG73: 谭悦 | AH73: 2025-07-25 20:47 | AI73: WYE27018 | AJ73: 考研英语无忧计划（27考研/基础） | AK73: 国内考试 | AM73: 3891.1 | AN73: 同科续费 | AP73: 续班 | AQ73: 未交接 | AR73: BJWY24032w1g8X | AS73: BJWY5564317069 | AT73: WYE270180013 | AU73: 2025-07-24 | AW73: 回访人：谭悦，回访时间：2025-07-25 20:47，回访内容：1；|回访人：谭悦，回访时间：2025-07-25 20:47，回访内容：1 | BB73: 67848549 | BC73: 否 | BD73: 26考季 | BE73: 无忧计划-啄木鸟,六级无忧计划,考研专业课300 | BF73: 专业课300,英语,政治 | BH73: 国内高校-双一流(非985/211) | BI73: 否 | BL73: 转出 | BN73: 本地人本地大学(常规)
A74: 地面业绩 | B74: 64 | C74: 北京大学部 | D74: 国内大学部 | F74: 103521996 | H74: 2025-05-23 14:18:38 | I74: 学生觉得来不及，于是准备明年的考试，基础一般，想考211，辛苦老师可以私信了解具体情况 | K74: 大三 | L74: 谭悦 | M74: 转介绍 | N74: 学管转介绍 | R74: 程悦 | S74: 谭悦 | T74: 29223564 | U74: 续费工单 | V74: 2025-07-20 13:04 | W74: A（六个月内有报课意向工单） | X74: 六级,考研专业课,考研无忧计划 | Y74: 大四 | Z74: 北京工商大学 | AA74: 生物 | AB74: 生物 | AC74: 程悦 | AD74: 5485946 | AE74: 谭悦 | AF74: 2025-07-20 13:05 | AG74: 谭悦 | AH74: 2025-07-20 13:05 | AI74: WYE27006 | AJ74: 考研英语无忧计划（27考研/基础） | AK74: 国内考试 | AM74: 3915 | AN74: 同科续费 | AP74: 续班 | AQ74: 未交接 | AR74: BJWY24032w1g8X | AS74: BJWY8477545262 | AT74: WYE270060017 | AU74: 2025-07-19 | AW74: 回访人：谭悦，回访时间：2025-07-20 13:04，回访内容：1；|回访人：谭悦，回访时间：2025-07-20 13:05，回访内容：1 | BB74: 70870277 | BC74: 否 | BD74: 27考季 | BE74: 无忧计划-啄木鸟,六级无忧计划,考研专业课300 | BF74: 英语,政治,专业课300 | BH74: 国内高校-双非 | BI74: 否 | BL74: 转出 | BN74: 本地人本地大学(常规)
A75: 地面业绩 | B75: 65 | C75: 北京大学部 | D75: 国内大学部 | F75: 88084630 | H75: 2024-11-09 17:09:46 | I75: 谭悦老师老带新 | K75: 大三 | L75: 谭悦 | M75: 转介绍 | N75: 顾问转介绍-老带新 | R75: 孙睿泽 | S75: 谭悦 | T75: 29193856 | U75: 续费工单 | V75: 2025-07-18 10:55 | W75: A（六个月内有报课意向工单） | X75: 考研VIP | Y75: 大三 | Z75: 对外经济贸易大学 | AA75: 英语学院 | AB75: 商务英语 | AC75: 孙睿泽 | AD75: 5455697 | AE75: 谭悦 | AF75: 2025-07-18 10:55 | AG75: 系统管理员 | AH75: 2025-07-18 10:55 | AI75: LP17320859591849 | AJ75: 考研初试专业课一对一伴学班（管综-26考季） | AM75: -8000 | AO75: 乔子恒 | AQ75: 未交接 | AS75: BJWY9403107977 | AU75: 2025-07-18 | AW75: 回访人：系统管理员，回访时间：2025-07-18 10:55，回访内容：学生转产品转入，创建续费工单。 | BB75: 64168068 | BC75: 否 | BD75: 26考季 | BE75: VIP - 伴学 | BF75: 英语,管综 | BH75: 国内高校-211 | BI75: 否
A76: 地面业绩 | B76: 66 | C76: 北京大学部 | D76: 国内大学部 | F76: 88084630 | H76: 2024-11-09 17:09:46 | I76: 谭悦老师老带新 | K76: 大三 | L76: 谭悦 | M76: 转介绍 | N76: 顾问转介绍-老带新 | R76: 孙睿泽 | S76: 谭悦 | T76: 29193856 | U76: 续费工单 | V76: 2025-07-18 10:55 | W76: A（六个月内有报课意向工单） | X76: 考研VIP | Y76: 大三 | Z76: 对外经济贸易大学 | AA76: 英语学院 | AB76: 商务英语 | AC76: 孙睿泽 | AD76: 5455697 | AE76: 谭悦 | AF76: 2025-07-18 10:55 | AG76: 系统管理员 | AH76: 2025-07-18 10:55 | AI76: LP1752806923377 | AJ76: 26考研一对一伴学（无忧） | AM76: 8000 | AO76: 乔子恒 | AQ76: 未交接 | AS76: BJWY9403107977 | AU76: 2025-07-18 | AW76: 回访人：系统管理员，回访时间：2025-07-18 10:55，回访内容：学生转产品转入，创建续费工单。 | BB76: 64168068 | BC76: 否 | BD76: 26考季 | BE76: VIP - 伴学 | BF76: 英语,管综 | BH76: 国内高校-211 | BI76: 否
A77: 代售网课 | B77: 67 | C77: 北京大学部 | D77: 国内大学部 | E77: 糖糖与汤圆 | F77: 117841907 | G77: 王朝群 | H77: 2025-07-07 09:42:19 | I77: 【王朝群】咨询考研线上课程 | K77: 大学已毕业 | L77: 谭悦 | M77: 线上运营-小红书 | N77: 小红书KOS | R77: 牛任杰 | S77: 谭悦 | T77: 28915558 | U77: 正常工单 | V77: 2025-07-07 10:49 | W77: A（六个月内有报课意向工单） | X77: 线上考研产品 | Y77: 大学已毕业 | Z77: 北京科技大学 | AA77: 土木与资源工程学院 | AB77: 采矿工程 | AC77: 牛任杰 | AD77: 5443051 | AE77: 谭悦 | AF77: 2025-07-07 19:37 | AI77: 67374296149 | AJ77: 2026考研政治全程班 6班,2026考研英语全程班 6班 | AM77: 2023 | AP77: 新签 | AQ77: 未交接 | AU77: 2025-07-07 | AW77: 回访人：谭悦，回访时间：2025-07-07 10:49，回访内容：在职研究生，了解英语政治网课，全程班，加微信了 ，任杰 | BA77: 长期班,长期班 | BB77: 21163465 | BC77: 是 | BD77: 26考季 | BE77: 线上全程班 | BF77: 英语,政治 | BG77: 其他 | BH77: 国内高校-211 | BI77: 否 | BM77: 110500249 | BO77: 市场
A78: 地面业绩 | B78: 68 | C78: 北京大学部 | D78: 国内大学部 | F78: 100771442 | H78: 2025-04-26 17:13:31 | I78: 续费原因：加一对一，5月中旬之前确定所需课时。辛苦转谭悦老师；该学生为保护期内续费，原顾问：国内大学部-谭悦(tanyue9@xdf.cn) | K78: 大三 | L78: 谭悦 | M78: 转介绍 | N78: 学管续费推荐 | R78: 黄禹淇 | S78: 谭悦 | T78: 28852432 | U78: 续费工单 | V78: 2025-07-05 16:43 | W78: A（六个月内有报课意向工单） | X78: 考研VIP | Y78: 大四 | Z78: 北京交通大学 | AA78: 机械与电子控制工程学院 | AB78: 机械工程 | AC78: 黄禹淇 | AD78: 5439870 | AE78: 谭悦 | AF78: 2025-07-05 16:44 | AI78: LP17517050881945 | AJ78: 考研专业课匹配费 | AM78: 500 | AP78: 续班 | AQ78: 未交接 | AS78: BJWY4049653605 | AU78: 2025-07-05 | AW78: 回访人：谭悦，回访时间：2025-07-05 16:43，回访内容：1 | BB78: 60647114 | BC78: 否 | BD78: 26考季 | BE78: VIP - 伴学 | BF78: 英语,政治,数学 | BH78: 国内高校-211 | BI78: 否 | BN78: 本地人本地大学(常规)
A79: 地面业绩 | B79: 69 | C79: 北京大学部 | D79: 国内大学部 | E79: 章俊骐 | F79: 116868306 | G79: 刘佳林 | H79: 2025-07-01 10:33:35 | I79: 续费原因：学生更换研究生，需要缴纳500元师资重新匹配费；该学生为保护期内续费，原顾问：国内大学部-谭悦(tanyue9@xdf.cn) | K79: 大四 | L79: 谭悦 | M79: 转介绍 | N79: 学管续费推荐 | O79: 刘佳林liujialin25@xdf.cn | R79: 章俊骐 | S79: 谭悦 | T79: 28732371 | U79: 续费工单 | V79: 2025-07-01 10:46 | W79: A（六个月内有报课意向工单） | X79: 考研专业课 | Y79: 大四 | Z79: 福建师范大学 | AA79: 计算机与网络空间安全学院 | AB79: 网络空间安全 | AC79: 章俊骐 | AD79: 5406797 | AE79: 谭悦 | AF79: 2025-07-01 10:48 | AG79: 谭悦 | AH79: 2025-07-01 10:49 | AI79: LP175133809710126 | AJ79: 考研专业课匹配费-集训 | AK79: 国内考试 | AM79: 500 | AO79: 刘佳林 | AP79: 续班 | AQ79: 未交接 | AS79: BJWY4692076178 | AU79: 2025-07-01 | AW79: 回访人：谭悦，回访时间：2025-07-01 10:46，回访内容：升级费500 | BB79: 63993771 | BC79: 否 | BD79: 26考季 | BE79: 考研专业课150 | BF79: 专业课150 | BG79: 其他 | BH79: 国内高校-双非 | BI79: 否 | BN79: 外地人外地大学(常规) | BO79: 学管续费推荐
A80: 地面业绩 | B80: 70 | C80: 北京大学部 | D80: 国内大学部 | E80: 北京市1795 | F80: 120777100 | G80: 杨俊42(国内) | H80: 2025-07-25 22:33:01 | I80: 渠道录入来源：新东方官网APP-客服 意向城市：北京访客省/城市：北京市 访客静态ID：01000000034659345380947287361795 接待分组ID：70458 搜索引擎： 搜索词： 关键词： 设备类型：phone 访客IP：114.254.3.108 对话详细内容：AI-Lbo0rDBXCyBY 2025-07-25 22:30:10 您好同学,欢迎访问北京新东方考研四六级中心. 考研线下课程26/27考季【考研全年集训营】【考研半年集训营】【考研全科线下走读班】【考研寒/暑假集训营】【考研一对一】【考研专业课】【四/六级课程】，热门课程火热报名中,咨询即可领取专享优惠。 **【考研全年集训营】=ff761f# **【考研半年集训营】=ff6b6b# **【考研全科线下走读班】=ffc158# **【考研寒/暑假集训营】=ffc158# **【考研一对一】=ff761f# **【考研专业课】=ff6caa# **【四/六级课程】=ff6caa# **【考研冲刺班】=60e27e# AI-Lbo0rDBXCyBY 2025-07-25 22:30:13 您是想咨询【线下课程】【线上课程】【考研规划】还是【在职考研】呢？**【线下课程】# **【线上课程】#**【考研规划】#**【在职考研】# 01000000034659345380947287361795 2025-07-25 22:30:17 【线下课程】 AI-Lbo0rDBXCyBY 2025-07-25 22:30:21 同学，你现在是在校还是在职呢？ 01000000034659345380947287361795 2025-07-25 22:30:28 在校 AI-Lbo0rDBXCyBY 2025-07-25 22:30:32 具体是想报考什么学校和专业呢？ 01000000034659345380947287361795 2025-07-25 22:30:44 没有想法 AI-Lbo0rDBXCyBY 2025-07-25 22:30:48 好的，我这边安排专业老师给您回电，详细沟通一下，请问您的电话是多少呢？ 01000000034659345380947287361795 2025-07-25 22:30:53 好的 AI-Lbo0rDBXCyBY 2025-07-25 22:30:57 嗯，那您联系方式是多少呢？ 01000000034659345380947287361795 2025-07-25 22:30:58 18210383301 AI-Lbo0rDBXCyBY 2025-07-25 22:31:01 好的，确认一下你的号码是否正确呢~ 01000000034659345380947287361795 2025-07-25 22:31:09 没问题 AI-Lbo0rDBXCyBY 2025-07-25 22:31:13 同学怎么称呼呢？ 01000000034659345380947287361795 2025-07-25 22:31:19 大概什么时候打电话 01000000034659345380947287361795 2025-07-25 22:31:22 关 AI-Lbo0rDBXCyBY 2025-07-25 22:31:26 好的，这个也是您的微信号吗？ 01000000034659345380947287361795 2025-07-25 22:31:34 不是 AI-Lbo0rDBXCyBY 2025-07-25 22:31:37 好的，那您正确的联系方式是多少呢？ 01000000034659345380947287361795 2025-07-25 22:31:39 15210674805 AI-Lbo0rDBXCyBY 2025-07-25 22:31:42 方便提供一下您的微信吗？到时候微信给您转发资料 01000000034659345380947287361795 2025-07-25 22:31:44 这个是微信 AI-Lbo0rDBXCyBY 2025-07-25 22:31:47 稍后老师会联系哈 01000000034659345380947287361795 2025-07-25 22:31:50 ok AI-Lbo0rDBXCyBY 2025-07-25 22:31:54 好的，请问还有其他问题需要咨询吗？ 01000000034659345380947287361795 2025-07-25 22:32:03 没了 AI-Lbo0rDBXCyBY 2025-07-25 22:32:06 联系方式已收到，第二天上午9点后与您联系的，感谢您的访问 祝您生活愉快！您可以关闭对话早点休息了。晚安~ 来源页：https://m.souke.xdf.cn/ 备注：18210383301 | J80: 2026财年第2财月易聊新东方官网APP | L80: 乔文娇 | M80: 新东方官网 | N80: 新东方官网APP | P80: 乔文娇 | Q80: 2025-07-26 09:55:02 | R80: 关淼水 | S80: 赵星火 | T80: 29366928 | U80: 正常工单 | V80: 2025-07-26 11:29 | W80: A（六个月内有报课意向工单） | X80: 六级,考研专业课,考研集训营 | Y80: 大三 | Z80: 南京师范大学 | AA80: 食品与制药工程学院 | AB80: 生物工程（制药方向） | AC80: 关淼水 | AD80: 5420738 | AE80: 赵星火 | AF80: 2025-07-30 15:51 | AG80: 赵星火 | AH80: 2025-07-30 15:52 | AI80: KYZ26001 | AJ80: 27考研大二集训营（住宿费） | AK80: 国内考试 | AM80: 2720 | AP80: 新签 | AQ80: 已交接 | AR80: BJWY2101498uW2 | AS80: BJWY7720709766 | AT80: KYZ260010069 | AU80: 2025-07-30 | AW80: 回访人：赵星火，回访时间：2025-07-26 11:29，回访内容：跟进学生情况中这边继续维护学生考虑中，跟进中；|回访人：赵星火，回访时间：2025-07-26 16:18，回访内容：面谈了这边继续维护学生情况周一要再来一次跟进中；|回访人：赵星火，回访时间：2025-07-28 14:57，回访内容：表示30号这边再来校区咨询看下时间安排继续维护中，维护跟进中 | BB80: 82414438 | BC80: 否 | BD80: 27考季 | BE80: 寒暑假集训营（春秋OMO）,考研专业课300,六级无忧计划 | BF80: 英语,政治,专业课300 | BG80: 教育 | BH80: 国内高校-211 | BI80: 是 | BL80: 报名 | BN80: 本地人本地大学(常规) | BO80: 易聊在线咨询
A81: 地面业绩 | B81: 71 | C81: 北京大学部 | D81: 国内大学部 | E81: 北京市1795 | F81: 120777100 | G81: 杨俊42(国内) | H81: 2025-07-25 22:33:01 | I81: 渠道录入来源：新东方官网APP-客服 意向城市：北京访客省/城市：北京市 访客静态ID：01000000034659345380947287361795 接待分组ID：70458 搜索引擎： 搜索词： 关键词： 设备类型：phone 访客IP：114.254.3.108 对话详细内容：AI-Lbo0rDBXCyBY 2025-07-25 22:30:10 您好同学,欢迎访问北京新东方考研四六级中心. 考研线下课程26/27考季【考研全年集训营】【考研半年集训营】【考研全科线下走读班】【考研寒/暑假集训营】【考研一对一】【考研专业课】【四/六级课程】，热门课程火热报名中,咨询即可领取专享优惠。 **【考研全年集训营】=ff761f# **【考研半年集训营】=ff6b6b# **【考研全科线下走读班】=ffc158# **【考研寒/暑假集训营】=ffc158# **【考研一对一】=ff761f# **【考研专业课】=ff6caa# **【四/六级课程】=ff6caa# **【考研冲刺班】=60e27e# AI-Lbo0rDBXCyBY 2025-07-25 22:30:13 您是想咨询【线下课程】【线上课程】【考研规划】还是【在职考研】呢？**【线下课程】# **【线上课程】#**【考研规划】#**【在职考研】# 01000000034659345380947287361795 2025-07-25 22:30:17 【线下课程】 AI-Lbo0rDBXCyBY 2025-07-25 22:30:21 同学，你现在是在校还是在职呢？ 01000000034659345380947287361795 2025-07-25 22:30:28 在校 AI-Lbo0rDBXCyBY 2025-07-25 22:30:32 具体是想报考什么学校和专业呢？ 01000000034659345380947287361795 2025-07-25 22:30:44 没有想法 AI-Lbo0rDBXCyBY 2025-07-25 22:30:48 好的，我这边安排专业老师给您回电，详细沟通一下，请问您的电话是多少呢？ 01000000034659345380947287361795 2025-07-25 22:30:53 好的 AI-Lbo0rDBXCyBY 2025-07-25 22:30:57 嗯，那您联系方式是多少呢？ 01000000034659345380947287361795 2025-07-25 22:30:58 18210383301 AI-Lbo0rDBXCyBY 2025-07-25 22:31:01 好的，确认一下你的号码是否正确呢~ 01000000034659345380947287361795 2025-07-25 22:31:09 没问题 AI-Lbo0rDBXCyBY 2025-07-25 22:31:13 同学怎么称呼呢？ 01000000034659345380947287361795 2025-07-25 22:31:19 大概什么时候打电话 01000000034659345380947287361795 2025-07-25 22:31:22 关 AI-Lbo0rDBXCyBY 2025-07-25 22:31:26 好的，这个也是您的微信号吗？ 01000000034659345380947287361795 2025-07-25 22:31:34 不是 AI-Lbo0rDBXCyBY 2025-07-25 22:31:37 好的，那您正确的联系方式是多少呢？ 01000000034659345380947287361795 2025-07-25 22:31:39 15210674805 AI-Lbo0rDBXCyBY 2025-07-25 22:31:42 方便提供一下您的微信吗？到时候微信给您转发资料 01000000034659345380947287361795 2025-07-25 22:31:44 这个是微信 AI-Lbo0rDBXCyBY 2025-07-25 22:31:47 稍后老师会联系哈 01000000034659345380947287361795 2025-07-25 22:31:50 ok AI-Lbo0rDBXCyBY 2025-07-25 22:31:54 好的，请问还有其他问题需要咨询吗？ 01000000034659345380947287361795 2025-07-25 22:32:03 没了 AI-Lbo0rDBXCyBY 2025-07-25 22:32:06 联系方式已收到，第二天上午9点后与您联系的，感谢您的访问 祝您生活愉快！您可以关闭对话早点休息了。晚安~ 来源页：https://m.souke.xdf.cn/ 备注：18210383301 | J81: 2026财年第2财月易聊新东方官网APP | L81: 乔文娇 | M81: 新东方官网 | N81: 新东方官网APP | P81: 乔文娇 | Q81: 2025-07-26 09:55:02 | R81: 关淼水 | S81: 赵星火 | T81: 29366928 | U81: 正常工单 | V81: 2025-07-26 11:29 | W81: A（六个月内有报课意向工单） | X81: 六级,考研专业课,考研集训营 | Y81: 大三 | Z81: 南京师范大学 | AA81: 食品与制药工程学院 | AB81: 生物工程（制药方向） | AC81: 关淼水 | AD81: 5420738 | AE81: 赵星火 | AF81: 2025-07-30 15:51 | AG81: 赵星火 | AH81: 2025-07-30 15:52 | AI81: KYJZ26003 | AJ81: 27考研政治寒暑集训营 | AK81: 国内考试 | AM81: 8829.3 | AP81: 新签 | AQ81: 已交接 | AR81: BJWY2101498uW2 | AS81: BJWY7720709766 | AT81: KYJZ260030017 | AU81: 2025-07-30 | AW81: 回访人：赵星火，回访时间：2025-07-26 11:29，回访内容：跟进学生情况中这边继续维护学生考虑中，跟进中；|回访人：赵星火，回访时间：2025-07-26 16:18，回访内容：面谈了这边继续维护学生情况周一要再来一次跟进中；|回访人：赵星火，回访时间：2025-07-28 14:57，回访内容：表示30号这边再来校区咨询看下时间安排继续维护中，维护跟进中 | BB81: 82414438 | BC81: 否 | BD81: 27考季 | BE81: 寒暑假集训营（春秋OMO）,考研专业课300,六级无忧计划 | BF81: 英语,政治,专业课300 | BG81: 教育 | BH81: 国内高校-211 | BI81: 是 | BL81: 报名 | BN81: 本地人本地大学(常规) | BO81: 易聊在线咨询
A82: 地面业绩 | B82: 72 | C82: 北京大学部 | D82: 国内大学部 | E82: 北京市1795 | F82: 120777100 | G82: 杨俊42(国内) | H82: 2025-07-25 22:33:01 | I82: 渠道录入来源：新东方官网APP-客服 意向城市：北京访客省/城市：北京市 访客静态ID：01000000034659345380947287361795 接待分组ID：70458 搜索引擎： 搜索词： 关键词： 设备类型：phone 访客IP：114.254.3.108 对话详细内容：AI-Lbo0rDBXCyBY 2025-07-25 22:30:10 您好同学,欢迎访问北京新东方考研四六级中心. 考研线下课程26/27考季【考研全年集训营】【考研半年集训营】【考研全科线下走读班】【考研寒/暑假集训营】【考研一对一】【考研专业课】【四/六级课程】，热门课程火热报名中,咨询即可领取专享优惠。 **【考研全年集训营】=ff761f# **【考研半年集训营】=ff6b6b# **【考研全科线下走读班】=ffc158# **【考研寒/暑假集训营】=ffc158# **【考研一对一】=ff761f# **【考研专业课】=ff6caa# **【四/六级课程】=ff6caa# **【考研冲刺班】=60e27e# AI-Lbo0rDBXCyBY 2025-07-25 22:30:13 您是想咨询【线下课程】【线上课程】【考研规划】还是【在职考研】呢？**【线下课程】# **【线上课程】#**【考研规划】#**【在职考研】# 01000000034659345380947287361795 2025-07-25 22:30:17 【线下课程】 AI-Lbo0rDBXCyBY 2025-07-25 22:30:21 同学，你现在是在校还是在职呢？ 01000000034659345380947287361795 2025-07-25 22:30:28 在校 AI-Lbo0rDBXCyBY 2025-07-25 22:30:32 具体是想报考什么学校和专业呢？ 01000000034659345380947287361795 2025-07-25 22:30:44 没有想法 AI-Lbo0rDBXCyBY 2025-07-25 22:30:48 好的，我这边安排专业老师给您回电，详细沟通一下，请问您的电话是多少呢？ 01000000034659345380947287361795 2025-07-25 22:30:53 好的 AI-Lbo0rDBXCyBY 2025-07-25 22:30:57 嗯，那您联系方式是多少呢？ 01000000034659345380947287361795 2025-07-25 22:30:58 18210383301 AI-Lbo0rDBXCyBY 2025-07-25 22:31:01 好的，确认一下你的号码是否正确呢~ 01000000034659345380947287361795 2025-07-25 22:31:09 没问题 AI-Lbo0rDBXCyBY 2025-07-25 22:31:13 同学怎么称呼呢？ 01000000034659345380947287361795 2025-07-25 22:31:19 大概什么时候打电话 01000000034659345380947287361795 2025-07-25 22:31:22 关 AI-Lbo0rDBXCyBY 2025-07-25 22:31:26 好的，这个也是您的微信号吗？ 01000000034659345380947287361795 2025-07-25 22:31:34 不是 AI-Lbo0rDBXCyBY 2025-07-25 22:31:37 好的，那您正确的联系方式是多少呢？ 01000000034659345380947287361795 2025-07-25 22:31:39 15210674805 AI-Lbo0rDBXCyBY 2025-07-25 22:31:42 方便提供一下您的微信吗？到时候微信给您转发资料 01000000034659345380947287361795 2025-07-25 22:31:44 这个是微信 AI-Lbo0rDBXCyBY 2025-07-25 22:31:47 稍后老师会联系哈 01000000034659345380947287361795 2025-07-25 22:31:50 ok AI-Lbo0rDBXCyBY 2025-07-25 22:31:54 好的，请问还有其他问题需要咨询吗？ 01000000034659345380947287361795 2025-07-25 22:32:03 没了 AI-Lbo0rDBXCyBY 2025-07-25 22:32:06 联系方式已收到，第二天上午9点后与您联系的，感谢您的访问 祝您生活愉快！您可以关闭对话早点休息了。晚安~ 来源页：https://m.souke.xdf.cn/ 备注：18210383301 | J82: 2026财年第2财月易聊新东方官网APP | L82: 乔文娇 | M82: 新东方官网 | N82: 新东方官网APP | P82: 乔文娇 | Q82: 2025-07-26 09:55:02 | R82: 关淼水 | S82: 赵星火 | T82: 29366928 | U82: 正常工单 | V82: 2025-07-26 11:29 | W82: A（六个月内有报课意向工单） | X82: 六级,考研专业课,考研集训营 | Y82: 大三 | Z82: 南京师范大学 | AA82: 食品与制药工程学院 | AB82: 生物工程（制药方向） | AC82: 关淼水 | AD82: 5420738 | AE82: 赵星火 | AF82: 2025-07-30 15:51 | AG82: 赵星火 | AH82: 2025-07-30 15:52 | AI82: KYZ26003 | AJ82: 27考研寒暑集训营（英政-住宿费） | AK82: 国内考试 | AM82: 7040 | AP82: 新签 | AQ82: 已交接 | AR82: BJWY2101498uW2 | AS82: BJWY7720709766 | AT82: KYZ260030017 | AU82: 2025-07-30 | AW82: 回访人：赵星火，回访时间：2025-07-26 11:29，回访内容：跟进学生情况中这边继续维护学生考虑中，跟进中；|回访人：赵星火，回访时间：2025-07-26 16:18，回访内容：面谈了这边继续维护学生情况周一要再来一次跟进中；|回访人：赵星火，回访时间：2025-07-28 14:57，回访内容：表示30号这边再来校区咨询看下时间安排继续维护中，维护跟进中 | BB82: 82414438 | BC82: 否 | BD82: 27考季 | BE82: 寒暑假集训营（春秋OMO）,考研专业课300,六级无忧计划 | BF82: 英语,政治,专业课300 | BG82: 教育 | BH82: 国内高校-211 | BI82: 是 | BL82: 报名 | BN82: 本地人本地大学(常规) | BO82: 易聊在线咨询
A83: 地面业绩 | B83: 73 | C83: 北京大学部 | D83: 国内大学部 | E83: 北京市1795 | F83: 120777100 | G83: 杨俊42(国内) | H83: 2025-07-25 22:33:01 | I83: 渠道录入来源：新东方官网APP-客服 意向城市：北京访客省/城市：北京市 访客静态ID：01000000034659345380947287361795 接待分组ID：70458 搜索引擎： 搜索词： 关键词： 设备类型：phone 访客IP：114.254.3.108 对话详细内容：AI-Lbo0rDBXCyBY 2025-07-25 22:30:10 您好同学,欢迎访问北京新东方考研四六级中心. 考研线下课程26/27考季【考研全年集训营】【考研半年集训营】【考研全科线下走读班】【考研寒/暑假集训营】【考研一对一】【考研专业课】【四/六级课程】，热门课程火热报名中,咨询即可领取专享优惠。 **【考研全年集训营】=ff761f# **【考研半年集训营】=ff6b6b# **【考研全科线下走读班】=ffc158# **【考研寒/暑假集训营】=ffc158# **【考研一对一】=ff761f# **【考研专业课】=ff6caa# **【四/六级课程】=ff6caa# **【考研冲刺班】=60e27e# AI-Lbo0rDBXCyBY 2025-07-25 22:30:13 您是想咨询【线下课程】【线上课程】【考研规划】还是【在职考研】呢？**【线下课程】# **【线上课程】#**【考研规划】#**【在职考研】# 01000000034659345380947287361795 2025-07-25 22:30:17 【线下课程】 AI-Lbo0rDBXCyBY 2025-07-25 22:30:21 同学，你现在是在校还是在职呢？ 01000000034659345380947287361795 2025-07-25 22:30:28 在校 AI-Lbo0rDBXCyBY 2025-07-25 22:30:32 具体是想报考什么学校和专业呢？ 01000000034659345380947287361795 2025-07-25 22:30:44 没有想法 AI-Lbo0rDBXCyBY 2025-07-25 22:30:48 好的，我这边安排专业老师给您回电，详细沟通一下，请问您的电话是多少呢？ 01000000034659345380947287361795 2025-07-25 22:30:53 好的 AI-Lbo0rDBXCyBY 2025-07-25 22:30:57 嗯，那您联系方式是多少呢？ 01000000034659345380947287361795 2025-07-25 22:30:58 18210383301 AI-Lbo0rDBXCyBY 2025-07-25 22:31:01 好的，确认一下你的号码是否正确呢~ 01000000034659345380947287361795 2025-07-25 22:31:09 没问题 AI-Lbo0rDBXCyBY 2025-07-25 22:31:13 同学怎么称呼呢？ 01000000034659345380947287361795 2025-07-25 22:31:19 大概什么时候打电话 01000000034659345380947287361795 2025-07-25 22:31:22 关 AI-Lbo0rDBXCyBY 2025-07-25 22:31:26 好的，这个也是您的微信号吗？ 01000000034659345380947287361795 2025-07-25 22:31:34 不是 AI-Lbo0rDBXCyBY 2025-07-25 22:31:37 好的，那您正确的联系方式是多少呢？ 01000000034659345380947287361795 2025-07-25 22:31:39 15210674805 AI-Lbo0rDBXCyBY 2025-07-25 22:31:42 方便提供一下您的微信吗？到时候微信给您转发资料 01000000034659345380947287361795 2025-07-25 22:31:44 这个是微信 AI-Lbo0rDBXCyBY 2025-07-25 22:31:47 稍后老师会联系哈 01000000034659345380947287361795 2025-07-25 22:31:50 ok AI-Lbo0rDBXCyBY 2025-07-25 22:31:54 好的，请问还有其他问题需要咨询吗？ 01000000034659345380947287361795 2025-07-25 22:32:03 没了 AI-Lbo0rDBXCyBY 2025-07-25 22:32:06 联系方式已收到，第二天上午9点后与您联系的，感谢您的访问 祝您生活愉快！您可以关闭对话早点休息了。晚安~ 来源页：https://m.souke.xdf.cn/ 备注：18210383301 | J83: 2026财年第2财月易聊新东方官网APP | L83: 乔文娇 | M83: 新东方官网 | N83: 新东方官网APP | P83: 乔文娇 | Q83: 2025-07-26 09:55:02 | R83: 关淼水 | S83: 赵星火 | T83: 29366928 | U83: 正常工单 | V83: 2025-07-26 11:29 | W83: A（六个月内有报课意向工单） | X83: 六级,考研专业课,考研集训营 | Y83: 大三 | Z83: 南京师范大学 | AA83: 食品与制药工程学院 | AB83: 生物工程（制药方向） | AC83: 关淼水 | AD83: 5420738 | AE83: 赵星火 | AF83: 2025-07-30 15:51 | AG83: 赵星火 | AH83: 2025-07-30 15:52 | AI83: KYJY26003 | AJ83: 27考研英语寒暑集训营 | AK83: 国内考试 | AM83: 11517.6 | AP83: 新签 | AQ83: 已交接 | AR83: BJWY2101498uW2 | AS83: BJWY7720709766 | AT83: KYJY260030017 | AU83: 2025-07-30 | AW83: 回访人：赵星火，回访时间：2025-07-26 11:29，回访内容：跟进学生情况中这边继续维护学生考虑中，跟进中；|回访人：赵星火，回访时间：2025-07-26 16:18，回访内容：面谈了这边继续维护学生情况周一要再来一次跟进中；|回访人：赵星火，回访时间：2025-07-28 14:57，回访内容：表示30号这边再来校区咨询看下时间安排继续维护中，维护跟进中 | BB83: 82414438 | BC83: 否 | BD83: 27考季 | BE83: 寒暑假集训营（春秋OMO）,考研专业课300,六级无忧计划 | BF83: 英语,政治,专业课300 | BG83: 教育 | BH83: 国内高校-211 | BI83: 是 | BL83: 报名 | BN83: 本地人本地大学(常规) | BO83: 易聊在线咨询
A84: 地面业绩 | B84: 74 | C84: 北京大学部 | D84: 国内大学部 | E84: 北京市1795 | F84: 120777100 | G84: 杨俊42(国内) | H84: 2025-07-25 22:33:01 | I84: 渠道录入来源：新东方官网APP-客服 意向城市：北京访客省/城市：北京市 访客静态ID：01000000034659345380947287361795 接待分组ID：70458 搜索引擎： 搜索词： 关键词： 设备类型：phone 访客IP：114.254.3.108 对话详细内容：AI-Lbo0rDBXCyBY 2025-07-25 22:30:10 您好同学,欢迎访问北京新东方考研四六级中心. 考研线下课程26/27考季【考研全年集训营】【考研半年集训营】【考研全科线下走读班】【考研寒/暑假集训营】【考研一对一】【考研专业课】【四/六级课程】，热门课程火热报名中,咨询即可领取专享优惠。 **【考研全年集训营】=ff761f# **【考研半年集训营】=ff6b6b# **【考研全科线下走读班】=ffc158# **【考研寒/暑假集训营】=ffc158# **【考研一对一】=ff761f# **【考研专业课】=ff6caa# **【四/六级课程】=ff6caa# **【考研冲刺班】=60e27e# AI-Lbo0rDBXCyBY 2025-07-25 22:30:13 您是想咨询【线下课程】【线上课程】【考研规划】还是【在职考研】呢？**【线下课程】# **【线上课程】#**【考研规划】#**【在职考研】# 01000000034659345380947287361795 2025-07-25 22:30:17 【线下课程】 AI-Lbo0rDBXCyBY 2025-07-25 22:30:21 同学，你现在是在校还是在职呢？ 01000000034659345380947287361795 2025-07-25 22:30:28 在校 AI-Lbo0rDBXCyBY 2025-07-25 22:30:32 具体是想报考什么学校和专业呢？ 01000000034659345380947287361795 2025-07-25 22:30:44 没有想法 AI-Lbo0rDBXCyBY 2025-07-25 22:30:48 好的，我这边安排专业老师给您回电，详细沟通一下，请问您的电话是多少呢？ 01000000034659345380947287361795 2025-07-25 22:30:53 好的 AI-Lbo0rDBXCyBY 2025-07-25 22:30:57 嗯，那您联系方式是多少呢？ 01000000034659345380947287361795 2025-07-25 22:30:58 18210383301 AI-Lbo0rDBXCyBY 2025-07-25 22:31:01 好的，确认一下你的号码是否正确呢~ 01000000034659345380947287361795 2025-07-25 22:31:09 没问题 AI-Lbo0rDBXCyBY 2025-07-25 22:31:13 同学怎么称呼呢？ 01000000034659345380947287361795 2025-07-25 22:31:19 大概什么时候打电话 01000000034659345380947287361795 2025-07-25 22:31:22 关 AI-Lbo0rDBXCyBY 2025-07-25 22:31:26 好的，这个也是您的微信号吗？ 01000000034659345380947287361795 2025-07-25 22:31:34 不是 AI-Lbo0rDBXCyBY 2025-07-25 22:31:37 好的，那您正确的联系方式是多少呢？ 01000000034659345380947287361795 2025-07-25 22:31:39 15210674805 AI-Lbo0rDBXCyBY 2025-07-25 22:31:42 方便提供一下您的微信吗？到时候微信给您转发资料 01000000034659345380947287361795 2025-07-25 22:31:44 这个是微信 AI-Lbo0rDBXCyBY 2025-07-25 22:31:47 稍后老师会联系哈 01000000034659345380947287361795 2025-07-25 22:31:50 ok AI-Lbo0rDBXCyBY 2025-07-25 22:31:54 好的，请问还有其他问题需要咨询吗？ 01000000034659345380947287361795 2025-07-25 22:32:03 没了 AI-Lbo0rDBXCyBY 2025-07-25 22:32:06 联系方式已收到，第二天上午9点后与您联系的，感谢您的访问 祝您生活愉快！您可以关闭对话早点休息了。晚安~ 来源页：https://m.souke.xdf.cn/ 备注：18210383301 | J84: 2026财年第2财月易聊新东方官网APP | L84: 乔文娇 | M84: 新东方官网 | N84: 新东方官网APP | P84: 乔文娇 | Q84: 2025-07-26 09:55:02 | R84: 关淼水 | S84: 赵星火 | T84: 29366928 | U84: 正常工单 | V84: 2025-07-26 11:29 | W84: A（六个月内有报课意向工单） | X84: 六级,考研专业课,考研集训营 | Y84: 大三 | Z84: 南京师范大学 | AA84: 食品与制药工程学院 | AB84: 生物工程（制药方向） | AC84: 关淼水 | AD84: 5420738 | AE84: 赵星火 | AF84: 2025-07-30 15:51 | AG84: 赵星火 | AH84: 2025-07-30 15:52 | AI84: KYJY26001 | AJ84: 27考研英语大二集训营 | AK84: 国内考试 | AM84: 8019.9 | AP84: 新签 | AQ84: 已交接 | AR84: BJWY2101498uW2 | AS84: BJWY7720709766 | AT84: KYJY260010068 | AU84: 2025-07-30 | AW84: 回访人：赵星火，回访时间：2025-07-26 11:29，回访内容：跟进学生情况中这边继续维护学生考虑中，跟进中；|回访人：赵星火，回访时间：2025-07-26 16:18，回访内容：面谈了这边继续维护学生情况周一要再来一次跟进中；|回访人：赵星火，回访时间：2025-07-28 14:57，回访内容：表示30号这边再来校区咨询看下时间安排继续维护中，维护跟进中 | BB84: 82414438 | BC84: 否 | BD84: 27考季 | BE84: 寒暑假集训营（春秋OMO）,考研专业课300,六级无忧计划 | BF84: 英语,政治,专业课300 | BG84: 教育 | BH84: 国内高校-211 | BI84: 是 | BL84: 报名 | BN84: 本地人本地大学(常规) | BO84: 易聊在线咨询
A85: 地面业绩 | B85: 75 | C85: 北京大学部 | D85: 国内大学部 | E85: 北京市1795 | F85: 120777100 | G85: 杨俊42(国内) | H85: 2025-07-25 22:33:01 | I85: 渠道录入来源：新东方官网APP-客服 意向城市：北京访客省/城市：北京市 访客静态ID：01000000034659345380947287361795 接待分组ID：70458 搜索引擎： 搜索词： 关键词： 设备类型：phone 访客IP：114.254.3.108 对话详细内容：AI-Lbo0rDBXCyBY 2025-07-25 22:30:10 您好同学,欢迎访问北京新东方考研四六级中心. 考研线下课程26/27考季【考研全年集训营】【考研半年集训营】【考研全科线下走读班】【考研寒/暑假集训营】【考研一对一】【考研专业课】【四/六级课程】，热门课程火热报名中,咨询即可领取专享优惠。 **【考研全年集训营】=ff761f# **【考研半年集训营】=ff6b6b# **【考研全科线下走读班】=ffc158# **【考研寒/暑假集训营】=ffc158# **【考研一对一】=ff761f# **【考研专业课】=ff6caa# **【四/六级课程】=ff6caa# **【考研冲刺班】=60e27e# AI-Lbo0rDBXCyBY 2025-07-25 22:30:13 您是想咨询【线下课程】【线上课程】【考研规划】还是【在职考研】呢？**【线下课程】# **【线上课程】#**【考研规划】#**【在职考研】# 01000000034659345380947287361795 2025-07-25 22:30:17 【线下课程】 AI-Lbo0rDBXCyBY 2025-07-25 22:30:21 同学，你现在是在校还是在职呢？ 01000000034659345380947287361795 2025-07-25 22:30:28 在校 AI-Lbo0rDBXCyBY 2025-07-25 22:30:32 具体是想报考什么学校和专业呢？ 01000000034659345380947287361795 2025-07-25 22:30:44 没有想法 AI-Lbo0rDBXCyBY 2025-07-25 22:30:48 好的，我这边安排专业老师给您回电，详细沟通一下，请问您的电话是多少呢？ 01000000034659345380947287361795 2025-07-25 22:30:53 好的 AI-Lbo0rDBXCyBY 2025-07-25 22:30:57 嗯，那您联系方式是多少呢？ 01000000034659345380947287361795 2025-07-25 22:30:58 18210383301 AI-Lbo0rDBXCyBY 2025-07-25 22:31:01 好的，确认一下你的号码是否正确呢~ 01000000034659345380947287361795 2025-07-25 22:31:09 没问题 AI-Lbo0rDBXCyBY 2025-07-25 22:31:13 同学怎么称呼呢？ 01000000034659345380947287361795 2025-07-25 22:31:19 大概什么时候打电话 01000000034659345380947287361795 2025-07-25 22:31:22 关 AI-Lbo0rDBXCyBY 2025-07-25 22:31:26 好的，这个也是您的微信号吗？ 01000000034659345380947287361795 2025-07-25 22:31:34 不是 AI-Lbo0rDBXCyBY 2025-07-25 22:31:37 好的，那您正确的联系方式是多少呢？ 01000000034659345380947287361795 2025-07-25 22:31:39 15210674805 AI-Lbo0rDBXCyBY 2025-07-25 22:31:42 方便提供一下您的微信吗？到时候微信给您转发资料 01000000034659345380947287361795 2025-07-25 22:31:44 这个是微信 AI-Lbo0rDBXCyBY 2025-07-25 22:31:47 稍后老师会联系哈 01000000034659345380947287361795 2025-07-25 22:31:50 ok AI-Lbo0rDBXCyBY 2025-07-25 22:31:54 好的，请问还有其他问题需要咨询吗？ 01000000034659345380947287361795 2025-07-25 22:32:03 没了 AI-Lbo0rDBXCyBY 2025-07-25 22:32:06 联系方式已收到，第二天上午9点后与您联系的，感谢您的访问 祝您生活愉快！您可以关闭对话早点休息了。晚安~ 来源页：https://m.souke.xdf.cn/ 备注：18210383301 | J85: 2026财年第2财月易聊新东方官网APP | L85: 乔文娇 | M85: 新东方官网 | N85: 新东方官网APP | P85: 乔文娇 | Q85: 2025-07-26 09:55:02 | R85: 关淼水 | S85: 赵星火 | T85: 29366928 | U85: 正常工单 | V85: 2025-07-26 11:29 | W85: A（六个月内有报课意向工单） | X85: 六级,考研专业课,考研集训营 | Y85: 大三 | Z85: 南京师范大学 | AA85: 食品与制药工程学院 | AB85: 生物工程（制药方向） | AC85: 关淼水 | AD85: 5420738 | AE85: 赵星火 | AF85: 2025-07-30 15:51 | AG85: 赵星火 | AH85: 2025-07-30 15:52 | AI85: WYS25035 | AJ85: 六级无忧计划 | AK85: 国内考试 | AM85: 3973.2 | AP85: 新签 | AQ85: 已交接 | AR85: BJWY2101498uW2 | AS85: BJWY7720709766 | AT85: WYS250350061 | AU85: 2025-07-30 | AW85: 回访人：赵星火，回访时间：2025-07-26 11:29，回访内容：跟进学生情况中这边继续维护学生考虑中，跟进中；|回访人：赵星火，回访时间：2025-07-26 16:18，回访内容：面谈了这边继续维护学生情况周一要再来一次跟进中；|回访人：赵星火，回访时间：2025-07-28 14:57，回访内容：表示30号这边再来校区咨询看下时间安排继续维护中，维护跟进中 | BB85: 82414438 | BC85: 否 | BD85: 27考季 | BE85: 寒暑假集训营（春秋OMO）,考研专业课300,六级无忧计划 | BF85: 英语,政治,专业课300 | BG85: 教育 | BH85: 国内高校-211 | BI85: 是 | BL85: 报名 | BN85: 本地人本地大学(常规) | BO85: 易聊在线咨询
A86: 地面业绩 | B86: 76 | C86: 北京大学部 | D86: 国内大学部 | E86: 北京市1795 | F86: 120777100 | G86: 杨俊42(国内) | H86: 2025-07-25 22:33:01 | I86: 渠道录入来源：新东方官网APP-客服 意向城市：北京访客省/城市：北京市 访客静态ID：01000000034659345380947287361795 接待分组ID：70458 搜索引擎： 搜索词： 关键词： 设备类型：phone 访客IP：114.254.3.108 对话详细内容：AI-Lbo0rDBXCyBY 2025-07-25 22:30:10 您好同学,欢迎访问北京新东方考研四六级中心. 考研线下课程26/27考季【考研全年集训营】【考研半年集训营】【考研全科线下走读班】【考研寒/暑假集训营】【考研一对一】【考研专业课】【四/六级课程】，热门课程火热报名中,咨询即可领取专享优惠。 **【考研全年集训营】=ff761f# **【考研半年集训营】=ff6b6b# **【考研全科线下走读班】=ffc158# **【考研寒/暑假集训营】=ffc158# **【考研一对一】=ff761f# **【考研专业课】=ff6caa# **【四/六级课程】=ff6caa# **【考研冲刺班】=60e27e# AI-Lbo0rDBXCyBY 2025-07-25 22:30:13 您是想咨询【线下课程】【线上课程】【考研规划】还是【在职考研】呢？**【线下课程】# **【线上课程】#**【考研规划】#**【在职考研】# 01000000034659345380947287361795 2025-07-25 22:30:17 【线下课程】 AI-Lbo0rDBXCyBY 2025-07-25 22:30:21 同学，你现在是在校还是在职呢？ 01000000034659345380947287361795 2025-07-25 22:30:28 在校 AI-Lbo0rDBXCyBY 2025-07-25 22:30:32 具体是想报考什么学校和专业呢？ 01000000034659345380947287361795 2025-07-25 22:30:44 没有想法 AI-Lbo0rDBXCyBY 2025-07-25 22:30:48 好的，我这边安排专业老师给您回电，详细沟通一下，请问您的电话是多少呢？ 01000000034659345380947287361795 2025-07-25 22:30:53 好的 AI-Lbo0rDBXCyBY 2025-07-25 22:30:57 嗯，那您联系方式是多少呢？ 01000000034659345380947287361795 2025-07-25 22:30:58 18210383301 AI-Lbo0rDBXCyBY 2025-07-25 22:31:01 好的，确认一下你的号码是否正确呢~ 01000000034659345380947287361795 2025-07-25 22:31:09 没问题 AI-Lbo0rDBXCyBY 2025-07-25 22:31:13 同学怎么称呼呢？ 01000000034659345380947287361795 2025-07-25 22:31:19 大概什么时候打电话 01000000034659345380947287361795 2025-07-25 22:31:22 关 AI-Lbo0rDBXCyBY 2025-07-25 22:31:26 好的，这个也是您的微信号吗？ 01000000034659345380947287361795 2025-07-25 22:31:34 不是 AI-Lbo0rDBXCyBY 2025-07-25 22:31:37 好的，那您正确的联系方式是多少呢？ 01000000034659345380947287361795 2025-07-25 22:31:39 15210674805 AI-Lbo0rDBXCyBY 2025-07-25 22:31:42 方便提供一下您的微信吗？到时候微信给您转发资料 01000000034659345380947287361795 2025-07-25 22:31:44 这个是微信 AI-Lbo0rDBXCyBY 2025-07-25 22:31:47 稍后老师会联系哈 01000000034659345380947287361795 2025-07-25 22:31:50 ok AI-Lbo0rDBXCyBY 2025-07-25 22:31:54 好的，请问还有其他问题需要咨询吗？ 01000000034659345380947287361795 2025-07-25 22:32:03 没了 AI-Lbo0rDBXCyBY 2025-07-25 22:32:06 联系方式已收到，第二天上午9点后与您联系的，感谢您的访问 祝您生活愉快！您可以关闭对话早点休息了。晚安~ 来源页：https://m.souke.xdf.cn/ 备注：18210383301 | J86: 2026财年第2财月易聊新东方官网APP | L86: 乔文娇 | M86: 新东方官网 | N86: 新东方官网APP | P86: 乔文娇 | Q86: 2025-07-26 09:55:02 | R86: 关淼水 | S86: 赵星火 | T86: 29366928 | U86: 正常工单 | V86: 2025-07-26 11:29 | W86: A（六个月内有报课意向工单） | X86: 六级,考研专业课,考研集训营 | Y86: 大三 | Z86: 南京师范大学 | AA86: 食品与制药工程学院 | AB86: 生物工程（制药方向） | AC86: 关淼水 | AD86: 5420738 | AE86: 赵星火 | AF86: 2025-07-30 15:51 | AG86: 赵星火 | AH86: 2025-07-30 15:52 | AI86: LP17538618671269 | AJ86: 985院校升级费-集训 | AK86: 国内考试 | AM86: 3000 | AP86: 新签 | AQ86: 已交接 | AR86: BJWY2101498uW2 | AS86: BJWY7720709766 | AU86: 2025-07-30 | AW86: 回访人：赵星火，回访时间：2025-07-26 11:29，回访内容：跟进学生情况中这边继续维护学生考虑中，跟进中；|回访人：赵星火，回访时间：2025-07-26 16:18，回访内容：面谈了这边继续维护学生情况周一要再来一次跟进中；|回访人：赵星火，回访时间：2025-07-28 14:57，回访内容：表示30号这边再来校区咨询看下时间安排继续维护中，维护跟进中 | BB86: 82414438 | BC86: 否 | BD86: 27考季 | BE86: 寒暑假集训营（春秋OMO）,考研专业课300,六级无忧计划 | BF86: 英语,政治,专业课300 | BG86: 教育 | BH86: 国内高校-211 | BI86: 是 | BN86: 本地人本地大学(常规) | BO86: 易聊在线咨询
A87: 地面业绩 | B87: 77 | C87: 北京大学部 | D87: 国内大学部 | E87: 北京市1795 | F87: 120777100 | G87: 杨俊42(国内) | H87: 2025-07-25 22:33:01 | I87: 渠道录入来源：新东方官网APP-客服 意向城市：北京访客省/城市：北京市 访客静态ID：01000000034659345380947287361795 接待分组ID：70458 搜索引擎： 搜索词： 关键词： 设备类型：phone 访客IP：114.254.3.108 对话详细内容：AI-Lbo0rDBXCyBY 2025-07-25 22:30:10 您好同学,欢迎访问北京新东方考研四六级中心. 考研线下课程26/27考季【考研全年集训营】【考研半年集训营】【考研全科线下走读班】【考研寒/暑假集训营】【考研一对一】【考研专业课】【四/六级课程】，热门课程火热报名中,咨询即可领取专享优惠。 **【考研全年集训营】=ff761f# **【考研半年集训营】=ff6b6b# **【考研全科线下走读班】=ffc158# **【考研寒/暑假集训营】=ffc158# **【考研一对一】=ff761f# **【考研专业课】=ff6caa# **【四/六级课程】=ff6caa# **【考研冲刺班】=60e27e# AI-Lbo0rDBXCyBY 2025-07-25 22:30:13 您是想咨询【线下课程】【线上课程】【考研规划】还是【在职考研】呢？**【线下课程】# **【线上课程】#**【考研规划】#**【在职考研】# 01000000034659345380947287361795 2025-07-25 22:30:17 【线下课程】 AI-Lbo0rDBXCyBY 2025-07-25 22:30:21 同学，你现在是在校还是在职呢？ 01000000034659345380947287361795 2025-07-25 22:30:28 在校 AI-Lbo0rDBXCyBY 2025-07-25 22:30:32 具体是想报考什么学校和专业呢？ 01000000034659345380947287361795 2025-07-25 22:30:44 没有想法 AI-Lbo0rDBXCyBY 2025-07-25 22:30:48 好的，我这边安排专业老师给您回电，详细沟通一下，请问您的电话是多少呢？ 01000000034659345380947287361795 2025-07-25 22:30:53 好的 AI-Lbo0rDBXCyBY 2025-07-25 22:30:57 嗯，那您联系方式是多少呢？ 01000000034659345380947287361795 2025-07-25 22:30:58 18210383301 AI-Lbo0rDBXCyBY 2025-07-25 22:31:01 好的，确认一下你的号码是否正确呢~ 01000000034659345380947287361795 2025-07-25 22:31:09 没问题 AI-Lbo0rDBXCyBY 2025-07-25 22:31:13 同学怎么称呼呢？ 01000000034659345380947287361795 2025-07-25 22:31:19 大概什么时候打电话 01000000034659345380947287361795 2025-07-25 22:31:22 关 AI-Lbo0rDBXCyBY 2025-07-25 22:31:26 好的，这个也是您的微信号吗？ 01000000034659345380947287361795 2025-07-25 22:31:34 不是 AI-Lbo0rDBXCyBY 2025-07-25 22:31:37 好的，那您正确的联系方式是多少呢？ 01000000034659345380947287361795 2025-07-25 22:31:39 15210674805 AI-Lbo0rDBXCyBY 2025-07-25 22:31:42 方便提供一下您的微信吗？到时候微信给您转发资料 01000000034659345380947287361795 2025-07-25 22:31:44 这个是微信 AI-Lbo0rDBXCyBY 2025-07-25 22:31:47 稍后老师会联系哈 01000000034659345380947287361795 2025-07-25 22:31:50 ok AI-Lbo0rDBXCyBY 2025-07-25 22:31:54 好的，请问还有其他问题需要咨询吗？ 01000000034659345380947287361795 2025-07-25 22:32:03 没了 AI-Lbo0rDBXCyBY 2025-07-25 22:32:06 联系方式已收到，第二天上午9点后与您联系的，感谢您的访问 祝您生活愉快！您可以关闭对话早点休息了。晚安~ 来源页：https://m.souke.xdf.cn/ 备注：18210383301 | J87: 2026财年第2财月易聊新东方官网APP | L87: 乔文娇 | M87: 新东方官网 | N87: 新东方官网APP | P87: 乔文娇 | Q87: 2025-07-26 09:55:02 | R87: 关淼水 | S87: 赵星火 | T87: 29366928 | U87: 正常工单 | V87: 2025-07-26 11:29 | W87: A（六个月内有报课意向工单） | X87: 六级,考研专业课,考研集训营 | Y87: 大三 | Z87: 南京师范大学 | AA87: 食品与制药工程学院 | AB87: 生物工程（制药方向） | AC87: 关淼水 | AD87: 5420738 | AE87: 赵星火 | AF87: 2025-07-30 15:51 | AG87: 赵星火 | AH87: 2025-07-30 15:52 | AI87: LP17538618651266 | AJ87: 考研初试专业课一对一（27考研/集训50小时） | AK87: 国内考试 | AM87: 20000 | AP87: 新签 | AQ87: 已交接 | AR87: BJWY2101498uW2 | AS87: BJWY7720709766 | AU87: 2025-07-30 | AW87: 回访人：赵星火，回访时间：2025-07-26 11:29，回访内容：跟进学生情况中这边继续维护学生考虑中，跟进中；|回访人：赵星火，回访时间：2025-07-26 16:18，回访内容：面谈了这边继续维护学生情况周一要再来一次跟进中；|回访人：赵星火，回访时间：2025-07-28 14:57，回访内容：表示30号这边再来校区咨询看下时间安排继续维护中，维护跟进中 | BB87: 82414438 | BC87: 否 | BD87: 27考季 | BE87: 寒暑假集训营（春秋OMO）,考研专业课300,六级无忧计划 | BF87: 英语,政治,专业课300 | BG87: 教育 | BH87: 国内高校-211 | BI87: 是 | BN87: 本地人本地大学(常规) | BO87: 易聊在线咨询
A88: 地面业绩 | B88: 78 | C88: 北京大学部 | D88: 国内大学部 | E88: 家长 | F88: 119685342 | G88: 曹伟杰2 | H88: 2025-07-18 10:19:16 | I88: 孩子目前办理了延毕，打算考研，目前孩子自己想学微积分1对1。考研想考中科院或者北科大，考化学专业。家长需要老师规划两个方面，1是院校专业进一步确定，2是看学1对1、集训还是走读。目前孩子想学微积分1对1。需要老师耐心给规划一下，方便回电。孩子叫黄泰淇。 | K88: 大四 | L88: 赵星火 | M88: 线上运营-私域中台 | N88: 社群、虚拟人 | R88: 黄泰淇 | S88: 赵星火 | T88: 29194623 | U88: 续费工单 | V88: 2025-07-18 11:35 | W88: A（六个月内有报课意向工单） | X88: 考研专业课,考研无忧计划,线上考研产品 | Y88: 大四 | Z88: 清华大学 | AA88: 化学工程系 | AB88: 化学工程与工业生物工程 | AC88: 黄泰淇 | AD88: 5420638 | AE88: 赵星火 | AF88: 2025-07-30 14:11 | AG88: 赵星火 | AH88: 2025-07-30 15:43 | AI88: WYFP26010 | AJ88: 考研政治无忧计划蜂鸟（26考研/冲刺） | AK88: 国内考试 | AM88: 6540 | AP88: 续班 | AQ88: 已交接 | AR88: BJWY24032w1g8X | AS88: BJWY9471012532 | AT88: WYFP260100026 | AU88: 2025-07-30 | AW88: 回访人：赵星火，回访时间：2025-07-24 20:51，回访内容：跟进学生情况中这边继续维护学生考虑继续维护。；|回访人：赵星火，回访时间：2025-07-28 17:05，回访内容：联系不上学生再次确认下学生情况这边继续维护中。 | BB88: 68322448 | BC88: 否 | BD88: 26考季 | BE88: 无忧计划-蜂鸟,线上直通车,考研专业课150 | BF88: 英语,政治,专业课300 | BH88: 国内高校-C9 | BI88: 是 | BL88: 报名 | BM88: 109948778 | BN88: 外地人本地大学(常规) | BO88: 市场
A89: 地面业绩 | B89: 79 | C89: 北京大学部 | D89: 国内大学部 | E89: 家长 | F89: 119685342 | G89: 曹伟杰2 | H89: 2025-07-18 10:19:16 | I89: 孩子目前办理了延毕，打算考研，目前孩子自己想学微积分1对1。考研想考中科院或者北科大，考化学专业。家长需要老师规划两个方面，1是院校专业进一步确定，2是看学1对1、集训还是走读。目前孩子想学微积分1对1。需要老师耐心给规划一下，方便回电。孩子叫黄泰淇。 | K89: 大四 | L89: 赵星火 | M89: 线上运营-私域中台 | N89: 社群、虚拟人 | R89: 黄泰淇 | S89: 赵星火 | T89: 29194623 | U89: 续费工单 | V89: 2025-07-18 11:35 | W89: A（六个月内有报课意向工单） | X89: 考研专业课,考研无忧计划,线上考研产品 | Y89: 大四 | Z89: 清华大学 | AA89: 化学工程系 | AB89: 化学工程与工业生物工程 | AC89: 黄泰淇 | AD89: 5420638 | AE89: 赵星火 | AF89: 2025-07-30 14:11 | AG89: 赵星火 | AH89: 2025-07-30 15:43 | AI89: WYFP26009 | AJ89: 考研政治无忧计划蜂鸟（26考研/强化） | AK89: 国内考试 | AM89: 5760 | AP89: 续班 | AQ89: 已交接 | AR89: BJWY24032w1g8X | AS89: BJWY9471012532 | AT89: WYFP260090026 | AU89: 2025-07-30 | AW89: 回访人：赵星火，回访时间：2025-07-24 20:51，回访内容：跟进学生情况中这边继续维护学生考虑继续维护。；|回访人：赵星火，回访时间：2025-07-28 17:05，回访内容：联系不上学生再次确认下学生情况这边继续维护中。 | BB89: 68322448 | BC89: 否 | BD89: 26考季 | BE89: 无忧计划-蜂鸟,线上直通车,考研专业课150 | BF89: 英语,政治,专业课300 | BH89: 国内高校-C9 | BI89: 是 | BL89: 报名 | BM89: 109948778 | BN89: 外地人本地大学(常规) | BO89: 市场
A90: 代售网课 | B90: 80 | C90: 北京大学部 | D90: 国内大学部 | E90: 家长 | F90: 119685342 | G90: 曹伟杰2 | H90: 2025-07-18 10:19:16 | I90: 孩子目前办理了延毕，打算考研，目前孩子自己想学微积分1对1。考研想考中科院或者北科大，考化学专业。家长需要老师规划两个方面，1是院校专业进一步确定，2是看学1对1、集训还是走读。目前孩子想学微积分1对1。需要老师耐心给规划一下，方便回电。孩子叫黄泰淇。 | K90: 大四 | L90: 赵星火 | M90: 线上运营-私域中台 | N90: 社群、虚拟人 | R90: 黄泰淇 | S90: 赵星火 | T90: 29194623 | U90: 续费工单 | V90: 2025-07-18 11:35 | W90: A（六个月内有报课意向工单） | X90: 考研专业课,考研无忧计划,线上考研产品 | Y90: 大四 | Z90: 清华大学 | AA90: 化学工程系 | AB90: 化学工程与工业生物工程 | AC90: 黄泰淇 | AD90: 5420638 | AE90: 赵星火 | AF90: 2025-07-30 14:11 | AG90: 赵星火 | AH90: 2025-07-30 15:43 | AI90: 95553333194 | AJ90: 2026考研英语直通车 6期 | AK90: 国内考试 | AM90: 6791.5 | AP90: 续班 | AQ90: 已交接 | AR90: BJWY24032w1g8X | AS90: BJWY9471012532 | AU90: 2025-07-30 | AW90: 回访人：赵星火，回访时间：2025-07-24 20:51，回访内容：跟进学生情况中这边继续维护学生考虑继续维护。；|回访人：赵星火，回访时间：2025-07-28 17:05，回访内容：联系不上学生再次确认下学生情况这边继续维护中。 | BA90: 长期班 | BB90: 68322448 | BC90: 是 | BD90: 26考季 | BE90: 无忧计划-蜂鸟,线上直通车,考研专业课150 | BF90: 英语,政治,专业课300 | BH90: 国内高校-C9 | BI90: 是 | BM90: 109948778 | BN90: 外地人本地大学(常规) | BO90: 市场
A91: 地面业绩 | B91: 81 | C91: 北京大学部 | D91: 国内大学部 | E91: 家长 | F91: 119685342 | G91: 曹伟杰2 | H91: 2025-07-18 10:19:16 | I91: 孩子目前办理了延毕，打算考研，目前孩子自己想学微积分1对1。考研想考中科院或者北科大，考化学专业。家长需要老师规划两个方面，1是院校专业进一步确定，2是看学1对1、集训还是走读。目前孩子想学微积分1对1。需要老师耐心给规划一下，方便回电。孩子叫黄泰淇。 | K91: 大四 | L91: 赵星火 | M91: 线上运营-私域中台 | N91: 社群、虚拟人 | R91: 黄泰淇 | S91: 赵星火 | T91: 29194623 | U91: 续费工单 | V91: 2025-07-18 11:35 | W91: A（六个月内有报课意向工单） | X91: 考研专业课,考研无忧计划,线上考研产品 | Y91: 大四 | Z91: 清华大学 | AA91: 化学工程系 | AB91: 化学工程与工业生物工程 | AC91: 黄泰淇 | AD91: 5420638 | AE91: 赵星火 | AF91: 2025-07-30 14:11 | AG91: 赵星火 | AH91: 2025-07-30 15:43 | AI91: LP1753855910860 | AJ91: 考研初试专业课一对一（26考研/无忧30小时） | AK91: 国内考试 | AM91: 18300 | AP91: 续班 | AQ91: 已交接 | AR91: BJWY24032w1g8X | AS91: BJWY9471012532 | AU91: 2025-07-30 | AW91: 回访人：赵星火，回访时间：2025-07-24 20:51，回访内容：跟进学生情况中这边继续维护学生考虑继续维护。；|回访人：赵星火，回访时间：2025-07-28 17:05，回访内容：联系不上学生再次确认下学生情况这边继续维护中。 | BB91: 68322448 | BC91: 否 | BD91: 26考季 | BE91: 无忧计划-蜂鸟,线上直通车,考研专业课150 | BF91: 英语,政治,专业课300 | BH91: 国内高校-C9 | BI91: 是 | BM91: 109948778 | BN91: 外地人本地大学(常规) | BO91: 市场
A92: 地面业绩 | B92: 82 | C92: 北京大学部 | D92: 国内大学部 | E92: 常雅凝 | F92: 118527057 | G92: 北京国内管理员 | H92: 2025-07-10 13:25:40 | I92: 资源录入来源：小表单 市场活动id：412422 市场活动名称：新东方集团官微【新东方】资源 活动所属学校id：10000 活动所属学校名称：总公司 线索接收人邮箱：yangjun42@xdf.cn 线索接受人类型：自定义 表单信息：表单id81512、表单名(对内)：新东方集团官微【新东方】资源、表单名（对外）：新东方课程报名、创建人邮箱：wuyue38@xdf.cn、表单链接：pages/index/index.html?scene=81512,,Lh8FwYc8 备注：来源:小表单;姓名:常雅凝;意向课程: 【课程】考研、四六级、专升本、成人英语/北京/北京; 新老生: 新生; 提交链接:pages/index/index.html?scene=81512,,Lh8FwYc8;地理位置:-;渠道:新媒体运营/公众号-品牌号 | J92: 2026财年小表单-新东方集团官微【新东方】资源 | K92: 未知 | L92: 徐利霞 | M92: 线上运营-私域中台 | N92: 公众号 | P92: 徐利霞 | Q92: 2025-07-10 14:29:29 | R92: 常雅凝 | S92: 谭悦 | T92: 28979350 | U92: 正常工单 | V92: 2025-07-10 15:13 | W92: A（六个月内有报课意向工单） | X92: 考研VIP | Y92: 大四 | Z92: 中国人民公安大学 | AA92: 公安管理学院 | AB92: 公安管理学 | AC92: 常雅凝 | AD92: 5496399 | AE92: 谭悦 | AF92: 2025-07-28 17:23 | AG92: 谭悦 | AH92: 2025-07-28 17:23 | AI92: LP17536945791415 | AJ92: 考研一对一伴学班（26考季） | AK92: 国内考试 | AM92: 17500 | AP92: 新签 | AQ92: 已交接 | AS92: BJWY4575181473 | AU92: 2025-07-28 | AW92: 回访人：谭悦，回访时间：2025-07-21 18:56，回访内容：家长还要等一段时间再说 ；|回访人：谭悦，回访时间：2025-07-28 16:22，回访内容：不回复 不着急 | BB92: 81476308 | BC92: 否 | BD92: 26考季 | BE92: VIP - 伴学 | BF92: 英语,法律硕士 | BG92: 其他 | BH92: 国内高校-双一流(非985/211) | BI92: 是 | BN92: 本地人本地大学(常规) | BO92: 小表单
A93: 地面业绩 | B93: 83 | C93: 北京大学部 | D93: 国内大学部 | E93: 李思成 | F93: 117561097 | G93: 陈晶 | H93: 2025-07-04 11:14:52 | I93: 续费原因：续费50课时，原顾问转岗；该学生为保护期内续费，原顾问：国内大学部-徐铁(xutie@xdf.cn) | K93: 大四 | L93: 谭悦 | M93: 转介绍 | N93: 学管续费推荐 | O93: 陈晶chenjing171@xdf.cn | R93: 李思成 | S93: 谭悦 | T93: 28855734 | U93: 续费工单 | V93: 2025-07-04 11:28 | W93: A（六个月内有报课意向工单） | X93: 考研VIP | Y93: 大四 | Z93: 哈尔滨工程大学 | AA93: 智能科学与工程学院 | AB93: 人工智能 | AC93: 李思成 | AD93: 5419399 | AE93: 谭悦 | AF93: 2025-07-27 12:42 | AG93: 谭悦 | AH93: 2025-07-27 14:33 | AI93: LP1753591374728 | AJ93: 考研一对一伴学班（26考季） | AK93: 国内考试 | AM93: 18400 | AO93: 陈晶 | AP93: 新签 | AQ93: 已交接 | AS93: BJWY1292748225 | AU93: 2025-07-27 | AW93: 回访人：谭悦，回访时间：2025-07-24 21:35，回访内容：1 | BB93: 70318208 | BC93: 否 | BD93: 26考季 | BE93: VIP - 伴学 | BF93: 英语 | BG93: 其他 | BH93: 国内高校-211 | BI93: 是 | BN93: 本地人外地大学(归巢) | BO93: 学管续费推荐
A94: 地面业绩 | B94: 84 | C94: 北京大学部 | D94: 国内大学部 | F94: 119707692 | H94: 2025-07-18 09:54:54 | I94: 死单激活流转谭悦老师 外呼主题：批量导入-北京学校-高端学员-23.9-24.6大三【入库数据】 | K94: 大二 | L94: 谭悦 | M94: 毛坯数据 | N94: 京内毛坯数据 | R94: 杨达京 | S94: 谭悦 | T94: 29332218 | U94: 续费工单 | V94: 2025-07-26 21:15 | W94: A（六个月内有报课意向工单） | X94: 四级 | Y94: 大二 | Z94: 北京科技职业学院 | AA94: 信息安全 | AB94: 信息安全 | AC94: 杨达京 | AD94: 5522538 | AE94: 谭悦 | AF94: 2025-07-26 21:16 | AG94: 谭悦 | AH94: 2025-07-26 21:16 | AI94: YKF25007 | AJ94: 四级无忧计划 | AK94: 国内考试 | AM94: 5180 | AN94: 同科续费 | AP94: 续班 | AQ94: 已交接 | AR94: BJWY22035556hl | AS94: BJWY8544603962 | AT94: YKF250070005 | AU94: 2025-07-26 | AW94: 回访人：谭悦，回访时间：2025-07-26 21:15，回访内容：1；|回访人：谭悦，回访时间：2025-07-26 21:16，回访内容：1 | BB94: 51138576 | BC94: 否 | BD94: 25下考季 | BE94: 四级无忧计划 | BH94: 国内高校-双非 | BI94: 是 | BL94: 转出 | BN94: 本地人本地大学(常规)
A95: 地面业绩 | B95: 85 | C95: 北京大学部 | D95: 国内大学部 | F95: 119707692 | H95: 2025-07-18 09:54:54 | I95: 死单激活流转谭悦老师 外呼主题：批量导入-北京学校-高端学员-23.9-24.6大三【入库数据】 | K95: 大二 | L95: 谭悦 | M95: 毛坯数据 | N95: 京内毛坯数据 | R95: 杨达京 | S95: 谭悦 | T95: 29332218 | U95: 续费工单 | V95: 2025-07-26 21:15 | W95: A（六个月内有报课意向工单） | X95: 四级 | Y95: 大二 | Z95: 北京科技职业学院 | AA95: 信息安全 | AB95: 信息安全 | AC95: 杨达京 | AD95: 5522538 | AE95: 谭悦 | AF95: 2025-07-26 21:16 | AG95: 谭悦 | AH95: 2025-07-26 21:16 | AI95: YKF25003 | AJ95: 四级无忧计划（新大一专属） | AK95: 国内考试 | AM95: 5180 | AN95: 同科续费 | AP95: 续班 | AQ95: 已交接 | AR95: BJWY22035556hl | AS95: BJWY8544603962 | AT95: YKF250030056 | AU95: 2025-07-26 | AW95: 回访人：谭悦，回访时间：2025-07-26 21:15，回访内容：1；|回访人：谭悦，回访时间：2025-07-26 21:16，回访内容：1 | BB95: 51138576 | BC95: 否 | BD95: 25下考季 | BE95: 四级无忧计划 | BH95: 国内高校-双非 | BI95: 是 | BL95: 转出 | BN95: 本地人本地大学(常规)
A96: 地面业绩 | B96: 86 | C96: 北京大学部 | D96: 国内大学部 | E96: 张兆霆 | F96: 98914664 | G96: 曹健 | H96: 2025-04-07 10:09:31 | I96: 18612987253，北京，一对一，家长（TMK主管分配TMK） | K96: 大三 | L96: 曹健 | M96: 毛坯数据 | N96: 毛坯数据 | P96: 曹健 | Q96: 2025-04-10 18:22:39 | R96: 张兆霆 | S96: 赵星火 | T96: 27503420 | U96: 续费工单 | V96: 2025-04-10 18:36 | W96: A（六个月内有报课意向工单） | X96: 考研集训营,线上考研产品 | Y96: 大三 | Z96: 北京物资学院 | AA96: 商学院 | AB96: 财务管理 | AC96: 张兆霆 | AD96: 5521885 | AE96: 赵星火 | AF96: 2025-07-26 11:25 | AG96: 赵星火 | AH96: 2025-07-26 11:40 | AI96: LP1753500326598 | AJ96: 考研一对一伴学班（26考季） | AK96: 国内考试 | AM96: 33500 | AP96: 新签 | AQ96: 已交接 | AS96: BJWY9988220339 | AU96: 2025-07-26 | AW96: 回访人：赵星火，回访时间：2025-07-19 19:50，回访内容：24号放假这边还是确定不下来跟进中；|回访人：赵星火，回访时间：2025-07-25 20:32，回访内容：推荐课程课时中这边继续维护跟进中继续维护 | BB96: 44438330 | BC96: 否 | BD96: 26考季 | BE96: 半年集训营 | BF96: 英语 | BG96: 其他 | BH96: 国内高校-双非 | BI96: 是 | BN96: 外地人外地大学(常规)
A97: 地面业绩 | B97: 87 | C97: 北京大学部 | D97: 国内大学部 | E97: 未告知 | F97: 120772513 | G97: 段同飞 | H97: 2025-07-25 18:07:03 | I97: 内推给赵星火老师 | K97: 高三 | L97: 赵星火 | M97: 转介绍 | N97: 前途推荐（批量推送） | O97: 秦胜辉+qinshenghui@xdf.cn+秦胜辉(新东方教育科技集团有限公司-培训学校-北京学校-高中一对一部-西北区-远大路分中心 | 课程顾问) | R97: 赵翎羽 | S97: 赵星火 | T97: 29365145 | U97: 正常工单 | V97: 2025-07-25 20:05 | W97: A（六个月内有报课意向工单） | X97: 大学预科 | Y97: 高三 | Z97: 首都经济贸易大学 | AA97: 统计学院 | AB97: 统计学 | AC97: 赵翎羽 | AD97: 5521795 | AE97: 赵星火 | AF97: 2025-07-26 10:19 | AG97: 赵星火 | AH97: 2025-07-26 11:47 | AI97: YKS25003 | AJ97: 六级无忧计划（新大一专属） | AK97: 国内考试 | AM97: 4880 | AO97: 秦胜辉+qinshenghui@xdf.cn+秦胜辉(新东方教育科技集团有限公司-培训学校-北京学校-高中一对一部-西北区-远大路分中心 | 课程顾问) | AP97: 新签 | AQ97: 已交接 | AR97: BJWY24032w1g8X | AS97: BJWY3595874926 | AT97: YKS250030021 | AU97: 2025-07-26 | AW97: 回访人：赵星火，回访时间：2025-07-25 20:05，回访内容：120分以上跟进中计划报名；|回访人：赵星火，回访时间：2025-07-26 10:19，回访内容：1 | BB97: 74808876 | BC97: 否 | BH97: 国内高校-双非 | BI97: 是 | BL97: 报名 | BN97: 本地人本地大学(常规) | BO97: 客服
A98: 地面业绩 | B98: 88 | C98: 北京大学部 | D98: 国内大学部 | E98: 同学 | F98: 118475232 | G98: 吴凯龙 | H98: 2025-07-09 17:48:25 | I98: 谭悦9的顾问转介绍工单 | K98: 在职 | L98: 谭悦 | M98: 转介绍 | N98: 顾问转介绍-老带新 | O98: 谭悦tanyue9@xdf.cn | R98: 刘祎迪 | S98: 谭悦 | T98: 28958477 | U98: 正常工单 | V98: 2025-07-09 18:36 | W98: A（六个月内有报课意向工单） | X98: 考研专业课,考研无忧计划 | Y98: 在职 | Z98: 北京农学院 | AA98: 经济管理学院 | AB98: 农林经济管理 | AC98: 刘祎迪 | AD98: 5494278 | AE98: 谭悦 | AF98: 2025-07-26 15:07 | AG98: 谭悦 | AH98: 2025-07-26 15:07 | AI98: WYE27018 | AJ98: 考研英语无忧计划（27考研/基础） | AK98: 国内考试 | AM98: 3463.1 | AO98: 谭悦 | AP98: 新签 | AQ98: 已交接 | AR98: BJWY22035556hl | AS98: BJWY5939288313 | AT98: WYE270180014 | AU98: 2025-07-26 | AW98: 回访人：谭悦，回访时间：2025-07-21 19:10，回访内容：微信跟进中，27考研的课程 ；|回访人：谭悦，回访时间：2025-07-26 15:07，回访内容：1 | BB98: 81442098 | BC98: 否 | BD98: 26考季 | BE98: 无忧计划-啄木鸟,考研专业课管综 | BF98: 英语,管综 | BG98: 其他 | BH98: 国内高校-双非 | BI98: 是 | BL98: 报名 | BO98: 客服
A99: 地面业绩 | B99: 89 | C99: 北京大学部 | D99: 国内大学部 | E99: 同学 | F99: 118475232 | G99: 吴凯龙 | H99: 2025-07-09 17:48:25 | I99: 谭悦9的顾问转介绍工单 | K99: 在职 | L99: 谭悦 | M99: 转介绍 | N99: 顾问转介绍-老带新 | O99: 谭悦tanyue9@xdf.cn | R99: 刘祎迪 | S99: 谭悦 | T99: 28958477 | U99: 正常工单 | V99: 2025-07-09 18:36 | W99: A（六个月内有报课意向工单） | X99: 考研专业课,考研无忧计划 | Y99: 在职 | Z99: 北京农学院 | AA99: 经济管理学院 | AB99: 农林经济管理 | AC99: 刘祎迪 | AD99: 5494278 | AE99: 谭悦 | AF99: 2025-07-26 15:07 | AG99: 谭悦 | AH99: 2025-07-26 15:07 | AI99: WYZ27001 | AJ99: 考研专业课无忧计划（27考研/199管综） | AK99: 国内考试 | AM99: 16597.4 | AO99: 谭悦 | AP99: 新签 | AQ99: 已交接 | AR99: BJWY22035556hl | AS99: BJWY5939288313 | AT99: WYZ270010011 | AU99: 2025-07-26 | AW99: 回访人：谭悦，回访时间：2025-07-21 19:10，回访内容：微信跟进中，27考研的课程 ；|回访人：谭悦，回访时间：2025-07-26 15:07，回访内容：1 | BB99: 81442098 | BC99: 否 | BD99: 26考季 | BE99: 无忧计划-啄木鸟,考研专业课管综 | BF99: 英语,管综 | BG99: 其他 | BH99: 国内高校-双非 | BI99: 是 | BL99: 报名 | BO99: 客服
A100: 地面业绩 | B100: 90 | C100: 北京大学部 | D100: 国内大学部 | E100: 同学 | F100: 118475232 | G100: 吴凯龙 | H100: 2025-07-09 17:48:25 | I100: 谭悦9的顾问转介绍工单 | K100: 在职 | L100: 谭悦 | M100: 转介绍 | N100: 顾问转介绍-老带新 | O100: 谭悦tanyue9@xdf.cn | R100: 刘祎迪 | S100: 谭悦 | T100: 28958477 | U100: 正常工单 | V100: 2025-07-09 18:36 | W100: A（六个月内有报课意向工单） | X100: 考研专业课,考研无忧计划 | Y100: 在职 | Z100: 北京农学院 | AA100: 经济管理学院 | AB100: 农林经济管理 | AC100: 刘祎迪 | AD100: 5494278 | AE100: 谭悦 | AF100: 2025-07-26 15:07 | AG100: 谭悦 | AH100: 2025-07-26 15:07 | AI100: WYE27016 | AJ100: 考研英语无忧计划（27考研/英二强化） | AK100: 国内考试 | AM100: 5857.9 | AO100: 谭悦 | AP100: 新签 | AQ100: 已交接 | AR100: BJWY22035556hl | AS100: BJWY5939288313 | AT100: WYE270160037 | AU100: 2025-07-26 | AW100: 回访人：谭悦，回访时间：2025-07-21 19:10，回访内容：微信跟进中，27考研的课程 ；|回访人：谭悦，回访时间：2025-07-26 15:07，回访内容：1 | BB100: 81442098 | BC100: 否 | BD100: 26考季 | BE100: 无忧计划-啄木鸟,考研专业课管综 | BF100: 英语,管综 | BG100: 其他 | BH100: 国内高校-双非 | BI100: 是 | BL100: 报名 | BO100: 客服
A101: 地面业绩 | B101: 91 | C101: 北京大学部 | D101: 国内大学部 | E101: 同学 | F101: 118475232 | G101: 吴凯龙 | H101: 2025-07-09 17:48:25 | I101: 谭悦9的顾问转介绍工单 | K101: 在职 | L101: 谭悦 | M101: 转介绍 | N101: 顾问转介绍-老带新 | O101: 谭悦tanyue9@xdf.cn | R101: 刘祎迪 | S101: 谭悦 | T101: 28958477 | U101: 正常工单 | V101: 2025-07-09 18:36 | W101: A（六个月内有报课意向工单） | X101: 考研专业课,考研无忧计划 | Y101: 在职 | Z101: 北京农学院 | AA101: 经济管理学院 | AB101: 农林经济管理 | AC101: 刘祎迪 | AD101: 5494278 | AE101: 谭悦 | AF101: 2025-07-26 15:07 | AG101: 谭悦 | AH101: 2025-07-26 15:07 | AI101: WYE27030 | AJ101: 考研英语无忧计划（27考研/英二冲刺） | AK101: 国内考试 | AM101: 4881.6 | AO101: 谭悦 | AP101: 新签 | AQ101: 已交接 | AR101: BJWY22035556hl | AS101: BJWY5939288313 | AT101: WYE270300024 | AU101: 2025-07-26 | AW101: 回访人：谭悦，回访时间：2025-07-21 19:10，回访内容：微信跟进中，27考研的课程 ；|回访人：谭悦，回访时间：2025-07-26 15:07，回访内容：1 | BB101: 81442098 | BC101: 否 | BD101: 26考季 | BE101: 无忧计划-啄木鸟,考研专业课管综 | BF101: 英语,管综 | BG101: 其他 | BH101: 国内高校-双非 | BI101: 是 | BL101: 报名 | BO101: 客服
...

Sheet 7月钉钉退费共享表明细
A1: 提交日期 | B1: 您所办理的业务类型 | C1: OA流水号 | D1: 学管姓名 | E1: 学管是否代办 | F1: 顾问姓名 | G1: 顾问是否代办 | H1: 91系统-最新报名二级渠道 | I1: 原班所属项目 | J1: 新报入班级所属项目 | K1: 退费阶段 | L1: 退费一级原因（开课前） | M1: 退费一级原因 (开课后) | N1: 退费二级原因（专业课师资匹配原因） | O1: 退费二级原因（学员意愿转变_开课前） | P1: 退费二级原因（计划冲突_开课前） | Q1: 退费二级原因（中心原因_开课前） | R1: 退费二级原因（签约话术） | S1: 退费二级原因（教师） | T1: 退费二级原因（教学） | U1: 退费二级原因（课程安排） | V1: 退费二级原因（配套服务） | W1: 退费二级原因（配套学习设施） | X1: 退费二级原因（中心原因_开课后） | Y1: 退费二级原因（计划冲突_开课后） | Z1: 退费二级原因（学员意愿转变_开课后） | AA1: 退费三级原因（完全匹配不上）-院校、学院、专业、专业课代码及名称 | AB1: 退费详细原因说明（与OA退费详细说明保持一致） | AC1: 预计报名新班学费金额 | AD1: 转班金额（请学管填写所在班级实际金额） | AE1: 转班详细原因说明 | AF1: 提交时间 | AG1: 学校 | AH1: 学院 | AI1: 年级 | AJ1: 专业 | AK1: 提交人 | AL1: 退费类型 | AM1: 学员姓名 | AN1: 学员编码 | AO1: 退费金额 | AP1: 退转金额 | AQ1: 办理日期-客服 | AR1: 退费方式-客服 | AS1: 需要跟进的顾问/学管 | AT1: 退费/转班特殊情况备注（若需要学管提供银行卡信息，可将需求填写在此处）-客服 | AU1: 是否完成退费/转班-客服 | AV1: 父记录 | AW1: 父记录
A2: 2025/07/02 | B2: 转班 | D2: 韦艺鑫 | F2: 谭悦 | H2: 大众点评 | I2: 无忧项目（弃用） | AD2: 9940.4 | AE2: 更换目标院校，改考英语二 | AF2: 2025-07-02 | AK2: 韦艺鑫 | AM2: 黄禹淇 | AN2: BJWY4049653605 | AP2: 9940.4 | AQ2: 2025/07/02 | AR2: 已转班 | AU2: TRUE
A3: 2025/07/30 | B3: 转班 | D3: 许庆典 | F3: 谭悦 | H3: 大众点评 | I3: 无忧项目-班课 | AD3: 6911.7 | AE3: 更换目标院校，改考英语一 | AF3: 2025-07-30 | AK3: 许庆典 | AM3: 黄禹淇 | AN3: BJWY4049653605 | AP3: 6911.7 | AQ3: 2025/07/30 | AR3: 已转班 | AU3: TRUE
A4: 2025/07/02 | B4: 退费 | C4: NO.4323455642276930888 | D4: 马一鸣16-马一鸣 | F4: 谭悦 | H4: 学管续费推荐 | I4: 无忧项目（弃用） | K4: 开课后退费 | M4: 学员意愿转变_开课后 | Z4: 考研信心不足（因跟不上、基础薄弱、目标过高） | AB4: 学生原先报考浙江大学，因测试后觉得自己考不上，打算报考本校北京交通大学，换一个更加稳妥的学校。 | AF4: 2025-07-04 | AK4: 马一鸣16-马一鸣 | AL4: 真实产生的退费 | AM4: 黄禹淇 | AN4: BJWY4049653605 | AO4: 2550 | AP4: 2550 | AQ4: 2025/07/05 | AR4: 7.9财务付款成功 7.7已转手工退至学员本人银行卡，用户短信已确认（6.8）@马一鸣16 (马一鸣) | AU4: TRUE
A5: 2025/07/02 | B5: 退费 | C5: 18750907 | D5: 郑雪新 | F5: 谭悦 | H5: 总部-百度投放 | I5: 集训营项目（弃用） | K5: 开课前退费 | L5: 计划冲突_开课前 | P5: 学校事务和新东方时间冲突 | AB5: 1】KYJS250180006 KYJS25018 26考研数学OMO全程集训营（政英数联报） 187602】KYJZ250180006 KYJZ25018 26考研政治OMO全程集训营（政英数联报）12043.23】KYJY250180006 KYJY25018 26考研英语OMO全程集训营（英政数联报）13816.84】KYZ250180006 KYZ25018 26考研OMO全程集训营（住宿费/政英数/经综）7680【扣7300补给专业课优惠】5】专业课系统费用11000，保留专业课需要扣除18800-500=18300，即补专业课7300元（此部分费用从住宿费班号扣除） | AF5: 2025-07-02 | AK5: 郑雪新 | AL5: 真实产生的退费 | AM5: 吴嘉豪 | AN5: BJWY8214160628 | AO5: 44620 | AP5: 44620 | AQ5: 2025/07/03 | AR5: 7.10财务付款成功 7.4已转手工退，用户短信已确认 | AU5: TRUE
A6: 2025/07/02 | B6: 退费 | C6: 18750919 | D6: 郑雪新 | F6: 谭悦 | H6: 总部-百度投放 | I6: 集训营项目（弃用） | K6: 开课前退费 | L6: 计划冲突_开课前 | P6: 学校事务和新东方时间冲突 | AB6: 1】KYJS250180006 KYJS25018 26考研数学OMO全程集训营（政英数联报） 187602】KYJZ250180006 KYJZ25018 26考研政治OMO全程集训营（政英数联报）12043.23】KYJY250180006 KYJY25018 26考研英语OMO全程集训营（英政数联报）13816.84】KYZ250180006 KYZ25018 26考研OMO全程集训营（住宿费/政英数/经综）7680【扣7300补给专业课优惠】5】专业课系统费用11000，保留专业课需要扣除18800-500=18300，即补专业课7300元（此部分费用从住宿费班号扣除） | AF6: 2025-07-02 | AK6: 郑雪新 | AL6: 真实产生的退费 | AM6: 吴嘉豪 | AN6: BJWY8214160628 | AO6: 380 | AP6: 380 | AQ6: 2025/07/03 | AR6: 7.10财务付款成功 7.4已转手工退，用户短信已确认 | AU6: TRUE
A7: 2025/07/06 | B7: 转班 | D7: 黄小妹7-黄小妹 | F7: 谭悦 | H7: 百度投放 | I7: 无忧项目-班课 | AD7: 9959.6 | AE7: 学生报考院校公告考试科目变更 英二转英一 | AF7: 2025-07-06 | AK7: 黄小妹7-黄小妹 | AM7: 刘明喆 | AN7: XDF032220080227974 | AP7: 9959.6 | AQ7: 2025/07/06 | AR7: 已转班 | AU7: TRUE
A8: 2025/07/06 | B8: 退费 | C8: 18770083 | D8: 张琦文6-张琦文 | F8: 谭悦 | H8: 小红书 | I8: 集训营项目（弃用） | J8: 集训营项目 | K8: 开课后退费 | M8: 中心原因_开课后 | X8: 退出重报（取消班/合班/延转/选班/扩科等） | AB8: 学员转班七月半年集训营，退出现有班级金额到学员账户，重新入班 | AC8: ¥67200.00 | AF8: 2025-07-06 | AK8: 张琦文6-张琦文 | AL8: 转项目/转班/退出重报等未产生实际退费 | AM8: 王仪阳 | AN8: BJWY6088825240 | AO8: 4960 | AP8: 4960 | AQ8: 2025/07/07 | AR8: 退至学员账户 | AU8: TRUE
A9: 2025/07/06 | B9: 退费 | C9: 18770068 | D9: 张琦文6-张琦文 | F9: 谭悦 | H9: 小红书 | I9: 集训营项目（弃用） | J9: 集训营项目 | K9: 开课后退费 | M9: 中心原因_开课后 | X9: 退出重报（取消班/合班/延转/选班/扩科等） | AB9: 学员转班七月半年集训营，退出现有班级金额到学员账户，重新入班 | AC9: ¥67200.00 | AF9: 2025-07-06 | AK9: 张琦文6-张琦文 | AL9: 转项目/转班/退出重报等未产生实际退费 | AM9: 王仪阳 | AN9: BJWY6088825240 | AO9: 11879 | AP9: 11879 | AQ9: 2025/07/07 | AR9: 退至学员账户 | AU9: TRUE
A10: 2025/07/06 | B10: 退费 | C10: 18770042 | D10: 张琦文6-张琦文 | F10: 谭悦 | H10: 小红书 | I10: 集训营项目（弃用） | J10: 集训营项目 | K10: 开课后退费 | M10: 中心原因_开课后 | X10: 退出重报（取消班/合班/延转/选班/扩科等） | AB10: 学员转班七月半年集训营，退出现有班级金额到学员账户，重新入班 | AC10: ¥67200.00 | AF10: 2025-07-06 | AK10: 张琦文6-张琦文 | AL10: 转项目/转班/退出重报等未产生实际退费 | AM10: 王仪阳 | AN10: BJWY6088825240 | AO10: 5863 | AP10: 5863 | AQ10: 2025/07/07 | AR10: 退至学员账户 | AU10: TRUE
A11: 2025/07/06 | B11: 退费 | C11: NO.1152921504608137010 | D11: 郭又华 | F11: 谭悦 | H11: 学管续费推荐 | I11: 无忧项目（弃用） | J11: VIP项目 | K11: 开课前退费 | L11: 中心原因_开课前 | Q11: 退出重报（取消班/合班/延转/选班/扩科等） | AB11: 学生心理状态不太好，今年先不打算考研了，想把公共课和专业课剩余课时全部退到学员账户，再转成一对一课程，重新报入 | AC11: ¥10000.00 | AF11: 2025-07-06 | AK11: 郭又华 | AL11: 转项目/转班/退出重报等未产生实际退费 | AM11: 陈一凡 | AN11: BJWY8503976521 | AO11: 10000 | AP11: 5863 | AQ11: 2025/07/14 | AR11: 要求退学生账户 | AU11: TRUE | AX11: 离职顾问代办理 | AY11: 10000
A12: 2025/07/11 | B12: 退费 | C12: 18783288 | D12: 唐源曼 | F12: 谭悦 | H12: 知了好学 | I12: 集训营项目-班课 | K12: 开课后退费 | M12: 学员意愿转变_开课后 | Z12: 考研信心不足（因跟不上、基础薄弱、目标过高） | AB12: 学员换了学校不需要考数三，转到七月政英经综班 | AF12: 2025-07-15 | AG12: 北京邮电大学 | AH12: 电子工程学院 | AI12: 已毕业 | AJ12: 电子信息科学与技术 | AK12: 唐源曼 | AL12: 真实产生的退费 | AM12: 王英帆 | AN12: BJWY4965756550 | AO12: 16900 | AP12: =AY12/2 -> 8450 | AQ12: 2025/07/16 | AR12: 7.23退款完成 7.22用户短信已确认，退款中@唐源曼 7.19转手工，待用户短信确认—————— 合计退费金额为81902.1 ，暂退至学员账户，原渠道为汇款，需提供原汇款账户6226622106991108的详细信息@唐源曼 [图片] | AU12: TRUE | AX12: 谭悦，星火分单 | AY12: 16900
A13: 2025/07/11 | B13: 退费 | C13: 18783290 | D13: 唐源曼 | F13: 谭悦 | H13: 知了好学 | I13: 集训营项目-班课 | K13: 开课后退费 | M13: 学员意愿转变_开课后 | Z13: 考研信心不足（因跟不上、基础薄弱、目标过高） | AB13: 学员换了学校不需要考数三，转到七月政英经综班 | AF13: 2025-07-15 | AG13: 北京邮电大学 | AH13: 电子工程学院 | AI13: 已毕业 | AJ13: 电子信息科学与技术 | AK13: 唐源曼 | AL13: 真实产生的退费 | AM13: 王英帆 | AN13: BJWY4965756550 | AO13: 4816.2 | AP13: =AY13/2 -> 2408.1 | AQ13: 2025/07/16 | AR13: 7.23退款完成 7.22用户短信已确认，退款中@唐源曼 7.19转手工，待用户短信确认—————— 合计退费金额为81902.1 ，暂退至学员账户，原渠道为汇款，需提供原汇款账户6226622106991108的详细信息@唐源曼 [图片] | AU13: TRUE | AX13: 谭悦，星火分单 | AY13: 4816.2
A14: 2025/07/11 | B14: 退费 | C14: 18783292 | D14: 唐源曼 | F14: 谭悦 | H14: 知了好学 | I14: 集训营项目-班课 | K14: 开课后退费 | M14: 学员意愿转变_开课后 | Z14: 考研信心不足（因跟不上、基础薄弱、目标过高） | AB14: 学员换了学校不需要考数三，转到七月政英经综班 | AF14: 2025-07-15 | AG14: 北京邮电大学 | AH14: 电子工程学院 | AI14: 已毕业 | AJ14: 电子信息科学与技术 | AK14: 唐源曼 | AL14: 真实产生的退费 | AM14: 王英帆 | AN14: BJWY4965756550 | AO14: 14855.3 | AP14: =AY14/2 -> 7427.65 | AQ14: 2025/07/16 | AR14: 7.23退款完成 7.22用户短信已确认，退款中@唐源曼 7.19转手工，待用户短信确认—————— 合计退费金额为81902.1 ，暂退至学员账户，原渠道为汇款，需提供原汇款账户6226622106991108的详细信息@唐源曼 [图片] | AU14: TRUE | AX14: 谭悦，星火分单 | AY14: 14855.3
A15: 2025/07/11 | B15: 退费 | C15: 18783293 | D15: 唐源曼 | F15: 谭悦 | H15: 知了好学 | I15: 集训营项目-班课 | K15: 开课后退费 | M15: 学员意愿转变_开课后 | Z15: 考研信心不足（因跟不上、基础薄弱、目标过高） | AB15: 学员换了学校不需要考数三，转到七月政英经综班 | AF15: 2025-07-15 | AG15: 北京邮电大学 | AH15: 电子工程学院 | AI15: 已毕业 | AJ15: 电子信息科学与技术 | AK15: 唐源曼 | AL15: 真实产生的退费 | AM15: 王英帆 | AN15: BJWY4965756550 | AO15: 5561.8 | AP15: =AY15/2 -> 2780.9 | AQ15: 2025/07/16 | AR15: 7.23退款完成 7.22用户短信已确认，退款中@唐源曼 7.19转手工，待用户短信确认—————— 合计退费金额为81902.1 ，暂退至学员账户，原渠道为汇款，需提供原汇款账户6226622106991108的详细信息@唐源曼 [图片] | AU15: TRUE | AX15: 谭悦，星火分单 | AY15: 5561.8
A16: 2025/07/11 | B16: 退费 | C16: 18783296 | D16: 唐源曼 | F16: 谭悦 | H16: 知了好学 | I16: 集训营项目-班课 | K16: 开课后退费 | M16: 学员意愿转变_开课后 | Z16: 考研信心不足（因跟不上、基础薄弱、目标过高） | AB16: 学员换了学校不需要考数三，转到七月政英经综班 | AF16: 2025-07-15 | AG16: 北京邮电大学 | AH16: 电子工程学院 | AI16: 已毕业 | AJ16: 电子信息科学与技术 | AK16: 唐源曼 | AL16: 真实产生的退费 | AM16: 王英帆 | AN16: BJWY4965756550 | AO16: 9703.8 | AP16: =AY16/2 -> 4851.9 | AQ16: 2025/07/16 | AR16: 7.23退款完成 7.22用户短信已确认，退款中@唐源曼 7.19转手工，待用户短信确认—————— 合计退费金额为81902.1 ，暂退至学员账户，原渠道为汇款，需提供原汇款账户6226622106991108的详细信息@唐源曼 [图片] | AU16: TRUE | AX16: 谭悦，星火分单 | AY16: 9703.8
A17: 2025/07/11 | B17: 退费 | C17: 18783285 | D17: 唐源曼 | F17: 谭悦 | H17: 知了好学 | I17: 集训营项目-班课 | K17: 开课前退费 | L17: 学员意愿转变_开课前 | O17: 考研信心不足（因跟不上、基础薄弱、目标过高） | AB17: 学员换了学校不需要考数三，转到七月政英经综班 | AF17: 2025-07-15 | AG17: 北京邮电大学 | AH17: 电子工程学院 | AI17: 已毕业 | AJ17: 电子信息科学与技术 | AK17: 唐源曼 | AL17: 真实产生的退费 | AM17: 王英帆 | AN17: BJWY4965756550 | AO17: 5265 | AP17: =AY17/2 -> 2632.5 | AQ17: 2025/07/17 | AR17: 7.23退款完成 7.22用户短信已确认，退款中@唐源曼 7.19转手工，待用户短信确认—————— 合计退费金额为81902.1 ，暂退至学员账户，原渠道为汇款，需提供原汇款账户6226622106991108的详细信息@唐源曼 [图片] | AU17: TRUE | AX17: 谭悦，星火分单 | AY17: 5265
A18: 2025/07/11 | B18: 退费 | C18: 18783281 | D18: 唐源曼 | F18: 谭悦 | H18: 知了好学 | I18: 集训营项目-班课 | K18: 开课后退费 | M18: 学员意愿转变_开课后 | Z18: 考研信心不足（因跟不上、基础薄弱、目标过高） | AB18: 学员换了学校不需要考数三，转到七月政英经综班 | AF18: 2025-07-15 | AG18: 北京邮电大学 | AH18: 电子工程学院 | AI18: 已毕业 | AJ18: 电子信息科学与技术 | AK18: 唐源曼 | AL18: 真实产生的退费 | AM18: 王英帆 | AN18: BJWY4965756550 | AO18: 24800 | AP18: =AY18/2 -> 12400 | AQ18: 2025/07/16 | AR18: 7.23退款完成 7.22用户短信已确认，退款中@唐源曼 7.19转手工，待用户短信确认—————— 合计退费金额为81902.1 ，暂退至学员账户，原渠道为汇款，需提供原汇款账户6226622106991108的详细信息@唐源曼 [图片] | AU18: TRUE | AX18: 谭悦，星火分单 | AY18: 24800
A19: 2025/07/10 | B19: 退费 | C19: 2025071100308 | D19: 陈晶171-陈晶 | F19: 谭悦 | H19: 集团-百度品专 | I19: VIP项目-VIP | K19: 开课后退费 | M19: 学员意愿转变_开课后 | Z19: 认为课程用处不大/不适合自己 | AB19: 初复试课时都没用完，现在收到录取通知书了，不辅导其他内容 | AF19: 2025-07-14 | AG19: 北京电影学院 | AH19: 表演系 | AI19: 大四 | AJ19: 表演 | AK19: 陈晶171-陈晶 | AL19: 真实产生的退费 | AM19: 祝雪妍 | AN19: BJWY1605479028 | AO19: 19200 | AP19: 19200 | AQ19: 2025/07/17 | AR19: 支付宝退回 | AU19: TRUE
A20: 2025/07/18 | B20: 退费 | C20: 18800865 | D20: 郝琨 | F20: 谭悦 | H20: 学管续费推荐 | I20: 无忧项目-班课 | J20: VIP项目 | K20: 开课前退费 | L20: 中心原因_开课前 | Q20: 退出重报（取消班/合班/延转/选班/扩科等） | AB20: 学生2000老生二战优惠保留给数学，英语退班需退出15800 实际分摊金额不够，需要从数学班中返款2000 | AC20: ¥20000.00 | AF20: 2025-07-18 | AG20: 北京邮电大学 | AH20: 计算机学院 | AI20: 毕业 | AJ20: 通信工程 | AK20: 郝琨 | AL20: 转项目/转班/退出重报等未产生实际退费 | AM20: 蔡哲 | AN20: BJWY0874092650 | AO20: 2000 | AP20: 2000 | AQ20: 2025/07/19 | AR20: 暂退账户2000 | AU20: TRUE
A21: 2025/07/18 | B21: 退费 | C21: 18800521 | D21: 郝琨 | F21: 谭悦 | H21: 学管续费推荐 | I21: 无忧项目-班课 | J21: VIP项目 | K21: 开课前退费 | L21: 中心原因_开课前 | Q21: 退出重报（取消班/合班/延转/选班/扩科等） | AB21: 学生姓名：蔡哲学员编号：BJWY0874092650退费方式：报英语数学退英语退费原因：学生退掉暑假候鸟班英语，保留数学班，保留二战优惠，退费到储值参加一对一辅导退费班级：WYHE26007、WYHE26005退费明细：英语班退出13800，从数学班返款2000，总计退出15800 | AC21: ¥20000.00 | AF21: 2025-07-18 | AG21: 北京邮电大学 | AH21: 计算机学院 | AI21: 毕业 | AJ21: 通信工程 | AK21: 郝琨 | AL21: 转项目/转班/退出重报等未产生实际退费 | AM21: 蔡哲 | AN21: BJWY0874092650 | AO21: 13800 | AP21: 13800 | AQ21: 2025/07/20 | AR21: 退回账户余额入班 | AU21: TRUE
A22: 2025/07/19 | B22: 转班 | D22: 黄小妹7-黄小妹 | F22: 谭悦 | H22: 学管转介绍 | I22: 无忧项目-班课 | AD22: 3915 | AE22: 学生时间冲突，向后转班 | AF22: 2025-07-19 | AK22: 黄小妹7-黄小妹 | AM22: 程悦 | AN22: BJWY8477545262 | AP22: 3915 | AQ22: 2025/07/19 | AR22: 已转班 | AU22: TRUE
A23: 2025/07/21 | B23: 退费 | C23: 18797336 | D23: 陈号东5-陈号东 | F23: 谭悦 | H23: 总部-巨量广告 | I23: 无忧项目-班课 | K23: 开课后退费 | M23: 学员意愿转变_开课后 | Z23: 认为课程用处不大/不适合自己 | AB23: 学生觉得课程简单，不想学中途离场 ，决定报名报网课 | AF23: 2025-07-21 | AG23: 北京交通大学 | AH23: 自动化与智能学院 | AI23: 2022级 | AJ23: 人工智能 | AK23: 陈号东5-陈号东 | AL23: 真实产生的退费 | AM23: 刘泽宇 | AN23: BJWY6304152842 | AO23: 18247.1 | AP23: 18247.1 | AQ23: 2025/07/22 | AR23: 7.24退款到账 银联商务POS退回：浦发银行621792*********5901 | AU23: TRUE
A24: 2025/07/24 | B24: 转班 | D24: 黄子琪3-黄子琪 | F24: 谭悦 | H24: 巨量广告 | I24: 无忧项目-班课 | AD24: 3891.1 | AE24: 姓名：郑雅洁 学员号：BJWY5564317069 转班信息如下：WYE27013转WYE27018 转班原因：时间有问题，想转到9月班上课 | AF24: 2025-07-24 | AK24: 黄子琪3-黄子琪 | AM24: 郑雅洁 | AN24: BJWY5564317069 | AP24: 3891.1 | AQ24: 2025/07/24 | AR24: 已转班 | AU24: TRUE
A25: 2025/07/25 | B25: 转班 | D25: 徐岩91-徐岩 | F25: 谭悦 | H25: 京内毛坯数据 | I25: 四六级项目-班课 | AD25: 6180 | AE25: 原班取消 | AF25: 2025-07-25 | AK25: 徐岩91-徐岩 | AM25: 杨达京 | AN25: BJWY8544603962 | AP25: 6180 | AQ25: 2025/07/27 | AR25: 已转班 | AU25: TRUE
A26: 2025/07/26 | B26: 转班 | D26: 徐岩91-徐岩 | F26: 谭悦 | G26: TRUE | H26: 京内毛坯数据 | I26: 四六级项目-班课 | AD26: 5180 | AE26: 从知春路班级，转到花园桥班级，已经办理，补流程。 | AF26: 2025-07-26 | AK26: 谭悦9-谭悦 | AM26: 杨达京 | AN26: BJWY8544603962 | AP26: 5180 | AQ26: 2025/07/27 | AR26: 已转班 | AU26: TRUE
A27: 2025/07/24 | B27: 退费 | C27: 18813759 | D27: 罗志勇1-罗志勇 | F27: 谭悦 | H27: 地图标点 | I27: 四六级项目-班课 | K27: 开课前退费 | L27: 学员意愿转变_开课前 | O27: 个人身体原因无法承受高强度学习 | AB27: 【开课前退费】张佳卉，ZVVA26001，学生和家长来现场报名四级集训营，由于身体不适去医院了，要调养三周，不能参加四级集训了，先做退费，后期再看需要什么样的课程。 | AF27: 2025-07-24 | AG27: 吉林建筑大学 | AH27: 建筑与规划学院 | AI27: 大四 | AJ27: 城乡规划 | AK27: 罗志勇1-罗志勇 | AL27: 真实产生的退费 | AM27: 张佳卉 | AN27: BJWY1792811322 | AO27: 15800 | AP27: 15800 | AQ27: 2025/07/31 | AR27: 微信退还 | AU27: TRUE
A28: 2025/07/28 | B28: 退费 | C28: 3458764513821909095 | D28: 史文涵1-史文涵 | F28: 谭悦 | H28: 学管续费推荐 | I28: 无忧项目-VIP | K28: 开课后退费 | M28: 学员意愿转变_开课后 | Z28: 考研信心不足（因跟不上、基础薄弱、目标过高） | AB28: 学员放弃考研 | AF28: 2025-07-28 | AG28: 北京联合大学 | AH28: 管理学院 | AI28: 大三 | AJ28: 工商管理 | AK28: 史文涵1-史文涵 | AL28: 真实产生的退费 | AM28: 孙宇航 | AN28: BJWY6390615397 | AO28: 33500 | AP28: 33500 | AQ28: 2025/07/31 | AR28: 微信退还 | AU28: TRUE
A29: 2025/07/10 | B29: 转班 | D29: 葛铭 | F29: 谭悦 | H29: 职递 | I29: 无忧项目-班课 | AD29: 4800 | AE29: 学员时间冲突，申请转班 | AF29: 2025-07-10 | AK29: 葛铭 | AM29: 毕琦昕 | AN29: BJWY1550131227 | AP29: 4800 | AQ29: 2025/07/10 | AR29: 已转班 | AU29: TRUE
A30: 2025/07/06 | B30: 退费 | C30: NO.2882303761518374667 | D30: 王嘉庆5-王嘉庆 | F30: 谭悦 | H30: 地图标点 | I30: 无忧项目（弃用） | K30: 开课前退费 | L30: 学员意愿转变_开课前 | O30: 去其他机构 | AB30: 学生自己通过朋友联系到了专业课老师，且不考虑转成其他课程 | AF30: 2025-07-06 | AK30: 王嘉庆5-王嘉庆 | AL30: 真实产生的退费 | AM30: 安麒 | AN30: BJWY3081505061 | AO30: 21000 | AP30: =AY30/2 -> 10500 | AQ30: 2025/07/11 | AR30: 支付宝退回 | AU30: TRUE | AX30: 谭悦,张俊旺分单 | AY30: 21000
A31: 2025/07/01 | B31: 转班 | D31: 郑雪新 | F31: 谭悦 | H31: 内部员工推荐 | I31: 集训营项目（弃用） | AD31: 0 | AE31: 姓名：章俊骐 学员号：BJWY4692076178 手机号：15313850822 转班信息如下：KYJY25004转到KYJY25003；KYJZ25004转到KYJZ25003 转班原因：学生英语二变更英语一，申请转班(学员原本是定的英二，今天突然更改确为英一） | AF31: 2025-07-01 | AK31: 郑雪新 | AL31: 集训批量转班 | AM31: 章俊骐 | AN31: BJWY4692076178 | AO31: 18999.4 | AP31: 38498.8 | AQ31: 2025/07/01 | AR31: 已转班 | AU31: TRUE
F32: 谭悦 | AK32: 郑雪新 | AL32: 集训批量转班 | AM32: 白恩宁 | AP32: 18969.1
F33: 谭悦 | AK33: 郑雪新 | AL33: 集训批量转班 | AM33: 谌蕙荃 | AP33: 18628.7
F34: 谭悦 | AK34: 郑雪新 | AL34: 集训批量转班 | AM34: 李兆同 | AP34: 14237.7
F35: 谭悦 | AK35: 郑雪新 | AL35: 集训批量转班 | AM35: 张思远 | AP35: 14237.8
F36: 谭悦 | AL36: 网课退费 | AM36: 学员h0d2p | AP36: 80 | AQ36: 45854.687
F37: 谭悦 | AL37: 网课退费 | AM37: DLS_7932216421 | AP37: 70 | AQ37: 45850.769
F38: 谭悦 | AL38: 网课退费 | AM38: 学员uh9jj | AP38: 100 | AQ38: 45841.552
AN39: 谭悦合计 | AP39: =SUM(AP2:AP38) -> 385713.05
A40: 2025/07/11 | B40: 退费 | C40: 18783288 | D40: 唐源曼 | F40: 赵星火 | H40: 知了好学 | I40: 集训营项目-班课 | K40: 开课后退费 | M40: 学员意愿转变_开课后 | Z40: 考研信心不足（因跟不上、基础薄弱、目标过高） | AB40: 学员换了学校不需要考数三，转到七月政英经综班 | AF40: 2025-07-15 | AG40: 北京邮电大学 | AH40: 电子工程学院 | AI40: 已毕业 | AJ40: 电子信息科学与技术 | AK40: 唐源曼 | AL40: 真实产生的退费 | AM40: 王英帆 | AN40: BJWY4965756550 | AO40: 16900 | AP40: =AY40/2 -> 8450 | AQ40: 2025/07/16 | AR40: 7.23退款完成 7.22用户短信已确认，退款中@唐源曼 7.19转手工，待用户短信确认—————— 合计退费金额为81902.1 ，暂退至学员账户，原渠道为汇款，需提供原汇款账户6226622106991108的详细信息@唐源曼 [图片] | AU40: TRUE | AX40: 谭悦，星火分单 | AY40: 16900
A41: 2025/07/11 | B41: 退费 | C41: 18783290 | D41: 唐源曼 | F41: 赵星火 | H41: 知了好学 | I41: 集训营项目-班课 | K41: 开课后退费 | M41: 学员意愿转变_开课后 | Z41: 考研信心不足（因跟不上、基础薄弱、目标过高） | AB41: 学员换了学校不需要考数三，转到七月政英经综班 | AF41: 2025-07-15 | AG41: 北京邮电大学 | AH41: 电子工程学院 | AI41: 已毕业 | AJ41: 电子信息科学与技术 | AK41: 唐源曼 | AL41: 真实产生的退费 | AM41: 王英帆 | AN41: BJWY4965756550 | AO41: 4816.2 | AP41: =AY41/2 -> 2408.1 | AQ41: 2025/07/16 | AR41: 7.23退款完成 7.22用户短信已确认，退款中@唐源曼 7.19转手工，待用户短信确认—————— 合计退费金额为81902.1 ，暂退至学员账户，原渠道为汇款，需提供原汇款账户6226622106991108的详细信息@唐源曼 [图片] | AU41: TRUE | AX41: 谭悦，星火分单 | AY41: 4816.2
A42: 2025/07/11 | B42: 退费 | C42: 18783292 | D42: 唐源曼 | F42: 赵星火 | H42: 知了好学 | I42: 集训营项目-班课 | K42: 开课后退费 | M42: 学员意愿转变_开课后 | Z42: 考研信心不足（因跟不上、基础薄弱、目标过高） | AB42: 学员换了学校不需要考数三，转到七月政英经综班 | AF42: 2025-07-15 | AG42: 北京邮电大学 | AH42: 电子工程学院 | AI42: 已毕业 | AJ42: 电子信息科学与技术 | AK42: 唐源曼 | AL42: 真实产生的退费 | AM42: 王英帆 | AN42: BJWY4965756550 | AO42: 14855.3 | AP42: =AY42/2 -> 7427.65 | AQ42: 2025/07/16 | AR42: 7.23退款完成 7.22用户短信已确认，退款中@唐源曼 7.19转手工，待用户短信确认—————— 合计退费金额为81902.1 ，暂退至学员账户，原渠道为汇款，需提供原汇款账户6226622106991108的详细信息@唐源曼 [图片] | AU42: TRUE | AX42: 谭悦，星火分单 | AY42: 14855.3
A43: 2025/07/11 | B43: 退费 | C43: 18783293 | D43: 唐源曼 | F43: 赵星火 | H43: 知了好学 | I43: 集训营项目-班课 | K43: 开课后退费 | M43: 学员意愿转变_开课后 | Z43: 考研信心不足（因跟不上、基础薄弱、目标过高） | AB43: 学员换了学校不需要考数三，转到七月政英经综班 | AF43: 2025-07-15 | AG43: 北京邮电大学 | AH43: 电子工程学院 | AI43: 已毕业 | AJ43: 电子信息科学与技术 | AK43: 唐源曼 | AL43: 真实产生的退费 | AM43: 王英帆 | AN43: BJWY4965756550 | AO43: 5561.8 | AP43: =AY43/2 -> 2780.9 | AQ43: 2025/07/16 | AR43: 7.23退款完成 7.22用户短信已确认，退款中@唐源曼 7.19转手工，待用户短信确认—————— 合计退费金额为81902.1 ，暂退至学员账户，原渠道为汇款，需提供原汇款账户6226622106991108的详细信息@唐源曼 [图片] | AU43: TRUE | AX43: 谭悦，星火分单 | AY43: 5561.8
A44: 2025/07/11 | B44: 退费 | C44: 18783296 | D44: 唐源曼 | F44: 赵星火 | H44: 知了好学 | I44: 集训营项目-班课 | K44: 开课后退费 | M44: 学员意愿转变_开课后 | Z44: 考研信心不足（因跟不上、基础薄弱、目标过高） | AB44: 学员换了学校不需要考数三，转到七月政英经综班 | AF44: 2025-07-15 | AG44: 北京邮电大学 | AH44: 电子工程学院 | AI44: 已毕业 | AJ44: 电子信息科学与技术 | AK44: 唐源曼 | AL44: 真实产生的退费 | AM44: 王英帆 | AN44: BJWY4965756550 | AO44: 9703.8 | AP44: =AY44/2 -> 4851.9 | AQ44: 2025/07/16 | AR44: 7.23退款完成 7.22用户短信已确认，退款中@唐源曼 7.19转手工，待用户短信确认—————— 合计退费金额为81902.1 ，暂退至学员账户，原渠道为汇款，需提供原汇款账户6226622106991108的详细信息@唐源曼 [图片] | AU44: TRUE | AX44: 谭悦，星火分单 | AY44: 9703.8
A45: 2025/07/11 | B45: 退费 | C45: 18783285 | D45: 唐源曼 | F45: 赵星火 | H45: 知了好学 | I45: 集训营项目-班课 | K45: 开课前退费 | L45: 学员意愿转变_开课前 | O45: 考研信心不足（因跟不上、基础薄弱、目标过高） | AB45: 学员换了学校不需要考数三，转到七月政英经综班 | AF45: 2025-07-15 | AG45: 北京邮电大学 | AH45: 电子工程学院 | AI45: 已毕业 | AJ45: 电子信息科学与技术 | AK45: 唐源曼 | AL45: 真实产生的退费 | AM45: 王英帆 | AN45: BJWY4965756550 | AO45: 5265 | AP45: =AY45/2 -> 2632.5 | AQ45: 2025/07/17 | AR45: 7.23退款完成 7.22用户短信已确认，退款中@唐源曼 7.19转手工，待用户短信确认—————— 合计退费金额为81902.1 ，暂退至学员账户，原渠道为汇款，需提供原汇款账户6226622106991108的详细信息@唐源曼 [图片] | AU45: TRUE | AX45: 谭悦，星火分单 | AY45: 5265
A46: 2025/07/11 | B46: 退费 | C46: 18783281 | D46: 唐源曼 | F46: 赵星火 | H46: 知了好学 | I46: 集训营项目-班课 | K46: 开课后退费 | M46: 学员意愿转变_开课后 | Z46: 考研信心不足（因跟不上、基础薄弱、目标过高） | AB46: 学员换了学校不需要考数三，转到七月政英经综班 | AF46: 2025-07-15 | AG46: 北京邮电大学 | AH46: 电子工程学院 | AI46: 已毕业 | AJ46: 电子信息科学与技术 | AK46: 唐源曼 | AL46: 真实产生的退费 | AM46: 王英帆 | AN46: BJWY4965756550 | AO46: 24800 | AP46: =AY46/2 -> 12400 | AQ46: 2025/07/16 | AR46: 7.23退款完成 7.22用户短信已确认，退款中@唐源曼 7.19转手工，待用户短信确认—————— 合计退费金额为81902.1 ，暂退至学员账户，原渠道为汇款，需提供原汇款账户6226622106991108的详细信息@唐源曼 [图片] | AU46: TRUE | AX46: 谭悦，星火分单 | AY46: 24800
A47: 2025/07/03 | B47: 退费 | C47: 18760838 | D47: 郑雪新 | F47: 赵星火 | H47: 新东方在线员工推荐 | I47: 集训营项目（弃用） | K47: 开课前退费 | L47: 学员意愿转变_开课前 | O47: 个人身体原因无法承受高强度学习 | AB47: 学生姓名：王钰淇学员编号：BJWY4540042254退费方式：实际退款退费原因：学员担心压力身体等原因，只退掉后续单独报入的冲刺班（之前的寒暑不变）退费班级：冲刺政英数退费明细：1】KYJS25022A0002 KYJS25022A 26考研数学集训营（强冲） 164002】KYJZ25022A0005 KYJZ25022A 26考研政治集训营（强冲）9471.73】KYZ250230002 KYZ25023 26考研冲刺集训营（住宿费）126404】KYJY25022A0006 KYJY25022 A26考研英语集训营（强冲/英语一）14988.3 冲刺班课前退费53500元 | AF47: 2025-07-03 | AK47: 郑雪新 | AL47: 真实产生的退费 | AM47: 王钰淇 | AN47: BJWY4540042254 | AO47: 53500 | AP47: 53500 | AQ47: 2025/07/04 | AR47: 支付宝原路退回 | AU47: TRUE
A48: 2025/07/08 | B48: 退费 | C48: 18774510 | D48: 郝琨 | F48: 赵星火 | H48: 京内毛坯数据 | I48: 无忧项目-班课 | K48: 开课前退费 | L48: 计划冲突_开课前 | P48: 实习和新东方时间冲突 | AB48: 学生姓名：杜昀洁学员编号：BJWY7527072721退费方式：报名英政候鸟，退英语退费原因：学生学校很忙，没有时间集中学习两科，学生坚持退英语，保留政治，后面考虑一对一退费班级：WYHE26004、WYHE26005退费明细：英政联报23800，保留政治15300，扣除单词书88，退出8412 | AF48: 2025-07-08 | AK48: 郝琨 | AL48: 真实产生的退费 | AM48: 杜昀洁 | AN48: BJWY7527072721 | AO48: 8412 | AP48: 8412 | AQ48: 2025/07/11 | AR48: 微信退回 | AU48: TRUE
A49: 2025/07/16 | B49: 转班 | D49: 葛铭 | F49: 赵星火 | H49: 其他网络投放 | I49: 无忧项目-班课 | AD49: 8261 | AE49: 学员更换科目，辛苦转班 | AF49: 2025-07-16 | AK49: 葛铭 | AM49: 朱博政 | AN49: BJWY5552920417 | AP49: 8261 | AQ49: 2025/07/17 | AR49: 已转班 | AU49: TRUE
A50: 2025/07/30 | B50: 转班 | D50: 葛铭 | F50: 赵星火 | H50: 其他网络投放 | I50: 无忧项目-班课 | AD50: 6990.1 | AE50: 学员更换专业，申请转班 | AF50: 2025-07-30 | AK50: 葛铭 | AM50: 朱博政 | AN50: BJWY5552920417 | AP50: 6990.1 | AQ50: 2025/07/30 | AR50: 已转班 | AU50: TRUE
A51: 2025/07/18 | B51: 退费 | C51: NO.2025071501692 | D51: 王立颖17-王立颖 | F51: 赵星火 | H51: 内部员工推荐 | I51: 在职项目-VIP | K51: 开课后退费 | M51: 学员意愿转变_开课后 | Z51: 考研信心不足（因跟不上、基础薄弱、目标过高） | AB51: 退费原因：学生目标是北大EMBA，资料提交了2个多月仍处于待定状态，未通过资料审核 | AF51: 2025-07-18 | AG51: 北京大学 | AH51: 光华管理学院 | AI51: 在职 | AJ51: 工商管理 | AK51: 王立颖17-王立颖 | AL51: 真实产生的退费 | AM51: 黄琳 | AN51: BJWY4447076368 | AO51: 3000 | AP51: 3000 | AQ51: 2025/07/19 | AR51: 微信退3000 | AU51: TRUE
A52: 2025/07/21 | B52: 退费 | C52: 2025072001114 | D52: 李润基 | F52: 赵星火 | H52: 其他（主动） | I52: 四六级项目-VIP | K52: 开课前退费 | L52: 学员意愿转变_开课前 | O52: 认为课程用处不大/不适合自己 | AB52: 还未使用过该课时包 没有课程需求，想要报高中应试辅导，暂无辅导能力，申请退费报高中部门，已经过挽退 | AF52: 2025-07-21 | AG52: 在职 | AH52: 在职 | AI52: 在职 | AJ52: 在职 | AK52: 李润基 | AL52: 真实产生的退费 | AM52: 李莺 | AN52: BJWY1799880736 | AO52: 10500 | AP52: 10500 | AQ52: 2025/07/29 | AR52: 微信退回 | AU52: TRUE
A53: 2025/07/17 | B53: 退费 | C53: NO.18799018 | D53: 焦子瑞 | F53: 赵星火,高龙明 | H53: 百度投放 | I53: 集训营项目-班课 | J53: 集训营项目 | K53: 开课前退费 | L53: 学员意愿转变_开课前 | O53: 个人身体原因无法承受高强度学习 | AB53: 开课前退费，费用退回至储值账户，转入8月半年的集训 退费原因：学生做了手术在康复期，公共课退费至储值账户，转入8月半年的集训课程。 专业课部分已提交另一个OA | AC53: ¥8100.00 | AF53: 2025-07-17 | AG53: 吉林大学 | AH53: 吉林大学 | AI53: 已毕业 | AJ53: 物理学 | AK53: 焦子瑞 | AL53: 转项目/转班/退出重报等未产生实际退费 | AM53: 陈廷进 | AN53: BJWY4776417923 | AO53: 6703 | AP53: =AX53/2 -> 3351.5 | AQ53: 2025/07/17 | AR53: 暂退至学员账户 | AU53: TRUE | AX53: 6703
A54: 2025/07/17 | B54: 退费 | C54: NO.18798750 | D54: 焦子瑞 | F54: 赵星火,高龙明 | H54: 百度投放 | I54: 集训营项目-班课 | J54: 集训营项目 | K54: 开课前退费 | L54: 学员意愿转变_开课前 | O54: 个人身体原因无法承受高强度学习 | AB54: 开课前退费，费用退回至储值账户，转入8月半年的集训 退费原因：学生做了手术在康复期，公共课退费至储值账户，转入8月半年的集训课程。 专业课部分已提交另一个OA | AC54: ¥9890.00 | AF54: 2025-07-17 | AG54: 吉林大学 | AH54: 物理学院 | AI54: 已毕业 | AJ54: 物理学 | AK54: 焦子瑞 | AL54: 转项目/转班/退出重报等未产生实际退费 | AM54: 陈廷进 | AN54: BJWY4776417923 | AO54: 8493 | AP54: =AX54/2 -> 4246.5 | AQ54: 2025/07/17 | AR54: 暂退至学员账户 | AU54: TRUE | AX54: 8493
A55: 2025/07/17 | B55: 退费 | C55: NO.18798017 | D55: 焦子瑞 | F55: 赵星火,高龙明 | H55: 百度投放 | I55: 集训营项目-班课 | J55: 集训营项目 | K55: 开课前退费 | L55: 学员意愿转变_开课前 | O55: 个人身体原因无法承受高强度学习 | AB55: 开课前退费，费用退回至储值账户，转入8月半年的集训 退费原因：学生做了手术在康复期，公共课退费至储值账户，转入8月半年的集训课程。 专业课部分已提交另一个OA | AC55: ¥16900.00 | AF55: 2025-07-17 | AG55: 吉林大学 | AH55: 物理学院 | AI55: 已毕业 | AJ55: 物理学 | AK55: 焦子瑞 | AL55: 转项目/转班/退出重报等未产生实际退费 | AM55: 陈廷进 | AN55: BJWY4776417923 | AO55: 15503 | AP55: =AX55/2 -> 7751.5 | AQ55: 2025/07/17 | AR55: 暂退至学员账户 | AU55: TRUE | AX55: 15503
A56: 2025/07/17 | B56: 退费 | C56: NO.18798206 | D56: 焦子瑞 | F56: 赵星火,高龙明 | H56: 百度投放 | I56: 集训营项目-班课 | J56: 集训营项目 | K56: 开课前退费 | L56: 学员意愿转变_开课前 | O56: 个人身体原因无法承受高强度学习 | AB56: 开课前退费，费用退回至储值账户，转入8月半年的集训 退费原因：学生做了手术在康复期，公共课退费至储值账户，转入8月半年的集训课程。 专业课部分已提交另一个OA | AC56: ¥7010.00 | AF56: 2025-07-17 | AG56: 吉林大学 | AH56: 物理学院 | AI56: 已毕业 | AJ56: 物理学 | AK56: 焦子瑞 | AL56: 转项目/转班/退出重报等未产生实际退费 | AM56: 陈廷进 | AN56: BJWY4776417923 | AO56: 5613 | AP56: =AX56/2 -> 2806.5 | AQ56: 2025/07/17 | AR56: 暂退至学员账户 | AU56: TRUE | AX56: 5613
A57: 2025/07/17 | B57: 退费 | C57: NO.18798262 | D57: 焦子瑞 | F57: 赵星火,高龙明 | H57: 百度投放 | I57: 集训营项目-班课 | J57: 集训营项目 | K57: 开课前退费 | L57: 学员意愿转变_开课前 | O57: 个人身体原因无法承受高强度学习 | AB57: 开课前退费，费用退回至储值账户，转入8月半年的集训 退费原因：学生做了手术在康复期，公共课退费至储值账户，转入8月半年的集训课程。 专业课部分已提交另一个OA | AC57: ¥9930.00 | AF57: 2025-07-17 | AG57: 吉林大学 | AH57: 物理学院 | AI57: 已毕业 | AJ57: 物理学 | AK57: 焦子瑞 | AL57: 转项目/转班/退出重报等未产生实际退费 | AM57: 陈廷进 | AN57: BJWY4776417923 | AO57: 8533 | AP57: =AX57/2 -> 4266.5 | AQ57: 2025/07/17 | AR57: 暂退至学员账户 | AU57: TRUE | AX57: 8533
A58: 2025/07/17 | B58: 退费 | C58: NO.18798356 | D58: 焦子瑞 | F58: 赵星火,高龙明 | H58: 百度投放 | I58: 集训营项目-班课 | J58: 集训营项目 | K58: 开课前退费 | L58: 学员意愿转变_开课前 | O58: 个人身体原因无法承受高强度学习 | AB58: 开课前退费，费用退回至储值账户，转入8月半年的集训 退费原因：学生做了手术在康复期，公共课退费至储值账户，转入8月半年的集训课程。 专业课部分已提交另一个OA | AC58: ¥21920.00 | AF58: 2025-07-17 | AG58: 吉林大学 | AH58: 物理学院 | AI58: 已毕业 | AJ58: 物理学 | AK58: 焦子瑞 | AL58: 转项目/转班/退出重报等未产生实际退费 | AM58: 陈廷进 | AN58: BJWY4776417923 | AO58: 24800 | AP58: =AX58/2 -> 12400 | AQ58: 2025/07/17 | AR58: 暂退至学员账户 | AU58: TRUE | AX58: 24800
A59: 2025/07/17 | B59: 退费 | C59: NO.18798443 | D59: 焦子瑞 | F59: 赵星火,高龙明 | H59: 百度投放 | I59: 集训营项目-班课 | J59: 集训营项目 | K59: 开课前退费 | L59: 学员意愿转变_开课前 | O59: 个人身体原因无法承受高强度学习 | AB59: 开课前退费，费用退回至储值账户，转入8月半年的集训 退费原因：学生做了手术在康复期，公共课退费至储值账户，转入8月半年的集训课程。 专业课部分已提交另一个OA | AC59: ¥15650.00 | AF59: 2025-07-17 | AG59: 吉林大学 | AH59: 物理学院 | AI59: 已毕业 | AJ59: 物理学 | AK59: 焦子瑞 | AL59: 转项目/转班/退出重报等未产生实际退费 | AM59: 陈廷进 | AN59: BJWY4776417923 | AO59: 14253 | AP59: =AX59/2 -> 7126.5 | AQ59: 2025/07/17 | AR59: 暂退至学员账户 | AU59: TRUE | AX59: 14253
A60: 2025/07/21 | B60: 退费 | C60: NO.3170534137670158103 | D60: 王士源13-王士源 | F60: 赵星火,高龙明 | H60: 百度投放 | I60: 集训营项目-专业课 | K60: 开课前退费 | L60: 中心原因_开课前 | Q60: 退出重报（取消班/合班/延转/选班/扩科等） | AB60: 已进行择校服务，基本确定院校，但学生做了手术在康复期，专业课退费至储值账户，转入8月半年的集训课程。 | AF60: 2025-07-21 | AG60: 吉林大学 | AH60: 物理学院 | AI60: 2021级 | AJ60: 物理学 | AK60: 王士源13-王士源 | AL60: 真实产生的退费 | AM60: 陈廷进 | AN60: BJWY4776417923 | AO60: 17402 | AP60: =AX60/2 -> 8701 | AQ60: 2025/07/21 | AR60: 退到学员账户 | AU60: TRUE | AX60: 17402
AL61: 集训批量转班 | AM61: 王舒桐 | AP61: 14237.7
AL62: 网课退费 | AM62: DLS_2090134225 | AP62: 7306.63 | AQ62: 45846
AL63: 网课退费 | AM63: 学员95e8h | AP63: 100 | AQ63: 45845
AN64: 星火合计 | AP64: =SUM(AP40:AP63) -> 203908.48

Sheet 7月绩效核算
C2: FY25-7月个性化顾问绩效核算
C3: 工号 | D3: 顾问 | E3: 备注 | F3: 转介绍工单目标 | G3: 转介绍工单完成 | H3: 顾问转介绍得分（50） | I3: 转介绍签约目标 | J3: 转介绍签约完成 | K3: 转介绍签约的份（30） | L3: 主动转化率目标 | M3: 主动转化率 | N3: 被动转化率目标 | O3: 被动转化率 | P3: 转化率得分（20） | Q3: 合计得分 | R3: 发放比例 | S3: 月度绩效标准 | T3: 月绩效应发
C4: 238256 | D4: 赵星火 | F4: 3 | G4: 5 | H4: 50 | I4: 1 | J4: 2 | K4: 30 | L4: 0.3 | M4: 0.27 | N4: 0.1 | O4: =3/60 -> 0.05 | P4: 12 | Q4: =H4+K4+P4 -> 92 | R4: 1 | S4: 1000 | T4: 920
C5: 341422 | D5: 谭悦 | F5: 3 | G5: 14 | H5: 50 | I5: 1 | J5: 5 | K5: 30 | L5: 0.3 | M5: 0.42 | N5: 0.1 | O5: =8/51 -> 0.15686275 | P5: 20 | Q5: 100 | R5: 0.7 | S5: 0 | T5: 0 | U5: O3无绩效

Sheet 8月绩效目标
B3: 序号 | C3: 年月 | D3: 部门 | E3: 工号 | F3: 姓名 | G3: 岗位 | H3: 绩效考核项
H4: 1.签约业绩 | I4: 2.主被动转化率 | J4: 3.老带新工单/人头/金额 | K4: 4.规划课签约人头 | L4: 5.回访时效
B5: 1 | C5: 202508 | D5: 个性化项目部 | E5: 238256 | F5: 赵星火 | G5: 学习顾问 | H5: 地面75w+代售在线3w | I5: 主动25%、被动10% | J5: 工单6/人头3/金额6 | K5: 2 | L5: 不低于中心50分位值
B6: 2 | C6: 202508 | E6: 341422 | F6: 谭悦 | H6: 地面75w+代售在线3w | I6: 主动25%、被动10% | J6: 工单6/人头3/金额6 | K6: 2 | L6: 不低于中心50分位值
B7: 3 | C7: 202508 | E7: 404905 | F7: 李涛 | H7: 整体10w | I7: 整体10% | L7: 不低于中心50分位值
