Workbook

Sheet 汇总
A1: 序号 | B1: 工号 | C1: 姓名 | D1: 部门 | E1: 岗位 | F1: 薪资项目 | G1: 金额 | H1: 备注 | K1: 说明
A2: 1 | B2: 238256 | C2: 赵星火 | D2: 考研个性化 | E2: 学习顾问 | F2: 月度绩效 | G2: =核算模版!P4 -> 600 | K2: 兵种 | L2: 薪资名称 | M2: 标化薪资项目请选择
A3: 2 | B3: 341422 | C3: 谭悦 | D3: 考研个性化 | E3: 学习顾问 | F3: 其他业绩奖金 | G3: 1000 | H3: 菁英计划签约奖金1000，学员陈政元 | K3: 顾问 | L3: 月绩效 | M3: 月度绩效
A4: 3 | B4: 404905 | C4: 李涛 | D4: 考研个性化 | E4: 学习顾问 | F4: 月度绩效 | G4: =核算模版!P6 -> 1200 | L4: 业绩提点 | M4: 提成奖金
A5: 4 | B5: 238256 | C5: 赵星火 | D5: 考研个性化 | E5: 学习顾问 | F5: 提成奖金 | G5: =核算模版!AG4 -> 1390.4312 | L5: 转介绍额外激励 | M5: 提成奖金
A6: 5 | B6: 341422 | C6: 谭悦 | D6: 考研个性化 | E6: 学习顾问 | F6: 提成奖金 | G6: =核算模版!AH5 -> 27810.468 | L6: PK赛激励 | M6: 其他业绩奖金
A7: 6 | B7: 404905 | C7: 李涛 | D7: 考研个性化 | E7: 学习顾问 | F7: 提成奖金 | G7: =核算模版!AD6 -> 0 | K7: 特殊项 | L7: 业绩回算正数 | M7: 往月薪资补发
A8: 7 | L8: 业绩回算负值 | M8: 业绩扣款
A9: 8
A10: 9
A11: 10
A12: 11
A13: 12
A14: 13
A15: 14
A16: 15
A17: 16
A18: 17
A19: 18
A20: 19
... A30: 29

Sheet 核算模版
A1: 手动填写灰色、蓝色单元格，其他含公式，勿动
A2: 个性化顾问 | D2: 转介绍业绩-30% | H2: 签约率-40% | K2: 日常管理-30% | M2: 月度绩效 | Q2: 基本提成 | AE2: 转介绍提成 | AG2: 提成奖金合计 | AH2: 合计
A3: 月份 | B3: 姓名 | C3: 职级（下滑选择） | D3: 转介绍目标 | E3: 转介绍业绩（净） | F3: 完成率 | G3: 得分 | H3: 目标 | I3: 签约率 | J3: 得分 | K3: 日常管理扣分次数 | L3: 得分 | M3: 总得分 | N3: 绩效基数 | O3: 发放比例 | P3: 发放金额 | Q3: 地面现金目标 | R3: 地面现金签约 | S3: 地面退费 | T3: 地面净现金 | U3: 在线现金目标 | V3: 在线现金签约 | W3: 在线退费 | X3: 在线净现金 | Y3: 总现金完成-退费后 | Z3: 现金完成率-退费后 | AA3: 现金完成率-退费前 | AB3: 上月退费后业绩完成率 | AC3: 奖金提点系数 | AD3: 基本提成 | AE3: 转介绍业绩提成比率 | AF3: 转介绍提成
A4: 202511 | B4: 赵星火 | C4: O2 | D4: 50000 | E4: 0 | F4: =E4/D4 -> 0 | G4: =IFERROR(IF(F4>=1,30,IF(AND(1>F4,F4>=0.7),F4*30,IF(F4<70,0))),0) -> 0 | H4: 0.25 | I4: =33/99 -> 0.33333333 | J4: =IFERROR(IF(I4>=H4,40,IF(AND(0.08>=H4-I4,H4-I4>=0.01),20-(H4-I4)*100*5,IF(H4-I4>0.08,0))),0) -> 40 | K4: 0 | L4: =IF(30-K4<0,0,30-K4) -> 30 | M4: =L4+J4+G4 -> 70 | N4: =IFERROR(IF(C4="O1",2000,IF(C4="O2",1000,IF(C4="O3",0,2000))),0) -> 1000 | O4: =IF(ISNUMBER(SEARCH("培训",C4)),1,IF(M4>=90,1,IF(M4>=70,1-(90-M4)*0.02,0))) -> 0.6 | P4: =IF(M4>=90,N4,IF(M4<70,0,IF(AND(90>M4,M4>=70),N4-N4*((90-M4)*0.02)))) -> 600 | Q4: 510000 | R4: 456580 | S4: =退费明细!AD49 -> 335830.5 | T4: =R4-S4 -> 120749.5 | U4: 5000 | V4: 53154.4 | W4: 100 | X4: =V4-W4 -> 53054.4 | Y4: =X4+T4 -> 173803.9 | Z4: =Y4/(Q4+U4) -> 0.3374833 | AA4: =(R4+V4)/Q4 -> 0.99947922 | AB4: 0.4 | AC4: =IF(ISNUMBER(SEARCH("保薪",C4)),IFERROR(IF(Z4<0.7,0%,IF(AND(Z4>=0.7,Z4<1),0.8%,IF(AND(Z4>=1,Z4<1.2),1.2%,IF(Z4>=1.2,2%)))),0),IFERROR(IF(AND(Z4>=1.5,AB4>=0.4),0.05,IF(AND(Z4>=1.5,AB4<0.4),0.04,IF(AND(Z4<1.5,Z4>=1.2),0.04,IF(AND(Z4<1.2,Z4>=1),0.03,IF(AND(Z4<1,Z4>=0.8),0.018,IF(AND(Z4<0.8,Z4>=0.7),0.008,IF(AND(Z4<0.7,AA4>=0.7),0.008,IF(AND(Z4<0.7,AA4<0.7),0)))))))),0)) -> 0.008 | AD4: =Y4*AC4 -> 1390.4312 | AE4: =IF(F4>=1,0.002,IF(F4<0.7,-0.002,IF(AND(F4>=0.7,F4<1),0))) -> -0.002 | AF4: =E4*(AE4) -> 0 | AG4: =AF4+AD4 -> 1390.4312 | AH4: =AF4+AD4+P4 -> 1990.4312
A5: 202511 | B5: 谭悦 | C5: O3 | D5: 50000 | E5: 33650 | F5: =E5/D5 -> 0.673 | G5: =IFERROR(IF(F5>=1,30,IF(AND(1>F5,F5>=0.7),F5*30,IF(F5<70,0))),0) -> 0 | H5: 0.25 | I5: =49/126 -> 0.38888889 | J5: =IFERROR(IF(I5>=H5,40,IF(AND(0.08>=H5-I5,H5-I5>=0.01),20-(H5-I5)*100*5,IF(H5-I5>0.08,0))),0) -> 40 | K5: 0 | L5: =IF(30-K5<0,0,30-K5) -> 30 | M5: =L5+J5+G5 -> 70 | N5: =IFERROR(IF(C5="O1",2000,IF(C5="O2",1000,IF(C5="O3",0,2000))),0) -> 0 | O5: =IF(ISNUMBER(SEARCH("培训",C5)),1,IF(M5>=90,1,IF(M5>=70,1-(90-M5)*0.02,0))) -> 0.6 | P5: =IF(M5>=90,N5,IF(M5<70,0,IF(AND(90>M5,M5>=70),N5-N5*((90-M5)*0.02)))) -> 0 | Q5: 510000 | R5: 746086.1 | S5: =退费明细!AD16 -> 105192.9 | T5: =R5-S5 -> 640893.2 | U5: 5000 | V5: 56251 | W5: 200 | X5: =V5-W5 -> 56051 | Y5: =X5+T5 -> 696944.2 | Z5: =Y5/(Q5+U5) -> 1.3532897 | AA5: =(R5+V5)/Q5 -> 1.57321 | AB5: 0.4 | AC5: =IF(ISNUMBER(SEARCH("保薪",C5)),IFERROR(IF(Z5<0.7,0%,IF(AND(Z5>=0.7,Z5<1),0.8%,IF(AND(Z5>=1,Z5<1.2),1.2%,IF(Z5>=1.2,2%)))),0),IFERROR(IF(AND(Z5>=1.5,AB5>=0.4),0.05,IF(AND(Z5>=1.5,AB5<0.4),0.04,IF(AND(Z5<1.5,Z5>=1.2),0.04,IF(AND(Z5<1.2,Z5>=1),0.03,IF(AND(Z5<1,Z5>=0.8),0.018,IF(AND(Z5<0.8,Z5>=0.7),0.008,IF(AND(Z5<0.7,AA5>=0.7),0.008,IF(AND(Z5<0.7,AA5<0.7),0)))))))),0)) -> 0.04 | AD5: =Y5*AC5 -> 27877.768 | AE5: =IF(F5>=1,0.002,IF(F5<0.7,-0.002,IF(AND(F5>=0.7,F5<1),0))) -> -0.002 | AF5: =E5*(AE5) -> -67.3 | AG5: =AF5+AD5 -> 27810.468 | AH5: =AF5+AD5+P5 -> 27810.468
A6: 202511 | B6: 李涛 | C6: O1 | D6: 40000 | E6: 0 | F6: =E6/D6 -> 0 | G6: =IFERROR(IF(F6>=1,30,IF(AND(1>F6,F6>=0.7),F6*30,IF(F6<70,0))),0) -> 0 | H6: 0.1 | I6: =8/43 -> 0.18604651 | J6: =IFERROR(IF(I6>=H6,40,IF(AND(0.08>=H6-I6,H6-I6>=0.01),20-(H6-I6)*100*5,IF(H6-I6>0.08,0))),0) -> 40 | K6: 0 | L6: =IF(30-K6<0,0,30-K6) -> 30 | M6: =L6+J6+G6 -> 70 | N6: =IFERROR(IF(C6="O1",2000,IF(C6="O2",1000,IF(C6="O3",0,2000))),0) -> 2000 | O6: =IF(ISNUMBER(SEARCH("培训",C6)),1,IF(M6>=90,1,IF(M6>=70,1-(90-M6)*0.02,0))) -> 0.6 | P6: =IF(M6>=90,N6,IF(M6<70,0,IF(AND(90>M6,M6>=70),N6-N6*((90-M6)*0.02)))) -> 1200 | Q6: 510000 | R6: 174610 | S6: =退费明细!AD4 -> 96900 | T6: =R6-S6 -> 77710 | U6: 4000 | V6: 18900 | W6: =退费明细!AD53 -> 27266.45 | X6: =V6-W6 -> -8366.45 | Y6: =X6+T6 -> 69343.55 | Z6: =Y6/(Q6+U6) -> 0.13490963 | AA6: =(R6+V6)/Q6 -> 0.37943137 | AB6: 0.4 | AC6: =IF(ISNUMBER(SEARCH("保薪",C6)),IFERROR(IF(Z6<0.7,0%,IF(AND(Z6>=0.7,Z6<1),0.8%,IF(AND(Z6>=1,Z6<1.2),1.2%,IF(Z6>=1.2,2%)))),0),IFERROR(IF(AND(Z6>=1.5,AB6>=0.4),0.05,IF(AND(Z6>=1.5,AB6<0.4),0.04,IF(AND(Z6<1.5,Z6>=1.2),0.04,IF(AND(Z6<1.2,Z6>=1),0.03,IF(AND(Z6<1,Z6>=0.8),0.018,IF(AND(Z6<0.8,Z6>=0.7),0.008,IF(AND(Z6<0.7,AA6>=0.7),0.008,IF(AND(Z6<0.7,AA6<0.7),0)))))))),0)) -> 0 | AD6: =Y6*AC6 -> 0 | AE6: =IF(F6>=1,0.002,IF(F6<0.7,-0.002,IF(AND(F6>=0.7,F6<1),0))) -> -0.002 | AF6: =E6*(AE6) -> 0 | AG6: =AF6+AD6 -> 0 | AH6: =AF6+AD6+P6 -> 1200
C7: 培训期 | F7: =E7/D7 -> #DIV/0! | G7: =IFERROR(IF(F7>=1,30,IF(AND(1>F7,F7>=0.7),F7*30,IF(F7<70,0))),0) -> 0 | J7: =IFERROR(IF(I7>=H7,40,IF(AND(0.08>=H7-I7,H7-I7>=0.01),20-(H7-I7)*100*5,IF(H7-I7>0.08,0))),0) -> 40 | L7: =IF(30-K7<0,0,30-K7) -> 30 | M7: =L7+J7+G7 -> 70 | N7: =IFERROR(IF(C7="O1",2000,IF(C7="O2",1000,IF(C7="O3",0,2000))),0) -> 2000 | O7: =IF(ISNUMBER(SEARCH("培训",C7)),1,IF(M7>=90,1,IF(M7>=70,1-(90-M7)*0.02,0))) -> 1 | P7: =IF(M7>=90,N7,IF(M7<70,0,IF(AND(90>M7,M7>=70),N7-N7*((90-M7)*0.02)))) -> 1200 | T7: =R7-S7 -> 0 | X7: =V7-W7 -> 0 | Y7: =X7+T7 -> 0 | Z7: =Y7/(Q7+U7) -> #DIV/0! | AA7: =(R7+V7)/Q7 -> #DIV/0! | AB7: 0.4 | AC7: =IF(ISNUMBER(SEARCH("保薪",C7)),IFERROR(IF(Z7<0.7,0%,IF(AND(Z7>=0.7,Z7<1),0.8%,IF(AND(Z7>=1,Z7<1.2),1.2%,IF(Z7>=1.2,2%)))),0),IFERROR(IF(AND(Z7>=1.5,AB7>=0.4),0.05,IF(AND(Z7>=1.5,AB7<0.4),0.04,IF(AND(Z7<1.5,Z7>=1.2),0.04,IF(AND(Z7<1.2,Z7>=1),0.03,IF(AND(Z7<1,Z7>=0.8),0.018,IF(AND(Z7<0.8,Z7>=0.7),0.008,IF(AND(Z7<0.7,AA7>=0.7),0.008,IF(AND(Z7<0.7,AA7<0.7),0)))))))),0)) -> 0 | AD7: =Y7*AC7 -> 0 | AE7: =IF(F7>=1,0.002,IF(F7<0.7,-0.002,IF(AND(F7>=0.7,F7<1),0))) -> #DIV/0! | AF7: =E7*(1+AE7) -> #DIV/0! | AG7: =AF7+AD7 -> #DIV/0! | AH7: =AF7+AD7+P7 -> #DIV/0!
C8: 培训期+保薪期 | F8: =E8/D8 -> #DIV/0! | G8: =IFERROR(IF(F8>=1,30,IF(AND(1>F8,F8>=0.7),F8*30,IF(F8<70,0))),0) -> 0 | J8: =IFERROR(IF(I8>=H8,40,IF(AND(0.08>=H8-I8,H8-I8>=0.01),20-(H8-I8)*100*5,IF(H8-I8>0.08,0))),0) -> 40 | L8: =IF(30-K8<0,0,30-K8) -> 30 | M8: =L8+J8+G8 -> 70 | N8: =IFERROR(IF(C8="O1",2000,IF(C8="O2",1000,IF(C8="O3",0,2000))),0) -> 2000 | O8: =IF(ISNUMBER(SEARCH("培训",C8)),1,IF(M8>=90,1,IF(M8>=70,1-(90-M8)*0.02,0))) -> 1 | P8: =IF(M8>=90,N8,IF(M8<70,0,IF(AND(90>M8,M8>=70),N8-N8*((90-M8)*0.02)))) -> 1200 | T8: =R8-S8 -> 0 | X8: =V8-W8 -> 0 | Y8: =X8+T8 -> 0 | Z8: =Y8/(Q8+U8) -> #DIV/0! | AA8: =(R8+V8)/Q8 -> #DIV/0! | AB8: 0.4 | AC8: =IF(ISNUMBER(SEARCH("保薪",C8)),IFERROR(IF(Z8<0.7,0%,IF(AND(Z8>=0.7,Z8<1),0.8%,IF(AND(Z8>=1,Z8<1.2),1.2%,IF(Z8>=1.2,2%)))),0),IFERROR(IF(AND(Z8>=1.5,AB8>=0.4),0.05,IF(AND(Z8>=1.5,AB8<0.4),0.04,IF(AND(Z8<1.5,Z8>=1.2),0.04,IF(AND(Z8<1.2,Z8>=1),0.03,IF(AND(Z8<1,Z8>=0.8),0.018,IF(AND(Z8<0.8,Z8>=0.7),0.008,IF(AND(Z8<0.7,AA8>=0.7),0.008,IF(AND(Z8<0.7,AA8<0.7),0)))))))),0)) -> 0 | AD8: =Y8*AC8 -> 0 | AE8: =IF(F8>=1,0.002,IF(F8<0.7,-0.002,IF(AND(F8>=0.7,F8<1),0))) -> #DIV/0! | AF8: =E8*(1+AE8) -> #DIV/0! | AG8: =AF8+AD8 -> #DIV/0! | AH8: =AF8+AD8+P8 -> #DIV/0!
B11: 职级 | C11: 说明
A12: 高提点方案 | B12: O1 | C12: 老顾问选择
B13: O2 | C13: 老顾问选择
B14: O3 | C14: 老顾问选择
B15: 培训期 | C15: 新顾问高提点方案选择，前三月阶段下标期间，选择此标签，全标后，正常选择【O1】
A16: 低提点方案 | B16: 培训期+保薪期 | C16: 新顾问低提点方案选择，前三月阶段下标期间，选择此标签，全标后，正常选择【保薪期】
B17: 保薪期 | C17: 新顾问低提点方案选择，结束保薪后正常选择【O1】

Sheet 签约明细
C1: 求和项:学费 | D1: 项目类别
C2: 签约单录入人 | D2: 个性化 | E2: 集训 | F2: 无忧 | G2: 在职 | H2: 四六级 | I2: 网课 | J2: 总计
C3: 李涛 | D3: 158460 | F3: 16150 | I3: 18900 | J3: 193510
C4: 谭悦 | D4: 431550 | E4: 4800 | F4: 149341.1 | G4: 65300 | H4: 95095 | I4: 56251 | J4: 802337.1
C5: 赵星火 | D5: 224130 | E5: 23500 | F5: 170550 | H5: 38400 | I5: 53154.4 | J5: 509734.4
C6: 总计 | D6: 814140 | E6: 28300 | F6: 336041.1 | G6: 65300 | H6: 133495 | I6: 128305.4 | J6: 1505581.5
A9: 序号 | B9: 学校 | C9: 部门 | D9: 资源姓名 | E9: 资源ID | F9: 资源录入人 | G9: 资源录入时间 | H9: 资源描述 | I9: 市场活动 | J9: 资源年级 | K9: 分配顾问/TMK | L9: 一级获取渠道 | M9: 二级获取渠道 | N9: 转介绍人 | O9: TMK激活人 | P9: TMK激活处理时间 | Q9: 工单姓名 | R9: 跟进顾问 | S9: 工单ID | T9: 工单类型 | U9: 工单录入时间 | V9: 工单等级 | W9: 咨询课程 | X9: 工单年级 | Y9: 学校 | Z9: 院系 | AA9: 专业 | AB9: 签约学生姓名 | AC9: 签约单ID | AD9: 签约单录入人 | AE9: 签约单录入时间 | AF9: 签约单更新人 | AG9: 签约单更新时间 | AH9: 项目类别 | AI9: 班号 | AJ9: 班级名称 | AK9: 面询表类型 | AL9: 订金 | AM9: 学费 | AN9: 续费类型 | AO9: 推荐人 | AP9: 类型 | AQ9: 是否交接 | AR9: 操作人编号 | AS9: 学员号 | AT9: 听课证号 | AU9: 报班日期 | AV9: 学员状态 | AW9: 回访记录 | AX9: 新老生类型 | AY9: 退费金额 | AZ9: 退费日期 | BA9: 课程类型 | BB9: 客户ID | BC9: 是否新东方在线签约 | BD9: 考季 | BE9: 报名产品 | BF9: 报名科目 | BG9: 意向报考专业 | BH9: 学校班型/类型 | BI9: 是否关联协议 | BJ9: 特殊备注 | BK9: 产品品类 | BL9: 业务类型 | BM9: 签约列表在线学员ID | BN9: 大学生源类型 | BO9: 资源来源
A10: 15 | B10: 北京大学部 | C10: 国内大学部 | E10: 127127668 | G10: 2025-09-11 16:33:44 | H10: 知春路直访，咨询考研 | J10: 大三 | K10: 谭悦 | L10: 直访 | M10: 直访 | Q10: 安思羽 | R10: 谭悦 | S10: 30745364 | T10: 续费工单 | U10: 2025-11-10 19:46 | V10: A（六个月内有报课意向工单） | W10: 考研专业课,考研无忧计划 | X10: 大三 | Y10: 北京科技大学 | Z10: 计算机与通信工程学院 | AA10: 计算机科学与技术 | AB10: 安思羽 | AC10: 5694808 | AD10: 谭悦 | AE10: 2025-11-10 19:46 | AF10: 谭悦 | AG10: 2025-11-10 19:46 | AH10: 无忧 | AI10: WYC27103 | AJ10: 考研专业课无忧Pro优才走读班（27考研/408计算机） | AK10: 国内考试 | AM10: 9000 | AN10: 同科续费 | AP10: 续班 | AQ10: 无须交接 | AR10: BJWY2101498uW2 | AS10: BJWY5747046882 | AT10: WYC271030004 | AU10: 2025-11-07 | AW10: 回访人：谭悦，回访时间：2025-11-10 19:46，回访内容：1；|回访人：谭悦，回访时间：2025-11-10 19:46，回访内容：1 | BB10: 84810126 | BC10: 否 | BD10: 27考季 | BE10: 无忧计划-啄木鸟,考研专业课150 | BF10: 英语,政治,数学,计算机 | BH10: 国内高校-211 | BI10: 否 | BL10: 转出 | BN10: 本地人本地大学(常规)
A11: 16 | B11: 北京大学部 | C11: 国内大学部 | E11: 115852926 | G11: 2025-06-23 16:42:01 | H11: 北京新东方考研18714556226 | J11: 幼儿 | K11: 杨晓超 | L11: 市场-代理商合作 | M11: 职递 | Q11: 毕琦昕 | R11: 杨晓超 | S11: 30715344 | T11: 续费工单 | U11: 2025-11-10 10:51 | V11: A（六个月内有报课意向工单） | W11: 考研专业课,考研无忧计划 | X11: 大三 | Y11: 北京邮电大学 | Z11: 国际学院 | AA11: 物联网工程 | AB11: 毕琦昕 | AC11: 5694390 | AD11: 谭悦 | AE11: 2025-11-10 10:51 | AF11: 杨晓超 | AG11: 2025-11-10 10:52 | AH11: 无忧 | AK11: 国内考试 | AM11: 4500 | AN11: 同科续费 | AP11: 分单 | AQ11: 无须交接 | AS11: BJWY1550131227 | AW11: 回访人：杨晓超，回访时间：2025-11-10 10:51，回访内容：1；|回访人：杨晓超，回访时间：2025-11-10 10:51，回访内容：签约 | BB11: 80376945 | BC11: 否 | BD11: 27考季 | BE11: 无忧计划-啄木鸟 | BF11: 英语,政治,数学,计算机 | BH11: 国内高校-211 | BI11: 否 | BN11: 外地人本地大学(常规)
A12: 85 | B12: 北京大学部 | C12: 国内大学部 | D12: 同学 | E12: 134565004 | F12: 陈伟钰 | G12: 2025-11-14 15:13:37 | H12: 钱雪冰的顾问转介绍-其他（不返现） | J12: 大三 | K12: 钱雪冰 | L12: 转介绍 | M12: 顾问转介绍-其他(不返现) | N12: 钱雪冰qianxuebing@xdf.cn | Q12: 蔡佳茵 | R12: 钱雪冰 | S12: 30761404 | T12: 正常工单 | U12: 2025-11-14 15:26 | V12: A（六个月内有报课意向工单） | W12: 考研专业课,考研VIP,考研无忧计划 | X12: 大三 | Y12: 燕京理工学院 | Z12: 文法学院 | AA12: 汉语言文学 | AB12: 蔡佳茵 | AC12: 5728268 | AD12: 谭悦 | AE12: 2025-11-15 15:18 | AF12: 钱雪冰 | AG12: 2025-11-15 15:19 | AH12: 无忧 | AK12: 国内考试 | AM12: 33650 | AO12: 钱雪冰 | AP12: 分单 | AQ12: 已交接 | AS12: BJWY1763277405 | AW12: 回访人：钱雪冰，回访时间：2025-11-14 15:26，回访内容：燕京理工学院 大三 汉语言文学专业，然后是想考郑州大学汉语言文学专业，比较在意是否有上岸的案例。比较在意上课的细节，明天过来校区听试听课程；|回访人：钱雪冰，回访时间：2025-11-15 15:18，回访内容：报名 | BB12: 87447997 | BC12: 否 | BD12: 27考季 | BE12: 无忧计划-候鸟,VIP - 伴学,考研专业课300 | BF12: 英语,政治 | BG12: 其他 | BH12: 国内高校-双非 | BI12: 否 | BN12: 本地人外地大学(归巢) | BO12: 客服
A13: 72 | B13: 北京大学部 | C13: 国内大学部 | D13: 曹泽恒 | E13: 134462228 | F13: 刘大庆 | G13: 2025-11-14 18:57:24 | H13: 续费原因：学员续费一对一，辛苦老师建单流转；该学生为保护期内续费，原顾问：国内大学部-赵星火(zhaoxinghuo@xdf.cn) | J13: 大学已毕业 | K13: 赵星火 | L13: 转介绍 | M13: 学管续费推荐 | N13: 刘大庆liudaqing1@xdf.cn | Q13: 曹泽恒 | R13: 赵星火 | S13: 30765656 | T13: 续费工单 | U13: 2025-11-15 15:30 | V13: A（六个月内有报课意向工单） | W13: 考研VIP | X13: 大学已毕业 | Y13: 北京工业大学 | Z13: 城市建设学部 | AA13: 土木工程 | AB13: 曹泽恒 | AC13: 5730320 | AD13: 赵星火 | AE13: 2025-11-18 19:32 | AF13: 赵星火 | AG13: 2025-11-18 20:40 | AH13: 集训 | AI13: LP17634655422194 | AJ13: 26考研一对一伴学（集训） | AK13: 国内考试 | AM13: 9600 | AO13: 刘大庆 | AP13: 续班 | AQ13: 已交接 | AS13: BJWY4116308585 | AU13: 2025-11-18 | AW13: 回访人：赵星火，回访时间：2025-11-15 15:30，回访内容：计划续费一对一这边看下课时跟进中；|回访人：赵星火，回访时间：2025-11-17 14:41，回访内容：跟进学生中继续维护学生考虑，看下课程考虑。；|回访人：赵星火，回访时间：2025-11-18 19:32，回访内容：系统自动签约 | BB13: 33140368 | BC13: 否 | BD13: 26考季 | BE13: VIP - 伴学 | BF13: 英语 | BG13: 其他 | BH13: 国内高校-211 | BI13: 是 | BO13: 学管续费推荐
A14: 10 | B14: 北京大学部 | C14: 国内大学部 | D14: 曾丹 | E14: 134232548 | F14: 李亚坤 | G14: 2025-11-12 17:32:45 | H14: 续费原因：家长择校完，说还是要考人大 300升级费需要交；该学生为保护期内续费，原顾问：国内大学部-谭悦(tanyue9@xdf.cn) | J14: 大三 | K14: 谭悦 | L14: 转介绍 | M14: 学管续费推荐 | N14: 李亚坤liyakun4@xdf.cn | Q14: 曾丹 | R14: 谭悦 | S14: 30729076 | T14: 续费工单 | U14: 2025-11-12 19:49 | V14: A（六个月内有报课意向工单） | W14: 考研专业课 | X14: 大三 | Y14: 中国农业大学 | Z14: 人文与发展学院 | AA14: 英语 | AB14: 曾丹 | AC14: 5696741 | AD14: 谭悦 | AE14: 2025-11-13 11:38 | AF14: 谭悦 | AG14: 2025-11-13 11:43 | AH14: 无忧 | AI14: LP1763005110401 | AJ14: 985院校升级费-无忧 | AK14: 国内考试 | AM14: 3000 | AO14: 李亚坤 | AP14: 续班 | AQ14: 未交接 | AS14: BJWY7684715389 | AU14: 2025-11-13 | AW14: 回访人：谭悦，回访时间：2025-11-12 19:49，回访内容：续费专业课 ；|回访人：谭悦，回访时间：2025-11-13 11:38，回访内容：系统自动签约 | BB14: 84876601 | BC14: 否 | BD14: 27考季 | BE14: 考研专业课300 | BF14: 专业课300 | BG14: 其他 | BH14: 国内高校-985 | BI14: 否 | BN14: 本地人本地大学(常规) | BO14: 学管续费推荐
A15: 40 | B15: 北京大学部 | C15: 国内大学部 | D15: 陈嘉硕 | E15: 133140096 | F15: 陈晶 | G15: 2025-11-03 15:46:32 | H15: 续费原因：报名专业课；该学生为保护期外续费，原顾问部门：国内大学部 | J15: 大学已毕业 | K15: 谭悦 | L15: 转介绍 | M15: 学管续费推荐 | N15: 陈晶chenjing171@xdf.cn | Q15: 陈嘉硕 | R15: 谭悦 | S15: 30652571 | T15: 续费工单 | U15: 2025-11-03 16:19 | V15: A（六个月内有报课意向工单） | W15: 考研专业课 | X15: 大学已毕业 | Y15: 西安邮电大学 | Z15: 计算机学院 | AA15: 计算机科学与技术 | AB15: 陈嘉硕 | AC15: 5691084 | AD15: 谭悦 | AE15: 2025-11-03 16:21 | AH15: 个性化 | AI15: LP1762158074916 | AJ15: 考研专业课一对一伴学班（12h/26考季） | AM15: 7200 | AO15: 陈晶 | AP15: 续班 | AQ15: 未交接 | AS15: BJWY7070266959 | AU15: 2025-11-03 | AW15: 回访人：谭悦，回访时间：2025-11-03 16:19，回访内容：报专业课 ；|回访人：谭悦，回访时间：2025-11-03 16:21，回访内容：系统自动签约 | BB15: 52706084 | BC15: 否 | BD15: 27考季 | BE15: 考研专业课150 | BF15: 专业课150 | BG15: 其他 | BH15: 国内高校-211 | BI15: 否 | BO15: 学管续费推荐
A16: 67 | B16: 北京大学部 | C16: 国内大学部 | D16: 陈嘉硕 | E16: 135330352 | F16: 陈晶 | G16: 2025-11-21 15:49:57 | H16: 续费原因：续课时，个性化；该学生为保护期内续费，原顾问：国内大学部-谭悦(tanyue9@xdf.cn) | J16: 大学已毕业 | K16: 谭悦 | L16: 转介绍 | M16: 学管续费推荐 | N16: 陈晶chenjing171@xdf.cn | Q16: 陈嘉硕 | R16: 谭悦 | S16: 30792786 | T16: 续费工单 | U16: 2025-11-21 15:58 | V16: A（六个月内有报课意向工单） | W16: 考研专业课 | X16: 大学已毕业 | Y16: 西安邮电大学 | Z16: 计算机学院 | AA16: 计算机科学与技术 | AB16: 陈嘉硕 | AC16: 5731913 | AD16: 谭悦 | AE16: 2025-11-21 16:45 | AF16: 谭悦 | AG16: 2025-11-21 16:48 | AH16: 个性化 | AI16: LP17637147081820 | AJ16: 考研初试专业课一对一（26考季/10小时） | AK16: 国内考试 | AM16: 6000 | AO16: 陈晶 | AP16: 续班 | AQ16: 已交接 | AS16: BJWY7070266959 | AU16: 2025-11-21 | AW16: 回访人：谭悦，回访时间：2025-11-21 15:58，回访内容：微信跟进中 ；|回访人：谭悦，回访时间：2025-11-21 16:45，回访内容：系统自动签约 | BB16: 52706084 | BC16: 否 | BD16: 26考季 | BE16: 考研专业课150 | BF16: 专业课150 | BG16: 其他 | BH16: 国内高校-211 | BI16: 是 | BO16: 学管续费推荐
A17: 121 | B17: 北京大学部 | C17: 国内大学部 | E17: 132605684 | G17: 2025-10-28 20:22:28 | H17: 【小红书资源】 咨询考研一对一，IP地址在北京 | J17: 大三 | K17: 李涛 | L17: 线上运营-小红书 | M17: 小红书 | Q17: 陈靓怡 | R17: 李涛 | S17: 30655508 | T17: 续费工单 | U17: 2025-11-03 11:47 | V17: A（六个月内有报课意向工单） | W17: 考研VIP | X17: 大三 | Y17: 北京信息科技大学 | Z17: 计算机学院 | AA17: 计算机科学与技术 | AB17: 陈靓怡 | AC17: 5691452 | AD17: 李涛 | AE17: 2025-11-04 15:50 | AF17: 李涛 | AG17: 2025-11-04 17:12 | AH17: 个性化 | AI17: 3201731 | AJ17: 考研督学计划 27考研英数督学计划 | AK17: 国内考试 | AM17: 80960 | AP17: 续班 | AQ17: 已交接 | AS17: BJWY7173848231 | AT17: 108320173100000001 | AU17: 2025-11-04 | AW17: 回访人：李涛，回访时间：2025-11-03 11:47，回访内容：重新下单；|回访人：李涛，回访时间：2025-11-03 18:46，回访内容：等退费 然后入班！；|回访人：李涛，回访时间：2025-11-04 15:50，回访内容：已报名 | BB17: 86751591 | BC17: 否 | BD17: 27考季 | BE17: VIP - 伴学 | BF17: 英语,政治,数学,计算机 | BH17: 国内高校-双非 | BI17: 是 | BN17: 本地人本地大学(常规)
A18: 36 | B18: 北京大学部 | C18: 国内大学部 | E18: 132519662 | G18: 2025-10-28 11:15:27 | H18: 续费原因：学生27考研，需要一对一，辛苦谭悦老师跟进；该学生为保护期内续费，原顾问：国内大学部-谭悦(tanyue9@xdf.cn) | J18: 大四 | K18: 谭悦 | L18: 转介绍 | M18: 学管续费推荐 | Q18: 陈一凡 | R18: 谭悦 | S18: 30690701 | T18: 续费工单 | U18: 2025-11-05 16:35 | V18: A（六个月内有报课意向工单） | W18: 考研VIP | X18: 大四 | Y18: 北方工业大学 | Z18: 信息学院 | AA18: 数据科学与大数据技术 | AB18: 陈一凡 | AC18: 5691927 | AD18: 谭悦 | AE18: 2025-11-05 16:35 | AF18: 系统管理员 | AG18: 2025-11-10 17:45 | AH18: 无忧 | AI18: LP1761622149221 | AJ18: 26考研一对一伴学（无忧） | AM18: -20400 | AQ18: 未交接 | AS18: BJWY8503976521 | AU18: 2025-11-05 | AW18: 回访人：系统管理员，回访时间：2025-11-05 16:35，回访内容：学生转产品转入，创建续费工单。 | BB18: 58815635 | BC18: 否 | BD18: 26考季 | BE18: VIP - 伴学 | BF18: 英语,政治 | BH18: 国内高校-211 | BI18: 否
A19: 37 | B19: 北京大学部 | C19: 国内大学部 | E19: 132519662 | G19: 2025-10-28 11:15:27 | H19: 续费原因：学生27考研，需要一对一，辛苦谭悦老师跟进；该学生为保护期内续费，原顾问：国内大学部-谭悦(tanyue9@xdf.cn) | J19: 大四 | K19: 谭悦 | L19: 转介绍 | M19: 学管续费推荐 | Q19: 陈一凡 | R19: 谭悦 | S19: 30690701 | T19: 续费工单 | U19: 2025-11-05 16:35 | V19: A（六个月内有报课意向工单） | W19: 考研VIP | X19: 大四 | Y19: 北方工业大学 | Z19: 信息学院 | AA19: 数据科学与大数据技术 | AB19: 陈一凡 | AC19: 5691927 | AD19: 谭悦 | AE19: 2025-11-05 16:35 | AF19: 系统管理员 | AG19: 2025-11-10 17:45 | AH19: 无忧 | AI19: LP17623311801419 | AJ19: 27考研一对一伴学(无忧) | AM19: 20400 | AQ19: 未交接 | AS19: BJWY8503976521 | AU19: 2025-11-05 | AW19: 回访人：系统管理员，回访时间：2025-11-05 16:35，回访内容：学生转产品转入，创建续费工单。 | BB19: 58815635 | BC19: 否 | BD19: 26考季 | BE19: VIP - 伴学 | BF19: 英语,政治 | BH19: 国内高校-211 | BI19: 否
A20: 38 | B20: 北京大学部 | C20: 国内大学部 | E20: 132519662 | G20: 2025-10-28 11:15:27 | H20: 续费原因：学生27考研，需要一对一，辛苦谭悦老师跟进；该学生为保护期内续费，原顾问：国内大学部-谭悦(tanyue9@xdf.cn) | J20: 大四 | K20: 谭悦 | L20: 转介绍 | M20: 学管续费推荐 | Q20: 陈一凡 | R20: 谭悦 | S20: 30690701 | T20: 续费工单 | U20: 2025-11-05 16:35 | V20: A（六个月内有报课意向工单） | W20: 考研VIP | X20: 大四 | Y20: 北方工业大学 | Z20: 信息学院 | AA20: 数据科学与大数据技术 | AB20: 陈一凡 | AC20: 5691927 | AD20: 谭悦 | AE20: 2025-11-05 16:35 | AF20: 系统管理员 | AG20: 2025-11-10 17:45 | AH20: 无忧 | AI20: LP17623311801419 | AJ20: 27考研一对一伴学(无忧) | AM20: 1200 | AQ20: 未交接 | AS20: BJWY8503976521 | AU20: 2025-11-10 | AW20: 回访人：系统管理员，回访时间：2025-11-05 16:35，回访内容：学生转产品转入，创建续费工单。 | BB20: 58815635 | BC20: 否 | BD20: 26考季 | BE20: VIP - 伴学 | BF20: 英语,政治 | BH20: 国内高校-211 | BI20: 否
A21: 39 | B21: 北京大学部 | C21: 国内大学部 | E21: 132519662 | G21: 2025-10-28 11:15:27 | H21: 续费原因：学生27考研，需要一对一，辛苦谭悦老师跟进；该学生为保护期内续费，原顾问：国内大学部-谭悦(tanyue9@xdf.cn) | J21: 大四 | K21: 谭悦 | L21: 转介绍 | M21: 学管续费推荐 | Q21: 陈一凡 | R21: 谭悦 | S21: 30690701 | T21: 续费工单 | U21: 2025-11-05 16:35 | V21: A（六个月内有报课意向工单） | W21: 考研VIP | X21: 大四 | Y21: 北方工业大学 | Z21: 信息学院 | AA21: 数据科学与大数据技术 | AB21: 陈一凡 | AC21: 5691927 | AD21: 谭悦 | AE21: 2025-11-05 16:35 | AF21: 系统管理员 | AG21: 2025-11-10 17:45 | AH21: 无忧 | AI21: LP1762767548850 | AJ21: 27考研一对一伴学(无忧) | AM21: 8500 | AQ21: 未交接 | AS21: BJWY8503976521 | AU21: 2025-11-10 | AW21: 回访人：系统管理员，回访时间：2025-11-05 16:35，回访内容：学生转产品转入，创建续费工单。 | BB21: 58815635 | BC21: 否 | BD21: 26考季 | BE21: VIP - 伴学 | BF21: 英语,政治 | BH21: 国内高校-211 | BI21: 否
A22: 109 | B22: 北京大学部 | C22: 国内大学部 | D22: 陈政元 | E22: 132406074 | F22: 北京国内管理员 | G22: 2025-10-26 21:48:56 | H22: 资源录入来源：小表单 市场活动id：412422 市场活动名称：新东方集团官微【新东方】资源 活动所属学校id：10000 活动所属学校名称：总公司 线索接收人邮箱：yangjun42@xdf.cn 线索接受人类型：自定义 表单信息：表单id81512、表单名(对内)：新东方集团官微【新东方】资源、表单名（对外）：新东方课程报名、创建人邮箱：wuyue38@xdf.cn、表单链接：pages/index/index.html?scene=81512,,ucwVUGil 备注：来源:小表单;姓名:陈政元;意向课程: 【课程】考研、四六级、专升本、成人英语/北京/北京; 新老生: 新生; 提交链接:pages/index/index.html?scene=81512,,ucwVUGil;地理位置:-;渠道:新媒体运营/集团品牌官微 | I22: 2026财年小表单-新东方集团官微【新东方】资源 | J22: 未知 | K22: 杨钰杰 | L22: 线上运营-私域中台 | M22: 集团官微 | O22: 杨钰杰 | P22: 2025-10-27 10:03:33 | Q22: 陈政元 | R22: 谭悦 | S22: 30560560 | T22: 正常工单 | U22: 2025-10-27 11:30 | V22: A（六个月内有报课意向工单） | W22: 考研专业课,考研VIP | X22: 大四 | Y22: 北京工商大学 | Z22: 人工智能学院 | AA22: 机械工程 | AB22: 陈政元 | AC22: 5694099 | AD22: 谭悦 | AE22: 2025-11-09 17:00 | AF22: 谭悦 | AG22: 2025-11-09 18:01 | AH22: 个性化 | AI22: 3234557 | AJ22: 北京中心菁英计划 27考研菁英A计划（英政数） | AK22: 国内考试 | AM22: 259000 | AP22: 新签 | AQ22: 已交接 | AS22: BJWY4807692593 | AT22: 108323455700000001 | AU22: 2025-11-09 | AW22: 回访人：谭悦，回访时间：2025-10-31 16:56，回访内容：学生要等家长回来，一起过来 ；|回访人：谭悦，回访时间：2025-11-05 12:03，回访内容：微信邀约来访面谈 ；|回访人：谭悦，回访时间：2025-11-09 17:00，回访内容：面谈接待，报名了菁英计划 | BB22: 86686253 | BC22: 否 | BD22: 27考季 | BE22: VIP - 畅学,考研专业课150 | BF22: 英语,政治,数学,专业课150 | BG22: 其他 | BH22: 国内高校-双非 | BI22: 是 | BN22: 本地人本地大学(常规) | BO22: 小表单
A23: 110 | B23: 北京大学部 | C23: 国内大学部 | D23: 陈政元 | E23: 132406074 | F23: 北京国内管理员 | G23: 2025-10-26 21:48:56 | H23: 资源录入来源：小表单 市场活动id：412422 市场活动名称：新东方集团官微【新东方】资源 活动所属学校id：10000 活动所属学校名称：总公司 线索接收人邮箱：yangjun42@xdf.cn 线索接受人类型：自定义 表单信息：表单id81512、表单名(对内)：新东方集团官微【新东方】资源、表单名（对外）：新东方课程报名、创建人邮箱：wuyue38@xdf.cn、表单链接：pages/index/index.html?scene=81512,,ucwVUGil 备注：来源:小表单;姓名:陈政元;意向课程: 【课程】考研、四六级、专升本、成人英语/北京/北京; 新老生: 新生; 提交链接:pages/index/index.html?scene=81512,,ucwVUGil;地理位置:-;渠道:新媒体运营/集团品牌官微 | I23: 2026财年小表单-新东方集团官微【新东方】资源 | J23: 未知 | K23: 杨钰杰 | L23: 线上运营-私域中台 | M23: 集团官微 | O23: 杨钰杰 | P23: 2025-10-27 10:03:33 | Q23: 陈政元 | R23: 谭悦 | S23: 30560560 | T23: 正常工单 | U23: 2025-10-27 11:30 | V23: A（六个月内有报课意向工单） | W23: 考研专业课,考研VIP | X23: 大四 | Y23: 北京工商大学 | Z23: 人工智能学院 | AA23: 机械工程 | AB23: 陈政元 | AC23: 5694099 | AD23: 谭悦 | AE23: 2025-11-09 17:00 | AF23: 谭悦 | AG23: 2025-11-09 18:01 | AH23: 个性化 | AI23: 3234573 | AJ23: 北京中心菁英计划 27考研菁英计划（英政数联报专业课30h | AK23: 国内考试 | AM23: 12000 | AP23: 新签 | AQ23: 已交接 | AS23: BJWY4807692593 | AT23: 108323457300000001 | AU23: 2025-11-09 | AW23: 回访人：谭悦，回访时间：2025-10-31 16:56，回访内容：学生要等家长回来，一起过来 ；|回访人：谭悦，回访时间：2025-11-05 12:03，回访内容：微信邀约来访面谈 ；|回访人：谭悦，回访时间：2025-11-09 17:00，回访内容：面谈接待，报名了菁英计划 | BB23: 86686253 | BC23: 否 | BD23: 27考季 | BE23: VIP - 畅学,考研专业课150 | BF23: 英语,政治,数学,专业课150 | BG23: 其他 | BH23: 国内高校-双非 | BI23: 是 | BN23: 本地人本地大学(常规) | BO23: 小表单
A24: 6 | B24: 北京大学部 | C24: 国内大学部 | D24: 崔好奇 | E24: 135201274 | F24: 北京国内管理员 | G24: 2025-11-20 20:13:46 | H24: 资源录入来源：小表单 城市：北京市 市场活动id：412422 市场活动名称：新东方集团官微【新东方】资源 活动所属学校id：10000 活动所属学校名称：总公司 线索接收人邮箱：yangjun42@xdf.cn 线索接受人类型：自定义 表单信息：表单id81512、表单名(对内)：新东方集团官微【新东方】资源、表单名（对外）：新东方课程报名、创建人邮箱：wuyue38@xdf.cn、表单链接：pages/index/index.html?scene=81512,,ucwVUGil 备注：来源:小表单;姓名:崔好奇;意向课程: 【课程】考研、四六级、专升本、成人英语/北京/北京; 新老生: 新生; 提交链接:pages/index/index.html?scene=81512,,ucwVUGil;地理位置:北京市丰台区东铁匠营街道西木樨园;渠道:新媒体运营/集团品牌官微 | I24: 2026财年小表单-新东方集团官微【新东方】资源 | J24: 未知 | K24: 杨钰杰 | L24: 线上运营-私域中台 | M24: 集团官微 | O24: 杨钰杰 | P24: 2025-11-20 20:24:25 | Q24: 崔好奇 | R24: 谭悦 | S24: 30848265 | T24: 正常工单 | U24: 2025-11-21 11:51 | V24: B（需长时间跟单或只需要规划） | W24: 线上考研产品 | X24: 在职 | Y24: 北京建筑大学 | Z24: 环境与能源工程学院 | AA24: 建筑环境与能源应用工程 | AB24: 崔好奇 | AC24: 5706702 | AD24: 谭悦 | AE24: 2025-11-22 17:57 | AF24: 谭悦 | AG24: 2025-11-22 17:57 | AH24: 网课 | AI24: 86231189510 | AJ24: 2028考研管综全科在校直通车（1期） | AK24: 国内考试 | AM24: 10144 | AP24: 新签 | AQ24: 无须交接 | AU24: 2025-11-22 | AW24: 回访人：谭悦，回访时间：2025-11-21 11:51，回访内容：25年毕业， 28考研， 跟进中 ，MEM 北建筑 ；|回访人：谭悦，回访时间：2025-11-22 17:57，回访内容：1 | BA24: 长期班 | BB24: 87668013 | BC24: 是 | BD24: 27考季 | BE24: 线上直通车 | BF24: 英语,管综 | BG24: 管综 | BH24: 国内高校-双非 | BI24: 否 | BM24: 107274163 | BO24: 小表单
A25: 105 | B25: 北京大学部 | C25: 国内大学部 | D25: 崔若琳 | E25: 134062030 | F25: 张泽7 | G25: 2025-11-10 18:24:44 | H25: 续费原因：每周三加一次写作；该学生为保护期内续费，原顾问：国内大学部-赵星火(zhaoxinghuo@xdf.cn) | J25: 大四 | K25: 赵星火 | L25: 转介绍 | M25: 学管续费推荐 | N25: 张泽7zhangze7@xdf.cn | Q25: 崔若琳 | R25: 赵星火 | S25: 30746685 | T25: 续费工单 | U25: 2025-11-11 11:41 | V25: A（六个月内有报课意向工单） | W25: 考研VIP | X25: 大四 | Y25: 北京农学院 | Z25: 生物与资源环境学院 | AA25: 生物工程 | AB25: 崔若琳 | AC25: 5695111 | AD25: 赵星火 | AE25: 2025-11-11 12:04 | AF25: 赵星火 | AG25: 2025-11-11 12:07 | AH25: 个性化 | AI25: LP1762833896560 | AJ25: 考研一对一伴学班（26考季） | AK25: 国内考试 | AM25: 7800 | AO25: 张泽7 | AP25: 续班 | AQ25: 已交接 | AS25: BJWY0122570561 | AU25: 2025-11-11 | AW25: 回访人：赵星火，回访时间：2025-11-11 11:41，回访内容：签约；|回访人：赵星火，回访时间：2025-11-11 12:04，回访内容：系统自动签约 | BB25: 19355703 | BC25: 否 | BD25: 26考季 | BE25: VIP - 伴学 | BF25: 英语 | BG25: 其他 | BH25: 国内高校-双非 | BI25: 是 | BN25: 本地人本地大学(常规) | BO25: 学管续费推荐
A26: 7 | B26: 北京大学部 | C26: 国内大学部 | D26: 同学 | E26: 135004856 | F26: 吕猛 | G26: 2025-11-18 21:22:49 | H26: 咨询一对一冲刺课程 | J26: 大四 | K26: 谭悦 | L26: 线上运营-本地生活平台 | M26: 大众点评 | Q26: 丹央 | R26: 谭悦 | S26: 30788504 | T26: 正常工单 | U26: 2025-11-19 11:50 | V26: A（六个月内有报课意向工单） | W26: 线上考研产品 | X26: 大四 | Y26: 国际关系学院 | Z26: 国际安全学院 | AA26: 国际政治 | AB26: 丹央 | AC26: 5575552 | AD26: 谭悦 | AE26: 2025-11-19 11:50 | AF26: 谭悦 | AG26: 2025-11-19 11:50 | AH26: 网课 | AI26: 02698866958 | AJ26: 2026考研专业课定制一对一（20h）-B班 | AK26: 国内考试 | AM26: 12240 | AP26: 新签 | AQ26: 无须交接 | AU26: 2025-11-19 | AW26: 回访人：谭悦，回访时间：2025-11-19 11:50，回访内容：国际关系学院，本科学的是公共管理。 | BA26: 长期班 | BB26: 87647271 | BC26: 是 | BD26: 26考季 | BE26: 专业课 | BF26: 专业课300 | BG26: 其他 | BH26: 国内高校-双非 | BI26: 否 | BM26: 109203918 | BN26: 本地人本地大学(常规) | BO26: 客服
A27: 73 | B27: 北京大学部 | C27: 国内大学部 | D27: 丁浩洋 | E27: 135003471 | F27: 李雪68 | G27: 2025-11-18 18:55:45 | H27: 罗玉骏+luoyujun@xdf.cn+罗玉骏(新东方教育科技集团有限公司-产业机构-国际教育培训事业部-国际教育北京中心-运营管理部-中学区域运营中心二区-国贸中学分中心 | 学业规划师) | J27: 未知 | K27: 赵星火 | L27: 转介绍 | M27: 内部员工推荐 | N27: 罗玉骏+luoyujun@xdf.cn+罗玉骏(新东方教育科技集团有限公司-产业机构-国际教育培训事业部-国际教育北京中心-运营管理部-中学区域运营中心二区-国贸中学分中心 | 学业规划师) | Q27: 丁浩洋 | R27: 赵星火 | S27: 30787958 | T27: 正常工单 | U27: 2025-11-18 18:59 | V27: A（六个月内有报课意向工单） | W27: 考研专业课 | X27: 大一 | Y27: 澳门科技大学 | Z27: 电子与信息技术 | AA27: 电子与信息技术 | AB27: 丁浩洋 | AC27: 5730315 | AD27: 赵星火 | AE27: 2025-11-18 19:11 | AF27: 赵星火 | AG27: 2025-11-18 19:29 | AH27: 个性化 | AI27: LP17634642652171 | AJ27: 考研初试专业课一对一（27考研/30小时） | AK27: 国内考试 | AM27: 18300 | AO27: 罗玉骏+luoyujun@xdf.cn+罗玉骏(新东方教育科技集团有限公司-产业机构-国际教育培训事业部-国际教育北京中心-运营管理部-中学区域运营中心二区-国贸中学分中心 | 学业规划师) | AP27: 新签 | AQ27: 已交接 | AS27: BJWY8381978400 | AU27: 2025-11-18 | AW27: 回访人：赵星火，回访时间：2025-11-18 18:59，回访内容：跟进中这边看下情况；|回访人：赵星火，回访时间：2025-11-18 19:11，回访内容：系统自动签约 | BB27: 87647140 | BC27: 否 | BD27: 27考季 | BE27: 考研专业课150 | BF27: 专业课150 | BG27: 其他 | BH27: 国内高校-双非 | BI27: 是 | BN27: 本地人外地大学(归巢) | BO27: 客服
A28: 28 | B28: 北京大学部 | C28: 国内大学部 | E28: 136043660 | G28: 2025-11-29 16:30:24 | H28: 续费原因：4h定制1v1，指定刘瑶；该学生为保护期内续费，原顾问：国内大学部-谭悦(tanyue9@xdf.cn) | J28: 大学已毕业 | K28: 谭悦 | L28: 转介绍 | M28: 学管续费推荐 | Q28: 冯晨阳 | R28: 谭悦 | S28: 30958049 | T28: 续费工单 | U28: 2025-12-01 20:15 | V28: A（六个月内有报课意向工单） | W28: 考研VIP | X28: 大学已毕业 | Y28: 首都医科大学 | Z28: 临床医学院 | AA28: 临床医学 | AB28: 冯晨阳 | AC28: 5713519 | AD28: 谭悦 | AE28: 2025-12-01 20:15 | AF28: 系统管理员 | AG28: 2025-12-01 20:15 | AH28: 个性化 | AI28: LP17644170743890 | AJ28: 考研一对一伴学班（定制/26考季） | AM28: -7200 | AQ28: 未交接 | AS28: BJWY9774040881 | AU28: 2025-12-01 | AW28: 回访人：系统管理员，回访时间：2025-12-01 20:15，回访内容：学生转产品转入，创建续费工单。 | BB28: 51853027 | BC28: 否 | BD28: 26考季 | BE28: VIP - 伴学 | BF28: 英语 | BH28: 国内高校-双非 | BI28: 否
A29: 29 | B29: 北京大学部 | C29: 国内大学部 | E29: 136043660 | G29: 2025-11-29 16:30:24 | H29: 续费原因：4h定制1v1，指定刘瑶；该学生为保护期内续费，原顾问：国内大学部-谭悦(tanyue9@xdf.cn) | J29: 大学已毕业 | K29: 谭悦 | L29: 转介绍 | M29: 学管续费推荐 | Q29: 冯晨阳 | R29: 谭悦 | S29: 30958049 | T29: 续费工单 | U29: 2025-12-01 20:15 | V29: A（六个月内有报课意向工单） | W29: 考研VIP | X29: 大学已毕业 | Y29: 首都医科大学 | Z29: 临床医学院 | AA29: 临床医学 | AB29: 冯晨阳 | AC29: 5713519 | AD29: 谭悦 | AE29: 2025-12-01 20:15 | AF29: 系统管理员 | AG29: 2025-12-01 20:15 | AH29: 无忧 | AI29: LP17645908628004 | AJ29: 26考研一对一伴学（定制/无忧） | AM29: 7200 | AQ29: 未交接 | AS29: BJWY9774040881 | AU29: 2025-12-01 | AW29: 回访人：系统管理员，回访时间：2025-12-01 20:15，回访内容：学生转产品转入，创建续费工单。 | BB29: 51853027 | BC29: 否 | BD29: 26考季 | BE29: VIP - 伴学 | BF29: 英语 | BH29: 国内高校-双非 | BI29: 否
A30: 46 | B30: 北京大学部 | C30: 国内大学部 | D30: 冯晨阳 | E30: 136043660 | F30: 许庆典 | G30: 2025-11-29 16:30:24 | H30: 续费原因：4h定制1v1，指定刘瑶；该学生为保护期内续费，原顾问：国内大学部-谭悦(tanyue9@xdf.cn) | J30: 大学已毕业 | K30: 谭悦 | L30: 转介绍 | M30: 学管续费推荐 | N30: 许庆典xuqingdian@xdf.cn | Q30: 冯晨阳 | R30: 谭悦 | S30: 30914217 | T30: 续费工单 | U30: 2025-11-29 19:45 | V30: A（六个月内有报课意向工单） | W30: 考研VIP | X30: 大学已毕业 | Y30: 首都医科大学 | Z30: 临床医学院 | AA30: 临床医学 | AB30: 冯晨阳 | AC30: 5737100 | AD30: 谭悦 | AE30: 2025-11-29 19:51 | AF30: 谭悦 | AG30: 2025-11-29 19:59 | AH30: 个性化 | AI30: LP17644170743890 | AJ30: 考研一对一伴学班（定制/26考季） | AK30: 国内考试 | AM30: 7200 | AO30: 许庆典 | AP30: 续班 | AQ30: 已交接 | AS30: BJWY9774040881 | AU30: 2025-11-29 | AW30: 回访人：谭悦，回访时间：2025-11-29 19:45，回访内容：1；|回访人：谭悦，回访时间：2025-11-29 19:51，回访内容：系统自动签约 | BB30: 51853027 | BC30: 否 | BD30: 26考季 | BE30: VIP - 伴学 | BF30: 英语 | BG30: 其他 | BH30: 国内高校-双非 | BI30: 是 | BO30: 学管续费推荐
A31: 60 | B31: 北京大学部 | C31: 国内大学部 | D31: 北京市5117 | E31: 135574278 | F31: 王静静 | G31: 2025-11-24 11:09:52 | H31: 考季：26 年级：在职 课程形式：考研VIP 学生情况：今年考研，咨询考研英语和政治的一对一【系统里有签约】；渠道录入来源：新东方官网M站-客服 意向城市：北京访客省/城市：北京市 访客静态ID：01000003465900269897988572415117 接待分组ID：70455 搜索引擎： 搜索词： 关键词： 设备类型：phone 访客IP：124.127.68.131 对话详细内容：AI-Lbo0rDBXCyBY 2025-11-09 22:36:20_x000D_ 您好同学,欢迎访问北京新东方考研四六级中心. 考研线下课程26/27考季【考研全年集训营】【考研半年集训营】【考研全科线下走读班】【考研寒/暑假集训营】【考研一对一】【考研专业课】【四/六级课程】，热门课程火热报名中,咨询即可领取专享优惠。 **【考研全年集训营】=ff761f# **【考研半年集训营】=ff6b6b# **【考研全科线下走读班】=ffc158# **【考研寒/暑假集训营】=ffc158# **【考研一对一】=ff761f# **【考研专业课】=ff6caa# **【四/六级课程】=ff6caa# **【考研冲刺班】=60e27e#_x000D_ _x000D_ AI-Lbo0rDBXCyBY 2025-11-09 22:36:23_x000D_ 您是想咨询【线下课程】【线上课程】【考研规划】还是【在职考研】呢？**【线下课程】# **【线上课程】#**【考研规划】#**【在职考研】#_x000D_ _x000D_ 01000003465900269897988572415117 2025-11-09 22:36:30_x000D_ 【线下课程】_x000D_ _x000D_ AI-Lbo0rDBXCyBY 2025-11-09 22:36:34_x000D_ 同学，你现在是在校还是在职呢？_x000D_ _x000D_ 01000003465900269897988572415117 2025-11-09 22:36:42_x000D_ 在校_x000D_ _x000D_ AI-Lbo0rDBXCyBY 2025-11-09 22:36:45_x000D_ 具体是想报考什么学校和专业呢？_x000D_ _x000D_ 01000003465900269897988572415117 2025-11-09 22:37:05_x000D_ 【考研一对一】_x000D_ _x000D_ AI-Lbo0rDBXCyBY 2025-11-09 22:37:09_x000D_ 好的，我这边安排专业老师给您回电，详细沟通一下，请问您的电话是多少呢？_x000D_ _x000D_ 01000003465900269897988572415117 2025-11-09 22:37:20_x000D_ 17338157357_x000D_ _x000D_ AI-Lbo0rDBXCyBY 2025-11-09 22:37:24_x000D_ 好的，确认一下你的号码是否正确呢~_x000D_ _x000D_ 01000003465900269897988572415117 2025-11-09 22:37:34_x000D_ 正确_x000D_ _x000D_ AI-Lbo0rDBXCyBY 2025-11-09 22:37:38_x000D_ 同学怎么称呼呢？_x000D_ _x000D_ 01000003465900269897988572415117 2025-11-09 22:37:45_x000D_ 冯_x000D_ _x000D_ AI-Lbo0rDBXCyBY 2025-11-09 22:37:49_x000D_ 好的，由于今天课程规划老师已经下班了，这边安排老师明天上午9点后给您回电请注意接听~_x000D_ _x000D_ 01000003465900269897988572415117 2025-11-09 22:38:23_x000D_ 上午十一点到十二点打吧_x000D_ _x000D_ AI-Lbo0rDBXCyBY 2025-11-09 22:38:26_x000D_ 好的，这个也是您的微信号吗？_x000D_ _x000D_ 01000003465900269897988572415117 2025-11-09 22:38:33_x000D_ 对_x000D_ _x000D_ AI-Lbo0rDBXCyBY 2025-11-09 22:38:36_x000D_ 稍后老师会联系哈_x000D_ _x000D_ 01000003465900269897988572415117 2025-11-09 22:38:48_x000D_ 直接加微信说吧_x000D_ _x000D_ AI-Lbo0rDBXCyBY 2025-11-09 22:38:52_x000D_ 可以的，你的微信是多少呢？_x000D_ _x000D_ 01000003465900269897988572415117 2025-11-09 22:39:05_x000D_ 就这个手机号_x000D_ _x000D_ AI-Lbo0rDBXCyBY 2025-11-09 22:39:08_x000D_ 好的，请问还有其他问题需要咨询吗？_x000D_ _x000D_ 01000003465900269897988572415117 2025-11-09 22:39:18_x000D_ 没_x000D_ _x000D_ AI-Lbo0rDBXCyBY 2025-11-09 22:39:21_x000D_ 联系方式已收到，第二天上午9点后与您联系的，感谢您的访问 祝您生活愉快！您可以关闭对话早点休息了。晚安~_x000D_ _x000D_ _x000D_ 来源页：https://group-live2.easyliao.com/live/chat.do?c=34659&g=70455&config=102466 备注： 外呼主题：2026财年第6财月易聊新东方官网M站 离职顾问：栗晓环(资源备注人:程远;资源备注时间:2025-11-10 10:00)（TMK主管分配TMK） | I31: 2026财年第6财月易聊新东方官网M站 | J31: 在职 | K31: 段同飞 | L31: 新东方官网 | M31: 新东方官网M站 | O31: 段同飞 | P31: 2025-11-24 12:15:58 | Q31: 冯晨阳 | R31: 谭悦 | S31: 30861560 | T31: 续费工单 | U31: 2025-11-24 14:15 | V31: A（六个月内有报课意向工单） | W31: 考研VIP | X31: 在职 | Y31: 首都医科大学 | Z31: 临床医学院 | AA31: 临床医学 | AB31: 冯晨阳 | AC31: 5576878 | AD31: 谭悦 | AE31: 2025-11-24 14:39 | AF31: 谭悦 | AG31: 2025-11-24 14:40 | AH31: 无忧 | AI31: LP1763966340551 | AJ31: 26考研一对一伴学（定制/无忧） | AK31: 国内考试 | AM31: 5200 | AP31: 续班 | AQ31: 已交接 | AS31: BJWY9774040881 | AU31: 2025-11-24 | AW31: 回访人：谭悦，回访时间：2025-11-24 14:15，回访内容：1；|回访人：谭悦，回访时间：2025-11-24 14:39，回访内容：系统自动签约 | BB31: 51853027 | BC31: 否 | BD31: 26考季 | BE31: VIP - 伴学 | BF31: 英语 | BG31: 其他 | BH31: 国内高校-双非 | BI31: 是
A32: 8 | B32: 北京大学部 | C32: 国内大学部 | D32: 沈 | E32: 134829313 | F32: 仇舰宁 | G32: 2025-11-17 15:20:49 | H32: 市场人员：刘子奇 备注：家长给孩子咨询26考研冲刺1对1辅导 | I32: 2026财年第6财月91校代系统资源活动 | K32: 李涛 | L32: 校代 | M32: 线上校代 | Q32: 冯靖桐 | R32: 李涛 | S32: 30833624 | T32: 正常工单 | U32: 2025-11-17 16:32 | V32: A（六个月内有报课意向工单） | W32: 考研VIP | X32: 大四 | Y32: 青岛农业大学 | Z32: 动漫与传媒学院 | AA32: 传播学（影视与网络） | AB32: 冯靖桐 | AC32: 5729816 | AD32: 李涛 | AE32: 2025-11-17 19:04 | AF32: 李涛 | AG32: 2025-11-17 19:05 | AH32: 网课 | AI32: 99860229334 | AJ32: 2026考研专业课定制一对一（20h）-A班 | AK32: 国内考试 | AM32: 9450 | AP32: 新签 | AQ32: 无须交接 | AU32: 2025-11-17 | AW32: 回访人：李涛，回访时间：2025-11-17 16:32，回访内容：想考山东师范大学 历史学！ 本科新闻传播学！ 现在主要是需要专业课的辅导！介绍一对一课程！；|回访人：李涛，回访时间：2025-11-17 19:04，回访内容：系统自动签约 | AY32: 9450.0 | AZ32: 2025-11-30 | BA32: 长期班 | BB32: 87568856 | BC32: 是 | BD32: 27考季 | BE32: VIP - 伴学 | BF32: 专业课150 | BG32: 其他 | BH32: 国内高校-双非 | BI32: 否 | BM32: 111185342 | BN32: 外地人外地大学(常规) | BO32: 新东方91校园大使
A33: 127 | B33: 北京大学部 | C33: 国内大学部 | D33: 成都市8577 | E33: 133164484 | F33: 张亚男 | G33: 2025-11-02 12:39:40 | H33: 渠道录入来源：北京中心-百度投放 意向城市：北京访客省/城市：成都市 访客静态ID：01000000034659205819616495768577 接待分组ID：82148 搜索引擎： 搜索词： 关键词： 设备类型：pc 访客IP：171.221.137.205 对话详细内容：AI-Lbo0rDBXCy 2025-11-02 12:36:38_x000D_ 您好同学,欢迎访问北京新东方考研四六级中心. 考研线下课程26/27考季【考研全年集训营】【考研半年集训营】【考研全科线下走读班】【考研寒/暑假集训营】【考研一对一】【考研专业课】【四/六级课程】，热门课程火热报名中,咨询即可领取专享优惠。 **【考研全年集训营】=ff761f# **【考研半年集训营】=ff6b6b# **【考研全科线下走读班】=ffc158# **【考研寒/暑假集训营】=ffc158# **【考研一对一】=ff761f# **【考研专业课】=ff6caa# **【四/六级课程】=ff6caa# **【考研冲刺班】=60e27e#_x000D_ _x000D_ AI-Lbo0rDBXCy 2025-11-02 12:36:41_x000D_ 您是想咨询【线下课程】【线上课程】【考研规划】还是【在职考研】呢？**【线下课程】# **【线上课程】#**【考研规划】#**【在职考研】#_x000D_ _x000D_ 01000000034659205819616495768577 2025-11-02 12:36:54_x000D_ 【考研一对一】_x000D_ _x000D_ AI-Lbo0rDBXCy 2025-11-02 12:36:57_x000D_ 同学，你现在是在校还是在职呢？_x000D_ _x000D_ 01000000034659205819616495768577 2025-11-02 12:37:04_x000D_ 在职_x000D_ _x000D_ AI-Lbo0rDBXCy 2025-11-02 12:37:07_x000D_ 具体是想报考什么学校和专业呢？_x000D_ _x000D_ 01000000034659205819616495768577 2025-11-02 12:37:19_x000D_ 清华大学 新闻与传播_x000D_ _x000D_ AI-Lbo0rDBXCy 2025-11-02 12:37:23_x000D_ 好的，我这边安排专业老师给您回电，详细沟通一下，请问您的电话是多少呢？_x000D_ _x000D_ 01000000034659205819616495768577 2025-11-02 12:37:39_x000D_ 13564410235_x000D_ _x000D_ AI-Lbo0rDBXCy 2025-11-02 12:37:43_x000D_ 好的，确认一下你的号码是否正确呢~_x000D_ _x000D_ 01000000034659205819616495768577 2025-11-02 12:37:53_x000D_ 确认_x000D_ _x000D_ AI-Lbo0rDBXCy 2025-11-02 12:37:56_x000D_ 同学怎么称呼呢？_x000D_ _x000D_ 01000000034659205819616495768577 2025-11-02 12:38:02_x000D_ 傅_x000D_ _x000D_ AI-Lbo0rDBXCy 2025-11-02 12:38:06_x000D_ 这边马上安排顾问老师联系您，预计半个小时左右给您回电请注意接听~_x000D_ _x000D_ 来源页：https://cn.bing.com/ 备注： | I33: 2026财年第6财月易聊百度投放 | K33: 谭悦 | L33: 线上运营-投放 | M33: 百度投放 | Q33: 傅寅杰 | R33: 谭悦 | S33: 30650543 | T33: 正常工单 | U33: 2025-11-03 10:25 | V33: A（六个月内有报课意向工单） | W33: 考研专业课 | X33: 在职 | Y33: 清华大学 | Z33: 新闻与传播学院 | AA33: 新闻学 | AB33: 傅寅杰 | AC33: 5690879 | AD33: 谭悦 | AE33: 2025-11-03 11:36 | AF33: 谭悦 | AG33: 2025-11-03 12:28 | AH33: 个性化 | AI33: LP1762140978258 | AJ33: 考研初试专业课一对一（27考研/50小时） | AK33: 国内考试 | AM33: 28800 | AP33: 新签 | AQ33: 已交接 | AS33: BJWY5387442298 | AU33: 2025-11-03 | AW33: 回访人：谭悦，回访时间：2025-11-03 10:25，回访内容：毕业几年了，24考研考的上海的新传，差20分， 今年考清华的学硕新传， 准备报专业课 ；|回访人：谭悦，回访时间：2025-11-03 11:36，回访内容：系统自动签约 | BB33: 86931058 | BC33: 否 | BD33: 27考季 | BE33: 考研专业课300 | BF33: 专业课300 | BG33: 其他 | BH33: 国内高校-C9 | BI33: 是 | BO33: 易聊在线咨询
A34: 128 | B34: 北京大学部 | C34: 国内大学部 | D34: 成都市8577 | E34: 133164484 | F34: 张亚男 | G34: 2025-11-02 12:39:40 | H34: 渠道录入来源：北京中心-百度投放 意向城市：北京访客省/城市：成都市 访客静态ID：01000000034659205819616495768577 接待分组ID：82148 搜索引擎： 搜索词： 关键词： 设备类型：pc 访客IP：171.221.137.205 对话详细内容：AI-Lbo0rDBXCy 2025-11-02 12:36:38_x000D_ 您好同学,欢迎访问北京新东方考研四六级中心. 考研线下课程26/27考季【考研全年集训营】【考研半年集训营】【考研全科线下走读班】【考研寒/暑假集训营】【考研一对一】【考研专业课】【四/六级课程】，热门课程火热报名中,咨询即可领取专享优惠。 **【考研全年集训营】=ff761f# **【考研半年集训营】=ff6b6b# **【考研全科线下走读班】=ffc158# **【考研寒/暑假集训营】=ffc158# **【考研一对一】=ff761f# **【考研专业课】=ff6caa# **【四/六级课程】=ff6caa# **【考研冲刺班】=60e27e#_x000D_ _x000D_ AI-Lbo0rDBXCy 2025-11-02 12:36:41_x000D_ 您是想咨询【线下课程】【线上课程】【考研规划】还是【在职考研】呢？**【线下课程】# **【线上课程】#**【考研规划】#**【在职考研】#_x000D_ _x000D_ 01000000034659205819616495768577 2025-11-02 12:36:54_x000D_ 【考研一对一】_x000D_ _x000D_ AI-Lbo0rDBXCy 2025-11-02 12:36:57_x000D_ 同学，你现在是在校还是在职呢？_x000D_ _x000D_ 01000000034659205819616495768577 2025-11-02 12:37:04_x000D_ 在职_x000D_ _x000D_ AI-Lbo0rDBXCy 2025-11-02 12:37:07_x000D_ 具体是想报考什么学校和专业呢？_x000D_ _x000D_ 01000000034659205819616495768577 2025-11-02 12:37:19_x000D_ 清华大学 新闻与传播_x000D_ _x000D_ AI-Lbo0rDBXCy 2025-11-02 12:37:23_x000D_ 好的，我这边安排专业老师给您回电，详细沟通一下，请问您的电话是多少呢？_x000D_ _x000D_ 01000000034659205819616495768577 2025-11-02 12:37:39_x000D_ 13564410235_x000D_ _x000D_ AI-Lbo0rDBXCy 2025-11-02 12:37:43_x000D_ 好的，确认一下你的号码是否正确呢~_x000D_ _x000D_ 01000000034659205819616495768577 2025-11-02 12:37:53_x000D_ 确认_x000D_ _x000D_ AI-Lbo0rDBXCy 2025-11-02 12:37:56_x000D_ 同学怎么称呼呢？_x000D_ _x000D_ 01000000034659205819616495768577 2025-11-02 12:38:02_x000D_ 傅_x000D_ _x000D_ AI-Lbo0rDBXCy 2025-11-02 12:38:06_x000D_ 这边马上安排顾问老师联系您，预计半个小时左右给您回电请注意接听~_x000D_ _x000D_ 来源页：https://cn.bing.com/ 备注： | I34: 2026财年第6财月易聊百度投放 | K34: 谭悦 | L34: 线上运营-投放 | M34: 百度投放 | Q34: 傅寅杰 | R34: 谭悦 | S34: 30650543 | T34: 正常工单 | U34: 2025-11-03 10:25 | V34: A（六个月内有报课意向工单） | W34: 考研专业课 | X34: 在职 | Y34: 清华大学 | Z34: 新闻与传播学院 | AA34: 新闻学 | AB34: 傅寅杰 | AC34: 5690879 | AD34: 谭悦 | AE34: 2025-11-03 11:36 | AF34: 谭悦 | AG34: 2025-11-03 12:28 | AH34: 个性化 | AI34: LP1762140978259 | AJ34: 清北院校升级费 | AK34: 国内考试 | AM34: 5000 | AP34: 新签 | AQ34: 已交接 | AS34: BJWY5387442298 | AU34: 2025-11-03 | AW34: 回访人：谭悦，回访时间：2025-11-03 10:25，回访内容：毕业几年了，24考研考的上海的新传，差20分， 今年考清华的学硕新传， 准备报专业课 ；|回访人：谭悦，回访时间：2025-11-03 11:36，回访内容：系统自动签约 | BB34: 86931058 | BC34: 否 | BD34: 27考季 | BE34: 考研专业课300 | BF34: 专业课300 | BG34: 其他 | BH34: 国内高校-C9 | BI34: 是 | BO34: 易聊在线咨询
A35: 84 | B35: 北京大学部 | C35: 国内大学部 | D35: 郭宸宇 | E35: 134712043 | F35: 徐岩 | G35: 2025-11-15 21:13:52 | H35: 续费原因：续费10小时数学课 辛苦流转谭悦；该学生为保护期内续费，原顾问：国内大学部-谭悦(tanyue9@xdf.cn) | J35: 大二 | K35: 谭悦 | L35: 转介绍 | M35: 学管续费推荐 | N35: 徐岩xuyan91@xdf.cn | Q35: 郭宸宇 | R35: 谭悦 | S35: 30767603 | T35: 续费工单 | U35: 2025-11-16 09:26 | V35: A（六个月内有报课意向工单） | W35: 六级 | X35: 大二 | Y35: 对外经济贸易大学 | Z35: 金融学院 | AA35: 金融学 | AB35: 郭宸宇 | AC35: 5574845 | AD35: 谭悦 | AE35: 2025-11-16 09:30 | AF35: 谭悦 | AG35: 2025-11-16 09:38 | AH35: 四六级 | AI35: LP17632566543722 | AJ35: 大学数学一对一伴学班（定制） | AK35: 国内考试 | AM35: 12000 | AO35: 徐岩 | AP35: 续班 | AQ35: 已交接 | AS35: BJWY5305138836 | AU35: 2025-11-16 | AW35: 回访人：谭悦，回访时间：2025-11-16 09:26，回访内容：报名数学一对一 ；|回访人：谭悦，回访时间：2025-11-16 09:30，回访内容：系统自动签约 | BB35: 59798822 | BC35: 否 | BD35: 25下考季 | BE35: 六级一对一 | BH35: 国内高校-211 | BI35: 是 | BN35: 本地人本地大学(常规) | BO35: 学管续费推荐
A36: 11 | B36: 北京大学部 | C36: 国内大学部 | D36: 107044026 | E36: 133903723 | F36: 张亚男 | G36: 2025-11-09 10:13:22 | H36: 渠道录入来源：抖音新东方考研直播间 koouserID：107044026 城市：北京 产品分组：考研 线索来源：直播间小风车收资-大学生-线下面授 市场人员： 是否兼职： 备注信息：请选择当前所属阶段：:大三;请选择倾向的备考方式：:线下面授;请选择备考城市：:北京 | I36: 2026财年第6财月抖音新东方考研直播间 | K36: 乔文娇 | L36: 线上运营-抖音 | M36: 抖音新东方考研直播间 | O36: 乔文娇 | P36: 2025-11-09 12:29:40 | Q36: 何年 | R36: 谭悦 | S36: 30708914 | T36: 正常工单 | U36: 2025-11-09 17:34 | V36: A（六个月内有报课意向工单） | W36: 线上考研产品 | X36: 大三 | Y36: 大连海事大学 | Z36: 法学院 | AA36: 法学（海商法） | AB36: 何年 | AC36: 5695630 | AD36: 谭悦 | AE36: 2025-11-11 21:14 | AF36: 谭悦 | AG36: 2025-11-11 22:53 | AH36: 网课 | AI36: 46455177697 | AJ36: 2027考研英语一无忧计划·7期,2027考研直通车VIP【法律硕士（法学）】,2027考研政治无忧计划·6期 | AK36: 国内考试 | AM36: 19685.6 | AP36: 新签 | AQ36: 无须交接 | AU36: 2025-11-11 | AW36: 回访人：谭悦，回访时间：2025-11-09 17:34，回访内容：法硕 面谈了， 大连海事想考北大法硕法学， 家长一起来的 ；|回访人：谭悦，回访时间：2025-11-11 18:45，回访内容：学生不回复消息，不怎么说话 ；|回访人：谭悦，回访时间：2025-11-11 21:14，回访内容：系统自动签约 | BA36: 长期班,长期班,长期班 | BB36: 87225932 | BC36: 是 | BD36: 27考季 | BE36: 线上直通车 | BF36: 政治,英语 | BG36: 其他 | BH36: 国内高校-211 | BI36: 否 | BM36: 107044026 | BN36: 外地人外地大学(常规) | BO36: 抖音新东方考研直播间
A37: 82 | B37: 北京大学部 | C37: 国内大学部 | E37: 134447281 | G37: 2025-11-14 09:47:52 | H37: 课程形式：考博英语一对一 学生情况：学生咨询考博英语，非医学专业，告知目前只有一对一辅导，也说了价格，可以了解一下，方便电话 | J37: 研究生以上 | K37: 赵星火 | L37: 电话 | M37: 大客服呼入 | Q37: 何晓涛 | R37: 赵星火 | S37: 30806542 | T37: 续费工单 | U37: 2025-11-17 10:13 | V37: A（六个月内有报课意向工单） | W37: 考博 | X37: 研究生以上 | Y37: 中国人民大学 | Z37: 信息学院 | AA37: 计算机科学与技术 | AB37: 何晓涛 | AC37: 5703459 | AD37: 赵星火 | AE37: 2025-11-17 10:20 | AF37: 赵星火 | AG37: 2025-11-17 10:27 | AH37: 个性化 | AI37: LP176334603072 | AJ37: 考博一对一伴学班 | AK37: 国内考试 | AM37: 18000 | AP37: 续班 | AQ37: 已交接 | AS37: BJWY4055776168 | AU37: 2025-11-17 | AW37: 回访人：赵星火，回访时间：2025-11-17 10:13，回访内容：1；|回访人：赵星火，回访时间：2025-11-17 10:20，回访内容：系统自动签约 | BB37: 87403705 | BC37: 否 | BH37: 国内高校-985 | BI37: 是
A38: 86 | B38: 北京大学部 | C38: 国内大学部 | D38: 考博 | E38: 134504635 | F38: 杨欢欢 | G38: 2025-11-14 09:19:17 | J38: 研究生以上 | K38: 杨欢欢 | L38: 电话 | M38: 大客服呼入 | O38: 杨欢欢 | P38: 2025-11-14 09:47:52 | Q38: 何晓涛 | R38: 赵星火 | S38: 30780026 | T38: 正常工单 | U38: 2025-11-14 10:24 | V38: A（六个月内有报课意向工单） | W38: 考博 | X38: 研究生以上 | Y38: 中国人民大学 | Z38: 信息学院 | AA38: 计算机科学与技术 | AB38: 何晓涛 | AC38: 5727982 | AD38: 赵星火 | AE38: 2025-11-15 10:38 | AF38: 赵星火 | AG38: 2025-11-15 10:47 | AH38: 个性化 | AI38: LP1763174337311 | AJ38: 考博一对一伴学班 | AK38: 国内考试 | AM38: 1800 | AP38: 新签 | AQ38: 已交接 | AS38: BJWY4055776168 | AU38: 2025-11-15 | AW38: 回访人：赵星火，回访时间：2025-11-14 10:24，回访内容：需要了解人大信息学院的考博的 内容近期想要上课，这边跟进中。；|回访人：赵星火，回访时间：2025-11-15 10:38，回访内容：系统自动签约 | BB38: 87403705 | BC38: 否 | BH38: 国内高校-985 | BI38: 是 | BO38: 客服
A39: 125 | B39: 北京大学部 | C39: 国内大学部 | D39: 贺其永歌 | E39: 133318501 | F39: 舒志豪 | G39: 2025-11-04 12:02:17 | H39: 续费原因：学员有续费英语六级需求；该学生为保护期内续费，原顾问：国内大学部-谭悦(tanyue9@xdf.cn) | J39: 大三 | K39: 谭悦 | L39: 转介绍 | M39: 学管续费推荐 | N39: 舒志豪shuzhihao1@xdf.cn | Q39: 贺其永歌 | R39: 谭悦 | S39: 30684897 | T39: 续费工单 | U39: 2025-11-04 12:13 | V39: A（六个月内有报课意向工单） | W39: 六级 | X39: 大三 | Y39: 首都师范大学 | Z39: 文学院 | AA39: 汉语言文学 | AB39: 贺其永歌 | AC39: 5571639 | AD39: 谭悦 | AE39: 2025-11-04 12:18 | AF39: 谭悦 | AG39: 2025-11-04 15:07 | AH39: 四六级 | AI39: LP1762229887473 | AJ39: 六级一对一伴学班 | AK39: 国内考试 | AM39: 9800 | AO39: 舒志豪 | AP39: 续班 | AQ39: 已交接 | AS39: BJWY9822893615 | AU39: 2025-11-04 | AW39: 回访人：谭悦，回访时间：2025-11-04 12:13，回访内容：六级一对一 ；|回访人：谭悦，回访时间：2025-11-04 12:18，回访内容：系统自动签约 | BB39: 53001132 | BC39: 否 | BD39: 25下考季 | BE39: 六级一对一 | BH39: 国内高校-双一流(非985/211) | BI39: 是 | BN39: 本地人本地大学(常规) | BO39: 学管续费推荐
A40: 2 | B40: 北京大学部 | C40: 国内大学部 | D40: 贺暄恒 | E40: 136464256 | F40: 郭又华 | G40: 2025-12-02 15:34:55 | H40: 续费原因：专业课还想再上2次；该学生为保护期内续费，原顾问：国内大学部-谭悦(tanyue9@xdf.cn) | J40: 大四 | K40: 谭悦 | L40: 转介绍 | M40: 学管续费推荐 | N40: 郭又华guoyouhua@xdf.cn | Q40: 贺暄恒 | R40: 谭悦 | S40: 30984866 | T40: 续费工单 | U40: 2025-12-02 17:28 | V40: A（六个月内有报课意向工单） | W40: 考研专业课 | X40: 大四 | Y40: 北京建筑大学 | Z40: 建筑与城市规划学院 | AA40: 建筑学 | AB40: 贺暄恒 | AC40: 5713857 | AD40: 谭悦 | AE40: 2025-12-02 17:37 | AF40: 谭悦 | AG40: 2025-12-02 17:44 | AH40: 无忧 | AI40: LP17646682272950 | AJ40: 考研初试专业课一对一（26考研/无忧） | AK40: 国内考试 | AM40: 2800 | AO40: 郭又华 | AP40: 续班 | AQ40: 已交接 | AS40: BJWY9142571360 | AU40: 2025-12-02 | AW40: 回访人：谭悦，回访时间：2025-12-02 17:28，回访内容：1；|回访人：谭悦，回访时间：2025-12-02 17:37，回访内容：系统自动签约 | BB40: 66477823 | BC40: 否 | BD40: 26考季 | BE40: 考研专业课150 | BF40: 专业课150 | BG40: 其他 | BH40: 国内高校-双非 | BI40: 是 | BN40: 本地人本地大学(常规) | BO40: 学管续费推荐
A41: 27 | B41: 北京大学部 | C41: 国内大学部 | D41: 贺暄恒 | E41: 132960286 | F41: 郭又华 | G41: 2025-11-01 11:27:06 | H41: 续费原因：学生专业课想再讲讲题，加4小时；该学生为保护期内续费，原顾问：国内大学部-谭悦(tanyue9@xdf.cn) | J41: 大四 | K41: 谭悦 | L41: 转介绍 | M41: 学管续费推荐 | N41: 郭又华guoyouhua@xdf.cn | Q41: 贺暄恒 | R41: 谭悦 | S41: 30576201 | T41: 续费工单 | U41: 2025-11-01 11:37 | V41: A（六个月内有报课意向工单） | W41: 考研专业课 | X41: 大四 | Y41: 北京建筑大学 | Z41: 建筑与城市规划学院 | AA41: 建筑学 | AB41: 贺暄恒 | AC41: 5570914 | AD41: 谭悦 | AE41: 2025-11-01 12:29 | AF41: 谭悦 | AG41: 2025-11-01 14:40 | AH41: 无忧 | AI41: LP17619713684250 | AJ41: 考研初试专业课一对一（26考研/无忧） | AK41: 国内考试 | AM41: 2800 | AO41: 郭又华 | AP41: 续班 | AQ41: 已交接 | AS41: BJWY9142571360 | AU41: 2025-11-01 | AW41: 回访人：谭悦，回访时间：2025-11-01 11:37，回访内容：续费；|回访人：谭悦，回访时间：2025-11-01 11:51，回访内容：专业课续费跟进；|回访人：谭悦，回访时间：2025-11-01 12:29，回访内容：系统自动签约 | BB41: 66477823 | BC41: 否 | BD41: 26考季 | BE41: 考研专业课150 | BF41: 专业课150 | BG41: 其他 | BH41: 国内高校-双非 | BI41: 是 | BN41: 本地人本地大学(常规) | BO41: 学管续费推荐
A42: 75 | B42: 北京大学部 | C42: 国内大学部 | D42: 贺暄恒 | E42: 134915707 | F42: 郭又华 | G42: 2025-11-18 11:25:29 | H42: 续费原因：学生专业课还想再加8小时讲讲真题；该学生为保护期内续费，原顾问：国内大学部-谭悦(tanyue9@xdf.cn) | J42: 大四 | K42: 谭悦 | L42: 转介绍 | M42: 学管续费推荐 | N42: 郭又华guoyouhua@xdf.cn | Q42: 贺暄恒 | R42: 谭悦 | S42: 30810914 | T42: 续费工单 | U42: 2025-11-18 11:45 | V42: A（六个月内有报课意向工单） | W42: 考研专业课 | X42: 大四 | Y42: 北京建筑大学 | Z42: 建筑与城市规划学院 | AA42: 建筑学 | AB42: 贺暄恒 | AC42: 5730051 | AD42: 谭悦 | AE42: 2025-11-18 11:52 | AF42: 谭悦 | AG42: 2025-11-18 11:55 | AH42: 无忧 | AI42: LP1763437959325 | AJ42: 考研初试专业课一对一（26考研/无忧） | AK42: 国内考试 | AM42: 5600 | AO42: 郭又华 | AP42: 续班 | AQ42: 已交接 | AS42: BJWY9142571360 | AU42: 2025-11-18 | AW42: 回访人：谭悦，回访时间：2025-11-18 11:45，回访内容：加8小时专业课 ；|回访人：谭悦，回访时间：2025-11-18 11:52，回访内容：系统自动签约 | BB42: 66477823 | BC42: 否 | BD42: 26考季 | BE42: 考研专业课150 | BF42: 专业课150 | BG42: 其他 | BH42: 国内高校-双非 | BI42: 否 | BN42: 本地人本地大学(常规) | BO42: 学管续费推荐
A43: 107 | B43: 北京大学部 | C43: 国内大学部 | D43: 霍盈杉 | E43: 133914690 | F43: 焦子瑞 | G43: 2025-11-09 14:33:00 | H43: 续费原因：学生想学集训营政治一对一的课程，推荐王晶老师，辛苦老师联系学生；该学生为保护期内续费，原顾问：国内大学部-赵星火(zhaoxinghuo@xdf.cn) | J43: 大四 | K43: 赵星火 | L43: 转介绍 | M43: 学管续费推荐 | N43: 焦子瑞jiaozirui@xdf.cn | Q43: 霍盈杉 | R43: 赵星火 | S43: 30714830 | T43: 续费工单 | U43: 2025-11-10 10:00 | V43: A（六个月内有报课意向工单） | W43: 考研VIP | X43: 大四 | Y43: 保定理工学院 | Z43: 资源与工程技术学院 | AA43: 土地资源管理 | AB43: 霍盈杉 | AC43: 5698305 | AD43: 赵星火 | AE43: 2025-11-10 10:23 | AF43: 赵星火 | AG43: 2025-11-10 11:38 | AH43: 集训 | AI43: LP176274139982 | AJ43: 26考研一对一伴学（集训） | AK43: 国内考试 | AM43: 13900 | AO43: 焦子瑞 | AP43: 续班 | AQ43: 已交接 | AS43: BJWY9038592627 | AU43: 2025-11-10 | AW43: 回访人：赵星火，回访时间：2025-11-10 10:00，回访内容：1；|回访人：赵星火，回访时间：2025-11-10 10:23，回访内容：系统自动签约 | BB43: 38346789 | BC43: 否 | BD43: 26考季 | BE43: VIP - 伴学 | BF43: 政治 | BG43: 其他 | BH43: 国内高校-双非 | BI43: 是 | BN43: 本地人本地大学(常规) | BO43: 学管续费推荐
A44: 56 | B44: 北京大学部 | C44: 国内大学部 | E44: 125552175 | G44: 2025-08-30 11:37:20 | H44: 续费原因：学生续费数学班课；该学生为保护期内续费，原顾问：国内大学部-谭悦(tanyue9@xdf.cn) | J44: 大四 | K44: 谭悦 | L44: 转介绍 | M44: 学管续费推荐 | Q44: 贾佳霖 | R44: 谭悦 | S44: 30862226 | T44: 续费工单 | U44: 2025-11-24 15:52 | V44: A（六个月内有报课意向工单） | W44: 考研无忧计划 | X44: 大四 | Y44: 北京化工大学 | Z44: 化学工程学院 | AA44: 环境工程 | AB44: 贾佳霖 | AC44: 5707837 | AD44: 谭悦 | AE44: 2025-11-24 16:04 | AF44: 谭悦 | AG44: 2025-11-24 16:16 | AH44: 无忧 | AI44: LP1763971496728 | AJ44: 26考研一对一伴学（老带新1H/无忧） | AK44: 国内考试 | AM44: 0 | AP44: 续班 | AQ44: 已交接 | AS44: BJWY0479852281 | AU44: 2025-11-24 | AW44: 回访人：谭悦，回访时间：2025-11-24 15:52，回访内容：1；|回访人：谭悦，回访时间：2025-11-24 16:04，回访内容：系统自动签约 | BB44: 79753776 | BC44: 否 | BD44: 26考季 | BE44: 无忧计划-啄木鸟 | BF44: 英语 | BH44: 国内高校-211 | BI44: 否 | BN44: 本地人本地大学(常规)
A45: 126 | B45: 北京大学部 | C45: 国内大学部 | D45: 同学 | E45: 133253349 | F45: 陈伟钰 | G45: 2025-11-03 13:27:26 | H45: 老生/转介绍人姓名 任玉婷/陈晶 资源描述/特殊备注 辛苦顾问加微信，已经和学员沟通好，先报10小时非定制学习写作 | J45: 大三 | K45: 谭悦 | L45: 转介绍 | M45: 学管转介绍 | N45: 陈晶chenjing171@xdf.cn | Q45: 姜昕彤 | R45: 谭悦 | S45: 30580122 | T45: 正常工单 | U45: 2025-11-03 14:46 | V45: A（六个月内有报课意向工单） | W45: 考研VIP | X45: 大三 | Y45: 北京工商大学 | Z45: 法学院 | AA45: 法学 | AB45: 姜昕彤 | AC45: 5691053 | AD45: 谭悦 | AE45: 2025-11-03 15:33 | AF45: 谭悦 | AG45: 2025-11-03 15:37 | AH45: 个性化 | AI45: LP1762155188808 | AJ45: 考研一对一伴学班（26考季） | AK45: 国内考试 | AM45: 8800 | AO45: 陈晶 | AP45: 新签 | AQ45: 已交接 | AS45: BJWY3434115421 | AU45: 2025-11-03 | AW45: 回访人：谭悦，回访时间：2025-11-03 14:46，回访内容：跟进考研一对一辅导，加微信；|回访人：谭悦，回访时间：2025-11-03 15:33，回访内容：系统自动签约 | BB45: 86978349 | BC45: 否 | BD45: 26考季 | BE45: VIP - 伴学 | BF45: 英语 | BG45: 其他 | BH45: 国内高校-双非 | BI45: 是 | BN45: 本地人本地大学(常规) | BO45: 客服
A46: 49 | B46: 北京大学部 | C46: 国内大学部 | D46: 蒋洲 | E46: 135849991 | F46: 陈晶 | G46: 2025-11-27 10:29:42 | H46: 续费原因：2小时，个性化；该学生为保护期内续费，原顾问：国内大学部-赵星火(zhaoxinghuo@xdf.cn) | J46: 大学已毕业 | K46: 赵星火 | L46: 转介绍 | M46: 学管续费推荐 | N46: 陈晶chenjing171@xdf.cn | Q46: 蒋洲 | R46: 赵星火 | S46: 30902510 | T46: 续费工单 | U46: 2025-11-27 10:33 | V46: A（六个月内有报课意向工单） | W46: 考研VIP | X46: 大学已毕业 | Y46: 首都师范大学 | Z46: 物理系 | AA46: 物理学 | AB46: 蒋洲 | AC46: 5735360 | AD46: 赵星火 | AE46: 2025-11-27 11:12 | AF46: 赵星火 | AG46: 2025-11-27 11:12 | AH46: 个性化 | AI46: LP1764213123276 | AJ46: 考研一对一伴学班（26考季） | AK46: 国内考试 | AM46: 1600 | AO46: 陈晶 | AP46: 续班 | AQ46: 已交接 | AS46: BJWY8202292766 | AU46: 2025-11-27 | AW46: 回访人：赵星火，回访时间：2025-11-27 10:33，回访内容：预计两小时；|回访人：赵星火，回访时间：2025-11-27 11:12，回访内容：系统自动签约 | BB46: 46865814 | BC46: 否 | BD46: 26考季 | BE46: VIP - 伴学 | BF46: 英语 | BG46: 其他 | BH46: 国内高校-双一流(非985/211) | BI46: 是 | BO46: 学管续费推荐
A47: 45 | B47: 北京大学部 | C47: 国内大学部 | D47: 雷才利 | E47: 136076596 | F47: 陈晶 | G47: 2025-11-30 15:26:26 | H47: 续费原因：需要续费2小时，选好教师后报课，个性化；该学生为保护期内续费，原顾问：国内大学部-谭悦(tanyue9@xdf.cn) | J47: 大学已毕业 | K47: 谭悦 | L47: 转介绍 | M47: 学管续费推荐 | N47: 陈晶chenjing171@xdf.cn | Q47: 雷才利 | R47: 谭悦 | S47: 30953965 | T47: 续费工单 | U47: 2025-11-30 19:01 | V47: A（六个月内有报课意向工单） | W47: 考研VIP | X47: 大学已毕业 | Y47: 华中农业大学 | Z47: 园艺林学学院 | AA47: 风景园林 | AB47: 雷才利 | AC47: 5712679 | AD47: 谭悦 | AE47: 2025-11-30 19:18 | AF47: 谭悦 | AG47: 2025-11-30 23:31 | AH47: 个性化 | AI47: LP17645014924982 | AJ47: 考研一对一伴学班（26考季） | AK47: 国内考试 | AM47: 1800 | AO47: 陈晶 | AP47: 续班 | AQ47: 已交接 | AS47: BJWY7202042206 | AU47: 2025-11-30 | AW47: 回访人：谭悦，回访时间：2025-11-30 19:01，回访内容：1；|回访人：谭悦，回访时间：2025-11-30 19:18，回访内容：系统自动签约 | BB47: 46040906 | BC47: 否 | BD47: 26考季 | BE47: VIP - 伴学 | BF47: 英语 | BG47: 其他 | BH47: 国内高校-211 | BI47: 是 | BO47: 学管续费推荐
A48: 47 | B48: 北京大学部 | C48: 国内大学部 | D48: 北京先不加哦 | E48: 133676602 | F48: 北京客服部 | G48: 2025-11-07 13:09:25 | H48: 北京 | I48: 2026财年第6财月代理商 | K48: 王静静 | L48: 线上运营-商务合作 | M48: 众学帮 | O48: 王静静 | P48: 2025-11-07 15:05:06 | Q48: 李丹尼 | R48: 赵星火 | S48: 30699753 | T48: 正常工单 | U48: 2025-11-07 15:52 | V48: A（六个月内有报课意向工单） | W48: 考研VIP | X48: 大三 | Y48: 北京石油化工学院 | Z48: 经济管理学院 | AA48: 电子商务 | AB48: 李丹尼 | AC48: 5710639 | AD48: 赵星火 | AE48: 2025-11-29 10:48 | AF48: 赵星火 | AG48: 2025-11-29 14:17 | AH48: 网课 | AI48: 21041968775 | AJ48: 2027考研管综无忧计划·1期 | AK48: 国内考试 | AM48: 17820 | AP48: 新签 | AQ48: 已交接 | AS48: BJWY9367616072 | AU48: 2025-11-29 | AW48: 回访人：赵星火，回访时间：2025-11-20 17:31，回访内容：回访学生情况这边跟进中继续维护学生 表示孩子哭了晚点再说；|回访人：赵星火，回访时间：2025-11-22 21:17，回访内容：临时有事明天回访；|回访人：赵星火，回访时间：2025-11-24 17:26，回访内容：回访学生之前表示孩子压力大 还没确定下来专业跟进中；|回访人：赵星火，回访时间：2025-11-28 17:57，回访内容：明天计划来校区这边沟通学习情况跟进中；|回访人：赵星火，回访时间：2025-11-29 10:48，回访内容：签约 | BA48: 长期班 | BB48: 87171481 | BC48: 是 | BD48: 27考季 | BE48: VIP - 伴学 | BF48: 英语 | BG48: 其他 | BH48: 国内高校-双非 | BI48: 是 | BM48: 111246636 | BN48: 本地人本地大学(常规) | BO48: 线下代理商
A49: 48 | B49: 北京大学部 | C49: 国内大学部 | D49: 北京先不加哦 | E49: 133676602 | F49: 北京客服部 | G49: 2025-11-07 13:09:25 | H49: 北京 | I49: 2026财年第6财月代理商 | K49: 王静静 | L49: 线上运营-商务合作 | M49: 众学帮 | O49: 王静静 | P49: 2025-11-07 15:05:06 | Q49: 李丹尼 | R49: 赵星火 | S49: 30699753 | T49: 正常工单 | U49: 2025-11-07 15:52 | V49: A（六个月内有报课意向工单） | W49: 考研VIP | X49: 大三 | Y49: 北京石油化工学院 | Z49: 经济管理学院 | AA49: 电子商务 | AB49: 李丹尼 | AC49: 5710639 | AD49: 赵星火 | AE49: 2025-11-29 10:48 | AF49: 赵星火 | AG49: 2025-11-29 14:17 | AH49: 个性化 | AI49: 3201727 | AJ49: 考研督学计划 27考研英语督学计划 | AK49: 国内考试 | AM49: 35980 | AP49: 新签 | AQ49: 已交接 | AS49: BJWY9367616072 | AT49: 108320172700000002 | AU49: 2025-11-29 | AW49: 回访人：赵星火，回访时间：2025-11-20 17:31，回访内容：回访学生情况这边跟进中继续维护学生 表示孩子哭了晚点再说；|回访人：赵星火，回访时间：2025-11-22 21:17，回访内容：临时有事明天回访；|回访人：赵星火，回访时间：2025-11-24 17:26，回访内容：回访学生之前表示孩子压力大 还没确定下来专业跟进中；|回访人：赵星火，回访时间：2025-11-28 17:57，回访内容：明天计划来校区这边沟通学习情况跟进中；|回访人：赵星火，回访时间：2025-11-29 10:48，回访内容：签约 | BB49: 87171481 | BC49: 否 | BD49: 27考季 | BE49: VIP - 伴学 | BF49: 英语 | BG49: 其他 | BH49: 国内高校-双非 | BI49: 是 | BM49: 111246636 | BN49: 本地人本地大学(常规) | BO49: 线下代理商
A50: 17 | B50: 北京大学部 | C50: 国内大学部 | E50: 94741951 | G50: 2025-02-16 17:07:41 | H50: 内部员工推荐给赵星火老师 | J50: 大二 | K50: 赵星火 | L50: 转介绍 | M50: 内部员工推荐 | Q50: 李昊鹏 | R50: 赵星火 | S50: 30710438 | T50: 续费工单 | U50: 2025-11-10 10:48 | V50: A（六个月内有报课意向工单） | W50: 考研专业课,考研无忧计划 | X50: 大三 | Y50: 中国劳动关系学院 | Z50: 应用技术学院 | AA50: 计算机科学与技术 | AB50: 李昊鹏 | AC50: 5694385 | AD50: 赵星火 | AE50: 2025-11-10 10:49 | AF50: 赵星火 | AG50: 2025-11-10 10:49 | AH50: 无忧 | AI50: WYC27002 | AJ50: 考研专业课无忧计划（27考研/408计算机） | AK50: 国内考试 | AM50: 10000 | AN50: 同科续费 | AO50: 刘红雎+liuhongju@xdf.cn+ID+产业机构-前途出国 | AP50: 续班 | AQ50: 已交接 | AR50: BJWY24032w1g8X | AS50: BJWY3908538703 | AT50: WYC270020001 | AU50: 2025-11-07 | AW50: 回访人：赵星火，回访时间：2025-11-10 10:48，回访内容：1；|回访人：赵星火，回访时间：2025-11-10 10:49，回访内容：1 | BB50: 66907521 | BC50: 否 | BD50: 27考季 | BE50: 无忧计划-啄木鸟,考研专业课150 | BF50: 英语,政治,数学,计算机 | BH50: 国内高校-双非 | BI50: 否 | BL50: 转出 | BN50: 本地人本地大学(常规)
A51: 18 | B51: 北京大学部 | C51: 国内大学部 | E51: 127312848 | G51: 2025-09-13 09:51:15 | H51: 内推给赵星火老师 | J51: 大三 | K51: 赵星火 | L51: 转介绍 | M51: 内部员工推荐 | Q51: 李嘉璐 | R51: 赵星火 | S51: 30710431 | T51: 续费工单 | U51: 2025-11-10 10:47 | V51: A（六个月内有报课意向工单） | W51: 考研专业课,考研集训营 | X51: 大三 | Y51: 北京工商大学嘉华学院 | Z51: 会计学院 | AA51: 会计 | AB51: 李嘉璐 | AC51: 5694383 | AD51: 赵星火 | AE51: 2025-11-10 10:48 | AF51: 赵星火 | AG51: 2025-11-10 10:48 | AH51: 无忧 | AI51: WYC27103 | AJ51: 考研专业课无忧Pro优才走读班（27考研/408计算机） | AK51: 国内考试 | AM51: 9000 | AN51: 同科续费 | AO51: 袁琳+yuanlin9@xdf.cn+袁琳9(新东方教育科技集团有限公司-培训学校-北京学校-高中一对一部-西北区-远大路分中心 | 分中心高级主管) | AP51: 续班 | AQ51: 无须交接 | AR51: BJWY2201F8pC6h | AS51: BJWY9464850685 | AT51: WYC271030005 | AU51: 2025-11-07 | AW51: 回访人：赵星火，回访时间：2025-11-10 10:47，回访内容：1；|回访人：赵星火，回访时间：2025-11-10 10:48，回访内容：1 | BB51: 43463837 | BC51: 否 | BD51: 27考季 | BE51: 寒暑假集训营（春秋OMO）,考研专业课300 | BF51: 英语,政治,专业课300 | BH51: 国内高校-211 | BI51: 否 | BL51: 转出 | BN51: 本地人本地大学(常规)
A52: 62 | B52: 北京大学部 | C52: 国内大学部 | D52: nu | E52: 135461015 | F52: 张冰 | G52: 2025-11-22 18:02:27 | H52: 咨询一对一，今年考研，着急联系 | J52: 大四 | K52: 李涛 | L52: 线上运营-投放 | M52: 总部-巨量广告 | Q52: 李孝妍 | R52: 李涛 | S52: 30831477 | T52: 正常工单 | U52: 2025-11-22 18:55 | V52: A（六个月内有报课意向工单） | W52: 考研VIP | X52: 大四 | Y52: 中央财经大学 | Z52: 经济学院 | AA52: 经济学 | AB52: 李孝妍 | AC52: 5706883 | AD52: 李涛 | AE52: 2025-11-23 09:08 | AF52: 系统管理员 | AG52: 2025-11-27 17:15 | AH52: 个性化 | AI52: LP17638601264498 | AJ52: 考研一对一伴学班（26考季） | AK52: 国内考试 | AM52: 18000 | AP52: 新签 | AQ52: 已交接 | AS52: BJWY7583492040 | AU52: 2025-11-23 | AW52: 回访人：李涛，回访时间：2025-11-22 18:55，回访内容：学生是央财沙河校区的，今年考，想要冲刺一下京东数学，基础不是很好，推荐1对1课程，介绍上课模式，推荐老师，加微信沟通中。；|回访人：李涛，回访时间：2025-11-23 09:08，回访内容：系统自动签约 | BB52: 87859245 | BC52: 否 | BD52: 26考季 | BE52: VIP - 伴学 | BF52: 数学,经综 | BG52: 其他 | BH52: 国内高校-211 | BI52: 是 | BN52: 本地人本地大学(常规) | BO52: 市场
A53: 63 | B53: 北京大学部 | C53: 国内大学部 | D53: nu | E53: 135461015 | F53: 张冰 | G53: 2025-11-22 18:02:27 | H53: 咨询一对一，今年考研，着急联系 | J53: 大四 | K53: 李涛 | L53: 线上运营-投放 | M53: 总部-巨量广告 | Q53: 李孝妍 | R53: 李涛 | S53: 30831477 | T53: 正常工单 | U53: 2025-11-22 18:55 | V53: A（六个月内有报课意向工单） | W53: 考研VIP | X53: 大四 | Y53: 中央财经大学 | Z53: 经济学院 | AA53: 经济学 | AB53: 李孝妍 | AC53: 5706883 | AD53: 李涛 | AE53: 2025-11-23 09:08 | AF53: 系统管理员 | AG53: 2025-11-27 17:15 | AH53: 个性化 | AI53: LP17638601264498 | AJ53: 考研一对一伴学班（26考季） | AK53: 国内考试 | AM53: -16200 | AP53: 新签 | AQ53: 已交接 | AS53: BJWY7583492040 | AU53: 2025-11-27 | AW53: 回访人：李涛，回访时间：2025-11-22 18:55，回访内容：学生是央财沙河校区的，今年考，想要冲刺一下京东数学，基础不是很好，推荐1对1课程，介绍上课模式，推荐老师，加微信沟通中。；|回访人：李涛，回访时间：2025-11-23 09:08，回访内容：系统自动签约 | BB53: 87859245 | BC53: 否 | BD53: 26考季 | BE53: VIP - 伴学 | BF53: 数学,经综 | BG53: 其他 | BH53: 国内高校-211 | BI53: 是 | BN53: 本地人本地大学(常规) | BO53: 市场
A54: 64 | B54: 北京大学部 | C54: 国内大学部 | D54: nu | E54: 135461015 | F54: 张冰 | G54: 2025-11-22 18:02:27 | H54: 咨询一对一，今年考研，着急联系 | J54: 大四 | K54: 李涛 | L54: 线上运营-投放 | M54: 总部-巨量广告 | Q54: 李孝妍 | R54: 李涛 | S54: 30831477 | T54: 正常工单 | U54: 2025-11-22 18:55 | V54: A（六个月内有报课意向工单） | W54: 考研VIP | X54: 大四 | Y54: 中央财经大学 | Z54: 经济学院 | AA54: 经济学 | AB54: 李孝妍 | AC54: 5706883 | AD54: 李涛 | AE54: 2025-11-23 09:08 | AF54: 系统管理员 | AG54: 2025-11-27 17:15 | AH54: 个性化 | AI54: LP17642348921845 | AJ54: 考研一对一伴学班（定制/26考季） | AK54: 国内考试 | AM54: 28800 | AP54: 新签 | AQ54: 已交接 | AS54: BJWY7583492040 | AU54: 2025-11-27 | AW54: 回访人：李涛，回访时间：2025-11-22 18:55，回访内容：学生是央财沙河校区的，今年考，想要冲刺一下京东数学，基础不是很好，推荐1对1课程，介绍上课模式，推荐老师，加微信沟通中。；|回访人：李涛，回访时间：2025-11-23 09:08，回访内容：系统自动签约 | BB54: 87859245 | BC54: 否 | BD54: 26考季 | BE54: VIP - 伴学 | BF54: 数学,经综 | BG54: 其他 | BH54: 国内高校-211 | BI54: 是 | BN54: 本地人本地大学(常规) | BO54: 市场
A55: 43 | B55: 北京大学部 | C55: 国内大学部 | D55: 李子扬 | E55: 136365156 | F55: 徐岩 | G55: 2025-12-01 17:37:19 | H55: 续费原因：续费8小时六级 辛苦流转星火；该学生为保护期内续费，原顾问：国内大学部-赵星火(zhaoxinghuo@xdf.cn) | J55: 大二 | K55: 赵星火 | L55: 转介绍 | M55: 学管续费推荐 | N55: 徐岩xuyan91@xdf.cn | Q55: 李子扬 | R55: 赵星火 | S55: 30921328 | T55: 续费工单 | U55: 2025-12-01 17:42 | V55: A（六个月内有报课意向工单） | W55: 六级 | X55: 大二 | Y55: 北京工业大学都柏林学院 | Z55: 金融学院 | AA55: 金融学 | AB55: 李子扬 | AC55: 5713478 | AD55: 赵星火 | AE55: 2025-12-01 18:27 | AF55: 赵星火 | AG55: 2025-12-01 18:54 | AH55: 四六级 | AI55: LP17645848687373 | AJ55: 六级一对一伴学班 | AK55: 国内考试 | AM55: 3900 | AO55: 徐岩 | AP55: 续班 | AQ55: 已交接 | AS55: BJWY5491797172 | AU55: 2025-12-01 | AW55: 回访人：赵星火，回访时间：2025-12-01 17:42，回访内容：计划续费4次课；|回访人：赵星火，回访时间：2025-12-01 18:27，回访内容：系统自动签约 | BB55: 64143332 | BC55: 否 | BD55: 25下考季 | BE55: 六级一对一 | BH55: 国内高校-双非 | BI55: 是 | BN55: 本地人本地大学(常规) | BO55: 学管续费推荐
A56: 95 | B56: 北京大学部 | C56: 国内大学部 | D56: 刘皓惟 | E56: 133486098 | F56: 徐岩 | G56: 2025-11-06 10:35:44 | H56: 续费原因：目前大三想准备考研 咨询一对一 ；该学生为保护期内续费，原顾问：国内大学部-刘文君(liuwenjun6@xdf.cn) | J56: 大三 | K56: 赵星火 | L56: 转介绍 | M56: 学管续费推荐 | N56: 徐岩xuyan91@xdf.cn | Q56: 刘皓惟 | R56: 赵星火 | S56: 30693071 | T56: 续费工单 | U56: 2025-11-06 10:56 | V56: A（六个月内有报课意向工单） | W56: 考研专业课,考研无忧计划 | X56: 大三 | Y56: 北京信息科技大学 | Z56: 信息管理学院 | AA56: 大数据管理与应用 | AB56: 刘皓惟 | AC56: 5695887 | AD56: 赵星火 | AE56: 2025-11-12 11:07 | AF56: 赵星火 | AG56: 2025-11-12 11:07 | AH56: 无忧 | AI56: WYM27021 | AJ56: 考研数学无忧计划（27考研/冲刺） | AK56: 国内考试 | AM56: 5745.8 | AO56: 徐岩 | AP56: 续班 | AQ56: 已交接 | AR56: WebReg | AS56: BJWY9243582547 | AT56: WYM270210029 | AU56: 2025-11-12 | AW56: 回访人：赵星火，回访时间：2025-11-06 10:56，回访内容：本科学校和专业 北信科 大数据专业 目标院校和专业 没有完全确定院校目标，不想要学习计算机相关的，之前给孩子看的是这种 地理信息系统遥感科学与技术 武汉大学的 就业 基本学情 四六级大学数学 四级 考过了 六级12月 数学现在还可以，十次课还剩余新东方课时 学习时间分配 学习习惯 介绍一对一邀约校区沟通；|回访人：赵星火，回访时间：2025-11-07 16:08，回访内容：跟进学生邀约面谈跟进中这边继续维护中。；|回访人：赵星火，回访时间：2025-11-09 22:03，回访内容：临时有事请假明天回访；|回访人：赵星火，回访时间：2025-11-10 17:02，回访内容：沟通专业院校中，这边想要华电的管理类的这边跟进中，继续维护；|回访人：赵星火，回访时间：2025-11-12 11:07，回访内容：跟进中 | BB56: 43538682 | BC56: 否 | BD56: 27考季 | BE56: 考研专业课150,无忧计划-早鸟 | BF56: 英语,政治,数学,专业课150 | BG56: 其他 | BH56: 国内高校-双非 | BI56: 是 | BL56: 报名 | BN56: 本地人本地大学(常规) | BO56: 学管续费推荐
A57: 96 | B57: 北京大学部 | C57: 国内大学部 | D57: 刘皓惟 | E57: 133486098 | F57: 徐岩 | G57: 2025-11-06 10:35:44 | H57: 续费原因：目前大三想准备考研 咨询一对一 ；该学生为保护期内续费，原顾问：国内大学部-刘文君(liuwenjun6@xdf.cn) | J57: 大三 | K57: 赵星火 | L57: 转介绍 | M57: 学管续费推荐 | N57: 徐岩xuyan91@xdf.cn | Q57: 刘皓惟 | R57: 赵星火 | S57: 30693071 | T57: 续费工单 | U57: 2025-11-06 10:56 | V57: A（六个月内有报课意向工单） | W57: 考研专业课,考研无忧计划 | X57: 大三 | Y57: 北京信息科技大学 | Z57: 信息管理学院 | AA57: 大数据管理与应用 | AB57: 刘皓惟 | AC57: 5695887 | AD57: 赵星火 | AE57: 2025-11-12 11:07 | AF57: 赵星火 | AG57: 2025-11-12 11:07 | AH57: 无忧 | AI57: WYE27201 | AJ57: 考研英语无忧计划（27考研/基础） | AK57: 国内考试 | AM57: 5107.7 | AO57: 徐岩 | AP57: 续班 | AQ57: 已交接 | AR57: WebReg | AS57: BJWY9243582547 | AT57: WYE272010013 | AU57: 2025-11-12 | AW57: 回访人：赵星火，回访时间：2025-11-06 10:56，回访内容：本科学校和专业 北信科 大数据专业 目标院校和专业 没有完全确定院校目标，不想要学习计算机相关的，之前给孩子看的是这种 地理信息系统遥感科学与技术 武汉大学的 就业 基本学情 四六级大学数学 四级 考过了 六级12月 数学现在还可以，十次课还剩余新东方课时 学习时间分配 学习习惯 介绍一对一邀约校区沟通；|回访人：赵星火，回访时间：2025-11-07 16:08，回访内容：跟进学生邀约面谈跟进中这边继续维护中。；|回访人：赵星火，回访时间：2025-11-09 22:03，回访内容：临时有事请假明天回访；|回访人：赵星火，回访时间：2025-11-10 17:02，回访内容：沟通专业院校中，这边想要华电的管理类的这边跟进中，继续维护；|回访人：赵星火，回访时间：2025-11-12 11:07，回访内容：跟进中 | BB57: 43538682 | BC57: 否 | BD57: 27考季 | BE57: 考研专业课150,无忧计划-早鸟 | BF57: 英语,政治,数学,专业课150 | BG57: 其他 | BH57: 国内高校-双非 | BI57: 是 | BL57: 报名 | BN57: 本地人本地大学(常规) | BO57: 学管续费推荐
A58: 97 | B58: 北京大学部 | C58: 国内大学部 | D58: 刘皓惟 | E58: 133486098 | F58: 徐岩 | G58: 2025-11-06 10:35:44 | H58: 续费原因：目前大三想准备考研 咨询一对一 ；该学生为保护期内续费，原顾问：国内大学部-刘文君(liuwenjun6@xdf.cn) | J58: 大三 | K58: 赵星火 | L58: 转介绍 | M58: 学管续费推荐 | N58: 徐岩xuyan91@xdf.cn | Q58: 刘皓惟 | R58: 赵星火 | S58: 30693071 | T58: 续费工单 | U58: 2025-11-06 10:56 | V58: A（六个月内有报课意向工单） | W58: 考研专业课,考研无忧计划 | X58: 大三 | Y58: 北京信息科技大学 | Z58: 信息管理学院 | AA58: 大数据管理与应用 | AB58: 刘皓惟 | AC58: 5695887 | AD58: 赵星火 | AE58: 2025-11-12 11:07 | AF58: 赵星火 | AG58: 2025-11-12 11:07 | AH58: 无忧 | AI58: WYP27201 | AJ58: 考研政治无忧计划（27考研/基础） | AK58: 国内考试 | AM58: 6624.1 | AO58: 徐岩 | AP58: 续班 | AQ58: 已交接 | AR58: WebReg | AS58: BJWY9243582547 | AT58: WYP272010010 | AU58: 2025-11-12 | AW58: 回访人：赵星火，回访时间：2025-11-06 10:56，回访内容：本科学校和专业 北信科 大数据专业 目标院校和专业 没有完全确定院校目标，不想要学习计算机相关的，之前给孩子看的是这种 地理信息系统遥感科学与技术 武汉大学的 就业 基本学情 四六级大学数学 四级 考过了 六级12月 数学现在还可以，十次课还剩余新东方课时 学习时间分配 学习习惯 介绍一对一邀约校区沟通；|回访人：赵星火，回访时间：2025-11-07 16:08，回访内容：跟进学生邀约面谈跟进中这边继续维护中。；|回访人：赵星火，回访时间：2025-11-09 22:03，回访内容：临时有事请假明天回访；|回访人：赵星火，回访时间：2025-11-10 17:02，回访内容：沟通专业院校中，这边想要华电的管理类的这边跟进中，继续维护；|回访人：赵星火，回访时间：2025-11-12 11:07，回访内容：跟进中 | BB58: 43538682 | BC58: 否 | BD58: 27考季 | BE58: 考研专业课150,无忧计划-早鸟 | BF58: 英语,政治,数学,专业课150 | BG58: 其他 | BH58: 国内高校-双非 | BI58: 是 | BL58: 报名 | BN58: 本地人本地大学(常规) | BO58: 学管续费推荐
A59: 98 | B59: 北京大学部 | C59: 国内大学部 | D59: 刘皓惟 | E59: 133486098 | F59: 徐岩 | G59: 2025-11-06 10:35:44 | H59: 续费原因：目前大三想准备考研 咨询一对一 ；该学生为保护期内续费，原顾问：国内大学部-刘文君(liuwenjun6@xdf.cn) | J59: 大三 | K59: 赵星火 | L59: 转介绍 | M59: 学管续费推荐 | N59: 徐岩xuyan91@xdf.cn | Q59: 刘皓惟 | R59: 赵星火 | S59: 30693071 | T59: 续费工单 | U59: 2025-11-06 10:56 | V59: A（六个月内有报课意向工单） | W59: 考研专业课,考研无忧计划 | X59: 大三 | Y59: 北京信息科技大学 | Z59: 信息管理学院 | AA59: 大数据管理与应用 | AB59: 刘皓惟 | AC59: 5695887 | AD59: 赵星火 | AE59: 2025-11-12 11:07 | AF59: 赵星火 | AG59: 2025-11-12 11:07 | AH59: 无忧 | AI59: WYE27020 | AJ59: 考研英语无忧计划（27考研/英一强化） | AK59: 国内考试 | AM59: 6703.9 | AO59: 徐岩 | AP59: 续班 | AQ59: 已交接 | AR59: WebReg | AS59: BJWY9243582547 | AT59: WYE270200030 | AU59: 2025-11-12 | AW59: 回访人：赵星火，回访时间：2025-11-06 10:56，回访内容：本科学校和专业 北信科 大数据专业 目标院校和专业 没有完全确定院校目标，不想要学习计算机相关的，之前给孩子看的是这种 地理信息系统遥感科学与技术 武汉大学的 就业 基本学情 四六级大学数学 四级 考过了 六级12月 数学现在还可以，十次课还剩余新东方课时 学习时间分配 学习习惯 介绍一对一邀约校区沟通；|回访人：赵星火，回访时间：2025-11-07 16:08，回访内容：跟进学生邀约面谈跟进中这边继续维护中。；|回访人：赵星火，回访时间：2025-11-09 22:03，回访内容：临时有事请假明天回访；|回访人：赵星火，回访时间：2025-11-10 17:02，回访内容：沟通专业院校中，这边想要华电的管理类的这边跟进中，继续维护；|回访人：赵星火，回访时间：2025-11-12 11:07，回访内容：跟进中 | BB59: 43538682 | BC59: 否 | BD59: 27考季 | BE59: 考研专业课150,无忧计划-早鸟 | BF59: 英语,政治,数学,专业课150 | BG59: 其他 | BH59: 国内高校-双非 | BI59: 是 | BL59: 报名 | BN59: 本地人本地大学(常规) | BO59: 学管续费推荐
A60: 99 | B60: 北京大学部 | C60: 国内大学部 | D60: 刘皓惟 | E60: 133486098 | F60: 徐岩 | G60: 2025-11-06 10:35:44 | H60: 续费原因：目前大三想准备考研 咨询一对一 ；该学生为保护期内续费，原顾问：国内大学部-刘文君(liuwenjun6@xdf.cn) | J60: 大三 | K60: 赵星火 | L60: 转介绍 | M60: 学管续费推荐 | N60: 徐岩xuyan91@xdf.cn | Q60: 刘皓惟 | R60: 赵星火 | S60: 30693071 | T60: 续费工单 | U60: 2025-11-06 10:56 | V60: A（六个月内有报课意向工单） | W60: 考研专业课,考研无忧计划 | X60: 大三 | Y60: 北京信息科技大学 | Z60: 信息管理学院 | AA60: 大数据管理与应用 | AB60: 刘皓惟 | AC60: 5695887 | AD60: 赵星火 | AE60: 2025-11-12 11:07 | AF60: 赵星火 | AG60: 2025-11-12 11:07 | AH60: 无忧 | AI60: WYE27021 | AJ60: 考研英语无忧计划（27考研/英一冲刺） | AK60: 国内考试 | AM60: 5586.6 | AO60: 徐岩 | AP60: 续班 | AQ60: 已交接 | AR60: WebReg | AS60: BJWY9243582547 | AT60: WYE270210030 | AU60: 2025-11-12 | AW60: 回访人：赵星火，回访时间：2025-11-06 10:56，回访内容：本科学校和专业 北信科 大数据专业 目标院校和专业 没有完全确定院校目标，不想要学习计算机相关的，之前给孩子看的是这种 地理信息系统遥感科学与技术 武汉大学的 就业 基本学情 四六级大学数学 四级 考过了 六级12月 数学现在还可以，十次课还剩余新东方课时 学习时间分配 学习习惯 介绍一对一邀约校区沟通；|回访人：赵星火，回访时间：2025-11-07 16:08，回访内容：跟进学生邀约面谈跟进中这边继续维护中。；|回访人：赵星火，回访时间：2025-11-09 22:03，回访内容：临时有事请假明天回访；|回访人：赵星火，回访时间：2025-11-10 17:02，回访内容：沟通专业院校中，这边想要华电的管理类的这边跟进中，继续维护；|回访人：赵星火，回访时间：2025-11-12 11:07，回访内容：跟进中 | BB60: 43538682 | BC60: 否 | BD60: 27考季 | BE60: 考研专业课150,无忧计划-早鸟 | BF60: 英语,政治,数学,专业课150 | BG60: 其他 | BH60: 国内高校-双非 | BI60: 是 | BL60: 报名 | BN60: 本地人本地大学(常规) | BO60: 学管续费推荐
A61: 100 | B61: 北京大学部 | C61: 国内大学部 | D61: 刘皓惟 | E61: 133486098 | F61: 徐岩 | G61: 2025-11-06 10:35:44 | H61: 续费原因：目前大三想准备考研 咨询一对一 ；该学生为保护期内续费，原顾问：国内大学部-刘文君(liuwenjun6@xdf.cn) | J61: 大三 | K61: 赵星火 | L61: 转介绍 | M61: 学管续费推荐 | N61: 徐岩xuyan91@xdf.cn | Q61: 刘皓惟 | R61: 赵星火 | S61: 30693071 | T61: 续费工单 | U61: 2025-11-06 10:56 | V61: A（六个月内有报课意向工单） | W61: 考研专业课,考研无忧计划 | X61: 大三 | Y61: 北京信息科技大学 | Z61: 信息管理学院 | AA61: 大数据管理与应用 | AB61: 刘皓惟 | AC61: 5695887 | AD61: 赵星火 | AE61: 2025-11-12 11:07 | AF61: 赵星火 | AG61: 2025-11-12 11:07 | AH61: 无忧 | AI61: WYM27019 | AJ61: 考研数学无忧计划（27考研/基础） | AK61: 国内考试 | AM61: 4628.9 | AO61: 徐岩 | AP61: 续班 | AQ61: 已交接 | AR61: WebReg | AS61: BJWY9243582547 | AT61: WYM270190030 | AU61: 2025-11-12 | AW61: 回访人：赵星火，回访时间：2025-11-06 10:56，回访内容：本科学校和专业 北信科 大数据专业 目标院校和专业 没有完全确定院校目标，不想要学习计算机相关的，之前给孩子看的是这种 地理信息系统遥感科学与技术 武汉大学的 就业 基本学情 四六级大学数学 四级 考过了 六级12月 数学现在还可以，十次课还剩余新东方课时 学习时间分配 学习习惯 介绍一对一邀约校区沟通；|回访人：赵星火，回访时间：2025-11-07 16:08，回访内容：跟进学生邀约面谈跟进中这边继续维护中。；|回访人：赵星火，回访时间：2025-11-09 22:03，回访内容：临时有事请假明天回访；|回访人：赵星火，回访时间：2025-11-10 17:02，回访内容：沟通专业院校中，这边想要华电的管理类的这边跟进中，继续维护；|回访人：赵星火，回访时间：2025-11-12 11:07，回访内容：跟进中 | BB61: 43538682 | BC61: 否 | BD61: 27考季 | BE61: 考研专业课150,无忧计划-早鸟 | BF61: 英语,政治,数学,专业课150 | BG61: 其他 | BH61: 国内高校-双非 | BI61: 是 | BL61: 报名 | BN61: 本地人本地大学(常规) | BO61: 学管续费推荐
A62: 101 | B62: 北京大学部 | C62: 国内大学部 | D62: 刘皓惟 | E62: 133486098 | F62: 徐岩 | G62: 2025-11-06 10:35:44 | H62: 续费原因：目前大三想准备考研 咨询一对一 ；该学生为保护期内续费，原顾问：国内大学部-刘文君(liuwenjun6@xdf.cn) | J62: 大三 | K62: 赵星火 | L62: 转介绍 | M62: 学管续费推荐 | N62: 徐岩xuyan91@xdf.cn | Q62: 刘皓惟 | R62: 赵星火 | S62: 30693071 | T62: 续费工单 | U62: 2025-11-06 10:56 | V62: A（六个月内有报课意向工单） | W62: 考研专业课,考研无忧计划 | X62: 大三 | Y62: 北京信息科技大学 | Z62: 信息管理学院 | AA62: 大数据管理与应用 | AB62: 刘皓惟 | AC62: 5695887 | AD62: 赵星火 | AE62: 2025-11-12 11:07 | AF62: 赵星火 | AG62: 2025-11-12 11:07 | AH62: 无忧 | AI62: WYM27020 | AJ62: 考研数学无忧计划（27考研/强化） | AK62: 国内考试 | AM62: 7023.1 | AO62: 徐岩 | AP62: 续班 | AQ62: 已交接 | AR62: WebReg | AS62: BJWY9243582547 | AT62: WYM270200029 | AU62: 2025-11-12 | AW62: 回访人：赵星火，回访时间：2025-11-06 10:56，回访内容：本科学校和专业 北信科 大数据专业 目标院校和专业 没有完全确定院校目标，不想要学习计算机相关的，之前给孩子看的是这种 地理信息系统遥感科学与技术 武汉大学的 就业 基本学情 四六级大学数学 四级 考过了 六级12月 数学现在还可以，十次课还剩余新东方课时 学习时间分配 学习习惯 介绍一对一邀约校区沟通；|回访人：赵星火，回访时间：2025-11-07 16:08，回访内容：跟进学生邀约面谈跟进中这边继续维护中。；|回访人：赵星火，回访时间：2025-11-09 22:03，回访内容：临时有事请假明天回访；|回访人：赵星火，回访时间：2025-11-10 17:02，回访内容：沟通专业院校中，这边想要华电的管理类的这边跟进中，继续维护；|回访人：赵星火，回访时间：2025-11-12 11:07，回访内容：跟进中 | BB62: 43538682 | BC62: 否 | BD62: 27考季 | BE62: 考研专业课150,无忧计划-早鸟 | BF62: 英语,政治,数学,专业课150 | BG62: 其他 | BH62: 国内高校-双非 | BI62: 是 | BL62: 报名 | BN62: 本地人本地大学(常规) | BO62: 学管续费推荐
A63: 102 | B63: 北京大学部 | C63: 国内大学部 | D63: 刘皓惟 | E63: 133486098 | F63: 徐岩 | G63: 2025-11-06 10:35:44 | H63: 续费原因：目前大三想准备考研 咨询一对一 ；该学生为保护期内续费，原顾问：国内大学部-刘文君(liuwenjun6@xdf.cn) | J63: 大三 | K63: 赵星火 | L63: 转介绍 | M63: 学管续费推荐 | N63: 徐岩xuyan91@xdf.cn | Q63: 刘皓惟 | R63: 赵星火 | S63: 30693071 | T63: 续费工单 | U63: 2025-11-06 10:56 | V63: A（六个月内有报课意向工单） | W63: 考研专业课,考研无忧计划 | X63: 大三 | Y63: 北京信息科技大学 | Z63: 信息管理学院 | AA63: 大数据管理与应用 | AB63: 刘皓惟 | AC63: 5695887 | AD63: 赵星火 | AE63: 2025-11-12 11:07 | AF63: 赵星火 | AG63: 2025-11-12 11:07 | AH63: 无忧 | AI63: WYP27202 | AJ63: 考研政治无忧计划（27考研/强化） | AK63: 国内考试 | AM63: 3830.8 | AO63: 徐岩 | AP63: 续班 | AQ63: 已交接 | AR63: WebReg | AS63: BJWY9243582547 | AT63: WYP272020010 | AU63: 2025-11-12 | AW63: 回访人：赵星火，回访时间：2025-11-06 10:56，回访内容：本科学校和专业 北信科 大数据专业 目标院校和专业 没有完全确定院校目标，不想要学习计算机相关的，之前给孩子看的是这种 地理信息系统遥感科学与技术 武汉大学的 就业 基本学情 四六级大学数学 四级 考过了 六级12月 数学现在还可以，十次课还剩余新东方课时 学习时间分配 学习习惯 介绍一对一邀约校区沟通；|回访人：赵星火，回访时间：2025-11-07 16:08，回访内容：跟进学生邀约面谈跟进中这边继续维护中。；|回访人：赵星火，回访时间：2025-11-09 22:03，回访内容：临时有事请假明天回访；|回访人：赵星火，回访时间：2025-11-10 17:02，回访内容：沟通专业院校中，这边想要华电的管理类的这边跟进中，继续维护；|回访人：赵星火，回访时间：2025-11-12 11:07，回访内容：跟进中 | BB63: 43538682 | BC63: 否 | BD63: 27考季 | BE63: 考研专业课150,无忧计划-早鸟 | BF63: 英语,政治,数学,专业课150 | BG63: 其他 | BH63: 国内高校-双非 | BI63: 是 | BL63: 报名 | BN63: 本地人本地大学(常规) | BO63: 学管续费推荐
A64: 103 | B64: 北京大学部 | C64: 国内大学部 | D64: 刘皓惟 | E64: 133486098 | F64: 徐岩 | G64: 2025-11-06 10:35:44 | H64: 续费原因：目前大三想准备考研 咨询一对一 ；该学生为保护期内续费，原顾问：国内大学部-刘文君(liuwenjun6@xdf.cn) | J64: 大三 | K64: 赵星火 | L64: 转介绍 | M64: 学管续费推荐 | N64: 徐岩xuyan91@xdf.cn | Q64: 刘皓惟 | R64: 赵星火 | S64: 30693071 | T64: 续费工单 | U64: 2025-11-06 10:56 | V64: A（六个月内有报课意向工单） | W64: 考研专业课,考研无忧计划 | X64: 大三 | Y64: 北京信息科技大学 | Z64: 信息管理学院 | AA64: 大数据管理与应用 | AB64: 刘皓惟 | AC64: 5695887 | AD64: 赵星火 | AE64: 2025-11-12 11:07 | AF64: 赵星火 | AG64: 2025-11-12 11:07 | AH64: 无忧 | AI64: WYP27203 | AJ64: 考研政治无忧计划（27考研/冲刺） | AK64: 国内考试 | AM64: 3549.1 | AO64: 徐岩 | AP64: 续班 | AQ64: 已交接 | AR64: WebReg | AS64: BJWY9243582547 | AT64: WYP272030010 | AU64: 2025-11-12 | AW64: 回访人：赵星火，回访时间：2025-11-06 10:56，回访内容：本科学校和专业 北信科 大数据专业 目标院校和专业 没有完全确定院校目标，不想要学习计算机相关的，之前给孩子看的是这种 地理信息系统遥感科学与技术 武汉大学的 就业 基本学情 四六级大学数学 四级 考过了 六级12月 数学现在还可以，十次课还剩余新东方课时 学习时间分配 学习习惯 介绍一对一邀约校区沟通；|回访人：赵星火，回访时间：2025-11-07 16:08，回访内容：跟进学生邀约面谈跟进中这边继续维护中。；|回访人：赵星火，回访时间：2025-11-09 22:03，回访内容：临时有事请假明天回访；|回访人：赵星火，回访时间：2025-11-10 17:02，回访内容：沟通专业院校中，这边想要华电的管理类的这边跟进中，继续维护；|回访人：赵星火，回访时间：2025-11-12 11:07，回访内容：跟进中 | BB64: 43538682 | BC64: 否 | BD64: 27考季 | BE64: 考研专业课150,无忧计划-早鸟 | BF64: 英语,政治,数学,专业课150 | BG64: 其他 | BH64: 国内高校-双非 | BI64: 是 | BL64: 报名 | BN64: 本地人本地大学(常规) | BO64: 学管续费推荐
A65: 104 | B65: 北京大学部 | C65: 国内大学部 | D65: 刘皓惟 | E65: 133486098 | F65: 徐岩 | G65: 2025-11-06 10:35:44 | H65: 续费原因：目前大三想准备考研 咨询一对一 ；该学生为保护期内续费，原顾问：国内大学部-刘文君(liuwenjun6@xdf.cn) | J65: 大三 | K65: 赵星火 | L65: 转介绍 | M65: 学管续费推荐 | N65: 徐岩xuyan91@xdf.cn | Q65: 刘皓惟 | R65: 赵星火 | S65: 30693071 | T65: 续费工单 | U65: 2025-11-06 10:56 | V65: A（六个月内有报课意向工单） | W65: 考研专业课,考研无忧计划 | X65: 大三 | Y65: 北京信息科技大学 | Z65: 信息管理学院 | AA65: 大数据管理与应用 | AB65: 刘皓惟 | AC65: 5695887 | AD65: 赵星火 | AE65: 2025-11-12 11:07 | AF65: 赵星火 | AG65: 2025-11-12 11:07 | AH65: 无忧 | AI65: LP1762915865331 | AJ65: 考研初试专业课一对一（27考研/无忧30小时） | AK65: 国内考试 | AM65: 10000 | AO65: 徐岩 | AP65: 续班 | AQ65: 已交接 | AR65: WebReg | AS65: BJWY9243582547 | AU65: 2025-11-12 | AW65: 回访人：赵星火，回访时间：2025-11-06 10:56，回访内容：本科学校和专业 北信科 大数据专业 目标院校和专业 没有完全确定院校目标，不想要学习计算机相关的，之前给孩子看的是这种 地理信息系统遥感科学与技术 武汉大学的 就业 基本学情 四六级大学数学 四级 考过了 六级12月 数学现在还可以，十次课还剩余新东方课时 学习时间分配 学习习惯 介绍一对一邀约校区沟通；|回访人：赵星火，回访时间：2025-11-07 16:08，回访内容：跟进学生邀约面谈跟进中这边继续维护中。；|回访人：赵星火，回访时间：2025-11-09 22:03，回访内容：临时有事请假明天回访；|回访人：赵星火，回访时间：2025-11-10 17:02，回访内容：沟通专业院校中，这边想要华电的管理类的这边跟进中，继续维护；|回访人：赵星火，回访时间：2025-11-12 11:07，回访内容：跟进中 | BB65: 43538682 | BC65: 否 | BD65: 27考季 | BE65: 考研专业课150,无忧计划-早鸟 | BF65: 英语,政治,数学,专业课150 | BG65: 其他 | BH65: 国内高校-双非 | BI65: 是 | BN65: 本地人本地大学(常规) | BO65: 学管续费推荐
A66: 44 | B66: 北京大学部 | C66: 国内大学部 | D66: 刘家豪 | E66: 136146714 | F66: 王天义 | G66: 2025-11-30 10:54:12 | H66: 续费原因：学生考虑续费三次一对一课程，非定制；该学生为保护期内续费，原顾问：国内大学部-谭悦(tanyue9@xdf.cn) | J66: 大四 | K66: 谭悦 | L66: 转介绍 | M66: 学管续费推荐 | N66: 王天义wangtianyi56@xdf.cn | Q66: 刘家豪 | R66: 谭悦 | S66: 30892629 | T66: 续费工单 | U66: 2025-11-30 15:54 | V66: A（六个月内有报课意向工单） | W66: 考研VIP | X66: 大四 | Y66: 北京交通大学 | Z66: 材料 | AA66: 材料 | AB66: 刘家豪 | AC66: 5737921 | AD66: 谭悦 | AE66: 2025-11-30 16:02 | AF66: 谭悦 | AG66: 2025-11-30 16:29 | AH66: 个性化 | AI66: LP17644897583010 | AJ66: 考研一对一伴学班（26考季） | AK66: 国内考试 | AM66: 4800 | AO66: 王天义 | AP66: 续班 | AQ66: 已交接 | AS66: BJWY3144689723 | AU66: 2025-11-30 | AW66: 回访人：谭悦，回访时间：2025-11-30 15:54，回访内容：1；|回访人：谭悦，回访时间：2025-11-30 16:02，回访内容：系统自动签约 | BB66: 30979793 | BC66: 否 | BD66: 26考季 | BE66: VIP - 伴学 | BF66: 英语 | BG66: 其他 | BH66: 国内高校-211 | BI66: 是 | BN66: 本地人本地大学(常规) | BO66: 学管续费推荐
A67: 42 | B67: 北京大学部 | C67: 国内大学部 | D67: 刘潇婧 | E67: 136235064 | F67: 李雪68 | G67: 2025-11-30 20:25:17 | H67: 学生学习英语和政治，先报12小时的非定制课程，教师是龚媛媛和王晶，辛苦加学生的微信沟通付款 | J67: 未知 | K67: 李涛 | L67: 转介绍 | M67: 学管转介绍 | N67: 陈晶chenjing171@xdf.cn | Q67: 刘潇婧 | R67: 李涛 | S67: 30954826 | T67: 正常工单 | U67: 2025-12-01 10:05 | V67: A（六个月内有报课意向工单） | W67: 考研VIP | X67: 大四 | Y67: 南京航空航天大学 | Z67: 未知 | AA67: 未知 | AB67: 刘潇婧 | AC67: 5739155 | AD67: 李涛 | AE67: 2025-12-01 14:56 | AF67: 李涛 | AG67: 2025-12-01 15:00 | AH67: 个性化 | AI67: LP17645721765147 | AJ67: 考研一对一伴学班（26考季） | AK67: 国内考试 | AM67: 8800 | AO67: 陈晶 | AP67: 新签 | AQ67: 已交接 | AS67: BJWY0762412108 | AU67: 2025-12-01 | AW67: 回访人：李涛，回访时间：2025-12-01 10:05，回访内容：学生学习英语和政治，先报12小时的非定制课程，教师是龚媛媛和王晶；|回访人：李涛，回访时间：2025-12-01 14:56，回访内容：系统自动签约 | BB67: 88224022 | BC67: 否 | BD67: 26考季 | BE67: VIP - 伴学 | BF67: 英语 | BG67: 其他 | BH67: 国内高校-211 | BI67: 否 | BN67: 外地人外地大学(常规) | BO67: 客服
A68: 111 | B68: 北京大学部 | C68: 国内大学部 | D68: 刘柱山 | E68: 133739987 | F68: 张泽7 | G68: 2025-11-07 15:32:10 | H68: 续费原因：加 3 次逻辑共 6 小时，2 次写作共 2 小时，一共 8 小时管综；该学生为保护期内续费，原顾问：国内大学部-谭悦(tanyue9@xdf.cn) | J68: 大四 | K68: 谭悦 | L68: 转介绍 | M68: 学管续费推荐 | N68: 张泽7zhangze7@xdf.cn | Q68: 刘柱山 | R68: 谭悦 | S68: 30706489 | T68: 续费工单 | U68: 2025-11-09 11:08 | V68: A（六个月内有报课意向工单） | W68: 考研VIP | X68: 大四 | Y68: 中央财经大学 | Z68: 国际经济与贸易学院 | AA68: 国际商务 | AB68: 刘柱山 | AC68: 5694025 | AD68: 谭悦 | AE68: 2025-11-09 15:57 | AF68: 谭悦 | AG68: 2025-11-09 17:09 | AH68: 个性化 | AI68: LP17626750221872 | AJ68: 考研初试专业课一对一伴学班（经综-26考季） | AK68: 国内考试 | AM68: 5400 | AO68: 张泽7 | AP68: 续班 | AQ68: 已交接 | AS68: BJWY3477910309 | AU68: 2025-11-09 | AW68: 回访人：谭悦，回访时间：2025-11-09 11:08，回访内容：1；|回访人：谭悦，回访时间：2025-11-09 15:57，回访内容：系统自动签约 | BB68: 61985429 | BC68: 否 | BD68: 26考季 | BE68: VIP - 伴学 | BF68: 英语,政治 | BG68: 其他 | BH68: 国内高校-中外合作办学 | BI68: 是 | BN68: 本地人本地大学(常规) | BO68: 学管续费推荐
A69: 65 | B69: 北京大学部 | C69: 国内大学部 | E69: 135414334 | G69: 2025-11-22 11:17:41 | H69: 续费原因：续费，个性化；该学生为保护期内续费，原顾问：国内大学部-谭悦(tanyue9@xdf.cn) | J69: 大学已毕业 | K69: 谭悦 | L69: 转介绍 | M69: 学管续费推荐 | Q69: 吕昊铭 | R69: 谭悦 | S69: 30856055 | T69: 续费工单 | U69: 2025-11-22 20:32 | V69: A（六个月内有报课意向工单） | W69: 考研VIP | X69: 大学已毕业 | Y69: 北京理工大学 | Z69: 材料学院 | AA69: 材料科学与工程 | AB69: 吕昊铭 | AC69: 5706823 | AD69: 谭悦 | AE69: 2025-11-22 20:33 | AF69: 谭悦 | AG69: 2025-11-22 20:35 | AH69: 个性化 | AI69: LP17638148124140 | AJ69: 考研一对一伴学班（26考季） | AK69: 国内考试 | AM69: 1600 | AP69: 续班 | AQ69: 已交接 | AS69: BJWY9628596430 | AU69: 2025-11-22 | AW69: 回访人：谭悦，回访时间：2025-11-22 20:32，回访内容：1；|回访人：谭悦，回访时间：2025-11-22 20:33，回访内容：系统自动签约 | BB69: 37964629 | BC69: 否 | BD69: 27考季 | BE69: VIP - 伴学 | BF69: 英语 | BH69: 国内高校-985 | BI69: 是
A70: 66 | B70: 北京大学部 | C70: 国内大学部 | D70: 吕昊铭 | E70: 135414334 | F70: 陈晶 | G70: 2025-11-22 11:17:41 | H70: 续费原因：续费，个性化；该学生为保护期内续费，原顾问：国内大学部-谭悦(tanyue9@xdf.cn) | J70: 大学已毕业 | K70: 谭悦 | L70: 转介绍 | M70: 学管续费推荐 | N70: 陈晶chenjing171@xdf.cn | Q70: 吕昊铭 | R70: 谭悦 | S70: 30853054 | T70: 续费工单 | U70: 2025-11-22 12:45 | V70: A（六个月内有报课意向工单） | W70: 考研VIP | X70: 大学已毕业 | Y70: 北京理工大学 | Z70: 材料学院 | AA70: 材料科学与工程 | AB70: 吕昊铭 | AC70: 5706621 | AD70: 谭悦 | AE70: 2025-11-22 17:01 | AF70: 谭悦 | AG70: 2025-11-22 17:15 | AH70: 四六级 | AI70: LP17638020862973 | AJ70: 六级一对一伴学班（定制） | AK70: 国内考试 | AM70: 12800 | AO70: 陈晶 | AP70: 续班 | AQ70: 已交接 | AS70: BJWY9628596430 | AU70: 2025-11-22 | AW70: 回访人：谭悦，回访时间：2025-11-22 12:45，回访内容：1；|回访人：谭悦，回访时间：2025-11-22 17:01，回访内容：系统自动签约 | BB70: 37964629 | BC70: 否 | BD70: 27考季 | BE70: VIP - 伴学 | BF70: 英语 | BG70: 其他 | BH70: 国内高校-985 | BI70: 否 | BO70: 学管续费推荐
A71: 32 | B71: 北京大学部 | C71: 国内大学部 | E71: 125744073 | G71: 2025-09-01 17:44:10 | H71: 死单激活，刘创； | J71: 大三 | K71: 刘创 | L71: 线上运营-投放 | M71: 总部-百度投放 | Q71: 吕松澄 | R71: 刘创 | S71: 30710678 | T71: 续费工单 | U71: 2025-11-10 11:01 | V71: B（需长时间跟单或只需要规划） | W71: 考研专业课,考研无忧计划 | X71: 大三 | Y71: 北京工业大学 | Z71: 信息学部 | AA71: 计算机科学与技术（实验班) | AB71: 吕松澄 | AC71: 5698344 | AD71: 赵星火 | AE71: 2025-11-10 11:02 | AF71: 刘创 | AG71: 2025-11-10 11:03 | AH71: 无忧 | AK71: 国内考试 | AM71: 6350 | AN71: 同科续费 | AP71: 分单 | AQ71: 无须交接 | AS71: BJWY6180564776 | AW71: 回访人：刘创，回访时间：2025-11-10 11:01，回访内容：1；|回访人：刘创，回访时间：2025-11-10 11:02，回访内容：1 | BB71: 69944517 | BC71: 否 | BD71: 26考季 | BE71: 无忧计划-啄木鸟,考研专业课150 | BF71: 英语,政治,数学,计算机 | BH71: 国内高校-211 | BI71: 否 | BN71: 本地人本地大学(常规)
A72: 130 | B72: 北京大学部 | C72: 国内大学部 | D72: Leb | E72: 133190727 | F72: 王朝群 | G72: 2025-11-02 15:01:53 | H72: 【王朝群】咨询考研英语+政治一对一辅导 | J72: 大四 | K72: 赵星火 | L72: 线上运营-小红书 | M72: 小红书KOS | Q72: 马欧力 | R72: 赵星火 | S72: 30648417 | T72: 正常工单 | U72: 2025-11-02 15:18 | V72: A（六个月内有报课意向工单） | W72: 考研VIP | X72: 大四 | Y72: 北京科技大学 | Z72: 机械工程学院 | AA72: 机械工程 | AB72: 马欧力 | AC72: 5665020 | AD72: 赵星火 | AE72: 2025-11-03 18:26 | AF72: 赵星火 | AG72: 2025-11-03 18:33 | AH72: 网课 | AI72: 36384969030 | AJ72: 2026考研专业课定制一对一（20h）-A班 | AK72: 国内考试 | AM72: 9450 | AP72: 新签 | AQ72: 已交接 | AS72: BJWY5875380161 | AU72: 2025-11-03 | AW72: 回访人：赵星火，回访时间：2025-11-02 15:18，回访内容：考本校本专业自述要370，英语需要做题技巧和写作，目标分70 政治没开始需要60+ 数学自己学习 专业课没开始介绍新东方的辅导，意向知春路；|回访人：赵星火，回访时间：2025-11-03 15:17，回访内容：回访学生情况考北科的机械，这边问下家里的考虑还没确认。；|回访人：赵星火，回访时间：2025-11-03 18:26，回访内容：系统自动签约 | BA72: 长期班 | BB72: 86961059 | BC72: 是 | BD72: 26考季 | BE72: VIP - 伴学 | BF72: 英语,政治 | BG72: 其他 | BH72: 国内高校-211 | BI72: 是 | BM72: 111109782 | BN72: 本地人本地大学(常规) | BO72: 市场
A73: 131 | B73: 北京大学部 | C73: 国内大学部 | D73: Leb | E73: 133190727 | F73: 王朝群 | G73: 2025-11-02 15:01:53 | H73: 【王朝群】咨询考研英语+政治一对一辅导 | J73: 大四 | K73: 赵星火 | L73: 线上运营-小红书 | M73: 小红书KOS | Q73: 马欧力 | R73: 赵星火 | S73: 30648417 | T73: 正常工单 | U73: 2025-11-02 15:18 | V73: A（六个月内有报课意向工单） | W73: 考研VIP | X73: 大四 | Y73: 北京科技大学 | Z73: 机械工程学院 | AA73: 机械工程 | AB73: 马欧力 | AC73: 5665020 | AD73: 赵星火 | AE73: 2025-11-03 18:26 | AF73: 赵星火 | AG73: 2025-11-03 18:33 | AH73: 个性化 | AI73: LP17621659211183 | AJ73: 考研一对一伴学班（26考季） | AK73: 国内考试 | AM73: 47100 | AP73: 新签 | AQ73: 已交接 | AS73: BJWY5875380161 | AU73: 2025-11-03 | AW73: 回访人：赵星火，回访时间：2025-11-02 15:18，回访内容：考本校本专业自述要370，英语需要做题技巧和写作，目标分70 政治没开始需要60+ 数学自己学习 专业课没开始介绍新东方的辅导，意向知春路；|回访人：赵星火，回访时间：2025-11-03 15:17，回访内容：回访学生情况考北科的机械，这边问下家里的考虑还没确认。；|回访人：赵星火，回访时间：2025-11-03 18:26，回访内容：系统自动签约 | BB73: 86961059 | BC73: 否 | BD73: 26考季 | BE73: VIP - 伴学 | BF73: 英语,政治 | BG73: 其他 | BH73: 国内高校-211 | BI73: 是 | BM73: 111109782 | BN73: 本地人本地大学(常规) | BO73: 市场
A74: 129 | B74: 北京大学部 | C74: 国内大学部 | D74: 马雨晨 | E74: 133209037 | F74: 张泽7 | G74: 2025-11-02 23:55:39 | H74: 续费原因：10小时专业课可以加；该学生为保护期内续费，原顾问：国内大学部-赵星火(zhaoxinghuo@xdf.cn) | J74: 大四 | K74: 赵星火 | L74: 转介绍 | M74: 学管续费推荐 | N74: 张泽7zhangze7@xdf.cn | Q74: 马雨晨 | R74: 赵星火 | S74: 30654908 | T74: 续费工单 | U74: 2025-11-03 10:20 | V74: A（六个月内有报课意向工单） | W74: 考研专业课 | X74: 大四 | Y74: 北京邮电大学世纪学院 | Z74: 外语系 | AA74: 英语 | AB74: 马雨晨 | AC74: 5690839 | AD74: 赵星火 | AE74: 2025-11-03 10:38 | AF74: 赵星火 | AG74: 2025-11-03 10:40 | AH74: 个性化 | AI74: LP1762137510106 | AJ74: 考研一对一伴学班（26考季） | AK74: 国内考试 | AM74: 8000 | AO74: 张泽7 | AP74: 续班 | AQ74: 已交接 | AS74: BJWY0133779918 | AU74: 2025-11-03 | AW74: 回访人：赵星火，回访时间：2025-11-03 10:20，回访内容：签约；|回访人：赵星火，回访时间：2025-11-03 10:38，回访内容：系统自动签约 | BB74: 63566151 | BC74: 否 | BD74: 26考季 | BE74: 考研专业课150 | BF74: 专业课150 | BG74: 其他 | BH74: 国内高校-双非 | BI74: 是 | BN74: 本地人本地大学(常规) | BO74: 学管续费推荐
A75: 74 | B75: 北京大学部 | C75: 国内大学部 | D75: 梅嘉润 | E75: 134865026 | F75: 王天义 | G75: 2025-11-17 19:51:01 | H75: 续费原因：学生续费 10h 数学课非定制；该学生为保护期内续费，原顾问：国内大学部-赵星火(zhaoxinghuo@xdf.cn) | J75: 大四 | K75: 赵星火 | L75: 转介绍 | M75: 学管续费推荐 | N75: 王天义wangtianyi56@xdf.cn | Q75: 梅嘉润 | R75: 赵星火 | S75: 30810388 | T75: 续费工单 | U75: 2025-11-18 10:29 | V75: A（六个月内有报课意向工单） | W75: 考研VIP | X75: 大四 | Y75: 辽宁大学 | Z75: 信息学院 | AA75: 电子信息科学与技术 | AB75: 梅嘉润 | AC75: 5730069 | AD75: 赵星火 | AE75: 2025-11-18 12:46 | AF75: 赵星火 | AG75: 2025-11-18 12:48 | AH75: 个性化 | AI75: LP1763441212420 | AJ75: 考研一对一伴学班（26考季） | AK75: 国内考试 | AM75: 9000 | AO75: 王天义 | AP75: 续班 | AQ75: 已交接 | AS75: BJWY8697479484 | AU75: 2025-11-18 | AW75: 回访人：赵星火，回访时间：2025-11-18 10:29，回访内容：1；|回访人：赵星火，回访时间：2025-11-18 12:46，回访内容：系统自动签约 | BB75: 85972134 | BC75: 否 | BD75: 26考季 | BE75: VIP - 伴学 | BF75: 数学 | BG75: 其他 | BH75: 国内高校-211 | BI75: 是 | BN75: 本地人本地大学(常规) | BO75: 学管续费推荐
A76: 78 | B76: 北京大学部 | C76: 国内大学部 | D76: 未知 | E76: 134524349 | F76: 李雪68 | G76: 2025-11-14 11:53:26 | H76: 四级英语 | J76: 大三 | K76: 赵星火 | L76: 线上运营-商务合作 | M76: 百教网 | Q76: 梅溪田 | R76: 赵星火 | S76: 30780899 | T76: 正常工单 | U76: 2025-11-14 15:54 | V76: A（六个月内有报课意向工单） | W76: 考研无忧计划 | X76: 大三 | Y76: 长春理工大学 | Z76: 光电工程学院 | AA76: 光电信息科学与工程（工学） | AB76: 梅溪田 | AC76: 5575371 | AD76: 赵星火 | AE76: 2025-11-18 12:35 | AF76: 赵星火 | AG76: 2025-11-18 12:39 | AH76: 无忧 | AI76: WYHM27001 | AJ76: 考研数学无忧计划候鸟（27考研/基础强化） | AK76: 国内考试 | AM76: 13962.8 | AP76: 新签 | AQ76: 已交接 | AR76: BJWY24032w1g8X | AS76: BJWY4119645110 | AT76: WYHM270010018 | AU76: 2025-11-18 | AW76: 回访人：赵星火，回访时间：2025-11-14 15:54，回访内容：表示就想要数学一的班课辅导，寒假的这边跟进中继续维护学生情况。；|回访人：赵星火，回访时间：2025-11-16 20:36，回访内容：临时有事明天回访；|回访人：赵星火，回访时间：2025-11-17 14:46，回访内容：回访学生情况这边继续维护学生考虑跟进中；|回访人：赵星火，回访时间：2025-11-18 12:35，回访内容：1 | BB76: 45801905 | BC76: 否 | BD76: 27考季 | BE76: 无忧计划-候鸟 | BF76: 数学 | BH76: 国内高校-双非 | BI76: 是 | BL76: 报名 | BN76: 本地人本地大学(常规) | BO76: 客服
A77: 79 | B77: 北京大学部 | C77: 国内大学部 | D77: 未知 | E77: 134524349 | F77: 李雪68 | G77: 2025-11-14 11:53:26 | H77: 四级英语 | J77: 大三 | K77: 赵星火 | L77: 线上运营-商务合作 | M77: 百教网 | Q77: 梅溪田 | R77: 赵星火 | S77: 30780899 | T77: 正常工单 | U77: 2025-11-14 15:54 | V77: A（六个月内有报课意向工单） | W77: 考研无忧计划 | X77: 大三 | Y77: 长春理工大学 | Z77: 光电工程学院 | AA77: 光电信息科学与工程（工学） | AB77: 梅溪田 | AC77: 5575371 | AD77: 赵星火 | AE77: 2025-11-18 12:35 | AF77: 赵星火 | AG77: 2025-11-18 12:39 | AH77: 无忧 | AI77: WYHM27002 | AJ77: 考研数学无忧计划候鸟（27考研/冲刺） | AK77: 国内考试 | AM77: 1337.2 | AP77: 新签 | AQ77: 已交接 | AR77: BJWY24032w1g8X | AS77: BJWY4119645110 | AT77: WYHM270020018 | AU77: 2025-11-18 | AW77: 回访人：赵星火，回访时间：2025-11-14 15:54，回访内容：表示就想要数学一的班课辅导，寒假的这边跟进中继续维护学生情况。；|回访人：赵星火，回访时间：2025-11-16 20:36，回访内容：临时有事明天回访；|回访人：赵星火，回访时间：2025-11-17 14:46，回访内容：回访学生情况这边继续维护学生考虑跟进中；|回访人：赵星火，回访时间：2025-11-18 12:35，回访内容：1 | BB77: 45801905 | BC77: 否 | BD77: 27考季 | BE77: 无忧计划-候鸟 | BF77: 数学 | BH77: 国内高校-双非 | BI77: 是 | BL77: 报名 | BN77: 本地人本地大学(常规) | BO77: 客服
A78: 13 | B78: 北京大学部 | C78: 国内大学部 | E78: 128355093 | G78: 2025-09-21 11:18:18 | H78: 激活 | J78: 大三 | K78: 赵星火 | L78: 线上运营-投放 | M78: 巨量广告 | Q78: 孟瑞航 | R78: 赵星火 | S78: 30710400 | T78: 续费工单 | U78: 2025-11-10 10:41 | V78: A（六个月内有报课意向工单） | W78: 考研专业课,考研无忧计划 | X78: 大三 | Y78: 北京工业大学 | Z78: 信息学部 | AA78: 软件工程（实验班） | AB78: 孟瑞航 | AC78: 5698324 | AD78: 赵星火 | AE78: 2025-11-10 10:44 | AF78: 赵星火 | AG78: 2025-11-10 10:44 | AH78: 无忧 | AI78: WYC27103 | AJ78: 考研专业课无忧Pro优才走读班（27考研/408计算机） | AK78: 国内考试 | AM78: 9000 | AN78: 同科续费 | AP78: 续班 | AQ78: 无须交接 | AR78: BJWY2101498uW2 | AS78: BJWY8048985572 | AT78: WYC271030009 | AU78: 2025-11-07 | AW78: 回访人：赵星火，回访时间：2025-11-10 10:41，回访内容：1；|回访人：赵星火，回访时间：2025-11-10 10:44，回访内容：1 | BB78: 81748797 | BC78: 否 | BD78: 27考季 | BE78: 无忧计划-早鸟,考研专业课150 | BF78: 英语,政治,数学,计算机,专业课150 | BH78: 国内高校-211 | BI78: 否 | BL78: 转出 | BN78: 本地人本地大学(常规)
A79: 132 | B79: 北京大学部 | C79: 国内大学部 | D79: 齐子涵 | E79: 133242906 | F79: 王天义 | G79: 2025-11-03 10:46:51 | H79: 续费原因：续费 6h；该学生为保护期内续费，原顾问：国内大学部-赵星火(zhaoxinghuo@xdf.cn) | J79: 大四 | K79: 赵星火 | L79: 转介绍 | M79: 学管续费推荐 | N79: 王天义wangtianyi56@xdf.cn | Q79: 齐子涵 | R79: 赵星火 | S79: 30650722 | T79: 续费工单 | U79: 2025-11-03 10:55 | V79: A（六个月内有报课意向工单） | W79: 考研VIP | X79: 大四 | Y79: 中国农业大学 | Z79: 工学院 | AA79: 农业工程 | AB79: 齐子涵 | AC79: 5664663 | AD79: 赵星火 | AE79: 2025-11-03 10:57 | AF79: 赵星火 | AG79: 2025-11-03 10:59 | AH79: 个性化 | AI79: LP1762138635165 | AJ79: 考研一对一伴学班（26考季） | AK79: 国内考试 | AM79: 5100 | AO79: 王天义 | AP79: 续班 | AQ79: 已交接 | AS79: BJWY2929284490 | AU79: 2025-11-03 | AW79: 回访人：赵星火，回访时间：2025-11-03 10:55，回访内容：1；|回访人：赵星火，回访时间：2025-11-03 10:57，回访内容：系统自动签约 | BB79: 68854313 | BC79: 否 | BD79: 26考季 | BE79: VIP - 伴学 | BF79: 英语 | BG79: 其他 | BH79: 国内高校-985 | BI79: 是 | BN79: 本地人本地大学(常规) | BO79: 学管续费推荐
A80: 122 | B80: 北京大学部 | C80: 国内大学部 | D80: 其乐木格 | E80: 133384773 | F80: 陈晶 | G80: 2025-11-04 15:00:37 | H80: 续费原因：续费，赵星火；该学生为保护期内续费，原顾问：国内大学部-赵星火(zhaoxinghuo@xdf.cn) | J80: 大四 | K80: 赵星火 | L80: 转介绍 | M80: 学管续费推荐 | N80: 陈晶chenjing171@xdf.cn | Q80: 其乐木格 | R80: 赵星火 | S80: 30660407 | T80: 续费工单 | U80: 2025-11-04 15:18 | V80: A（六个月内有报课意向工单） | W80: 考研VIP | X80: 大四 | Y80: 中国人民大学 | Z80: 马克思主义学院 | AA80: 中国共产党历史 | AB80: 其乐木格 | AC80: 5691427 | AD80: 赵星火 | AE80: 2025-11-04 15:19 | AF80: 赵星火 | AG80: 2025-11-04 15:30 | AH80: 个性化 | AI80: LP1762240780945 | AJ80: 考研一对一伴学班（26考季） | AK80: 国内考试 | AM80: 8500 | AO80: 陈晶 | AP80: 续班 | AQ80: 已交接 | AS80: BJWY9831867979 | AU80: 2025-11-04 | AW80: 回访人：赵星火，回访时间：2025-11-04 15:18，回访内容：签约1；|回访人：赵星火，回访时间：2025-11-04 15:19，回访内容：系统自动签约 | BB80: 64618455 | BC80: 否 | BD80: 26考季 | BE80: VIP - 伴学 | BF80: 数学 | BG80: 其他 | BH80: 国内高校-985 | BI80: 是 | BN80: 本地人本地大学(常规) | BO80: 学管续费推荐
A81: 30 | B81: 北京大学部 | C81: 国内大学部 | E81: 124719714 | G81: 2025-08-22 11:32:22 | H81: 考北大 文学现代汉语，咨询考研专业课，目前在北京可以到校区面询 渠道录入来源：大众点评 事件名称：400电话 大众点评门店名称：新东方考研四六级(中关村总部) 店铺绑定的校区：临时教学校区 店铺管理员邮箱：lvmeng2@xdf.cn 备注：2025-08-22 11:32:20,用户在大众点评新东方考研四六级(中关村总部)呼入400电话 已接 | I81: 2026财年第3财月大众点评在线咨询 | J81: 未知 | K81: 赵星火 | L81: 线上运营-本地生活平台 | M81: 大众点评 | Q81: 青松 | R81: 赵星火 | S81: 30880653 | T81: 续费工单 | U81: 2025-11-27 16:45 | V81: A（六个月内有报课意向工单） | W81: 考研专业课 | X81: 大四 | Y81: 广东财经大学 | Z81: 文学院 | AA81: 汉语言文学 | AB81: 青松 | AC81: 5709811 | AD81: 赵星火 | AE81: 2025-11-27 16:45 | AF81: 系统管理员 | AG81: 2025-11-27 16:45 | AH81: 个性化 | AI81: LP17587025531109 | AJ81: 考研一对一伴学班（26考季） | AM81: -11600 | AQ81: 未交接 | AS81: BJWY1260307992 | AU81: 2025-11-27 | AW81: 回访人：系统管理员，回访时间：2025-11-27 16:45，回访内容：学生转产品转入，创建续费工单。 | BB81: 83898131 | BC81: 否 | BD81: 26考季 | BE81: 考研专业课300 | BF81: 专业课300 | BH81: 国内高校-双非 | BI81: 否
A82: 31 | B82: 北京大学部 | C82: 国内大学部 | E82: 124719714 | G82: 2025-08-22 11:32:22 | H82: 考北大 文学现代汉语，咨询考研专业课，目前在北京可以到校区面询 渠道录入来源：大众点评 事件名称：400电话 大众点评门店名称：新东方考研四六级(中关村总部) 店铺绑定的校区：临时教学校区 店铺管理员邮箱：lvmeng2@xdf.cn 备注：2025-08-22 11:32:20,用户在大众点评新东方考研四六级(中关村总部)呼入400电话 已接 | I82: 2026财年第3财月大众点评在线咨询 | J82: 未知 | K82: 赵星火 | L82: 线上运营-本地生活平台 | M82: 大众点评 | Q82: 青松 | R82: 赵星火 | S82: 30880653 | T82: 续费工单 | U82: 2025-11-27 16:45 | V82: A（六个月内有报课意向工单） | W82: 考研专业课 | X82: 大四 | Y82: 广东财经大学 | Z82: 文学院 | AA82: 汉语言文学 | AB82: 青松 | AC82: 5709811 | AD82: 赵星火 | AE82: 2025-11-27 16:45 | AF82: 系统管理员 | AG82: 2025-11-27 16:45 | AH82: 个性化 | AI82: LP17642330441626 | AJ82: 考研一对一伴学班（定制/26考季） | AM82: 9900 | AQ82: 未交接 | AS82: BJWY1260307992 | AU82: 2025-11-27 | AW82: 回访人：系统管理员，回访时间：2025-11-27 16:45，回访内容：学生转产品转入，创建续费工单。 | BB82: 83898131 | BC82: 否 | BD82: 26考季 | BE82: 考研专业课300 | BF82: 专业课300 | BH82: 国内高校-双非 | BI82: 否
A83: 25 | B83: 北京大学部 | C83: 国内大学部 | D83: 未知 | E83: 132181335 | F83: 张亚男 | G83: 2025-10-24 15:01:02 | H83: 渠道录入来源：集团百度搜索-基木鱼-新媒体管家 活动所属学校id：108 活动所属学校名称：北京大学事业部 统一活动id：2824107 统一活动名称：北京大学事业部25年10月百度搜索在线咨询 线索接收学校id：108 线索id：18be486027f8183461b1b1b59f78d55e 线索接收部门code：02 线索接收二级部门code：0201 渠道名称：网络营销-百度搜索-在线咨询 线索接收人邮箱：zhangyanan13@xdf.cn 备注：当前线索来源于百度搜索 账户ID：60103473 线索类型：咨询 留资时间：2025-10-24 14:52:10 流量渠道：百度-搜索推广 线索地域：北京 通话状态：未接通 搜索词：北京线下考研辅导机构哪家好 C端用户名称： 账号名称： 关键词：新东方考研机构价目表 站点名称：新东方考研专属客服 站点URL：https://ada.baidu.com/site/wjz2uk75/agent?imid=b9cc3f4ec469d744ef91d47374486c78 推广计划：新东方-考研 IP: 1.202.53.35 | I83: 2026财年第5财月集团百度搜索-基木鱼-新媒体管家 | J83: 未知 | K83: 赵星火 | L83: 线上运营-投放 | M83: 总部-百度投放 | Q83: 秋何故 | R83: 赵星火 | S83: 30548084 | T83: 正常工单 | U83: 2025-10-24 15:25 | V83: A（六个月内有报课意向工单） | W83: 考研集训营 | X83: 在职 | Y83: 北京第二外国语学院 | Z83: 英语学院 | AA83: 英语 | AB83: 秋何故 | AC83: 5664573 | AD83: 赵星火 | AE83: 2025-11-02 21:24 | AF83: 赵星火 | AG83: 2025-11-02 22:12 | AH83: 网课 | AI83: 39232209222 | AJ83: 2027考研专业课定制一对一（50h）-A班 | AK83: 国内考试 | AM83: 19125 | AP83: 新签 | AQ83: 无须交接 | AU83: 2025-11-02 | AW83: 回访人：赵星火，回访时间：2025-10-24 15:25，回访内容：本科学校和专业，现在在职想要明年考试，本科 目标院校和专业，想要政法大学法学，全日制的，法律非法，纪检监察学 就业，现在从事语言类的工作， 基本学情 四六级大学数学,之前考过英语一70， 学习时间分配 学习习惯，集体宿舍，教培行业 了解全年集训和半年集训跟进中，继续维护。；|回访人：赵星火，回访时间：2025-10-25 15:06，回访内容：给到联报优惠 大班 课程跟进中继续维护；|回访人：赵星火，回访时间：2025-10-27 15:39，回访内容：表示最近工作在忙，还要再确定一下，也问了具体研究方向，还有上岸情况给到信心；|回访人：赵星火，回访时间：2025-10-29 17:56，回访内容：给到报名优惠倒计时跟进学生情况中继续维护；|回访人：赵星火，回访时间：2025-10-31 16:23，回访内容：回访学生情况这边继续维护学生考虑跟进中；|回访人：赵星火，回访时间：2025-11-02 21:24，回访内容：系统自动签约 | BA83: 长期班 | BB83: 86565652 | BC83: 是 | BD83: 27考季 | BE83: 全年集训营 | BF83: 英语 | BG83: 其他 | BH83: 国内高校-双非 | BI83: 否 | BM83: 103528874 | BO83: 集团百度搜索-基木鱼-新媒体管家
A84: 26 | B84: 北京大学部 | C84: 国内大学部 | D84: 未知 | E84: 132181335 | F84: 张亚男 | G84: 2025-10-24 15:01:02 | H84: 渠道录入来源：集团百度搜索-基木鱼-新媒体管家 活动所属学校id：108 活动所属学校名称：北京大学事业部 统一活动id：2824107 统一活动名称：北京大学事业部25年10月百度搜索在线咨询 线索接收学校id：108 线索id：18be486027f8183461b1b1b59f78d55e 线索接收部门code：02 线索接收二级部门code：0201 渠道名称：网络营销-百度搜索-在线咨询 线索接收人邮箱：zhangyanan13@xdf.cn 备注：当前线索来源于百度搜索 账户ID：60103473 线索类型：咨询 留资时间：2025-10-24 14:52:10 流量渠道：百度-搜索推广 线索地域：北京 通话状态：未接通 搜索词：北京线下考研辅导机构哪家好 C端用户名称： 账号名称： 关键词：新东方考研机构价目表 站点名称：新东方考研专属客服 站点URL：https://ada.baidu.com/site/wjz2uk75/agent?imid=b9cc3f4ec469d744ef91d47374486c78 推广计划：新东方-考研 IP: 1.202.53.35 | I84: 2026财年第5财月集团百度搜索-基木鱼-新媒体管家 | J84: 未知 | K84: 赵星火 | L84: 线上运营-投放 | M84: 总部-百度投放 | Q84: 秋何故 | R84: 赵星火 | S84: 30548084 | T84: 正常工单 | U84: 2025-10-24 15:25 | V84: A（六个月内有报课意向工单） | W84: 考研集训营 | X84: 在职 | Y84: 北京第二外国语学院 | Z84: 英语学院 | AA84: 英语 | AB84: 秋何故 | AC84: 5664573 | AD84: 赵星火 | AE84: 2025-11-02 21:24 | AF84: 赵星火 | AG84: 2025-11-02 22:12 | AH84: 网课 | AI84: 84737872942 | AJ84: 2027考研政治全程班 早鸟4班,2027考研英语全程班 早鸟4班 | AK84: 国内考试 | AM84: 1809.4 | AP84: 新签 | AQ84: 无须交接 | AU84: 2025-11-02 | AW84: 回访人：赵星火，回访时间：2025-10-24 15:25，回访内容：本科学校和专业，现在在职想要明年考试，本科 目标院校和专业，想要政法大学法学，全日制的，法律非法，纪检监察学 就业，现在从事语言类的工作， 基本学情 四六级大学数学,之前考过英语一70， 学习时间分配 学习习惯，集体宿舍，教培行业 了解全年集训和半年集训跟进中，继续维护。；|回访人：赵星火，回访时间：2025-10-25 15:06，回访内容：给到联报优惠 大班 课程跟进中继续维护；|回访人：赵星火，回访时间：2025-10-27 15:39，回访内容：表示最近工作在忙，还要再确定一下，也问了具体研究方向，还有上岸情况给到信心；|回访人：赵星火，回访时间：2025-10-29 17:56，回访内容：给到报名优惠倒计时跟进学生情况中继续维护；|回访人：赵星火，回访时间：2025-10-31 16:23，回访内容：回访学生情况这边继续维护学生考虑跟进中；|回访人：赵星火，回访时间：2025-11-02 21:24，回访内容：系统自动签约 | BA84: 长期班,长期班 | BB84: 86565652 | BC84: 是 | BD84: 27考季 | BE84: 全年集训营 | BF84: 英语 | BG84: 其他 | BH84: 国内高校-双非 | BI84: 否 | BM84: 103528874 | BO84: 集团百度搜索-基木鱼-新媒体管家
A85: 117 | B85: 北京大学部 | C85: 国内大学部 | D85: 沈劲成 | E85: 133507822 | F85: 徐岩 | G85: 2025-11-05 15:08:02 | H85: 续费原因：续费 辛苦分配谭悦；该学生为保护期内续费，原顾问：国内大学部-谭悦(tanyue9@xdf.cn) | J85: 大二 | K85: 谭悦 | L85: 转介绍 | M85: 学管续费推荐 | N85: 徐岩xuyan91@xdf.cn | Q85: 沈劲成 | R85: 谭悦 | S85: 30664691 | T85: 续费工单 | U85: 2025-11-05 15:40 | V85: A（六个月内有报课意向工单） | W85: 六级,四级 | X85: 大二 | Y85: 河北医科大学 | Z85: 医学院 | AA85: 临床医学药物分析 | AB85: 沈劲成 | AC85: 5665945 | AD85: 谭悦 | AE85: 2025-11-05 18:43 | AF85: 谭悦 | AG85: 2025-11-05 19:09 | AH85: 四六级 | AI85: LP17623394251960 | AJ85: 六级一对一伴学班 | AK85: 国内考试 | AM85: 29500 | AO85: 徐岩 | AP85: 续班 | AQ85: 已交接 | AS85: XDF082122170236310 | AU85: 2025-11-05 | AW85: 回访人：谭悦，回访时间：2025-11-05 15:40，回访内容：续费一对一，跟进中 ；|回访人：谭悦，回访时间：2025-11-05 15:54，回访内容：续费；|回访人：谭悦，回访时间：2025-11-05 18:43，回访内容：系统自动签约 | BB85: 60134074 | BC85: 否 | BD85: 25下考季 | BE85: 四级一对一 | BH85: 国内高校-C9 | BI85: 是 | BN85: 本地人外地大学(归巢) | BO85: 学管续费推荐
A86: 118 | B86: 北京大学部 | C86: 国内大学部 | D86: 沈劲成 | E86: 133507822 | F86: 徐岩 | G86: 2025-11-05 15:08:02 | H86: 续费原因：续费 辛苦分配谭悦；该学生为保护期内续费，原顾问：国内大学部-谭悦(tanyue9@xdf.cn) | J86: 大二 | K86: 谭悦 | L86: 转介绍 | M86: 学管续费推荐 | N86: 徐岩xuyan91@xdf.cn | Q86: 沈劲成 | R86: 谭悦 | S86: 30664691 | T86: 续费工单 | U86: 2025-11-05 15:40 | V86: A（六个月内有报课意向工单） | W86: 六级,四级 | X86: 大二 | Y86: 河北医科大学 | Z86: 医学院 | AA86: 临床医学药物分析 | AB86: 沈劲成 | AC86: 5665945 | AD86: 谭悦 | AE86: 2025-11-05 18:43 | AF86: 谭悦 | AG86: 2025-11-05 19:09 | AH86: 四六级 | AI86: LP17623400011970 | AJ86: 六级一对一伴学班 | AK86: 国内考试 | AM86: 29500 | AO86: 徐岩 | AP86: 续班 | AQ86: 已交接 | AS86: XDF082122170236310 | AU86: 2025-11-05 | AW86: 回访人：谭悦，回访时间：2025-11-05 15:40，回访内容：续费一对一，跟进中 ；|回访人：谭悦，回访时间：2025-11-05 15:54，回访内容：续费；|回访人：谭悦，回访时间：2025-11-05 18:43，回访内容：系统自动签约 | BB86: 60134074 | BC86: 否 | BD86: 25下考季 | BE86: 四级一对一 | BH86: 国内高校-C9 | BI86: 是 | BN86: 本地人外地大学(归巢) | BO86: 学管续费推荐
A87: 19 | B87: 北京大学部 | C87: 国内大学部 | D87: 未知 | E87: 132801311 | F87: 吕猛 | G87: 2025-10-30 12:56:52 | H87: 考中传播音主持，咨询考研课程 渠道录入来源：大众点评 事件名称：400电话 大众点评门店名称：新东方考研四六级(中关村总部) 店铺绑定的校区：临时教学校区 店铺管理员邮箱：lvmeng2@xdf.cn 备注：2025-10-30 12:56:48,用户在大众点评新东方考研四六级(中关村总部)呼入400电话 已接 | I87: 2026财年第5财月大众点评在线咨询 | J87: 在职 | K87: 谭悦 | L87: 线上运营-本地生活平台 | M87: 大众点评 | Q87: 舒凌 | R87: 谭悦 | S87: 30635616 | T87: 正常工单 | U87: 2025-10-30 15:09 | V87: A（六个月内有报课意向工单） | W87: 线上考研产品 | X87: 在职 | Y87: 毕业/在职 | Z87: 在职 | AA87: 在职 | AB87: 舒凌 | AC87: 5666203 | AD87: 谭悦 | AE87: 2025-11-06 14:47 | AF87: 谭悦 | AG87: 2025-11-06 14:56 | AH87: 网课 | AI87: 01034781574 | AJ87: 2027考研政治直通车 长线4期,2027考研英语直通车 长线4期 | AK87: 国内考试 | AM87: 8781.4 | AP87: 新签 | AQ87: 无须交接 | AU87: 2025-11-06 | AW87: 回访人：谭悦，回访时间：2025-10-30 15:09，回访内容：自考本科，北影，演员，想考中传播音主持， 介绍了菁英，督学，无忧，学生自己凑钱报课，说攒三个月才能有8000块钱，要分期，问全程班淘宝只要一千多。 没有消费能力，12月才能攒到钱报名 ；|回访人：谭悦，回访时间：2025-11-06 14:40，回访内容：准备报英语政治网课 ；|回访人：谭悦，回访时间：2025-11-06 14:47，回访内容：系统自动签约 | BA87: 长期班,长期班 | BB87: 86787226 | BC87: 是 | BD87: 27考季 | BE87: 线上直通车 | BF87: 英语,政治 | BG87: 其他 | BH87: 国内高校-双非 | BI87: 否 | BM87: 111126639 | BO87: 新媒体管家-点评
A88: 14 | B88: 北京大学部 | C88: 国内大学部 | E88: 127719805 | G88: 2025-09-16 17:56:14 | H88: 咨询考研线课程，想到校区咨询 渠道录入来源：百度地图 事件名称：电话咨询 百度门店id：64751032 百度门店名称：新东方考研四六级（良乡大学城校区） 店铺绑定的学校id：108 店铺绑定的部门code：02 活动所属学校id：108 活动所属学校名称：北京大学事业部 统一活动id：2756755 统一活动名称：北京大学事业部25年9月百度地图电话咨询 渠道名称：网络营销-百度地图店铺-电话咨询 店铺管理员邮箱：lvmeng2@xdf.cn 备注：用户在【2025-09-16 17:54:02】从【百度地图】渠道拨打了店铺电话，电话【已接通】。来源页面：【https://aisite.wejianzhan.com/site/wjzavdcm/de49a8a9-51d7-4236-ade1-e9780d284a02】 | I88: 2026财年第4财月百度地图 | J88: 大三 | K88: 谭悦 | L88: 线上运营-本地生活平台 | M88: 百度地图 | Q88: 孙嘉珩 | R88: 谭悦 | S88: 30773971 | T88: 续费工单 | U88: 2025-11-10 19:49 | V88: A（六个月内有报课意向工单） | W88: 考研专业课,考研无忧计划 | X88: 大三 | Y88: 北京工商大学 | Z88: 计算机学院 | AA88: 计算机科学与技术 | AB88: 孙嘉珩 | AC88: 5694809 | AD88: 谭悦 | AE88: 2025-11-10 19:49 | AF88: 谭悦 | AG88: 2025-11-10 19:50 | AH88: 无忧 | AI88: WYC27103 | AJ88: 考研专业课无忧Pro优才走读班（27考研/408计算机） | AK88: 国内考试 | AM88: 9000 | AN88: 同科续费 | AP88: 续班 | AQ88: 无须交接 | AR88: BJWY2101498uW2 | AS88: BJWY6729478911 | AT88: WYC271030008 | AU88: 2025-11-07 | AW88: 回访人：谭悦，回访时间：2025-11-10 19:49，回访内容：1；|回访人：谭悦，回访时间：2025-11-10 19:49，回访内容：1 | BB88: 84997321 | BC88: 否 | BD88: 27考季 | BE88: 无忧计划-早鸟,考研专业课150 | BF88: 英语,政治,数学,计算机 | BH88: 国内高校-双非 | BI88: 否 | BL88: 转出 | BN88: 本地人本地大学(常规)
A89: 3 | B89: 北京大学部 | C89: 国内大学部 | D89: 孙彤 | E89: 136250209 | F89: 陈号东 | G89: 2025-12-01 10:20:06 | H89: 续费原因：学生续费公共课一对一；该学生为保护期内续费，原顾问：国内大学部-谭悦(tanyue9@xdf.cn) | J89: 大四 | K89: 谭悦 | L89: 转介绍 | M89: 学管续费推荐 | N89: 陈号东chenhaodong5@xdf.cn | Q89: 孙彤 | R89: 谭悦 | S89: 30920432 | T89: 续费工单 | U89: 2025-12-01 15:41 | V89: A（六个月内有报课意向工单） | W89: 考研VIP | X89: 大四 | Y89: 中国石油大学(北京) | Z89: 计算机 | AA89: 计算机 | AB89: 孙彤 | AC89: 5739210 | AD89: 谭悦 | AE89: 2025-12-01 16:07 | AF89: 谭悦 | AG89: 2025-12-01 16:29 | AH89: 个性化 | AI89: LP17645764426042 | AJ89: 考研专业课一对一伴学班（其他/26考季） | AK89: 国内考试 | AM89: 1400 | AO89: 陈号东 | AP89: 续班 | AQ89: 已交接 | AS89: BJWY1101020582 | AU89: 2025-12-01 | AW89: 回访人：谭悦，回访时间：2025-12-01 15:41，回访内容：1；|回访人：谭悦，回访时间：2025-12-01 16:07，回访内容：系统自动签约 | BB89: 60533082 | BC89: 否 | BD89: 26考季 | BE89: VIP - 伴学 | BF89: 英语 | BG89: 其他 | BH89: 国内高校-211 | BI89: 是 | BN89: 本地人本地大学(常规) | BO89: 学管续费推荐
A90: 4 | B90: 北京大学部 | C90: 国内大学部 | D90: 孙彤 | E90: 136250209 | F90: 陈号东 | G90: 2025-12-01 10:20:06 | H90: 续费原因：学生续费公共课一对一；该学生为保护期内续费，原顾问：国内大学部-谭悦(tanyue9@xdf.cn) | J90: 大四 | K90: 谭悦 | L90: 转介绍 | M90: 学管续费推荐 | N90: 陈号东chenhaodong5@xdf.cn | Q90: 孙彤 | R90: 谭悦 | S90: 30920432 | T90: 续费工单 | U90: 2025-12-01 15:41 | V90: A（六个月内有报课意向工单） | W90: 考研VIP | X90: 大四 | Y90: 中国石油大学(北京) | Z90: 计算机 | AA90: 计算机 | AB90: 孙彤 | AC90: 5739210 | AD90: 谭悦 | AE90: 2025-12-01 16:07 | AF90: 谭悦 | AG90: 2025-12-01 16:29 | AH90: 无忧 | AI90: LP17645764416040 | AJ90: 26考研一对一伴学（定制/无忧） | AK90: 国内考试 | AM90: 7200 | AO90: 陈号东 | AP90: 续班 | AQ90: 已交接 | AS90: BJWY1101020582 | AU90: 2025-12-01 | AW90: 回访人：谭悦，回访时间：2025-12-01 15:41，回访内容：1；|回访人：谭悦，回访时间：2025-12-01 16:07，回访内容：系统自动签约 | BB90: 60533082 | BC90: 否 | BD90: 26考季 | BE90: VIP - 伴学 | BF90: 英语 | BG90: 其他 | BH90: 国内高校-211 | BI90: 是 | BN90: 本地人本地大学(常规) | BO90: 学管续费推荐
A91: 34 | B91: 北京大学部 | C91: 国内大学部 | E91: 130402259 | G91: 2025-10-12 17:41:21 | H91: 续费原因：学生续费一对一；该学生为保护期内续费，原顾问：国内大学部-谭悦(tanyue9@xdf.cn) | J91: 大四 | K91: 谭悦 | L91: 转介绍 | M91: 学管续费推荐 | Q91: 孙彤 | R91: 谭悦 | S91: 30690803 | T91: 续费工单 | U91: 2025-11-05 16:45 | V91: A（六个月内有报课意向工单） | W91: 考研VIP | X91: 大四 | Y91: 中国石油大学(北京) | Z91: 计算机 | AA91: 计算机 | AB91: 孙彤 | AC91: 5691935 | AD91: 谭悦 | AE91: 2025-11-05 16:45 | AF91: 系统管理员 | AG91: 2025-11-05 16:45 | AH91: 无忧 | AI91: LP17612921611105 | AJ91: 26考研一对一伴学（20h定制/无忧） | AM91: -4500 | AQ91: 未交接 | AS91: BJWY1101020582 | AU91: 2025-11-05 | AW91: 回访人：系统管理员，回访时间：2025-11-05 16:45，回访内容：学生转产品转入，创建续费工单。 | BB91: 60533082 | BC91: 否 | BD91: 26考季 | BE91: VIP - 伴学 | BF91: 英语,政治,数学 | BH91: 国内高校-211 | BI91: 否
A92: 35 | B92: 北京大学部 | C92: 国内大学部 | E92: 130402259 | G92: 2025-10-12 17:41:21 | H92: 续费原因：学生续费一对一；该学生为保护期内续费，原顾问：国内大学部-谭悦(tanyue9@xdf.cn) | J92: 大四 | K92: 谭悦 | L92: 转介绍 | M92: 学管续费推荐 | Q92: 孙彤 | R92: 谭悦 | S92: 30690803 | T92: 续费工单 | U92: 2025-11-05 16:45 | V92: A（六个月内有报课意向工单） | W92: 考研VIP | X92: 大四 | Y92: 中国石油大学(北京) | Z92: 计算机 | AA92: 计算机 | AB92: 孙彤 | AC92: 5691935 | AD92: 谭悦 | AE92: 2025-11-05 16:45 | AF92: 系统管理员 | AG92: 2025-11-05 16:45 | AH92: 无忧 | AI92: LP17623319811465 | AJ92: 考研初试专业课一对一（26考研/无忧） | AM92: 4200 | AQ92: 未交接 | AS92: BJWY1101020582 | AU92: 2025-11-05 | AW92: 回访人：系统管理员，回访时间：2025-11-05 16:45，回访内容：学生转产品转入，创建续费工单。 | BB92: 60533082 | BC92: 否 | BD92: 26考季 | BE92: VIP - 伴学 | BF92: 英语,政治,数学 | BH92: 国内高校-211 | BI92: 否
A93: 41 | B93: 北京大学部 | C93: 国内大学部 | D93: 孙仲余 | E93: 135563350 | F93: 郝琨 | G93: 2025-11-24 14:37:48 | H93: 续费原因：学生续费一对一；该学生为保护期内续费，原顾问：国内大学部-赵星火(zhaoxinghuo@xdf.cn) | J93: 大四 | K93: 赵星火 | L93: 转介绍 | M93: 学管续费推荐 | N93: 郝琨haokun@xdf.cn | Q93: 孙仲余 | R93: 赵星火 | S93: 30896188 | T93: 续费工单 | U93: 2025-11-25 15:43 | V93: A（六个月内有报课意向工单） | W93: 考研专业课 | X93: 大四 | Y93: 中国农业大学 | Z93: 经济管理学院 | AA93: 国际经济与贸易 | AB93: 孙仲余 | AC93: 5713623 | AD93: 赵星火 | AE93: 2025-12-02 11:05 | AF93: 赵星火 | AG93: 2025-12-02 11:08 | AH93: 无忧 | AI93: LP1764644728420 | AJ93: 26考研一对一伴学（无忧） | AK93: 国内考试 | AM93: 10700 | AO93: 郝琨 | AP93: 续班 | AQ93: 已交接 | AS93: XDF112220010736709 | AU93: 2025-12-02 | AW93: 回访人：赵星火，回访时间：2025-11-25 15:43，回访内容：想要政治专业课的这些主观题辅导跟进学生师资看下情况；|回访人：赵星火，回访时间：2025-11-27 16:31，回访内容：要试一次课程，没问题再续费跟进中继续维护。；|回访人：赵星火，回访时间：2025-12-02 11:05，回访内容：系统自动签约 | BB93: 51610475 | BC93: 否 | BD93: 26考季 | BE93: 考研专业课150 | BF93: 英语 | BG93: 其他 | BH93: 国内高校-985 | BI93: 是 | BN93: 本地人本地大学(常规) | BO93: 学管续费推荐
A94: 1 | B94: 北京大学部 | C94: 国内大学部 | D94: 塔娜 | E94: 136246961 | F94: 陈晶 | G94: 2025-12-01 09:32:56 | H94: 续费原因：直接联系学生报4小时非定制课程即可，个性化；该学生为保护期内续费，原顾问：国内大学部-赵星火(zhaoxinghuo@xdf.cn) | J94: 大四 | K94: 赵星火 | L94: 转介绍 | M94: 学管续费推荐 | N94: 陈晶chenjing171@xdf.cn | Q94: 塔娜 | R94: 赵星火 | S94: 30919535 | T94: 续费工单 | U94: 2025-12-01 12:54 | V94: A（六个月内有报课意向工单） | W94: 考研VIP | X94: 大四 | Y94: 中国地质大学(北京) | Z94: 资勘 | AA94: 资勘 | AB94: 塔娜 | AC94: 5739515 | AD94: 赵星火 | AE94: 2025-12-02 14:06 | AF94: 赵星火 | AG94: 2025-12-02 14:07 | AH94: 个性化 | AI94: LP17646555731273 | AJ94: 考研一对一伴学班（26考季） | AK94: 国内考试 | AM94: 3400 | AO94: 陈晶 | AP94: 续班 | AQ94: 已交接 | AS94: BJWY0438533775 | AU94: 2025-12-02 | AW94: 回访人：赵星火，回访时间：2025-12-01 12:54，回访内容：续费；|回访人：赵星火，回访时间：2025-12-01 18:56，回访内容：已发订单；|回访人：赵星火，回访时间：2025-12-02 14:06，回访内容：系统自动签约 | BB94: 85923249 | BC94: 否 | BD94: 26考季 | BE94: VIP - 伴学 | BF94: 英语 | BG94: 其他 | BH94: 国内高校-211 | BI94: 是 | BN94: 本地人本地大学(常规) | BO94: 学管续费推荐
A95: 51 | B95: 北京大学部 | C95: 国内大学部 | D95: 唐欣 | E95: 135756822 | F95: 陈晶 | G95: 2025-11-26 11:51:35 | H95: 续费原因：续费，个性化；该学生为保护期内续费，原顾问：国内大学部-赵星火(zhaoxinghuo@xdf.cn) | J95: 在职 | K95: 赵星火 | L95: 转介绍 | M95: 学管续费推荐 | N95: 陈晶chenjing171@xdf.cn | Q95: 唐欣 | R95: 赵星火 | S95: 30801397 | T95: 续费工单 | U95: 2025-11-26 14:08 | V95: A（六个月内有报课意向工单） | W95: 考研VIP | X95: 在职 | Y95: 中国人民大学 | Z95: 马克思主义学院 | AA95: 中国共产党历史 | AB95: 唐欣 | AC95: 5577456 | AD95: 赵星火 | AE95: 2025-11-26 14:22 | AF95: 赵星火 | AG95: 2025-11-26 14:22 | AH95: 个性化 | AI95: LP17641381251250 | AJ95: 考研一对一伴学班（26考季） | AK95: 国内考试 | AM95: 1800 | AO95: 陈晶 | AP95: 续班 | AQ95: 已交接 | AS95: BJWY1667668404 | AU95: 2025-11-26 | AW95: 回访人：赵星火，回访时间：2025-11-26 14:08，回访内容：1；|回访人：赵星火，回访时间：2025-11-26 14:22，回访内容：系统自动签约 | BB95: 87883690 | BC95: 否 | BD95: 26考季 | BE95: VIP - 伴学 | BF95: 政治 | BG95: 其他 | BH95: 国内高校-985 | BI95: 是 | BO95: 学管续费推荐
A96: 55 | B96: 北京大学部 | C96: 国内大学部 | D96: 北京市7352 | E96: 135571041 | F96: 杨俊42(国内) | G96: 2025-11-24 17:26:21 | H96: 渠道录入来源：新东方PC官网-客服 意向城市：北京访客省/城市：北京市 访客静态ID：01000000034659397621681165517352 接待分组ID：70447 搜索引擎： 搜索词： 关键词： 设备类型：phone 访客IP：120.245.66.93 对话详细内容：AI-Lbo0rDBXCyBY 2025-11-24 17:23:38_x000D_ 您好同学,欢迎访问北京新东方考研四六级中心. 考研线下课程26/27考季【考研全年集训营】【考研半年集训营】【考研全科线下走读班】【考研寒/暑假集训营】【考研一对一】【考研专业课】【四/六级课程】，热门课程火热报名中,咨询即可领取专享优惠。 **【考研全年集训营】=ff761f# **【考研半年集训营】=ff6b6b# **【考研全科线下走读班】=ffc158# **【考研寒/暑假集训营】=ffc158# **【考研一对一】=ff761f# **【考研专业课】=ff6caa# **【四/六级课程】=ff6caa# **【考研冲刺班】=60e27e#_x000D_ _x000D_ AI-Lbo0rDBXCyBY 2025-11-24 17:23:41_x000D_ 您是想咨询【线下课程】【线上课程】【考研规划】还是【在职考研】呢？**【线下课程】# **【线上课程】#**【考研规划】#**【在职考研】#_x000D_ _x000D_ 01000000034659397621681165517352 2025-11-24 17:23:44_x000D_ 【考研一对一】_x000D_ _x000D_ AI-Lbo0rDBXCyBY 2025-11-24 17:23:47_x000D_ 同学，你现在是在校还是在职呢？_x000D_ _x000D_ 01000000034659397621681165517352 2025-11-24 17:23:48_x000D_ 【线上课程】_x000D_ _x000D_ AI-Lbo0rDBXCyBY 2025-11-24 17:23:51_x000D_ 具体是想报考什么学校和专业呢？_x000D_ _x000D_ 01000000034659397621681165517352 2025-11-24 17:24:05_x000D_ 在职 需要一对一政治老师_x000D_ _x000D_ AI-Lbo0rDBXCyBY 2025-11-24 17:24:08_x000D_ 好的，我这边安排专业老师给您回电，详细沟通一下，请问您的电话是多少呢？_x000D_ _x000D_ 01000000034659397621681165517352 2025-11-24 17:24:18_x000D_ 13522721802_x000D_ _x000D_ AI-Lbo0rDBXCyBY 2025-11-24 17:24:22_x000D_ 好的，确认一下你的号码是否正确呢~_x000D_ _x000D_ 01000000034659397621681165517352 2025-11-24 17:24:32_x000D_ 正确_x000D_ _x000D_ AI-Lbo0rDBXCyBY 2025-11-24 17:24:35_x000D_ 同学怎么称呼呢？_x000D_ _x000D_ 01000000034659397621681165517352 2025-11-24 17:24:51_x000D_ 唐女士_x000D_ _x000D_ AI-Lbo0rDBXCyBY 2025-11-24 17:24:54_x000D_ 这边马上安排顾问老师联系您，预计半个小时左右给您回电请注意接听~_x000D_ _x000D_ 来源页：https://kaoyan.xdf.cn/ 备注： | I96: 2026财年第6财月易聊新东方PC官网 | K96: 曹健 | L96: 新东方官网 | M96: 新东方PC官网 | O96: 曹健 | P96: 2025-11-24 17:38:13 | Q96: 唐欣 | R96: 赵星火 | S96: 30869032 | T96: 正常工单 | U96: 2025-11-24 17:56 | V96: A（六个月内有报课意向工单） | W96: 考研VIP | X96: 在职 | Y96: 中国人民大学 | Z96: 马克思主义学院 | AA96: 中国共产党历史 | AB96: 唐欣 | AC96: 5707971 | AD96: 赵星火 | AE96: 2025-11-24 18:51 | AF96: 赵星火 | AG96: 2025-11-24 18:52 | AH96: 个性化 | AI96: LP17639814851108 | AJ96: 考研一对一伴学班（26考季） | AK96: 国内考试 | AM96: 1800 | AP96: 新签 | AQ96: 已交接 | AS96: BJWY1667668404 | AU96: 2025-11-24 | AW96: 回访人：赵星火，回访时间：2025-11-24 17:56，回访内容：不想要两小时，然后主观题需要老师有经验的，建议试听一次课的；|回访人：赵星火，回访时间：2025-11-24 18:51，回访内容：系统自动签约 | BB96: 87883690 | BC96: 否 | BD96: 26考季 | BE96: VIP - 伴学 | BF96: 政治 | BG96: 其他 | BH96: 国内高校-985 | BI96: 是 | BO96: 易聊在线咨询
A97: 87 | B97: 北京大学部 | C97: 国内大学部 | D97: 25 | E97: 134577369 | F97: 崔佳慧 | G97: 2025-11-14 20:36:06 | H97: 渠道录入来源：小红书 事件名称：私信留资 小红书账号id：659bd1020000000022000003 小红书账号名称：北京新东方考研一对一咨询 广告投放账号名称：北京新东方考研一对一咨询 活动所属学校id：108 活动所属学校名称：北京大学事业部 统一活动id：2896637 统一活动名称：北京大学事业部25年11月小红书专业号投放 渠道名称：网络营销-小红书-专业号投放 线索创建人邮箱：cuijiahui2@xdf.cn 资源跟进人邮箱：cuijiahui2@xdf.cn 备注：用户地区是【北京市北京市】，在【2025-11-14 20:34:05】留资，私信通线索标签为【留客资】，来源于【北京新东方考研一对一咨询】投放账户，意向项目是【考研/考博】，留资笔记是【】，备注【-】 | I97: 2026财年第6财月小红书 | J97: 未知 | K97: 谭悦 | L97: 线上运营-小红书 | M97: 小红书 | Q97: 陶雪婷 | R97: 谭悦 | S97: 30782672 | T97: 正常工单 | U97: 2025-11-15 15:49 | V97: A（六个月内有报课意向工单） | W97: 考研VIP | X97: 大四 | Y97: 北京科技大学 | Z97: 土木与资源工程学院 | AA97: 采矿工程 | AB97: 陶雪婷 | AC97: 5702637 | AD97: 谭悦 | AE97: 2025-11-15 20:57 | AF97: 谭悦 | AG97: 2025-11-15 22:19 | AH97: 个性化 | AI97: LP17632114193282 | AJ97: 考研一对一伴学班（26考季） | AK97: 国内考试 | AM97: 9000 | AP97: 新签 | AQ97: 已交接 | AS97: BJWY6033725486 | AU97: 2025-11-15 | AW97: 回访人：谭悦，回访时间：2025-11-15 15:49，回访内容：考虑报英语二一对一 ；|回访人：谭悦，回访时间：2025-11-15 20:57，回访内容：系统自动签约 | BB97: 87452223 | BC97: 否 | BD97: 26考季 | BE97: VIP - 伴学 | BF97: 英语 | BG97: 其他 | BH97: 国内高校-211 | BI97: 是 | BN97: 本地人本地大学(常规) | BO97: 小红书
A98: 94 | B98: 北京大学部 | C98: 国内大学部 | D98: 家长 | E98: 133555234 | F98: 吕猛 | G98: 2025-11-06 11:49:59 | H98: 在去花园桥校区的路上，开车前往，30分左右到，尽快联系 | J98: 大三 | K98: 王志远 | L98: 线上运营-本地生活平台 | M98: 大众点评 | Q98: 田羽歆 | R98: 王志远 | S98: 30668221 | T98: 正常工单 | U98: 2025-11-06 12:31 | V98: A（六个月内有报课意向工单） | W98: 考研集训营,考研无忧计划,线上考研产品 | X98: 大三 | Y98: 北京工商大学 | Z98: 商学院 | AA98: 财务管理 | AB98: 田羽歆 | AC98: 5573912 | AD98: 李涛 | AE98: 2025-11-13 10:55 | AF98: 王志远 | AG98: 2025-11-13 11:09 | AH98: 无忧 | AK98: 国内考试 | AM98: 16150 | AP98: 分单 | AQ98: 已交接 | AS98: XDF1557036491 | AW98: 回访人：王志远，回访时间：2025-11-06 12:31，回访内容：直访花园桥校区，李涛老师接待；|回访人：王志远，回访时间：2025-11-07 18:00，回访内容：花园桥直访，李涛代接待，规划的是无忧早鸟全科和少量一对一，今天微信消息未回复，周六电话联系~；|回访人：王志远，回访时间：2025-11-08 18:37，回访内容：花园桥直访，李涛代接待，规划的是无忧早鸟全科，两边同时跟进，同步了定金膨胀的活动，询问一下意向；|回访人：王志远，回访时间：2025-11-10 18:36，回访内容：李涛代接待，咨询后就失联，现在两边联系都无人回应，判其“死”；|回访人：王志远，回访时间：2025-11-13 10:55，回访内容：报名签约 | BB98: 44433929 | BC98: 否 | BD98: 27考季 | BE98: 无忧计划-早鸟,寒暑假集训营（春秋OMO） | BF98: 英语,政治 | BG98: 教育 | BH98: 国内高校-双非 | BI98: 否 | BN98: 本地人本地大学(常规) | BO98: 市场
A99: 61 | B99: 北京大学部 | C99: 国内大学部 | D99: 王浩儒 | E99: 135461435 | F99: 陈晶 | G99: 2025-11-22 18:26:54 | H99: 续费原因：续费，个性化；该学生为保护期内续费，原顾问：国内大学部-谭悦(tanyue9@xdf.cn) | J99: 大四 | K99: 谭悦 | L99: 转介绍 | M99: 学管续费推荐 | N99: 陈晶chenjing171@xdf.cn | Q99: 王浩儒 | R99: 谭悦 | S99: 30831401 | T99: 续费工单 | U99: 2025-11-22 18:44 | V99: A（六个月内有报课意向工单） | W99: 考研VIP | X99: 大四 | Y99: 北方工业大学 | Z99: 信息学院 | AA99: 计算机科学与技术 | AB99: 王浩儒 | AC99: 5733033 | AD99: 谭悦 | AE99: 2025-11-23 14:50 | AF99: 谭悦 | AG99: 2025-11-23 16:41 | AH99: 个性化 | AI99: LP17638806041652 | AJ99: 考研一对一伴学班（26考季） | AK99: 国内考试 | AM99: 7800 | AO99: 陈晶 | AP99: 续班 | AQ99: 已交接 | AS99: BJWY2816785503 | AU99: 2025-11-23 | AW99: 回访人：谭悦，回访时间：2025-11-22 18:44，回访内容：1；|回访人：谭悦，回访时间：2025-11-23 14:50，回访内容：系统自动签约 | BB99: 59931709 | BC99: 否 | BD99: 26考季 | BE99: VIP - 伴学 | BF99: 英语 | BG99: 其他 | BH99: 国内高校-双非 | BI99: 是 | BN99: 本地人本地大学(常规) | BO99: 学管续费推荐
A100: 68 | B100: 北京大学部 | C100: 国内大学部 | D100: 同学 | E100: 132634051 | F100: 段同飞 | G100: 2025-10-29 11:16:33 | J100: 未知 | K100: 赵星火 | L100: 线上运营-商务合作 | M100: 91好学校 | Q100: 王妍 | R100: 赵星火 | S100: 30602952 | T100: 正常工单 | U100: 2025-10-29 11:22 | V100: A（六个月内有报课意向工单） | W100: 考研VIP | X100: 大四 | Y100: 首都师范大学 | Z100: 文学院 | AA100: 英语语言文学 | AB100: 王妍 | AC100: 5576125 | AD100: 赵星火 | AE100: 2025-11-21 15:33 | AF100: 赵星火 | AG100: 2025-11-21 15:36 | AH100: 个性化 | AI100: LP17637103981436 | AJ100: 考研一对一伴学班（定制/26考季） | AK100: 国内考试 | AM100: 11500 | AP100: 新签 | AQ100: 已交接 | AS100: BJWY8603201784 | AU100: 2025-11-21 | AW100: 回访人：赵星火，回访时间：2025-11-12 16:43，回访内容：回访学生情况这边看下到京时间跟进中；|回访人：赵星火，回访时间：2025-11-15 17:17，回访内容：电话呼出联系不上学生微信没回复这边跟进中。；|回访人：赵星火，回访时间：2025-11-20 18:40，回访内容：表示还没确定下来 后面需要再联系；|回访人：赵星火，回访时间：2025-11-21 15:33，回访内容：系统自动签约 | BB100: 74100131 | BC100: 否 | BD100: 26考季 | BE100: VIP - 伴学 | BF100: 英语 | BG100: 其他 | BH100: 国内高校-中外合作办学 | BI100: 是 | BN100: 外地人本地大学(常规) | BO100: 客服
A101: 69 | B101: 北京大学部 | C101: 国内大学部 | D101: 王仪阳 | E101: 135126353 | F101: 郑雪新 | G101: 2025-11-19 20:19:23 | H101: 续费原因：集训营续费；该学生为保护期内续费，原顾问：国内大学部-谭悦(tanyue9@xdf.cn) | J101: 大四 | K101: 谭悦 | L101: 转介绍 | M101: 学管续费推荐 | N101: 郑雪新zhengxuexin@xdf.cn | Q101: 王仪阳 | R101: 谭悦 | S101: 30846665 | T101: 续费工单 | U101: 2025-11-20 18:07 | V101: A（六个月内有报课意向工单） | W101: 考研VIP | X101: 大四 | Y101: 南京传媒学院 | Z101: 戏剧影视学院 | AA101: 戏剧影视导演 | AB101: 王仪阳 | AC101: 5731484 | AD101: 谭悦 | AE101: 2025-11-20 18:18 | AF101: 谭悦 | AG101: 2025-11-20 18:32 | AH101: 集训 | AI101: LP17636339302456 | AJ101: 26考研一对一伴学（定制/集训） | AK101: 国内考试 | AM101: 4800 | AO101: 郑雪新 | AP101: 续班 | AQ101: 已交接 | AS101: BJWY6088825240 | AU101: 2025-11-20 | AW101: 回访人：谭悦，回访时间：2025-11-20 18:07，回访内容：1；|回访人：谭悦，回访时间：2025-11-20 18:18，回访内容：系统自动签约 | BB101: 61991830 | BC101: 否 | BD101: 26考季 | BE101: VIP - 伴学 | BF101: 英语 | BG101: 其他 | BH101: 国内高校-双非 | BI101: 是 | BN101: 外地人外地大学(常规) | BO101: 学管续费推荐
A102: 80 | B102: 北京大学部 | C102: 国内大学部 | D102: 重庆市5958 | E102: 134690484 | F102: 杨俊42(国内) | G102: 2025-11-16 10:41:10 | H102: 渠道录入来源：新东方PC官网-客服 意向城市：北京访客省/城市：重庆市 访客静态ID：01000003465900326063551590405958 接待分组ID：70447 搜索引擎： 搜索词： 关键词： 设备类型：phone 访客IP：111.55.209.122 对话详细内容：AI-Lbo0rDBXCyBY 2025-11-16 10:37:17_x000D_ 您好同学,欢迎访问北京新东方考研四六级中心. 考研线下课程26/27考季【考研全年集训营】【考研半年集训营】【考研全科线下走读班】【考研寒/暑假集训营】【考研一对一】【考研专业课】【四/六级课程】，热门课程火热报名中,咨询即可领取专享优惠。 **【考研全年集训营】=ff761f# **【考研半年集训营】=ff6b6b# **【考研全科线下走读班】=ffc158# **【考研寒/暑假集训营】=ffc158# **【考研一对一】=ff761f# **【考研专业课】=ff6caa# **【四/六级课程】=ff6caa# **【考研冲刺班】=60e27e#_x000D_ _x000D_ AI-Lbo0rDBXCyBY 2025-11-16 10:37:20_x000D_ 您是想咨询【线下课程】【线上课程】【考研规划】还是【在职考研】呢？**【线下课程】# **【线上课程】#**【考研规划】#**【在职考研】#_x000D_ _x000D_ 01000003465900326063551590405958 2025-11-16 10:37:32_x000D_ 【线上课程】_x000D_ _x000D_ AI-Lbo0rDBXCyBY 2025-11-16 10:37:36_x000D_ 同学，你现在是在校还是在职呢？_x000D_ _x000D_ 01000003465900326063551590405958 2025-11-16 10:37:58_x000D_ 在校_x000D_ _x000D_ AI-Lbo0rDBXCyBY 2025-11-16 10:38:02_x000D_ 具体是想报考什么学校和专业呢？_x000D_ _x000D_ AI-Lbo0rDBXCyBY 2025-11-16 10:38:39_x000D_ 您好，能看到我的对话吗？如有疑问，可以在此留电咨询！_x000D_ _x000D_ 01000003465900326063551590405958 2025-11-16 10:38:49_x000D_ 中国政法大学，法学专业_x000D_ _x000D_ AI-Lbo0rDBXCyBY 2025-11-16 10:38:52_x000D_ 好的，我这边安排专业老师给您回电，详细沟通一下，请问您的电话是多少呢？_x000D_ _x000D_ 01000003465900326063551590405958 2025-11-16 10:39:08_x000D_ 15889686058_x000D_ _x000D_ AI-Lbo0rDBXCyBY 2025-11-16 10:39:12_x000D_ 好的，确认一下你的号码是否正确呢~_x000D_ _x000D_ 01000003465900326063551590405958 2025-11-16 10:39:24_x000D_ 正确_x000D_ _x000D_ AI-Lbo0rDBXCyBY 2025-11-16 10:39:27_x000D_ 同学怎么称呼呢？_x000D_ _x000D_ 01000003465900326063551590405958 2025-11-16 10:39:35_x000D_ 文_x000D_ _x000D_ AI-Lbo0rDBXCyBY 2025-11-16 10:39:39_x000D_ 这边马上安排顾问老师联系您，预计半个小时左右给您回电请注意接听~_x000D_ _x000D_ 01000003465900326063551590405958 2025-11-16 10:39:51_x000D_ 好的，谢谢_x000D_ _x000D_ AI-Lbo0rDBXCyBY 2025-11-16 10:39:54_x000D_ 好的，这个也是您的微信号吗？_x000D_ _x000D_ 01000003465900326063551590405958 2025-11-16 10:40:01_x000D_ 是的_x000D_ _x000D_ AI-Lbo0rDBXCyBY 2025-11-16 10:40:05_x000D_ 稍后老师会联系哈_x000D_ _x000D_ 01000003465900326063551590405958 2025-11-16 10:40:12_x000D_ 好的_x000D_ _x000D_ AI-Lbo0rDBXCyBY 2025-11-16 10:40:15_x000D_ 嗯嗯_x000D_ _x000D_ 来源页：https://m.xdf.cn/city/110100?binded=false 备注： | I102: 2026财年第6财月易聊新东方PC官网 | K102: 曹健 | L102: 新东方官网 | M102: 新东方PC官网 | O102: 曹健 | P102: 2025-11-16 11:03:02 | Q102: 文丰裕 | R102: 谭悦 | S102: 30768413 | T102: 正常工单 | U102: 2025-11-16 11:40 | V102: A（六个月内有报课意向工单） | W102: 考研专业课 | X102: 大二 | Y102: 中国政法大学 | Z102: 法学院 | AA102: 法学（法学人才培养模式改革实验班） | AB102: 文丰裕 | AC102: 5729855 | AD102: 谭悦 | AE102: 2025-11-17 20:56 | AF102: 谭悦 | AG102: 2025-11-17 21:03 | AH102: 个性化 | AI102: LP17633841631342 | AJ102: 考研初试专业课一对一伴学班（法硕-26考季） | AK102: 国内考试 | AM102: 10300 | AP102: 新签 | AQ102: 已交接 | AS102: BJWY6517078363 | AU102: 2025-11-17 | AW102: 回访人：谭悦，回访时间：2025-11-16 11:40，回访内容：中国政法，大二，香港留学和国内考研两手准备，咨询期末考试和科研论文 ；|回访人：谭悦，回访时间：2025-11-17 18:51，回访内容：打算报名专业课 ；|回访人：谭悦，回访时间：2025-11-17 20:56，回访内容：系统自动签约 | BB102: 87535475 | BC102: 否 | BD102: 26考季 | BE102: 考研专业课150 | BF102: 专业课150 | BG102: 其他 | BH102: 国内高校-211 | BI102: 是 | BN102: 本地人本地大学(常规) | BO102: 易聊在线咨询
...

Sheet 退费明细
A1: 提交日期 | B1: OA流水号 | C1: 学管姓名 | D1: 学管是否代办 | E1: 顾问姓名 | F1: 顾问是否代办 | G1: 91系统-最新报名二级渠道 | H1: 原班所属项目 | I1: 新报入班级所属项目 | J1: 退费阶段 | K1: 退费一级原因（开课前） | L1: 退费一级原因 (开课后) | M1: 退费二级原因（专业课师资匹配原因） | N1: 退费二级原因（学员意愿转变_开课后） | O1: 退费三级原因（完全匹配不上）-院校、学院、专业、专业课代码及名称 | P1: 退费详细原因说明（与OA退费详细说明保持一致） | Q1: 预计报名新班学费金额 | R1: 转班金额（请学管填写所在班级实际金额） | S1: 转班详细原因说明 | T1: 提交时间 | U1: 学校 | V1: 学院 | W1: 年级 | X1: 专业 | Y1: 您所办理的业务类型 | Z1: 提交人 | AA1: 退费类型 | AB1: 学员姓名 | AC1: 学员编码 | AD1: 退费金额 | AE1: 办理日期-客服 | AF1: 退费方式-客服 | AG1: 需要跟进的顾问/学管 | AH1: 退费/转班特殊情况备注（若需要学管提供银行卡信息，可将需求填写在此处）-客服 | AI1: 是否完成退费/转班-客服 | AJ1: 父记录 | AK1: 父记录
A2: 2025/11/03 | B2: 2025110300814 | C2: 葛铭 | E2: 李涛48 | G2: 小红书 | H2: 无忧项目-VIP | I2: VIP项目 | J2: 开课前退费 | K2: 中心原因_开课前 | P2: 学员退出改报一对一督学 | Q2: ¥80000.00 | T2: 2025-11-03 | U2: 北京信息科技大学 | V2: 计算机 | W2: 大三 | X2: 计算机技术 | Y2: 退费 | Z2: 葛铭 | AA2: 转项目/转班/退出重报等未产生实际退费 | AB2: 陈靓怡 | AC2: BJWY7173848231 | AD2: 80000 | AE2: 2025/11/04 | AF2: 11.4，退回账户余额 11.4未办理，oa未到前台@葛铭@李涛48 (李涛) [图片] | AI2: TRUE
A3: 2025/11/11 | B3: 2025110402621 | C3: 王天义56 | E3: 李涛48 | G3: 新东方PC官网 | H3: VIP项目-专业课 | J3: 开课后退费 | L3: 学员意愿转变_开课后 | N3: 认为课程用处不大/不适合自己 | P3: 退费原因：1、学生觉得信息差导致焦虑报名课程，研究生第一次授课后学员觉得溢价，并提到“经过学长提点”；2、学院家庭条件不太富裕；3、目标院校的学习通上可以下载专业课的知识点，并从二手群收购资料。引导学生专业课的复习不光是知识点的掌握，更是结合时政热点，学长手里也有实时的解题思路、模板和规划，会节约复习时间等，学生坚持退费。 退费金额：报名金额-课消金额-研究生匹配费=18800-2*700-500=16900元 | T3: 2025-11-11 | U3: 上海交通大学 | V3: 经济学院 | W3: 2022 | X3: 金融学 | Y3: 退费 | Z3: 王天义56 | AA3: 真实产生的退费 | AB3: 熊新 | AC3: BJWY2441731275 | AD3: 16900 | AE3: 2025/11/13 | AF3: 11.13支付宝退回16900———————— 11.12未办理：未查询到顾问的挽单记录@王天义56 (王天义) | AI3: TRUE
AD4: =SUM(AD2:AD3) -> 96900
A5: 2025/10/30 | B5: 18967906 | C5: 余韵7 | E5: 谭悦9 | G5: 大众点评 | H5: 无忧项目-班课 | J5: 开课后退费 | L5: 学员意愿转变_开课后 | N5: 认为课程用处不大/不适合自己 | P5: 学生姓名：许凯贤 学员编号：BJWY0058842315 报名班级：无忧英语政治 报名手机号：18611288017 考勤截至日期：10月19号 实际课消：英语2次课共4课时 退费明细：资料费用68.2元 其中已开课班次WYE27019退4184-（2/108）*21800-68.2元=3712.1元 其他未开课班次WYP27016，WYP27017，WYP27018，WYE27022，WYE27023退23116元 总退费金额：3712.1+23116=26828.1元 | T5: 2025-10-30 | U5: 首都体育学院 | V5: 体育教育训练学院 | W5: 在职 | X5: 体育教育 | Y5: 退费 | Z5: 余韵7 | AA5: 真实产生的退费 | AB5: 许凯贤 | AC5: BJWY0058842315 | AD5: 0 | AE5: 2025/11/01 | AF5: 11.11退款已到账 11.11已确认，退款中 [图片] 11.10已转手工（26828.1已经申请提现，务必提醒学生进入短信链接确认（注意不是短信回复验证码），自确认之日起7-15个工作日到账。）：@余韵7 (余韵) 户 名：许凯贤 卡 号：6214680096962319 开户行：北京银行中关村石景山园支行 11.9银联扫码退款失败 11.8头寸不足，退回失败，是否需要转手工退回，如否继续等待，如是，需提供学员本人银行卡信息@余韵7 (余韵)———————————— 11.7头寸不足@余韵7 (余韵) 11.6头寸不足@余韵7 (余韵) 11.5头寸不足@余韵7 (余韵) 11.4头寸不足@余韵7 (余韵) [图片] 11.1已提交退款，目前显示退款失败商户头寸不足，原因如下图，辛苦老师确认@余韵7 (余韵)[图片] 10.31暂退学生账户，学生另一个班级课消有误@余韵7 (余韵) 10.30未办理，oa未到前台@余韵7 (余韵) | AI5: TRUE | AJ5: 花园桥取消班，不计算顾问退费，因学管操作，上月未及时推出 | AK5: 3712.1
A6: 2025/11/02 | C6: 黄小妹7 | E6: 谭悦9 | G6: 巨量广告 | H6: 无忧项目-班课 | R6: 3891.1 | S6: 学生需要往后转班3月花园桥上课，持续转班 | T6: 2025-11-02 | Y6: 转班 | Z6: 黄小妹7 | AB6: 郑雅洁 | AC6: BJWY5564317069 | AD6: =R6 -> 3891.1 | AE6: 2025/11/02 | AF6: 已转班 | AI6: TRUE
A7: 2025/11/13 | B7: NO.2025111000162 | C7: 张泽7 | E7: 谭悦9 | G7: 学管续费推荐 | H7: VIP项目-VIP | J7: 开课前退费 | K7: 学员意愿转变_开课前 | P7: 学员家长给学员报名一对一课程，经多次沟通学员均拒绝上课，家长沟通无果决定退出费用，目前没有其他课程需要了 | T7: 2025-11-13 | U7: 北京航空航天 | V7: 信息 | W7: 大三 | X7: 计算机 | Y7: 退费 | Z7: 张泽7 | AA7: 真实产生的退费 | AB7: 赵一泽 | AC7: BJWY5334447793 | AD7: 18000 | AE7: 2025/11/19 | AF7: 微信退回 未办理：OA未到前台（11.18）@张泽7 (张泽) 未办理：OA未到前台（11.17）@张泽7 (张泽)—————————— 11.15未办理：OA未到前台，无顾问挽单记录@张泽7 (张泽) 11.14未办理：OA未到前台 11.13未办理：OA未到前台 | AI7: TRUE
A8: 2025/11/30 | B8: 19012339 | C8: 黄小妹7 | E8: 谭悦9 | G8: 内部员工推荐 | H8: 无忧项目-班课 | J8: 开课后退费 | L8: 学员意愿转变_开课后 | N8: 认为课程用处不大/不适合自己 | P8: 【开课前退费】学生表示个人原因，不透露其他，说有需求会再联系。 | T8: 2025-11-30 | U8: 北京建筑大学 | V8: 机电与车辆工程学院 | W8: 大三 | X8: 机械工程 | Y8: 退费 | Z8: 黄小妹7 | AA8: 真实产生的退费 | AB8: 温宇飞 | AC8: BJWY4724508572 | AD8: 42857 | AE8: 2025/11/30 | AF8: 12.2支付宝退42857———————— [图片] 12.01需要等专业课退费后合并提现 暂退至学员账户，待专业课退费后合并提现 | AI8: TRUE
A9: 2025/11/30 | B9: 19012035 | C9: 黄小妹7 | E9: 谭悦9 | G9: 内部员工推荐 | H9: 无忧项目-班课 | J9: 开课后退费 | L9: 学员意愿转变_开课后 | N9: 认为课程用处不大/不适合自己 | P9: 【开课后退费】学生表示个人原因，不透露其他，说有需求会再联系。 | T9: 2025-11-30 | U9: 北京建筑大学 | V9: 机电与车辆工程学院 | W9: 大三 | X9: 机械工程 | Y9: 退费 | Z9: 黄小妹7 | AA9: 真实产生的退费 | AB9: 温宇飞 | AC9: BJWY4724508572 | AD9: 3988.8 | AE9: 2025/11/30 | AF9: 12.2支付宝退3988.8元———————————— [图片] 12.01需要等专业课退费后合并提现 暂退至学员账户，待专业课退费后合并提现 | AI9: TRUE
A10: 2025/11/26 | B10: 19008961 | C10: 焦子瑞 | E10: 谭悦9 | G10: 新东方PC官网 | H10: 集训营项目-专业课 | J10: 开课后退费 | L10: 计划冲突_开课后 | P10: 退费方式：开课后退费，费用原路退回。退费原因：学生学校事情太多，无法继续参加后续的线下课程了，申请退费。 | T10: 2025-11-26 | U10: 青岛农业大学 | V10: 生命科学学院 | W10: 大四 | X10: 生物科学 | Y10: 退费 | Z10: 焦子瑞 | AA10: 真实产生的退费 | AB10: 刘晓瑜 | AC10: BJWY4340261185 | AD10: =AK10/2 -> 2880 | AE10: 2025/11/28 | AF10: 邮件已审批，合计18912微信退回 11.28邮件和审核对不上，已重新群内审核，需要重新发邮件 11.27未办理：退费群内无审核记录@焦子瑞[图片] [图片] | AI10: TRUE | AJ10: 谭悦星火分单，18912 | AK10: 5760
A11: 2025/11/26 | B11: 19008870 | C11: 焦子瑞 | E11: 谭悦9 | G11: 新东方PC官网 | H11: 集训营项目-专业课 | J11: 开课后退费 | L11: 计划冲突_开课后 | P11: 退费方式：开课后退费，费用原路退回。 退费原因：学生学校事情太多，无法继续参加后续的线下课程了，申请退费。 | T11: 2025-11-26 | U11: 青岛农业大学 | V11: 生命科学学院 | W11: 大四 | X11: 生物科学 | Y11: 退费 | Z11: 焦子瑞 | AA11: 真实产生的退费 | AB11: 刘晓瑜 | AC11: BJWY4340261185 | AD11: =AK11/2 -> 3315.35 | AE11: 2025/11/28 | AF11: 邮件已审批，合计18912微信退回 11.28邮件和审核对不上，已重新群内审核，需要重新发邮件 11.27未办理：退费群内无审核记录@焦子瑞[图片] [图片] | AI11: TRUE | AK11: 6630.7
A12: 2025/11/27 | B12: 19010532 | C12: 焦子瑞 | E12: 谭悦9 | G12: 新东方PC官网 | H12: 集训营项目-班课 | J12: 开课后退费 | L12: 计划冲突_开课后 | P12: 退费方式：开课后退费，费用原路退回。 退费原因：学生学校事情太多，无法继续参加后续的线下课程了，申请退费。 | T12: 2025-11-27 | U12: 青岛农业大学 | V12: 生命科学学院 | W12: 大四 | X12: 生物科学 | Y12: 退费 | Z12: 焦子瑞 | AA12: 真实产生的退费 | AB12: 刘晓瑜 | AC12: BJWY4340261185 | AD12: =AK12/2 -> 3260.65 | AE12: 2025/11/28 | AF12: 邮件已审批，合计18912微信退回 11.28邮件和审核对不上，已重新群内审核，需要重新发邮件 | AI12: TRUE | AK12: 6521.3
AA13: 无忧408第一次转班 | AB13: 安思羽 | AC13: 安思羽 | AD13: 9000
AA14: 无忧408第一次转班 | AB14: 孙嘉珩 | AC14: 孙嘉珩 | AD14: 9000
AA15: 无忧408第一次转班 | AB15: 余欣然 | AC15: 余欣然 | AD15: 9000
AD16: =SUM(AD5:AD15) -> 105192.9
A17: 2025/11/01 | B17: 2025102800224 | C17: 王天义56 | E17: 赵星火 | G17: 学管续费推荐 | H17: VIP项目-专业课 | J17: 开课前退费 | K17: 专业课师资匹配原因 | M17: 对专业课教师资质不满意 | P17: 师资无法匹配，辅导科目比较难： 1、大部分是数学专业内容，计算机专业无法授课，数学专业又无法讲解计算机部分； 2、匹配到了学生本校研究生，研究生反馈这门课网上没有课件，及格都比较难，当时找学校领导反应过太难，学不会，相应的专业研究生很难辅导； 3、匹配到可以带的 211 研究生，家长不满意研究生院校，想要北京的师资。 引导家长放宽匹配范围，家长要求退款，由于学生有四六级、数学课时包，所以引导家长学习考研预科，挖掘考研需求，家长不考虑。 | T17: 2025-11-01 | U17: 西安电子科技大学 | V17: 网络与信息安全学院 | W17: 2024 | X17: 信息安全 | Y17: 退费 | Z17: 王天义56 | AA17: 真实产生的退费 | AB17: 郭泽恩 | AC17: BJWY2399718106 | AD17: 15800 | AE17: 2025/11/01 | AF17: 11.1已原路退回@王天义56 (王天义)[图片] | AI17: TRUE
A18: 2025/11/11 | B18: 2025110601399 | C18: 徐岩91 | E18: 赵星火 | G18: 学管续费推荐 | H18: 四六级项目-VIP | J18: 开课后退费 | L18: 学员意愿转变_开课后 | N18: 找到工作 | P18: 学员已经毕业 工作了 四六级都过了 大学挂科的也都过了 么有需要了 申请退费 | T18: 2025-11-11 | U18: 北方工业大学 | V18: 信息学院 | W18: 毕业 | X18: 数字媒体技术 | Y18: 退费 | Z18: 徐岩91 | AA18: 真实产生的退费 | AB18: 罗浩轩 | AC18: BJWY8238689300 | AD18: 2300 | AE18: 2025/11/13 | AF18: 11.14退款完成 11.14退款中 11.13银联商务POS退回，退款中@徐岩91 (徐岩)[图片] 11.12未办理：需提供下学管端口挽单截图@徐岩91 (徐岩)[图片] | AI18: TRUE
A19: 2025/11/14 | B19: 18994744 | C19: 郑雪新 | E19: 赵星火 | G19: 学管转介绍 | H19: 集训营项目-班课 | J19: 开课前退费 | K19: 学员意愿转变_开课前 | P19: 姓名：赵梓伊学员编号:BJWY8307774892退费计算过程：退费班级：20264047；KYHSJX2702Z；KYHSJXY2702；KYHSJXZ2702报名实缴费45800（课前退费）；共计应退费用：25500+6900+7000+6400=45800元1】20264047；27考研一对一伴学(30小时/集训)；255002】KYHSJX2702Z；27考研寒暑集训营（住宿费）；69003】KYHSJXY2702；27考研寒暑集训营英语；70004】KYHSJXZ2702；27考研寒暑集训营政治；6400 | T19: 2025-11-14 | U19: 北京邮电大学世纪学院 | V19: 艺术与传媒学院 | W19: 大三 | X19: 传播学（数字媒体策划与传播） | Y19: 退费 | Z19: 郑雪新 | AA19: 真实产生的退费 | AB19: 赵梓伊 | AC19: BJWY8307774892 | AD19: 20300 | AE19: 2025/11/18 | AF19: 11.24退款成功 (11.22)原路径退还65800，银联扫码退款中：@郑雪新@王天一55 (王天一) [图片] 暂退至学员账户 未办理：无顾问、学管挽单记录（11.18）@郑雪新 未办理：无顾问、学管挽单记录（11.17）@郑雪新 | AI19: TRUE
A20: 2025/11/14 | B20: NO.5764607523035810600 | C20: 王天一55 | E20: 赵星火 | G20: 学管转介绍 | H20: 集训营项目-专业课 | J20: 开课前退费 | K20: 学员意愿转变_开课前 | P20: 学生跟家长商量后决定不考研了，想要直接工作，退费意愿强烈 | T20: 2025-11-14 | U20: 北京邮电大学世纪学院 | V20: 艺术与传媒学院 | W20: 大三 | X20: 传播学 | Y20: 退费 | Z20: 王天一55 | AA20: 真实产生的退费 | AB20: 赵梓伊 | AC20: BJWY8307774892 | AD20: 20000 | AE20: 2025/11/19 | AF20: 11.24退款成功 (11.22)原路径退还65800，银联扫码退款中：@郑雪新@王天一55 (王天一) [图片] 暂退至学员账户 未办理：无顾问、学管挽单记录（11.18）@郑雪新 未办理：无顾问、学管挽单记录（11.17）@郑雪新 | AI20: TRUE
A21: 2025/11/06 | B21: NO.4323455642277300862 | C21: 郭又华 | E21: 赵星火 | G21: 大众点评 | H21: 无忧项目-专业课 | J21: 开课后退费 | L21: 学员意愿转变_开课后 | N21: 认为课程用处不大/不适合自己 | P21: 学生从24年就报名了，但是本人是公司老板，一直没有时间学习，感觉课程设计不太合适，今年考研也没有报名，想要全科退费，目前没有其他课程需要了 | T21: 2025-11-06 | U21: 学生不愿告知 | V21: 学生不愿告知 | W21: 在职 | X21: 学生不愿告知 | Y21: 退费 | Z21: 郭又华 | AA21: 真实产生的退费 | AB21: 唐庆银 | AC21: BJWY4636639194 | AD21: 4486.7 | AE21: 2025/11/10 | AF21: 11.26退款成功。 11.25合计提现24569.5，已转手工退至原汇款账户，待短信确认：北京从云科技有限公司632967667中国民生银行股份有限公司北京魏公村支行@许庆典 [图片] [图片] 11.10已退回账户余4486.7，待公共课办理后一起提现（11.17）——————————@郭又华 [图片] 未办理：OA未到客服（11.9） 未办理：OA未到客服（11.8）—————————— 11.6未办理，oa未到前台 | AI21: TRUE
A22: 2025/11/15 | B22: 18986796 | C22: 史文涵1 | E22: 赵星火 | G22: 大众点评 | H22: 无忧项目-班课 | J22: 开课后退费 | L22: 学员意愿转变_开课后 | N22: 认为课程用处不大/不适合自己 | P22: 学员因自己前期没怎么上课，威胁投诉，要求退还剩余费用，已申请特批退款,邮件已抄送客服 | T22: 2025-11-15 | U22: 北京交通大学 | V22: 计算机 | W22: 在职 | X22: 计算机 | Y22: 退费 | Z22: 史文涵1 | AA22: 真实产生的退费 | AB22: 唐庆银 | AC22: BJWY4636639194 | AD22: 2967.8 | AE22: 2025/11/25 | AF22: 11.26退款成功。 11.25合计提现24569.5，已转手工退至原汇款账户，待短信确认：北京从云科技有限公司632967667中国民生银行股份有限公司北京魏公村支行@许庆典 [图片] [图片] 11.25未办理，暂时没有收到邮件 未办理：邮件还未审核完成（11.24）@史文涵1 (史文涵)@梁小东2 (梁小东) 未办理：邮件还未审核完成（11.23）@史文涵1 (史文涵)@梁小东2 (梁小东) 未办理：邮件还未审核完成（11.22） 未办理：辛苦老师将邮件完整的审批记录抄送至【大学事业部北京中心客户服务部前台客服部】（11.21）@史文涵1 (史文涵) 未办理：邮件审批流程未完成（11.20）@史文涵1 (史文涵) 未办理：邮件审批流程未完成（11.19）@史文涵1 (史文涵)[图片] 未办理：邮件审批流程未完成（11.18） 未办理：邮件审批流程未完成（11.17） | AG22: 许庆典 | AI22: TRUE
A23: 2025/11/15 | B23: 18990802 | C23: 史文涵1 | E23: 赵星火 | G23: 大众点评 | H23: 无忧项目-班课 | J23: 开课后退费 | L23: 学员意愿转变_开课后 | N23: 认为课程用处不大/不适合自己 | P23: 学员因自己前期没怎么上课，威胁投诉，要求退还剩余费用，已申请特批退款,邮件已抄送客服 | T23: 2025-11-15 | U23: 北京交通大学 | V23: 计算机 | W23: 在职 | X23: 计算机 | Y23: 退费 | Z23: 史文涵1 | AA23: 真实产生的退费 | AB23: 唐庆银 | AC23: BJWY4636639194 | AD23: 3298.8 | AE23: 2025/11/25 | AF23: 11.26退款成功。 11.25合计提现24569.5，已转手工退至原汇款账户，待短信确认：北京从云科技有限公司632967667中国民生银行股份有限公司北京魏公村支行@许庆典 [图片] [图片] 11.25未办理，暂时没有收到邮件 未办理：邮件还未审核完成（11.24）@史文涵1 (史文涵)@梁小东2 (梁小东) 未办理：邮件还未审核完成（11.23）@史文涵1 (史文涵)@梁小东2 (梁小东) 未办理：邮件还未审核完成（11.22） 未办理：辛苦老师将邮件完整的审批记录抄送至【大学事业部北京中心客户服务部前台客服部】（11.21）@史文涵1 (史文涵) 未办理：邮件审批流程未完成（11.20）@史文涵1 (史文涵) 未办理：邮件审批流程未完成（11.19）@史文涵1 (史文涵)[图片] 未办理：邮件审批流程未完成（11.18） 未办理：邮件审批流程未完成（11.17） | AI23: TRUE
A24: 2025/11/15 | B24: 18990954 | C24: 史文涵1 | E24: 赵星火 | G24: 大众点评 | H24: 无忧项目-班课 | J24: 开课后退费 | L24: 学员意愿转变_开课后 | N24: 认为课程用处不大/不适合自己 | P24: 学员因自己前期没怎么上课，威胁投诉，要求退还剩余费用，已申请特批退款,邮件已抄送客服 | T24: 2025-11-15 | U24: 北京交通大学 | V24: 计算机 | W24: 在职 | X24: 计算机 | Y24: 退费 | Z24: 史文涵1 | AA24: 真实产生的退费 | AB24: 唐庆银 | AC24: BJWY4636639194 | AD24: 1592.3 | AE24: 2025/11/25 | AF24: 11.26退款成功。 11.25合计提现24569.5，已转手工退至原汇款账户，待短信确认：北京从云科技有限公司632967667中国民生银行股份有限公司北京魏公村支行@许庆典 [图片] [图片] 11.25未办理，暂时没有收到邮件 未办理：邮件还未审核完成（11.24）@史文涵1 (史文涵)@梁小东2 (梁小东) 未办理：邮件还未审核完成（11.23）@史文涵1 (史文涵)@梁小东2 (梁小东) 未办理：邮件还未审核完成（11.22） 未办理：辛苦老师将邮件完整的审批记录抄送至【大学事业部北京中心客户服务部前台客服部】（11.21）@史文涵1 (史文涵) 未办理：邮件审批流程未完成（11.20）@史文涵1 (史文涵) 未办理：邮件审批流程未完成（11.19）@史文涵1 (史文涵)[图片] 未办理：邮件审批流程未完成（11.18） 未办理：邮件审批流程未完成（11.17） | AI24: TRUE
A25: 2025/11/15 | B25: 18990973 | C25: 史文涵1 | E25: 赵星火 | G25: 大众点评 | H25: 无忧项目-班课 | J25: 开课后退费 | L25: 学员意愿转变_开课后 | N25: 认为课程用处不大/不适合自己 | P25: 学员因自己前期没怎么上课，威胁投诉，要求退还剩余费用，已申请特批退款,邮件已抄送客服 | T25: 2025-11-15 | U25: 北京交通大学 | V25: 计算机 | W25: 在职 | X25: 计算机 | Y25: 退费 | Z25: 史文涵1 | AA25: 真实产生的退费 | AB25: 唐庆银 | AC25: BJWY4636639194 | AD25: 5341.1 | AE25: 2025/11/25 | AF25: 11.26退款成功。 11.25合计提现24569.5，已转手工退至原汇款账户，待短信确认：北京从云科技有限公司632967667中国民生银行股份有限公司北京魏公村支行@许庆典 [图片] [图片] 11.25未办理，暂时没有收到邮件 未办理：邮件还未审核完成（11.24）@史文涵1 (史文涵)@梁小东2 (梁小东) 未办理：邮件还未审核完成（11.23）@史文涵1 (史文涵)@梁小东2 (梁小东) 未办理：邮件还未审核完成（11.22） 未办理：辛苦老师将邮件完整的审批记录抄送至【大学事业部北京中心客户服务部前台客服部】（11.21）@史文涵1 (史文涵) 未办理：邮件审批流程未完成（11.20）@史文涵1 (史文涵) 未办理：邮件审批流程未完成（11.19）@史文涵1 (史文涵)[图片] 未办理：邮件审批流程未完成（11.18） 未办理：邮件审批流程未完成（11.17） | AI25: TRUE
A26: 2025/11/15 | B26: 18991963 | C26: 史文涵1 | E26: 赵星火 | G26: 大众点评 | H26: 无忧项目-班课 | J26: 开课后退费 | L26: 学员意愿转变_开课后 | N26: 认为课程用处不大/不适合自己 | P26: 学员因自己前期没怎么上课，威胁投诉，要求退还剩余费用，已申请特批退款,邮件已抄送客服 | T26: 2025-11-15 | U26: 北京交通大学 | V26: 计算机 | W26: 在职 | X26: 计算机 | Y26: 退费 | Z26: 史文涵1 | AA26: 真实产生的退费 | AB26: 唐庆银 | AC26: BJWY4636639194 | AD26: 3770.2 | AE26: 2025/11/25 | AF26: 11.26退款成功。 11.25合计提现24569.5，已转手工退至原汇款账户，待短信确认：北京从云科技有限公司632967667中国民生银行股份有限公司北京魏公村支行@许庆典 [图片] [图片] 11.25未办理，暂时没有收到邮件 未办理：邮件还未审核完成（11.24）@史文涵1 (史文涵)@梁小东2 (梁小东) 未办理：邮件还未审核完成（11.23）@史文涵1 (史文涵)@梁小东2 (梁小东) 未办理：邮件还未审核完成（11.22） 未办理：辛苦老师将邮件完整的审批记录抄送至【大学事业部北京中心客户服务部前台客服部】（11.21）@史文涵1 (史文涵) 未办理：邮件审批流程未完成（11.20）@史文涵1 (史文涵) 未办理：邮件审批流程未完成（11.19）@史文涵1 (史文涵)[图片] 未办理：邮件审批流程未完成（11.18） 未办理：邮件审批流程未完成（11.17） | AI26: TRUE
A27: 2025/11/15 | B27: 18991941 | C27: 史文涵1 | E27: 赵星火 | G27: 大众点评 | H27: 无忧项目-班课 | J27: 开课后退费 | L27: 学员意愿转变_开课后 | N27: 认为课程用处不大/不适合自己 | P27: 学员因自己前期没怎么上课，威胁投诉，要求退还剩余费用，已申请特批退款,邮件已抄送客服 | T27: 2025-11-15 | U27: 北京交通大学 | V27: 计算机 | W27: 在职 | X27: 计算机 | Y27: 退费 | Z27: 史文涵1 | AA27: 真实产生的退费 | AB27: 唐庆银 | AC27: BJWY4636639194 | AD27: 3112.6 | AE27: 2025/11/25 | AF27: 11.26退款成功。 11.25合计提现24569.5，已转手工退至原汇款账户，待短信确认：北京从云科技有限公司632967667中国民生银行股份有限公司北京魏公村支行@许庆典 [图片] [图片] 11.25未办理，暂时没有收到邮件 未办理：邮件还未审核完成（11.24）@史文涵1 (史文涵)@梁小东2 (梁小东) 未办理：邮件还未审核完成（11.23）@史文涵1 (史文涵)@梁小东2 (梁小东) 未办理：邮件还未审核完成（11.22） 未办理：辛苦老师将邮件完整的审批记录抄送至【大学事业部北京中心客户服务部前台客服部】（11.21）@史文涵1 (史文涵) 未办理：邮件审批流程未完成（11.20）@史文涵1 (史文涵) 未办理：邮件审批流程未完成（11.19）@史文涵1 (史文涵)[图片] 未办理：邮件审批流程未完成（11.18） 未办理：邮件审批流程未完成（11.17） | AI27: TRUE
A28: 2025/11/15 | B28: 18990927 | C28: 史文涵1 | E28: 赵星火 | G28: 大众点评 | H28: 无忧项目-班课 | J28: 开课后退费 | L28: 学员意愿转变_开课后 | N28: 认为课程用处不大/不适合自己 | P28: 学员因自己前期没怎么上课，威胁投诉，要求退还剩余费用，已申请特批退款,邮件已抄送客服 | T28: 2025-11-15 | U28: 北京交通大学 | V28: 计算机 | W28: 在职 | X28: 计算机 | Y28: 退费 | Z28: 史文涵1 | AA28: 真实产生的退费 | AB28: 唐庆银 | AC28: BJWY4636639194 | AD28: 0 | AE28: 2025/11/25 | AF28: 0元离班 11.25未办理，暂时没有收到邮件 未办理：邮件还未审核完成（11.24）@史文涵1 (史文涵)@梁小东2 (梁小东) 未办理：邮件还未审核完成（11.23）@史文涵1 (史文涵)@梁小东2 (梁小东) 未办理：邮件还未审核完成（11.22） 未办理：辛苦老师将邮件完整的审批记录抄送至【大学事业部北京中心客户服务部前台客服部】（11.21）@史文涵1 (史文涵) 未办理：邮件审批流程未完成（11.20）@史文涵1 (史文涵) 未办理：邮件审批流程未完成（11.19）@史文涵1 (史文涵)[图片] 未办理：邮件审批流程未完成（11.18） 未办理：邮件审批流程未完成（11.17） | AI28: TRUE
A29: 2025/11/15 | B29: 18991920 | C29: 史文涵1 | E29: 赵星火 | G29: 大众点评 | H29: 无忧项目-班课 | J29: 开课后退费 | L29: 学员意愿转变_开课后 | N29: 认为课程用处不大/不适合自己 | P29: 学员因自己前期没怎么上课，威胁投诉，要求退还剩余费用，已申请特批退款,邮件已抄送客服 | T29: 2025-11-15 | U29: 北京交通大学 | V29: 计算机 | W29: 大四 | X29: 计算机 | Y29: 退费 | Z29: 史文涵1 | AA29: 真实产生的退费 | AB29: 唐庆银 | AC29: BJWY4636639194 | AD29: 0 | AE29: 2025/11/25 | AF29: 0元离班 11.25未办理，暂时没有收到邮件 未办理：邮件还未审核完成（11.24）@史文涵1 (史文涵)@梁小东2 (梁小东) 未办理：邮件还未审核完成（11.23）@史文涵1 (史文涵)@梁小东2 (梁小东) 未办理：邮件还未审核完成（11.22） 未办理：辛苦老师将邮件完整的审批记录抄送至【大学事业部北京中心客户服务部前台客服部】（11.21）@史文涵1 (史文涵) 未办理：邮件审批流程未完成（11.20）@史文涵1 (史文涵) 未办理：邮件审批流程未完成（11.19）@史文涵1 (史文涵)[图片] 未办理：邮件审批流程未完成（11.18） 未办理：邮件审批流程未完成（11.17） | AI29: TRUE
A30: 2025/11/15 | B30: 18989761 | C30: 史文涵1 | E30: 赵星火 | G30: 大众点评 | H30: 无忧项目-班课 | J30: 开课后退费 | L30: 学员意愿转变_开课后 | N30: 认为课程用处不大/不适合自己 | P30: 学员因自己前期没怎么上课，威胁投诉，要求退还剩余费用，已申请特批退款,邮件已抄送客服 | T30: 2025-11-15 | U30: 北京交通大学 | V30: 计算机 | W30: 在职 | X30: 计算机 | Y30: 退费 | Z30: 史文涵1 | AA30: 真实产生的退费 | AB30: 唐庆银 | AC30: BJWY4636639194 | AD30: 0 | AE30: 2025/11/25 | AF30: 0元离班 11.25未办理，暂时没有收到邮件 未办理：邮件还未审核完成（11.24）@史文涵1 (史文涵)@梁小东2 (梁小东) 未办理：邮件还未审核完成（11.23）@史文涵1 (史文涵)@梁小东2 (梁小东) 未办理：邮件还未审核完成（11.22） 未办理：辛苦老师将邮件完整的审批记录抄送至【大学事业部北京中心客户服务部前台客服部】（11.21）@史文涵1 (史文涵) 未办理：邮件审批流程未完成（11.20）@史文涵1 (史文涵) 未办理：邮件审批流程未完成（11.19）@史文涵1 (史文涵)[图片] 未办理：邮件审批流程未完成（11.18） 未办理：邮件审批流程未完成（11.17） | AI30: TRUE
A31: 2025/11/15 | B31: 18973649 | C31: 罗志勇1 | E31: 赵星火 | G31: 内部员工推荐 | H31: 四六级项目-班课 | J31: 开课后退费 | L31: 计划冲突_开课后 | P31: 学生家长反馈学生周末学校有安排，实在没有办法上课，直播效果不好，一直强调不是老师的问题，是自己的原因，坚持退费，拒绝转班 | T31: 2025-11-15 | U31: 北京工商大学 | V31: 人工智能学院 | W31: 大一 | X31: 智能制造 | Y31: 退费 | Z31: 罗志勇1 | AA31: 真实产生的退费 | AB31: 杨辛 | AC31: BJWY1788882002 | AD31: 3692 | AE31: 2025/11/16 | AF31: 11.16 微信原渠道退还@罗志勇1 (罗志勇) | AI31: TRUE
A32: 2025/11/19 | B32: 4035225266125600297 | C32: 郑雪新 | E32: 赵星火 | G32: 学管转介绍 | H32: 集训营项目-VIP | J32: 开课前退费 | K32: 学员意愿转变_开课前 | P32: 姓名：赵梓伊 学员编号:BJWY8307774892 退费计算过程：班号20264047 ；27考研一对一伴学(30小时/集训)；25500 | T32: 2025-11-19 | U32: 北京邮电大学世纪学院 | V32: 艺术与传媒学院 | W32: 大三 | X32: 传播学（数字媒体策划与传播） | Y32: 退费 | Z32: 郑雪新 | AA32: 真实产生的退费 | AB32: 赵梓伊 | AC32: BJWY8307774892 | AD32: 25500 | AE32: 2025/11/22 | AF32: 11.29退款完成———————— 11.28商务银联退款中 11.27商务银联退款中[图片] 11.26商务银联退款中 11.25商务银联退款中[图片] 11.24商务银联退款中 [图片] (11.22)原路径退还65800，银联扫码退款中：@郑雪新@王天一55 (王天一) [图片] 未办理：群内未查到该班级的退费申请以及金额审核记录（11.21）@王天一55 (王天一) | AI32: TRUE
A33: 2025/11/20 | B33: 2025111600666 | C33: 王天义56 | E33: 赵星火 | G33: 放心学 | H33: VIP项目-VIP | J33: 开课后退费 | L33: 计划冲突_开课后 | P33: 家长因孩子专业课压力大，提出英语课仅下周二上最后一节作文课收尾，剩余英语课退费，政治做保留。学管询问孩子今年是否还考试，家长确认肯定考试，只因专业课任务重，英语上完最后一节即可。学管说明英语课在续课时已压缩，当时选择了课时较少的方案，讲课速度较快，若孩子觉得压力大可查看云教室的课程回放，并指出若不上会影响孩子英语成绩提升和复习。家长表示清楚后果并自愿承担，坚持退费。引导家长保留一部分课时用来上政治，家长保留 2h，共退出 12h。 | T33: 2025-11-20 | U33: 北京林业大学 | V33: 林学院 | W33: 2022 | X33: 林学 | Y33: 退费 | Z33: 王天义56 | AA33: 真实产生的退费 | AB33: 刘宵含 | AC33: BJWY0430086011 | AD33: 11700 | AE33: 2025/11/20 | AF33: 微信退回 | AI33: TRUE
A34: 2025/11/22 | B34: 2025111500523 | C34: 王天义56 | D34: TRUE | E34: 赵星火 | G34: 学管续费推荐 | H34: VIP项目-VIP | J34: 开课前退费 | K34: 学员意愿转变_开课前 | P34: 25 考季学员，已经工作，家长表示无心考研，由于报名比较早，存在价差，建议家长保留课时，需要的时候再报名的话会花费更多，并推荐非全，家长坚持退费。 | T34: 2025-11-22 | U34: 北方工业大学 | V34: 信息学院 | W34: 毕业/已就业 | X34: 数字媒体技术 | Y34: 退费 | Z34: 王天义56 | AA34: 真实产生的退费 | AB34: 罗浩轩 | AC34: BJWY8238689300 | AD34: 95500 | AE34: 2025/11/22 | AF34: 11.26退款成功。 11.26已确认，退款中，待到账 11.25已确认，退款中，待到账 [图片] 11.24已转手工退至学员本人银行卡，待短信确认：高新章6217000010112474112建设银行北京天宁寺支行@王天义56 (王天义) 11.23再次提醒 (11.22)退回账户余额，原支付渠道超时失效，请提供原支付银行卡信息来手工退款@王天义56 (王天义) 中国建设银行621700*********4112 [图片] | AI34: TRUE
A35: 2025/11/23 | B35: 19005767 | C35: 许庆典 | E35: 赵星火 | G35: 小红书 | H35: 无忧项目-班课 | J35: 开课后退费 | L35: 学员意愿转变_开课后 | N35: 认为课程用处不大/不适合自己 | P35: 放弃考研 | T35: 2025-11-23 | U35: 北京工业大学 | V35: 生物技术 | W35: 大四 | X35: 生物技术 | Y35: 退费 | Z35: 许庆典 | AA35: 真实产生的退费 | AB35: 韩宜航 | AC35: BJWY8146889572 | AD35: 518.2 | AE35: 2025/11/27 | AF35: 微信退回 11.26未办理，oa未到客服 11.25未办理，oa未到客服 未办理：OA未到客服（11.24） | AI35: TRUE
A36: 2025/11/23 | B36: 19005869 | C36: 许庆典 | E36: 赵星火 | G36: 小红书 | H36: 无忧项目-班课 | J36: 开课后退费 | L36: 学员意愿转变_开课后 | N36: 认为课程用处不大/不适合自己 | P36: 放弃考研 | T36: 2025-11-23 | U36: 北京工业大学 | V36: 生物科技 | W36: 大四 | X36: 生物科技 | Y36: 退费 | Z36: 许庆典 | AA36: 真实产生的退费 | AB36: 韩宜航 | AC36: BJWY8146889572 | AD36: 800 | AE36: 2025/11/27 | AF36: 微信退回 11.26未办理，oa未到客服 11.25未办理，oa未到客服 未办理：OA未到客服（11.24） | AI36: TRUE
A37: 2025/11/25 | B37: 2025111802284 | C37: 徐岩91 | D37: TRUE | E37: 赵星火 | G37: 内部员工推荐 | H37: 四六级项目-VIP | J37: 开课后退费 | L37: 学员意愿转变_开课后 | N37: 找到工作 | P37: 孩子没有别的需求 六级，数学，考研，雅思课都不需要啦 申请退费 | T37: 2025-11-25 | U37: 大专 | V37: 大专 | W37: 大二 | X37: 大专 | Y37: 退费 | Z37: 徐岩91 | AA37: 真实产生的退费 | AB37: 王樱 | AC37: BJWY1989106679 | AD37: 10600 | AE37: 2025/11/25 | AF37: 11.28退款完成 11.28已确认，退款中，待到账 [图片] 11.27已短信确认/退款中 11.26已转手工，待短信确认@徐岩91 (徐岩) 11.25已办理退至学员账户，原支付渠道失效，请提醒学生本人银行卡信息转手工退款@徐岩91 (徐岩)[图片] | AI37: TRUE
A38: 2025/11/25 | B38: NO.6629298651491008139 | C38: 马一鸣16 | E38: 赵星火 | G38: 百度投放 | H38: 无忧项目-专业课 | J38: 开课前退费 | K38: 学员意愿转变_开课前 | P38: 学生目前找了辅导专业课的老师，不需要这边匹配了。和学生沟通是否需要转到英语政治一对一提升一下，学生拒绝，挽单失败。 | T38: 2025-11-25 | U38: 北京联合大学 | V38: 艺术学院 | W38: 大三 | X38: 绘画 | Y38: 退费 | Z38: 马一鸣16 | AA38: 真实产生的退费 | AB38: 方越 | AC38: BJWY2391065562 | AD38: 21000 | AE38: 2025/11/27 | AF38: 微信退回 11.26未办理，未查询到顾问的挽单记录@马一鸣16 (马一鸣) | AI38: TRUE
A39: 2025/11/26 | B39: 19008961 | C39: 焦子瑞 | E39: 赵星火 | G39: 新东方PC官网 | H39: 集训营项目-专业课 | J39: 开课后退费 | L39: 计划冲突_开课后 | P39: 退费方式：开课后退费，费用原路退回。退费原因：学生学校事情太多，无法继续参加后续的线下课程了，申请退费。 | T39: 2025-11-26 | U39: 青岛农业大学 | V39: 生命科学学院 | W39: 大四 | X39: 生物科学 | Y39: 退费 | Z39: 焦子瑞 | AA39: 真实产生的退费 | AB39: 刘晓瑜 | AC39: BJWY4340261185 | AD39: =AK39/2 -> 2880 | AE39: 2025/11/28 | AF39: 邮件已审批，合计18912微信退回 11.28邮件和审核对不上，已重新群内审核，需要重新发邮件 11.27未办理：退费群内无审核记录@焦子瑞[图片] [图片] | AI39: TRUE | AJ39: 谭悦星火分单，18912 | AK39: 5760
A40: 2025/11/26 | B40: 19008870 | C40: 焦子瑞 | E40: 赵星火 | G40: 新东方PC官网 | H40: 集训营项目-专业课 | J40: 开课后退费 | L40: 计划冲突_开课后 | P40: 退费方式：开课后退费，费用原路退回。 退费原因：学生学校事情太多，无法继续参加后续的线下课程了，申请退费。 | T40: 2025-11-26 | U40: 青岛农业大学 | V40: 生命科学学院 | W40: 大四 | X40: 生物科学 | Y40: 退费 | Z40: 焦子瑞 | AA40: 真实产生的退费 | AB40: 刘晓瑜 | AC40: BJWY4340261185 | AD40: =AK40/2 -> 3315.35 | AE40: 2025/11/28 | AF40: 邮件已审批，合计18912微信退回 11.28邮件和审核对不上，已重新群内审核，需要重新发邮件 11.27未办理：退费群内无审核记录@焦子瑞[图片] [图片] | AI40: TRUE | AK40: 6630.7
A41: 2025/11/27 | B41: 19010532 | C41: 焦子瑞 | E41: 赵星火 | G41: 新东方PC官网 | H41: 集训营项目-班课 | J41: 开课后退费 | L41: 计划冲突_开课后 | P41: 退费方式：开课后退费，费用原路退回。 退费原因：学生学校事情太多，无法继续参加后续的线下课程了，申请退费。 | T41: 2025-11-27 | U41: 青岛农业大学 | V41: 生命科学学院 | W41: 大四 | X41: 生物科学 | Y41: 退费 | Z41: 焦子瑞 | AA41: 真实产生的退费 | AB41: 刘晓瑜 | AC41: BJWY4340261185 | AD41: =AK41/2 -> 3260.65 | AE41: 2025/11/28 | AF41: 邮件已审批，合计18912微信退回 11.28邮件和审核对不上，已重新群内审核，需要重新发邮件 | AI41: TRUE | AK41: 6521.3
A42: 2025/11/28 | B42: 19011600 | C42: 焦子瑞 | E42: 赵星火 | G42: 学管续费推荐 | H42: 集训营项目-班课 | J42: 开课后退费 | L42: 计划冲突_开课后 | P42: 退费方式：开课后退费，原路退回。 退费原因：学生学校事情太多，无法继续参加后续的线下课程了，申请退费 | T42: 2025-11-28 | U42: 保定理工学院 | V42: 资源与工程技术学院 | W42: 大四 | X42: 土地资源管理 | Y42: 退费 | Z42: 焦子瑞 | AA42: 真实产生的退费 | AB42: 霍盈杉 | AC42: BJWY9038592627 | AD42: 7004.8 | AE42: 2025/11/29 | AF42: 支付宝退回12444.8元，微信退回1元 | AI42: TRUE
A43: 2025/11/28 | B43: 19011766 | C43: 焦子瑞 | E43: 赵星火 | G43: 学管续费推荐 | H43: 集训营项目-班课 | J43: 开课后退费 | L43: 计划冲突_开课后 | P43: 退费方式：开课后退费，原路退回。 退费原因：学生学校事情太多，无法继续参加后续的线下课程了，申请退费。 | T43: 2025-11-28 | U43: 保定理工学院 | V43: 资源与工程技术学院 | W43: 大四 | X43: 土地资源管理 | Y43: 退费 | Z43: 焦子瑞 | AA43: 真实产生的退费 | AB43: 霍盈杉 | AC43: BJWY9038592627 | AD43: 5440 | AE43: 2025/11/29 | AF43: 支付宝退回12444.8元，微信退回1元 | AI43: TRUE
A44: 2025/11/29 | B44: NO.2025112402751 | C44: 王天义56 | E44: 赵星火 | G44: 学管续费推荐 | H44: VIP项目-VIP | J44: 开课后退费 | L44: 学员意愿转变_开课后 | N44: 个人身体原因无法承受高强度学习 | P44: 学员范围， 2025-08-23报名100h，开课日期为2025-08-24，课消 98h，剩余 2h；2025-10-16续费，续费 34h，课消为 0，每周课频为 3-5 次课。计算剩余课时和授课进度，与老师沟通所需课时，劝说学生于提前续费，按计划可在考前上完。 与家长 11/14 电话沟通，学生压力大经常失眠，去医院检查后，医生建议停课一周观察，家长觉得身体要紧遵从医嘱；一周后复查，医生不建议继续考试，表示学生身体已经亮红灯，家长不愿冒风险，考研也是为了满足孩子的心愿，身体最重要，选择放弃考试，托关系找工作就业。 8月末开始系统复习考试，复习时间很短，在学生生病前，我在校区见到同学多次鼓励，并在模考时将学生安排在我监考的场次，考试后成绩不理想也进行心理疏导；科任老师平时上课也对学生进行鼓励式教育。家长很认可老师们的努力，并表示感谢，后续如果考在职研会再联系。 | T44: 2025-11-29 | U44: 北京建筑大学 | V44: 土木与交通工程学院 | W44: 2022 | X44: 土木工程 | Y44: 退费 | Z44: 王天义56 | AA44: 真实产生的退费 | AB44: 范围 | AC44: BJWY1871741452 | AD44: 27300 | AE44: 2025/11/29 | AF44: 12.3已再次发送短信，请提醒学生短信确认@王天义56 (王天义) [图片] 12.2再次提醒短信确认@王天义56 (王天义)—————————— 12.01已办理提交手工退费，已发送确认短信到137****5363 ，需要提醒学生短信确认@王天义56 (王天义) [图片] 暂退至学员账户，提供原汇款账户信息@王天义56 (王天义)———————— [图片]
E45: 赵星火 | AA45: 无忧408第一次转班 | AB45: 孟瑞航 | AD45: 10000
E46: 赵星火 | AA46: 无忧408第一次转班 | AB46: 李嘉璐 | AD46: 9000
E47: 赵星火 | AA47: 无忧408第一次转班 | AB47: 孟瑞航 | AD47: 9000
AB48: 吕松澄 | AD48: 6350
AD49: =SUM(AD17:AD48) -> 335830.5
E50: 李涛48 | AC50: 学员27djm | AD50: 13950
E51: 李涛48 | AC51: DLS_5044115304 | AD51: 9450
E52: 李涛48 | AC52: 学员rkfe7 | AD52: 3866.45
E53: 李涛48在线退费 | AD53: =SUM(AD50:AD52) -> 27266.45
E54: 谭悦9 | AC54: 学员4908565 | AD54: 100
E55: 谭悦9 | AC55: 学员ubxdc | AD55: 100
E56: 赵星火 | AC56: 学员komf2 | AD56: 100

Sheet 11月绩效核算
B2: 顾问 | E2: 转介绍 | L2: 签约率 | S2: 日常管理
B3: 工号 | C3: 顾问姓名 | D3: 备注 | E3: 工单目标 | F3: 工单实际 | G3: 完成率 | H3: 签约目标 | I3: 签约实际 | J3: 完成率 | K3: 占比 | L3: 主动目标 | M3: 主动实际 | N3: 完成情况 | O3: 被动目标 | P3: 被动实际 | Q3: 完成情况 | R3: 占比 | S3: 自签占比目标比 | T3: 实际 | U3: 占比 | V3: 回访时效 | W3: 占比 | X3: 得分
B4: 238256 | C4: 赵星火 | E4: 6 | F4: 2 | G4: =F4/E4 -> 0.33333333 | H4: 5 | I4: 0 | J4: =I4/H4 -> 0 | K4: 0.3 | L4: 0.25 | M4: 0.55 | N4: 完成 | O4: 0.1 | P4: 0.36 | Q4: 完成 | R4: 0.4 | S4: 0.3 | T4: 0.45 | U4: 0.2 | V4: 合格 | W4: 0.1 | X4: 20
B5: 404905 | C5: 李涛 | D5: 结束保护期 | E5: 4 | F5: 1 | G5: =F5/E5 -> 0.25 | H5: 4 | I5: 0 | J5: =I5/H5 -> 0 | K5: 0.3 | L5: 0.1 | M5: 0.2 | N5: 完成 | O5: 0.1 | P5: 0.17 | Q5: 完成 | R5: 0.4 | S5: 0.3 | T5: 0.51 | U5: 0.2 | V5: 合格 | W5: 0.1 | X5: =U5*100+10 -> 30
B6: 341422 | C6: 谭悦 | D6: O3无考核指标 | E6: 6 | F6: 3 | G6: =F6/E6 -> 0.5 | H6: 5 | I6: 4.245 | J6: =I6/H6 -> 0.849 | K6: 0.3 | L6: 0.25 | M6: 0.62 | N6: 完成 | O6: 0.1 | P6: 0.22 | Q6: 完成 | R6: 0.4 | S6: 0.3 | T6: 0.89 | U6: 0.2 | V6: 合格 | W6: 0.1 | X6: =U6*100+10 -> 30

Sheet 12月绩效目标
B2: 序号 | C2: 年月 | D2: 部门 | E2: 工号 | F2: 姓名 | G2: 岗位 | H2: 绩效考核项
H3: 1.签约业绩 | I3: 2.主被动转化率 | J3: 3.老带新工单/人头/金额 | K3: 4.项目自签占比 | L3: 5.回访时效
B4: 1 | C4: 202512 | D4: 个性化项目部 | E4: 238256 | F4: 赵星火 | G4: 学习顾问 | H4: 37.8w（含在线代售8000） | I4: 主动25%、被动10% | J4: 工单2/人头1/金额1 | K4: 0.35 | L4: 不低于中心75分位值
B5: 2 | C5: 202512 | E5: 341422 | F5: 谭悦 | H5: 40.8w（含在线代售8000） | I5: 主动25%、被动10% | J5: 工单2/人头1/金额1 | K5: 0.35 | L5: 不低于中心75分位值
B6: 3 | C6: 202512 | E6: 404905 | F6: 李涛 | H6: 32.5w（含在线代售5000） | I6: 主动20%、被动10% | J6: 工单2/人头1/金额1 | K6: 0.35 | L6: 不低于中心75分位值
I7: 占比40% | J7: 占比30% | K7: 占比30%
