Workbook

Sheet 业绩奖金
A1: 业绩奖金表（一人可多条，需写清类别）
A2: 序号 | B2: 机构 | C2: 年月 | D2: 工号 | E2: 姓名 | F2: 部门 | G2: 薪资项目 | H2: 金额 | I2: 备注
A3: 1 | B3: 北京中心 | C3: 2025.07 | D3: 258756 | E3: 刘文君 | F3: B级学习顾问 | G3: 管理绩效 | H3: 4000 | J3: OK
A4: 2 | B4: 北京中心 | C4: 2025.07 | D4: 258756 | E4: 刘文君 | F4: B级学习顾问 | G4: 岗位补贴 | H4: 4000 | J4: OK
A5: 3 | B5: 北京中心 | C5: 2025.07 | D5: 004192 | E5: 刘晓娟 | F5: B级学习顾问 | G5: 月度绩效 | H5: 2000 | J5: ok
A6: 4 | B6: 北京中心 | C6: 2025.07 | D6: 004192 | E6: 刘晓娟 | F6: B级学习顾问 | G6: 顾问签约奖金 | H6: 71254
A7: 5 | B7: 北京中心 | C7: 2025.07 | D7: 004192 | E7: 刘晓娟 | F7: B级学习顾问 | G7: 其它奖金 | H7: 2000 | I7: 过渡性补贴2000 | J7: OK
A8: 6 | B8: 北京中心 | C8: 2025.07 | D8: 004192 | E8: 刘晓娟 | F8: B级学习顾问 | G8: 顾问pk赛 | H8: 3000 | J8: OK
A9: 7 | B9: 北京中心 | C9: 2025.07 | D9: 004192 | E9: 刘晓娟 | F9: B级学习顾问 | G9: 积分pk赛 | H9: 1000 | J9: 未公示，先不发放
A10: 8 | B10: 北京中心 | C10: 2025.07 | D10: 590299 | E10: 徐健坤 | F10: B级学习顾问 | G10: 月度绩效 | H10: 1580 | J10: ok
A11: 9 | B11: 北京中心 | C11: 2025.07 | D11: 590299 | E11: 徐健坤 | F11: B级学习顾问 | G11: 顾问签约奖金 | H11: 0
A12: 10 | B12: 北京中心 | C12: 2025.07 | D12: 590299 | E12: 徐健坤 | F12: B级学习顾问 | G12: 其它奖金 | H12: 1097 | I12: 过渡性补贴2000，7.17最后一天出勤在岗，绩效核算：2000*（17/31） | J12: OK
A13: 11 | B13: 北京中心 | C13: 2025.07 | D13: 594606 | E13: 房国超 | F13: B级学习顾问 | G13: 月度绩效 | H13: 2000 | J13: ok
A14: 12 | B14: 北京中心 | C14: 2025.07 | D14: 594606 | E14: 房国超 | F14: B级学习顾问 | G14: 顾问签约奖金 | H14: 35781
A15: 13 | B15: 北京中心 | C15: 2025.07 | D15: 594606 | E15: 房国超 | F15: B级学习顾问 | G15: 其它奖金 | H15: 2000 | I15: 过渡性补贴2000 | J15: OK
A16: 14 | B16: 北京中心 | C16: 2025.07 | D16: 594606 | E16: 房国超 | F16: B级学习顾问 | G16: 顾问pk赛 | H16: 2000 | J16: OK
A17: 15 | B17: 北京中心 | C17: 2025.07 | D17: 594605 | E17: 李政 | F17: B级学习顾问 | G17: 月度绩效 | H17: 0 | J17: ok
A18: 16 | B18: 北京中心 | C18: 2025.07 | D18: 594605 | E18: 李政 | F18: B级学习顾问 | G18: 顾问签约奖金 | H18: 0
A19: 17 | B19: 北京中心 | C19: 2025.07 | D19: 594605 | E19: 李政 | F19: B级学习顾问 | G19: 其它奖金 | H19: 2000 | I19: 过渡性补贴2000 | J19: OK
A20: 18 | B20: 北京中心 | C20: 2025.07 | D20: 608630 | E20: 宋增辉 | F20: B级学习顾问 | G20: 月度绩效 | H20: 2000 | I20: 新人第三个月，打满 | J20: ok
A21: 19 | B21: 北京中心 | C21: 2025.07 | D21: 608630 | E21: 宋增辉 | F21: B级学习顾问 | G21: 顾问签约奖金 | H21: 29204
A22: 20 | B22: 北京中心 | C22: 2025.07 | D22: 608630 | E22: 宋增辉 | F22: B级学习顾问 | G22: 其它奖金 | H22: 2000 | I22: 过渡性补贴2000 | J22: OK
A23: 21 | B23: 北京中心 | C23: 2025.07 | D23: 608630 | E23: 宋增辉 | F23: B级学习顾问 | G23: 顾问pk赛 | H23: 1000 | J23: OK
A24: 22 | B24: 北京中心 | C24: 2025.07 | D24: 608617 | E24: 田一禾 | F24: B级学习顾问 | G24: 月度绩效 | H24: 2000 | I24: 新人第三个月，打满 | J24: ok
A25: 23 | B25: 北京中心 | C25: 2025.07 | D25: 608617 | E25: 田一禾 | F25: B级学习顾问 | G25: 顾问签约奖金 | H25: 28682
A26: 24 | B26: 北京中心 | C26: 2025.07 | D26: 608617 | E26: 田一禾 | F26: B级学习顾问 | G26: 其它奖金 | H26: 2000 | I26: 过渡性补贴2000 | J26: OK
A27: 25 | B27: 北京中心 | C27: 2025.07 | D27: 608617 | E27: 田一禾 | F27: B级学习顾问 | G27: 顾问pk赛 | H27: 500 | J27: OK
A28: 26 | B28: 北京中心 | C28: 2025.07 | D28: 608681 | E28: 张博奥 | F28: B级学习顾问 | G28: 月度绩效 | H28: 2000 | I28: 新人第三个月，打满 | J28: ok
A29: 27 | B29: 北京中心 | C29: 2025.07 | D29: 608681 | E29: 张博奥 | F29: B级学习顾问 | G29: 顾问签约奖金 | H29: 3056
A30: 28 | B30: 北京中心 | C30: 2025.07 | D30: 608681 | E30: 张博奥 | F30: B级学习顾问 | G30: 其它奖金 | H30: 2000 | I30: 过渡性补贴2000 | J30: OK
A31: 29 | B31: 北京中心 | C31: 2025.07 | D31: 343549 | E31: 黄智超 | F31: B级学习顾问 | G31: 月度绩效 | H31: 2000 | I31: 新人第二个月，打满 | J31: ok
A32: 30 | B32: 北京中心 | C32: 2025.07 | D32: 343549 | E32: 黄智超 | F32: B级学习顾问 | G32: 顾问签约奖金 | H32: 49696
A33: 31 | B33: 北京中心 | C33: 2025.07 | D33: 343549 | E33: 黄智超 | F33: B级学习顾问 | G33: 其它奖金 | H33: 2000 | I33: 过渡性补贴2000 | J33: OK
A34: 32 | B34: 北京中心 | C34: 2025.07 | D34: 343549 | E34: 黄智超 | F34: B级学习顾问 | G34: 往月补发 | H34: 3000 | I34: 保障性收入部分：入职次月即第一个完整的考勤月，额外发放3000元保薪提成。（6月） | J34: OK
A35: 33 | B35: 北京中心 | C35: 2025.07 | D35: 343549 | E35: 黄智超 | F35: B级学习顾问 | G35: 顾问pk赛 | H35: 1500 | J35: OK
A36: 34 | B36: 北京中心 | C36: 2025.07 | D36: 合计 | H36: =SUM(H3:H34) -> 264850
A38: 备注
A39: 此张表格中的绩效奖金包含提成奖金、月度绩效、季度绩效、其他业绩奖金

Sheet 业绩核算明细
A1: 国内顾问业绩汇总（7月）
A2: 排名 | B2: 组别 | C2: 顾问 | D2: 月度数据
D3: 本月目标 | E3: 总进账 | F3: 线下退费 | G3: 手动加 | H3: 综合业绩 | I3: 月度完成率 | J3: 转介绍总业绩 | K3: 考研转介绍金额 | L3: 四六级转介绍金额 | M3: 对应提点 | N3: 提点奖金 | O3: 减去转介绍的剩余业绩 | P3: 对应提点 | Q3: 提点奖金 | R3: 总计奖金 | T3: 加考研
A4: 四六级 | C4: 刘晓娟 | D4: 650000 | E4: 1396995.6 | F4: 192383.4 | H4: =E4-F4+G4 -> 1204612.2 | I4: =H4/D4 -> 1.8532496 | J4: 187809.15 | K4: 107294.6 | L4: =J4-K4 -> 80514.55 | M4: 0.052 | N4: =L4*M4 -> 4186.7566 | O4: =H4-L4 -> 1124097.7 | P4: 0.05 | Q4: =O4*P4 -> 56204.885 | R4: =N4+Q4 -> 60391.642 | T4: =L18+R4 -> 71253.993 | V4: =VLOOKUP(C4,[1]汇总!$B:$W,22,0) -> 1543401.8 | W4: =VLOOKUP(C4,[1]汇总!$B$6:$T$53,19,0) -> 1804234.4 | X4: =W4-E4 -> 407238.8 | Y4: =V4-H4 -> 338789.5
C5: 徐健坤 | D5: 650000 | E5: 352973.3 | F5: 197846.4 | G5: 15540 | H5: =E5-F5+G5 -> 170666.9 | I5: =H5/D5 -> 0.26256446 | J5: 38550 | K5: 0 | L5: =J5-K5 -> 38550 | O5: =H5-L5 -> 132116.9 | Q5: =O5*P5 -> 0 | R5: =N5+Q5 -> 0 | V5: =VLOOKUP(C5,[1]汇总!$B:$W,22,0) -> 225898.3 | W5: =VLOOKUP(C5,[1]汇总!$B$6:$T$53,19,0) -> 353519 | X5: =W5-E5 -> 545.7 | Y5: =V5-H5 -> 55231.4
C6: 房国超 | D6: 650000 | E6: 976589.7 | F6: 86550.8 | H6: =E6-F6+G6 -> 890038.9 | I6: =H6/D6 -> 1.3692906 | J6: 89520 | K6: 0 | L6: =J6-K6 -> 89520 | M6: 0.042 | N6: =L6*M6 -> 3759.84 | O6: =H6-L6 -> 800518.9 | P6: 0.04 | Q6: =O6*P6 -> 32020.756 | R6: =N6+Q6 -> 35780.596 | V6: =VLOOKUP(C6,[1]汇总!$B:$W,22,0) -> 891090.4 | W6: =VLOOKUP(C6,[1]汇总!$B$6:$T$53,19,0) -> 973115.5 | X6: =W6-E6 -> -3474.2 | Y6: =V6-H6 -> 1051.5
C7: 李政 | D7: 650000 | E7: 396210 | F7: 82238.7 | H7: =E7-F7+G7 -> 313971.3 | I7: =H7/D7 -> 0.48303277 | J7: 31780 | K7: 0 | L7: =J7-K7 -> 31780 | O7: =H7-L7 -> 282191.3 | Q7: =O7*P7 -> 0 | R7: =N7+Q7 -> 0 | V7: =VLOOKUP(C7,[1]汇总!$B:$W,22,0) -> 329988 | W7: =VLOOKUP(C7,[1]汇总!$B$6:$T$53,19,0) -> 396455.7 | X7: =W7-E7 -> 245.7 | Y7: =V7-H7 -> 16016.7
C8: 宋增辉 | D8: 520000 | E8: 878316.7 | F8: 156062.2 | H8: =E8-F8+G8 -> 722254.5 | I8: =H8/D8 -> 1.388951 | J8: 157010 | K8: 0 | L8: =J8-K8 -> 157010 | M8: 0.042 | N8: =L8*M8 -> 6594.42 | O8: =H8-L8 -> 565244.5 | P8: 0.04 | Q8: =O8*P8 -> 22609.78 | R8: =N8+Q8 -> 29204.2 | V8: =VLOOKUP(C8,[1]汇总!$B:$W,22,0) -> 709013.5 | W8: =VLOOKUP(C8,[1]汇总!$B$6:$T$53,19,0) -> 825816.7 | X8: =W8-E8 -> -52500 | Y8: =V8-H8 -> -13241
C9: 田一禾 | D9: 520000 | E9: 758217.95 | F9: 42550.5 | H9: =E9-F9+G9 -> 715667.45 | I9: =H9/D9 -> 1.3762836 | J9: 27540 | K9: 0 | L9: =J9-K9 -> 27540 | M9: 0.042 | N9: =L9*M9 -> 1156.68 | O9: =H9-L9 -> 688127.45 | P9: 0.04 | Q9: =O9*P9 -> 27525.098 | R9: =N9+Q9 -> 28681.778 | V9: =VLOOKUP(C9,[1]汇总!$B:$W,22,0) -> 703067.75 | W9: =VLOOKUP(C9,[1]汇总!$B$6:$T$53,19,0) -> 752324.65 | X9: =W9-E9 -> -5893.3 | Y9: =V9-H9 -> -12599.7
C10: 张博奥 | D10: 520000 | E10: 418279 | F10: 36239 | H10: =E10-F10+G10 -> 382040 | I10: =H10/D10 -> 0.73469231 | O10: =H10-L10 -> 382040 | P10: 0.008 | Q10: =O10*P10 -> 3056.32 | R10: =N10+Q10 -> 3056.32 | V10: =VLOOKUP(C10,[1]汇总!$B:$W,22,0) -> 396599 | W10: =VLOOKUP(C10,[1]汇总!$B$6:$T$53,19,0) -> 418279 | X10: =W10-E10 -> 0 | Y10: =V10-H10 -> 14559
C11: 黄智超 | D11: 325000 | E11: 1225176.4 | F11: 234032.3 | H11: =E11-F11+G11 -> 991144.1 | I11: =H11/D11 -> 3.0496742 | J11: 69539 | K11: 0 | L11: =J11-K11 -> 69539 | M11: 0.052 | N11: =L11*M11 -> 3616.028 | O11: =H11-L11 -> 921605.1 | P11: 0.05 | Q11: =O11*P11 -> 46080.255 | R11: =N11+Q11 -> 49696.283 | V11: =VLOOKUP(C11,[1]汇总!$B:$W,22,0) -> 1005022.7 | W11: =VLOOKUP(C11,[1]汇总!$B$6:$T$53,19,0) -> 1208212.3 | X11: =W11-E11 -> -16964.1 | Y11: =V11-H11 -> 13878.6
C12: 小组合计 | D12: =SUM(D4:D11) -> 4485000 | E12: =SUM(E4:E11) -> 6402758.7 | F12: =SUM(F4:F11) -> 1027903.3 | G12: =SUM(G4:G7) -> 15540 | H12: =SUM(H4:H11) -> 5390395.4 | I12: =H12/D12 -> 1.2018719 | N12: =SUM(N4:N11) -> 19313.725 | Q12: =SUM(Q4:Q11) -> 187497.09 | R12: =SUM(R4:R11) -> 206810.82
A16: 排名 | B16: 组别 | C16: 顾问 | D16: 月度数据
D17: 总进账 | E17: 考研转介绍 | F17: 对应提点 | G17: 提点奖金 | H17: 减去转介绍的剩余业绩 | I17: 对应提点 | J17: 提点奖金 | K17: 退费扣除金额 | L17: 考研净奖金
A18: 考研 | C18: 刘晓娟 | D18: 358705.4 | E18: 107294.6 | F18: 0.032 | G18: =E18*F18 -> 3433.4272 | H18: =D18-E18 -> 251410.8 | I18: 0.03 | J18: =H18*I18 -> 7542.324 | K18: 113.4 | L18: =G18+J18-K18 -> 10862.351

Sheet 绩效明细
A1: 四六级 | D1: 资源处理时效（10） | H1: 老带新签约人头（30） | L1: 6月新增资源签约率（60） | P1: 合计得分 | Q1: 发放比例 | R1: 月度绩效标准 | S1: 月绩效应发
A2: 工号 | B2: 顾问 | C2: 备注 | D2: 目标 | E2: 数据 | F2: 完成率 | G2: 得分 | H2: 目标 | I2: 完成 | J2: 完成率 | K2: 得分 | L2: 目标 | M2: 完成情况 | N2: 完成率 | O2: 得分
A3: 004192 | B3: 刘晓娟 | C3: / | D3: 60min | E3: 60.03 | F3: 完成 | G3: 10 | H3: 7 | I3: 16 | J3: =I3/H3 -> 2.2857143 | K3: =30*J3 -> 68.571429 | L3: 0.27 | M3: 0.328 | N3: 1 | O3: 60 | P3: =G3+K3+O3 -> 138.57143 | Q3: 1 | R3: 2000 | S3: =R3*Q3 -> 2000
A4: 590299 | B4: 徐健坤 | C4: / | D4: 60min | E4: 24.26 | F4: 完成 | G4: 10 | H4: 7 | I4: 2 | J4: =I4/H4 -> 0.28571429 | K4: =30*J4 -> 8.5714286 | L4: 0.27 | M4: 0.2727 | N4: 1 | O4: =60*N4 -> 60 | P4: =G4+K4+O4 -> 78.571429 | Q4: 0.79 | R4: 2000 | S4: =R4*Q4 -> 1580
A5: 594606 | B5: 房国超 | C5: / | D5: 60min | E5: 9.5 | F5: 完成 | G5: 10 | H5: 7 | I5: 8 | J5: =I5/H5 -> 1.1428571 | K5: =30*J5 -> 34.285714 | L5: 0.27 | M5: 0.2699 | N5: 1 | O5: =60*N5 -> 60 | P5: =G5+K5+O5 -> 104.28571 | Q5: 1 | R5: 2000 | S5: =R5*Q5 -> 2000
A6: 594605 | B6: 李政 | C6: / | D6: 60min | E6: 无数据 | F6: 完成 | G6: 10 | H6: 7 | I6: 5 | J6: =I6/H6 -> 0.71428571 | K6: =30*J6 -> 21.428571 | L6: 0.27 | M6: 0.202 | N6: 0.444 | O6: =60*N6 -> 26.64 | P6: =G6+K6+O6 -> 58.068571 | Q6: 0 | R6: 2000 | S6: =R6*Q6 -> 0
A7: 608630 | B7: 宋增辉 | C7: 新人第三个月保护期打满 | P7: 100 | Q7: 1 | R7: 2000 | S7: 2000
A8: 608617 | B8: 田一禾 | P8: 100 | Q8: 1 | R8: 2000 | S8: 2000
A9: 608681 | B9: 张博奥 | P9: 100 | Q9: 1 | R9: 2000 | S9: 2000
A10: 343549 | B10: 黄智超 | C10: 新人第二个月保护期打满 | P10: 100 | Q10: 1 | R10: 2000 | S10: 2000

Sheet 7月顾问两周pk赛
B2: 顾问pk赛
B3: 第一周 | C3: 刘晓娟 | D3: 2000
C4: 黄智超 | D4: 1000
C5: 宋增辉 | D5: 500
B6: 第二周 | C6: 房国超 | D6: 2000
C7: 刘晓娟 | D7: 1000
C8: 宋增辉 | D8: 500
C9: 黄智超 | D9: 500
C10: 田一禾 | D10: 500

Sheet 退费数据 四六级
A1: 提交日期 | B1: 您所办理的业务类型 | C1: OA流水号 | D1: 学管姓名 | E1: 学管是否代办 | F1: 顾问姓名 | G1: 顾问是否代办 | H1: 91系统-最新报名二级渠道 | I1: 原班所属项目 | J1: 新报入班级所属项目 | K1: 退费阶段 | L1: 退费一级原因（开课前） | M1: 退费一级原因 (开课后) | N1: 退费二级原因（专业课师资匹配原因） | O1: 退费二级原因（学员意愿转变_开课前） | P1: 退费二级原因（计划冲突_开课前） | Q1: 退费二级原因（中心原因_开课前） | R1: 退费二级原因（签约话术） | S1: 退费二级原因（教师） | T1: 退费二级原因（教学） | U1: 退费二级原因（课程安排） | V1: 退费二级原因（配套服务） | W1: 退费二级原因（配套学习设施） | X1: 退费二级原因（中心原因_开课后） | Y1: 退费二级原因（计划冲突_开课后） | Z1: 退费二级原因（学员意愿转变_开课后） | AA1: 退费三级原因（完全匹配不上）-院校、学院、专业、专业课代码及名称 | AB1: 退费详细原因说明（与OA退费详细说明保持一致） | AC1: 预计报名新班学费金额 | AD1: 转班金额（请学管填写所在班级实际金额） | AE1: 转班详细原因说明 | AF1: 提交时间 | AG1: 学校 | AH1: 学院 | AI1: 年级 | AJ1: 专业 | AK1: 提交人 | AL1: 退费类型 | AM1: 学员姓名 | AN1: 学员编码 | AO1: 退费金额 | AP1: 办理日期-客服 | AQ1: 退费方式-客服 | AR1: 需要跟进的顾问/学管 | AS1: 退费/转班特殊情况备注（若需要学管提供银行卡信息，可将需求填写在此处）-客服 | AT1: 是否完成退费/转班-客服 | AU1: 父记录 | AV1: 父记录 | AW1: 备注
A2: 2025/06/17 | B2: 退费 | C2: 2025061702417 | D2: 刘畅778-刘畅 | F2: 徐健坤 | H2: 学管续费推荐 | I2: 四六级项目（弃用） | K2: 开课后退费 | M2: 计划冲突_开课后 | Y2: 个人生活/工作事务和新东方时间冲突 | AB2: 最后一节课学生上不了了，之前一直从天津跑过来上线下，不考虑线上，也不考虑保留着一节课，后面有需要再报 | AF2: 2025-06-30 | AK2: 刘畅778-刘畅 | AL2: 真实产生的退费 | AM2: 穆德佳 | AN2: BJWY4754614205 | AO2: 1800 | AP2: 2025/07/09 | AQ2: 微信退1800[图片] | AT2: TRUE
A3: 2025/06/24 | B3: 退费 | C3: 2025061500283 | D3: 李润基 | F3: 徐健坤 | H3: 其他（主动） | I3: 四六级项目-VIP | K3: 开课后退费 | M3: 计划冲突_开课后 | Y3: 个人生活/工作事务和新东方时间冲突 | AB3: 学生学校课很多，不能按照规划上课，取消了五节课，37000-850×40=3000 | AF3: 2025-06-30 | AK3: 李润基 | AL3: 真实产生的退费 | AM3: 郑好 | AN3: BJWY5610701694 | AO3: 3000 | AP3: 2025/07/01 | AQ3: 微信退回 | AT3: TRUE
A4: 2025/06/30 | B4: 退费 | C4: 18739969 | D4: 罗志勇1-罗志勇 | F4: 徐健坤 | H4: 新东方PC官网 | I4: 四六级项目（弃用） | K4: 开课前退费 | L4: 计划冲突_开课前 | P4: 学校事务和新东方时间冲突 | AB4: 学生专升本，学校两年内不让考四六级 | AF4: 2025-06-30 | AK4: 罗志勇1-罗志勇 | AL4: 真实产生的退费 | AM4: 王禹尧 | AN4: BJWY2840412022 | AO4: 15500 | AP4: 2025/07/02 | AQ4: 7.2退款成功。银联扫码支付宝退回 | AT4: TRUE
A5: 2025/07/01 | B5: 退费 | C5: 18752114 | D5: 边鑫博 | F5: 刘晓娟 | H5: 客服前台 | I5: 四六级项目（弃用） | J5: 四六级项目 | K5: 开课前退费 | L5: 中心原因_开课前 | Q5: 退出重报（报错班级） | AB5: 退出重报，占座，费用退到学员账户重新入班 | AC5: ¥5680.00 | AF5: 2025-07-01 | AK5: 边鑫博 | AL5: 转项目/转班/退出重报等未产生实际退费 | AM5: 田谨睿 | AN5: BJWY5207562563 | AO5: 5680 | AP5: 2025/07/01 | AQ5: 退至学员账户 | AT5: TRUE
A6: 2025/07/01 | B6: 退费 | C6: 18753067 | D6: 罗志勇1-罗志勇 | F6: 张博奥 | H6: 抖音来客 | I6: 四六级项目（弃用） | K6: 开课前退费 | L6: 学员意愿转变_开课前 | O6: 选择出国留学 | AB6: 高考失利 去学雅思 | AF6: 2025-07-01 | AK6: 罗志勇1-罗志勇 | AL6: 真实产生的退费 | AM6: 齐子昂 | AN6: BJWY3131685015 | AO6: 15500 | AP6: 2025/07/02 | AQ6: 微信退回 | AT6: TRUE
A7: 2025/07/02 | B7: 转班 | D7: 边鑫博 | F7: 刘晓娟 | H7: 大客服呼入 | I7: 四六级项目（弃用） | AE7: 换校区上课 | AF7: 2025-07-02 | AK7: 边鑫博 | AM7: 顾雨涵 | AN7: BJWY6589289284 | AO7: 19300 | AP7: 2025/07/02 | AQ7: 已转班 | AT7: TRUE
A8: 2025/07/02 | B8: 转班 | D8: 边鑫博 | F8: 黄智超 | G8: TRUE | H8: 线上运营推荐 | I8: 四六级项目（弃用） | AE8: 学生觉得四级单词比较简单，想转去六级班去学 原班号：YKF25001，需转至班号：YKS25001。辛苦老师操作 | AF8: 2025-07-02 | AK8: 黄智超1-黄智超 | AM8: 路靖远 | AN8: BJWY9575617816 | AO8: 5434.4 | AP8: 2025/07/02 | AQ8: 已转班 | AT8: TRUE
A9: 2025/07/03 | B9: 退费 | C9: 18762286 | D9: 边鑫博 | F9: 黄智超 | G9: TRUE | H9: 内部员工推荐 | I9: 四六级项目（弃用） | K9: 开课前退费 | L9: 学员意愿转变_开课前 | O9: 认为课程用处不大/不适合自己 | AB9: 学生报名预科小班，把大班课程退出 | AF9: 2025-07-03 | AK9: 黄智超1-黄智超 | AL9: 真实产生的退费 | AM9: 于奥洋 | AN9: BJWY8894097228 | AO9: 5680 | AP9: 2025/07/04 | AQ9: 微信原渠道退回 | AT9: TRUE
A10: 2025/07/04 | B10: 转班 | D10: 罗志勇1-罗志勇 | F10: 徐健坤 | H10: 内部员工推荐 | I10: 四六级项目（弃用） | AE10: 顾问入错班 | AF10: 2025-07-04 | AK10: 罗志勇1-罗志勇 | AM10: 陈晨 | AN10: BJWY2672207145 | AO10: 5680 | AP10: 2025/07/04 | AQ10: 已转班 | AT10: TRUE
A11: 2025/07/04 | B11: 退费 | C11: 18764400 | D11: 边鑫博 | F11: 李政 | H11: 内部员工推荐 | I11: 四六级项目（弃用） | K11: 开课前退费 | L11: 计划冲突_开课前 | P11: 个人生活/工作事务和新东方时间冲突 | AB11: 孩子暑假有夏令营，时间有冲突，不考虑线上课程，其他的时间也不方便上课 | AF11: 2025-07-04 | AK11: 边鑫博 | AL11: 真实产生的退费 | AM11: 王艺霏 | AN11: BJWY6664634220 | AO11: 4880 | AP11: 2025/07/07 | AQ11: 微信退回 | AT11: TRUE
A12: 2025/07/02 | B12: 退费 | C12: 18766840 | D12: 李小龙25-李小龙 | F12: 刘晓娟 | H12: 集团资源 | I12: 四六级项目（弃用） | K12: 开课前退费 | L12: 计划冲突_开课前 | P12: 个人生活/工作事务和新东方时间冲突 | AB12: 家长给孩子报名的新东方的雅思课程，未来想保研或出国，暂时打算先准备雅思。 | AF12: 2025-07-05 | AK12: 李小龙25-李小龙 | AL12: 真实产生的退费 | AM12: 李梓侨 | AN12: BJWY3436505557 | AO12: 6180 | AP12: 2025/07/15 | AQ12: 微信退回 | AT12: TRUE
A13: 2025/07/05 | B13: 转班 | D13: 李小龙25-李小龙 | F13: 刘晓娟 | H13: 新东方官网小程序 | I13: 四六级项目（弃用） | AE13: 7.16的班级时间冲突，需要转入WYS25035 | AF13: 2025-07-05 | AK13: 李小龙25-李小龙 | AM13: 秋清耀 | AN13: BJWY5355250935 | AO13: 6180 | AP13: 2025/07/05 | AQ13: 已转班 | AT13: TRUE
A14: 2025/07/06 | B14: 退费 | C14: 18770460 | D14: 李小龙25-李小龙 | F14: 黄智超 | H14: 小红书 | I14: 四六级项目-班课 | K14: 开课前退费 | L14: 学员意愿转变_开课前 | O14: 家人不支持考研/不支持跟班学习/意见不一致 | AB14: 孩子的情况想玩不想学习，沟通家长联系孩子去说服学习，学生还是执意不学习 | AF14: 2025-07-06 | AK14: 李小龙25-李小龙 | AL14: 真实产生的退费 | AM14: 李梓妍 | AN14: BJWY9542200862 | AO14: 19300 | AP14: 2025/07/26 | AQ14: 原渠道微信退回 | AT14: TRUE
A15: 2025/07/07 | B15: 转班 | D15: 边鑫博 | F15: 黄智超 | G15: TRUE | H15: 小红书 | I15: 四六级项目-班课 | AE15: 学员报名四级小班，8.1号开课（花园桥校区），现在想转到6级班课（花园桥校区），价格一样，课程编码不同，需要从YKF25005操作转班至YKS25005～ | AF15: 2025-07-07 | AK15: 黄智超1-黄智超 | AM15: 许博铭 | AN15: BJWY4996201639 | AO15: 20300 | AP15: 2025/07/08 | AQ15: 已转班 | AT15: TRUE
A16: 2025/07/08 | B16: 转班 | D16: 李小龙25-李小龙 | F16: 刘晓娟 | H16: 学管转介绍 | I16: 四六级项目-班课 | AE16: 想学六级课 | AF16: 2025-07-08 | AK16: 李小龙25-李小龙 | AM16: 张嘉懿 | AN16: BJWY7254640234 | AO16: 19100 | AP16: 2025/07/08 | AQ16: 已转班 | AT16: TRUE
A17: 2025/07/08 | B17: 退费 | C17: 18769348 | D17: 罗志勇1-罗志勇 | F17: 房国超 | G17: TRUE | H17: 顾问转介绍-老带新 | I17: 四六级项目-班课 | K17: 开课前退费 | L17: 学员意愿转变_开课前 | O17: 家人不支持考研/不支持跟班学习/意见不一致 | AB17: 报名时是家长先占上了课程优惠， 后续和孩子沟通，学生不想学习，家长反复劝说无果，学生不学，转班不考虑，家长无奈选择退费 | AF17: 2025-07-08 | AK17: 房国超 | AL17: 真实产生的退费 | AM17: 邹先御 | AN17: BJWY7373402810 | AO17: 15300 | AP17: 2025/07/09 | AQ17: 微信退15300[图片] | AT17: TRUE
A18: 2025/07/08 | B18: 转班 | D18: 边鑫博 | F18: 黄智超 | G18: TRUE | H18: 大客服呼入 | I18: 四六级项目-班课 | AE18: 学员报名六级和高数课程 目前想把高数转成口语，价格一样 辛苦老师操作 原班级编码：YKM25001；需转至：YK25002 辛苦老师操作。 | AF18: 2025-07-08 | AK18: 黄智超1-黄智超 | AM18: 张馨予 | AN18: BJWY8390237928 | AO18: 3725.6 | AP18: 2025/07/08 | AQ18: 已转班 | AT18: TRUE
A19: 2025/07/09 | B19: 退费 | C19: 18776707 | D19: 边鑫博 | F19: 刘晓娟 | H19: 京内毛坯数据 | I19: 四六级项目-班课 | K19: 开课前退费 | L19: 计划冲突_开课前 | P19: 个人生活/工作事务和新东方时间冲突 | AB19: 由于时间问题想先取消一下课，说明年报，保留课程拒绝 | AF19: 2025-07-09 | AK19: 边鑫博 | AL19: 真实产生的退费 | AM19: 刘昊阳 | AN19: BJWY5526467904 | AO19: 19300 | AP19: 2025/07/09 | AQ19: 微信退19300[图片] | AT19: TRUE
A20: 2025/07/09 | B20: 退费 | C20: 18776823 | D20: 边鑫博 | F20: 徐健坤 | H20: 顾问转介绍-老带新 | I20: 四六级项目-班课 | J20: 四六级项目 | K20: 开课前退费 | L20: 计划冲突_开课前 | P20: 个人生活/工作事务和新东方时间冲突 | AB20: 由于时间原因转班，退费后重新报名 | AC20: ¥6480.00 | AF20: 2025-07-09 | AK20: 边鑫博 | AL20: 转项目/转班/退出重报等未产生实际退费 | AM20: 王文涵 | AN20: XDF1928799125 | AO20: 19100 | AP20: 2025/07/11 | AQ20: 退回学员账户余额 | AT20: TRUE
F21: 刘晓娟 | I21: 四六级项目-班课 | AM21: 陈松乔 | AO21: 4402.8 | AP21: 2025/07/12 | AW21: 补加
A22: 2025/07/09 | B22: 退费 | C22: 18776843 | D22: 边鑫博 | F22: 徐健坤 | H22: 大众点评 | I22: 四六级项目-班课 | J22: 四六级项目 | K22: 开课前退费 | L22: 计划冲突_开课前 | P22: 个人生活/工作事务和新东方时间冲突 | AB22: 由于时间原因转班，退费后重新报名 | AC22: ¥6480.00 | AF22: 2025-07-09 | AK22: 边鑫博 | AL22: 转项目/转班/退出重报等未产生实际退费 | AM22: 刘东熠 | AN22: BJWY0362994456 | AO22: 19300 | AP22: 2025/07/11 | AQ22: 退回学员账户余额 | AT22: TRUE
A23: 2025/07/09 | B23: 退费 | C23: 18778970 | D23: 罗志勇1-罗志勇 | F23: 房国超 | H23: 顾问转介绍-老带新 | I23: 四六级项目-班课 | K23: 开课前退费 | L23: 计划冲突_开课前 | P23: 个人生活/工作事务和新东方时间冲突 | AB23: 学习意愿低 不考了 要去实习 | AF23: 2025-07-09 | AK23: 罗志勇1-罗志勇 | AL23: 真实产生的退费 | AM23: 杜梦琪 | AN23: BJWY5148939979 | AO23: 5680 | AP23: 2025/07/23 | AQ23: 支付宝退回 | AT23: TRUE
A24: 2025/07/09 | B24: 退费 | C24: 18776785 | D24: 罗志勇1-罗志勇 | F24: 刘晓娟 | H24: 新东方PC官网 | I24: 四六级项目-班课 | K24: 开课前退费 | L24: 计划冲突_开课前 | P24: 个人生活/工作事务和新东方时间冲突 | AB24: 暑假去学习雅思了 时间冲突 拒绝转班 | AF24: 2025-07-09 | AK24: 罗志勇1-罗志勇 | AL24: 真实产生的退费 | AM24: 李伊然 | AN24: BJWY6831352125 | AO24: 15000 | AP24: 2025/07/15 | AQ24: 7.23已完成付款 7.22用户短信未确认，已重新发送 7.16已转手工，待客户短信确认@罗志勇1 (罗志勇)—————— 暂退学生账户，原渠道为汇款，需提供原卡6235735000000768596的银行卡详细信息转手工退@罗志勇1 (罗志勇)[图片] | AT24: TRUE
A25: 2025/07/09 | B25: 退费 | C25: 18779247 | D25: 罗志勇1-罗志勇 | F25: 李政 | H25: 新东方官网APP | I25: 四六级项目-班课 | J25: 四六级项目 | K25: 开课前退费 | L25: 计划冲突_开课前 | P25: 个人生活/工作事务和新东方时间冲突 | AB25: 学生去学雅思 以及要转入线下的数学班课 | AC25: ¥4000.00 | AF25: 2025-07-09 | AK25: 罗志勇1-罗志勇 | AL25: 转项目/转班/退出重报等未产生实际退费 | AM25: 黄乐容 | AN25: BJWY9725876002 | AO25: 15000 | AP25: 2025/07/11 | AQ25: 退回学员账户余额 | AT25: TRUE
A26: 2025/07/10 | B26: 转班 | D26: 边鑫博 | F26: 黄智超 | G26: TRUE | H26: 大客服呼入 | I26: 四六级项目-班课 | AE26: 老师好 学员报名花园桥二期班：需操作转班，班号YKS25002，之前这个班未开放报名 | AF26: 2025-07-10 | AK26: 黄智超1-黄智超 | AM26: 张馨予 | AN26: BJWY8390237928 | AO26: 5434.4 | AP26: 2025/07/10 | AQ26: 已转班 | AT26: TRUE
A27: 2025/07/10 | B27: 转班 | D27: 边鑫博 | F27: 黄智超 | G27: TRUE | H27: 公众号 | I27: 四六级项目-班课 | AE27: 由于预科四级二班名额之前未开放，临近开课需将预科四级一班转至预科四级二班，价格一致，原班级编码：YKF25001；需转至：YKF25002 | AF27: 2025-07-10 | AK27: 黄智超1-黄智超 | AM27: 梁睿男 | AN27: BJWY7658289293 | AO27: 5434.4 | AP27: 2025/07/11 | AQ27: 已转班 | AT27: TRUE
A28: 2025/07/10 | B28: 转班 | D28: 余平瑶 | F28: 黄智超 | H28: 内部员工推荐 | I28: 四六级项目-班课 | AE28: 改学四级 | AF28: 2025-07-10 | AK28: 余平瑶 | AM28: 黄洋 | AN28: BJWY1884260416 | AO28: 5680 | AP28: 2025/07/11 | AQ28: 已转班 | AT28: TRUE
A29: 2025/07/11 | B29: 转班 | D29: 李玉迪1-李玉迪 | F29: 徐健坤 | H29: 小红书 | I29: 四六级项目-班课 | AE29: 学员转到第二期班上课 | AF29: 2025-07-11 | AK29: 李玉迪1-李玉迪 | AM29: 李宇萱 | AN29: BJWY7288551134 | AO29: 9160 | AP29: 2025/07/11 | AQ29: 已转班 | AT29: TRUE
A30: 2025/07/11 | B30: 转班 | D30: 李玉迪1-李玉迪 | F30: 徐健坤 | H30: 新东方官网小程序 | I30: 四六级项目-班课 | AE30: 学员时间安排转回第一期课上班，加数学课，为了时间不冲突需要搭配第一套英语课 | AF30: 2025-07-11 | AK30: 李玉迪1-李玉迪 | AM30: 高靖淇 | AN30: BJWY8253848251 | AO30: 5180 | AP30: 2025/07/11 | AQ30: 已转班 | AT30: TRUE
A31: 2025/07/11 | B31: 转班 | D31: 李玉迪1-李玉迪 | F31: 徐健坤 | H31: 内部员工推荐 | I31: 四六级项目-班课 | AE31: 学员时间安排需要转到第二套班上课 | AF31: 2025-07-11 | AK31: 李玉迪1-李玉迪 | AM31: 王韵嘉 | AN31: BJWY3569894740 | AO31: 5180 | AP31: 2025/07/11 | AQ31: 已转班 | AT31: TRUE
A32: 2025/07/11 | B32: 转班 | D32: 李玉迪1-李玉迪 | F32: 田一禾 | H32: 公众号 | I32: 四六级项目-班课 | AE32: 学生基础较好，从四级班转到六级上课 | AF32: 2025-07-11 | AK32: 李玉迪1-李玉迪 | AM32: 王洛欢 | AN32: BJWY7022979955 | AO32: 4880 | AP32: 2025/07/11 | AQ32: 已转班 | AT32: TRUE
A33: 2025/07/11 | B33: 转班 | D33: 边鑫博 | F33: 黄智超 | G33: TRUE | H33: 顾问转介绍-老带新 | I33: 四六级项目-班课 | AE33: 学员跟二期班，报名时二期班未开放名额，需要操作转班，转至班号YKS25002 | AF33: 2025-07-11 | AK33: 黄智超1-黄智超 | AM33: 郑初妍 | AN33: BJWY5518228982 | AO33: 5434.4 | AP33: 2025/07/11 | AQ33: 已转班 | AT33: TRUE
A34: 2025/07/11 | B34: 转班 | D34: 李玉迪1-李玉迪 | F34: 徐健坤 | H34: TMK合作 | I34: 四六级项目-班课 | AE34: 时间不合适 需要更换到YKF25002 | AF34: 2025-07-11 | AK34: 徐健坤1-徐健坤 | AM34: 李左文 | AN34: BJWY4028539388 | AO34: 5180 | AP34: 2025/07/12 | AQ34: 已转班 | AT34: TRUE
A35: 2025/07/11 | B35: 转班 | D35: 边鑫博 | F35: 黄智超 | G35: TRUE | H35: 顾问转介绍-老带新 | I35: 四六级项目-班课 | AE35: 家长需求将四级线下课，转为四级线上直播课 原班号：YKS25001，需转至YKSJ25001 | AF35: 2025-07-11 | AK35: 黄智超1-黄智超 | AM35: 王祎 | AN35: BJWY1508600205 | AO35: 5434.4 | AP35: 2025/07/12 | AQ35: 已转班 | AT35: TRUE
A36: 2025/07/12 | B36: 转班 | D36: 边鑫博 | F36: 徐健坤 | H36: 社群、虚拟人 | I36: 四六级项目-班课 | AE36: 时间冲突，都上不了课 | AF36: 2025-07-12 | AK36: 边鑫博 | AM36: 王美琪 | AN36: BJWY6250044765 | AO36: 4880 | AP36: 2025/07/12 | AQ36: 已转班 | AT36: TRUE
A37: 2025/07/13 | B37: 转班 | D37: 李小龙25-李小龙 | F37: 刘晓娟 | H37: 直访 | I37: 四六级项目-班课 | AE37: 没报上6月的考试，先转暑假班，等秋季班安排出来，插班转秋季班 | AF37: 2025-07-13 | AK37: 李小龙25-李小龙 | AM37: 吴丰恺 | AN37: BJWY3487591469 | AO37: 4314.7 | AP37: 2025/07/13 | AQ37: 已转班 | AT37: TRUE
A38: 2025/07/13 | B38: 退费 | C38: 18788911 | D38: 李小龙25-李小龙 | F38: 刘晓娟 | H38: 公众号 | I38: 四六级项目-班课 | K38: 开课前退费 | L38: 计划冲突_开课前 | P38: 个人生活/工作事务和新东方时间冲突 | AB38: 孩子选择复读，家长报名了高考暑期班，时间冲突 | AF38: 2025-07-13 | AG38: 北京市第一五六中学 | AH38: 询问院系未告知 | AI38: 高三 | AJ38: 询问院系未告知 | AK38: 李小龙25-李小龙 | AL38: 真实产生的退费 | AM38: 熊晟源 | AN38: BJWY2545661711 | AO38: 0 | AP38: 2025/07/15 | AQ38: 7.22已退款[图片] 300微信退回，19000转手工，退款中（7.19）———————— 暂退学生账户，原渠道为现金，需提供学生本人姓名的银行卡信息转手工退@李小龙25 (李小龙)[图片] | AT38: TRUE | AW38: 不算：19300
A39: 2025/07/13 | B39: 退费 | C39: 18789074 | D39: 李小龙25-李小龙 | F39: 宋增辉 | H39: 91搜课网 | I39: 四六级项目-班课 | K39: 开课前退费 | L39: 计划冲突_开课前 | P39: 个人生活/工作事务和新东方时间冲突 | AB39: 家长给孩子报名了其他机构的雅思，由于时间过早无法延期，和孩子商量后打算先去学雅思，等后面考六级前在报名 | AF39: 2025-07-13 | AG39: 中央民族大学 | AH39: 信息工程学院 | AI39: 大二 | AJ39: 电子信息工程 | AK39: 李小龙25-李小龙 | AL39: 真实产生的退费 | AM39: 虎葆霖 | AN39: BJWY9727135037 | AO39: 6180 | AP39: 2025/07/26 | AQ39: 原渠道微信退回 | AT39: TRUE
A40: 2025/07/13 | B40: 转班 | D40: 李玉迪1-李玉迪 | F40: 房国超 | G40: TRUE | H40: 内部员工推荐 | I40: 四六级项目-班课 | AE40: 用户先报的四级小班YKF25006，YKF25006未开课，家长感觉四级对孩子简单些，申请转班到六级小班YKS25004， | AF40: 2025-07-13 | AK40: 房国超 | AM40: 王彦均 | AN40: BJWY8590362294 | AO40: 19500 | AP40: 2025/07/13 | AQ40: 已转班 | AT40: TRUE
A41: 2025/07/13 | B41: 转班 | D41: 边鑫博 | F41: 李政 | H41: 公众号 | I41: 四六级项目-班课 | AE41: 学生难度要提高，四级班转六级班 平行转 | AF41: 2025-07-13 | AK41: 边鑫博 | AM41: 韩明轩 | AN41: BJWY6308568833 | AO41: 4802.1 | AP41: 2025/07/13 | AQ41: 已转班 | AT41: TRUE
A42: 2025/07/13 | B42: 转班 | D42: 边鑫博 | F42: 宋增辉 | H42: 顾问转介绍-老带新 | I42: 四六级项目-班课 | AE42: 转班原因：学生时间冲突，换校区上课 | AF42: 2025-07-13 | AK42: 边鑫博 | AM42: 倪昊越 | AN42: BJWY7142051109 | AO42: 8801.1 | AP42: 2025/07/13 | AQ42: 已转班 | AT42: TRUE
A43: 2025/07/14 | B43: 转班 | D43: 边鑫博 | F43: 张博奥 | H43: 集团资源 | I43: 四六级项目-班课 | AE43: 时间不合适 | AF43: 2025-07-14 | AK43: 边鑫博 | AM43: 葛思曈 | AN43: BJWY0612472125 | AO43: 6180 | AP43: 2025/07/14 | AQ43: 已转班 | AT43: TRUE
A44: 2025/07/14 | B44: 转班 | D44: 余平瑶 | F44: 刘晓娟 | H44: 大客服呼入 | I44: 四六级项目-班课 | AE44: 孩子是新大一，上六级怕跟不上。转班到四级 | AF44: 2025-07-14 | AK44: 余平瑶 | AM44: 王钧浩 | AN44: BJWY5992971962 | AO44: 5680 | AP44: 2025/07/14 | AQ44: 已转班 | AT44: TRUE
A45: 2025/07/14 | B45: 转班 | D45: 边鑫博 | F45: 房国超 | H45: 线上运营推荐 | I45: 四六级项目-班课 | AE45: 就是要上秋季班 | AF45: 2025-07-14 | AK45: 边鑫博 | AM45: 姜昕雨 | AN45: BJWY7159258932 | AO45: 19300 | AP45: 2025/07/14 | AQ45: 已转班 | AT45: TRUE
A46: 2025/07/14 | B46: 转班 | D46: 李玉迪1-李玉迪 | F46: 刘文君6-刘文君(北京四六级/专四专八/大学预科) | H46: 内部员工推荐 | I46: 四六级项目-班课 | AE46: 学员时间不合适需要转班到秋季 | AF46: 2025-07-14 | AK46: 李玉迪1-李玉迪 | AM46: 田郭禹杰 | AN46: BJWY1784039439 | AO46: 4558.8 | AP46: 2025/07/14 | AQ46: 已转班 | AT46: TRUE
A47: 2025/07/04 | B47: 退费 | C47: NO.2025070402107 | D47: 刘畅778-刘畅 | F47: 刘晓娟 | H47: 新东方官网小程序 | I47: 四六级项目-VIP | K47: 开课后退费 | M47: 学员意愿转变_开课后 | Z47: 个人身体原因无法承受高强度学习 | AB47: 学生已经报名了大班课了，所以要把一对一退掉 | AF47: 2025-07-15 | AG47: 北京工业大学 | AH47: 文法学部 | AI47: 大二 | AJ47: 法学 | AK47: 刘畅778-刘畅 | AL47: 真实产生的退费 | AM47: 刘雨璐 | AN47: BJWY3672853625 | AO47: 4900 | AP47: 2025/07/17 | AQ47: 支付宝退回 | AT47: TRUE
A48: 2025/07/15 | B48: 转班 | D48: 李玉迪1-李玉迪 | F48: 刘晓娟 | H48: 京内毛坯数据 | I48: 四六级项目-班课 | AE48: 学员时间不合适，需要转班 | AF48: 2025-07-15 | AK48: 李玉迪1-李玉迪 | AM48: 王若维 | AN48: XDF072231222318376 | AO48: 0 | AP48: 2025/07/15 | AQ48: 已转班 | AT48: TRUE | AW48: 作废，代办，不算进账和退费 | AX48: 5180
A49: 2025/07/16 | B49: 退费 | C49: 18796059 | D49: 李小龙25-李小龙 | F49: 刘晓娟 | H49: 内部员工推荐 | I49: 四六级项目-班课 | K49: 开课前退费 | L49: 计划冲突_开课前 | P49: 个人生活/工作事务和新东方时间冲突 | AB49: 学员3月报名的，没有时间学习，态度强硬 | AF49: 2025-07-16 | AG49: 北京体育大学 | AH49: 体育商学院 | AI49: 大二 | AJ49: 体育 | AK49: 李小龙25-李小龙 | AL49: 真实产生的退费 | AM49: 卫洋 | AN49: BJWY6384005178 | AO49: 19800 | AP49: 2025/07/19 | AQ49: 微信退19800[图片] | AT49: TRUE
A50: 2025/07/16 | B50: 转班 | D50: 李玉迪1-李玉迪 | F50: 田一禾 | H50: TMK合作 | I50: 四六级项目-班课 | AE50: 时间不合适需要转到秋季班线上 | AF50: 2025-07-16 | AK50: 李玉迪1-李玉迪 | AM50: 黄雨琨 | AN50: BJWY7854104471 | AO50: 6180 | AP50: 2025/07/16 | AQ50: 已转班，500差价原渠道微信退回 | AT50: TRUE
A51: 2025/07/16 | B51: 转班 | D51: 边鑫博 | F51: 黄智超 | H51: 小红书 | I51: 四六级项目-班课 | AE51: 要上八月份班级[图片] | AF51: 2025-07-16 | AK51: 边鑫博 | AM51: 许博铭 | AN51: BJWY4996201639 | AO51: 20300 | AP51: 2025/07/16 | AQ51: 已转班 | AT51: TRUE
A52: 2025/07/17 | B52: 转班 | D52: 边鑫博 | F52: 宋增辉 | H52: 学管转介绍 | I52: 四六级项目-班课 | AE52: 转班花园桥，离家近 | AF52: 2025-07-17 | AK52: 边鑫博 | AM52: 周天韵 | AN52: BJWY3220705249 | AO52: 19800 | AP52: 2025/07/17 | AQ52: 已转班 | AT52: TRUE
A53: 2025/07/18 | B53: 转班 | D53: 边鑫博 | F53: 黄智超 | H53: 内部员工推荐 | I53: 四六级项目-班课 | AE53: 没时间上，往后期转 | AF53: 2025-07-18 | AK53: 边鑫博 | AM53: 于奥洋 | AN53: BJWY8894097228 | AO53: 20300 | AP53: 2025/07/18 | AQ53: 已转班 | AT53: TRUE
A54: 2025/07/18 | B54: 转班 | D54: 余平瑶 | F54: 黄智超 | H54: 内部员工推荐 | I54: 四六级项目-班课 | AE54: 学生基础较好，直接上六级 | AF54: 2025-07-18 | AK54: 余平瑶 | AM54: 翟培越 | AN54: BJWY7484451181 | AO54: 5680 | AP54: 2025/07/18 | AQ54: 已转班 | AT54: TRUE
A55: 2025/07/18 | B55: 转班 | D55: 李玉迪1-李玉迪 | F55: 黄智超 | H55: 新东方官网M站 | I55: 四六级项目-班课 | AE55: 学生八月要学车，申请转班 | AF55: 2025-07-18 | AK55: 李玉迪1-李玉迪 | AM55: 何格 | AN55: BJWY7411043612 | AO55: 5180 | AP55: 2025/07/18 | AQ55: 已转班 | AT55: TRUE
A56: 2025/07/18 | B56: 退费 | C56: 18780198 | D56: 边鑫博 | F56: 黄智超 | H56: 小红书 | I56: 四六级项目-班课 | K56: 开课前退费 | L56: 计划冲突_开课前 | P56: 学校事务和新东方时间冲突 | AB56: 退到储值账户，留着保命一对一 孩子家长给孩子提前报名预科全科课程，后来孩子来听试听课，感觉内容太深奥了听不懂，家长想要把费用退至储值，后续有一对一需求再续费报名，要等到开学以后孩子确定数学是哪本书再决定。 | AF56: 2025-07-18 | AG56: 人大附中北京经济技术开发区学校 | AH56: 无 | AI56: 高三 | AJ56: 无 | AK56: 边鑫博 | AL56: 真实产生的退费 | AM56: 张雨白 | AN56: BJWY6774392790 | AO56: 2840 | AP56: 2025/07/18 | AQ56: 退至学员账户[图片] | AT56: TRUE
A57: 2025/07/18 | B57: 退费 | C57: 18799609 | D57: 李玉迪1-李玉迪 | E57: TRUE | F57: 房国超 | H57: 小红书 | I57: 四六级项目-班课 | K57: 开课前退费 | L57: 中心原因_开课前 | Q57: 特殊优惠 | AB57: 计费错误返款（学员退费完成后，发现计费错误导致再次退费） 用户报名时未使用团报优惠，用户在朋友得知有团报优惠，未给使用，强烈要求返还差价补优惠 | AF57: 2025-07-18 | AG57: 未知 | AH57: 未知 | AI57: 新大一 | AJ57: 未知 | AK57: 李玉迪1-李玉迪 | AL57: 真实产生的退费 | AM57: 陈昊然 | AN57: BJWY3597699881 | AO57: 800 | AP57: 2025/07/31 | AQ57: 支付宝退回 | AT57: TRUE
A58: 2025/07/18 | B58: 退费 | C58: 18799518 | D58: 李玉迪1-李玉迪 | F58: 徐健坤 | H58: 阿里本地通 | I58: 四六级项目-班课 | K58: 开课前退费 | L58: 学员意愿转变_开课前 | O58: 自己找到老师复习 | AB58: 开课前退费，WYF25031。7.5号跟顾问提出要退，顾问开课前两天同步。未消耗课时。学员暑期实践不合适不参与暑假班，建议转到秋季，说家里人不放心学费放外面，要上课了再说，不考虑转班。电话沟通，说可以给家里人打电话表明一下学费在新东方很安全，但是学生情绪比较激动，说时间很久了，家长那边也沟通过没效果，要求快点退出，加急办理 | AF58: 2025-07-18 | AG58: 北京农学院 | AH58: 食品科学与工程学院 | AI58: 大二 | AJ58: 食品科学与工程 | AK58: 李玉迪1-李玉迪 | AL58: 真实产生的退费 | AM58: 段戌 | AN58: BJWY7036398711 | AO58: 6180 | AP58: 2025/07/19 | AQ58: 微信退6180[图片] | AT58: TRUE
A59: 2025/07/19 | B59: 转班 | D59: 徐岩91-徐岩 | F59: 刘晓娟 | H59: 内部员工推荐 | I59: 四六级项目-班课 | AE59: 学员想学六级 | AF59: 2025-07-19 | AK59: 徐岩91-徐岩 | AM59: 张瀚霖 | AN59: BJWY8453580263 | AO59: 19300 | AP59: 2025/07/19 | AQ59: 已转班 | AT59: TRUE
A60: 2025/07/20 | B60: 退费 | C60: 2025072000380 | D60: 徐岩91-徐岩 | F60: 刘晓娟 | H60: 小红书 | I60: 四六级项目-VIP | J60: 四六级项目 | K60: 开课前退费 | L60: 学员意愿转变_开课前 | O60: 认为课程用处不大/不适合自己 | AB60: 退费报大课时 | AC60: ¥51500.00 | AF60: 2025-07-20 | AG60: 工商大学 | AH60: 经济 | AI60: 大四 | AJ60: 数学 | AK60: 徐岩91-徐岩 | AL60: 转项目/转班/退出重报等未产生实际退费 | AM60: 贺思瀚 | AN60: BJWY5120583544 | AO60: 0 | AP60: 2025/07/20 | AQ60: 退回账户余额 | AT60: TRUE | AW60: 作废，当月补钱入班，算进账，无退费
A61: 2025/07/20 | B61: 转班 | D61: 罗志勇1-罗志勇 | F61: 刘晓娟 | H61: 小红书 | I61: 四六级项目-班课 | AE61: 学生没有时间上 先转到秋季，然后转到寒假 | AF61: 2025-07-20 | AK61: 罗志勇1-罗志勇 | AM61: 汪宣晓 | AN61: BJWY5490718239 | AO61: 5680 | AP61: 2025/07/20 | AQ61: 已转班 | AT61: TRUE
A62: 2025/07/20 | B62: 转班 | D62: 罗志勇1-罗志勇 | F62: 刘晓娟 | H62: 京内毛坯数据 | I62: 四六级项目-班课 | AE62: 学生暑假没时间 转到秋季上 | AF62: 2025-07-20 | AK62: 罗志勇1-罗志勇 | AM62: 张伯泽 | AN62: BJWY7505841062 | AO62: 5531 | AP62: 2025/07/20 | AQ62: 已转班 | AT62: TRUE
A63: 2025/07/20 | B63: 转班 | D63: 李玉迪1-李玉迪 | F63: 李政 | G63: TRUE | H63: 顾问转介绍-老带新 | I63: 四六级项目-班课 | AE63: 李政老师报名时班号输入错误，同一个班级，价格一样，辛苦老师操作转班 | AF63: 2025-07-20 | AK63: 李政79-李政 | AM63: 涂昕童 | AN63: BJWY2751118744 | AO63: 5680 | AP63: 2025/07/20 | AQ63: 已转班 | AT63: TRUE
A64: 2025/07/20 | B64: 转班 | D64: 李玉迪1-李玉迪 | F64: 李政 | G64: TRUE | H64: 顾问转介绍-老带新 | I64: 四六级项目-班课 | AE64: 李政老师输入班号错误 | AF64: 2025-07-20 | AK64: 李政79-李政 | AM64: 涂昕童 | AN64: BJWY2751118744 | AO64: 5680 | AP64: 2025/07/20 | AQ64: 已转班 | AT64: TRUE
A65: 2025/07/21 | B65: 转班 | D65: 罗志勇1-罗志勇 | F65: 刘晓娟 | H65: 小红书 | I65: 四六级项目-班课 | AE65: 学生从暑假班就开始转班，但是第二期暑假线上不开，现在转到秋季，学生最终决定转暑假跟线上直播 | AF65: 2025-07-21 | AK65: 罗志勇1-罗志勇 | AM65: 汪宣晓 | AN65: BJWY5490718239 | AO65: 5680 | AP65: 2025/07/21 | AQ65: 已转班 | AT65: TRUE
A66: 2025/07/21 | B66: 转班 | D66: 李玉迪1-李玉迪 | F66: 李政 | G66: TRUE | H66: 京内毛坯数据 | I66: 四六级项目-班课 | AE66: 家长查看完所有课程安排后，想要从YKF25003转到YKF25005班级 辛苦老师把原班级5180退回余额，差价已经补齐 | AF66: 2025-07-21 | AK66: 李政79-李政 | AM66: 唐灵浩 | AN66: XDF082307162051911 | AO66: 5180 | AP66: 2025/07/21 | AQ66: 已转班 | AT66: TRUE
A67: 2025/07/21 | B67: 转班 | D67: 边鑫博 | F67: 黄智超 | G67: TRUE | H67: 会销/讲座 | I67: 四六级项目-班课 | AE67: 家长要更换孩子学习的课程 把口语换成数学 价格一样 | AF67: 2025-07-21 | AK67: 黄智超1-黄智超 | AM67: 唐瑡淼 | AN67: BJWY0866987120 | AO67: 4680 | AP67: 2025/07/21 | AQ67: 已转班 | AT67: TRUE
A68: 2025/07/21 | B68: 转班 | D68: 边鑫博 | F68: 黄智超 | G68: TRUE | H68: 内部员工推荐 | I68: 四六级项目-班课 | AE68: 家长需要孩子换到花园桥校区上课，辛苦老师转班～ | AF68: 2025-07-21 | AK68: 黄智超1-黄智超 | AM68: 汤镓珲 | AN68: BJWY7103788159 | AO68: 5680 | AP68: 2025/07/21 | AQ68: 已转 | AT68: TRUE
A69: 2025/07/22 | B69: 转班 | D69: 余平瑶 | F69: 田一禾 | H69: 新东方官网小程序 | I69: 四六级项目-班课 | AE69: 学员申请转到线下上课 | AF69: 2025-07-22 | AK69: 李玉迪1-李玉迪 | AM69: 陈兆骞 | AN69: BJWY3877559849 | AO69: 5680 | AP69: 2025/07/22 | AQ69: 已转班 | AT69: TRUE
A70: 2025/07/22 | B70: 退费 | C70: 18809548 | D70: 罗志勇1-罗志勇 | F70: 李政 | H70: 大客服呼入 | I70: 四六级项目-班课 | K70: 开课后退费 | M70: 计划冲突_开课后 | Y70: 个人生活/工作事务和新东方时间冲突 | AB70: 【开课后退费】学生蔡乙鸣，WYSJ25033，学生打电话反馈时间不合适，经过沟通后，学生是有一份实习的工作，每天晚上都需要加班，无法跟直播。建议沟通看回放或者转到秋季。学生反馈秋季自己没时间，每天晚上都有课，回放的话效果不好。拒绝转班 | AF70: 2025-07-22 | AG70: 北京物资学院 | AH70: 商学院 | AI70: 大二 | AJ70: 会计学 | AK70: 罗志勇1-罗志勇 | AL70: 真实产生的退费 | AM70: 蔡乙鸣 | AN70: BJWY4522476575 | AO70: 4745.6 | AP70: 2025/07/31 | AQ70: 微信退还 | AT70: TRUE
A71: 2025/07/22 | B71: 退费 | C71: 18809660 | D71: 李玉迪1-李玉迪 | F71: 田一禾 | H71: 新东方官网小程序 | I71: 四六级项目-班课 | J71: 四六级项目 | K71: 开课前退费 | L71: 中心原因_开课前 | Q71: 退出重报（取消班/合班/延转/选班/扩科等） | AB71: 学员报名线上班，但是计划有变转到线下班，转班操作问题目前有几节没有转，需要把目前在班金额退出重新转班。之前课程未上课无考勤打卡记录，将缺勤部分转走 | AC71: ¥5680.00 | AF71: 2025-07-22 | AG71: 新大一 | AH71: 新大一 | AI71: 大一 | AJ71: 未知 | AK71: 李玉迪1-李玉迪 | AL71: 转项目/转班/退出重报等未产生实际退费 | AM71: 陈兆骞 | AN71: BJWY3877559849 | AO71: 710 | AP71: 2025/07/22 | AQ71: 退回学员账户 | AT71: TRUE
A72: 2025/07/22 | B72: 转班 | D72: 李玉迪1-李玉迪 | F72: 田一禾 | H72: 新东方官网小程序 | I72: 四六级项目-班课 | AE72: 学员重新办理转班 | AF72: 2025-07-22 | AK72: 李玉迪1-李玉迪 | AM72: 陈兆骞 | AN72: BJWY3877559849 | AO72: 0 | AP72: 2025/07/22 | AQ72: 已转班 | AT72: TRUE | AW72: 重复，作废，4870
A73: 2025/07/22 | B73: 退费 | C73: 18809938 | D73: 罗志勇1-罗志勇 | F73: 田一禾 | H73: 社群、虚拟人 | I73: 四六级项目-班课 | K73: 开课前退费 | L73: 学员意愿转变_开课前 | O73: 家人不支持考研/不支持跟班学习/意见不一致 | AB73: 开课前退费】贺子岳，WYFJ25033 学生妈妈给学生报名的，在报名的时候孩子就不同意，在开课前期就联系不上孩子，微信，电话均拒绝沟通。妈妈最后无奈孩子不上课，没有办法，只能申请退费 | AF73: 2025-07-22 | AG73: 北京石油化工学院 | AH73: 机械工程学院 | AI73: 大二 | AJ73: 机器人工程 | AK73: 罗志勇1-罗志勇 | AL73: 真实产生的退费 | AM73: 贺子岳 | AN73: BJWY3956726108 | AO73: 5622 | AP73: 2025/07/31 | AQ73: 微信退还 | AT73: TRUE
A74: 2025/07/22 | B74: 转班 | D74: 李玉迪1-李玉迪 | F74: 宋增辉 | H74: 地图标点 | I74: 四六级项目-班课 | AE74: 时间不合适需要转班 | AF74: 2025-07-22 | AK74: 李玉迪1-李玉迪 | AM74: 王思雨 | AN74: BJWY8251464999 | AO74: 5434.4 | AP74: 2025/07/23 | AQ74: 已转班 | AT74: TRUE
A75: 2025/07/22 | B75: 转班 | D75: 李玉迪1-李玉迪 | F75: 徐健坤 | H75: TMK合作 | I75: 四六级项目-班课 | AE75: 时间不合适需要转班 | AF75: 2025-07-22 | AK75: 李玉迪1-李玉迪 | AM75: 李左文 | AN75: BJWY4028539388 | AO75: 5180 | AP75: 2025/07/23 | AQ75: 已转班 | AT75: TRUE
A76: 2025/07/22 | B76: 转班 | D76: 李玉迪1-李玉迪 | F76: 宋增辉 | H76: 线上校代 | I76: 四六级项目-班课 | AE76: 时间不合适需要转班 | AF76: 2025-07-22 | AK76: 李玉迪1-李玉迪 | AM76: 李想 | AN76: BJWY7275817502 | AO76: 5680 | AP76: 2025/07/23 | AQ76: 已转班 | AT76: TRUE
A77: 2025/07/22 | B77: 转班 | D77: 李玉迪1-李玉迪 | F77: 刘晓娟 | H77: 京内毛坯数据 | I77: 四六级项目-班课 | AE77: 时间不合适需要转班 | AF77: 2025-07-22 | AK77: 李玉迪1-李玉迪 | AM77: 贺语柔 | AN77: BJWY3188416484 | AO77: 2317 | AP77: 2025/07/23 | AQ77: 已转班 | AT77: TRUE | AW77: 跟一禾分单
A78: 2025/07/23 | B78: 退费 | C78: 18811765 | D78: 罗志勇1-罗志勇 | F78: 宋增辉 | H78: 新东方PC官网 | I78: 四六级项目-班课 | K78: 开课前退费 | L78: 学员意愿转变_开课前 | O78: 认为课程用处不大/不适合自己 | AB78: 【开课前退费】李睿鹏，WYSJ25033，在缴费还未交接时就提出退费，和家长沟通过后确认要看历史回放，不跟新班，保留教材 | AF78: 2025-07-23 | AG78: 首都医科大学 | AH78: 拒绝告知 | AI78: 大二 | AJ78: 拒绝告知 | AK78: 罗志勇1-罗志勇 | AL78: 真实产生的退费 | AM78: 李睿鹏 | AN78: XDF4356697707 | AO78: 5622 | AP78: 2025/07/31 | AQ78: 微信退还 | AT78: TRUE
A79: 2025/07/23 | B79: 退费 | C79: 18811876 | D79: 罗志勇1-罗志勇 | F79: 宋增辉 | H79: 新东方官网M站 | I79: 四六级项目-班课 | K79: 开课前退费 | L79: 学员意愿转变_开课前 | O79: 家人不支持考研/不支持跟班学习/意见不一致 | AB79: 【开课前退费】吴文轩，WYFJ25033，孩子不愿意去学，家长劝不动，顾问和孩子视频沟通过，孩子不愿意去学，不接受转班，要求退费。 | AF79: 2025-07-23 | AG79: 华南师范大学 | AH79: 电子工程与科学学院 | AI79: 大二 | AJ79: 集成电路设计 | AK79: 罗志勇1-罗志勇 | AL79: 真实产生的退费 | AM79: 吴文轩 | AN79: BJWY0333152891 | AO79: 5622 | AP79: 2025/07/31 | AQ79: 微信退还 | AT79: TRUE
A80: 2025/07/23 | B80: 转班 | D80: 罗志勇1-罗志勇 | F80: 刘晓娟 | H80: 京内毛坯数据 | I80: 四六级项目-班课 | AE80: 学员姓名：赵亦楠 学员编号：BJWY8969534080 转班原因： 时间不合适需要转班，原计划转线上二期班，现在二期班取消，已经额外申请500补偿。顾问已经申请优惠特批 班级信息：WYSJ25033转到WYS25035 | AF80: 2025-07-23 | AK80: 罗志勇1-罗志勇 | AM80: 赵亦楠 | AN80: BJWY8969534080 | AO80: 5180 | AP80: 2025/07/24 | AQ80: 已转班 | AT80: TRUE
A81: 2025/07/23 | B81: 退费 | C81: 18782020 | D81: 边鑫博 | F81: 刘晓娟 | H81: 坦途网 | I81: 四六级项目-班课 | K81: 开课前退费 | L81: 计划冲突_开课前 | P81: 个人生活/工作事务和新东方时间冲突 | AB81: 孩子在北京全身过敏 | AF81: 2025-07-23 | AG81: 黑龙江省大庆市铁人中学 | AH81: 询问院系未告知 | AI81: 高三 | AJ81: 询问院系未告知 | AK81: 边鑫博 | AL81: 真实产生的退费 | AM81: 田谨睿 | AN81: BJWY5207562563 | AO81: 5680 | AP81: 2025/07/23 | AQ81: 微信退5680[图片] | AT81: TRUE
A82: 2025/07/23 | B82: 退费 | C82: 18801738 | D82: 徐岩91-徐岩 | F82: 徐健坤 | H82: 教育宝 | I82: 四六级项目-班课 | K82: 开课前退费 | L82: 计划冲突_开课前 | P82: 个人生活/工作事务和新东方时间冲突 | AB82: 孩子自己不想学习 家长给报的 | AF82: 2025-07-23 | AG82: 北京工商大学 | AH82: 金融 | AI82: 大二 | AJ82: 未告知 | AK82: 徐岩91-徐岩 | AL82: 真实产生的退费 | AM82: 李子尧 | AN82: BJWY4332051597 | AO82: 6180 | AP82: 2025/07/23 | AQ82: 支付宝退回 | AT82: TRUE
A83: 2025/07/23 | B83: 退费 | C83: 18812452 | D83: 徐岩91-徐岩 | F83: 徐健坤 | H83: TMK合作 | I83: 四六级项目-班课 | K83: 开课前退费 | L83: 计划冲突_开课前 | P83: 个人生活/工作事务和新东方时间冲突 | AB83: 孩子暑假要留校，跟导师做项目，要来北京有可能明年六月份，线上课不接受，觉得线上效果不行，孩子学习状态不适合线上，寒假孩子不来北京，无转班计划，申请退费 | AF83: 2025-07-23 | AG83: 西安医学院 | AH83: 药学院 | AI83: 大一 | AJ83: 药学 | AK83: 徐岩91-徐岩 | AL83: 真实产生的退费 | AM83: 杨恺乐 | AN83: BJWY4572974158 | AO83: 6180 | AP83: 2025/07/23 | AQ83: 微信退6180[图片] | AT83: TRUE
A84: 2025/07/24 | B84: 退费 | C84: 18795197 | D84: 边鑫博 | F84: 黄智超 | H84: 内部员工推荐 | I84: 四六级项目-班课 | K84: 开课后退费 | M84: 课程安排 | U84: 休息时间安排合理性 | AB84: 上午英语，下午数学上一天很困效果不好，家长反馈学生一天8小时吃不消，且数学内容对于学生本人来说存在一定难度 | AF84: 2025-07-24 | AG84: 北京一零一中石油分校 | AH84: 北京一零一中石油分校 | AI84: 高三 | AJ84: 北京一零一中石油分校 | AK84: 边鑫博 | AL84: 真实产生的退费 | AM84: 林子欣 | AN84: BJWY3796719619 | AO84: 3068.6 | AP84: 2025/07/24 | AQ84: 微信退3068.6[图片] | AT84: TRUE
A85: 2025/07/24 | B85: 退费 | C85: 18802918 | D85: 边鑫博 | F85: 房国超 | H85: 公众号 | I85: 四六级项目-班课 | K85: 开课后退费 | M85: 计划冲突_开课后 | Y85: 个人生活/工作事务和新东方时间冲突 | AB85: 【开课后退费】报名班级WYF25032，7.18号提出退费消耗4课次，退费原因学生暑假时间紧凑，也有腰伤，暂不考虑暑假补课了。给出建议看线上或者转班秋季均拒绝，目前已排练为主，开学学生有考试。有希望回流 | AF85: 2025-07-24 | AG85: 北京舞蹈学院 | AH85: 未告知 | AI85: 高三 | AJ85: 未告知 | AK85: 边鑫博 | AL85: 真实产生的退费 | AM85: 胡馨月 | AN85: BJWY1899809049 | AO85: 17565.1 | AP85: 2025/07/24 | AQ85: 微信退17565.1[图片] | AT85: TRUE
A86: 2025/07/24 | B86: 转班 | D86: 边鑫博 | F86: 黄智超 | H86: 内部员工推荐 | I86: 四六级项目-班课 | AE86: 时间原因 | AF86: 2025-07-24 | AK86: 边鑫博 | AM86: 于奥洋 | AN86: BJWY8894097228 | AO86: 20300 | AP86: 2025/07/24 | AQ86: 已转班 | AT86: TRUE
A87: 2025/07/24 | B87: 转班 | D87: 边鑫博 | F87: 刘晓娟 | H87: 公众号 | I87: 四六级项目-班课 | AE87: 和数学冲突 | AF87: 2025-07-24 | AK87: 边鑫博 | AM87: 严悦城 | AN87: BJWY5002435758 | AO87: 3998.9 | AP87: 2025/07/24 | AQ87: 已转班 | AT87: TRUE
A88: 2025/07/25 | B88: 退费 | C88: 18807444 | D88: 李玉迪1-李玉迪 | F88: 刘晓娟 | H88: 内部员工推荐 | I88: 四六级项目-班课 | K88: 开课前退费 | L88: 学员意愿转变_开课前 | O88: 认为课程用处不大/不适合自己 | AB88: 开课前退费，YKF25002，未消耗课时。家长同时了解咨询四级和雅思，最终决定学雅思退掉四级课，跟家长建议了四六级都是要考的进行引导，但是家长不愿多沟通执意退费，且登录公众号又提交一次退费，需要尽快办理退出。之后有回流可能性 | AF88: 2025-07-25 | AG88: 新大一 | AH88: 新大一 | AI88: 新大一 | AJ88: 新大一 | AK88: 李玉迪1-李玉迪 | AL88: 真实产生的退费 | AM88: 夏枢豪 | AN88: BJWY2889681785 | AO88: 5180 | AP88: 2025/07/25 | AQ88: 微信退回 | AT88: TRUE
A89: 2025/07/25 | B89: 退费 | C89: 18799555 | D89: 李玉迪1-李玉迪 | F89: 李政 | H89: 职递 | I89: 四六级项目-班课 | K89: 开课前退费 | L89: 学员意愿转变_开课前 | O89: 认为课程用处不大/不适合自己 | AB89: 开课前退费，WYF25031。学员开课前一天晚上提出退费。未消耗课时学员下学期学校考不了四级，这半年不跟班学习了，建议转到寒假或者是春季班，和家里商量之后觉得还是先退出，不考虑转班。电话劝转班提前学习导学课和背单词监督，挂完电话微信说还是退吧，以后再说。有回流可能性 | AF89: 2025-07-25 | AG89: 新大一 | AH89: 新大一 | AI89: 新大一 | AJ89: 新大一 | AK89: 李玉迪1-李玉迪 | AL89: 真实产生的退费 | AM89: 王丛睿 | AN89: BJWY0433349223 | AO89: 6180 | AP89: 2025/07/26 | AQ89: 原渠道微信退回 | AT89: TRUE
A90: 2025/07/26 | B90: 转班 | D90: 徐岩91-徐岩 | F90: 黄智超 | H90: 学管续费推荐 | I90: 四六级项目-班课 | AE90: 原班级取消 秋季上课 | AF90: 2025-07-26 | AK90: 徐岩91-徐岩 | AM90: 王熙昆 | AN90: BJWY1229796316 | AO90: 6180 | AP90: 2025/07/26 | AQ90: 已转班 | AT90: TRUE
A91: 2025/07/27 | B91: 退费 | C91: 18819247 | D91: 余平瑶 | F91: 宋增辉 | H91: 顾问转介绍-新带新 | I91: 四六级项目-班课 | K91: 开课后退费 | M91: 学员意愿转变_开课后 | Z91: 认为课程用处不大/不适合自己 | AB91: 【已开课退费】学生报名六级无忧计划（线上优享/新大一专属），学生表示大一学校不让考四六级，现在学习有些早。家长也让孩子先退掉，寒假的时候再报名。转班、费用保留都不再考虑。寒假班上线后可进行回流。消耗2课次 | AF91: 2025-07-27 | AG91: 未告知 | AH91: 未告知 | AI91: 大一 | AJ91: 未告知 | AK91: 余平瑶 | AL91: 真实产生的退费 | AM91: 马一伊 | AN91: BJWY0650681029 | AO91: 4323.7 | AP91: 2025/07/28 | AQ91: 微信退回 | AT91: TRUE
A92: 2025/07/27 | B92: 退费 | C92: 18819511 | D92: 余平瑶 | F92: 田一禾 | H92: 代理商合作 | I92: 四六级项目-班课 | K92: 开课后退费 | M92: 学员意愿转变_开课后 | Z92: 认为课程用处不大/不适合自己 | AB92: 【已开课退费】学生报名新大一六级线上课程，当前是录取到了北京联合大学。六级课程上了4次，学生不太能跟得上。跟家长沟通可以转班到四级，或者上一对一，家长都不考虑。且学生12月也考不了四级。一对一的课程，学生在初高中的时候就有跟一位老师在上，这个老师也能上四六级的内容。家长要准备回去跟这个老师上一对一的课。态度也比较坚决要退出。 | AF92: 2025-07-27 | AG92: 北京联合大学 | AH92: 会计学院 | AI92: 大一 | AJ92: 会计学 | AK92: 余平瑶 | AL92: 真实产生的退费 | AM92: 祁睿 | AN92: BJWY7589974408 | AO92: 4625.3 | AP92: 2025/07/28 | AQ92: 支付宝退回 | AT92: TRUE
A93: 2025/07/27 | B93: 转班 | D93: 刘晓娟 | F93: 刘晓娟 | G93: TRUE | H93: 京内毛坯数据 | I93: 四六级项目-班课 | AE93: 原班取消（1、学生在2月常规班涨价前报的，当时常规班5980-双十一800优惠，实缴5180，保留800优惠2、其他学员转班有1000返款，给家长同等返款力度，共1000元） | AF93: 2025-07-27 | AK93: 刘晓娟 | AM93: 王若维 | AN93: XDF072231222318376 | AO93: 0 | AP93: 2025/07/27 | AQ93: 已转班 | AT93: TRUE | AW93: 作废，代办，不算进账和退费 | AX93: 5180
A94: 2025/07/28 | B94: 退费 | C94: 18813163 | D94: 边鑫博 | F94: 黄智超 | H94: 顾问转介绍-老带新 | I94: 四六级项目-班课 | K94: 开课前退费 | L94: 计划冲突_开课前 | P94: 个人生活/工作事务和新东方时间冲突 | AB94: 退费原因学生家长反馈孩子录取到了中外合作办学的学校，申请退掉线上四级（19号开课，已过4小时课程）和口语课程，意向比较坚决要去学雅思了。给出建议看线上或者转班秋季均拒绝，目前已排练为主 | AF94: 2025-07-28 | AG94: 北京第一六六中学（166中学） | AH94: 询问院系未告知 | AI94: 高三 | AJ94: 询问院系未告知 | AK94: 边鑫博 | AL94: 真实产生的退费 | AM94: 王祎 | AN94: BJWY1508600205 | AO94: 4525.6 | AP94: 2025/07/28 | AQ94: 原路径微信退回 | AT94: TRUE
A95: 2025/07/28 | B95: 退费 | C95: 18813011 | D95: 边鑫博 | F95: 黄智超 | H95: 顾问转介绍-老带新 | I95: 四六级项目-班课 | K95: 开课后退费 | M95: 计划冲突_开课后 | Y95: 个人生活/工作事务和新东方时间冲突 | AB95: 退费原因学生家长反馈孩子录取到了中外合作办学的学校，申请退掉线上四级（19号开课，已过4小时课程）和口语课程，意向比较坚决要去学雅思了。给出建议看线上或者转班秋季均拒绝，目前已排练为主 | AF95: 2025-07-28 | AG95: 北京第一六六中学（166中学） | AH95: 询问院系未告知 | AI95: 高三 | AJ95: 询问院系未告知 | AK95: 边鑫博 | AL95: 真实产生的退费 | AM95: 王祎 | AN95: BJWY1508600205 | AO95: 4878.1 | AP95: 2025/07/28 | AQ95: 原路径微信退回 | AT95: TRUE
A96: 2025/07/29 | B96: 退费 | C96: 3170534137670167676 | D96: 李润基 | F96: 宋增辉 | H96: 其他（主动） | I96: 四六级项目-VIP | K96: 开课前退费 | L96: 计划冲突_开课前 | P96: 个人生活/工作事务和新东方时间冲突 | AB96: 学生是首师大的新大一，数学系，想要在八月假期前置学习数分和高代，家长想要定制老师，但是定制老师都没办法马上上课，至少需要等到九月，所以家长要退费，经过挽退，家长不同意保留这个课时包，同意换成非定制的唐亮老师带10个课时，但是要先退出来才能报，已经和家长约好今天下午上第一节课，家长很急请尽快处理，感谢！ | AF96: 2025-07-29 | AG96: 首都师范大学 | AH96: 数学院 | AI96: 新大一 | AJ96: 数学系 | AK96: 李润基 | AL96: 真实产生的退费 | AM96: 王子昱 | AN96: BJWY2457805016 | AO96: 52500 | AP96: 2025/07/31 | AQ96: 微信退还@李润基 | AT96: TRUE
A97: 2025/07/29 | B97: 退费 | C97: 18822642 | D97: 余平瑶 | F97: 田一禾 | H97: 内部员工推荐 | I97: 四六级项目-班课 | K97: 开课后退费 | M97: 学员意愿转变_开课后 | Z97: 认为课程用处不大/不适合自己 | AB97: 【已开课退费】学员报名大学预科英数。数学开课前，家长报名时就由于孩子自己不愿意上数学课，后续有退费风险。并且最终录取专业也不一定学数学。孩子在考虑这些天后，还是不愿意上数学课程，家长不再进行劝说，并且也让学管不要再进行劝导。后学生收到录取通知书，并且和学校确认了大一不允许考四级，所以当前先不学习四级六级课程，待能考试时，再进行学习。也不再进行费用保留。所以将数学和英语班级均退出费用。数学未消耗课时，英语消耗5课次 | AF97: 2025-07-29 | AG97: 未告知 | AH97: 未告知 | AI97: 大一 | AJ97: 未告知 | AK97: 余平瑶 | AL97: 真实产生的退费 | AM97: 高胤程 | AN97: BJWY5800930598 | AO97: 4130.5 | AP97: 2025/07/29 | AQ97: 微信退回 | AT97: TRUE
A98: 2025/07/29 | B98: 退费 | C98: 18822696 | D98: 余平瑶 | F98: 田一禾 | H98: 内部员工推荐 | I98: 四六级项目-班课 | K98: 开课后退费 | M98: 学员意愿转变_开课后 | Z98: 认为课程用处不大/不适合自己 | AB98: 【已开课退费】学员报名大学预科英数。数学开课前，家长报名时就由于孩子自己不愿意上数学课，后续有退费风险。并且最终录取专业也不一定学数学。孩子在考虑这些天后，还是不愿意上数学课程，家长不再进行劝说，并且也让学管不要再进行劝导。后学生收到录取通知书，并且和学校确认了大一不允许考四级，所以当前先不学习四级六级课程，待能考试时，再进行学习。也不再进行费用保留。所以将数学和英语班级均退出费用。数学未消耗课时，英语消耗5课次 | AF98: 2025-07-29 | AG98: 未告知 | AH98: 未告知 | AI98: 大一 | AJ98: 未告知 | AK98: 余平瑶 | AL98: 真实产生的退费 | AM98: 高胤程 | AN98: BJWY5800930598 | AO98: 3725.7 | AP98: 2025/07/29 | AQ98: 微信退回 | AT98: TRUE
A99: 2025/07/29 | B99: 退费 | C99: 18823524 | D99: 余平瑶 | F99: 李政 | G99: TRUE | H99: 顾问转介绍-老带新 | I99: 四六级项目-班课 | K99: 开课后退费 | M99: 学员意愿转变_开课后 | Z99: 认为课程用处不大/不适合自己 | AB99: 【已开课退费】学生报名大学预科数学（线上优享/新大一专属），截止7月19日，消耗1课次。学生上完一次课之后因为数学比较枯燥，再加上在线上上课，课堂氛围不太活跃，上课就会犯困，不想再上课了。和学生沟通后，学生也表示高中老师比较幽默风趣，自己习惯了，一时间还不太适应。所以就先不上了，一对一也不考虑。等上大学之后，有希望在期末考试前进行一对一的回流 | AF99: 2025-07-29 | AG99: 未告知 | AH99: 未告知 | AI99: 大一 | AJ99: 未告知 | AK99: 余平瑶 | AL99: 真实产生的退费 | AM99: 张嘉会 | AN99: BJWY9158446648 | AO99: 3824.3 | AP99: 2025/07/30 | AQ99: 微信退3824.3[图片] | AT99: TRUE
A100: 2025/07/30 | B100: 退费 | C100: 18816612 | D100: 李玉迪1-李玉迪 | F100: 黄智超 | H100: 新东方官网M站 | I100: 四六级项目-班课 | K100: 开课后退费 | M100: 学员意愿转变_开课后 | Z100: 认为课程用处不大/不适合自己 | AB100: YKF25002，开课后退费，消耗6课时学员基础比较好，四级课对自己帮助不大，想退费，建议转到六级班学习，学生觉得六级还比较远，先暂不考虑了，之后考六级有回流的可能性。 | AF100: 2025-07-30 | AG100: 新大一 | AH100: 新大一 | AI100: 新大一 | AJ100: 新大一 | AK100: 李玉迪1-李玉迪 | AL100: 真实产生的退费 | AM100: 何格 | AN100: BJWY7411043612 | AO100: 3685 | AP100: 2025/07/30 | AQ100: 支付宝退3685[图片] | AT100: TRUE
...

Sheet 四六级退费-数据透视
A1: 顾问姓名 | B1: 求和项:退费金额
A2: 房国超 | B2: 86550.8
A3: 黄智超 | B3: 234032.3
A4: 刘晓娟 | B4: 192383.4
A5: 宋增辉 | B5: 156062.2
A6: 田一禾 | B6: 42550.5
A7: 张博奥 | B7: 36239

Sheet 考研业绩退费
A1: 提交日期 | B1: 您所办理的业务类型 | C1: OA流水号 | D1: 学管姓名 | E1: 学管是否代办 | F1: 顾问姓名 | G1: 顾问是否代办 | H1: 91系统-最新报名二级渠道 | I1: 原班所属项目 | J1: 新报入班级所属项目 | K1: 退费阶段 | L1: 退费一级原因（开课前） | M1: 退费一级原因 (开课后) | N1: 退费二级原因（专业课师资匹配原因） | O1: 退费二级原因（学员意愿转变_开课后） | P1: 退费三级原因（完全匹配不上）-院校、学院、专业、专业课代码及名称 | Q1: 退费详细原因说明（与OA退费详细说明保持一致） | R1: 预计报名新班学费金额 | S1: 转班金额（请学管填写所在班级实际金额） | T1: 转班详细原因说明 | U1: 提交时间 | V1: 学校 | W1: 学院 | X1: 年级 | Y1: 专业 | Z1: 提交人 | AA1: 退费类型 | AB1: 学员姓名 | AC1: 学员编码 | AD1: 退费金额 | AE1: 办理日期-客服 | AF1: 退费方式-客服 | AG1: 需要跟进的顾问/学管 | AH1: 退费/转班特殊情况备注（若需要学管提供银行卡信息，可将需求填写在此处）-客服 | AI1: 是否完成退费/转班-客服 | AJ1: 父记录 | AK1: 父记录
A2: 2025/07/06 | B2: 转班 | D2: 黄子琪3-黄子琪 | F2: 刘晓娟 | H2: 内部员工推荐 | I2: 无忧项目-班课 | S2: 1573.8 | T2: 从WYHE26005转WYHE26006 转班原因：学生专业变动英语一变英语二 | U2: 2025-07-06 | Z2: 黄子琪3-黄子琪 | AB2: 车子越 | AC2: BJWY2366756820 | AE2: 2025/07/06 | AF2: 已转班 | AI2: TRUE
A3: 2025/07/10 | B3: 退费 | C3: 2025071002653 | D3: 陈晶171-陈晶 | F3: 刘晓娟 | H3: 学管续费推荐 | I3: VIP项目-VIP | K3: 开课后退费 | M3: 学员意愿转变_开课后 | O3: 认为课程用处不大/不适合自己 | Q3: 学员是24考研鱼柳了课时，去年没有上课，现在已经考上研究生，不需要辅导其他内容，剩余的要办理退费 | U3: 2025-07-15 | V3: 北京化工大学 | W3: 信息学院 | X3: 大四 | Y3: 计算机 | Z3: 陈晶171-陈晶 | AA3: 真实产生的退费 | AB3: 李泽善 | AC3: BJWY9389688874 | AD3: 6300 | AE3: 2025/07/17 | AF3: 7.23已完成付款 7.22用户短信已确认，退款中@陈晶171 (陈晶) 7.21转手工退6300，待客户短信确认————@陈晶171 (陈晶) 暂退学员账户，原渠道失效，提供本人银行卡信息7.18@陈晶171 (陈晶) [图片] | AI3: TRUE
A4: 2025/07/15 | B4: 转班 | D4: 黄子琪3-黄子琪 | F4: 田一禾3-田一禾 | H4: 新东方PC官网 | I4: 无忧项目-班课 | S4: 9333.4 | T4: 姓名：梁好 学员号： BJWY4821923897 转班信息如下： WYFE26017转WYFE26019 WYFE26018转WYFE26020 转班原因：英语一转英二 已登记表格，辛苦老师办理@北京中心客服组 | U4: 2025-07-15 | Z4: 黄子琪3-黄子琪 | AB4: 梁好 | AC4: BJWY4821923897 | AE4: 2025/07/15 | AF4: 已转班 | AI4: TRUE
G8: 考研一对一续费时间 | H8: 当月提点 | M8: 扣费金额
G9: 45221 | H9: 0.018 | I9: 李泽善 | J9: 刘晓娟 | K9: 6300 | L9: ✅ | M9: =H9*K9 -> 113.4
I14: 另外两笔转班，不算进账，不算退费

Sheet 考研业绩进账
A1: 签约学生姓名 | B1: 签约单录入人 | C1: 班级名称 | D1: 报名产品 | E1: 学费 | F1: 备注
A2: 陈松乔 | B2: 刘晓娟 | C2: 考研英语无忧计划（27考研/基础） | D2: 无忧计划-啄木鸟,考研专业课300,六级无忧计划 | F2: 作废 | G2: 31.8
A3: 陈松乔 | B3: 刘晓娟 | C3: 考研数学无忧计划（27考研/冲刺） | D3: 无忧计划-啄木鸟,考研专业课300,六级无忧计划 | F3: 作废 | G3: 35.8
A4: 陈松乔 | B4: 刘晓娟 | C4: 考研数学无忧计划（27考研/基础） | D4: 无忧计划-啄木鸟,考研专业课300,六级无忧计划 | F4: 作废 | G4: 28.8
A5: 陈松乔 | B5: 刘晓娟 | C5: 考研英语无忧计划（27考研/英一冲刺） | D5: 无忧计划-啄木鸟,考研专业课300,六级无忧计划 | F5: 作废 | G5: 34.8
A6: 陈松乔 | B6: 刘晓娟 | C6: 考研政治无忧计划（27考研/强化） | D6: 无忧计划-啄木鸟,考研专业课300,六级无忧计划 | F6: 作废 | G6: 23.9
A7: 陈松乔 | B7: 刘晓娟 | C7: 考研政治无忧计划（27考研/冲刺） | D7: 无忧计划-啄木鸟,考研专业课300,六级无忧计划 | F7: 作废 | G7: 28.4
A8: 陈松乔 | B8: 刘晓娟 | C8: 考研英语无忧计划（27考研/英一强化） | D8: 无忧计划-啄木鸟,考研专业课300,六级无忧计划 | F8: 作废 | G8: 41.8
A9: 陈松乔 | B9: 刘晓娟 | C9: 考研政治无忧计划（27考研/基础） | D9: 无忧计划-啄木鸟,考研专业课300,六级无忧计划 | F9: 作废 | G9: 41.2
A10: 陈松乔 | B10: 刘晓娟 | C10: 考研数学无忧计划（27考研/强化） | D10: 无忧计划-啄木鸟,考研专业课300,六级无忧计划 | F10: 作废 | G10: 43.7
A11: 王远航8 | B11: 刘晓娟 | C11: 考研规划热线 | E11: 399
A12: 魏天奇 | B12: 刘晓娟 | C12: 2027考研政治直通车 长线2期,2027考研数学直通车 长线2期,2027考研英语直通车 长线2期 | D12: 线上直通车,考研专业课150 | E12: 11902.8
A13: 魏天奇 | B13: 刘晓娟 | C13: 2027考研专业课定制一对一（30h）-A班 | D13: 线上直通车,考研专业课150 | E13: 11900
A14: 马玄轶 | B14: 刘晓娟 | C14: 2026考研英语全程班 6班 | D14: 线上全程班 | E14: 1096.5
A15: 陈松乔 | B15: 刘晓娟 | C15: 考研英语无忧计划（27考研/基础） | D15: 无忧计划-啄木鸟,考研专业课300,六级无忧计划 | F15: 作废 | G15: 2174.2
A16: 曲俊昊 | B16: 刘晓娟 | C16: 26考研英语全程集训营（寒暑） | D16: 考研专业课150,寒暑假集训营（春秋OMO） | F16: 作废 | G16: 7019.5 | H16: 转班不算业绩
A17: 曲俊昊 | B17: 刘晓娟 | C17: 26考研政治全程集训营（寒暑） | D17: 考研专业课150,寒暑假集训营（春秋OMO） | F17: 作废 | G17: 12229.9
A18: 曲俊昊 | B18: 刘晓娟 | C18: 26考研政治全程集训营（寒暑） | D18: 考研专业课150,寒暑假集训营（春秋OMO） | F18: 作废 | G18: 12229.9
A19: 曲俊昊 | B19: 刘晓娟 | C19: 26考研英语全程集训营（寒暑） | D19: 考研专业课150,寒暑假集训营（春秋OMO） | F19: 作废 | G19: 7019.5
A20: 李秋熠 | B20: 刘晓娟 | C20: 考研数学无忧计划（27考研/强化） | D20: 无忧计划-啄木鸟 | E20: 8800
A21: 李秋熠 | B21: 刘晓娟 | C21: 考研数学无忧计划（27考研/基础） | D21: 无忧计划-啄木鸟 | E21: 5800
A22: 李秋熠 | B22: 刘晓娟 | C22: 考研数学无忧计划（27考研/冲刺） | D22: 无忧计划-啄木鸟 | E22: 6700
A23: 李昱志 | B23: 刘晓娟 | C23: 27考研大二集训营（住宿费） | D23: 暑假集训营 | E23: 2720
A24: 李昱志 | B24: 刘晓娟 | C24: 27考研英语大二集训营 | D24: 暑假集训营 | E24: 12040
A25: 李昱志 | B25: 刘晓娟 | C25: 27考研数学大二集训营 | D25: 暑假集训营 | E25: 11540
A26: 郁名栋 | B26: 刘晓娟 | C26: 考研初试专业课一对一（26考研/30小时） | D26: 考研专业课300 | E26: 18300
A27: 陈静 | B27: 刘晓娟 | C27: 27考研一对一伴学（定制） | D27: VIP - 伴学 | E27: 11500
A28: 顾逸闻 | B28: 刘晓娟 | C28: 考研英语无忧计划候鸟（27考研/英二冲刺） | D28: 考研专业课150,无忧计划-候鸟,VIP - 伴学 | E28: 721.5
A29: 顾逸闻 | B29: 刘晓娟 | C29: 考研英语无忧计划候鸟（27考研/基础强化） | D29: 考研专业课150,无忧计划-候鸟,VIP - 伴学 | E29: 4978.5
A30: 顾逸闻 | B30: 刘晓娟 | C30: 考研政治无忧计划候鸟（27考研/基础强化） | D30: 考研专业课150,无忧计划-候鸟,VIP - 伴学 | E30: 4978.5
A31: 顾逸闻 | B31: 刘晓娟 | C31: 考研政治无忧计划候鸟（27考研/冲刺） | D31: 考研专业课150,无忧计划-候鸟,VIP - 伴学 | E31: 471.5
... A55: 李宇 | B55: 刘晓娟 | C55: 考研分单 | D55: 半年集训营 | E55: 33012.5

Sheet 考研业绩进账-数据透视
A1: 签约单录入人 | B1: 求和项:学费
A2: 黄智超
A3: 刘晓娟 | B3: 358705.4
A4: 田一禾 | B4: 0
A5: (空白)
A6: 总计 | B6: 358705.4

Sheet 四六级业绩进账
A1: 序号 | B1: 学校 | C1: 部门 | D1: 资源姓名 | E1: 资源ID | F1: 资源录入人 | G1: 资源录入时间 | H1: 资源描述 | I1: 市场活动 | J1: 资源年级 | K1: 分配顾问/TMK | L1: 一级获取渠道 | M1: 二级获取渠道 | N1: 转介绍人 | O1: TMK激活人 | P1: TMK激活处理时间 | Q1: 工单姓名 | R1: 跟进顾问 | S1: 工单ID | T1: 工单类型 | U1: 工单录入时间 | V1: 工单等级 | W1: 咨询课程 | X1: 工单年级 | Y1: 学校 | Z1: 院系 | AA1: 专业 | AB1: 签约学生姓名 | AC1: 签约单ID | AD1: 签约单录入人 | AE1: 签约单录入时间 | AF1: 签约单更新人 | AG1: 签约单更新时间 | AH1: 班号 | AI1: 班级名称 | AJ1: 面询表类型 | AK1: 订金 | AL1: 学费 | AM1: 续费类型 | AN1: 推荐人 | AO1: 类型 | AP1: 是否交接 | AQ1: 操作人编号 | AR1: 学员号 | AS1: 听课证号 | AT1: 报班日期 | AU1: 学员状态 | AV1: 回访记录 | AW1: 新老生类型 | AX1: 退费金额 | AY1: 退费日期 | AZ1: 课程类型 | BA1: 客户ID | BB1: 是否新东方在线签约 | BC1: 考季 | BD1: 报名产品 | BE1: 报名科目 | BF1: 意向报考专业 | BG1: 学校班型/类型 | BH1: 是否关联协议 | BI1: 特殊备注 | BJ1: 产品品类 | BK1: 业务类型 | BL1: 签约列表在线学员ID | BM1: 大学生源类型 | BN1: 资源来源 | BO1: 备注
A2: 10 | B2: 北京大学部 | C2: 国内大学部 | E2: 115875126 | G2: 2025-06-23 19:04:25 | H2: 死单激活流转黄智超；薛小刚+运营管理部+304901+xuexiaogang@xdf.cn（TMK主管分配TMK） 外呼主题：FY25-国内6月死单回访（6.9-6.15） | J2: 大三 | K2: 刘晓娟 | L2: 毛坯数据 | M2: 毛坯数据 | Q2: 陈松乔 | R2: 刘晓娟 | S2: 29045634 | T2: 续费工单 | U2: 2025-07-12 12:10 | V2: A（六个月内有报课意向工单） | W2: 六级,考研专业课,考研无忧计划 | X2: 大三 | Y2: 北京语言大学 | Z2: 信息科学学院 | AA2: 计算机科学与技术 | AB2: 陈松乔 | AC2: 5412571 | AD2: 刘晓娟 | AE2: 2025-07-12 12:11 | AF2: 刘晓娟 | AG2: 2025-07-12 12:11 | AH2: WYSJ25033 | AI2: 六级无忧计划 | AJ2: 国内考试 | AL2: 4402.8 | AM2: 同科续费 | AO2: 续班 | AP2: 已交接 | AQ2: BJWY22035556hl | AR2: BJWY0772435935 | AS2: WYSJ250330065 | AT2: 2025-07-12 | AV2: 回访人：刘晓娟，回访时间：2025-07-12 12:10，回访内容：转班；|回访人：刘晓娟，回访时间：2025-07-12 12:11，回访内容：转班 | BA2: 43431754 | BB2: 否 | BC2: 27考季 | BD2: 无忧计划-啄木鸟,考研专业课300,六级无忧计划 | BE2: 计算机,英语,政治,数学 | BG2: 国内高校-双非 | BH2: 是 | BK2: 转出 | BM2: 本地人本地大学(常规)
A3: 11 | B3: 北京大学部 | C3: 国内大学部 | D3: 锦伊 | E3: 120656775 | F3: 程远 | G3: 2025-07-24 18:46:40 | H3: 谷婷婷+gutingting7@xdf.cn+ID+谷婷婷7(新东方教育科技集团有限公司-产业机构-前途出国-前途欧亚事业部-北京中心-语培业务部-销售部-咨询一组 | 语培顾问主管)，刘晓娟； | J3: 大二 | K3: 刘晓娟 | L3: 转介绍 | M3: 内部员工推荐 | N3: 谷婷婷+gutingting7@xdf.cn+ID+谷婷婷7(新东方教育科技集团有限公司-产业机构-前途出国-前途欧亚事业部-北京中心-语培业务部-销售部-咨询一组 | 语培顾问主管) | Q3: 张锦伊 | R3: 刘晓娟 | S3: 29295848 | T3: 正常工单 | U3: 2025-07-24 19:08 | V3: A（六个月内有报课意向工单） | W3: 专四 | X3: 大二 | Y3: 北京第二外国语学院 | Z3: 英语学院 | AA3: 英语 | AB3: 张锦伊 | AC3: 5520476 | AD3: 刘晓娟 | AE3: 2025-07-24 19:08 | AF3: 刘晓娟 | AG3: 2025-07-24 19:09 | AH3: 66275033475 | AI3: 2026英语专业四级全程班【直播 + 录播】 | AJ3: 国内考试 | AL3: 1529.15 | AN3: 谷婷婷+gutingting7@xdf.cn+ID+谷婷婷7(新东方教育科技集团有限公司-产业机构-前途出国-前途欧亚事业部-北京中心-语培业务部-销售部-咨询一组 | 语培顾问主管) | AO3: 新签 | AP3: 无须交接 | AT3: 2025-07-24 | AV3: 回访人：刘晓娟，回访时间：2025-07-24 19:08，回访内容：报名 | AZ3: 长期班 | BA3: 56558941 | BB3: 是 | BG3: 国内高校-C9 | BH3: 否 | BL3: 82855942 | BM3: 本地人本地大学(常规) | BN3: 客服
A4: 12 | B4: 北京大学部 | C4: 国内大学部 | E4: 117158030 | G4: 2025-07-02 14:13:36 | J4: 大二 | K4: 黄智超 | L4: 转介绍 | M4: 内部员工推荐 | Q4: 于奥洋 | R4: 黄智超 | S4: 29202795 | T4: 续费工单 | U4: 2025-07-18 22:47 | V4: A（六个月内有报课意向工单） | W4: 六级,大学预科 | X4: 大一 | Y4: 深圳大学 | Z4: 经济学院 | AA4: 经济学 | AB4: 于奥洋 | AC4: 5484575 | AD4: 黄智超 | AE4: 2025-07-18 22:47 | AF4: 黄智超 | AG4: 2025-08-03 12:20 | AH4: WYS25039 | AI4: 六级精英计划 | AJ4: 国内考试 | AL4: 20300 | AM4: 同科续费 | AN4: 高晶+gaojing43@xdf.cn+312057+培训学校-北京学校-高中一对一部-西南区-玉泉路分中心 | AO4: 续班 | AP4: 已交接 | AQ4: BJWY24032w1g8X | AR4: BJWY8894097228 | AS4: WYS250390005 | AT4: 2025-07-24 | AV4: 回访人：黄智超，回访时间：2025-07-18 22:47，回访内容：转班；|回访人：黄智超，回访时间：2025-07-18 22:47，回访内容：转班；|回访人：黄智超，回访时间：2025-07-23 22:27，回访内容：联系家长 添加学管老师微信 及时同步课程 | BA4: 56143849 | BB4: 否 | BC4: 25下考季 | BD4: 六级无忧计划 | BG4: 国内高校-双非 | BH4: 否 | BK4: 转出 | BM4: 本地人本地大学(常规)
A5: 13 | B5: 北京大学部 | C5: 国内大学部 | E5: 119941935 | G5: 2025-07-20 20:17:42 | H5: 准大一新生，家长咨询四级线下走读课程，离知春路校区比较近，让微信发送课程介绍，手机号即微信号；AI-37815-01a 2025-07-20 19:58:02_x000D_ 您好同学，欢迎访问新东方考研官网，【新东方考研】全新升级，课程灵活多样，【考研全年集训营】【考研半年集训营】【考研冲刺营】【线下走读班】【考研一对一】【在职考研】【四六级】火热报名中 ，现在报名更有高达3000元优惠！_x000D_ _x000D_ AI-37815-01a 2025-07-20 19:58:04_x000D_ 您是想咨询【考研走读班】【考研集训营】【考研规划】还是【在职考研】呢？_x000D_ _x000D_ 01000000037815301266328043346910 2025-07-20 19:58:42_x000D_ 新大一，四级英语课，上几次？价位？_x000D_ _x000D_ AI-37815-01a 2025-07-20 19:58:46_x000D_ 我们拥有多种授课模式，不同的学习内容价格是存在差异的，您可以留下您的姓名电话，我们会安排老师第一时间为您回电_x000D_ _x000D_ _x000D_ 01000000037815301266328043346910 2025-07-20 19:59:01_x000D_ 13552696321_x000D_ _x000D_ AI-37815-01a 2025-07-20 19:59:04_x000D_ 好的，确认一下你的号码是否正确呢~_x000D_ _x000D_ 外呼主题：2026财年第2财月百度投放新东方官网小程序 | I5: 2026财年第2财月百度投放新东方官网小程序 | J5: 大一 | K5: 田一禾 | L5: 新东方官网 | M5: 新东方官网小程序 | Q5: 陈兆骞 | R5: 田一禾 | S5: 29475921 | T5: 续费工单 | U5: 2025-08-03 11:33 | V5: A（六个月内有报课意向工单） | W5: 四级,大学预科 | X5: 大一 | Y5: 首都师范大学 | Z5: 化学系 | AA5: 化学 | AB5: 陈兆骞 | AC5: 5530644 | AD5: 田一禾 | AE5: 2025-08-03 11:36 | AF5: 田一禾 | AG5: 2025-08-03 11:37 | AH5: YKS25002 | AI5: 六级无忧计划（新大一专属） | AJ5: 国内考试 | AL5: 5680 | AM5: 同科续费 | AO5: 续班 | AP5: 已交接 | AQ5: BJWY2011wXCx1W | AR5: BJWY3877559849 | AS5: YKS250020038 | AT5: 2025-07-22 | AV5: 回访人：田一禾，回访时间：2025-08-03 11:33，回访内容：转班；|回访人：田一禾，回访时间：2025-08-03 11:36，回访内容：转班操作 | BA5: 82060903 | BB5: 否 | BC5: 25下考季 | BD5: 四级线上网课 | BG5: 国内高校-双一流(非985/211) | BH5: 是 | BK5: 转出 | BM5: 本地人本地大学(常规)
A6: 16 | B6: 北京大学部 | C6: 国内大学部 | D6: 张婧辰 | E6: 119666526 | F6: 王天义 | G6: 2025-07-18 14:48:24 | H6: 续费原因：专业课课时八月中旬消耗完，之前和家长聊过，课时不足可以续费，目的就是想让学生这次上岸；今天上午电话沟通家长说一定保证数学一周一次课，后续我会和家长初步沟通续费情况。；该学生为保护期内续费，原顾问：国内大学部-苏乾楠(suqiannan@xdf.cn) | J6: 大学已毕业 | K6: 苏乾楠 | L6: 转介绍 | M6: 学管续费推荐 | N6: 王天义wangtianyi56@xdf.cn | Q6: 张婧辰 | R6: 苏乾楠 | S6: 29197476 | T6: 续费工单 | U6: 2025-07-18 15:02 | V6: A（六个月内有报课意向工单） | W6: 考研专业课 | X6: 大学已毕业 | Y6: 北京信息科技大学 | Z6: 经济管理学院 | AA6: 会计学 | AB6: 张婧辰 | AC6: 5517645 | AD6: 刘晓娟 | AE6: 2025-07-21 19:25 | AF6: 苏乾楠 | AG6: 2025-07-21 19:26 | AJ6: 国内考试 | AL6: 3750 | AN6: 王天义 | AO6: 分单 | AP6: 已交接 | AR6: BJWY1217641283 | AV6: 回访人：苏乾楠，回访时间：2025-07-18 15:02，回访内容：学管老师先跟进 今天在校区沟通；|回访人：苏乾楠，回访时间：2025-07-21 19:21，回访内容：报名 | BA6: 52122438 | BB6: 否 | BC6: 26考季 | BD6: 考研专业课管综 | BE6: 管综 | BF6: 管综 | BG6: 国内高校-双非 | BH6: 否 | BN6: 学管续费推荐
A7: 17 | B7: 北京大学部 | C7: 国内大学部 | D7: 润欣 | E7: 118632154 | F7: 程远 | G7: 2025-07-11 14:21:04 | H7: 卢嘉雯+lujiawen3@xdf.cn+213598+培训学校 北京学校 高中一对一部 西北区 展春园分中心，黄智超； | J7: 大二 | K7: 黄智超 | L7: 转介绍 | M7: 内部员工推荐 | N7: 卢嘉雯+lujiawen3@xdf.cn+213598+培训学校 北京学校 高中一对一部 西北区 展春园分中心 | Q7: 沈润欣 | R7: 黄智超 | S7: 28983533 | T7: 正常工单 | U7: 2025-07-11 14:48 | V7: A（六个月内有报课意向工单） | W7: 六级,大学预科 | X7: 大一 | Y7: 北京建华实验亦庄学校 | Z7: 新大一 | AA7: 新大一 | AB7: 沈润欣 | AC7: 5489793 | AD7: 黄智超 | AE7: 2025-07-21 22:38 | AF7: 黄智超 | AG7: 2025-07-21 22:38 | AH7: YKSJ25001 | AI7: 六级无忧计划（线上优享/新大一专属） | AJ7: 国内考试 | AL7: 5180 | AN7: 卢嘉雯+lujiawen3@xdf.cn+213598+培训学校 北京学校 高中一对一部 西北区 展春园分中心 | AO7: 新签 | AP7: 已交接 | AQ7: BJWY2101498uW2 | AR7: BJWY7973903583 | AS7: YKSJ250010051 | AT7: 2025-07-21 | AV7: 回访人：黄智超，回访时间：2025-07-14 20:56，回访内容：家长需求微信联系 目前就是觉得线下距离远，学六级又有点早，网课又不倾向，家长明确说明微信以后沟通 别打电话，孩子是k12老生；|回访人：黄智超，回访时间：2025-07-20 12:04，回访内容：家长明确说明不要打电活联系 微信沟通 目前不确定是否报名 再缓缓；|回访人：黄智超，回访时间：2025-07-21 22:38，回访内容：已签约 5180 预科线上六级课～YKSJ25001 | BA7: 74686638 | BB7: 否 | BC7: 25下考季 | BD7: 六级无忧计划 | BG7: 普通学校-普高 | BH7: 否 | BK7: 报名 | BM7: 本地人本地大学(常规) | BN7: 客服
A8: 18 | B8: 北京大学部 | C8: 国内大学部 | D8: 王东 | E8: 108040003 | F8: 北京国内管理员 | G8: 2025-06-04 10:09:49 | H8: 来源:北京百学汇; | I8: 【2025-CRM高三资源】-北京大学部 | J8: 大一 | K8: 高晓慧 | L8: 毛坯数据 | M8: 毛坯数据 | O8: 高晓慧 | P8: 2025-07-15 16:09:16 | Q8: 王开睿 | R8: 李政(离职) | S8: 29091887 | T8: 正常工单 | U8: 2025-07-15 16:19 | V8: A（六个月内有报课意向工单） | W8: 四级,大学预科 | X8: 大一 | Y8: 不详 | Z8: 询问未告知 | AA8: 新大一 | AB8: 王开睿 | AC8: 5488602 | AD8: 李政(离职) | AE8: 2025-07-20 19:10 | AF8: 李政(离职) | AG8: 2025-07-20 19:10 | AH8: YKF25002 | AI8: 四级无忧计划（新大一专属） | AJ8: 国内考试 | AL8: 4880 | AO8: 新签 | AP8: 已交接 | AQ8: BJWY25030q8UPI | AR8: BJWY5651022809 | AS8: YKF250020045 | AT8: 2025-07-20 | AV8: 回访人：李政(离职)，回访时间：2025-07-15 16:19，回访内容：家长帮孩子咨询，不方便沟通，先都看看；|回访人：李政(离职)，回访时间：2025-07-17 14:52，回访内容：电话无人接听，询问家长的课程意向，家长无回复；|回访人：李政(离职)，回访时间：2025-07-20 19:09，回访内容：试听课来参加；|回访人：李政(离职)，回访时间：2025-07-20 19:10，回访内容：签约 | BA8: 74844973 | BB8: 否 | BC8: 25下考季 | BD8: 四级无忧计划 | BG8: 国内高校-双非 | BH8: 否 | BK8: 报名 | BM8: 本地人本地大学(常规) | BN8: 新CRM
A9: 19 | B9: 北京大学部 | C9: 国内大学部 | E9: 93426823 | G9: 2025-01-19 18:44:34 | H9: 【王朝群】咨询四六级课程 | J9: 大二 | K9: 刘晓娟 | L9: 线上运营-小红书 | M9: 小红书 | Q9: 汪宣晓 | R9: 刘晓娟 | S9: 29243397 | T9: 续费工单 | U9: 2025-07-20 16:02 | V9: A（六个月内有报课意向工单） | W9: 四级 | X9: 大二 | Y9: 武汉音乐学院 | Z9: 中国器乐系 | AA9: 古琴 | AB9: 汪宣晓 | AC9: 5488193 | AD9: 刘晓娟 | AE9: 2025-07-20 16:06 | AF9: 刘晓娟 | AG9: 2025-07-20 16:06 | AH9: WYFJ25040 | AI9: 四级无忧计划 | AJ9: 国内考试 | AL9: 5680 | AM9: 同科续费 | AO9: 续班 | AP9: 未交接 | AQ9: BJWY22035556hl | AR9: BJWY5490718239 | AS9: WYFJ250400002 | AT9: 2025-07-20 | AV9: 回访人：刘晓娟，回访时间：2025-07-20 16:02，回访内容：转班；|回访人：刘晓娟，回访时间：2025-07-20 16:06，回访内容：转班 | BA9: 66365835 | BB9: 否 | BC9: 25下考季 | BD9: 四级无忧计划 | BG9: 国内高校-双非 | BH9: 否 | BK9: 转出 | BM9: 本地人外地大学(归巢)
A10: 20 | B10: 北京大学部 | C10: 国内大学部 | E10: 117158030 | G10: 2025-07-02 14:13:36 | J10: 大二 | K10: 黄智超 | L10: 转介绍 | M10: 内部员工推荐 | Q10: 于奥洋 | R10: 黄智超 | S10: 29476388 | T10: 续费工单 | U10: 2025-08-03 12:26 | V10: A（六个月内有报课意向工单） | W10: 六级,大学预科 | X10: 大一 | Y10: 深圳大学 | Z10: 经济学院 | AA10: 经济学 | AB10: 于奥洋 | AC10: 5502967 | AD10: 黄智超 | AE10: 2025-08-03 12:26 | AF10: 黄智超 | AG10: 2025-08-03 12:27 | AH10: YKS25005 | AI10: 六级精英计划（新大一专属） | AJ10: 国内考试 | AL10: 20300 | AM10: 同科续费 | AN10: 高晶+gaojing43@xdf.cn+312057+培训学校-北京学校-高中一对一部-西南区-玉泉路分中心 | AO10: 续班 | AP10: 已交接 | AQ10: BJWY2011wXCx1W | AR10: BJWY8894097228 | AS10: YKS250050005 | AT10: 2025-07-18 | AV10: 回访人：黄智超，回访时间：2025-08-03 12:26，回访内容：转班；|回访人：黄智超，回访时间：2025-08-03 12:26，回访内容：转班 | BA10: 56143849 | BB10: 否 | BC10: 25下考季 | BD10: 六级无忧计划 | BG10: 国内高校-双非 | BH10: 是 | BK10: 转出 | BM10: 本地人本地大学(常规)
A11: 21 | B11: 北京大学部 | C11: 国内大学部 | D11: 徐子翔 | E11: 115186765 | F11: 曹伟杰2 | G11: 2025-06-19 10:56:40 | H11: 家长咨询四六级暑期班 辛苦老师分配给原顾问黄智超，合并工单，不占顺序。之前整错渠道啦 | J11: 高三 | K11: 黄智超 | L11: 转介绍 | M11: 内部员工推荐 | N11: 吕玉珠+lvyuzhu1@xdf.cn+444957+培训学校-北京学校-高中一对一部-增长中心-线上社群组 | Q11: 徐子翔 | R11: 黄智超 | S11: 28429430 | T11: 续费工单 | U11: 2025-06-19 11:35 | V11: A（六个月内有报课意向工单） | W11: 四级 | X11: 高三 | Y11: 北京市第十一中学 | Z11: 新大一 | AA11: 新大一 | AB11: 徐子翔 | AC11: 5415457 | AD11: 黄智超 | AE11: 2025-07-18 10:44 | AF11: 黄智超 | AG11: 2025-07-19 18:37 | AH11: 37912747353 | AI11: 【返学费】四级暑期直通车【2025年12考季】 | AJ11: 国内考试 | AN11: 吕玉珠+lvyuzhu1@xdf.cn+444957+培训学校-北京学校-高中一对一部-增长中心-线上社群组 | AO11: 新签 | AP11: 无须交接 | AT11: 2025-07-18 | AV11: 回访人：黄智超，回访时间：2025-07-12 16:36，回访内容：电话接不通 同事电话也不接 微信回复觉得课程价格贵；|回访人：黄智超，回访时间：2025-07-13 17:52，回访内容：家长觉得课程价格贵 就规划了新东方在线的网课，家长看到返学费的 又问了考试的事情 目前也不知道能不能给孩子报名；|回访人：黄智超，回访时间：2025-07-22 14:11，回访内容：发送四级资料维护一下 | AZ11: 长期班 | BA11: 75302707 | BB11: 是 | BC11: 25下考季 | BD11: 四级无忧计划 | BG11: 普通学校-普高 | BH11: 否 | BL11: 110560210 | BM11: 本地人本地大学(常规) | BN11: 市场 | BO11: 在线不算 | BP11: 279
A12: 22 | B12: 北京大学部 | C12: 国内大学部 | D12: 吴优 | E12: 119674385 | F12: 杨沫 | G12: 2025-07-17 19:29:32 | H12: 张鸿伟+zhanghongwei9@xdf.cn+ 162245+培训学校-北京学校-高中一对一部-学员服务管理中心-西南区 房国超 | J12: 大二 | K12: 房国超 | L12: 转介绍 | M12: 内部员工推荐 | N12: 张鸿伟+zhanghongwei9@xdf.cn+ 162245+培训学校-北京学校-高中一对一部-学员服务管理中心-西南区 | Q12: 吴优 | R12: 房国超 | S12: 29192447 | T12: 续费工单 | U12: 2025-07-17 20:07 | V12: A（六个月内有报课意向工单） | W12: 六级 | X12: 大二 | Y12: 北京工商大学 | Z12: 数学与统计学院 | AA12: 经济统计学 | AB12: 吴优 | AC12: 5415404 | AD12: 房国超 | AE12: 2025-07-18 09:04 | AF12: 房国超 | AG12: 2025-07-18 09:11 | AH12: 88527312393 | AI12: 【返学费】六级暑期直通车【2025年12考季】 | AJ12: 国内考试 | AN12: 张鸿伟+zhanghongwei9@xdf.cn+ 162245+培训学校-北京学校-高中一对一部-学员服务管理中心-西南区 | AO12: 新签 | AP12: 无须交接 | AT12: 2025-07-18 | AV12: 回访人：房国超，回访时间：2025-07-17 20:07，回访内容：家长咨询，学生四级 480多，家长想让孩子暑假学学， 推荐直播课 和小班，微信详聊 | AZ12: 长期班 | BA12: 56483959 | BB12: 是 | BC12: 25下考季 | BD12: 六级无忧计划 | BG12: 国内高校-双非 | BH12: 否 | BL12: 110559692 | BM12: 外地人本地大学(常规) | BN12: 客服 | BO12: 在线不算 | BP12: 279
A13: 23 | B13: 北京大学部 | C13: 国内大学部 | D13: 北京市3774 | E13: 116690066 | F13: 杨俊42(国内) | G13: 2025-06-30 20:08:54 | H13: 渠道录入来源：新东方官网M站-客服 意向城市：北京访客省/城市：北京市 访客静态ID：01000000034659128491454282423774 接待分组ID：70455 搜索引擎： 搜索词： 关键词： 设备类型：pc 访客IP：120.244.194.194 对话详细内容：AI-Lbo0rDBXCyBY 2025-06-30 20:05:10_x000D_ 您好同学,欢迎访问北京新东方考研四六级中心. 考研线下课程26/27考季【考研全年集训营】【考研半年集训营】【考研全科线下走读班】【考研寒/暑假集训营】【考研一对一】【考研专业课】【四/六级课程】，热门课程火热报名中,咨询即可领取专享优惠。 **【考研全年集训营】=ff761f# **【考研半年集训营】=ff6b6b# **【考研全科线下走读班】=ffc158# **【考研寒/暑假集训营】=ffc158# **【考研一对一】=ff761f# **【考研专业课】=ff6caa# **【四/六级课程】=ff6caa# **【考研冲刺班】=60e27e#_x000D_ _x000D_ AI-Lbo0rDBXCyBY 2025-06-30 20:05:13_x000D_ 您是想咨询【线下课程】【线上课程】【考研规划】还是【在职考研】呢？**【线下课程】# **【线上课程】#**【考研规划】#**【在职考研】#_x000D_ _x000D_ 01000000034659128491454282423774 2025-06-30 20:05:22_x000D_ 【线下课程】_x000D_ _x000D_ AI-Lbo0rDBXCyBY 2025-06-30 20:05:25_x000D_ 同学，你现在是在校还是在职呢？_x000D_ _x000D_ 01000000034659128491454282423774 2025-06-30 20:05:44_x000D_ 学生_x000D_ _x000D_ AI-Lbo0rDBXCyBY 2025-06-30 20:05:48_x000D_ 具体是想报考什么学校和专业呢？_x000D_ _x000D_ 01000000034659128491454282423774 2025-06-30 20:05:55_x000D_ 报考4级_x000D_ _x000D_ AI-Lbo0rDBXCyBY 2025-06-30 20:05:59_x000D_ 您目前在学的院校是哪所呢？_x000D_ _x000D_ AI-Lbo0rDBXCyBY 2025-06-30 20:06:36_x000D_ 您好，能看到我的对话吗？如有疑问，可以在此留电咨询！_x000D_ _x000D_ 01000000034659128491454282423774 2025-06-30 20:06:53_x000D_ 13641067224_x000D_ _x000D_ AI-Lbo0rDBXCyBY 2025-06-30 20:06:57_x000D_ 好的，确认一下你的号码是否正确呢~_x000D_ _x000D_ 01000000034659128491454282423774 2025-06-30 20:07:10_x000D_ 正确_x000D_ _x000D_ AI-Lbo0rDBXCyBY 2025-06-30 20:07:14_x000D_ 同学怎么称呼呢？_x000D_ _x000D_ 01000000034659128491454282423774 2025-06-30 20:07:26_x000D_ 何_x000D_ _x000D_ AI-Lbo0rDBXCyBY 2025-06-30 20:07:29_x000D_ 这边马上安排顾问老师联系您，预计半个小时左右给您回电请注意接听~_x000D_ _x000D_ 来源页：https://www.xdf.cn/beijing/ 备注： | I13: 2026财年第1财月易聊新东方官网M站 | K13: 徐利霞 | L13: 新东方官网 | M13: 新东方官网M站 | O13: 徐利霞 | P13: 2025-07-01 11:43:20 | Q13: 何格 | R13: 黄智超 | S13: 28764973 | T13: 正常工单 | U13: 2025-07-01 13:40 | V13: A（六个月内有报课意向工单） | W13: 四级,大学预科 | X13: 大一 | Y13: 北京第二外国语学院 | Z13: 中东学院 | AA13: 阿拉伯语 | AB13: 何格 | AC13: 5483208 | AD13: 黄智超 | AE13: 2025-07-17 16:14 | AF13: 黄智超 | AG13: 2025-07-18 15:48 | AH13: YKF25003 | AI13: 四级无忧计划（新大一专属） | AJ13: 国内考试 | AL13: 5180 | AO13: 新签 | AP13: 已交接 | AQ13: BJWY2101498uW2 | AR13: BJWY7411043612 | AS13: YKF250030011 | AT13: 2025-07-17 | AV13: 回访人：黄智超，回访时间：2025-07-08 17:48，回访内容：孩子上次听完试听课回家之后进行了赔偿，今天关心了一下身体，目前反馈还可以，需要等待考录取结果出来之后再决定～；|回访人：黄智超，回访时间：2025-07-11 14:18，回访内容：目前录取结果还没有出来，学生不太确定，还需要再跟进跟进，等一等时间。；|回访人：黄智超，回访时间：2025-07-14 19:27，回访内容：之前试听课过来，要等录取结果出来才能报名，现在结果出来了，学生觉得课程价格高，打算明天给走个五人团 看看能不能交钱；|回访人：黄智超，回访时间：2025-07-15 20:09，回访内容：还是在纠结 在跟家长沟通一下；|回访人：黄智超，回访时间：2025-07-16 18:17，回访内容：目前是跟孩子在沟通，特殊情况还是先不要触达家长 告知了课程团报优惠 孩子还没回复我；|回访人：黄智超，回访时间：2025-07-17 16:14，回访内容：报名暑假预科四级三班（花园桥校区）8月4号开课的班级YKF25003，之前试听课喝我们赠送的水过期了 家长当时有情绪 辛苦老师维护好学生～ | BA13: 80808745 | BB13: 否 | BC13: 25下考季 | BD13: 四级无忧计划 | BG13: 国内高校-双非 | BH13: 否 | BK13: 报名 | BM13: 本地人本地大学(常规) | BN13: 易聊在线咨询
A14: 24 | B14: 北京大学部 | C14: 国内大学部 | D14: 老带新用户 | E14: 119497203 | F14: 黄智超 | G14: 2025-07-16 23:30:44 | H14: 渠道录入来源：老带新系统 老生userid：385b6138-50b9-4f54-ba17-69594722a147 老生学号：BJWY7771366384 老生姓名：肖遥 产品类型：1 活动所属学校名称：北京大学事业部 老带新活动名称：邀好友，大家一起来省钱（班课专用）新 老带新活动id：2366032 推广邮箱：huangzhichao1@xdf.cn | I14: 2026财年第2财月老带新系统 | K14: 黄智超 | L14: 转介绍 | M14: 老带新系统顾问 | N14: 黄智超huangzhichao1@xdf.cn | Q14: 郑文予 | R14: 黄智超 | S14: 29188775 | T14: 正常工单 | U14: 2025-07-17 15:51 | V14: A（六个月内有报课意向工单） | W14: 六级 | X14: 大一 | Y14: 北京市第五十中学 | Z14: 新大一 | AA14: 新大一 | AB14: 郑文予 | AC14: 5415253 | AD14: 黄智超 | AE14: 2025-07-17 16:10 | AF14: 黄智超 | AG14: 2025-07-25 13:36 | AH14: YKS25002 | AI14: 六级无忧计划（新大一专属） | AJ14: 国内考试 | AL14: 5480 | AN14: 黄智超 | AO14: 新签 | AP14: 已交接 | AQ14: WebReg | AR14: BJWY3837265523 | AS14: YKS250020026 | AT14: 2025-07-17 | AV14: 回访人：黄智超，回访时间：2025-07-17 15:51，回访内容：准备和肖遥同学一起报名暑假6级预科二班；|回访人：黄智超，回访时间：2025-07-17 16:10，回访内容：报名暑假预科六级二班（肖遥的同学）YKS25002 | BA14: 81849719 | BB14: 否 | BC14: 25下考季 | BD14: 六级无忧计划 | BG14: 普通学校-普高 | BH14: 否 | BK14: 报名 | BM14: 本地人本地大学(常规) | BN14: 老带新系统
A15: 25 | B15: 北京大学部 | C15: 国内大学部 | D15: 吴昭睿 | E15: 117589255 | F15: 曹伟杰2 | G15: 2025-07-04 14:07:49 | H15: 家长咨询暑期6级线上，报过价格【张志威公众号】 | J15: 大二 | K15: 徐健坤 | L15: 线上运营-私域中台 | M15: 公众号 | Q15: 吴昭睿 | R15: 黄智超 | S15: 28804436 | T15: 正常工单 | U15: 2025-07-16 14:32 | V15: A（六个月内有报课意向工单） | W15: 六级 | X15: 大一 | Y15: 新大一 | Z15: 新大一 | AA15: 新大一 | AB15: 吴昭睿 | AC15: 5414679 | AD15: 黄智超 | AE15: 2025-07-16 14:35 | AF15: 黄智超 | AG15: 2025-07-16 14:36 | AH15: 85308838525 | AI15: 【返学费】六级暑期直通车【2025年12考季】 | AJ15: 国内考试 | AO15: 新签 | AP15: 无须交接 | AT15: 2025-07-16 | AV15: 回访人：徐健坤，回访时间：2025-07-09 22:24，回访内容：电话没有接听 留言；|回访人：刘文君，回访时间：2025-07-13 21:11，回访内容：两遍没接；|回访人：刘文君，回访时间：2025-07-16 12:11，回访内容：2、3k 不在意录播 与其他班型推荐一下 看看试听课 ；|回访人：黄智超，回访时间：2025-07-16 14:35，回访内容：签约 279线上网课 | AZ15: 长期班 | BA15: 56358343 | BB15: 是 | BC15: 25下考季 | BD15: 六级无忧计划 | BG15: 普通学校-普高 | BH15: 否 | BL15: 110549969 | BM15: 本地人本地大学(常规) | BN15: 市场 | BO15: 在线不算 | BP15: 279
A16: 27 | B16: 北京大学部 | C16: 国内大学部 | D16: 张敏 | E16: 118960010 | F16: 杨沫 | G16: 2025-07-14 09:42:07 | H16: 黄智超 | J16: 大学已毕业 | K16: 黄智超 | L16: 转介绍 | M16: 顾问转介绍-新带新 | N16: 张晴 | Q16: 张敏 | R16: 黄智超 | S16: 28993241 | T16: 正常工单 | U16: 2025-07-14 09:54 | V16: A（六个月内有报课意向工单） | W16: 专升本 | X16: 大学已毕业 | Y16: 北京工业职业技术学院 | Z16: 电子科技 | AA16: 电子信息 | AB16: 张敏 | AC16: 5479462 | AD16: 黄智超 | AE16: 2025-07-14 11:44 | AF16: 黄智超 | AG16: 2025-07-14 11:53 | AH16: 24419587709 | AI16: 26通用专升本慧学班-英语 | AJ16: 国内考试 | AL16: 1999 | AN16: 张晴 | AO16: 新签 | AP16: 无须交接 | AT16: 2025-07-14 | AV16: 回访人：黄智超，回访时间：2025-07-14 09:54，回访内容： 张晴同学的表姐，专升本的推荐一对一和网课，预计报名英语网课；|回访人：黄智超，回访时间：2025-07-19 08:09，回访内容：给学生邮寄了4级单词书，维护一下，学生非常开心。 | AZ16: 长期班 | BA16: 81656739 | BB16: 是 | BC16: 26考季 | BD16: 专升本全科全程班 | BE16: 英语 | BG16: 国内高校-大专 | BH16: 否 | BL16: 110536506 | BN16: 客服
A17: 28 | B17: 北京大学部 | C17: 国内大学部 | E17: 116382146 | G17: 2025-06-26 20:00:26 | H17: 【四级】家长咨询，孩子刚高考完，咨询四级线上课程，方便电话；线上四级 | J17: 高三 | K17: 刘晓娟 | L17: 电话 | M17: 大客服呼入 | Q17: 王钧浩 | R17: 刘晓娟 | S17: 29101013 | T17: 续费工单 | U17: 2025-07-14 23:17 | V17: A（六个月内有报课意向工单） | W17: 六级,大学预科 | X17: 大一 | Y17: 北京市第十九中学 | Z17: 新大一 | AA17: 新大一 | AB17: 王钧浩 | AC17: 5413943 | AD17: 刘晓娟 | AE17: 2025-07-14 23:18 | AF17: 刘晓娟 | AG17: 2025-07-14 23:18 | AH17: YKFJ25001 | AI17: 四级无忧计划（线上优享/新大一专属） | AJ17: 国内考试 | AL17: 5680 | AM17: 扩科续费 | AO17: 续班 | AP17: 无须交接 | AQ17: BJWY22035556hl | AR17: BJWY5992971962 | AS17: YKFJ250010059 | AT17: 2025-07-14 | AV17: 回访人：刘晓娟，回访时间：2025-07-14 23:17，回访内容：转班；|回访人：刘晓娟，回访时间：2025-07-14 23:18，回访内容：转班 | BA17: 80589207 | BB17: 否 | BC17: 25下考季 | BD17: 六级无忧计划 | BG17: 普通学校-普高 | BH17: 否 | BK17: 转出 | BM17: 本地人本地大学(常规)
A18: 29 | B18: 北京大学部 | C18: 国内大学部 | E18: 95427640 | G18: 2025-02-24 11:38:58 | H18: （吴丰恺）魏公村直访，刘晓娟接待； | J18: 大一 | K18: 刘晓娟 | L18: 直访 | M18: 直访 | Q18: 吴丰恺 | R18: 刘晓娟 | S18: 29059531 | T18: 续费工单 | U18: 2025-07-13 18:23 | V18: A（六个月内有报课意向工单） | W18: 六级 | X18: 大二 | Y18: 中央财经大学 | Z18: 财政税务学院 | AA18: 财政学 | AB18: 吴丰恺 | AC18: 5478903 | AD18: 刘晓娟 | AE18: 2025-07-13 18:24 | AF18: 刘晓娟 | AG18: 2025-07-13 18:24 | AH18: WYS25042 | AI18: 六级无忧计划 | AJ18: 国内考试 | AL18: 4314.7 | AM18: 同科续费 | AO18: 续班 | AP18: 未交接 | AQ18: BJWY24032w1g8X | AR18: BJWY3487591469 | AS18: WYS250420001 | AT18: 2025-07-13 | AV18: 回访人：刘晓娟，回访时间：2025-07-13 18:23，回访内容：转班；|回访人：刘晓娟，回访时间：2025-07-13 18:24，回访内容：转班 | BA18: 67227543 | BB18: 否 | BC18: 25下考季 | BD18: 六级无忧计划 | BG18: 国内高校-211 | BH18: 否 | BK18: 转出 | BM18: 外地人本地大学(常规)
A19: 30 | B19: 北京大学部 | C19: 国内大学部 | D19: 未知 | E19: 116992462 | F19: 吕猛 | G19: 2025-07-01 18:56:54 | H19: 咨询六级线下课程 渠道录入来源：大众点评 事件名称：在线咨询 大众点评门店名称：新东方考研四六级(惠新东街校区) 店铺绑定的校区：临时教学校区 店铺管理员邮箱：lvmeng2@xdf.cn 备注：2025-07-01 18:56:52,用户在大众点评新东方考研四六级(惠新东街校区)在线咨询 | I19: 2026财年第2财月大众点评在线咨询 | J19: 未知 | K19: 黄智超 | L19: 线上运营-本地生活平台 | M19: 大众点评 | Q19: 何嘉蔚 | R19: 黄智超 | S19: 28751369 | T19: 正常工单 | U19: 2025-07-01 20:31 | V19: A（六个月内有报课意向工单） | W19: 六级 | X19: 大二 | Y19: 北京工业大学 | Z19: 经济与管理学院 | AA19: 经济统计学 | AB19: 何嘉蔚 | AC19: 5478861 | AD19: 黄智超 | AE19: 2025-07-13 18:10 | AF19: 黄智超 | AG19: 2025-07-17 12:55 | AH19: WYS25035 | AI19: 六级无忧计划 | AJ19: 国内考试 | AL19: 6180 | AO19: 新签 | AP19: 已交接 | AQ19: BJWY2011wXCx1W | AR19: BJWY0320886291 | AS19: WYS250350036 | AT19: 2025-07-13 | AV19: 回访人：黄智超，回访时间：2025-07-05 09:46，回访内容：问问家长和孩子沟通的结果，家长暂未回微信。；|回访人：黄智超，回访时间：2025-07-07 21:26，回访内容：目前孩子的时间冲突，所以还在观望中，孩子目前只能接受纯8月开课的。；|回访人：黄智超，回访时间：2025-07-09 17:08，回访内容：家长只接受8月份的班 目前也没时间 还需要沟通孩子；|回访人：黄智超，回访时间：2025-07-13 18:10，回访内容：报名六级二班，WYS25035昨天交了5680今天补500 6180入班 | BA19: 56508496 | BB19: 否 | BC19: 25下考季 | BD19: 六级无忧计划 | BG19: 国内高校-211 | BH19: 是 | BK19: 报名 | BM19: 本地人本地大学(常规) | BN19: 新媒体管家-点评
A20: 31 | B20: 北京大学部 | C20: 国内大学部 | D20: 许致浩 | E20: 118802764 | F20: 方勃文 | G20: 2025-07-12 21:43:13 | H20: 学生在辽宁，咨询四级线上课，加微信发送课程【已在群内反馈】 | J20: 大三 | K20: 黄智超 | L20: 线上运营-私域中台 | M20: 社群、虚拟人 | Q20: 许致浩 | R20: 黄智超 | S20: 29055010 | T20: 正常工单 | U20: 2025-07-13 13:21 | V20: A（六个月内有报课意向工单） | W20: 四级 | X20: 大三 | Y20: 北京科技大学 | Z20: 土木与资源工程学院 | AA20: 建筑设备与能源应用工程 | AB20: 许致浩 | AC20: 5478547 | AD20: 黄智超 | AE20: 2025-07-13 16:02 | AF20: 黄智超 | AG20: 2025-07-13 16:51 | AH20: 17096309135 | AI20: 【返学费】四级暑期直通车【2025年12考季】 | AJ20: 国内考试 | AO20: 新签 | AP20: 无须交接 | AT20: 2025-07-13 | AV20: 回访人：黄智超，回访时间：2025-07-13 13:21，回访内容：学生在忙 微信通过后沟通 目前考虑网课 但是我们的5980课程价格高 学生不能接受 推荐在线网课 看看孩子的反馈；|回访人：黄智超，回访时间：2025-07-19 08:12，回访内容：给学生邮寄了4级词汇书，祝愿他4级顺利通过吧～ | AZ20: 长期班 | BA20: 81621863 | BB20: 是 | BC20: 27下考季 | BD20: 四级无忧计划 | BG20: 国内高校-211 | BH20: 否 | BL20: 109227936 | BM20: 外地人本地大学(常规) | BN20: 市场 | BO20: 在线不算 | BP20: 279
A21: 35 | B21: 北京大学部 | C21: 国内大学部 | D21: 顾芳丞 | E21: 113731966 | F21: 陈自强 | G21: 2025-06-11 15:19:56 | H21: 高三家长资源，按毛坯数据话术回访即可，重点沟通大学预科以及四六级课程暑期学习重要性，引导了解 | I21: 批量导入-京内-渠道推荐-高三-陈自强-250611 | J21: 高三 | K21: 曹健 | L21: 市场活动 | M21: 京内会销/讲座 | O21: 曹健 | P21: 2025-06-19 18:22:38 | Q21: 顾芳丞 | R21: 刘晓娟 | S21: 28497327 | T21: 正常工单 | U21: 2025-06-19 19:19 | V21: A（六个月内有报课意向工单） | W21: 六级,大学预科 | X21: 大一 | Y21: 北京西城区裕中中学 | Z21: 新大一 | AA21: 新大一 | AB21: 顾芳丞 | AC21: 5477552 | AD21: 刘晓娟 | AE21: 2025-07-12 18:06 | AF21: 刘晓娟 | AG21: 2025-07-14 23:16 | AH21: YKS25002 | AI21: 六级无忧计划（新大一专属） | AJ21: 国内考试 | AL21: 4880 | AO21: 新签 | AP21: 已交接 | AQ21: BJWY2101498uW2 | AR21: BJWY7653144964 | AS21: YKS250020021 | AT21: 2025-07-12 | AV21: 回访人：刘晓娟，回访时间：2025-07-03 14:59，回访内容：邀约讲座；|回访人：刘晓娟，回访时间：2025-07-10 19:14，回访内容：邀约讲座；|回访人：刘晓娟，回访时间：2025-07-12 18:06，回访内容：报名 | BA21: 74585485 | BB21: 否 | BC21: 25下考季 | BD21: 六级无忧计划 | BG21: 普通学校-普高 | BH21: 是 | BK21: 报名 | BM21: 本地人本地大学(常规) | BN21: 市场
A22: 36 | B22: 北京大学部 | C22: 国内大学部 | E22: 116612399 | G22: 2025-06-29 13:38:30 | H22: 孩子高一，家长意向8月4- 8月16四级，加微信联系，备注曹老师推荐【张志威公众号】 | J22: 高一 | K22: 田一禾 | L22: 线上运营-私域中台 | M22: 公众号 | Q22: 王洛欢 | R22: 田一禾 | S22: 29362963 | T22: 续费工单 | U22: 2025-08-03 11:44 | V22: B（需长时间跟单或只需要规划） | W22: 四级,大学预科 | X22: 大一 | Y22: 询问院校未告知 | Z22: 询问院系未告知 | AA22: 询问专业未告知 | AB22: 王洛欢 | AC22: 5530669 | AD22: 田一禾 | AE22: 2025-08-03 11:45 | AF22: 田一禾 | AG22: 2025-08-03 11:46 | AH22: YKS25003 | AI22: 六级无忧计划（新大一专属） | AJ22: 国内考试 | AL22: 4880 | AM22: 扩科续费 | AO22: 续班 | AP22: 已交接 | AQ22: BJWY2101498uW2 | AR22: BJWY7022979955 | AS22: YKS250030004 | AT22: 2025-07-11 | AV22: 回访人：田一禾，回访时间：2025-08-03 11:44，回访内容：转班；|回访人：田一禾，回访时间：2025-08-03 11:45，回访内容：转班操作 | BA22: 80712352 | BB22: 否 | BC22: 28下考季 | BD22: 四级无忧计划 | BG22: 普通学校-普高 | BH22: 是 | BK22: 转出
A23: 37 | B23: 北京大学部 | C23: 国内大学部 | D23: Sunshine | E23: 116905889 | F23: 王朝群 | G23: 2025-07-01 23:50:32 | H23: 【王朝群】咨询大学预科 | I23: 2026财年第2财月小红书 | J23: 大一 | K23: 黄智超 | L23: 线上运营-小红书 | M23: 小红书 | Q23: 田沐家 | R23: 黄智超 | S23: 28756058 | T23: 正常工单 | U23: 2025-07-02 14:05 | V23: A（六个月内有报课意向工单） | W23: 六级,大学预科 | X23: 大一 | Y23: 北师大二附中海淀校区 | Z23: 询问院系未告知 | AA23: 询问专业未告知 | AB23: 田沐家 | AC23: 5411942 | AD23: 黄智超 | AE23: 2025-07-10 21:38 | AF23: 黄智超 | AG23: 2025-07-13 15:53 | AH23: YK25002 | AI23: 大学口语特训营 | AJ23: 国内考试 | AL23: 3998.9 | AO23: 新签 | AP23: 已交接 | AQ23: WebReg | AR23: BJWY7835063861 | AS23: YK250020016 | AT23: 2025-07-10 | AV23: 回访人：黄智超，回访时间：2025-07-02 14:05，回访内容：孩子英语基础不错 130分左右 建议学六级小班 也咨询了六级大班的课程安排 微信电话沟通 目前意向比较高 持续联系 邀约试听课；|回访人：黄智超，回访时间：2025-07-04 23:31，回访内容：问问家长和孩子沟通的情况如何 目前暂未回复；|回访人：黄智超，回访时间：2025-07-08 21:32，回访内容：准备报名了 家长还未付款 明天重新发送；|回访人：黄智超，回访时间：2025-07-09 16:34，回访内容：电话不接 缴费码都发了 还没交钱；|回访人：黄智超，回访时间：2025-07-10 21:38，回访内容：已签约，预科六级全科（魏公村）；|回访人：黄智超，回访时间：2025-07-15 21:55，回访内容：告知线上线下的课程区别，鼓励孩子尽可能来线下学习 | BA23: 67717559 | BB23: 否 | BC23: 25下考季 | BD23: 六级无忧计划 | BG23: 普通学校-普高 | BH23: 是 | BK23: 报名 | BM23: 本地人本地大学(常规) | BN23: 小红书
A24: 38 | B24: 北京大学部 | C24: 国内大学部 | D24: Sunshine | E24: 116905889 | F24: 王朝群 | G24: 2025-07-01 23:50:32 | H24: 【王朝群】咨询大学预科 | I24: 2026财年第2财月小红书 | J24: 大一 | K24: 黄智超 | L24: 线上运营-小红书 | M24: 小红书 | Q24: 田沐家 | R24: 黄智超 | S24: 28756058 | T24: 正常工单 | U24: 2025-07-02 14:05 | V24: A（六个月内有报课意向工单） | W24: 六级,大学预科 | X24: 大一 | Y24: 北师大二附中海淀校区 | Z24: 询问院系未告知 | AA24: 询问专业未告知 | AB24: 田沐家 | AC24: 5411942 | AD24: 黄智超 | AE24: 2025-07-10 21:38 | AF24: 黄智超 | AG24: 2025-07-13 15:53 | AH24: YKS25001 | AI24: 六级无忧计划（新大一专属） | AJ24: 国内考试 | AL24: 4802.1 | AO24: 新签 | AP24: 已交接 | AQ24: WebReg | AR24: BJWY7835063861 | AS24: YKS250010047 | AT24: 2025-07-10 | AV24: 回访人：黄智超，回访时间：2025-07-02 14:05，回访内容：孩子英语基础不错 130分左右 建议学六级小班 也咨询了六级大班的课程安排 微信电话沟通 目前意向比较高 持续联系 邀约试听课；|回访人：黄智超，回访时间：2025-07-04 23:31，回访内容：问问家长和孩子沟通的情况如何 目前暂未回复；|回访人：黄智超，回访时间：2025-07-08 21:32，回访内容：准备报名了 家长还未付款 明天重新发送；|回访人：黄智超，回访时间：2025-07-09 16:34，回访内容：电话不接 缴费码都发了 还没交钱；|回访人：黄智超，回访时间：2025-07-10 21:38，回访内容：已签约，预科六级全科（魏公村）；|回访人：黄智超，回访时间：2025-07-15 21:55，回访内容：告知线上线下的课程区别，鼓励孩子尽可能来线下学习 | BA24: 67717559 | BB24: 否 | BC24: 25下考季 | BD24: 六级无忧计划 | BG24: 普通学校-普高 | BH24: 是 | BK24: 报名 | BM24: 本地人本地大学(常规) | BN24: 小红书
A25: 39 | B25: 北京大学部 | C25: 国内大学部 | D25: Sunshine | E25: 116905889 | F25: 王朝群 | G25: 2025-07-01 23:50:32 | H25: 【王朝群】咨询大学预科 | I25: 2026财年第2财月小红书 | J25: 大一 | K25: 黄智超 | L25: 线上运营-小红书 | M25: 小红书 | Q25: 田沐家 | R25: 黄智超 | S25: 28756058 | T25: 正常工单 | U25: 2025-07-02 14:05 | V25: A（六个月内有报课意向工单） | W25: 六级,大学预科 | X25: 大一 | Y25: 北师大二附中海淀校区 | Z25: 询问院系未告知 | AA25: 询问专业未告知 | AB25: 田沐家 | AC25: 5411942 | AD25: 黄智超 | AE25: 2025-07-10 21:38 | AF25: 黄智超 | AG25: 2025-07-13 15:53 | AH25: YKM25001 | AI25: 大学预科数学（新大一专属） | AJ25: 国内考试 | AL25: 3999 | AO25: 新签 | AP25: 已交接 | AQ25: WebReg | AR25: BJWY7835063861 | AS25: YKM250010042 | AT25: 2025-07-10 | AV25: 回访人：黄智超，回访时间：2025-07-02 14:05，回访内容：孩子英语基础不错 130分左右 建议学六级小班 也咨询了六级大班的课程安排 微信电话沟通 目前意向比较高 持续联系 邀约试听课；|回访人：黄智超，回访时间：2025-07-04 23:31，回访内容：问问家长和孩子沟通的情况如何 目前暂未回复；|回访人：黄智超，回访时间：2025-07-08 21:32，回访内容：准备报名了 家长还未付款 明天重新发送；|回访人：黄智超，回访时间：2025-07-09 16:34，回访内容：电话不接 缴费码都发了 还没交钱；|回访人：黄智超，回访时间：2025-07-10 21:38，回访内容：已签约，预科六级全科（魏公村）；|回访人：黄智超，回访时间：2025-07-15 21:55，回访内容：告知线上线下的课程区别，鼓励孩子尽可能来线下学习 | BA25: 67717559 | BB25: 否 | BC25: 25下考季 | BD25: 六级无忧计划 | BG25: 普通学校-普高 | BH25: 是 | BK25: 报名 | BM25: 本地人本地大学(常规) | BN25: 小红书
A26: 40 | B26: 北京大学部 | C26: 国内大学部 | D26: 李嘉泽 | E26: 117825382 | F26: 曹伟杰2 | G26: 2025-07-06 17:19:07 | H26: 家长咨询暑期四级【tmk合作徐树萌老师】 | J26: 大一 | K26: 徐树萌 | L26: 线上运营-私域中台 | M26: TMK合作 | O26: 徐树萌 | P26: 2025-07-06 17:33:18 | Q26: 李左文 | R26: 徐健坤 | S26: 28893730 | T26: 正常工单 | U26: 2025-07-06 18:30 | V26: A（六个月内有报课意向工单） | W26: 四级,大学预科 | X26: 大一 | Y26: 清华大学附属中学（奥森校区） | Z26: 新大一 | AA26: 新大一 | AB26: 李左文 | AC26: 5473056 | AD26: 徐健坤 | AE26: 2025-07-08 22:19 | AF26: 徐健坤 | AG26: 2025-07-15 16:36 | AH26: YKF25001 | AI26: 四级无忧计划（新大一专属） | AJ26: 国内考试 | AL26: 5180 | AO26: 新签 | AP26: 已交接 | AQ26: BJWY25030q8UPI | AR26: BJWY4028539388 | AS26: YKF250010053 | AT26: 2025-07-08 | AV26: 回访人：徐健坤，回访时间：2025-07-06 18:30，回访内容：英语99 基础薄弱 小班；|回访人：徐健坤，回访时间：2025-07-07 22:01，回访内容：看了课表；|回访人：徐健坤，回访时间：2025-07-08 22:19，回访内容：签约 | BA26: 59777577 | BB26: 否 | BC26: 25下考季 | BD26: 四级无忧计划 | BG26: 普通学校-普高 | BH26: 否 | BK26: 报名 | BM26: 本地人本地大学(常规) | BN26: 市场
A27: 41 | B27: 北京大学部 | C27: 国内大学部 | D27: 头头 | E27: 114348125 | F27: 王朝群 | G27: 2025-06-14 17:03:28 | H27: 【王朝群】咨询四六级暑期班 | I27: 2026财年第1财月小红书 | J27: 大二 | K27: 黄智超 | L27: 线上运营-小红书 | M27: 小红书 | Q27: 许博铭 | R27: 黄智超 | S27: 28358094 | T27: 续费工单 | U27: 2025-06-14 18:01 | V27: A（六个月内有报课意向工单） | W27: 六级,大学预科 | X27: 高三 | Y27: 北京市八一中学 | Z27: 新大一 | AA27: 新大一 | AB27: 许博铭 | AC27: 5470637 | AD27: 黄智超 | AE27: 2025-07-06 22:48 | AF27: 黄智超 | AG27: 2025-07-09 15:39 | AH27: YKS25004 | AI27: 六级精英计划（新大一专属） | AJ27: 国内考试 | AL27: 20300 | AO27: 新签 | AP27: 已交接 | AQ27: BJWY2101498uW2 | AR27: BJWY4996201639 | AS27: YKS250040007 | AT27: 2025-07-08 | AV27: 回访人：黄智超，回访时间：2025-07-02 22:13，回访内容：高考志愿填报结束 邀约试听课 看看能不能来 再持续沟通；|回访人：黄智超，回访时间：2025-07-04 19:40，回访内容：明天来线下试听课 跟孩子一起过来；|回访人：黄智超，回访时间：2025-07-05 23:56，回访内容：试听课邀约现场；|回访人：黄智超，回访时间：2025-07-06 22:48，回访内容：签约，四级暑假小班2期，20300 | BA27: 74677393 | BB27: 否 | BC27: 25下考季 | BD27: 六级无忧计划 | BG27: 国内高校-双非 | BH27: 否 | BK27: 转出 | BN27: 小红书
A28: 42 | B28: 北京大学部 | C28: 国内大学部 | D28: 张雅冬同学 | E28: 117632295 | F28: 吴凯龙 | G28: 2025-07-04 19:26:26 | H28: 徐健坤1的内部员工推荐工单 | J28: 高三 | K28: 徐健坤 | L28: 转介绍 | M28: 内部员工推荐 | N28: 郑威+zhengwei16@xdf.cn+ID+培训学校-北京学校-高中一对一部-东南区-蒲黄榆分中心 | Q28: 张雅冬 | R28: 徐健坤 | S28: 28864952 | T28: 正常工单 | U28: 2025-07-04 22:30 | V28: A（六个月内有报课意向工单） | W28: 六级,大学预科 | X28: 高三 | Y28: 香港科技大学 | Z28: 询问院系未告知 | AA28: 询问专业未告知 | AB28: 张雅冬 | AC28: 5442109 | AD28: 徐健坤 | AE28: 2025-07-07 10:20 | AF28: 徐健坤 | AG28: 2025-07-07 23:01 | AH28: LP1751854837306 | AI28: 大学英语一对一（30H） | AJ28: 国内考试 | AL28: 25000 | AN28: 郑威+zhengwei16@xdf.cn+ID+培训学校-北京学校-高中一对一部-东南区-蒲黄榆分中心 | AO28: 新签 | AP28: 已交接 | AR28: BJWY8096770861 | AT28: 2025-07-07 | AV28: 回访人：徐健坤，回访时间：2025-07-04 22:30，回访内容：高考英语133 基础不错 听力口语稍差 一对一方式 总结：您与北京新东方徐老师建立了联系，徐老师负责多种国内考试咨询，并邀请您参加明天的试听课。试听课由韩老师主讲四六级内容，口语部分由娜扎老师负责，她是北外英语演讲比赛的评委，发音纯正。您已预约试听课，并表示如有变动会提前通知。 下次回访建议：建议在试听课后跟进，了解您对课程内容和教师教学的反馈，同时询问是否有进一步的学习需求或问题，以便提供更个性化的教育咨询服务。；|回访人：徐健坤，回访时间：2025-07-06 23:04，回访内容：已经支付 明天交接 总结：北京新东方徐老师通过微信联系，提供大学预科、专升本、四六级、考研等国内考试咨询服务。双方讨论了试听课的安排，确认了授课老师（韩老师和娜扎老师）及课程内容（四六级和口语）。家长为孩子（张雅冬）报名了四六级VIP课程，并签署了培训协议，完成了支付流程。徐老师将后续安排入班对接。 下次回访建议： 1. 确认张雅冬同学的上课时间和地点是否已协调妥当，尤其是娜扎老师在国贸的课程安排。 2. 跟进学生对试听课的反馈，了解其学习需求和目标，以便进一步调整课程计划。 3. 提醒家长和学生关于课程进度和后续安排，确保学习计划顺利推进。 4. 如有其他优惠活动或课程推荐，可适时告知家长，增加合作机会。 | BA28: 75637628 | BB28: 否 | BC28: 25下考季 | BD28: 六级一对一 | BG28: 海外学校-国外大学-其他 | BH28: 是 | BM28: 本地人外地大学(归巢) | BN28: 客服
A29: 45 | B29: 北京大学部 | C29: 国内大学部 | D29: 未知 | E29: 114207297 | F29: 李雪68 | G29: 2025-06-13 17:22:01 | H29: 激活 | J29: 大四 | K29: 刘晓娟 | L29: 转介绍 | M29: 顾问转介绍-老带新 | N29: 激活 | Q29: 张裾扬 | R29: 刘晓娟 | S29: 28327261 | T29: 正常工单 | U29: 2025-06-13 17:38 | V29: A（六个月内有报课意向工单） | W29: 专八 | X29: 大四 | Y29: 中国石油大学(北京) | Z29: 英语 | AA29: 英语 | AB29: 张裾扬 | AC29: 5439737 | AD29: 刘晓娟 | AE29: 2025-07-05 15:42 | AF29: 刘晓娟 | AG29: 2025-07-05 15:42 | AH29: 16684991291 | AI29: 2026英语专业八级全程班【直播 + 录播】 | AJ29: 国内考试 | AL29: 1529.15 | AN29: 激活 | AO29: 新签 | AP29: 无须交接 | AT29: 2025-07-05 | AV29: 回访人：刘晓娟，回访时间：2025-06-27 18:19，回访内容：等放假再报；|回访人：刘晓娟，回访时间：2025-07-04 18:31，回访内容：确认放假时间，等回复；|回访人：刘晓娟，回访时间：2025-07-05 15:42，回访内容：报名 | AZ29: 长期班 | BA29: 67366752 | BB29: 是 | BG29: 国内高校-211 | BH29: 否 | BL29: 110483407 | BM29: 本地人本地大学(常规) | BN29: 客服
A30: 46 | B30: 北京大学部 | C30: 国内大学部 | D30: 家长 | E30: 117067786 | F30: 乔文娇 | G30: 2025-07-02 10:11:27 | H30: 新大一，高考英语130多分，学四六级，告知还有口语特训 | J30: 大一 | K30: 乔文娇 | L30: 电话 | M30: 大客服呼入 | O30: 乔文娇 | P30: 2025-07-02 10:29:10 | Q30: 张馨予 | R30: 黄智超 | S30: 28782116 | T30: 正常工单 | U30: 2025-07-02 21:57 | V30: A（六个月内有报课意向工单） | W30: 六级,大学预科 | X30: 大一 | Y30: 新大一 | Z30: 新大一 | AA30: 新大一 | AB30: 张馨予 | AC30: 5409352 | AD30: 黄智超 | AE30: 2025-07-05 22:44 | AF30: 黄智超 | AG30: 2025-07-08 16:37 | AH30: YKM25001 | AI30: 大学预科数学（新大一专属） | AJ30: 国内考试 | AL30: 3725.6 | AO30: 新签 | AP30: 已交接 | AQ30: BJWY2011wXCx1W | AR30: BJWY8390237928 | AS30: YKM250010029 | AT30: 2025-07-05 | AV30: 回访人：黄智超，回访时间：2025-07-02 21:57，回访内容：家长给孩子咨询暑假课程 推荐了预科联报的课程 邀约试听课 家长来添加我的微信 ；|回访人：黄智超，回访时间：2025-07-04 23:11，回访内容：确认邀明天试听课 跟孩子一起来；|回访人：黄智超，回访时间：2025-07-05 22:44，回访内容：签约 大学预科花园桥校区2期班 9160：YKS25002+YKM25002 | BA30: 80891575 | BB30: 否 | BC30: 25下考季 | BD30: 六级无忧计划 | BG30: 国内高校-双非 | BH30: 否 | BI30: 老师好 学员需要报名花园桥二期班：需操作转班，班号YKS25002+YKM25002 | BK30: 报名 | BM30: 本地人本地大学(常规) | BN30: 客服
A31: 47 | B31: 北京大学部 | C31: 国内大学部 | D31: 家长 | E31: 117067786 | F31: 乔文娇 | G31: 2025-07-02 10:11:27 | H31: 新大一，高考英语130多分，学四六级，告知还有口语特训 | J31: 大一 | K31: 乔文娇 | L31: 电话 | M31: 大客服呼入 | O31: 乔文娇 | P31: 2025-07-02 10:29:10 | Q31: 张馨予 | R31: 黄智超 | S31: 28782116 | T31: 正常工单 | U31: 2025-07-02 21:57 | V31: A（六个月内有报课意向工单） | W31: 六级,大学预科 | X31: 大一 | Y31: 新大一 | Z31: 新大一 | AA31: 新大一 | AB31: 张馨予 | AC31: 5409352 | AD31: 黄智超 | AE31: 2025-07-05 22:44 | AF31: 黄智超 | AG31: 2025-07-08 16:37 | AH31: YKS25001 | AI31: 六级无忧计划（新大一专属） | AJ31: 国内考试 | AL31: 5434.4 | AO31: 新签 | AP31: 已交接 | AQ31: BJWY2011wXCx1W | AR31: BJWY8390237928 | AS31: YKS250010027 | AT31: 2025-07-05 | AV31: 回访人：黄智超，回访时间：2025-07-02 21:57，回访内容：家长给孩子咨询暑假课程 推荐了预科联报的课程 邀约试听课 家长来添加我的微信 ；|回访人：黄智超，回访时间：2025-07-04 23:11，回访内容：确认邀明天试听课 跟孩子一起来；|回访人：黄智超，回访时间：2025-07-05 22:44，回访内容：签约 大学预科花园桥校区2期班 9160：YKS25002+YKM25002 | BA31: 80891575 | BB31: 否 | BC31: 25下考季 | BD31: 六级无忧计划 | BG31: 国内高校-双非 | BH31: 否 | BI31: 老师好 学员需要报名花园桥二期班：需操作转班，班号YKS25002+YKM25002 | BK31: 报名 | BM31: 本地人本地大学(常规) | BN31: 客服
A32: 48 | B32: 北京大学部 | C32: 国内大学部 | D32: 未知 | E32: 116611280 | F32: 吕猛 | G32: 2025-06-29 11:56:39 | H32: 准大一，咨询四级课程，高考成绩 88 分，其中听力 44 分，下午3点打电话 渠道录入来源：大众点评 事件名称：在线咨询 大众点评门店名称：新东方考研四六级(良乡大学城校区) 店铺绑定的校区：临时教学校区 店铺管理员邮箱：lvmeng2@xdf.cn 备注：2025-06-29 11:56:37,用户在大众点评新东方考研四六级(良乡大学城校区)在线咨询 | I32: 2026财年第1财月大众点评在线咨询 | J32: 大一 | K32: 张博奥 | L32: 线上运营-本地生活平台 | M32: 大众点评 | Q32: 牟锡泽 | R32: 张博奥 | S32: 28631574 | T32: 正常工单 | U32: 2025-06-29 15:49 | V32: A（六个月内有报课意向工单） | W32: 四级,大学预科 | X32: 高三 | Y32: 北京市海淀外国语实验学校 | Z32: 询问院系未告知 | AA32: 询问专业未告知 | AB32: 牟锡泽 | AC32: 5468639 | AD32: 张博奥 | AE32: 2025-07-05 17:43 | AF32: 张博奥 | AG32: 2025-07-08 23:01 | AH32: YKF25001 | AI32: 四级无忧计划（新大一专属） | AJ32: 国内考试 | AL32: 4880 | AO32: 新签 | AP32: 已交接 | AQ32: BJWY24032w1g8X | AR32: BJWY3145941871 | AS32: YKF250010036 | AT32: 2025-07-04 | AV32: 回访人：张博奥，回访时间：2025-06-29 15:49，回访内容：孩子本人接听，英语基础薄弱，意向小班课，需要和家长商量一下，强调了优惠，持续跟进；|回访人：张博奥，回访时间：2025-06-30 21:09，回访内容：给同学提供了第二套学习方案，孩子表示要和家里商量一下，给孩子说了优惠问题，加紧跟进；|回访人：张博奥，回访时间：2025-07-02 10:26，回访内容：昨天已经分别和孩子和孩子父亲取得有效沟通，孩子对课程没有其他问题，父亲缴费，父亲在持续的了解课程细节，此前给孩子规划的大班套10小时一对一，现在家长又想了解小班课程；|回访人：张博奥，回访时间：2025-07-04 23:09，回访内容：已报名；|回访人：张博奥，回访时间：2025-07-05 17:29，回访内容：张博奥进行了退单操作!(本条回访记录由系统自动记录) | BA32: 80711737 | BB32: 否 | BC32: 25下考季 | BD32: 四级无忧计划,四级一对一 | BG32: 普通学校-普高 | BH32: 是 | BI32: 请学管老师尽快联系 | BK32: 报名 | BM32: 本地人本地大学(常规) | BN32: 新媒体管家-点评
A33: 49 | B33: 北京大学部 | C33: 国内大学部 | D33: 未知 | E33: 116611280 | F33: 吕猛 | G33: 2025-06-29 11:56:39 | H33: 准大一，咨询四级课程，高考成绩 88 分，其中听力 44 分，下午3点打电话 渠道录入来源：大众点评 事件名称：在线咨询 大众点评门店名称：新东方考研四六级(良乡大学城校区) 店铺绑定的校区：临时教学校区 店铺管理员邮箱：lvmeng2@xdf.cn 备注：2025-06-29 11:56:37,用户在大众点评新东方考研四六级(良乡大学城校区)在线咨询 | I33: 2026财年第1财月大众点评在线咨询 | J33: 大一 | K33: 张博奥 | L33: 线上运营-本地生活平台 | M33: 大众点评 | Q33: 牟锡泽 | R33: 张博奥 | S33: 28631574 | T33: 正常工单 | U33: 2025-06-29 15:49 | V33: A（六个月内有报课意向工单） | W33: 四级,大学预科 | X33: 高三 | Y33: 北京市海淀外国语实验学校 | Z33: 询问院系未告知 | AA33: 询问专业未告知 | AB33: 牟锡泽 | AC33: 5468639 | AD33: 张博奥 | AE33: 2025-07-05 17:43 | AF33: 张博奥 | AG33: 2025-07-08 23:01 | AH33: LP17517086222288 | AI33: 四级一对一伴学班 | AJ33: 国内考试 | AL33: 8500 | AO33: 新签 | AP33: 已交接 | AQ33: BJWY24032w1g8X | AR33: BJWY3145941871 | AT33: 2025-07-05 | AV33: 回访人：张博奥，回访时间：2025-06-29 15:49，回访内容：孩子本人接听，英语基础薄弱，意向小班课，需要和家长商量一下，强调了优惠，持续跟进；|回访人：张博奥，回访时间：2025-06-30 21:09，回访内容：给同学提供了第二套学习方案，孩子表示要和家里商量一下，给孩子说了优惠问题，加紧跟进；|回访人：张博奥，回访时间：2025-07-02 10:26，回访内容：昨天已经分别和孩子和孩子父亲取得有效沟通，孩子对课程没有其他问题，父亲缴费，父亲在持续的了解课程细节，此前给孩子规划的大班套10小时一对一，现在家长又想了解小班课程；|回访人：张博奥，回访时间：2025-07-04 23:09，回访内容：已报名；|回访人：张博奥，回访时间：2025-07-05 17:29，回访内容：张博奥进行了退单操作!(本条回访记录由系统自动记录) | BA33: 80711737 | BB33: 否 | BC33: 25下考季 | BD33: 四级无忧计划,四级一对一 | BG33: 普通学校-普高 | BH33: 是 | BI33: 请学管老师尽快联系 | BM33: 本地人本地大学(常规) | BN33: 新媒体管家-点评
A34: 50 | B34: 北京大学部 | C34: 国内大学部 | D34: 于奥洋 | E34: 117158030 | F34: 李雪68 | G34: 2025-07-02 14:13:36 | J34: 大二 | K34: 黄智超 | L34: 转介绍 | M34: 内部员工推荐 | N34: 高晶+gaojing43@xdf.cn+312057+培训学校-北京学校-高中一对一部-西南区-玉泉路分中心 | Q34: 于奥洋 | R34: 黄智超 | S34: 28775947 | T34: 续费工单 | U34: 2025-07-02 14:23 | V34: A（六个月内有报课意向工单） | W34: 六级,大学预科 | X34: 大一 | Y34: 北师大朝阳附中 | Z34: 询问院系未告知 | AA34: 询问专业未告知 | AB34: 于奥洋 | AC34: 5465163 | AD34: 黄智超 | AE34: 2025-07-02 21:20 | AF34: 黄智超 | AG34: 2025-08-03 12:24 | AH34: YKS25001 | AI34: 六级无忧计划（新大一专属） | AJ34: 国内考试 | AL34: 5680 | AN34: 高晶+gaojing43@xdf.cn+312057+培训学校-北京学校-高中一对一部-西南区-玉泉路分中心 | AO34: 新签 | AP34: 已交接 | AQ34: WebReg | AR34: BJWY8894097228 | AS34: YKS250010018 | AT34: 2025-07-02 | AV34: 回访人：黄智超，回访时间：2025-07-02 14:23，回访内容：孩子自己咨询，暑假四六级课程，基础比较好，137高考英语，可以直接学习六级课程，介绍的比较详细，孩子倾向小班授课，添加微信具体沟通；|回访人：黄智超，回访时间：2025-07-02 21:20，回访内容：签约 大预六级精英计划 | BA34: 56143849 | BB34: 否 | BC34: 25下考季 | BD34: 六级无忧计划 | BG34: 国内高校-双非 | BH34: 否 | BK34: 报名 | BM34: 本地人本地大学(常规) | BN34: 客服
A35: 51 | B35: 北京大学部 | C35: 国内大学部 | D35: 于奥洋 | E35: 117158030 | F35: 李雪68 | G35: 2025-07-02 14:13:36 | J35: 大二 | K35: 黄智超 | L35: 转介绍 | M35: 内部员工推荐 | N35: 高晶+gaojing43@xdf.cn+312057+培训学校-北京学校-高中一对一部-西南区-玉泉路分中心 | Q35: 于奥洋 | R35: 黄智超 | S35: 28775947 | T35: 续费工单 | U35: 2025-07-02 14:23 | V35: A（六个月内有报课意向工单） | W35: 六级,大学预科 | X35: 大一 | Y35: 北师大朝阳附中 | Z35: 询问院系未告知 | AA35: 询问专业未告知 | AB35: 于奥洋 | AC35: 5465163 | AD35: 黄智超 | AE35: 2025-07-02 21:20 | AF35: 黄智超 | AG35: 2025-08-03 12:24 | AH35: YKS25004 | AI35: 六级精英计划（新大一专属） | AJ35: 国内考试 | AL35: 20300 | AN35: 高晶+gaojing43@xdf.cn+312057+培训学校-北京学校-高中一对一部-西南区-玉泉路分中心 | AO35: 新签 | AP35: 已交接 | AQ35: BJWY25030q8UPI | AR35: BJWY8894097228 | AS35: YKS250040003 | AT35: 2025-07-03 | AV35: 回访人：黄智超，回访时间：2025-07-02 14:23，回访内容：孩子自己咨询，暑假四六级课程，基础比较好，137高考英语，可以直接学习六级课程，介绍的比较详细，孩子倾向小班授课，添加微信具体沟通；|回访人：黄智超，回访时间：2025-07-02 21:20，回访内容：签约 大预六级精英计划 | BA35: 56143849 | BB35: 否 | BC35: 25下考季 | BD35: 六级无忧计划 | BG35: 国内高校-双非 | BH35: 否 | BK35: 报名 | BM35: 本地人本地大学(常规) | BN35: 客服
A36: 52 | B36: 北京大学部 | C36: 国内大学部 | D36: 魏亚桐 | E36: 116713488 | F36: 程远 | G36: 2025-06-30 11:16:41 | H36: 李文萱+liwenxuan3@xdf.cn+国际教育培训事业部-国际教育北京中心-运营管理部-运营中心-魏公村分中心，徐健坤； | J36: 大三 | K36: 徐健坤 | L36: 转介绍 | M36: 内部员工推荐 | N36: 李文萱+liwenxuan3@xdf.cn+国际教育培训事业部-国际教育北京中心-运营管理部-运营中心-魏公村分中心 | Q36: 陈晨 | R36: 徐健坤 | S36: 28731103 | T36: 正常工单 | U36: 2025-06-30 23:20 | V36: A（六个月内有报课意向工单） | W36: 四级 | X36: 大二 | Y36: 淮北师范大学 | Z36: 数学科学学院 | AA36: 数学与应用数学（师范） | AB36: 陈晨 | AC36: 5436483 | AD36: 徐健坤 | AE36: 2025-07-02 22:46 | AF36: 徐健坤 | AG36: 2025-07-06 10:13 | AH36: WYSJ25033 | AI36: 六级无忧计划 | AJ36: 国内考试 | AL36: 2840 | AN36: 李文萱+liwenxuan3@xdf.cn+国际教育培训事业部-国际教育北京中心-运营管理部-运营中心-魏公村分中心 | AO36: 新签 | AP36: 已交接 | AQ36: BJWY2101498uW2 | AR36: BJWY2672207145 | AS36: WYSJ250330042 | AT36: 2025-07-02 | AV36: 回访人：徐健坤，回访时间：2025-06-30 23:20，回访内容：基础不好 自制性一般 家长想让孩子稳妥的通过四级 明后天决定；|回访人：徐健坤，回访时间：2025-07-02 22:46，回访内容：签约 | BA36: 80737003 | BB36: 否 | BC36: 25下考季 | BD36: 四级无忧计划 | BG36: 国内高校-双非 | BH36: 是 | BK36: 报名 | BM36: 外地人外地大学(常规) | BN36: 客服
A37: 53 | B37: 北京大学部 | C37: 国内大学部 | D37: 学生 | E37: 116951608 | F37: 乔文娇 | G37: 2025-07-01 12:44:31 | H37: 新大一，大学预科 | J37: 大一 | K37: 乔文娇 | L37: 电话 | M37: 大客服呼入 | O37: 乔文娇 | P37: 2025-07-01 13:06:20 | Q37: 程笑飞 | R37: 黄智超 | S37: 28745890 | T37: 续费工单 | U37: 2025-07-01 14:30 | V37: A（六个月内有报课意向工单） | W37: 四级,大学预科 | X37: 大一 | Y37: 新大一 | Z37: 新大一 | AA37: 新大一 | AB37: 程笑飞 | AC37: 5435125 | AD37: 黄智超 | AE37: 2025-07-01 23:06 | AF37: 黄智超 | AG37: 2025-07-08 19:12 | AH37: YKS25001 | AI37: 六级无忧计划（新大一专属） | AJ37: 国内考试 | AL37: 4934.3 | AO37: 新签 | AP37: 已交接 | AQ37: WebReg | AR37: BJWY1951479294 | AS37: YKS250010015 | AT37: 2025-07-01 | AV37: 回访人：黄智超，回访时间：2025-07-01 14:30，回访内容：学生需求微信联系 已经添加 并且发送具体的课程安排 学生详细看一下 ；|回访人：黄智超，回访时间：2025-07-01 23:06，回访内容：签约 大学预科六级2班+口语 | BA37: 80863336 | BB37: 否 | BC37: 25下考季 | BD37: 四级无忧计划 | BG37: 普通学校-普高 | BH37: 是 | BI37: YKS25001需要转班至YKS25002（大预六级二班，辛苦老师留意） | BK37: 报名 | BM37: 本地人本地大学(常规) | BN37: 客服
A38: 54 | B38: 北京大学部 | C38: 国内大学部 | D38: 学生 | E38: 116951608 | F38: 乔文娇 | G38: 2025-07-01 12:44:31 | H38: 新大一，大学预科 | J38: 大一 | K38: 乔文娇 | L38: 电话 | M38: 大客服呼入 | O38: 乔文娇 | P38: 2025-07-01 13:06:20 | Q38: 程笑飞 | R38: 黄智超 | S38: 28745890 | T38: 续费工单 | U38: 2025-07-01 14:30 | V38: A（六个月内有报课意向工单） | W38: 四级,大学预科 | X38: 大一 | Y38: 新大一 | Z38: 新大一 | AA38: 新大一 | AB38: 程笑飞 | AC38: 5435125 | AD38: 黄智超 | AE38: 2025-07-01 23:06 | AF38: 黄智超 | AG38: 2025-07-08 19:12 | AH38: YK25001 | AI38: 大学口语特训营 | AJ38: 国内考试 | AL38: 4525.7 | AO38: 新签 | AP38: 已交接 | AQ38: WebReg | AR38: BJWY1951479294 | AS38: YK250010016 | AT38: 2025-07-01 | AV38: 回访人：黄智超，回访时间：2025-07-01 14:30，回访内容：学生需求微信联系 已经添加 并且发送具体的课程安排 学生详细看一下 ；|回访人：黄智超，回访时间：2025-07-01 23:06，回访内容：签约 大学预科六级2班+口语 | BA38: 80863336 | BB38: 否 | BC38: 25下考季 | BD38: 四级无忧计划 | BG38: 普通学校-普高 | BH38: 是 | BI38: YKS25001需要转班至YKS25002（大预六级二班，辛苦老师留意） | BK38: 报名 | BM38: 本地人本地大学(常规) | BN38: 客服
A39: 57 | B39: 北京大学部 | C39: 国内大学部 | D39: 未知 | E39: 120770627 | F39: 李雪68 | G39: 2025-07-25 17:32:52 | H39: 激活 | J39: 大三 | K39: 刘晓娟 | L39: 毛坯数据 | M39: 毛坯数据 | Q39: 尚家伟1 | R39: 刘晓娟 | S39: 29323001 | T39: 正常工单 | U39: 2025-07-25 17:36 | V39: A（六个月内有报课意向工单） | W39: 专升本 | X39: 大三 | Y39: 北京农学院 | Z39: 食品科学与工程学院 | AA39: 食品科学与工程 | AB39: 尚家伟1 | AC39: 5493522 | AD39: 刘晓娟 | AE39: 2025-07-25 17:36 | AF39: 刘晓娟 | AG39: 2025-07-25 17:36 | AH39: 79186518410 | AI39: 26通用专升本慧学班-英语 | AJ39: 国内考试 | AL39: 1999 | AO39: 新签 | AP39: 未交接 | AT39: 2025-07-25 | AV39: 回访人：刘晓娟，回访时间：2025-07-25 17:36，回访内容：专升本，班课，报名 | AZ39: 长期班 | BA39: 44682323 | BB39: 是 | BC39: 26考季 | BD39: 专升本全科全程班 | BE39: 英语 | BG39: 国内高校-双非 | BH39: 否 | BL39: 110598783 | BM39: 本地人本地大学(常规) | BN39: 客服
A40: 58 | B40: 北京大学部 | C40: 国内大学部 | D40: 王若维 | E40: 119242626 | F40: 吴凯龙 | G40: 2025-07-15 18:18:17 | H40: 辛苦老师分配给顾问寇源；销售主管分配TMK主管 外呼主题：国内大学部死单2024-10-25（TMK主管分配TMK） | J40: 大二 | K40: 吴凯龙 | L40: 毛坯数据 | M40: 毛坯数据 | O40: 吴凯龙 | P40: 2025-07-15 18:19:27 | Q40: 王若维 | R40: 刘晓娟 | S40: 29000468 | T40: 续费工单 | U40: 2025-07-15 18:21 | V40: A（六个月内有报课意向工单） | W40: 四级 | X40: 大二 | Y40: 北京信息科技大学 | Z40: 经济管理学院 | AA40: 财务管理 | AB40: 王若维 | AC40: 5414357 | AD40: 刘晓娟 | AE40: 2025-07-15 18:21 | AF40: 刘晓娟 | AG40: 2025-07-16 10:20 | AH40: WYF25035 | AI40: 取消四级无忧计划 | AJ40: 国内考试 | AL40: 0 | AM40: 同科续费 | AO40: 续班 | AP40: 未交接 | AQ40: BJWY25030q8UPI | AR40: XDF072231222318376 | AS40: WYF250350004 | AT40: 2025-07-15 | AV40: 回访人：刘晓娟，回访时间：2025-07-15 18:21，回访内容：转班 | BA40: 60212805 | BB40: 否 | BC40: 25上考季 | BD40: 四级无忧计划 | BG40: 国内高校-双非 | BH40: 否 | BK40: 转出 | BM40: 本地人本地大学(常规) | BO40: 作废，代办，不算进账和退费 | BP40: 5180.00
A41: 59 | B41: 北京大学部 | C41: 国内大学部 | E41: 118539803 | G41: 2025-07-10 13:20:09 | H41: 黄智超1的顾问转介绍工单 | J41: 大一 | K41: 黄智超 | L41: 转介绍 | M41: 顾问转介绍-老带新 | Q41: 王祎 | R41: 黄智超 | S41: 29170004 | T41: 续费工单 | U41: 2025-07-21 13:44 | V41: A（六个月内有报课意向工单） | W41: 四级,大学预科 | X41: 大一 | Y41: 北京第一六六中学（166中学） | Z41: 询问院系未告知 | AA41: 询问专业未告知 | AB41: 王祎 | AC41: 5487156 | AD41: 黄智超 | AE41: 2025-07-21 13:45 | AF41: 黄智超 | AG41: 2025-07-21 13:46 | AH41: YKFJ25001 | AI41: 四级无忧计划（线上优享/新大一专属） | AJ41: 国内考试 | AL41: 5434.4 | AM41: 同科续费 | AN41: 邵嘉凡 | AO41: 续班 | AP41: 未交接 | AQ41: BJWY25030q8UPI | AR41: BJWY1508600205 | AS41: YKFJ250010055 | AT41: 2025-07-12 | AV41: 回访人：黄智超，回访时间：2025-07-21 13:44，回访内容：转班；|回访人：黄智超，回访时间：2025-07-21 13:45，回访内容：转班 | BA41: 81453845 | BB41: 否 | BC41: 25下考季 | BD41: 四级无忧计划 | BG41: 普通学校-普高 | BH41: 否 | BK41: 转出 | BM41: 本地人本地大学(常规)
A42: 60 | B42: 北京大学部 | C42: 国内大学部 | D42: 北京市1457 | E42: 113502768 | F42: 杨俊42(国内) | G42: 2025-06-10 08:13:49 | H42: 渠道录入来源：新东方官网M站-客服 意向城市：北京访客省/城市：北京市 访客静态ID：01000000034659951423418074421457 接待分组ID：70455 搜索引擎： 搜索词： 关键词： 设备类型：phone 访客IP：123.112.121.231 对话详细内容：AI-Lbo0rDBXCyBY 2025-06-10 08:10:35_x000D_ 您好同学,欢迎访问北京新东方考研四六级中心. 考研线下课程26/27考季【考研全年集训营】【考研半年集训营】【考研全科线下走读班】【考研寒/暑假集训营】【考研一对一】【考研专业课】【四/六级课程】，热门课程火热报名中,咨询即可领取专享优惠。 **【考研全年集训营】=ff761f# **【考研半年集训营】=ff6b6b# **【考研全科线下走读班】=ffc158# **【考研寒/暑假集训营】=ffc158# **【考研一对一】=ff761f# **【考研专业课】=ff6caa# **【四/六级课程】=ff6caa# **【考研复试】=60e27e#_x000D_ _x000D_ AI-Lbo0rDBXCyBY 2025-06-10 08:10:38_x000D_ 您是想咨询【线下课程】【线上课程】【考研规划】还是【在职考研】呢？**【线下课程】# **【线上课程】#**【考研规划】#**【在职考研】#_x000D_ _x000D_ 01000000034659951423418074421457 2025-06-10 08:10:41_x000D_ 【线下课程】_x000D_ _x000D_ AI-Lbo0rDBXCyBY 2025-06-10 08:10:45_x000D_ 同学，你现在是在校还是在职呢？_x000D_ _x000D_ 01000000034659951423418074421457 2025-06-10 08:11:02_x000D_ 在校 想学专升本英语_x000D_ _x000D_ AI-Lbo0rDBXCyBY 2025-06-10 08:11:06_x000D_ 具体是想报考什么学校和专业呢？_x000D_ _x000D_ 01000000034659951423418074421457 2025-06-10 08:11:27_x000D_ 北京农学院食品质量与安全专业_x000D_ _x000D_ AI-Lbo0rDBXCyBY 2025-06-10 08:11:30_x000D_ 好的，我这边安排专业老师给您回电，详细沟通一下，请问您的电话是多少呢？_x000D_ _x000D_ 01000000034659951423418074421457 2025-06-10 08:11:46_x000D_ 13011261885_x000D_ _x000D_ AI-Lbo0rDBXCyBY 2025-06-10 08:11:49_x000D_ 好的，确认一下你的号码是否正确呢~_x000D_ _x000D_ 01000000034659951423418074421457 2025-06-10 08:12:00_x000D_ 正确_x000D_ _x000D_ AI-Lbo0rDBXCyBY 2025-06-10 08:12:03_x000D_ 同学怎么称呼呢？_x000D_ _x000D_ 01000000034659951423418074421457 2025-06-10 08:12:30_x000D_ 刘彬_x000D_ _x000D_ AI-Lbo0rDBXCyBY 2025-06-10 08:12:33_x000D_ 好的，由于今天课程规划老师还没有上班，这边安排老师上午9点后给您回电请注意接听~_x000D_ _x000D_ 来源页：https://click.xdf.cn/ 备注： | I42: 2026财年第1财月易聊新东方官网M站 | K42: 徐利霞 | L42: 新东方官网 | M42: 新东方官网M站 | O42: 徐利霞 | P42: 2025-06-10 09:24:53 | Q42: 刘彬 | R42: 刘晓娟 | S42: 28254065 | T42: 正常工单 | U42: 2025-06-10 11:00 | V42: A（六个月内有报课意向工单） | W42: 专升本 | X42: 大二 | Y42: 北京农业职业学院 | Z42: 食品质量与安全专业 | AA42: 食品质量与安全专业 | AB42: 刘彬 | AC42: 5475972 | AD42: 刘晓娟 | AE42: 2025-07-11 13:57 | AH42: 22933283430 | AI42: 26通用专升本慧学班-英语 | AL42: 1999 | AO42: 新签 | AP42: 未交接 | AT42: 2025-07-11 | AV42: 回访人：刘晓娟，回访时间：2025-07-03 15:05，回访内容：微信没回复，电话联系，无人；|回访人：刘晓娟，回访时间：2025-07-04 18:35，回访内容：报线上课程，这几周报，等优惠有了通知学员；|回访人：刘晓娟，回访时间：2025-07-11 11:24，回访内容：发了订单信息，等下午缴费 | AZ42: 长期班 | BA42: 79375909 | BB42: 是 | BC42: 26考季 | BD42: 专升本全科全程班,专升本VIP | BE42: 英语 | BG42: 国内高校-大专 | BH42: 否 | BL42: 110520369 | BM42: 本地人本地大学(常规) | BN42: 易聊在线咨询
A43: 61 | B43: 北京大学部 | C43: 国内大学部 | D43: 佟浩然 | E43: 114407277 | F43: 北京国内管理员 | G43: 2025-06-15 22:02:15 | H43: 资源录入来源：小表单 城市：北京市 市场活动id：412422 市场活动名称：新东方集团官微【新东方】资源 活动所属学校id：10000 活动所属学校名称：总公司 线索接收人邮箱：yangjun42@xdf.cn 线索接受人类型：自定义 表单信息：表单id81512、表单名(对内)：新东方集团官微【新东方】资源、表单名（对外）：新东方课程报名、创建人邮箱：wuyue38@xdf.cn、表单链接：pages/index/index.html?scene=81512,,Lh8FwYc8 备注：来源:小表单;姓名:佟浩然;意向课程: 【课程】考研、四六级、专升本、成人英语/北京/北京; 新老生: 新生; 提交链接:pages/index/index.html?scene=81512,,Lh8FwYc8;地理位置:北京市海淀区西北旺镇土井社区居委会图景嘉园;渠道:新媒体运营/公众号-品牌号 | I43: 2026财年小表单-新东方集团官微【新东方】资源 | J43: 未知 | K43: 徐树萌 | L43: 线上运营-私域中台 | M43: 公众号 | O43: 徐树萌 | P43: 2025-06-16 20:07:33 | Q43: 佟浩然 | R43: 张博奥 | S43: 28387693 | T43: 正常工单 | U43: 2025-06-16 20:55 | V43: A（六个月内有报课意向工单） | W43: 专升本 | X43: 高三 | Y43: 北京经济管理职业学院 | Z43: 外语与学前教育学院 | AA43: 教育学 | AB43: 佟浩然 | AC43: 5528516 | AD43: 张博奥 | AE43: 2025-07-31 23:11 | AF43: 张博奥 | AG43: 2025-07-31 23:25 | AH43: LP17539747023577 | AI43: 四级一对一畅学班（80H） | AJ43: 国内考试 | AL43: 51500 | AO43: 新签 | AP43: 已交接 | AR43: BJWY5130807562 | AT43: 2025-07-31 | AV43: 回访人：张博奥，回访时间：2025-07-24 22:19，回访内容：对老师没有任何问题，但是最近不在家，暂时无法报名，持续跟进；|回访人：张博奥，回访时间：2025-07-30 19:41，回访内容：需要逼单，孩子九月份的周六周日进行排课，加紧跟进；|回访人：张博奥，回访时间：2025-07-31 18:44，回访内容：给同学提前拉进了群，老师给学生进行一些简单的了解，逼单 | BA43: 79691041 | BB43: 否 | BC43: 26考季 | BD43: 专升本VIP | BE43: 英语 | BG43: 国内高校-大专 | BH43: 是 | BI43: 请学管老师尽快联系 | BN43: 小表单
A44: 62 | B44: 北京大学部 | C44: 国内大学部 | D44: 无 | E44: 116158765 | F44: 程远 | G44: 2025-06-25 15:13:35 | H44: 袁琳+yuanlin9@xdf.cn+157118+培训学校-北京学校-高中一对一部-西北区-远大路分中心，黄智超； | J44: 未知 | K44: 黄智超 | L44: 转介绍 | M44: 内部员工推荐 | N44: 袁琳+yuanlin9@xdf.cn+157118+培训学校-北京学校-高中一对一部-西北区-远大路分中心 | Q44: 项佳琳 | R44: 黄智超 | S44: 28593829 | T44: 正常工单 | U44: 2025-06-25 15:25 | V44: A（六个月内有报课意向工单） | W44: 四级,大学预科 | X44: 高三 | Y44: 北京市第六十六中学（66中） | Z44: 新大一 | AA44: 新大一 | AB44: 项佳琳 | AC44: 5527927 | AD44: 黄智超 | AE44: 2025-07-31 18:46 | AF44: 黄智超 | AG44: 2025-07-31 18:46 | AH44: YKF25007 | AI44: 四级无忧计划 | AJ44: 国内考试 | AL44: 5180 | AN44: 袁琳+yuanlin9@xdf.cn+157118+培训学校-北京学校-高中一对一部-西北区-远大路分中心 | AO44: 新签 | AP44: 已交接 | AQ44: BJWY2101498uW2 | AR44: BJWY8032747610 | AS44: YKF250070039 | AT44: 2025-07-31 | AV44: 回访人：黄智超，回访时间：2025-07-27 17:21，回访内容：发送详细课程介绍 推进8.4课程报名～；|回访人：黄智超，回访时间：2025-07-31 18:46，回访内容：已签约 预科四级大班 知春路校区～ | BA44: 74470622 | BB44: 否 | BC44: 25下考季 | BD44: 四级无忧计划 | BG44: 普通学校-普高 | BH44: 是 | BK44: 报名 | BN44: 客服
A45: 63 | B45: 北京大学部 | C45: 国内大学部 | D45: 任倬君 | E45: 116622240 | F45: 北京国内管理员 | G45: 2025-06-29 15:56:54 | H45: 渠道录入来源：SCRM-客服推送 商机ID：5009167718 商机编码：XSJ20250629030634 针对人群：高中 学员号：BJ2564215 学生学校：不详 咨询课程：英语 创建人邮箱：liuxinyi91@xdf.cn 创建时间：2025-06-29 15:56:47 资源类型：单个资源 跟进记录：商机备注：孩子妈妈来电，孩子新大一，想提前学习四六级，为12月份考试做准备，辛苦顾问老师联系;接触点：呼入； | J45: 高三 | K45: 张博奥 | L45: 线上运营-本地生活平台 | M45: 阿里本地通 | Q45: 任倬君 | R45: 张博奥 | S45: 28717077 | T45: 正常工单 | U45: 2025-06-29 16:32 | V45: A（六个月内有报课意向工单） | W45: 六级,大学预科 | X45: 高三 | Y45: 首都医科大学 | Z45: 临床医学院 | AA45: 临床医学 | AB45: 任倬君 | AC45: 5527835 | AD45: 张博奥 | AE45: 2025-07-31 18:10 | AF45: 张博奥 | AG45: 2025-07-31 18:11 | AH45: YKS25003 | AI45: 六级无忧计划（新大一专属） | AJ45: 国内考试 | AL45: 5180 | AO45: 新签 | AP45: 已交接 | AQ45: BJWY2101498uW2 | AR45: BJWY4295783617 | AS45: YKS250030040 | AT45: 2025-07-31 | AV45: 回访人：张博奥，回访时间：2025-07-24 21:28，回访内容：昨天微信触达微信未回，今日邀约讲座依然未回；|回访人：张博奥，回访时间：2025-07-31 18:08，回访内容：家长约7.31到校区参观签约；|回访人：张博奥，回访时间：2025-07-31 18:10，回访内容：已报名 | BA45: 56607822 | BB45: 否 | BC45: 25下考季 | BG45: 国内高校-双非 | BH45: 是 | BI45: 请学管老师尽快联系并发送导学课 | BK45: 报名 | BN45: SCRM-客服推送
A46: 64 | B46: 北京大学部 | C46: 国内大学部 | D46: 李佳羲 | E46: 121569567 | F46: 李玉迪 | G46: 2025-07-31 10:52:46 | H46: 续费原因：续费；该学生为保护期内续费，原顾问：国内大学部-田一禾(tianyihe3@xdf.cn) | J46: 大一 | K46: 田一禾 | L46: 转介绍 | M46: 学管续费推荐 | N46: 李玉迪liyudi1@xdf.cn | Q46: 李佳羲 | R46: 田一禾 | S46: 29356615 | T46: 续费工单 | U46: 2025-07-31 17:28 | V46: A（六个月内有报课意向工单） | W46: 四级,大学预科 | X46: 大一 | Y46: 北京城市学院 | Z46: 信息学部 | AA46: 数据科学与大数据技术 | AB46: 李佳羲 | AC46: 5527727 | AD46: 田一禾 | AE46: 2025-07-31 17:34 | AF46: 田一禾 | AG46: 2025-07-31 17:35 | AH46: YKM25002 | AI46: 大学预科数学（新大一专属） | AJ46: 国内考试 | AL46: 4480 | AM46: 同科续费 | AN46: 李玉迪 | AO46: 续班 | AP46: 已交接 | AQ46: BJWY22035556hl | AR46: BJWY8658744284 | AS46: YKM250020050 | AT46: 2025-07-31 | AV46: 回访人：田一禾，回访时间：2025-07-31 17:28，回访内容：续费数学。保证原渠道；|回访人：田一禾，回访时间：2025-07-31 17:34，回访内容：j | BA46: 74852982 | BB46: 否 | BC46: 25下考季 | BD46: 四级无忧计划,大学数学预科 | BG46: 国内高校-双非 | BH46: 是 | BK46: 追加优惠 | BM46: 本地人本地大学(常规) | BN46: 学管续费推荐
A47: 65 | B47: 北京大学部 | C47: 国内大学部 | D47: 石家庄市5057 | E47: 121496375 | F47: 杨俊42(国内) | G47: 2025-07-30 20:44:24 | H47: 渠道录入来源：新东方官网M站-客服 意向城市：北京访客省/城市：石家庄市 访客静态ID：01000000034659387924057130055057 接待分组ID：70455 搜索引擎： 搜索词： 关键词： 设备类型：phone 访客IP：111.55.24.68 对话详细内容：AI-Lbo0rDBXCyBY 2025-07-30 20:40:45_x000D_ 您好同学,欢迎访问北京新东方考研四六级中心. 考研线下课程26/27考季【考研全年集训营】【考研半年集训营】【考研全科线下走读班】【考研寒/暑假集训营】【考研一对一】【考研专业课】【四/六级课程】，热门课程火热报名中,咨询即可领取专享优惠。 **【考研全年集训营】=ff761f# **【考研半年集训营】=ff6b6b# **【考研全科线下走读班】=ffc158# **【考研寒/暑假集训营】=ffc158# **【考研一对一】=ff761f# **【考研专业课】=ff6caa# **【四/六级课程】=ff6caa# **【考研冲刺班】=60e27e#_x000D_ _x000D_ AI-Lbo0rDBXCyBY 2025-07-30 20:40:47_x000D_ 您是想咨询【线下课程】【线上课程】【考研规划】还是【在职考研】呢？**【线下课程】# **【线上课程】#**【考研规划】#**【在职考研】#_x000D_ _x000D_ 01000000034659387924057130055057 2025-07-30 20:41:00_x000D_ 【四/六级课程】_x000D_ _x000D_ AI-Lbo0rDBXCyBY 2025-07-30 20:41:03_x000D_ 您目前在学的院校是哪所呢？_x000D_ _x000D_ 01000000034659387924057130055057 2025-07-30 20:41:34_x000D_ 石家庄市17中，高考结束了，想让孩子升入大学后过4，6级_x000D_ _x000D_ AI-Lbo0rDBXCyBY 2025-07-30 20:41:38_x000D_ 您目前英语基础如何呢？_x000D_ _x000D_ 01000000034659387924057130055057 2025-07-30 20:41:53_x000D_ 目前英语能考100分左右_x000D_ _x000D_ AI-Lbo0rDBXCyBY 2025-07-30 20:41:57_x000D_ 这样，您微信还是电话方便呢？我安排四六级老师联系您，将课程的详细内容介绍给您_x000D_ _x000D_ 01000000034659387924057130055057 2025-07-30 20:42:23_x000D_ 电话吧，13831145946_x000D_ _x000D_ AI-Lbo0rDBXCyBY 2025-07-30 20:42:27_x000D_ 好的，确认一下你的号码是否正确呢~_x000D_ _x000D_ 01000000034659387924057130055057 2025-07-30 20:42:40_x000D_ 正确_x000D_ _x000D_ AI-Lbo0rDBXCyBY 2025-07-30 20:42:43_x000D_ 同学怎么称呼呢？_x000D_ _x000D_ 01000000034659387924057130055057 2025-07-30 20:42:58_x000D_ 孟令坤家长_x000D_ _x000D_ AI-Lbo0rDBXCyBY 2025-07-30 20:43:02_x000D_ 这边马上安排顾问老师联系您，预计半个小时左右给您回电请注意接听~_x000D_ _x000D_ 01000000034659387924057130055057 2025-07-30 20:43:14_x000D_ 好的，谢谢_x000D_ _x000D_ AI-Lbo0rDBXCyBY 2025-07-30 20:43:18_x000D_ 好的，这个也是您的微信号吗？_x000D_ _x000D_ 01000000034659387924057130055057 2025-07-30 20:43:29_x000D_ 是的_x000D_ _x000D_ AI-Lbo0rDBXCyBY 2025-07-30 20:43:32_x000D_ 稍后老师会联系哈_x000D_ _x000D_ 来源页：https://bj.xdf.cn/ 备注： | I47: 2026财年第2财月易聊新东方官网M站 | K47: 杨欢欢 | L47: 新东方官网 | M47: 新东方官网M站 | O47: 杨欢欢 | P47: 2025-07-31 10:30:33 | Q47: 孟令坤 | R47: 房国超 | S47: 29437786 | T47: 正常工单 | U47: 2025-07-31 15:39 | V47: A（六个月内有报课意向工单） | W47: 四级,大学预科 | X47: 高三 | Y47: 新大一 | Z47: 新大一 | AA47: 新大一 | AB47: 孟令坤 | AC47: 5527621 | AD47: 房国超 | AE47: 2025-07-31 16:59 | AF47: 房国超 | AG47: 2025-07-31 17:00 | AH47: YKFJ25001 | AI47: 四级无忧计划（线上优享/新大一专属） | AJ47: 国内考试 | AL47: 5680 | AO47: 新签 | AP47: 已交接 | AQ47: WebReg | AR47: XDF012315124129087 | AS47: YKFJ250010102 | AT47: 2025-07-31 | AV47: 回访人：房国超，回访时间：2025-07-31 15:39，回访内容：家长咨询，英语100左右， 理科， 想让孩子学英语， 微信详聊；|回访人：房国超，回访时间：2025-07-31 16:59，回访内容：报名 | BA47: 82692576 | BB47: 否 | BC47: 25下考季 | BD47: 四级无忧计划 | BG47: 普通学校-普高 | BH47: 是 | BK47: 报名 | BM47: 外地人外地大学(常规) | BN47: 易聊在线咨询
A48: 66 | B48: 北京大学部 | C48: 国内大学部 | D48: 聂一诺 | E48: 117807189 | F48: 北京国内管理员 | G48: 2025-07-06 13:20:12 | H48: 渠道录入来源：SCRM-客服推送 商机ID：5009246009 商机编码：XSJ20250706016277 针对人群：大学 学员号：BJ1683879 学生学校：不详 咨询课程：英语 创建人邮箱：wangyue328@xdf.cn 创建时间：2025-07-06 13:20:07 资源类型：单个资源 跟进记录：商机备注：妈妈来电，新大一，咨询四六级课程，辛苦老师联系介绍;接触点：呼入； | J48: 大一 | K48: 刘晓娟 | L48: 新东方官网 | M48: 新东方PC官网 | Q48: 聂一诺 | R48: 刘晓娟 | S48: 28878006 | T48: 正常工单 | U48: 2025-07-06 13:58 | V48: A（六个月内有报课意向工单） | W48: 四级,大学预科 | X48: 高三 | Y48: 丰台区左安门中学 | Z48: 新大一 | AA48: 新大一 | AB48: 聂一诺 | AC48: 5527608 | AD48: 刘晓娟 | AE48: 2025-07-31 16:55 | AF48: 刘晓娟 | AG48: 2025-07-31 16:55 | AH48: YKF25007 | AI48: 四级无忧计划 | AJ48: 国内考试 | AL48: 5180 | AO48: 新签 | AP48: 已交接 | AQ48: BJWY2101498uW2 | AR48: BJWY9725405485 | AS48: YKF250070042 | AT48: 2025-07-31 | AV48: 回访人：刘晓娟，回访时间：2025-07-23 15:09，回访内容：微信留言，再次确认意向；|回访人：刘晓娟，回访时间：2025-07-29 14:42，回访内容：家长是没问题，孩子说要再考虑下再说；|回访人：刘晓娟，回访时间：2025-07-31 16:55，回访内容：报名 | BA48: 74521335 | BB48: 否 | BC48: 25下考季 | BD48: 四级无忧计划 | BG48: 普通学校-普高 | BH48: 是 | BK48: 报名 | BM48: 本地人本地大学(常规) | BN48: SCRM-客服推送
A49: 67 | B49: 北京大学部 | C49: 国内大学部 | D49: 张安琪 | E49: 120898162 | F49: 段同飞 | G49: 2025-07-27 09:10:41 | H49: 内推给黄智超 | J49: 大一 | K49: 黄智超 | L49: 转介绍 | M49: 内部员工推荐 | N49: 宋彬霞+songbinxia@xdf.cn+355911+培训学校-北京学校-高中一对一部-增长中心-升学规划组+升学规划师 | Q49: 张安琪 | R49: 黄智超 | S49: 29333010 | T49: 正常工单 | U49: 2025-07-27 09:16 | V49: A（六个月内有报课意向工单） | W49: 四级,大学预科 | X49: 大一 | Y49: 首都师范大学 | Z49: 外国语学院 | AA49: 英语 | AB49: 张安琪 | AC49: 5527334 | AD49: 黄智超 | AE49: 2025-07-31 15:19 | AF49: 黄智超 | AG49: 2025-07-31 15:19 | AH49: YKF25007 | AI49: 四级无忧计划 | AJ49: 国内考试 | AL49: 5680 | AN49: 宋彬霞+songbinxia@xdf.cn+355911+培训学校-北京学校-高中一对一部-增长中心-升学规划组+升学规划师 | AO49: 新签 | AP49: 已交接 | AQ49: WebReg | AR49: BJWY5502112811 | AS49: YKF250070037 | AT49: 2025-07-31 | AV49: 回访人：黄智超，回访时间：2025-07-27 09:16，回访内容：家长主要咨询4级课程的整体安排，大班小班的介绍了，目前还没有确定报名的意向。；|回访人：黄智超，回访时间：2025-07-29 14:35，回访内容：告知课程安排 等待家长确定报名哪个～；|回访人：黄智超，回访时间：2025-07-31 15:19，回访内容：签约 5680 8.4开课四级大班 | BA49: 74641699 | BB49: 否 | BC49: 25下考季 | BD49: 四级无忧计划 | BG49: 国内高校-中外合作办学 | BH49: 是 | BK49: 报名 | BM49: 本地人本地大学(常规) | BN49: 客服
A50: 68 | B50: 北京大学部 | C50: 国内大学部 | D50: 同学 | E50: 121624375 | F50: 吴凯龙 | G50: 2025-07-31 12:59:20 | H50: 死单一个月，原渠道激活刘晓娟 | J50: 大二 | K50: 刘晓娟 | L50: 线上运营-小红书 | M50: 小红书 | Q50: 姬月 | R50: 刘晓娟 | S50: 29435978 | T50: 正常工单 | U50: 2025-07-31 13:01 | V50: A（六个月内有报课意向工单） | W50: 四级,大学预科 | X50: 高三 | Y50: 北京海淀凯文学校 | Z50: 新大一 | AA50: 新大一 | AB50: 姬月 | AC50: 5527219 | AD50: 刘晓娟 | AE50: 2025-07-31 14:32 | AF50: 刘晓娟 | AG50: 2025-07-31 14:34 | AH50: YKF25007 | AI50: 四级无忧计划 | AJ50: 国内考试 | AL50: 4784 | AO50: 新签 | AP50: 已交接 | AQ50: WebReg | AR50: BJWY2402366756 | AS50: YKF250070036 | AT50: 2025-07-31 | AV50: 回访人：刘晓娟，回访时间：2025-07-31 13:01，回访内容：四级大班，8.4知春路的，报名，新大一的额，母亲咨询；|回访人：刘晓娟，回访时间：2025-07-31 14:32，回访内容：报名 | BA50: 74455703 | BB50: 否 | BC50: 25下考季 | BD50: 四级无忧计划 | BG50: 普通学校-普高 | BH50: 是 | BK50: 报名 | BM50: 本地人本地大学(常规) | BN50: 客服
A51: 69 | B51: 北京大学部 | C51: 国内大学部 | D51: 家长 | E51: 121415524 | F51: 吕猛 | G51: 2025-07-30 14:34:31 | H51: 咨询四级课程，已到花园桥楼下，辛苦分黄志超老师，占顺序 | J51: 未知 | K51: 黄智超 | L51: 线上运营-本地生活平台 | M51: 地图标点 | Q51: 姚俊毅 | R51: 黄智超 | S51: 29352165 | T51: 正常工单 | U51: 2025-07-30 15:01 | V51: A（六个月内有报课意向工单） | W51: 四级,大学预科 | X51: 大一 | Y51: 北京中医药大学 | Z51: 中药学院 | AA51: 中药制药 | AB51: 姚俊毅 | AC51: 5527090 | AD51: 黄智超 | AE51: 2025-07-31 13:24 | AF51: 黄智超 | AG51: 2025-07-31 13:40 | AH51: LP1753939481915 | AI51: 四级一对一畅学班（50H） | AJ51: 国内考试 | AL51: 37500 | AO51: 新签 | AP51: 已交接 | AR51: BJWY8577043608 | AT51: 2025-07-31 | AV51: 回访人：黄智超，回访时间：2025-07-30 15:01，回访内容：准备校区面访沟通～；|回访人：黄智超，回访时间：2025-07-30 19:19，回访内容：家长夫妻二人到场 咨询暑假四级课程 一对一 或者小班课 家长需要沟通孩子～；|回访人：黄智超，回访时间：2025-07-31 11:24，回访内容：想要花园桥校区一对一学习 看看有没有老师可以讲～ | BA51: 74518469 | BB51: 否 | BC51: 25下考季 | BD51: 四级无忧计划 | BG51: 国内高校-211 | BH51: 是 | BM51: 本地人本地大学(常规) | BN51: 市场
A52: 70 | B52: 北京大学部 | C52: 国内大学部 | E52: 118799662 | G52: 2025-07-12 17:25:29 | H52: 家长，孩子准大一，英语不好，想提前学习下四级辅导，现在方便回电；王女士 13910625162 北京海淀 英语四级 | J52: 大一 | K52: 李政(离职) | L52: 线上运营-商务合作 | M52: 百教网 | Q52: 李铭泽 | R52: 黄智超 | S52: 29441113 | T52: 续费工单 | U52: 2025-07-31 23:39 | V52: A（六个月内有报课意向工单） | W52: 四级,大学预科 | X52: 大一 | Y52: 北方工业大学 | Z52: 信息学院 | AA52: 电子信息工程 | AB52: 李铭泽 | AC52: 5500786 | AD52: 黄智超 | AE52: 2025-07-31 23:39 | AF52: 黄智超 | AG52: 2025-07-31 23:40 | AH52: YKF25003 | AI52: 四级无忧计划（新大一专属） | AJ52: 国内考试 | AL52: 5434.4 | AM52: 扩科续费 | AO52: 续班 | AP52: 已交接 | AQ52: BJWY2101498uW2 | AR52: BJWY2261657598 | AS52: YKF250030059 | AT52: 2025-07-31 | AV52: 回访人：黄智超，回访时间：2025-07-31 23:39，回访内容：联报；|回访人：黄智超，回访时间：2025-07-31 23:39，回访内容：联报高数英语 | BA52: 81606824 | BB52: 否 | BC52: 25下考季 | BD52: 四级无忧计划 | BG52: 普通学校-普高 | BH52: 否 | BK52: 追加优惠 | BM52: 本地人本地大学(常规)
A53: 71 | B53: 北京大学部 | C53: 国内大学部 | D53: 吴昀阳同学 | E53: 121627016 | F53: 吴凯龙 | G53: 2025-07-31 13:52:23 | H53: 黄智超1的内部员工推荐工单 | J53: 大一 | K53: 黄智超 | L53: 转介绍 | M53: 内部员工推荐 | N53: 袁琳+yuanlin9@xdf.cn+培训学校-北京学校-高中一对一部-增长中心-升学规划组+升学规划师 | Q53: 吴昀阳 | R53: 黄智超 | S53: 29457629 | T53: 正常工单 | U53: 2025-07-31 15:06 | V53: A（六个月内有报课意向工单） | W53: 四级,大学预科 | X53: 大一 | Y53: 新大一 | Z53: 新大一 | AA53: 新大一 | AB53: 吴昀阳 | AC53: 5500186 | AD53: 黄智超 | AE53: 2025-07-31 18:48 | AF53: 黄智超 | AG53: 2025-07-31 18:48 | AH53: YKF25007 | AI53: 四级无忧计划 | AJ53: 国内考试 | AL53: 5180 | AN53: 袁琳+yuanlin9@xdf.cn+培训学校-北京学校-高中一对一部-增长中心-升学规划组+升学规划师 | AO53: 新签 | AP53: 已交接 | AQ53: BJWY2101498uW2 | AR53: BJWY7375791672 | AS53: YKF250070041 | AT53: 2025-07-31 | AV53: 回访人：黄智超，回访时间：2025-07-31 15:06，回访内容：准备报名8.4开课的四级大班；|回访人：黄智超，回访时间：2025-07-31 18:48，回访内容：已签约 8.4 知春路四级大班～ | BA53: 74848961 | BB53: 否 | BC53: 25下考季 | BD53: 四级无忧计划 | BG53: 普通学校-普高 | BH53: 是 | BK53: 报名 | BM53: 本地人本地大学(常规) | BN53: 客服
A54: 72 | B54: 北京大学部 | C54: 国内大学部 | D54: 小红薯5C2E67D0 | E54: 120856318 | F54: 王朝群 | G54: 2025-07-26 20:25:07 | H54: 渠道录入来源：小红书 事件名称：私信留资 小红书账号id：656d6b0e000000003d02849b 小红书账号名称：北京新东方四六级咨询 广告投放账号名称：北京新东方四六级咨询 活动所属学校id：108 活动所属学校名称：北京大学事业部 统一活动id：2593748 统一活动名称：北京大学事业部25年7月小红书专业号投放 渠道名称：网络营销-小红书-专业号投放 线索创建人邮箱：wangchaoqun2@xdf.cn 资源跟进人邮箱：wangchaoqun2@xdf.cn 备注：用户地区是【北京市北京市】，在【2025-07-26 20:25:04】留资，私信通线索标签为【留客资】，来源于【北京新东方四六级咨询】投放账户，意向项目是【四六级】，留资笔记是【】，备注【-】 | I54: 2026财年第2财月小红书 | J54: 未知 | K54: 刘晓娟 | L54: 线上运营-小红书 | M54: 小红书 | Q54: 李奥燃 | R54: 刘晓娟 | S54: 29332136 | T54: 正常工单 | U54: 2025-07-26 20:40 | V54: A（六个月内有报课意向工单） | W54: 四级,大学预科 | X54: 高三 | Y54: 通州区甘棠中学 | Z54: 新大一 | AA54: 新大一 | AB54: 李奥燃 | AC54: 5500122 | AD54: 刘晓娟 | AE54: 2025-07-31 18:24 | AF54: 刘晓娟 | AG54: 2025-07-31 18:24 | AH54: YKF25007 | AI54: 四级无忧计划 | AJ54: 国内考试 | AL54: 5180 | AO54: 新签 | AP54: 已交接 | AQ54: BJWY22035556hl | AR54: BJWY2962161532 | AS54: YKF250070044 | AT54: 2025-07-31 | AV54: 回访人：刘晓娟，回访时间：2025-07-26 20:40，回访内容：孩子母亲咨询高考英语一百零几分新大一想了解4级线下的课程，介绍了大班和小班家长跟孩子商量一下。；|回访人：刘晓娟，回访时间：2025-07-27 10:24，回访内容：线上的课程价格是多少，可以看回放吗，介绍全款报名和插班报名；|回访人：刘晓娟，回访时间：2025-07-30 15:17，回访内容：线上的家长是担心连贯的，介绍了线下的课程，现在在海淀住，大概8月12以后要回房山，建议考虑线下班课，冲突的时间可以线上看，家长考虑下，也邀约讲座了；|回访人：刘晓娟，回访时间：2025-07-31 18:24，回访内容：报名 | BA54: 82386122 | BB54: 否 | BC54: 25下考季 | BD54: 四级无忧计划 | BG54: 普通学校-普高 | BH54: 是 | BK54: 报名 | BM54: 本地人本地大学(常规) | BN54: 小红书
A55: 73 | B55: 北京大学部 | C55: 国内大学部 | D55: 四级 | E55: 121332604 | F55: 王朝群 | G55: 2025-07-30 11:05:48 | H55: 【王朝群】咨询四六级暑期班，家长咨询 | J55: 大一 | K55: 田一禾 | L55: 线上运营-小红书 | M55: 小红书 | Q55: 孙毅 | R55: 田一禾 | S55: 29429578 | T55: 正常工单 | U55: 2025-07-30 15:01 | V55: B（需长时间跟单或只需要规划） | W55: 六级,大学预科 | X55: 高三 | Y55: 北京工业大学 | Z55: 信息学部 | AA55: 电子信息工程（实验班） | AB55: 孙毅 | AC55: 5500116 | AD55: 田一禾 | AE55: 2025-07-31 18:22 | AF55: 田一禾 | AG55: 2025-07-31 18:22 | AH55: YKS25003 | AI55: 六级无忧计划（新大一专属） | AJ55: 国内考试 | AL55: 5180 | AO55: 新签 | AP55: 已交接 | AQ55: BJWY2101498uW2 | AR55: BJWY7110352392 | AS55: YKS250030038 | AT55: 2025-07-31 | AV55: 回访人：田一禾，回访时间：2025-07-30 15:01，回访内容：想让孩子过来知春路？不知道具体的特点和打算，过来预计面谈？尚且不确定。；|回访人：田一禾，回访时间：2025-07-31 18:22，回访内容：今日签约 | BA55: 74505696 | BB55: 否 | BC55: 25下考季 | BD55: 六级无忧计划 | BG55: 国内高校-211 | BH55: 是 | BK55: 报名 | BM55: 本地人本地大学(常规) | BN55: 市场
A56: 74 | B56: 北京大学部 | C56: 国内大学部 | D56: 朱海平 | E56: 120061030 | F56: 曹伟杰2 | G56: 2025-07-22 13:55:36 | H56: 新大一家长咨询暑期四级班，问老生优惠 冯景丽+fengjingli@xdf.cn+ID+培训学校-北京学校-高中一对一部-西南区-公主坟分中心 | J56: 大一 | K56: 刘晓娟 | L56: 转介绍 | M56: 内部员工推荐 | N56: 冯景丽+fengjingli@xdf.cn+ID+培训学校-北京学校-高中一对一部-西南区-公主坟分中心 | Q56: 冯浩然 | R56: 刘晓娟 | S56: 29176207 | T56: 正常工单 | U56: 2025-07-23 08:47 | V56: A（六个月内有报课意向工单） | W56: 四级 | X56: 大三 | Y56: 北京城市学院 | Z56: 信息学部 | AA56: 计算机科学与技术 | AB56: 冯浩然 | AC56: 5499850 | AD56: 刘晓娟 | AE56: 2025-07-31 17:02 | AF56: 刘晓娟 | AG56: 2025-07-31 17:02 | AH56: YKF25007 | AI56: 四级无忧计划 | AJ56: 国内考试 | AL56: 5180 | AN56: 冯景丽+fengjingli@xdf.cn+ID+培训学校-北京学校-高中一对一部-西南区-公主坟分中心 | AO56: 新签 | AP56: 已交接 | AQ56: BJWY2101498uW2 | AR56: BJWY2373038150 | AS56: YKF250070038 | AT56: 2025-07-31 | AV56: 回访人：刘晓娟，回访时间：2025-07-23 08:47，回访内容：家长咨询嗯想要了解四六级的课程然后介绍了四六级的课程安排想要测试班课没有测试可以发套真题让孩子做一下；|回访人：刘晓娟，回访时间：2025-07-26 11:02，回访内容：微信留言，确认意向；|回访人：刘晓娟，回访时间：2025-07-30 16:12，回访内容：明天过来面谈，北京城市学院上学，开学大三，学的物联网，四级考了一次，没出成绩，规划考研；|回访人：刘晓娟，回访时间：2025-07-31 17:02，回访内容：报名 | BA56: 74689611 | BB56: 否 | BC56: 25下考季 | BD56: 四级无忧计划 | BG56: 国内高校-双非 | BH56: 是 | BK56: 报名 | BM56: 本地人本地大学(常规) | BN56: 市场
A57: 75 | B57: 北京大学部 | C57: 国内大学部 | D57: 家长 | E57: 121435223 | F57: 吕猛 | G57: 2025-07-31 09:42:51 | H57: 咨询四级课程 | J57: 大一 | K57: 房国超 | L57: 线上运营-本地生活平台 | M57: 地图标点 | Q57: 杨雨萱 | R57: 房国超 | S57: 29455702 | T57: 正常工单 | U57: 2025-07-31 12:02 | V57: A（六个月内有报课意向工单） | W57: 六级,大学预科 | X57: 高三 | Y57: 新大一 | Z57: 新大一 | AA57: 新大一 | AB57: 杨雨萱 | AC57: 5499845 | AD57: 房国超 | AE57: 2025-07-31 17:01 | AF57: 房国超 | AG57: 2025-07-31 17:01 | AH57: YKS25003 | AI57: 六级无忧计划（新大一专属） | AJ57: 国内考试 | AL57: 2440 | AO57: 新签 | AP57: 已交接 | AQ57: BJWY22035556hl | AR57: BJWY9252687850 | AS57: YKS250030039 | AT57: 2025-07-31 | AV57: 回访人：房国超，回访时间：2025-07-31 12:02，回访内容：家长咨询，新大一128，医学， 有保研规划， 推荐六级， 住德胜门附近，；|回访人：房国超，回访时间：2025-07-31 17:01，回访内容：报名 | BA57: 74486794 | BB57: 否 | BC57: 25下考季 | BD57: 六级无忧计划 | BG57: 普通学校-普高 | BH57: 是 | BK57: 报名 | BM57: 本地人本地大学(常规) | BN57: 市场
A58: 76 | B58: 北京大学部 | C58: 国内大学部 | D58: 高龄宝妈 | E58: 119969107 | F58: 王朝群 | G58: 2025-07-20 23:56:16 | H58: 【王朝群】咨询四六级暑期班 | I58: 2026财年第2财月小红书 | J58: 大二 | K58: 房国超 | L58: 线上运营-小红书 | M58: 小红书 | Q58: 刘睿 | R58: 房国超 | S58: 29249086 | T58: 正常工单 | U58: 2025-07-21 12:04 | V58: A（六个月内有报课意向工单） | W58: 四级,大学预科 | X58: 高三 | Y58: 新大一 | Z58: 新大一 | AA58: 新大一 | AB58: 刘睿 | AC58: 5499835 | AD58: 房国超 | AE58: 2025-07-31 16:58 | AF58: 房国超 | AG58: 2025-07-31 16:58 | AH58: YKF25007 | AI58: 四级无忧计划 | AJ58: 国内考试 | AL58: 4880 | AO58: 新签 | AP58: 已交接 | AQ58: BJWY22035556hl | AR58: BJWY3100093167 | AS58: YKF250070040 | AT58: 2025-07-31 | AV58: 回访人：房国超，回访时间：2025-07-23 17:32，回访内容：说孩子月底回来， 还没商量 ，微信未通过，邀约试听，没时间；|回访人：房国超，回访时间：2025-07-29 18:21，回访内容：4号知春路校区上课， 和孩子商量 ，4880， ；|回访人：房国超，回访时间：2025-07-31 16:58，回访内容：报名 | BA58: 56563249 | BB58: 否 | BC58: 25下考季 | BD58: 四级无忧计划 | BG58: 普通学校-普高 | BH58: 是 | BK58: 报名 | BM58: 本地人本地大学(常规) | BN58: 小红书
A59: 77 | B59: 北京大学部 | C59: 国内大学部 | D59: 同学 | E59: 121589041 | F59: 吴凯龙 | G59: 2025-07-31 13:54:04 | H59: 黄智超1的内部员工推荐工单 | J59: 大一 | K59: 黄智超 | L59: 转介绍 | M59: 内部员工推荐 | N59: 袁琳+yuanlin9@xdf.cn+培训学校-北京学校-高中一对一部-增长中心-升学规划组+升学规划师 | Q59: 季思铭 | R59: 黄智超 | S59: 29436378 | T59: 正常工单 | U59: 2025-07-31 13:57 | V59: A（六个月内有报课意向工单） | W59: 四级,大学预科 | X59: 大一 | Y59: 北京物资学院 | Z59: 信息学院 | AA59: 信息管理与信息系统 | AB59: 季思铭 | AC59: 5421636 | AD59: 黄智超 | AE59: 2025-07-31 18:50 | AF59: 黄智超 | AG59: 2025-07-31 18:51 | AH59: YKF25007 | AI59: 四级无忧计划 | AJ59: 国内考试 | AL59: 5180 | AN59: 袁琳+yuanlin9@xdf.cn+培训学校-北京学校-高中一对一部-增长中心-升学规划组+升学规划师 | AO59: 新签 | AP59: 已交接 | AQ59: BJWY22035556hl | AR59: BJWY8958262402 | AS59: YKF250070043 | AT59: 2025-07-31 | AV59: 回访人：黄智超，回访时间：2025-07-31 13:57，回访内容：预计报名8.4开课的四级大班；|回访人：黄智超，回访时间：2025-07-31 18:50，回访内容：签约 四级8.4开班课程 | BA59: 82788722 | BB59: 否 | BC59: 25下考季 | BD59: 四级无忧计划 | BG59: 国内高校-双非 | BH59: 是 | BK59: 报名 | BM59: 本地人本地大学(常规) | BN59: 客服
A60: 78 | B60: 北京大学部 | C60: 国内大学部 | D60: 北京市1110 | E60: 121034487 | F60: 杨俊42(国内) | G60: 2025-07-28 21:25:48 | H60: 渠道录入来源：新东方PC官网-客服 意向城市：北京访客省/城市：北京市 访客静态ID：01000000034659370892156192261110 接待分组ID：70447 搜索引擎： 搜索词： 关键词： 设备类型：pc 访客IP：120.244.179.93 对话详细内容：AI-Lbo0rDBXCyBY 2025-07-28 21:22:02_x000D_ 您好同学,欢迎访问北京新东方考研四六级中心. 考研线下课程26/27考季【考研全年集训营】【考研半年集训营】【考研全科线下走读班】【考研寒/暑假集训营】【考研一对一】【考研专业课】【四/六级课程】，热门课程火热报名中,咨询即可领取专享优惠。 **【考研全年集训营】=ff761f# **【考研半年集训营】=ff6b6b# **【考研全科线下走读班】=ffc158# **【考研寒/暑假集训营】=ffc158# **【考研一对一】=ff761f# **【考研专业课】=ff6caa# **【四/六级课程】=ff6caa# **【考研冲刺班】=60e27e#_x000D_ _x000D_ AI-Lbo0rDBXCyBY 2025-07-28 21:22:05_x000D_ 您是想咨询【线下课程】【线上课程】【考研规划】还是【在职考研】呢？**【线下课程】# **【线上课程】#**【考研规划】#**【在职考研】#_x000D_ _x000D_ 01000000034659370892156192261110 2025-07-28 21:22:39_x000D_ 【线上课程】_x000D_ _x000D_ AI-Lbo0rDBXCyBY 2025-07-28 21:22:42_x000D_ 同学，你现在是在校还是在职呢？_x000D_ _x000D_ 01000000034659370892156192261110 2025-07-28 21:22:55_x000D_ 四级考试_x000D_ _x000D_ AI-Lbo0rDBXCyBY 2025-07-28 21:22:59_x000D_ 您目前在学的院校是哪所呢？_x000D_ _x000D_ 01000000034659370892156192261110 2025-07-28 21:23:11_x000D_ 还没入学_x000D_ _x000D_ AI-Lbo0rDBXCyBY 2025-07-28 21:23:15_x000D_ 您目前英语基础如何呢？_x000D_ _x000D_ 01000000034659370892156192261110 2025-07-28 21:23:23_x000D_ 高考135_x000D_ _x000D_ AI-Lbo0rDBXCyBY 2025-07-28 21:23:27_x000D_ 这样，您微信还是电话方便呢？我安排四六级老师联系您，将课程的详细内容介绍给您_x000D_ _x000D_ 01000000034659370892156192261110 2025-07-28 21:23:45_x000D_ 13810956236_x000D_ _x000D_ AI-Lbo0rDBXCyBY 2025-07-28 21:23:48_x000D_ 好的，确认一下你的号码是否正确呢~_x000D_ _x000D_ 01000000034659370892156192261110 2025-07-28 21:24:05_x000D_ 没问题_x000D_ _x000D_ AI-Lbo0rDBXCyBY 2025-07-28 21:24:08_x000D_ 同学怎么称呼呢？_x000D_ _x000D_ 01000000034659370892156192261110 2025-07-28 21:24:33_x000D_ 有四级课程吗？_x000D_ _x000D_ AI-Lbo0rDBXCyBY 2025-07-28 21:24:37_x000D_ 好的，由于今天课程规划老师已经下班了，这边安排老师明天上午9点后给您回电请注意接听~_x000D_ _x000D_ 01000000034659370892156192261110 2025-07-28 21:24:49_x000D_ 好的_x000D_ _x000D_ AI-Lbo0rDBXCyBY 2025-07-28 21:24:53_x000D_ 好的，这个也是您的微信号吗？_x000D_ _x000D_ 01000000034659370892156192261110 2025-07-28 21:25:11_x000D_ 先电话联系吧_x000D_ _x000D_ AI-Lbo0rDBXCyBY 2025-07-28 21:25:14_x000D_ 稍后老师会联系哈_x000D_ _x000D_ 01000000034659370892156192261110 2025-07-28 21:25:21_x000D_ 好的_x000D_ _x000D_ AI-Lbo0rDBXCyBY 2025-07-28 21:25:25_x000D_ 嗯嗯_x000D_ _x000D_ 来源页：https://souke.xdf.cn/search?cid=1&ccc=424&attr=0&v=5 备注： | I60: 2026财年第2财月易聊新东方PC官网 | K60: 徐利霞 | L60: 新东方官网 | M60: 新东方PC官网 | O60: 徐利霞 | P60: 2025-07-29 12:08:42 | Q60: 赵中翰 | R60: 房国超 | S60: 29390849 | T60: 正常工单 | U60: 2025-07-29 12:19 | V60: A（六个月内有报课意向工单） | W60: 六级,四级,大学预科 | X60: 高三 | Y60: 北京理工大学 | Z60: 机电学院 | AA60: 机械电子工程 | AB60: 赵中翰 | AC60: 5421492 | AD60: 房国超 | AE60: 2025-07-31 17:06 | AF60: 房国超 | AG60: 2025-07-31 17:06 | AH60: YKSJ25001 | AI60: 六级无忧计划（线上优享/新大一专属） | AJ60: 国内考试 | AL60: 4880 | AO60: 新签 | AP60: 已交接 | AQ60: BJWY22035556hl | AR60: BJWY5755598249 | AS60: YKSJ250010064 | AT60: 2025-07-31 | AV60: 回访人：房国超，回访时间：2025-07-29 12:19，回访内容：家长咨询，新大一，英语135， 住西四环和五环， 推荐六级小班和大班，微信详聊；|回访人：房国超，回访时间：2025-07-30 14:12，回访内容： 家长咨询，新大一，英语135， 住西四环和五环， 推荐六级小班和大班，微信详聊；|回访人：房国超，回访时间：2025-07-31 17:06，回访内容：报名 | BA60: 82517108 | BB60: 否 | BC60: 25下考季 | BD60: 六级无忧计划 | BG60: 国内高校-985 | BH60: 是 | BK60: 报名 | BM60: 本地人本地大学(常规) | BN60: 易聊在线咨询
A61: 79 | B61: 北京大学部 | C61: 国内大学部 | D61: 常思源 | E61: 121423097 | F61: 曹伟杰2 | G61: 2025-07-30 16:32:04 | H61: 家长要报四级课，在开车，直接打电话 秦思瑶+qinsiyao@xdf.cn+新东方教育科技集团有限公司-培训学校-北京学校-高中一对一部-东北区-朝阳北分中心 | 学习顾问 | J61: 大一 | K61: 刘晓娟 | L61: 转介绍 | M61: 内部员工推荐 | N61: 秦思瑶+qinsiyao@xdf.cn+新东方教育科技集团有限公司-培训学校-北京学校-高中一对一部-东北区-朝阳北分中心 | 学习顾问 | Q61: 常思源 | R61: 刘晓娟 | S61: 29421630 | T61: 正常工单 | U61: 2025-07-30 17:22 | V61: A（六个月内有报课意向工单） | W61: 四级,大学预科 | X61: 高三 | Y61: 北京海淀凯文学校 | Z61: 新大一 | AA61: 新大一 | AB61: 常思源 | AC61: 5421279 | AD61: 刘晓娟 | AE61: 2025-07-31 14:25 | AF61: 刘晓娟 | AG61: 2025-07-31 14:35 | AH61: YKF25007 | AI61: 四级无忧计划 | AJ61: 国内考试 | AL61: 4784 | AN61: 秦思瑶+qinsiyao@xdf.cn+新东方教育科技集团有限公司-培训学校-北京学校-高中一对一部-东北区-朝阳北分中心 | 学习顾问 | AO61: 新签 | AP61: 已交接 | AQ61: WebReg | AR61: BJWY3084293987 | AS61: YKF250070035 | AT61: 2025-07-31 | AV61: 回访人：刘晓娟，回访时间：2025-07-30 17:22，回访内容：孩子家长咨询，四级大班，介绍，家长要跟孩子商量下，之前中学的老生，也问了优惠，不加微信，考虑下；|回访人：刘晓娟，回访时间：2025-07-31 14:25，回访内容：报名 | BA61: 82539831 | BB61: 否 | BC61: 25下考季 | BD61: 四级无忧计划 | BG61: 普通学校-普高 | BH61: 是 | BK61: 报名 | BM61: 本地人本地大学(常规) | BN61: 市场
A62: 80 | B62: 北京大学部 | C62: 国内大学部 | D62: 未知 | E62: 120060180 | F62: 李雪68 | G62: 2025-07-22 13:30:53 | H62: 激活 | J62: 初三 | K62: 宋增辉 | L62: 毛坯数据 | M62: 毛坯数据 | Q62: 王子昱 | R62: 宋增辉 | S62: 29240315 | T62: 正常工单 | U62: 2025-07-22 13:41 | V62: A（六个月内有报课意向工单） | W62: 四级,大学预科 | X62: 大一 | Y62: 首都师范大学 | Z62: 数学科学学院 | AA62: 数学师范 | AB62: 王子昱 | AC62: 5421120 | AD62: 宋增辉 | AE62: 2025-07-31 11:29 | AF62: 宋增辉 | AG62: 2025-07-31 11:32 | AH62: LP1753932591605 | AI62: 大学课程一对一伴学班（其它） | AJ62: 国内考试 | AL62: 9000 | AO62: 新签 | AP62: 已交接 | AR62: BJWY2457805016 | AT62: 2025-07-31 | AV62: 回访人：宋增辉，回访时间：2025-07-22 13:41，回访内容：一直跟进，决定报名学习，想要学习数学类课程 总结：客户希望预约成小伟老师的数学课程，成老师经验丰富且耐心，但时间安排较为紧张，仅下午有空闲。课程费用为1300元/小时，根据课时有梯度优惠。客户孩子为首师大数学师范专业准大一学生，需补充较多数学内容。由于暑假老师时间紧张，无法提供试听课，建议先报名50小时课程进行试听。客户之前在新东方报名了法语课，但无法跨部门使用费用，需申请退费处理。 下次回访建议：1. 确认成小伟老师的具体上课时间安排，确保与客户需求一致。2. 提供详细的课程内容和安排，确保客户了解课程进度和重点。3. 跟进法语课退费进度，确保客户及时收到退款。4. 确认客户对课程内容和安排的满意度，及时调整课程计划。5. 提供课程反馈渠道，确保客户能够及时反馈学习情况和需求。；|回访人：宋增辉，回访时间：2025-07-22 16:29，回访内容：限额，分开二维码报名学习 总结：客户希望预约数学专业老师成小伟的课程，并询问了老师的耐心程度、收费标准和试听课安排。成老师时间紧张，只能安排下午课程，且无试听课，但可先报名两小时课程试听。客户最终决定报名50小时课程，并完成了协议签署和支付。 下次回访建议：1. 确认成小伟老师的课程安排是否顺利，确保客户满意。2. 询问客户对试听课程的评价，了解是否需要调整教学计划。3. 提醒客户注意转退班制度，确保客户了解相关规则。4. 关注客户对课程的整体满意度，及时解决可能出现的问题。5. 询问客户是否有其他需求或问题，提供进一步帮助。；|回访人：宋增辉，回访时间：2025-07-23 13:46，回访内容：已经报名；|回访人：宋增辉，回访时间：2025-07-31 10:35，回访内容：宋增辉进行了退单操作!(本条回访记录由系统自动记录)；|回访人：宋增辉，回访时间：2025-07-31 11:32，回访内容：已经报名 | BA62: 74562361 | BB62: 否 | BC62: 25下考季 | BD62: 四级一对一 | BG62: 国内高校-双一流(非985/211) | BH62: 是 | BM62: 本地人本地大学(常规) | BN62: 客服
A63: 81 | B63: 北京大学部 | C63: 国内大学部 | D63: 张瀛 | E63: 121329964 | F63: 段同飞 | G63: 2025-07-30 10:52:52 | J63: 大一 | K63: 杨晓超 | L63: 转介绍 | M63: 内部员工推荐 | N63: 丁雨晴+dingyuqing@xdf.cn+id+丁雨晴(新东方教育科技集团有限公司-产业机构-国际教育培训事业部-国际教育北京中心-运营管理部-大学区域运营中心-国贸大学分中心 | 学业规划师) | Q63: 张瀛 | R63: 杨晓超 | S63: 29352293 | T63: 正常工单 | U63: 2025-07-30 15:13 | V63: A（六个月内有报课意向工单） | W63: 四级 | X63: 大一 | Y63: 南京农业大学 | Z63: 生命科学学院 | AA63: 生物技术 | AB63: 张瀛 | AC63: 5526584 | AD63: 宋增辉 | AE63: 2025-07-30 21:01 | AF63: 杨晓超 | AG63: 2025-07-30 21:04 | AJ63: 国内考试 | AL63: 9750 | AN63: 丁雨晴+dingyuqing@xdf.cn+id+丁雨晴(新东方教育科技集团有限公司-产业机构-国际教育培训事业部-国际教育北京中心-运营管理部-大学区域运营中心-国贸大学分中心 | 学业规划师) | AO63: 分单 | AP63: 已交接 | AR63: BJWY7294315735 | AV63: 回访人：杨晓超，回访时间：2025-07-30 15:13，回访内容：知春路面谈 ，四级课程沟通 ；|回访人：杨晓超，回访时间：2025-07-30 21:01，回访内容：签约 | BA63: 74471428 | BB63: 否 | BC63: 25上考季 | BD63: 四级无忧计划 | BG63: 国内高校-211 | BH63: 否 | BM63: 本地人外地大学(归巢) | BN63: 客服
A64: 82 | B64: 北京大学部 | C64: 国内大学部 | D64: 张先生 | E64: 121091295 | F64: 曹伟杰2 | G64: 2025-07-28 22:41:35 | H64: 咨询四级线下课【张志威公众号】 | J64: 大一 | K64: 房国超 | L64: 线上运营-私域中台 | M64: 公众号 | Q64: 宫思宇 | R64: 房国超 | S64: 29389995 | T64: 正常工单 | U64: 2025-07-29 11:09 | V64: A（六个月内有报课意向工单） | W64: 四级,大学预科 | X64: 高三 | Y64: 北京邮电大学世纪学院 | Z64: 外语系 | AA64: 英语 | AB64: 宫思宇 | AC64: 5526409 | AD64: 房国超 | AE64: 2025-07-30 18:23 | AF64: 房国超 | AG64: 2025-07-30 18:23 | AH64: YKF25007 | AI64: 四级无忧计划 | AJ64: 国内考试 | AL64: 4880 | AO64: 新签 | AP64: 已交接 | AQ64: BJWY24032w1g8X | AR64: BJWY4636648239 | AS64: YKF250070033 | AT64: 2025-07-30 | AV64: 回访人：房国超，回访时间：2025-07-29 11:09，回访内容：家长咨询，学生高考英语105，之前都是100以下， 推荐学四级小班 ，距离花园桥校区近， 微信详聊；|回访人：房国超，回访时间：2025-07-29 11:10，回访内容：家长咨询，学生高考英语105，之前都是100以下， 推荐学四级小班 ，距离花园桥校区近；|回访人：房国超，回访时间：2025-07-30 15:44，回访内容：已储值，英语专业，报名4号知春路校区大班 ；|回访人：房国超，回访时间：2025-07-30 18:23，回访内容：报名 | BA64: 82513315 | BB64: 否 | BC64: 25下考季 | BD64: 四级无忧计划 | BG64: 普通学校-普高 | BH64: 是 | BK64: 报名 | BM64: 本地人本地大学(常规) | BN64: 市场
A65: 83 | B65: 北京大学部 | C65: 国内大学部 | D65: 赵梓言同学 | E65: 120999088 | F65: 吴凯龙 | G65: 2025-07-28 10:53:24 | H65: 刘晓娟的内部员工推荐工单 | J65: 大一 | K65: 刘晓娟 | L65: 转介绍 | M65: 内部员工推荐 | N65: 方园卉+fangyuanhui@xdf.cn+ID+方园卉(新东方教育科技集团有限公司-培训学校-北京学校-智慧学习部-门店运营中心-望京校区 | 销售主管) | Q65: 赵梓言 | R65: 刘晓娟 | S65: 29344602 | T65: 正常工单 | U65: 2025-07-28 11:06 | V65: A（六个月内有报课意向工单） | W65: 四级,大学预科 | X65: 高三 | Y65: 北京石景山区实验中学 | Z65: 新大一 | AA65: 新大一 | AB65: 赵梓言 | AC65: 5526399 | AD65: 刘晓娟 | AE65: 2025-07-30 18:19 | AF65: 刘晓娟 | AG65: 2025-07-30 18:19 | AH65: YKF25007 | AI65: 四级无忧计划 | AJ65: 国内考试 | AL65: 5180 | AN65: 方园卉+fangyuanhui@xdf.cn+ID+方园卉(新东方教育科技集团有限公司-培训学校-北京学校-智慧学习部-门店运营中心-望京校区 | 销售主管) | AO65: 新签 | AP65: 已交接 | AQ65: BJWY2101498uW2 | AR65: BJWY6086763468 | AS65: YKF250070034 | AT65: 2025-07-30 | AV65: 回访人：刘晓娟，回访时间：2025-07-28 11:06，回访内容：孩子高考106，母亲咨询，家里知春路近一些，介绍四级8.4的班级，稍后通过我的微信发送课程安排；|回访人：刘晓娟，回访时间：2025-07-30 18:19，回访内容：报名 | BA65: 74519415 | BB65: 否 | BC65: 25下考季 | BD65: 四级无忧计划 | BG65: 普通学校-普高 | BH65: 是 | BK65: 报名 | BM65: 本地人本地大学(常规) | BN65: 客服
A66: 84 | B66: 北京大学部 | C66: 国内大学部 | D66: 杨振远 | E66: 120821628 | F66: 曹伟杰2 | G66: 2025-07-26 11:13:16 | H66: 新大一家长咨询暑期四级班【张志威公众号】 | J66: 大一 | K66: 宋增辉 | L66: 线上运营-私域中台 | M66: 公众号 | Q66: 杨振远 | R66: 宋增辉 | S66: 29327303 | T66: 正常工单 | U66: 2025-07-26 12:08 | V66: B（需长时间跟单或只需要规划） | W66: 六级,大学预科 | X66: 大一 | Y66: 北京工业大学 | Z66: 材料与制造学部 | AA66: 材料科学与工程 | AB66: 杨振远 | AC66: 5526391 | AD66: 宋增辉 | AE66: 2025-07-30 18:16 | AF66: 宋增辉 | AG66: 2025-07-30 18:16 | AH66: YKS25003 | AI66: 六级无忧计划（新大一专属） | AJ66: 国内考试 | AL66: 5180 | AO66: 新签 | AP66: 已交接 | AQ66: BJWY24032w1g8X | AR66: BJWY4029885069 | AS66: YKS250030035 | AT66: 2025-07-30 | AV66: 回访人：宋增辉，回访时间：2025-07-26 12:08，回访内容：家长要和孩子商量，推荐了数学和英语六级大班，询问有没有分班测；|回访人：宋增辉，回访时间：2025-07-30 18:16，回访内容：已报名 | BA66: 59757743 | BB66: 否 | BC66: 25下考季 | BD66: 六级无忧计划 | BG66: 国内高校-211 | BH66: 是 | BK66: 报名 | BM66: 本地人本地大学(常规) | BN66: 市场
A67: 85 | B67: 北京大学部 | C67: 国内大学部 | D67: 凌梦曦 | E67: 108304313 | F67: 北京国内管理员 | G67: 2025-06-04 13:52:17 | H67: 来源:北京学校; | I67: 【2025-CRM高三资源】-北京大学部 | J67: 大一 | K67: 杨雨童(离职) | L67: 毛坯数据 | M67: 毛坯数据 | O67: 杨雨童(离职) | P67: 2025-07-08 16:32:42 | Q67: 凌梦曦 | R67: 刘晓娟 | S67: 28933571 | T67: 正常工单 | U67: 2025-07-30 08:51 | V67: A（六个月内有报课意向工单） | W67: 六级,大学预科 | X67: 高三 | Y67: 河北省廊坊市恒威学校 | Z67: 新大一 | AA67: 新大一 | AB67: 凌梦曦 | AC67: 5526132 | AD67: 刘晓娟 | AE67: 2025-07-30 15:52 | AF67: 刘晓娟 | AG67: 2025-07-30 15:52 | AH67: YKSJ25001 | AI67: 六级无忧计划（线上优享/新大一专属） | AJ67: 国内考试 | AL67: 3239.2 | AO67: 新签 | AP67: 已交接 | AQ67: WebReg | AR67: BJWY5267658662 | AS67: YKSJ250010063 | AT67: 2025-07-30 | AV67: 回访人：刘晓娟，回访时间：2025-07-25 18:12，回访内容：微信再次留言，确认意向；|回访人：刘晓娟，回访时间：2025-07-29 09:54，回访内容：孩子自己买网课学习了，不退，也不考虑了；|回访人：段同飞，回访时间：2025-07-30 08:51，回访内容：段同飞恢复工单, 系统自动生成回访记录!；|回访人：刘晓娟，回访时间：2025-07-30 11:32，回访内容：打算上一节课试试，建议插班报名；|回访人：刘晓娟，回访时间：2025-07-30 15:52，回访内容：报名 | BA67: 74723304 | BB67: 否 | BC67: 25下考季 | BD67: 六级无忧计划 | BG67: 国内高校-双非 | BH67: 是 | BK67: 报名 | BM67: 外地人外地大学(常规) | BN67: 新CRM
A68: 86 | B68: 北京大学部 | C68: 国内大学部 | D68: 付建行 | E68: 121422640 | F68: 段同飞 | G68: 2025-07-30 16:26:09 | H68: 张子杰同学推荐 | J68: 大一 | K68: 张博奥 | L68: 转介绍 | M68: 顾问转介绍-老带新 | N68: 张博奥zhangboao@xdf.cn | Q68: 付建行 | R68: 张博奥 | S68: 29431034 | T68: 正常工单 | U68: 2025-07-30 16:28 | V68: A（六个月内有报课意向工单） | W68: 六级 | X68: 大一 | Y68: 北京信息科技大学 | Z68: 信息管理学院 | AA68: 信息安全 | AB68: 付建行 | AC68: 5498706 | AD68: 张博奥 | AE68: 2025-07-30 19:56 | AF68: 张博奥 | AG68: 2025-07-30 19:57 | AH68: YKS25003 | AI68: 六级无忧计划（新大一专属） | AJ68: 国内考试 | AL68: 4880 | AN68: 张博奥 | AO68: 新签 | AP68: 已交接 | AQ68: BJWY2101498uW2 | AR68: BJWY8488037202 | AS68: YKS250030036 | AT68: 2025-07-30 | AV68: 回访人：张博奥，回访时间：2025-07-30 16:28，回访内容：准备报名；|回访人：张博奥，回访时间：2025-07-30 19:56，回访内容：已报名 | BA68: 82539414 | BB68: 否 | BC68: 25下考季 | BD68: 六级无忧计划 | BG68: 国内高校-双非 | BH68: 是 | BI68: 辛苦学管老师尽快联系学生并发送导学课 | BK68: 报名 | BM68: 本地人外地大学(归巢) | BN68: 客服
A69: 87 | B69: 北京大学部 | C69: 国内大学部 | D69: 同学 | E69: 120969074 | F69: 吴凯龙 | G69: 2025-07-28 10:25:32 | H69: 刘晓娟的顾问转介绍工单 | J69: 大一 | K69: 刘晓娟 | L69: 转介绍 | M69: 顾问转介绍-老带新 | N69: 刘晓娟liuxiaojuan@xdf.cn | Q69: 罗杰夫 | R69: 刘晓娟 | S69: 29380913 | T69: 正常工单 | U69: 2025-07-28 10:30 | V69: A（六个月内有报课意向工单） | W69: 四级,大学预科 | X69: 高三 | Y69: 北京石景山区实验中学 | Z69: 新大一 | AA69: 新大一 | AB69: 罗杰夫 | AC69: 5498561 | AD69: 刘晓娟 | AE69: 2025-07-30 18:16 | AF69: 刘晓娟 | AG69: 2025-07-30 18:16 | AH69: YKS25003 | AI69: 六级无忧计划（新大一专属） | AJ69: 国内考试 | AL69: 5180 | AN69: 刘晓娟 | AO69: 新签 | AP69: 已交接 | AQ69: BJWY24032w1g8X | AR69: BJWY6865910226 | AS69: YKS250030037 | AT69: 2025-07-30 | AV69: 回访人：刘晓娟，回访时间：2025-07-28 10:30，回访内容：家长拉群，咨询，新大一，想看看暑假四级的课程，介绍8月4日的四级班；|回访人：刘晓娟，回访时间：2025-07-30 18:16，回访内容：报名 | BA69: 82478037 | BB69: 否 | BC69: 25下考季 | BD69: 四级无忧计划 | BG69: 普通学校-普高 | BH69: 是 | BK69: 报名 | BM69: 本地人本地大学(常规) | BN69: 客服
A70: 88 | B70: 北京大学部 | C70: 国内大学部 | D70: 白沙骐 | E70: 121033544 | F70: 杨欢欢 | G70: 2025-07-28 18:32:05 | H70: 家长咨询四级口语【张志威视频号】（TMK主管分配TMK） | J70: 大一 | K70: 段同飞 | L70: 线上运营-私域中台 | M70: 视频号 | O70: 段同飞 | P70: 2025-07-30 17:45:48 | Q70: 白沙骐 | R70: 刘晓娟 | S70: 29432111 | T70: 正常工单 | U70: 2025-07-30 17:49 | V70: A（六个月内有报课意向工单） | W70: 大学预科 | X70: 高三 | Y70: 内蒙古鄂尔多斯市第一中学 | Z70: 新大一 | AA70: 新大一 | AB70: 白沙骐 | AC70: 5498526 | AD70: 刘晓娟 | AE70: 2025-07-30 18:00 | AF70: 刘晓娟 | AG70: 2025-07-30 18:00 | AH70: YK25002 | AI70: 大学口语特训营 | AJ70: 国内考试 | AL70: 4680 | AO70: 新签 | AP70: 已交接 | AQ70: WebReg | AR70: BJWY0190980765 | AS70: YK250020023 | AT70: 2025-07-30 | AV70: 回访人：刘晓娟，回访时间：2025-07-30 17:49，回访内容：大学口语的课程，介绍，8.4的班级，报名；|回访人：刘晓娟，回访时间：2025-07-30 18:00，回访内容：报名 | BA70: 81134651 | BB70: 否 | BG70: 普通学校-普高 | BH70: 是 | BK70: 报名 | BM70: 本地人本地大学(常规)
A71: 89 | B71: 北京大学部 | C71: 国内大学部 | D71: 乐啸涵 | E71: 108395788 | F71: 北京国内管理员 | G71: 2025-06-04 15:11:02 | H71: 来源:北京学校; | I71: 【2025-CRM高三资源】-北京大学部 | J71: 大一 | K71: 赖欢 | L71: 毛坯数据 | M71: 毛坯数据 | O71: 赖欢 | P71: 2025-07-15 11:10:12 | Q71: 乐啸涵 | R71: 宋增辉 | S71: 29117815 | T71: 正常工单 | U71: 2025-07-16 15:32 | V71: A（六个月内有报课意向工单） | W71: 四级,大学预科 | X71: 大一 | Y71: 首都医科大学 | Z71: 临床医学院 | AA71: 口腔医学 | AB71: 乐啸涵 | AC71: 5498440 | AD71: 宋增辉 | AE71: 2025-07-30 17:18 | AF71: 宋增辉 | AG71: 2025-07-30 17:18 | AH71: WYFJ25040 | AI71: 四级无忧计划 | AJ71: 国内考试 | AL71: 5680 | AO71: 新签 | AP71: 已交接 | AQ71: WebReg | AR71: BJWY7301760995 | AS71: WYFJ250400005 | AT71: 2025-07-30 | AV71: 回访人：宋增辉，回访时间：2025-07-22 20:39，回访内容：电话危机，微信留言；|回访人：宋增辉，回访时间：2025-07-26 14:35，回访内容：电话未接，要来听试听课；|回访人：宋增辉，回访时间：2025-07-26 16:39，回访内容：孩子过来的，没找见人，下课直接跑了。；|回访人：宋增辉，回访时间：2025-07-29 17:35，回访内容：微信沟通要学习秋季四级班，已经发了协议；|回访人：宋增辉，回访时间：2025-07-30 17:18，回访内容：已报名 | BA71: 74810632 | BB71: 否 | BC71: 25下考季 | BD71: 四级无忧计划 | BG71: 国内高校-双非 | BH71: 是 | BK71: 报名 | BM71: 本地人本地大学(常规) | BN71: 新CRM
A72: 90 | B72: 北京大学部 | C72: 国内大学部 | D72: 彩虹 | E72: 119880708 | F72: 王朝群 | G72: 2025-07-19 14:36:05 | H72: 【王朝群】咨询四级暑期班 | I72: 2026财年第2财月小红书 | J72: 大二 | K72: 房国超 | L72: 线上运营-小红书 | M72: 小红书 | Q72: 孙昌熇 | R72: 房国超 | S72: 29206346 | T72: 正常工单 | U72: 2025-07-19 15:48 | V72: A（六个月内有报课意向工单） | W72: 四级 | X72: 大一 | Y72: 南昌航空大学 | Z72: 飞行器工程学院 | AA72: 飞行器设计与工程 | AB72: 孙昌熇 | AC72: 5498025 | AD72: 房国超 | AE72: 2025-07-30 13:28 | AF72: 房国超 | AG72: 2025-07-30 13:28 | AH72: YKF25007 | AI72: 四级无忧计划 | AJ72: 国内考试 | AL72: 5680 | AO72: 新签 | AP72: 已交接 | AQ72: WebReg | AR72: BJWY3708864030 | AS72: YKF250070031 | AT72: 2025-07-30 | AV72: 回访人：房国超，回访时间：2025-07-21 15:17，回访内容：梳理工单；|回访人：房国超，回访时间：2025-07-21 15:55，回访内容：梳理工单；|回访人：房国超，回访时间：2025-07-23 18:30，回访内容：小孩有点不太想学， 家长想让孩子自己决定；|回访人：房国超，回访时间：2025-07-23 20:31，回访内容：家长问有试听课嘛， 告知了试听安排，；|回访人：房国超，回访时间：2025-07-27 21:47，回访内容：电话无人接，微信留言；|回访人：房国超，回访时间：2025-07-29 18:50，回访内容：时间可能不合适， 再和孩子商量；|回访人：房国超，回访时间：2025-07-30 13:28，回访内容：报名 | BA72: 80205023 | BB72: 否 | BC72: 25下考季 | BD72: 四级无忧计划 | BG72: 国内高校-双非 | BH72: 是 | BK72: 报名 | BM72: 本地人本地大学(常规) | BN72: 小红书
A73: 91 | B73: 北京大学部 | C73: 国内大学部 | D73: 高佳文 | E73: 121109036 | F73: 杨沫 | G73: 2025-07-29 10:11:43 | H73: 潘美洋+panmeiyang@xdf.cn培训学校-北京学校-高中一对一部-西北区-知春路分中心-课程顾问 黄智超 | J73: 大一 | K73: 黄智超 | L73: 转介绍 | M73: 内部员工推荐 | N73: 潘美洋+panmeiyang@xdf.cn培训学校-北京学校-高中一对一部-西北区-知春路分中心+课程顾问 | Q73: 高佳文 | R73: 黄智超 | S73: 29389388 | T73: 正常工单 | U73: 2025-07-29 10:29 | V73: B（需长时间跟单或只需要规划） | W73: 大学预科 | X73: 大一 | Y73: 北京建筑大学 | Z73: 电气与信息工程学院 | AA73: 电气工程及其自动化 | AB73: 高佳文 | AC73: 5420888 | AD73: 黄智超 | AE73: 2025-07-30 18:27 | AF73: 黄智超 | AG73: 2025-07-30 18:28 | AH73: YKMJ25001 | AI73: 大学预科数学（线上优享/新大一专属） | AJ73: 国内考试 | AL73: 4680 | AN73: 潘美洋+panmeiyang@xdf.cn培训学校-北京学校-高中一对一部-西北区-知春路分中心+课程顾问 | AO73: 新签 | AP73: 已交接 | AQ73: WebReg | AR73: BJWY4111661392 | AS73: YKMJ250010040 | AT73: 2025-07-30 | AV73: 回访人：黄智超，回访时间：2025-07-29 10:29，回访内容：准备给孩子报名一个预科4级线上课程可以接受看回放。今天在搬家，有噪音，所以明天再报吧～；|回访人：黄智超，回访时间：2025-07-30 18:27，回访内容：已报名 预科线上高数课程～ | BA73: 18231055 | BB73: 否 | BG73: 国内高校-双非 | BH73: 是 | BK73: 报名 | BM73: 本地人本地大学(常规) | BN73: 客服
A74: 92 | B74: 北京大学部 | C74: 国内大学部 | D74: 无 | E74: 120835251 | F74: 程远 | G74: 2025-07-26 16:08:37 | H74: 渠道:百教招生 姓名:北京市9164 电话:13801201275 区域:北京市门头沟区 | J74: 未知 | K74: 杨钰杰 | L74: 线上运营-商务合作 | M74: 百教网 | O74: 杨钰杰 | P74: 2025-07-26 16:13:48 | Q74: 杨瑾瑶 | R74: 房国超 | S74: 29330117 | T74: 正常工单 | U74: 2025-07-26 16:33 | V74: A（六个月内有报课意向工单） | W74: 六级 | X74: 大一 | Y74: 重庆医科大学 | Z74: 第二临床学院 | AA74: 康复治疗学 | AB74: 杨瑾瑶 | AC74: 5525100 | AD74: 房国超 | AE74: 2025-07-29 15:34 | AF74: 房国超 | AG74: 2025-07-29 15:34 | AH74: YKS25005 | AI74: 六级精英计划（新大一专属） | AJ74: 国内考试 | AL74: 19800 | AO74: 新签 | AP74: 已交接 | AQ74: BJWY2101498uW2 | AR74: BJWY4851110805 | AS74: YKS250050013 | AT74: 2025-07-29 | AV74: 回访人：房国超，回访时间：2025-07-26 16:33，回访内容：新大二，四级考试480， 备考六级， 推荐小班，校区距离远，微信详聊；|回访人：房国超，回访时间：2025-07-27 16:44，回访内容：新大二，四级考试480， 备考六级， 推荐小班，校区距离远，微信详聊, 倾向小班，但是嫌贵，再考虑；|回访人：房国超，回访时间：2025-07-28 17:02，回访内容：发协议了，等待签字，说和孩子爸爸商量；|回访人：房国超，回访时间：2025-07-29 15:34，回访内容：报名 | BA74: 82457617 | BB74: 否 | BC74: 25下考季 | BD74: 六级无忧计划 | BG74: 国内高校-双非 | BH74: 是 | BK74: 报名 | BM74: 本地人本地大学(常规) | BN74: 客服
A75: 93 | B75: 北京大学部 | C75: 国内大学部 | D75: 憎恶 | E75: 119629915 | F75: 王朝群 | G75: 2025-07-17 18:21:44 | H75: 【王朝群】咨询四六级暑期班【微信联系，不方便电话】 | I75: 2026财年第2财月小红书 | J75: 大二 | K75: 田一禾 | L75: 线上运营-小红书 | M75: 小红书 | Q75: 曾悦祥 | R75: 田一禾 | S75: 29147820 | T75: 正常工单 | U75: 2025-07-18 11:42 | V75: B（需长时间跟单或只需要规划） | W75: 六级 | X75: 大四 | Y75: 首都医科大学 | Z75: 临床医学院 | AA75: 临床医学 | AB75: 曾悦祥 | AC75: 5525043 | AD75: 田一禾 | AE75: 2025-07-29 15:03 | AF75: 田一禾 | AG75: 2025-07-29 15:06 | AH75: WYSJ25040 | AI75: 六级无忧计划 | AJ75: 国内考试 | AL75: 5680 | AO75: 新签 | AP75: 已交接 | AQ75: BJWY2101498uW2 | AR75: BJWY6573949689 | AS75: WYSJ250400011 | AT75: 2025-07-29 | AV75: 回访人：田一禾，回访时间：2025-07-20 14:34，回访内容：询问线上开课计划，上课模式和答疑模式，但是支付能力预计一般。；|回访人：田一禾，回访时间：2025-07-24 22:30，回访内容：电话不接，支付能力中下，不是得等待，就是得死单。；|回访人：田一禾，回访时间：2025-07-29 15:03，回访内容：今日签约 | BA75: 38837869 | BB75: 否 | BC75: 25下考季 | BD75: 六级无忧计划 | BG75: 国内高校-双非 | BH75: 是 | BK75: 报名 | BM75: 本地人本地大学(常规) | BN75: 小红书
A76: 94 | B76: 北京大学部 | C76: 国内大学部 | D76: 韩舜宇 | E76: 121136198 | F76: 李玉迪 | G76: 2025-07-29 13:46:29 | H76: 续费原因：学员续费数学，辛苦流转刘晓娟老师；该学生为保护期内续费，原顾问：国内大学部-刘晓娟(liuxiaojuan@xdf.cn) | J76: 大一 | K76: 刘晓娟 | L76: 转介绍 | M76: 学管续费推荐 | N76: 李玉迪liyudi1@xdf.cn | Q76: 韩舜宇 | R76: 刘晓娟 | S76: 29391273 | T76: 续费工单 | U76: 2025-07-29 13:52 | V76: A（六个月内有报课意向工单） | W76: 大学预科 | X76: 大一 | Y76: 北京丰台第七中学 | Z76: 新大一 | AA76: 新大一 | AB76: 韩舜宇 | AC76: 5524926 | AD76: 刘晓娟 | AE76: 2025-07-29 13:52 | AF76: 刘晓娟 | AG76: 2025-07-29 13:53 | AH76: YKMJ25001 | AI76: 大学预科数学（线上优享/新大一专属） | AJ76: 国内考试 | AL76: 4525.7 | AM76: 扩科续费 | AN76: 李玉迪 | AO76: 续班 | AP76: 已交接 | AQ76: BJWY2101498uW2 | AR76: BJWY6686847945 | AS76: YKMJ250010039 | AT76: 2025-07-29 | AV76: 回访人：刘晓娟，回访时间：2025-07-29 13:52，回访内容：报名数学 | BA76: 82176141 | BB76: 否 | BG76: 普通学校-普高 | BH76: 是 | BK76: 追加优惠 | BM76: 本地人本地大学(常规) | BN76: 学管续费推荐
A77: 95 | B77: 北京大学部 | C77: 国内大学部 | D77: 张女士帮孩子 | E77: 121128790 | F77: 北京客服部 | G77: 2025-07-29 10:55:31 | H77: 四六级英语 北京/西城区 北京哪里有，高三毕业18岁面授课，咨询李阳，推荐这 | I77: 2026财年第2财月代理商 | K77: 杨欢欢 | L77: 线上运营-商务合作 | M77: 勤学网 | O77: 杨欢欢 | P77: 2025-07-29 11:51:39 | Q77: 雷济宇 | R77: 宋增辉 | S77: 29391018 | T77: 正常工单 | U77: 2025-07-29 13:05 | V77: A（六个月内有报课意向工单） | W77: 四级,大学预科 | X77: 大一 | Y77: 北京石油化工学院 | Z77: 材料科学与工程学院 | AA77: 高分子材料与工程 | AB77: 雷济宇 | AC77: 5524920 | AD77: 宋增辉 | AE77: 2025-07-29 13:49 | AF77: 宋增辉 | AG77: 2025-07-29 14:03 | AH77: LP1753768173882 | AI77: 四级一对一（30H） | AJ77: 国内考试 | AL77: 25000 | AO77: 新签 | AP77: 已交接 | AR77: BJWY8876741976 | AT77: 2025-07-29 | AV77: 回访人：宋增辉，回访时间：2025-07-29 13:05，回访内容：当面沟通，孩子想要学习英语一对一，规划了10小时，现在报名；|回访人：宋增辉，回访时间：2025-07-30 09:38，回访内容：已报名 | BA77: 82561232 | BB77: 否 | BC77: 25下考季 | BD77: 四级一对一 | BG77: 国内高校-双非 | BH77: 是 | BM77: 本地人本地大学(常规) | BN77: 线下代理商
A78: 96 | B78: 北京大学部 | C78: 国内大学部 | D78: 沈 | E78: 117025995 | F78: 郭欣宇 | G78: 2025-07-01 22:33:51 | H78: 18612082846，北京，四六级，家长 | J78: 未知 | K78: 房国超 | L78: 线上运营-投放 | M78: 巨量广告 | Q78: 沈州杰 | R78: 房国超 | S78: 28773432 | T78: 正常工单 | U78: 2025-07-02 11:20 | V78: A（六个月内有报课意向工单） | W78: 四级,大学预科 | X78: 高三 | Y78: 东北林业大学 | Z78: 经济管理学院 | AA78: 工商管理 | AB78: 沈州杰 | AC78: 5524849 | AD78: 房国超 | AE78: 2025-07-29 12:22 | AF78: 房国超 | AG78: 2025-07-29 12:22 | AH78: YKF25008 | AI78: 四级精英计划 | AJ78: 国内考试 | AL78: 19500 | AO78: 新签 | AP78: 已交接 | AQ78: BJWY2101498uW2 | AR78: BJWY2104419659 | AS78: YKF250080002 | AT78: 2025-07-29 | AV78: 回访人：房国超，回访时间：2025-07-24 22:53，回访内容：电话无人接，微信留言邀约试听 ；|回访人：房国超，回访时间：2025-07-28 18:38，回访内容：告知了4号的新班安排 ， 说和孩子商量下；|回访人：房国超，回访时间：2025-07-28 21:09，回访内容：已储值19500；|回访人：房国超，回访时间：2025-07-29 12:22，回访内容：报名 | BA78: 74584286 | BB78: 否 | BC78: 25下考季 | BD78: 四级无忧计划 | BG78: 国内高校-211 | BH78: 是 | BK78: 报名 | BM78: 本地人外地大学(归巢) | BN78: 市场
A79: 97 | B79: 北京大学部 | C79: 国内大学部 | D79: 鲁先生 | E79: 120940958 | F79: 曹伟杰2 | G79: 2025-07-27 15:00:11 | H79: 咨询四级线上课【张志威公众号】 | J79: 大一 | K79: 房国超 | L79: 线上运营-私域中台 | M79: 公众号 | Q79: 鲁子钡 | R79: 房国超 | S79: 29377348 | T79: 正常工单 | U79: 2025-07-27 16:41 | V79: A（六个月内有报课意向工单） | W79: 六级,大学预科 | X79: 高三 | Y79: 华中科技大学 | Z79: 人工智能与自动化学院 | AA79: 自动化 | AB79: 鲁子钡 | AC79: 5524847 | AD79: 房国超 | AE79: 2025-07-29 12:21 | AF79: 房国超 | AG79: 2025-07-29 12:21 | AH79: YKSJ25001 | AI79: 六级无忧计划（线上优享/新大一专属） | AJ79: 国内考试 | AL79: 4880 | AO79: 新签 | AP79: 已交接 | AQ79: BJWY2101498uW2 | AR79: BJWY5880090271 | AS79: YKSJ250010062 | AT79: 2025-07-29 | AV79: 回访人：房国超，回访时间：2025-07-27 16:41，回访内容：家长咨询， 浙江的，舟山， 英语138，优先线上直播课， ，一对一说考虑下， 让找杭州附近的线下走读班， 微信详聊；|回访人：房国超，回访时间：2025-07-28 16:49，回访内容：电话无人接，微信留言；|回访人：房国超，回访时间：2025-07-28 22:10，回访内容：打算报名六级直播课；|回访人：房国超，回访时间：2025-07-29 12:21，回访内容：报名 | BA79: 82494894 | BB79: 否 | BC79: 25下考季 | BD79: 六级无忧计划 | BG79: 国内高校-985 | BH79: 是 | BK79: 报名 | BM79: 外地人外地大学(常规) | BN79: 市场
A80: 98 | B80: 北京大学部 | C80: 国内大学部 | D80: 田鸿雁 | E80: 120935786 | F80: 段同飞 | G80: 2025-07-27 12:06:35 | J80: 大一 | K80: 宋增辉 | L80: 转介绍 | M80: 内部员工推荐 | N80: 刘双双+liushuangshuang3@xdf.cn+(新东方教育科技集团有限公司-培训学校-北京学校-高中一对一部-西南区-公主坟分中心 | 分中心高级主管) | Q80: 张景旸 | R80: 宋增辉 | S80: 29394840 | T80: 正常工单 | U80: 2025-07-27 13:25 | V80: A（六个月内有报课意向工单） | W80: 大学学科辅导 | X80: 大一 | Y80: 中国矿业大学 | Z80: 建筑与设计学院 | AA80: 建筑学 | AB80: 张景旸 | AC80: 5524672 | AD80: 宋增辉 | AE80: 2025-07-29 10:17 | AF80: 宋增辉 | AG80: 2025-07-29 10:21 | AH80: LP1753755460268 | AI80: 大学课程一对一（其它/30H） | AJ80: 国内考试 | AL80: 25000 | AN80: 刘双双+liushuangshuang3@xdf.cn+(新东方教育科技集团有限公司-培训学校-北京学校-高中一对一部-西南区-公主坟分中心 | 分中心高级主管) | AO80: 新签 | AP80: 已交接 | AR80: BJWY9526521857 | AT80: 2025-07-29 | AV80: 回访人：宋增辉，回访时间：2025-07-27 13:25，回访内容：咨询一对一，同步了上课老师的安排，家长想要试听，推荐了贺老师；|回访人：宋增辉，回访时间：2025-08-01 18:54，回访内容：已报名 | BA80: 75325594 | BB80: 否 | BC80: 25下考季 | BD80: 大学学科辅导 | BE80: 专业课 | BG80: 国内高校-211 | BH80: 是 | BM80: 本地人本地大学(常规) | BN80: 客服
A81: 99 | B81: 北京大学部 | C81: 国内大学部 | D81: 谢小元 | E81: 120758833 | F81: 曹伟杰2 | G81: 2025-07-25 15:00:37 | H81: 家长咨询暑期线下课【张志威公众号】 | J81: 大一 | K81: 宋增辉 | L81: 线上运营-私域中台 | M81: 公众号 | Q81: 李佳倩 | R81: 宋增辉 | S81: 29336423 | T81: 正常工单 | U81: 2025-07-25 15:34 | V81: B（需长时间跟单或只需要规划） | W81: 六级,大学预科 | X81: 大一 | Y81: 首都师范大学 | Z81: 数学科学学院 | AA81: 数学与应用数学 | AB81: 李佳倩 | AC81: 5497368 | AD81: 宋增辉 | AE81: 2025-07-29 16:44 | AF81: 宋增辉 | AG81: 2025-07-29 16:45 | AH81: YKS25003 | AI81: 六级无忧计划（新大一专属） | AJ81: 国内考试 | AL81: 5680 | AO81: 新签 | AP81: 已交接 | AQ81: WebReg | AR81: BJWY5931473104 | AS81: YKS250030034 | AT81: 2025-07-29 | AV81: 回访人：宋增辉，回访时间：2025-07-25 15:34，回访内容：家长赶飞机，说了课程安排，北京孩子，推荐了大班和小班，要和孩子商量呢；|回访人：宋增辉，回访时间：2025-07-29 16:44，回访内容：已经报名 | BA81: 82406387 | BB81: 否 | BC81: 25下考季 | BD81: 六级无忧计划 | BG81: 国内高校-双一流(非985/211) | BH81: 是 | BK81: 报名 | BM81: 外地人本地大学(常规) | BN81: 市场
A82: 100 | B82: 北京大学部 | C82: 国内大学部 | D82: 密思雨 | E82: 119278870 | F82: 曹伟杰2 | G82: 2025-07-16 15:41:24 | H82: 家长咨询专升本课程 | J82: 大三 | K82: 宋增辉 | L82: 线上运营-私域中台 | M82: 社群、虚拟人 | Q82: 密思雨 | R82: 宋增辉 | S82: 29118850 | T82: 正常工单 | U82: 2025-07-16 16:13 | V82: B（需长时间跟单或只需要规划） | W82: 专升本 | X82: 大三 | Y82: 北京科技职业学院 | Z82: 信息院 | AA82: 数字媒体 | AB82: 密思雨 | AC82: 5497269 | AD82: 张博奥 | AE82: 2025-07-29 15:35 | AF82: 宋增辉 | AG82: 2025-07-29 17:55 | AJ82: 国内考试 | AL82: 18750 | AO82: 分单 | AP82: 已交接 | AR82: BJWY3288691480 | AV82: 回访人：宋增辉，回访时间：2025-07-22 20:47，回访内容：现在在旅游稍后再定呢 ；|回访人：宋增辉，回访时间：2025-07-27 11:20，回访内容：昨天和老师沟通了，家长明天在中公有试听课，要对比机构，完了之后决定；|回访人：宋增辉，回访时间：2025-07-29 15:25，回访内容：已经报名；|回访人：宋增辉，回访时间：2025-07-29 15:26，回访内容：宋增辉进行了退单操作!(本条回访记录由系统自动记录)；|回访人：宋增辉，回访时间：2025-07-29 16:27，回访内容：已报名 | BA82: 44776513 | BB82: 否 | BC82: 26考季 | BD82: 专升本VIP | BE82: 英语 | BG82: 国内高校-大专 | BH82: 否 | BM82: 本地人本地大学(常规) | BN82: 市场
A83: 101 | B83: 北京大学部 | C83: 国内大学部 | D83: 郑 | E83: 117439907 | F83: 曹晗曦 | G83: 2025-07-03 16:39:32 | H83: 新大一家长咨询，在北京，咨询暑期四级集训，先加微信，晚上可以电话 | J83: 大一 | K83: 田一禾 | L83: 线上运营-私域中台 | M83: 社群、虚拟人 | Q83: 郑瀚麒 | R83: 田一禾 | S83: 28947946 | T83: 正常工单 | U83: 2025-07-08 22:19 | V83: B（需长时间跟单或只需要规划） | W83: 四级,大学预科 | X83: 大一 | Y83: 北京联合大学 | Z83: 生物化学工程学院 | AA83: 生物科学与工程 | AB83: 郑瀚麒 | AC83: 5497217 | AD83: 田一禾 | AE83: 2025-07-29 15:13 | AF83: 田一禾 | AG83: 2025-07-29 15:13 | AH83: YKF25007 | AI83: 四级无忧计划 | AJ83: 国内考试 | AL83: 5680 | AO83: 新签 | AP83: 已交接 | AQ83: BJWY24032w1g8X | AR83: BJWY5332504608 | AS83: YKF250070029 | AT83: 2025-07-29 | AV83: 回访人：田一禾，回访时间：2025-07-28 14:12，回访内容：回来再沟通，今天发送了八月份安排，改日再跟进。；|回访人：田一禾，回访时间：2025-07-29 15:13，回访内容：今日签约 | BA83: 74623584 | BB83: 否 | BC83: 25下考季 | BD83: 四级无忧计划 | BG83: 国内高校-双非 | BH83: 是 | BK83: 报名 | BM83: 本地人本地大学(常规) | BN83: 市场
A84: 102 | B84: 北京大学部 | C84: 国内大学部 | D84: 无 | E84: 120693417 | F84: 关秋冬 | G84: 2025-07-24 19:39:07 | H84: 咨询四级 IP：北京 | J84: 未知 | K84: 刘晓娟 | L84: 线上运营-投放 | M84: 其他网络投放 | Q84: 张胤博 | R84: 刘晓娟 | S84: 29296160 | T84: 正常工单 | U84: 2025-07-24 20:33 | V84: A（六个月内有报课意向工单） | W84: 四级,大学预科 | X84: 高三 | Y84: 北京市第一五九中学 | Z84: 新大一 | AA84: 新大一 | AB84: 张胤博 | AC84: 5496995 | AD84: 刘晓娟 | AE84: 2025-07-29 12:37 | AF84: 刘晓娟 | AG84: 2025-07-29 12:37 | AH84: YKF25007 | AI84: 四级无忧计划 | AJ84: 国内考试 | AL84: 5180 | AO84: 新签 | AP84: 已交接 | AQ84: BJWY2101498uW2 | AR84: BJWY0772996053 | AS84: YKF250070027 | AT84: 2025-07-29 | AV84: 回访人：刘晓娟，回访时间：2025-07-24 20:33，回访内容：孩子父亲咨询孩子新大一高考英语，100分加在中关村附近，想咨询4级线下的课程，介绍了大班和小班家长，跟孩子商量一下。；|回访人：刘晓娟，回访时间：2025-07-26 10:29，回访内容：微信留言，确认意向；|回访人：刘晓娟，回访时间：2025-07-29 12:37，回访内容：报名 | BA84: 82330284 | BB84: 否 | BC84: 25下考季 | BD84: 四级无忧计划 | BG84: 普通学校-普高 | BH84: 是 | BK84: 报名 | BM84: 本地人本地大学(常规) | BN84: 市场
A85: 103 | B85: 北京大学部 | C85: 国内大学部 | D85: 马舒云 | E85: 121035876 | F85: 杨沫 | G85: 2025-07-29 09:30:34 | H85: 贺磊+helei24@xdf.cn+ID+新东方教育科技集团有限公司-培训学校-北京学校-高中一对一部-西南区-公主坟分中心- 课程顾问 刘晓娟 | J85: 大一 | K85: 刘晓娟 | L85: 转介绍 | M85: 内部员工推荐 | N85: 贺磊+helei24@xdf.cn+ID+新东方教育科技集团有限公司-培训学校-北京学校-高中一对一部-西南区-公主坟分中心- 课程顾问 | Q85: 马舒云 | R85: 刘晓娟 | S85: 29408105 | T85: 正常工单 | U85: 2025-07-29 09:43 | V85: A（六个月内有报课意向工单） | W85: 四级,大学预科 | X85: 高三 | Y85: 北京海淀区明光中学 | Z85: 新大一 | AA85: 新大一 | AB85: 马舒云 | AC85: 5496989 | AD85: 刘晓娟 | AE85: 2025-07-29 12:34 | AF85: 刘晓娟 | AG85: 2025-07-29 12:34 | AH85: YKF25007 | AI85: 四级无忧计划 | AJ85: 国内考试 | AL85: 5180 | AN85: 贺磊+helei24@xdf.cn+ID+新东方教育科技集团有限公司-培训学校-北京学校-高中一对一部-西南区-公主坟分中心- 课程顾问 | AO85: 新签 | AP85: 已交接 | AQ85: BJWY2101498uW2 | AR85: BJWY7374815624 | AS85: YKF250070028 | AT85: 2025-07-29 | AV85: 回访人：刘晓娟，回访时间：2025-07-29 09:43，回访内容：家长给孩子咨询新大一本科是要去外地上学，想了解四级线下的课程介绍四级大班报名；|回访人：刘晓娟，回访时间：2025-07-29 12:34，回访内容：报名 | BA85: 82517937 | BB85: 否 | BC85: 25下考季 | BD85: 四级无忧计划 | BG85: 普通学校-普高 | BH85: 是 | BK85: 报名 | BM85: 本地人本地大学(常规) | BN85: 客服
A86: 104 | B86: 北京大学部 | C86: 国内大学部 | D86: 容容 | E86: 121163041 | F86: 杨沫 | G86: 2025-07-29 14:09:28 | H86: 吕玉珠+lvyuzhu1@xdf.cn+444957+培训学校-北京学校-高中一对一部-增长中心-线上社群组-社群运营专员 黄智超 | J86: 大一 | K86: 黄智超 | L86: 转介绍 | M86: 内部员工推荐 | N86: 吕玉珠+lvyuzhu1@xdf.cn+444957+培训学校-北京学校-高中一对一部-增长中心-线上社群组-社群运营专员 | Q86: 佟昀萱 | R86: 黄智超 | S86: 29391632 | T86: 正常工单 | U86: 2025-07-29 14:20 | V86: A（六个月内有报课意向工单） | W86: 四级,大学预科 | X86: 大一 | Y86: 首都经济贸易大学 | Z86: 财政税务学院 | AA86: 税务 | AB86: 佟昀萱 | AC86: 5420342 | AD86: 黄智超 | AE86: 2025-07-29 17:38 | AF86: 黄智超 | AG86: 2025-07-29 17:49 | AH86: YKF25007 | AI86: 四级无忧计划 | AJ86: 国内考试 | AL86: 5680 | AN86: 吕玉珠+lvyuzhu1@xdf.cn+444957+培训学校-北京学校-高中一对一部-增长中心-线上社群组-社群运营专员 | AO86: 新签 | AP86: 已交接 | AQ86: BJWY24032w1g8X | AR86: BJWY0531996201 | AS86: YKF250070030 | AT86: 2025-07-29 | AV86: 回访人：黄智超，回访时间：2025-07-29 14:20，回访内容：预计报名 暑假四级班课 8.4知春路校区 等看看小伙伴能不能一起学～；|回访人：黄智超，回访时间：2025-07-29 17:38，回访内容：已报名 5680 四级大班 8.4开课 | BA86: 56503475 | BB86: 否 | BC86: 25下考季 | BD86: 四级无忧计划 | BG86: 国内高校-双非 | BH86: 是 | BK86: 报名 | BM86: 本地人本地大学(常规) | BN86: 客服
A87: 105 | B87: 北京大学部 | C87: 国内大学部 | D87: 边浩鑫 | E87: 116558143 | F87: 北京国内管理员 | G87: 2025-06-28 11:54:41 | H87: 渠道录入来源：SCRM-客服推送 商机ID：5009137634 商机编码：XSJ20250628014232 针对人群：高中 咨询课程：不区分 创建人邮箱：lidongmei1@xdf.cn 创建时间：2025-06-28 11:54:36 资源类型：单个资源 跟进记录：商机备注：国内大一预科班咨询，英语120分，北京海淀区的，微信同手机，辛苦加微信咨询谢谢;接触点：企点-环信； | J87: 高二 | K87: 宋增辉 | L87: 合作 | M87: 集团资源 | Q87: 边浩鑫 | R87: 宋增辉 | S87: 28690082 | T87: 正常工单 | U87: 2025-06-28 17:47 | V87: A（六个月内有报课意向工单） | W87: 四级,大学预科 | X87: 大一 | Y87: 山西省朔州市怀仁县第一中学 | Z87: 新大一 | AA87: 新大一 | AB87: 边浩鑫 | AC87: 5420273 | AD87: 宋增辉 | AE87: 2025-07-29 15:53 | AF87: 宋增辉 | AG87: 2025-07-29 15:53 | AH87: YKS25003 | AI87: 六级无忧计划（新大一专属） | AJ87: 国内考试 | AL87: 5180 | AO87: 新签 | AP87: 已交接 | AQ87: BJWY2101498uW2 | AR87: BJWY6194993520 | AS87: YKS250030033 | AT87: 2025-07-29 | AV87: 回访人：宋增辉，回访时间：2025-07-21 19:59，回访内容：孩子还在沟通考虑呢，暂时没结果呢 总结：客户表示目前没有需要解决的问题或进一步的需求。 下次回访建议：建议在适当的时间再次联系客户，了解是否有新的需求或问题，并继续保持良好的沟通关系。；|回访人：宋增辉，回访时间：2025-07-26 11:02，回访内容：代咨询，孩子不愿意学习，拒绝一次；|回访人：宋增辉，回访时间：2025-07-29 15:53，回访内容：已经报名 | BA87: 80678311 | BB87: 否 | BC87: 25下考季 | BD87: 四级无忧计划 | BG87: 普通学校-普高 | BH87: 是 | BK87: 报名 | BM87: 外地人外地大学(常规) | BN87: SCRM-客服推送
A88: 106 | B88: 北京大学部 | C88: 国内大学部 | D88: 密思雨 | E88: 119278870 | F88: 曹伟杰2 | G88: 2025-07-16 15:41:24 | H88: 家长咨询专升本课程 | J88: 大三 | K88: 宋增辉 | L88: 线上运营-私域中台 | M88: 社群、虚拟人 | Q88: 密思雨 | R88: 宋增辉 | S88: 29118850 | T88: 正常工单 | U88: 2025-07-16 16:13 | V88: B（需长时间跟单或只需要规划） | W88: 专升本 | X88: 大三 | Y88: 北京科技职业学院 | Z88: 信息院 | AA88: 数字媒体 | AB88: 密思雨 | AC88: 5420265 | AD88: 宋增辉 | AE88: 2025-07-29 15:35 | AF88: 宋增辉 | AG88: 2025-07-29 17:55 | AH88: LP17537745181311 | AI88: 四级一对一畅学班（50H） | AJ88: 国内考试 | AL88: 18750 | AO88: 新签 | AP88: 已交接 | AR88: BJWY3288691480 | AT88: 2025-07-29 | AV88: 回访人：宋增辉，回访时间：2025-07-22 20:47，回访内容：现在在旅游稍后再定呢 ；|回访人：宋增辉，回访时间：2025-07-27 11:20，回访内容：昨天和老师沟通了，家长明天在中公有试听课，要对比机构，完了之后决定；|回访人：宋增辉，回访时间：2025-07-29 15:25，回访内容：已经报名；|回访人：宋增辉，回访时间：2025-07-29 15:26，回访内容：宋增辉进行了退单操作!(本条回访记录由系统自动记录)；|回访人：宋增辉，回访时间：2025-07-29 16:27，回访内容：已报名 | BA88: 44776513 | BB88: 否 | BC88: 26考季 | BD88: 专升本VIP | BE88: 英语 | BG88: 国内高校-大专 | BH88: 否 | BM88: 本地人本地大学(常规) | BN88: 市场
A89: 107 | B89: 北京大学部 | C89: 国内大学部 | D89: 李如九 | E89: 108319654 | F89: 北京国内管理员 | G89: 2025-06-04 14:29:14 | H89: 来源:北京学校;【FY25已报名】金额：343019.00元，报了【FY25高端/一对一】 | I89: 【2025-CRM高三资源】-北京大学部 | J89: 大一 | K89: 王静静 | L89: 毛坯数据 | M89: 毛坯数据 | O89: 王静静 | P89: 2025-07-31 21:20:58 | Q89: 李如九 | R89: 黄智超 | S89: 29461196 | T89: 正常工单 | U89: 2025-07-31 21:26 | V89: A（六个月内有报课意向工单） | W89: 大学预科 | X89: 大一 | Y89: 东北师范大学附属中学朝阳学校 | Z89: 其他 | AA89: 其他 | AB89: 李如九 | AC89: 5528736 | AD89: 黄智超 | AE89: 2025-08-01 10:52 | AF89: 黄智超 | AG89: 2025-08-01 10:53 | AH89: YKF25008 | AI89: 四级精英计划 | AJ89: 国内考试 | AL89: 20300 | AO89: 新签 | AP89: 已交接 | AQ89: BJWY2011wXCx1W | AR89: BJWY1740497802 | AS89: YKF250080001 | AT89: 2025-07-28 | AV89: 回访人：黄智超，回访时间：2025-07-31 21:26，回访内容：重新绑单；|回访人：黄智超，回访时间：2025-08-01 10:52，回访内容：签约 绑单 | BA89: 75302052 | BB89: 否 | BG89: 国内高校-双非 | BH89: 是 | BK89: 报名 | BM89: 本地人本地大学(常规) | BN89: 新CRM
A90: 108 | B90: 北京大学部 | C90: 国内大学部 | D90: 北京市1506 | E90: 120914745 | F90: 杨俊42(国内) | G90: 2025-07-27 14:00:39 | H90: 渠道录入来源：新东方官网M资讯站-客服 意向城市：北京访客省/城市：北京市 访客静态ID：01000000034659359580640117931506 接待分组ID：70457 搜索引擎：www.baidu.com 搜索词： 关键词： 设备类型：phone 访客IP：114.246.238.224 对话详细内容：AI-Lbo0rDBXCyBY 2025-07-27 13:56:49_x000D_ 您好同学,欢迎访问北京新东方考研四六级中心. 考研线下课程26/27考季【考研全年集训营】【考研半年集训营】【考研全科线下走读班】【考研寒/暑假集训营】【考研一对一】【考研专业课】【四/六级课程】，热门课程火热报名中,咨询即可领取专享优惠。 **【考研全年集训营】=ff761f# **【考研半年集训营】=ff6b6b# **【考研全科线下走读班】=ffc158# **【考研寒/暑假集训营】=ffc158# **【考研一对一】=ff761f# **【考研专业课】=ff6caa# **【四/六级课程】=ff6caa# **【考研冲刺班】=60e27e#_x000D_ _x000D_ AI-Lbo0rDBXCyBY 2025-07-27 13:56:52_x000D_ 您是想咨询【线下课程】【线上课程】【考研规划】还是【在职考研】呢？**【线下课程】# **【线上课程】#**【考研规划】#**【在职考研】#_x000D_ _x000D_ 01000000034659359580640117931506 2025-07-27 13:57:05_x000D_ 【线下课程】_x000D_ _x000D_ AI-Lbo0rDBXCyBY 2025-07-27 13:57:09_x000D_ 同学，你现在是在校还是在职呢？_x000D_ _x000D_ 01000000034659359580640117931506 2025-07-27 13:57:17_x000D_ 大二_x000D_ _x000D_ AI-Lbo0rDBXCyBY 2025-07-27 13:57:20_x000D_ 具体是想报考什么学校和专业呢？_x000D_ _x000D_ 01000000034659359580640117931506 2025-07-27 13:57:35_x000D_ 交通运输_x000D_ _x000D_ AI-Lbo0rDBXCyBY 2025-07-27 13:57:38_x000D_ 好的，我这边安排专业老师给您回电，详细沟通一下，请问您的电话是多少呢？_x000D_ _x000D_ 01000000034659359580640117931506 2025-07-27 13:57:46_x000D_ 空管_x000D_ _x000D_ AI-Lbo0rDBXCyBY 2025-07-27 13:57:50_x000D_ 嗯嗯 好的那同学稍后方便接听电话吗？我这边可以立刻安排专业老师给您回电呢_x000D_ _x000D_ AI-Lbo0rDBXCyBY 2025-07-27 13:58:27_x000D_ 您好，能看到我的对话吗？如有疑问，可以在此留电咨询！_x000D_ _x000D_ 01000000034659359580640117931506 2025-07-27 13:58:37_x000D_ 13911156756_x000D_ _x000D_ AI-Lbo0rDBXCyBY 2025-07-27 13:58:40_x000D_ 好的，确认一下你的号码是否正确呢~_x000D_ _x000D_ 01000000034659359580640117931506 2025-07-27 13:58:56_x000D_ 正确_x000D_ _x000D_ AI-Lbo0rDBXCyBY 2025-07-27 13:59:00_x000D_ 同学怎么称呼呢？_x000D_ _x000D_ 01000000034659359580640117931506 2025-07-27 13:59:16_x000D_ 冯_x000D_ _x000D_ AI-Lbo0rDBXCyBY 2025-07-27 13:59:19_x000D_ 这边马上安排顾问老师联系您，预计半个小时左右给您回电请注意接听~_x000D_ _x000D_ 来源页：https://m.baidu.com/from=1019311v/bd_page_type=1/ssid=0/uid=0/pu=usm%400%2Csz%401320_1001%2Cta%40iphone_2_15.0_19_25.5/baiduid=96484127471D70DEC725E9206A612C56/w=0_10_/t=iphone/l=1/tc?clk_type=1&vit=osres&l=1&baiduid=96484127471D70DEC725E9206A612C56&t=iphone&ref=www_iphone&from=1019311v&ssid=0&lid=15845977081861498325&bd_page_type=1&pu=usm%400%2Csz%401320_1001%2Cta%40iphone_2_15.0_19_25.5&order=1&fm=alop&extra=%7B%22auth_s%22%3A%222%22%2C%22is_officialu%22%3A1%7D&isAtom=1&waplogo=1&clk_info=%7B%22tplname%22%3A%22www_index%22%2C%22srcid%22%3A1539%2C%22jumpType%22%3A%22%22%2C%22urlsign%22%3A%2213748173475154659823%22%2C%22t%22%3A1753595801344%2C%22xpath%22%3A%22div-div(sgl_img)-article(sc_ala)-section-div-div(title)%22%7D&is_baidu=0&tj=www_index_1_0_10_title&cltj=normal_title&asres=1&phoneos=bd_search_iphone&wd=&eqid=dbe838334b55e5d5100000036885bf90&w_qd=IlPT2AEptyoA_ykzqhAd5xyuCVxPiXEa7VgYnhLV6vQtVwcyRUldtozgdQV8i_gTyP_&bdver=2_1&tcplug=1&dict=-1&sec=5309&di=5f919d109068c6c9&bdenc=1&nsrc=lMCOzHesDoaO24DE868dVnRoFvqUtOoq2bD1LgE0PKBzEqM9d%2FKabrV6UukdU18%2FmsRBGE%2BgoX5%2BP9xwHGw9tg%3D%3D&ck0=711&ck1=279&ck2=191&ck3=407&ck6=4&ck7=332&ala_anti=ck0%40711%2Cck1%40279%2Cck7%40332 备注： | I90: 2026财年第2财月易聊新东方官网M资讯站 | K90: 乔文娇 | L90: 新东方官网 | M90: 新东方官网M资讯站 | O90: 乔文娇 | P90: 2025-07-27 14:27:43 | Q90: 冯喆玄 | R90: 房国超 | S90: 29342865 | T90: 正常工单 | U90: 2025-07-27 15:02 | V90: A（六个月内有报课意向工单） | W90: 六级 | X90: 大二 | Y90: 中国民用航空飞行学院 | Z90: 空中交通管理学院 | AA90: 交通运输 | AB90: 冯喆玄 | AC90: 5524257 | AD90: 房国超 | AE90: 2025-07-28 16:50 | AF90: 房国超 | AG90: 2025-07-28 16:50 | AH90: YKS25005 | AI90: 六级精英计划（新大一专属） | AJ90: 国内考试 | AL90: 19800 | AO90: 新签 | AP90: 已交接 | AQ90: BJWY25030q8UPI | AR90: BJWY8505014128 | AS90: YKS250050012 | AT90: 2025-07-28 | AV90: 回访人：房国超，回访时间：2025-07-27 15:02，回访内容：家长咨询，学生刚考完四级 ，感觉可能能过线， 之前考过一次四级，没过， 住顺义， 想下午上课，推荐小班，；|回访人：房国超，回访时间：2025-07-28 16:50，回访内容：报名 | BA90: 82465638 | BB90: 否 | BC90: 25下考季 | BD90: 六级无忧计划 | BG90: 国内高校-双非 | BH90: 是 | BK90: 报名 | BM90: 本地人外地大学(归巢) | BN90: 易聊在线咨询
A91: 109 | B91: 北京大学部 | C91: 国内大学部 | D91: 俞佳平 | E91: 119844420 | F91: 北京国内管理员 | G91: 2025-07-20 18:44:08 | H91: 渠道录入来源：SCRM-客服推送 商机ID：5009296558 商机编码：XSJ20250720030375 针对人群：大学 学员号：BJ1947767496 学生学校：不详 咨询课程：英语 创建人邮箱：lichunshan@xdf.cn 创建时间：2025-07-20 18:44:02 资源类型：单个资源 跟进记录：商机备注： 【呼入组+57640860】家长给孩子咨询四级，同学高中毕业，高考英语120，考虑中关村校区，辛苦老师协助介绍，谢谢;接触点：呼入； | J91: 大一 | K91: 田一禾 | L91: 线上运营-投放 | M91: 总部-百度投放 | Q91: 俞博涵 | R91: 田一禾 | S91: 29227808 | T91: 正常工单 | U91: 2025-07-20 19:12 | V91: B（需长时间跟单或只需要规划） | W91: 四级,大学预科 | X91: 大一 | Y91: 新大一 | Z91: 新大一 | AA91: 新大一 | AB91: 俞博涵 | AC91: 5524130 | AD91: 田一禾 | AE91: 2025-07-28 15:31 | AF91: 田一禾 | AG91: 2025-07-28 15:33 | AH91: YKS25003 | AI91: 六级无忧计划（新大一专属） | AJ91: 国内考试 | AL91: 5680 | AO91: 新签 | AP91: 已交接 | AQ91: WebReg | AR91: BJWY5393725949 | AS91: YKS250030032 | AT91: 2025-07-28 | AV91: 回访人：田一禾，回访时间：2025-07-20 19:12，回访内容：孩子爸爸问，英语120+推荐六级，刷分保研需求，消费能力不确定，先跟进看看。；|回访人：田一禾，回访时间：2025-07-22 22:53，回访内容：邀约生涯规划课，暂时未回复。；|回访人：田一禾，回访时间：2025-07-25 22:33，回访内容：电话不接，考虑居多，下次不回复，先死单处理。；|回访人：田一禾，回访时间：2025-07-28 15:31，回访内容：今日签约 | BA91: 81970232 | BB91: 否 | BC91: 25下考季 | BD91: 四级无忧计划 | BG91: 普通学校-普高 | BH91: 是 | BI91: 家长不告知基本信息，后面附截图 | BK91: 报名 | BM91: 外地人本地大学(常规) | BN91: SCRM-客服推送
A92: 110 | B92: 北京大学部 | C92: 国内大学部 | D92: 未知 | E92: 120803719 | F92: 李雪68 | G92: 2025-07-25 17:32:03 | H92: 激活 | J92: 大一 | K92: 宋增辉 | L92: 转介绍 | M92: 内部员工推荐 | N92: 激活 | Q92: 张一 | R92: 宋增辉 | S92: 29363642 | T92: 正常工单 | U92: 2025-07-25 17:41 | V92: A（六个月内有报课意向工单） | W92: 六级,大学预科 | X92: 大一 | Y92: 西北工业大学 | Z92: 航空学院 | AA92: 航空航天工程 | AB92: 张一 | AC92: 5524113 | AD92: 宋增辉 | AE92: 2025-07-28 15:24 | AF92: 宋增辉 | AG92: 2025-07-28 15:25 | AH92: YKSJ25001 | AI92: 六级无忧计划（线上优享/新大一专属） | AJ92: 国内考试 | AL92: 5180 | AN92: 激活 | AO92: 新签 | AP92: 已交接 | AQ92: BJWY22035556hl | AR92: BJWY2560035766 | AS92: YKSJ250010061 | AT92: 2025-07-28 | AV92: 回访人：宋增辉，回访时间：2025-07-25 17:41，回访内容：已确定报名，发协议等待回复；|回访人：宋增辉，回访时间：2025-07-26 10:55，回访内容：微信询问情况，孩子只同意学习英语；|回访人：宋增辉，回访时间：2025-07-27 17:26，回访内容：不考虑学了，拒绝+1；|回访人：宋增辉，回访时间：2025-07-28 15:24，回访内容：已报名 | BA92: 81021031 | BB92: 否 | BC92: 25下考季 | BD92: 六级无忧计划 | BG92: 国内高校-985 | BH92: 是 | BK92: 报名 | BM92: 本地人外地大学(归巢) | BN92: 客服
A93: 111 | B93: 北京大学部 | C93: 国内大学部 | D93: 唐黎雪 | E93: 113732090 | F93: 陈自强 | G93: 2025-06-11 15:20:17 | H93: 高三家长资源，按毛坯数据话术回访即可，重点沟通大学预科以及四六级课程暑期学习重要性，引导了解 | I93: 批量导入-京内-渠道推荐-高三-陈自强-250611 | J93: 大一 | K93: 杨欢欢 | L93: 市场活动 | M93: 京内会销/讲座 | O93: 杨欢欢 | P93: 2025-07-27 16:29:34 | Q93: 焦冠叶 | R93: 黄智超 | S93: 29396675 | T93: 正常工单 | U93: 2025-07-27 16:45 | V93: A（六个月内有报课意向工单） | W93: 六级,大学预科 | X93: 大一 | Y93: 首都师范大学 | Z93: 国际文化学院 | AA93: 法语 | AB93: 焦冠叶 | AC93: 5524010 | AD93: 黄智超 | AE93: 2025-07-28 14:17 | AF93: 黄智超 | AG93: 2025-07-28 14:17 | AH93: YKS25003 | AI93: 六级无忧计划（新大一专属） | AJ93: 国内考试 | AL93: 5680 | AO93: 新签 | AP93: 已交接 | AQ93: WebReg | AR93: BJWY4224468841 | AS93: YKS250030028 | AT93: 2025-07-28 | AV93: 回访人：黄智超，回访时间：2025-07-27 16:45，回访内容：家长反馈孩子是129分，平时135分，推荐六级班8.4-8.16号开班的，跟孩子商量一下 等家长加我的微信；|回访人：黄智超，回访时间：2025-07-28 14:17，回访内容：已签约 5680 预科六级大班 8.4开课 | BA93: 79449883 | BB93: 否 | BC93: 25下考季 | BD93: 六级无忧计划 | BG93: 国内高校-中外合作办学 | BH93: 是 | BK93: 报名 | BM93: 本地人本地大学(常规) | BN93: 市场
A94: 112 | B94: 北京大学部 | C94: 国内大学部 | D94: 北京市5524 | E94: 119919867 | F94: 杨俊42(国内) | G94: 2025-07-20 08:39:27 | H94: 渠道录入来源：新东方官网M站-客服 意向城市：北京访客省/城市：北京市 访客静态ID：01000000034659297177568814685524 接待分组ID：70455 搜索引擎： 搜索词： 关键词： 设备类型：phone 访客IP：223.104.40.207 对话详细内容：AI-Lbo0rDBXCyBY 2025-07-20 08:36:16_x000D_ 您好同学,欢迎访问北京新东方考研四六级中心. 考研线下课程26/27考季【考研全年集训营】【考研半年集训营】【考研全科线下走读班】【考研寒/暑假集训营】【考研一对一】【考研专业课】【四/六级课程】，热门课程火热报名中,咨询即可领取专享优惠。 **【考研全年集训营】=ff761f# **【考研半年集训营】=ff6b6b# **【考研全科线下走读班】=ffc158# **【考研寒/暑假集训营】=ffc158# **【考研一对一】=ff761f# **【考研专业课】=ff6caa# **【四/六级课程】=ff6caa# **【考研冲刺班】=60e27e#_x000D_ _x000D_ AI-Lbo0rDBXCyBY 2025-07-20 08:36:19_x000D_ 您是想咨询【线下课程】【线上课程】【考研规划】还是【在职考研】呢？**【线下课程】# **【线上课程】#**【考研规划】#**【在职考研】#_x000D_ _x000D_ 01000000034659297177568814685524 2025-07-20 08:36:24_x000D_ 【线下课程】_x000D_ _x000D_ AI-Lbo0rDBXCyBY 2025-07-20 08:36:28_x000D_ 同学，你现在是在校还是在职呢？_x000D_ _x000D_ 01000000034659297177568814685524 2025-07-20 08:36:30_x000D_ 四六级考试_x000D_ _x000D_ AI-Lbo0rDBXCyBY 2025-07-20 08:36:34_x000D_ 您目前在学的院校是哪所呢？_x000D_ _x000D_ 01000000034659297177568814685524 2025-07-20 08:36:53_x000D_ 高考刚结束_x000D_ _x000D_ AI-Lbo0rDBXCyBY 2025-07-20 08:36:57_x000D_ 您目前英语基础如何呢？_x000D_ _x000D_ 01000000034659297177568814685524 2025-07-20 08:37:08_x000D_ 不是很好_x000D_ _x000D_ AI-Lbo0rDBXCyBY 2025-07-20 08:37:12_x000D_ 这样，您微信还是电话方便呢？我安排四六级老师联系您，将课程的详细内容介绍给您_x000D_ _x000D_ 01000000034659297177568814685524 2025-07-20 08:37:26_x000D_ 13451360166这是我的微信_x000D_ _x000D_ AI-Lbo0rDBXCyBY 2025-07-20 08:37:29_x000D_ 好的，确认一下您的号码是否正确呢？_x000D_ _x000D_ 01000000034659297177568814685524 2025-07-20 08:37:38_x000D_ 正确_x000D_ _x000D_ AI-Lbo0rDBXCyBY 2025-07-20 08:37:41_x000D_ 同学怎么称呼呢？_x000D_ _x000D_ 01000000034659297177568814685524 2025-07-20 08:38:10_x000D_ 姓张_x000D_ _x000D_ AI-Lbo0rDBXCyBY 2025-07-20 08:38:14_x000D_ 好的，由于今天课程规划老师还没有上班，这边安排老师上午9点后给您回电请注意接听~_x000D_ _x000D_ 01000000034659297177568814685524 2025-07-20 08:38:23_x000D_ 好的_x000D_ _x000D_ AI-Lbo0rDBXCyBY 2025-07-20 08:38:26_x000D_ 嗯嗯_x000D_ _x000D_ 来源页：https://click.xdf.cn/ 备注： | I94: 2026财年第2财月易聊新东方官网M站 | K94: 王静静 | L94: 新东方官网 | M94: 新东方官网M站 | O94: 王静静 | P94: 2025-07-20 15:07:30 | Q94: 张硕 | R94: 刘晓娟 | S94: 29224817 | T94: 正常工单 | U94: 2025-07-20 15:15 | V94: A（六个月内有报课意向工单） | W94: 四级,大学预科 | X94: 高三 | Y94: 通州区甘棠中学 | Z94: 新大一 | AA94: 新大一 | AB94: 张硕 | AC94: 5523939 | AD94: 刘晓娟 | AE94: 2025-07-28 12:52 | AF94: 刘晓娟 | AG94: 2025-07-28 12:53 | AH94: YKF25007 | AI94: 四级无忧计划 | AJ94: 国内考试 | AL94: 5180 | AO94: 新签 | AP94: 已交接 | AQ94: BJWY22035556hl | AR94: BJWY1785756253 | AS94: YKF250070023 | AT94: 2025-07-28 | AV94: 回访人：刘晓娟，回访时间：2025-07-20 15:15，回访内容：孩子母亲咨询，孩子刚高考完，成绩50-60，想看看四级线下的课程，介绍大班，小班和一对一，稍后通过我微信，发送课程安排；|回访人：刘晓娟，回访时间：2025-07-22 13:12，回访内容：微信留言，确认意向；|回访人：刘晓娟，回访时间：2025-07-26 11:17，回访内容：接通了，说是准备报，但是现在有事，晚点找我；|回访人：刘晓娟，回访时间：2025-07-28 12:52，回访内容：报名 | BA94: 82053941 | BB94: 否 | BC94: 25下考季 | BD94: 四级无忧计划 | BG94: 普通学校-普高 | BH94: 是 | BK94: 报名 | BM94: 本地人本地大学(常规) | BN94: 易聊在线咨询
A95: 113 | B95: 北京大学部 | C95: 国内大学部 | D95: 赵泽润同学 | E95: 120690701 | F95: 段同飞 | G95: 2025-07-25 19:24:33 | H95: 宋增辉老师老带新 | J95: 大一 | K95: 宋增辉 | L95: 转介绍 | M95: 顾问转介绍-老带新 | N95: 宋增辉songzenghui@xdf.cn | Q95: 赵泽润 | R95: 宋增辉 | S95: 29324646 | T95: 正常工单 | U95: 2025-07-25 19:34 | V95: B（需长时间跟单或只需要规划） | W95: 六级,其他,大学预科 | X95: 大一 | Y95: 北京工业大学 | Z95: 理学部 | AA95: 应用物理学 | AB95: 赵泽润 | AC95: 5496248 | AD95: 宋增辉 | AE95: 2025-07-28 15:29 | AF95: 宋增辉 | AG95: 2025-07-28 15:29 | AH95: YKS25003 | AI95: 六级无忧计划（新大一专属） | AJ95: 国内考试 | AL95: 4634.3 | AN95: 宋增辉 | AO95: 新签 | AP95: 已交接 | AQ95: BJWY22035556hl | AR95: BJWY8482657226 | AS95: YKS250030029 | AT95: 2025-07-28 | AV95: 回访人：宋增辉，回访时间：2025-07-25 19:34，回访内容：马上报名。正在发协议；|回访人：宋增辉，回访时间：2025-07-26 10:54，回访内容：昨晚没有和孩子商量，中午给结果 总结：客户赵泽润初步决定报名六级大班课程，原价5980元，优惠800元后价格为5180元。客户已提供基本信息，包括姓名、性别、听课手机号、院校、专业年级及紧急联系人手机号。课程将于8月4日开始，客户将通过微信支付费用。客户还询问了关于优惠和退班制度的具体情况，特别是关于老带新优惠和退班费用的计算方式。客户表示需要与孩子进一步确认后再决定是否签署协议。 下次回访建议：在客户与孩子确认后，及时跟进客户的最终决定。如果客户确认报名，协助完成协议签署和支付流程。如果客户有任何疑问或需要进一步了解优惠和退班制度，提供详细解答。同时，确认客户是否对课程安排和教材有任何特殊需求，确保客户对课程内容和服务有充分了解。；|回访人：宋增辉，回访时间：2025-07-28 15:29，回访内容：已报名 | BA95: 75244328 | BB95: 否 | BC95: 25下考季 | BD95: 六级无忧计划 | BG95: 国内高校-211 | BH95: 是 | BK95: 报名 | BM95: 本地人本地大学(常规) | BN95: 客服
A96: 114 | B96: 北京大学部 | C96: 国内大学部 | D96: 赵泽润同学 | E96: 120690701 | F96: 段同飞 | G96: 2025-07-25 19:24:33 | H96: 宋增辉老师老带新 | J96: 大一 | K96: 宋增辉 | L96: 转介绍 | M96: 顾问转介绍-老带新 | N96: 宋增辉songzenghui@xdf.cn | Q96: 赵泽润 | R96: 宋增辉 | S96: 29324646 | T96: 正常工单 | U96: 2025-07-25 19:34 | V96: B（需长时间跟单或只需要规划） | W96: 六级,其他,大学预科 | X96: 大一 | Y96: 北京工业大学 | Z96: 理学部 | AA96: 应用物理学 | AB96: 赵泽润 | AC96: 5496248 | AD96: 宋增辉 | AE96: 2025-07-28 15:29 | AF96: 宋增辉 | AG96: 2025-07-28 15:29 | AH96: YKM25002 | AI96: 大学预科数学（新大一专属） | AJ96: 国内考试 | AL96: 4525.7 | AN96: 宋增辉 | AO96: 新签 | AP96: 已交接 | AQ96: BJWY22035556hl | AR96: BJWY8482657226 | AS96: YKM250020049 | AT96: 2025-07-28 | AV96: 回访人：宋增辉，回访时间：2025-07-25 19:34，回访内容：马上报名。正在发协议；|回访人：宋增辉，回访时间：2025-07-26 10:54，回访内容：昨晚没有和孩子商量，中午给结果 总结：客户赵泽润初步决定报名六级大班课程，原价5980元，优惠800元后价格为5180元。客户已提供基本信息，包括姓名、性别、听课手机号、院校、专业年级及紧急联系人手机号。课程将于8月4日开始，客户将通过微信支付费用。客户还询问了关于优惠和退班制度的具体情况，特别是关于老带新优惠和退班费用的计算方式。客户表示需要与孩子进一步确认后再决定是否签署协议。 下次回访建议：在客户与孩子确认后，及时跟进客户的最终决定。如果客户确认报名，协助完成协议签署和支付流程。如果客户有任何疑问或需要进一步了解优惠和退班制度，提供详细解答。同时，确认客户是否对课程安排和教材有任何特殊需求，确保客户对课程内容和服务有充分了解。；|回访人：宋增辉，回访时间：2025-07-28 15:29，回访内容：已报名 | BA96: 75244328 | BB96: 否 | BC96: 25下考季 | BD96: 六级无忧计划 | BG96: 国内高校-211 | BH96: 是 | BK96: 报名 | BM96: 本地人本地大学(常规) | BN96: 客服
A97: 115 | B97: 北京大学部 | C97: 国内大学部 | D97: 五谷丰登 | E97: 120896355 | F97: 郭欣宇 | G97: 2025-07-26 21:40:24 | H97: 18201023802，北京，四级小班课或者集训 | J97: 未知 | K97: 黄智超 | L97: 线上运营-投放 | M97: 巨量广告 | Q97: 谷浩宇 | R97: 黄智超 | S97: 29341986 | T97: 正常工单 | U97: 2025-07-27 10:55 | V97: A（六个月内有报课意向工单） | W97: 四级 | X97: 大二 | Y97: 北京警察学院 | Z97: 侦查系 | AA97: 侦查学 | AB97: 谷浩宇 | AC97: 5496182 | AD97: 黄智超 | AE97: 2025-07-28 14:47 | AF97: 黄智超 | AG97: 2025-07-28 14:48 | AH97: YKF25007 | AI97: 四级无忧计划 | AJ97: 国内考试 | AL97: 5680 | AO97: 新签 | AP97: 已交接 | AQ97: WebReg | AR97: BJWY1003907538 | AS97: YKF250070025 | AT97: 2025-07-28 | AV97: 回访人：黄智超，回访时间：2025-07-27 10:55，回访内容：学生咨询暑假四级课程 告知大班 小班的课程安排 添加微信 发送详细介绍 谷浩宇；|回访人：黄智超，回访时间：2025-07-28 14:47，回访内容：等线下报名缴费；|回访人：黄智超，回访时间：2025-07-28 14:47，回访内容：已签约报名～5680元8.4开课四级班 | BA97: 82488206 | BB97: 否 | BC97: 25下考季 | BD97: 四级无忧计划 | BG97: 国内高校-双非 | BH97: 是 | BK97: 报名 | BM97: 本地人本地大学(常规) | BN97: 市场
A98: 116 | B98: 北京大学部 | C98: 国内大学部 | D98: 康康 | E98: 116756527 | F98: 北京国内管理员 | G98: 2025-06-30 15:41:31 | H98: 渠道录入来源：SCRM-客服推送 商机ID：5009142906 商机编码：XSJ20250630021534 针对人群：高中 学员号：BJ5711910286 咨询课程：英语 创建人邮箱：wenhuan3@xdf.cn 创建时间：2025-06-30 14:28:50 资源类型：单个资源 跟进记录：商机备注：【北京课程】北京考生，高考成绩是115分，想报考英语专业，希望在暑期英语能力提升，简单介绍了四级和口语集训，家长希望进一步了解。康亚文，手机号137****2649。;接触点：微信； | J98: 高三 | K98: 刘晓娟 | L98: 线上运营-私域中台 | M98: 公众号 | Q98: 康亚文 | R98: 刘晓娟 | S98: 28729609 | T98: 正常工单 | U98: 2025-07-28 12:52 | V98: A（六个月内有报课意向工单） | W98: 四级,大学预科 | X98: 高三 | Y98: 北京东城综合中学 | Z98: 新大一 | AA98: 新大一 | AB98: 康亚文 | AC98: 5496044 | AD98: 刘晓娟 | AE98: 2025-07-28 12:54 | AF98: 刘晓娟 | AG98: 2025-07-28 12:54 | AH98: YKF25007 | AI98: 四级无忧计划 | AJ98: 国内考试 | AL98: 5180 | AO98: 新签 | AP98: 已交接 | AQ98: BJWY22035556hl | AR98: BJWY7717404064 | AS98: YKF250070022 | AT98: 2025-07-28 | AV98: 回访人：刘晓娟，回访时间：2025-07-25 18:17，回访内容：近期想安排上课，介绍28的班级，考虑下；|回访人：刘晓娟，回访时间：2025-07-28 12:49，回访内容：报名；|回访人：段同飞，回访时间：2025-07-28 12:52，回访内容：段同飞恢复工单, 系统自动生成回访记录!；|回访人：刘晓娟，回访时间：2025-07-28 12:54，回访内容：报名 | BA98: 74897890 | BB98: 否 | BC98: 25下考季 | BD98: 四级无忧计划 | BG98: 普通学校-普高 | BH98: 是 | BK98: 报名 | BM98: 本地人本地大学(常规) | BN98: SCRM-客服推送
A99: 117 | B99: 北京大学部 | C99: 国内大学部 | D99: 毛毛球球 | E99: 120309854 | F99: 王朝群 | G99: 2025-07-23 09:13:27 | H99: 【王朝群】咨询四六级暑期班 | I99: 2026财年第2财月小红书 | J99: 大二 | K99: 张博奥 | L99: 线上运营-小红书 | M99: 小红书 | Q99: 张珈瑄 | R99: 张博奥 | S99: 29272627 | T99: 正常工单 | U99: 2025-07-23 17:07 | V99: A（六个月内有报课意向工单） | W99: 四级,大学预科 | X99: 大一 | Y99: 北京农学院 | Z99: 动物科学技术学院 | AA99: 动物科学 | AB99: 张珈瑄 | AC99: 5495981 | AD99: 张博奥 | AE99: 2025-07-28 11:50 | AF99: 张博奥 | AG99: 2025-07-28 11:52 | AH99: YKFJ25001 | AI99: 四级无忧计划（线上优享/新大一专属） | AJ99: 国内考试 | AL99: 5680 | AO99: 新签 | AP99: 已交接 | AQ99: BJWY2011wXCx1W | AR99: BJWY7182729111 | AS99: YKFJ250010101 | AT99: 2025-07-28 | AV99: 回访人：张博奥，回访时间：2025-07-23 17:07，回访内容：家长咨询四级课程，学生基础一般，家长比较意向小班课，持续跟进；|回访人：张博奥，回访时间：2025-07-25 21:21，回访内容：询问家长的意向，意向小班，微信没有回复；|回访人：张博奥，回访时间：2025-07-28 11:50，回访内容：已报名 | BA99: 82216787 | BB99: 否 | BC99: 25下考季 | BD99: 四级无忧计划 | BG99: 普通学校-普高 | BH99: 是 | BI99: 学生今天晚上线上有课，辛苦学管老师加紧联系学生，并邮寄教材讲义和一本四级词汇书 | BK99: 报名 | BM99: 本地人本地大学(常规) | BN99: 小红书
A100: 118 | B100: 北京大学部 | C100: 国内大学部 | D100: 李志谦 | E100: 116395608 | F100: 北京国内管理员 | G100: 2025-06-27 10:30:04 | H100: 渠道录入来源：SCRM-客服推送 商机ID：5009159324 商机编码：XSJ20250627008919 针对人群：高中 学员号：BJ2672498 学生学校：不详 咨询课程：专业课 创建人邮箱：zhaochenghao@xdf.cn 创建时间：2025-06-27 10:29:57 资源类型：单个资源 跟进记录：商机备注：孩子妈妈来电，九月份新大一，说孩子考的是警校，想提前规划下考研，告知目前针对新大一有专门的预科，家长让都介绍下，辛苦老师对接下;接触点：呼入； | J100: 高三 | K100: 刘晓娟 | L100: 新东方官网 | M100: 新东方PC官网 | Q100: 李志谦 | R100: 刘晓娟 | S100: 28660701 | T100: 正常工单 | U100: 2025-06-27 10:56 | V100: A（六个月内有报课意向工单） | W100: 四级,大学预科 | X100: 高三 | Y100: 北京东城综合中学 | Z100: 新大一 | AA100: 新大一 | AB100: 李志谦 | AC100: 5495902 | AD100: 刘晓娟 | AE100: 2025-07-28 10:48 | AF100: 刘晓娟 | AG100: 2025-07-28 12:06 | AH100: WYF25042 | AI100: 四级无忧计划 | AJ100: 国内考试 | AL100: 6180 | AO100: 新签 | AP100: 已交接 | AQ100: BJWY2011wXCx1W | AR100: BJWY7886868512 | AS100: WYF250420009 | AT100: 2025-07-28 | AV100: 回访人：刘晓娟，回访时间：2025-07-22 14:47，回访内容：接通，考虑秋季四级线下的课程，介绍大班和小班，考虑下；|回访人：刘晓娟，回访时间：2025-07-28 10:48，回访内容：报名 | BA100: 80616813 | BB100: 否 | BC100: 25下考季 | BD100: 四级无忧计划 | BG100: 普通学校-普高 | BH100: 是 | BK100: 报名 | BM100: 本地人本地大学(常规) | BN100: SCRM-客服推送
...

Sheet 四六级业绩进账-数据透视
A1: 签约单录入人 | B1: 求和项:学费
A2: 房国超 | B2: 976589.7
A3: 黄智超 | B3: 1225176.4
A4: 刘晓娟 | B4: 1396995.6
A5: 宋增辉 | B5: 878316.7
A6: 田一禾 | B6: 758217.95
A7: 张博奥 | B7: 418279

Sheet 转介绍进账
A1: 序号 | B1: 学校 | C1: 部门 | D1: 资源姓名 | E1: 资源ID | F1: 资源录入人 | G1: 资源录入时间 | H1: 资源描述 | I1: 市场活动 | J1: 资源年级 | K1: 分配顾问/TMK | L1: 一级获取渠道 | M1: 二级获取渠道 | N1: 转介绍人 | O1: TMK激活人 | P1: TMK激活处理时间 | Q1: 工单姓名 | R1: 跟进顾问 | S1: 工单ID | T1: 工单类型 | U1: 工单录入时间 | V1: 工单等级 | W1: 咨询课程 | X1: 工单年级 | Y1: 学校 | Z1: 院系 | AA1: 专业 | AB1: 签约学生姓名 | AC1: 签约单ID | AD1: 签约单录入人 | AE1: 备注 | AF1: 签约单录入时间 | AG1: 签约单更新人 | AH1: 签约单更新时间 | AI1: 班号 | AJ1: 班级名称 | AK1: 面询表类型 | AL1: 订金 | AM1: 学费 | AN1: 续费类型 | AO1: 推荐人 | AP1: 类型 | AQ1: 是否交接 | AR1: 操作人编号 | AS1: 学员号 | AT1: 听课证号 | AU1: 报班日期 | AV1: 学员状态 | AW1: 回访记录 | AX1: 新老生类型 | AY1: 退费金额 | AZ1: 退费日期 | BA1: 课程类型 | BB1: 客户ID | BC1: 是否新东方在线签约 | BD1: 考季 | BE1: 报名产品 | BF1: 报名科目 | BG1: 意向报考专业 | BH1: 学校班型/类型 | BI1: 是否关联协议 | BJ1: 特殊备注 | BK1: 产品品类 | BL1: 业务类型 | BM1: 签约列表在线学员ID | BN1: 大学生源类型 | BO1: 资源来源
A2: 2 | B2: 北京大学部 | C2: 国内大学部 | D2: 老带新用户 | E2: 119497203 | F2: 黄智超 | G2: 2025-07-16 23:30:44 | H2: 渠道录入来源：老带新系统 老生userid：385b6138-50b9-4f54-ba17-69594722a147 老生学号：BJWY7771366384 老生姓名：肖遥 产品类型：1 活动所属学校名称：北京大学事业部 老带新活动名称：邀好友，大家一起来省钱（班课专用）新 老带新活动id：2366032 推广邮箱：huangzhichao1@xdf.cn | I2: 2026财年第2财月老带新系统 | K2: 黄智超 | L2: 转介绍 | M2: 老带新系统顾问 | N2: 黄智超huangzhichao1@xdf.cn | Q2: 郑文予 | R2: 黄智超 | S2: 29188775 | T2: 正常工单 | U2: 2025-07-17 15:51 | V2: A（六个月内有报课意向工单） | W2: 六级 | X2: 大一 | Y2: 北京市第五十中学 | Z2: 新大一 | AA2: 新大一 | AB2: 郑文予 | AC2: 5415253 | AD2: 黄智超 | AF2: 2025-07-17 16:10 | AG2: 黄智超 | AH2: 2025-07-25 13:36 | AI2: YKS25002 | AJ2: 六级无忧计划（新大一专属） | AK2: 国内考试 | AM2: 5480 | AO2: 黄智超 | AP2: 新签 | AQ2: 已交接 | AR2: WebReg | AS2: BJWY3837265523 | AT2: YKS250020026 | AU2: 2025-07-17 | AW2: 回访人：黄智超，回访时间：2025-07-17 15:51，回访内容：准备和肖遥同学一起报名暑假6级预科二班；|回访人：黄智超，回访时间：2025-07-17 16:10，回访内容：报名暑假预科六级二班（肖遥的同学）YKS25002 | BB2: 81849719 | BC2: 否 | BD2: 25下考季 | BE2: 六级无忧计划 | BH2: 普通学校-普高 | BI2: 否 | BL2: 报名 | BN2: 本地人本地大学(常规) | BO2: 老带新系统
A3: 3 | B3: 北京大学部 | C3: 国内大学部 | D3: 张敏 | E3: 118960010 | F3: 杨沫 | G3: 2025-07-14 09:42:07 | H3: 黄智超 | J3: 大学已毕业 | K3: 黄智超 | L3: 转介绍 | M3: 顾问转介绍-新带新 | N3: 张晴 | Q3: 张敏 | R3: 黄智超 | S3: 28993241 | T3: 正常工单 | U3: 2025-07-14 09:54 | V3: A（六个月内有报课意向工单） | W3: 专升本 | X3: 大学已毕业 | Y3: 北京工业职业技术学院 | Z3: 电子科技 | AA3: 电子信息 | AB3: 张敏 | AC3: 5479462 | AD3: 黄智超 | AF3: 2025-07-14 11:44 | AG3: 黄智超 | AH3: 2025-07-14 11:53 | AI3: 24419587709 | AJ3: 26通用专升本慧学班-英语 | AK3: 国内考试 | AM3: 1999 | AO3: 张晴 | AP3: 新签 | AQ3: 无须交接 | AU3: 2025-07-14 | AW3: 回访人：黄智超，回访时间：2025-07-14 09:54，回访内容： 张晴同学的表姐，专升本的推荐一对一和网课，预计报名英语网课；|回访人：黄智超，回访时间：2025-07-19 08:09，回访内容：给学生邮寄了4级单词书，维护一下，学生非常开心。 | BA3: 长期班 | BB3: 81656739 | BC3: 是 | BD3: 26考季 | BE3: 专升本全科全程班 | BF3: 英语 | BH3: 国内高校-大专 | BI3: 否 | BM3: 110536506 | BO3: 客服
A4: 4 | B4: 北京大学部 | C4: 国内大学部 | D4: 未知 | E4: 114207297 | F4: 李雪68 | G4: 2025-06-13 17:22:01 | H4: 激活 | J4: 大四 | K4: 刘晓娟 | L4: 转介绍 | M4: 顾问转介绍-老带新 | N4: 激活 | Q4: 张裾扬 | R4: 刘晓娟 | S4: 28327261 | T4: 正常工单 | U4: 2025-06-13 17:38 | V4: A（六个月内有报课意向工单） | W4: 专八 | X4: 大四 | Y4: 中国石油大学(北京) | Z4: 英语 | AA4: 英语 | AB4: 张裾扬 | AC4: 5439737 | AD4: 刘晓娟 | AF4: 2025-07-05 15:42 | AG4: 刘晓娟 | AH4: 2025-07-05 15:42 | AI4: 16684991291 | AJ4: 2026英语专业八级全程班【直播 + 录播】 | AK4: 国内考试 | AM4: 1529.15 | AO4: 激活 | AP4: 新签 | AQ4: 无须交接 | AU4: 2025-07-05 | AW4: 回访人：刘晓娟，回访时间：2025-06-27 18:19，回访内容：等放假再报；|回访人：刘晓娟，回访时间：2025-07-04 18:31，回访内容：确认放假时间，等回复；|回访人：刘晓娟，回访时间：2025-07-05 15:42，回访内容：报名 | BA4: 长期班 | BB4: 67366752 | BC4: 是 | BH4: 国内高校-211 | BI4: 否 | BM4: 110483407 | BN4: 本地人本地大学(常规) | BO4: 客服
A5: 5 | B5: 北京大学部 | C5: 国内大学部 | E5: 118539803 | G5: 2025-07-10 13:20:09 | H5: 黄智超1的顾问转介绍工单 | J5: 大一 | K5: 黄智超 | L5: 转介绍 | M5: 顾问转介绍-老带新 | Q5: 王祎 | R5: 黄智超 | S5: 29170004 | T5: 续费工单 | U5: 2025-07-21 13:44 | V5: A（六个月内有报课意向工单） | W5: 四级,大学预科 | X5: 大一 | Y5: 北京第一六六中学（166中学） | Z5: 询问院系未告知 | AA5: 询问专业未告知 | AB5: 王祎 | AC5: 5487156 | AD5: 黄智超 | AE5: 转班不算 | AF5: 2025-07-21 13:45 | AG5: 黄智超 | AH5: 2025-07-21 13:46 | AI5: YKFJ25001 | AJ5: 四级无忧计划（线上优享/新大一专属） | AK5: 国内考试 | AM5: 0 | AN5: 同科续费 | AO5: 邵嘉凡 | AP5: 续班 | AQ5: 未交接 | AR5: BJWY25030q8UPI | AS5: BJWY1508600205 | AT5: YKFJ250010055 | AU5: 2025-07-12 | AW5: 回访人：黄智超，回访时间：2025-07-21 13:44，回访内容：转班；|回访人：黄智超，回访时间：2025-07-21 13:45，回访内容：转班 | BB5: 81453845 | BC5: 否 | BD5: 25下考季 | BE5: 四级无忧计划 | BH5: 普通学校-普高 | BI5: 否 | BL5: 转出 | BN5: 本地人本地大学(常规)
A6: 6 | B6: 北京大学部 | C6: 国内大学部 | D6: 付建行 | E6: 121422640 | F6: 段同飞 | G6: 2025-07-30 16:26:09 | H6: 张子杰同学推荐 | J6: 大一 | K6: 张博奥 | L6: 转介绍 | M6: 顾问转介绍-老带新 | N6: 张博奥zhangboao@xdf.cn | Q6: 付建行 | R6: 张博奥 | S6: 29431034 | T6: 正常工单 | U6: 2025-07-30 16:28 | V6: A（六个月内有报课意向工单） | W6: 六级 | X6: 大一 | Y6: 北京信息科技大学 | Z6: 信息管理学院 | AA6: 信息安全 | AB6: 付建行 | AC6: 5498706 | AD6: 张博奥 | AF6: 2025-07-30 19:56 | AG6: 张博奥 | AH6: 2025-07-30 19:57 | AI6: YKS25003 | AJ6: 六级无忧计划（新大一专属） | AK6: 国内考试 | AM6: 4880 | AO6: 张博奥 | AP6: 新签 | AQ6: 已交接 | AR6: BJWY2101498uW2 | AS6: BJWY8488037202 | AT6: YKS250030036 | AU6: 2025-07-30 | AW6: 回访人：张博奥，回访时间：2025-07-30 16:28，回访内容：准备报名；|回访人：张博奥，回访时间：2025-07-30 19:56，回访内容：已报名 | BB6: 82539414 | BC6: 否 | BD6: 25下考季 | BE6: 六级无忧计划 | BH6: 国内高校-双非 | BI6: 是 | BJ6: 辛苦学管老师尽快联系学生并发送导学课 | BL6: 报名 | BN6: 本地人外地大学(归巢) | BO6: 客服
A7: 7 | B7: 北京大学部 | C7: 国内大学部 | D7: 同学 | E7: 120969074 | F7: 吴凯龙 | G7: 2025-07-28 10:25:32 | H7: 刘晓娟的顾问转介绍工单 | J7: 大一 | K7: 刘晓娟 | L7: 转介绍 | M7: 顾问转介绍-老带新 | N7: 刘晓娟liuxiaojuan@xdf.cn | Q7: 罗杰夫 | R7: 刘晓娟 | S7: 29380913 | T7: 正常工单 | U7: 2025-07-28 10:30 | V7: A（六个月内有报课意向工单） | W7: 四级,大学预科 | X7: 高三 | Y7: 北京石景山区实验中学 | Z7: 新大一 | AA7: 新大一 | AB7: 罗杰夫 | AC7: 5498561 | AD7: 刘晓娟 | AF7: 2025-07-30 18:16 | AG7: 刘晓娟 | AH7: 2025-07-30 18:16 | AI7: YKS25003 | AJ7: 六级无忧计划（新大一专属） | AK7: 国内考试 | AM7: 5180 | AO7: 刘晓娟 | AP7: 新签 | AQ7: 已交接 | AR7: BJWY24032w1g8X | AS7: BJWY6865910226 | AT7: YKS250030037 | AU7: 2025-07-30 | AW7: 回访人：刘晓娟，回访时间：2025-07-28 10:30，回访内容：家长拉群，咨询，新大一，想看看暑假四级的课程，介绍8月4日的四级班；|回访人：刘晓娟，回访时间：2025-07-30 18:16，回访内容：报名 | BB7: 82478037 | BC7: 否 | BD7: 25下考季 | BE7: 四级无忧计划 | BH7: 普通学校-普高 | BI7: 是 | BL7: 报名 | BN7: 本地人本地大学(常规) | BO7: 客服
A8: 8 | B8: 北京大学部 | C8: 国内大学部 | D8: 赵泽润同学 | E8: 120690701 | F8: 段同飞 | G8: 2025-07-25 19:24:33 | H8: 宋增辉老师老带新 | J8: 大一 | K8: 宋增辉 | L8: 转介绍 | M8: 顾问转介绍-老带新 | N8: 宋增辉songzenghui@xdf.cn | Q8: 赵泽润 | R8: 宋增辉 | S8: 29324646 | T8: 正常工单 | U8: 2025-07-25 19:34 | V8: B（需长时间跟单或只需要规划） | W8: 六级,其他,大学预科 | X8: 大一 | Y8: 北京工业大学 | Z8: 理学部 | AA8: 应用物理学 | AB8: 赵泽润 | AC8: 5496248 | AD8: 宋增辉 | AF8: 2025-07-28 15:29 | AG8: 宋增辉 | AH8: 2025-07-28 15:29 | AI8: YKS25003 | AJ8: 六级无忧计划（新大一专属） | AK8: 国内考试 | AM8: 4634.3 | AO8: 宋增辉 | AP8: 新签 | AQ8: 已交接 | AR8: BJWY22035556hl | AS8: BJWY8482657226 | AT8: YKS250030029 | AU8: 2025-07-28 | AW8: 回访人：宋增辉，回访时间：2025-07-25 19:34，回访内容：马上报名。正在发协议；|回访人：宋增辉，回访时间：2025-07-26 10:54，回访内容：昨晚没有和孩子商量，中午给结果 总结：客户赵泽润初步决定报名六级大班课程，原价5980元，优惠800元后价格为5180元。客户已提供基本信息，包括姓名、性别、听课手机号、院校、专业年级及紧急联系人手机号。课程将于8月4日开始，客户将通过微信支付费用。客户还询问了关于优惠和退班制度的具体情况，特别是关于老带新优惠和退班费用的计算方式。客户表示需要与孩子进一步确认后再决定是否签署协议。 下次回访建议：在客户与孩子确认后，及时跟进客户的最终决定。如果客户确认报名，协助完成协议签署和支付流程。如果客户有任何疑问或需要进一步了解优惠和退班制度，提供详细解答。同时，确认客户是否对课程安排和教材有任何特殊需求，确保客户对课程内容和服务有充分了解。；|回访人：宋增辉，回访时间：2025-07-28 15:29，回访内容：已报名 | BB8: 75244328 | BC8: 否 | BD8: 25下考季 | BE8: 六级无忧计划 | BH8: 国内高校-211 | BI8: 是 | BL8: 报名 | BN8: 本地人本地大学(常规) | BO8: 客服
A9: 9 | B9: 北京大学部 | C9: 国内大学部 | D9: 赵泽润同学 | E9: 120690701 | F9: 段同飞 | G9: 2025-07-25 19:24:33 | H9: 宋增辉老师老带新 | J9: 大一 | K9: 宋增辉 | L9: 转介绍 | M9: 顾问转介绍-老带新 | N9: 宋增辉songzenghui@xdf.cn | Q9: 赵泽润 | R9: 宋增辉 | S9: 29324646 | T9: 正常工单 | U9: 2025-07-25 19:34 | V9: B（需长时间跟单或只需要规划） | W9: 六级,其他,大学预科 | X9: 大一 | Y9: 北京工业大学 | Z9: 理学部 | AA9: 应用物理学 | AB9: 赵泽润 | AC9: 5496248 | AD9: 宋增辉 | AF9: 2025-07-28 15:29 | AG9: 宋增辉 | AH9: 2025-07-28 15:29 | AI9: YKM25002 | AJ9: 大学预科数学（新大一专属） | AK9: 国内考试 | AM9: 4525.7 | AO9: 宋增辉 | AP9: 新签 | AQ9: 已交接 | AR9: BJWY22035556hl | AS9: BJWY8482657226 | AT9: YKM250020049 | AU9: 2025-07-28 | AW9: 回访人：宋增辉，回访时间：2025-07-25 19:34，回访内容：马上报名。正在发协议；|回访人：宋增辉，回访时间：2025-07-26 10:54，回访内容：昨晚没有和孩子商量，中午给结果 总结：客户赵泽润初步决定报名六级大班课程，原价5980元，优惠800元后价格为5180元。客户已提供基本信息，包括姓名、性别、听课手机号、院校、专业年级及紧急联系人手机号。课程将于8月4日开始，客户将通过微信支付费用。客户还询问了关于优惠和退班制度的具体情况，特别是关于老带新优惠和退班费用的计算方式。客户表示需要与孩子进一步确认后再决定是否签署协议。 下次回访建议：在客户与孩子确认后，及时跟进客户的最终决定。如果客户确认报名，协助完成协议签署和支付流程。如果客户有任何疑问或需要进一步了解优惠和退班制度，提供详细解答。同时，确认客户是否对课程安排和教材有任何特殊需求，确保客户对课程内容和服务有充分了解。；|回访人：宋增辉，回访时间：2025-07-28 15:29，回访内容：已报名 | BB9: 75244328 | BC9: 否 | BD9: 25下考季 | BE9: 六级无忧计划 | BH9: 国内高校-211 | BI9: 是 | BL9: 报名 | BN9: 本地人本地大学(常规) | BO9: 客服
A10: 10 | B10: 北京大学部 | C10: 国内大学部 | D10: 刘锦霖 | E10: 120860686 | F10: 段同飞 | G10: 2025-07-27 11:51:37 | J10: 大二 | K10: 刘晓娟 | L10: 转介绍 | M10: 顾问转介绍-老带新 | N10: 刘晓娟liuxiaojuan@xdf.cn | Q10: 刘锦霖 | R10: 刘晓娟 | S10: 29374981 | T10: 正常工单 | U10: 2025-07-27 11:54 | V10: A（六个月内有报课意向工单） | W10: 六级 | X10: 大二 | Y10: 天津理工大学 | Z10: 机械工程学院 | AA10: 机械工程 | AB10: 刘锦霖 | AC10: 5523148 | AD10: 刘晓娟 | AF10: 2025-07-27 15:52 | AG10: 刘晓娟 | AH10: 2025-07-27 15:52 | AI10: WYS25035 | AJ10: 六级无忧计划 | AK10: 国内考试 | AM10: 5980 | AO10: 刘晓娟 | AP10: 新签 | AQ10: 已交接 | AR10: BJWY2101498uW2 | AS10: BJWY8744849386 | AT10: WYS250350058 | AU10: 2025-07-27 | AW10: 回访人：刘晓娟，回访时间：2025-07-27 11:54，回访内容：家长推荐，想报名六级线下的课程，介绍大班，报名；|回访人：刘晓娟，回访时间：2025-07-27 15:20，回访内容：已经支付，等老带新海报；|回访人：刘晓娟，回访时间：2025-07-27 15:52，回访内容：报名 | BB10: 82388472 | BC10: 否 | BD10: 25下考季 | BE10: 六级无忧计划 | BH10: 国内高校-双非 | BI10: 是 | BL10: 报名 | BN10: 本地人外地大学(归巢) | BO10: 客服
A11: 11 | B11: 北京大学部 | C11: 国内大学部 | D11: 钟宛莹 | E11: 120916460 | F11: 段同飞 | G11: 2025-07-27 14:37:06 | J11: 大一 | K11: 刘晓娟 | L11: 转介绍 | M11: 顾问转介绍-老带新 | N11: 刘晓娟liuxiaojuan@xdf.cn | Q11: 钟宛莹 | R11: 刘晓娟 | S11: 29376005 | T11: 正常工单 | U11: 2025-07-27 14:45 | V11: A（六个月内有报课意向工单） | W11: 四级,大学预科 | X11: 高三 | Y11: 北京海淀区明光中学 | Z11: 新大一 | AA11: 新大一 | AB11: 钟宛莹 | AC11: 5495393 | AD11: 刘晓娟 | AF11: 2025-07-27 16:56 | AG11: 刘晓娟 | AH11: 2025-07-27 16:56 | AI11: YKF25007 | AJ11: 四级无忧计划 | AK11: 国内考试 | AM11: 5180 | AO11: 刘晓娟 | AP11: 新签 | AQ11: 已交接 | AR11: BJWY25030q8UPI | AS11: BJWY3384243858 | AT11: YKF250070017 | AU11: 2025-07-27 | AW11: 回访人：刘晓娟，回访时间：2025-07-27 14:45，回访内容：四级，新大一，家长咨询，线下的，介绍四级8.4的班级；|回访人：刘晓娟，回访时间：2025-07-27 16:56，回访内容：报名 | BB11: 51136935 | BC11: 否 | BD11: 25下考季 | BE11: 四级无忧计划 | BH11: 普通学校-普高 | BI11: 是 | BL11: 报名 | BN11: 本地人本地大学(常规) | BO11: 客服
A12: 12 | B12: 北京大学部 | C12: 国内大学部 | D12: 钟宛芸 | E12: 120862790 | F12: 段同飞 | G12: 2025-07-27 14:39:54 | J12: 未知 | K12: 刘晓娟 | L12: 转介绍 | M12: 顾问转介绍-老带新 | N12: 刘晓娟liuxiaojuan@xdf.cn | Q12: 钟宛芸 | R12: 刘晓娟 | S12: 29376012 | T12: 正常工单 | U12: 2025-07-27 14:46 | V12: A（六个月内有报课意向工单） | W12: 四级,大学预科 | X12: 高三 | Y12: 北京海淀区明光中学 | Z12: 新大一 | AA12: 新大一 | AB12: 钟宛芸 | AC12: 5495387 | AD12: 刘晓娟 | AF12: 2025-07-27 16:55 | AG12: 刘晓娟 | AH12: 2025-07-27 16:55 | AI12: YKF25007 | AJ12: 四级无忧计划 | AK12: 国内考试 | AM12: 5180 | AO12: 刘晓娟 | AP12: 新签 | AQ12: 已交接 | AR12: BJWY25030q8UPI | AS12: BJWY1448386951 | AT12: YKF250070016 | AU12: 2025-07-27 | AW12: 回访人：刘晓娟，回访时间：2025-07-27 14:46，回访内容：四级，新大一，家长咨询，线下的，介绍四级8.4的班级；|回访人：刘晓娟，回访时间：2025-07-27 16:55，回访内容：报名 | BB12: 51112344 | BC12: 否 | BD12: 25下考季 | BE12: 四级无忧计划 | BH12: 普通学校-普高 | BI12: 是 | BL12: 报名 | BN12: 本地人本地大学(常规) | BO12: 客服
A13: 13 | B13: 北京大学部 | C13: 国内大学部 | D13: 吴江祺 | E13: 120857586 | F13: 段同飞 | G13: 2025-07-27 09:12:33 | J13: 大一 | K13: 黄智超 | L13: 转介绍 | M13: 顾问转介绍-老带新 | N13: 黄智超huangzhichao1@xdf.cn | Q13: 吴江祺 | R13: 黄智超 | S13: 29341709 | T13: 正常工单 | U13: 2025-07-27 09:23 | V13: A（六个月内有报课意向工单） | W13: 六级,四级,大学预科 | X13: 大一 | Y13: 北京印刷学院 | Z13: 新闻出版学院 | AA13: 文化产业管理 | AB13: 吴江祺 | AC13: 5495094 | AD13: 黄智超 | AF13: 2025-07-27 13:38 | AG13: 黄智超 | AH13: 2025-07-27 22:00 | AI13: YKF25007 | AJ13: 四级无忧计划 | AK13: 国内考试 | AM13: 5180 | AO13: 黄智超 | AP13: 新签 | AQ13: 已交接 | AR13: BJWY2101498uW2 | AS13: BJWY4582350636 | AT13: YKF250070013 | AU13: 2025-07-27 | AW13: 回访人：黄智超，回访时间：2025-07-27 09:23，回访内容：准备给孩子报名8.4开课的4级班；|回访人：黄智超，回访时间：2025-07-27 13:38，回访内容：签约 预科四级8.4魏公村班 团班 | BB13: 76759510 | BC13: 否 | BD13: 25下考季 | BE13: 四级无忧计划 | BH13: 国内高校-双非 | BI13: 是 | BL13: 报名 | BN13: 本地人本地大学(常规) | BO13: 客服
A14: 14 | B14: 北京大学部 | C14: 国内大学部 | D14: 无 | E14: 120817116 | F14: 程远 | G14: 2025-07-26 09:23:50 | H14: 在跟工单转介绍拉进一批人，田一禾； | J14: 大一 | K14: 田一禾 | L14: 转介绍 | M14: 顾问转介绍-老带新 | N14: 李珈钰 | Q14: 顾桐语 | R14: 田一禾 | S14: 29325447 | T14: 正常工单 | U14: 2025-07-26 09:36 | V14: A（六个月内有报课意向工单） | W14: 四级,大学预科 | X14: 高三 | Y14: 北京石油化工学院 | Z14: 化学工程学院 | AA14: 生物制药 | AB14: 顾桐语 | AC14: 5522025 | AD14: 田一禾 | AF14: 2025-07-26 14:03 | AG14: 田一禾 | AH14: 2025-07-26 14:04 | AI14: YKF25003 | AJ14: 四级无忧计划（新大一专属） | AK14: 国内考试 | AM14: 4880 | AO14: 李珈钰 | AP14: 新签 | AQ14: 已交接 | AR14: BJWY22035556hl | AS14: BJWY2529813604 | AT14: YKF250030049 | AU14: 2025-07-26 | AW14: 回访人：田一禾，回访时间：2025-07-26 09:36，回访内容：拼团组合一起，转介绍3号，今日预计发团；|回访人：田一禾，回访时间：2025-07-26 14:03，回访内容：今日签约。 | BB14: 82449041 | BC14: 否 | BD14: 25下考季 | BE14: 四级无忧计划 | BH14: 国内高校-双非 | BI14: 是 | BL14: 报名 | BN14: 本地人本地大学(常规) | BO14: 客服
A15: 15 | B15: 北京大学部 | C15: 国内大学部 | D15: 同学 | E15: 120808980 | F15: 段同飞 | G15: 2025-07-25 20:30:35 | H15: 刘晓娟老师老带新 | J15: 大一 | K15: 刘晓娟 | L15: 转介绍 | M15: 顾问转介绍-老带新 | N15: 刘晓娟liuxiaojuan@xdf.cn | Q15: 李泽妤 | R15: 刘晓娟 | S15: 29365268 | T15: 正常工单 | U15: 2025-07-25 20:42 | V15: A（六个月内有报课意向工单） | W15: 四级,大学预科 | X15: 高三 | Y15: 北京海淀区明光中学 | Z15: 新大一 | AA15: 新大一 | AB15: 李泽妤 | AC15: 5521778 | AD15: 刘晓娟 | AF15: 2025-07-26 09:57 | AG15: 刘晓娟 | AH15: 2025-07-26 11:00 | AI15: YKF25003 | AJ15: 四级无忧计划（新大一专属） | AK15: 国内考试 | AM15: 5180 | AO15: 刘晓娟 | AP15: 新签 | AQ15: 已交接 | AR15: BJWY24032w1g8X | AS15: BJWY2325667517 | AT15: YKF250030046 | AU15: 2025-07-26 | AW15: 回访人：刘晓娟，回访时间：2025-07-25 20:42，回访内容：老学员推荐，家长咨询，孩子也是新大一想了解四级线下的课程报名大班；|回访人：刘晓娟，回访时间：2025-07-26 09:57，回访内容：报名 | BB15: 82445731 | BC15: 否 | BD15: 25下考季 | BE15: 四级无忧计划 | BH15: 普通学校-普高 | BI15: 是 | BL15: 报名 | BN15: 本地人本地大学(常规) | BO15: 客服
A16: 16 | B16: 北京大学部 | C16: 国内大学部 | D16: 戴嘉浩 | E16: 119012366 | F16: 程远 | G16: 2025-07-14 17:32:08 | H16: 刘晓娟； | J16: 大一 | K16: 刘晓娟 | L16: 转介绍 | M16: 顾问转介绍-老带新 | N16: 李林 | Q16: 戴嘉浩 | R16: 刘晓娟 | S16: 28996338 | T16: 正常工单 | U16: 2025-07-14 18:03 | V16: A（六个月内有报课意向工单） | W16: 六级,大学预科 | X16: 高三 | Y16: 北京市第十九中学 | Z16: 新大一 | AA16: 新大一 | AB16: 戴嘉浩 | AC16: 5494654 | AD16: 刘晓娟 | AF16: 2025-07-26 18:53 | AG16: 刘晓娟 | AH16: 2025-07-26 18:53 | AI16: YKS25003 | AJ16: 六级无忧计划（新大一专属） | AK16: 国内考试 | AM16: 5180 | AO16: 李林 | AP16: 新签 | AQ16: 已交接 | AR16: BJWY2101498uW2 | AS16: BJWY6599593643 | AT16: YKS250030026 | AU16: 2025-07-26 | AW16: 回访人：刘晓娟，回访时间：2025-07-19 11:16，回访内容：微信留言，确认意向；|回访人：刘晓娟，回访时间：2025-07-26 14:40，回访内容：微信留言，确认意向；|回访人：刘晓娟，回访时间：2025-07-26 18:53，回访内容：报名 | BB16: 81685420 | BC16: 否 | BD16: 25下考季 | BE16: 六级无忧计划 | BH16: 普通学校-普高 | BI16: 是 | BL16: 报名 | BN16: 本地人本地大学(常规) | BO16: 客服
A17: 17 | B17: 北京大学部 | C17: 国内大学部 | D17: 吴亚宁 | E17: 120691743 | F17: 段同飞 | G17: 2025-07-25 21:00:48 | H17: 田一禾老师老带新 | J17: 高三 | K17: 田一禾 | L17: 转介绍 | M17: 顾问转介绍-老带新 | N17: 田一禾tianyihe3@xdf.cn | Q17: 吴亚宁 | R17: 田一禾 | S17: 29338349 | T17: 正常工单 | U17: 2025-07-25 21:23 | V17: A（六个月内有报课意向工单） | W17: 四级,大学预科 | X17: 高三 | Y17: 北京交通大学 | Z17: 交通运输学院 | AA17: 物流工程 | AB17: 吴亚宁 | AC17: 5494381 | AD17: 田一禾 | AF17: 2025-07-26 16:18 | AG17: 田一禾 | AH17: 2025-07-26 16:18 | AI17: YKF25003 | AJ17: 四级无忧计划（新大一专属） | AK17: 国内考试 | AM17: 4880 | AO17: 田一禾 | AP17: 新签 | AQ17: 已交接 | AR17: BJWY22035556hl | AS17: BJWY5284651526 | AT17: YKF250030055 | AU17: 2025-07-26 | AW17: 回访人：田一禾，回访时间：2025-07-25 21:23，回访内容：珈钰老带新1，拼团准备（介绍1）；|回访人：田一禾，回访时间：2025-07-26 16:18，回访内容：今日签约 | BB17: 74485243 | BC17: 否 | BD17: 25下考季 | BE17: 四级无忧计划 | BH17: 国内高校-211 | BI17: 是 | BL17: 报名 | BO17: 客服
A18: 18 | B18: 北京大学部 | C18: 国内大学部 | D18: 未知 | E18: 120819772 | F18: 李雪68 | G18: 2025-07-26 10:11:01 | J18: 大一 | K18: 田一禾 | L18: 转介绍 | M18: 顾问转介绍-老带新 | N18: 李珈钰 | Q18: 郭子涵 | R18: 田一禾 | S18: 29325733 | T18: 正常工单 | U18: 2025-07-26 10:18 | V18: B（需长时间跟单或只需要规划） | W18: 四级,大学预科 | X18: 大一 | Y18: 首都经济贸易大学 | Z18: 统计学院 | AA18: 统计学 | AB18: 郭子涵 | AC18: 5494248 | AD18: 田一禾 | AF18: 2025-07-26 14:51 | AG18: 田一禾 | AH18: 2025-07-26 14:51 | AI18: YKF25003 | AJ18: 四级无忧计划（新大一专属） | AK18: 国内考试 | AM18: 4880 | AO18: 李珈钰 | AP18: 新签 | AQ18: 已交接 | AR18: BJWY22035556hl | AS18: BJWY6154217477 | AT18: YKF250030051 | AU18: 2025-07-26 | AW18: 回访人：田一禾，回访时间：2025-07-26 10:18，回访内容：今日转介绍第四号，准备一起入，一起操作；|回访人：田一禾，回访时间：2025-07-26 14:51，回访内容：今日签约 | BB18: 74838658 | BC18: 否 | BD18: 25下考季 | BE18: 四级无忧计划 | BH18: 国内高校-双非 | BI18: 是 | BL18: 报名 | BN18: 外地人本地大学(常规) | BO18: 客服
A19: 19 | B19: 北京大学部 | C19: 国内大学部 | D19: 孙炑祺 | E19: 120817125 | F19: 程远 | G19: 2025-07-26 09:25:43 | H19: 田一禾； | J19: 大一 | K19: 田一禾 | L19: 转介绍 | M19: 顾问转介绍-老带新 | N19: 李珈钰 | Q19: 孙炑祺 | R19: 田一禾 | S19: 29325439 | T19: 正常工单 | U19: 2025-07-26 09:33 | V19: A（六个月内有报课意向工单） | W19: 四级,大学预科 | X19: 高三 | Y19: 北京工商大学 | Z19: 食品与健康学院 | AA19: 食品科学与工程 | AB19: 孙炑祺 | AC19: 5494155 | AD19: 田一禾 | AF19: 2025-07-26 13:52 | AG19: 田一禾 | AH19: 2025-07-26 13:54 | AI19: YKF25003 | AJ19: 四级无忧计划（新大一专属） | AK19: 国内考试 | AM19: 4880 | AO19: 李珈钰 | AP19: 新签 | AQ19: 已交接 | AR19: BJWY22035556hl | AS19: BJWY4972443309 | AT19: YKF250030050 | AU19: 2025-07-26 | AW19: 回访人：田一禾，回访时间：2025-07-26 09:33，回访内容：拼团报入，准备成团 转介绍2；|回访人：田一禾，回访时间：2025-07-26 13:52，回访内容：今日签约。转介绍 | BB19: 56334937 | BC19: 否 | BD19: 25下考季 | BE19: 四级无忧计划 | BH19: 国内高校-双非 | BI19: 是 | BL19: 报名 | BN19: 本地人本地大学(常规) | BO19: 客服
A20: 20 | B20: 北京大学部 | C20: 国内大学部 | D20: 李知非 | E20: 120690089 | F20: 段同飞 | G20: 2025-07-25 18:34:20 | H20: 转介绍建单 | J20: 高三 | K20: 田一禾 | L20: 转介绍 | M20: 顾问转介绍-老带新 | N20: 田一禾tianyihe3@xdf.cn | Q20: 李知非 | R20: 田一禾 | S20: 29324100 | T20: 正常工单 | U20: 2025-07-25 18:36 | V20: B（需长时间跟单或只需要规划） | W20: 六级,大学预科 | X20: 高三 | Y20: 北京交通大学 | Z20: 计算机与信息技术学院 | AA20: 计算机科学与技术 | AB20: 李知非 | AC20: 5493778 | AD20: 田一禾 | AF20: 2025-07-25 22:37 | AG20: 田一禾 | AH20: 2025-07-26 13:45 | AI20: YKS25003 | AJ20: 六级无忧计划（新大一专属） | AK20: 国内考试 | AM20: 5180 | AO20: 田一禾 | AP20: 新签 | AQ20: 已交接 | AR20: BJWY22035556hl | AS20: BJWY2079358066 | AT20: YKS250030023 | AU20: 2025-07-26 | AW20: 回访人：田一禾，回访时间：2025-07-25 18:36，回访内容：老带新一起报六级新大一班，；|回访人：田一禾，回访时间：2025-07-25 21:26，回访内容：李荣晋介绍1 ，明天预计会报六级预科班；|回访人：田一禾，回访时间：2025-07-25 22:37，回访内容：今日签约暂存 | BB20: 76297562 | BC20: 否 | BD20: 25下考季 | BE20: 六级无忧计划 | BH20: 国内高校-211 | BI20: 是 | BJ20: 这是六级大班的李知非，不是一个人。 | BL20: 报名 | BO20: 客服
A21: 21 | B21: 北京大学部 | C21: 国内大学部 | D21: 未知 | E21: 119890417 | F21: 杨沫 | G21: 2025-07-19 12:16:24 | H21: 黄智超 | J21: 大一 | K21: 黄智超 | L21: 转介绍 | M21: 顾问转介绍-老带新 | N21: 郭沛瑶 | Q21: 齐雪桐 | R21: 黄智超 | S21: 29164472 | T21: 正常工单 | U21: 2025-07-19 12:36 | V21: A（六个月内有报课意向工单） | W21: 四级,大学预科 | X21: 大一 | Y21: 北京语言大学 | Z21: 国际关系学院 | AA21: 国际事务与国际关系 | AB21: 齐雪桐 | AC21: 5521346 | AD21: 黄智超 | AF21: 2025-07-25 16:18 | AG21: 黄智超 | AH21: 2025-07-25 16:18 | AI21: YKF25003 | AJ21: 四级无忧计划（新大一专属） | AK21: 国内考试 | AM21: 5180 | AO21: 郭沛瑶 | AP21: 新签 | AQ21: 已交接 | AR21: BJWY22035556hl | AS21: BJWY2771129747 | AT21: YKF250030044 | AU21: 2025-07-25 | AW21: 回访人：黄智超，回访时间：2025-07-19 12:36，回访内容：郭沛瑶的同学 线下面访 介绍四六级课程 意向高 看看报名哪个班 凑3人团；|回访人：黄智超，回访时间：2025-07-19 12:37，回访内容：已添加微信 现在沟通了 等待确定报名哪个班；|回访人：黄智超，回访时间：2025-07-21 20:58，回访内容：电话未接 确定一下报名课程的意向 看看能不能找到小伙伴组团～；|回访人：黄智超，回访时间：2025-07-23 22:19，回访内容：电话未通 再跟进 等看看能不能再凑一个～；|回访人：黄智超，回访时间：2025-07-25 16:18，回访内容：签约 预科四级大班8.4花园桥 | BB21: 74785509 | BC21: 否 | BD21: 25下考季 | BE21: 四级无忧计划 | BH21: 国内高校-双非 | BI21: 是 | BL21: 报名 | BN21: 本地人外地大学(归巢) | BO21: 客服
A22: 22 | B22: 北京大学部 | C22: 国内大学部 | D22: 种道轩 | E22: 120657385 | F22: 吴凯龙 | G22: 2025-07-24 20:00:46 | H22: 房国超的顾问转介绍工单 | J22: 大一 | K22: 房国超 | L22: 转介绍 | M22: 顾问转介绍-老带新 | N22: 房国超fangguochao@xdf.cn | Q22: 种道轩 | R22: 房国超 | S22: 29296072 | T22: 正常工单 | U22: 2025-07-24 20:02 | V22: A（六个月内有报课意向工单） | W22: 四级,大学预科 | X22: 高三 | Y22: 新大一 | Z22: 新大一 | AA22: 新大一 | AB22: 种道轩 | AC22: 5418748 | AD22: 房国超 | AF22: 2025-07-25 17:30 | AG22: 房国超 | AH22: 2025-07-25 17:30 | AI22: YKF25003 | AJ22: 四级无忧计划（新大一专属） | AK22: 国内考试 | AM22: 4880 | AO22: 房国超 | AP22: 新签 | AQ22: 已交接 | AR22: BJWY22035556hl | AS22: BJWY4220650794 | AT22: YKF250030039 | AU22: 2025-07-25 | AW22: 回访人：房国超，回访时间：2025-07-24 20:02，回访内容：同学推荐，一起学，英语90多，偏科；|回访人：房国超，回访时间：2025-07-25 17:30，回访内容：报名 | BB22: 82355509 | BC22: 否 | BD22: 25下考季 | BE22: 四级无忧计划 | BH22: 普通学校-普高 | BI22: 是 | BL22: 报名 | BN22: 本地人本地大学(常规) | BO22: 客服
A23: 23 | B23: 北京大学部 | C23: 国内大学部 | E23: 117785459 | G23: 2025-07-05 20:12:20 | H23: 黄智超 | J23: 大一 | K23: 黄智超 | L23: 转介绍 | M23: 顾问转介绍-老带新 | Q23: 郑初妍 | R23: 黄智超 | S23: 29315538 | T23: 续费工单 | U23: 2025-07-24 22:29 | V23: A（六个月内有报课意向工单） | W23: 六级,大学预科 | X23: 大一 | Y23: 新大一 | Z23: 新大一 | AA23: 新大一 | AB23: 郑初妍 | AC23: 5520592 | AD23: 黄智超 | AE23: 转班不算 | AF23: 2025-07-24 22:30 | AG23: 黄智超 | AH23: 2025-07-24 22:30 | AI23: YKS25003 | AJ23: 六级无忧计划（新大一专属） | AK23: 国内考试 | AN23: 同科续费 | AO23: 党同学 | AP23: 续班 | AQ23: 已交接 | AR23: BJWY25030q8UPI | AS23: BJWY5518228982 | AT23: YKS250030012 | AU23: 2025-07-24 | AW23: 回访人：黄智超，回访时间：2025-07-24 22:29，回访内容：转班；|回访人：黄智超，回访时间：2025-07-24 22:30，回访内容：转班 | BB23: 74628058 | BC23: 否 | BD23: 25下考季 | BE23: 六级无忧计划 | BH23: 普通学校-普高 | BI23: 是 | BL23: 转出 | BN23: 本地人本地大学(常规)
A24: 24 | B24: 北京大学部 | C24: 国内大学部 | D24: 蔡立达 | E24: 120621426 | F24: 杨沫 | G24: 2025-07-24 16:07:59 | H24: 宋增辉 | J24: 大一 | K24: 宋增辉 | L24: 转介绍 | M24: 顾问转介绍-老带新 | N24: 谢嘉睿 | Q24: 蔡立达 | R24: 宋增辉 | S24: 29311865 | T24: 正常工单 | U24: 2025-07-24 16:13 | V24: A（六个月内有报课意向工单） | W24: 六级,大学预科 | X24: 大一 | Y24: 人大附中航天城学校 | Z24: 新大一 | AA24: 新大一 | AB24: 蔡立达 | AC24: 5520528 | AD24: 宋增辉 | AF24: 2025-07-24 20:39 | AG24: 宋增辉 | AH24: 2025-07-24 20:39 | AI24: YKSJ25001 | AJ24: 六级无忧计划（线上优享/新大一专属） | AK24: 国内考试 | AM24: 5180 | AO24: 谢嘉睿 | AP24: 新签 | AQ24: 已交接 | AR24: BJWY25030q8UPI | AS24: BJWY7097470991 | AT24: YKSJ250010056 | AU24: 2025-07-24 | AW24: 回访人：宋增辉，回访时间：2025-07-24 16:13，回访内容：已确认报名。等待缴费；|回访人：宋增辉，回访时间：2025-07-24 20:39，回访内容：已报名 | BB24: 82325106 | BC24: 否 | BD24: 25下考季 | BE24: 六级无忧计划 | BH24: 国内高校-双非 | BI24: 是 | BL24: 报名 | BN24: 本地人本地大学(常规) | BO24: 客服
A25: 25 | B25: 北京大学部 | C25: 国内大学部 | D25: 张千寻 | E25: 120494984 | F25: 杨沫 | G25: 2025-07-23 19:35:46 | H25: 杨晓超 | J25: 大一 | K25: 杨晓超 | L25: 转介绍 | M25: 顾问转介绍-老带新 | N25: 张 | Q25: 张千寻 | R25: 杨晓超 | S25: 29304939 | T25: 正常工单 | U25: 2025-07-23 19:39 | V25: A（六个月内有报课意向工单） | W25: 六级,大学预科 | X25: 大一 | Y25: 南京农业大学 | Z25: 生命科学学院 | AA25: 生物科学 | AB25: 张千寻 | AC25: 5520463 | AD25: 宋增辉 | AF25: 2025-07-24 17:08 | AG25: 杨晓超 | AH25: 2025-07-25 10:16 | AK25: 国内考试 | AM25: 2590 | AO25: 张 | AP25: 分单 | AQ25: 已交接 | AS25: BJWY0638731537 | AW25: 回访人：杨晓超，回访时间：2025-07-23 19:39，回访内容：大学预科学习 ；|回访人：杨晓超，回访时间：2025-07-24 17:08，回访内容：签约 | BB25: 82268895 | BC25: 否 | BD25: 25下考季 | BE25: 六级无忧计划 | BH25: 国内高校-211 | BI25: 否 | BN25: 本地人本地大学(常规) | BO25: 客服
A26: 26 | B26: 北京大学部 | C26: 国内大学部 | D26: 家长 | E26: 120563447 | F26: 杨沫 | G26: 2025-07-24 11:09:59 | H26: 刘晓娟 | J26: 大二 | K26: 刘晓娟 | L26: 转介绍 | M26: 顾问转介绍-老带新 | N26: 刘俊 | Q26: 李昱志 | R26: 刘晓娟 | S26: 29306992 | T26: 正常工单 | U26: 2025-07-24 11:14 | V26: A（六个月内有报课意向工单） | W26: 考研集训营 | X26: 大二 | Y26: 北京工商大学 | Z26: 计算机 | AA26: 计算机 | AB26: 李昱志 | AC26: 5418120 | AD26: 刘晓娟 | AF26: 2025-07-24 14:01 | AG26: 刘晓娟 | AH26: 2025-07-24 14:01 | AI26: KYZ26001 | AJ26: 27考研大二集训营（住宿费） | AK26: 国内考试 | AM26: 2720 | AO26: 刘俊 | AP26: 新签 | AQ26: 已交接 | AR26: WebReg | AS26: BJWY0757959044 | AT26: KYZ260010064 | AU26: 2025-07-24 | AW26: 回访人：刘晓娟，回访时间：2025-07-24 11:14，回访内容：明年考研，咨询考研课程，介绍大二英语数学集训营，介绍；|回访人：刘晓娟，回访时间：2025-07-24 14:01，回访内容：报名 | BB26: 82306175 | BC26: 否 | BD26: 27考季 | BE26: 暑假集训营 | BF26: 英语,数学 | BG26: 计算机 | BH26: 国内高校-双非 | BI26: 是 | BL26: 报名 | BN26: 外地人本地大学(常规) | BO26: 客服
A27: 27 | B27: 北京大学部 | C27: 国内大学部 | D27: 家长 | E27: 120563447 | F27: 杨沫 | G27: 2025-07-24 11:09:59 | H27: 刘晓娟 | J27: 大二 | K27: 刘晓娟 | L27: 转介绍 | M27: 顾问转介绍-老带新 | N27: 刘俊 | Q27: 李昱志 | R27: 刘晓娟 | S27: 29306992 | T27: 正常工单 | U27: 2025-07-24 11:14 | V27: A（六个月内有报课意向工单） | W27: 考研集训营 | X27: 大二 | Y27: 北京工商大学 | Z27: 计算机 | AA27: 计算机 | AB27: 李昱志 | AC27: 5418120 | AD27: 刘晓娟 | AF27: 2025-07-24 14:01 | AG27: 刘晓娟 | AH27: 2025-07-24 14:01 | AI27: KYJY26001 | AJ27: 27考研英语大二集训营 | AK27: 国内考试 | AM27: 12040 | AO27: 刘俊 | AP27: 新签 | AQ27: 已交接 | AR27: WebReg | AS27: BJWY0757959044 | AT27: KYJY260010063 | AU27: 2025-07-24 | AW27: 回访人：刘晓娟，回访时间：2025-07-24 11:14，回访内容：明年考研，咨询考研课程，介绍大二英语数学集训营，介绍；|回访人：刘晓娟，回访时间：2025-07-24 14:01，回访内容：报名 | BB27: 82306175 | BC27: 否 | BD27: 27考季 | BE27: 暑假集训营 | BF27: 英语,数学 | BG27: 计算机 | BH27: 国内高校-双非 | BI27: 是 | BL27: 报名 | BN27: 外地人本地大学(常规) | BO27: 客服
A28: 28 | B28: 北京大学部 | C28: 国内大学部 | D28: 家长 | E28: 120563447 | F28: 杨沫 | G28: 2025-07-24 11:09:59 | H28: 刘晓娟 | J28: 大二 | K28: 刘晓娟 | L28: 转介绍 | M28: 顾问转介绍-老带新 | N28: 刘俊 | Q28: 李昱志 | R28: 刘晓娟 | S28: 29306992 | T28: 正常工单 | U28: 2025-07-24 11:14 | V28: A（六个月内有报课意向工单） | W28: 考研集训营 | X28: 大二 | Y28: 北京工商大学 | Z28: 计算机 | AA28: 计算机 | AB28: 李昱志 | AC28: 5418120 | AD28: 刘晓娟 | AF28: 2025-07-24 14:01 | AG28: 刘晓娟 | AH28: 2025-07-24 14:01 | AI28: KYJS26001 | AJ28: 27考研数学大二集训营 | AK28: 国内考试 | AM28: 11540 | AO28: 刘俊 | AP28: 新签 | AQ28: 已交接 | AR28: WebReg | AS28: BJWY0757959044 | AT28: KYJS260010035 | AU28: 2025-07-24 | AW28: 回访人：刘晓娟，回访时间：2025-07-24 11:14，回访内容：明年考研，咨询考研课程，介绍大二英语数学集训营，介绍；|回访人：刘晓娟，回访时间：2025-07-24 14:01，回访内容：报名 | BB28: 82306175 | BC28: 否 | BD28: 27考季 | BE28: 暑假集训营 | BF28: 英语,数学 | BG28: 计算机 | BH28: 国内高校-双非 | BI28: 是 | BL28: 报名 | BN28: 外地人本地大学(常规) | BO28: 客服
A29: 29 | B29: 北京大学部 | C29: 国内大学部 | D29: 杨柳祎 | E29: 118652904 | F29: 吴凯龙 | G29: 2025-07-12 14:05:50 | H29: 宋增辉的顾问转介绍工单 | J29: 高三 | K29: 宋增辉 | L29: 转介绍 | M29: 顾问转介绍-老带新 | N29: 宋增辉songzenghui@xdf.cn | Q29: 杨柳祎 | R29: 宋增辉 | S29: 29046756 | T29: 正常工单 | U29: 2025-07-12 14:20 | V29: B（需长时间跟单或只需要规划） | W29: 六级,大学预科 | X29: 大一 | Y29: 北京市第十一中学 | Z29: 新大一 | AA29: 新大一 | AB29: 杨柳祎 | AC29: 5491776 | AD29: 宋增辉 | AF29: 2025-07-24 10:50 | AG29: 宋增辉 | AH29: 2025-07-24 10:50 | AI29: YKS25003 | AJ29: 六级无忧计划（新大一专属） | AK29: 国内考试 | AM29: 5180 | AO29: 宋增辉 | AP29: 新签 | AQ29: 已交接 | AR29: BJWY2011wXCx1W | AS29: BJWY6654774927 | AT29: YKS250030008 | AU29: 2025-07-23 | AW29: 回访人：宋增辉，回访时间：2025-07-17 12:55，回访内容：电话未接，微信留言；|回访人：宋增辉，回访时间：2025-07-22 19:56，回访内容：在忙，稍后沟通；|回访人：宋增辉，回访时间：2025-07-23 18:24，回访内容：电话未接，微信留言；|回访人：宋增辉，回访时间：2025-07-24 10:50，回访内容：已报名 | BB29: 81567479 | BC29: 否 | BD29: 25下考季 | BE29: 六级无忧计划 | BH29: 国内高校-双非 | BI29: 是 | BL29: 报名 | BN29: 本地人本地大学(常规) | BO29: 客服
A30: 30 | B30: 北京大学部 | C30: 国内大学部 | D30: 王辰荟 | E30: 120207451 | F30: 程远 | G30: 2025-07-22 15:41:20 | H30: 宋增辉 ； | J30: 大一 | K30: 宋增辉 | L30: 转介绍 | M30: 顾问转介绍-老带新 | N30: 谢嘉睿 | Q30: 王辰荟 | R30: 宋增辉 | S30: 29261177 | T30: 正常工单 | U30: 2025-07-22 15:52 | V30: A（六个月内有报课意向工单） | W30: 四级,大学预科 | X30: 大一 | Y30: 首都师范大学 | Z30: 小学教育 | AA30: 小学教育 | AB30: 王辰荟 | AC30: 5417771 | AD30: 宋增辉 | AF30: 2025-07-23 15:26 | AG30: 宋增辉 | AH30: 2025-07-23 15:26 | AI30: YKF25003 | AJ30: 四级无忧计划（新大一专属） | AK30: 国内考试 | AM30: 5180 | AO30: 谢嘉睿 | AP30: 新签 | AQ30: 已交接 | AR30: BJWY22035556hl | AS30: BJWY8979636076 | AT30: YKF250030023 | AU30: 2025-07-23 | AW30: 回访人：宋增辉，回访时间：2025-07-22 15:52，回访内容：家长要去跟8月4号四级去学习，已经沟通号；|回访人：宋增辉，回访时间：2025-07-22 16:28，回访内容：发了协议，等待协议签署，马上报名 总结：北京新东方增辉老师负责大学预科、专升本、四六级等国内考试咨询，提供专业教育服务。有家长咨询四级辅导班，询问课程安排、费用、师资及退费政策。家长倾向于线下课，老师介绍了线下课补课机制和师资保障。家长最终决定报名8月4日开始的线下课，享受了组团优惠，学费从5680元降至5180元，并签署了服务协议。 下次回访建议：在开课前一周联系家长，确认是否已签署协议并支付费用，提醒开课时间和地点。开课后一周内回访，了解孩子上课情况，确认是否适应课程内容，解答家长疑问。课程中期回访，了解学习进度，提供学习建议。课程结束前回访，询问家长对课程的整体满意度，收集反馈，为后续课程推荐做准备。；|回访人：宋增辉，回访时间：2025-07-23 15:26，回访内容：已报名 | BB30: 82189251 | BC30: 否 | BD30: 25下考季 | BE30: 四级无忧计划 | BH30: 国内高校-中外合作办学 | BI30: 是 | BL30: 报名 | BN30: 本地人本地大学(常规) | BO30: 客服
A31: 31 | B31: 北京大学部 | C31: 国内大学部 | D31: 老带新用户 | E31: 120117849 | F31: 宋增辉 | G31: 2025-07-22 08:51:20 | H31: 渠道录入来源：老带新系统 老生userid：a61e75c0-d5cc-4da0-a5db-fd1f588c919e 老生学号：BJWY4335225382 老生姓名：蓝浩瑜 产品类型：1 活动所属学校名称：北京大学事业部 老带新活动名称：邀好友，大家一起来省钱（VIP课程专享）新 老带新活动id：2366380 推广邮箱：songzenghui@xdf.cn | I31: 2026财年第2财月老带新系统 | K31: 宋增辉 | L31: 转介绍 | M31: 老带新系统顾问 | N31: 宋增辉songzenghui@xdf.cn | Q31: 庞佳璇 | R31: 宋增辉 | S31: 29237457 | T31: 正常工单 | U31: 2025-07-22 09:22 | V31: B（需长时间跟单或只需要规划） | W31: 四级,大学预科 | X31: 大一 | Y31: 北京161中学（北校区） | Z31: 新大一 | AA31: 新大一 | AB31: 庞佳璇 | AC31: 5490104 | AD31: 宋增辉 | AF31: 2025-07-22 13:11 | AG31: 宋增辉 | AH31: 2025-07-22 13:15 | AI31: LP1753161092790 | AJ31: 四级一对一畅学班（50H） | AK31: 国内考试 | AM31: 37000 | AO31: 宋增辉 | AP31: 新签 | AQ31: 已交接 | AS31: BJWY4093372722 | AU31: 2025-07-22 | AW31: 回访人：宋增辉，回访时间：2025-07-22 09:22，回访内容：已沟通，决定学习一对一，和家长已将沟通，已报名家长转介绍；|回访人：宋增辉，回访时间：2025-07-22 13:59，回访内容：已报名 | BB31: 74908041 | BC31: 否 | BD31: 25下考季 | BE31: 四级一对一 | BH31: 普通学校-普高 | BI31: 是 | BN31: 本地人本地大学(常规) | BO31: 老带新系统
A32: 32 | B32: 北京大学部 | C32: 国内大学部 | D32: 老带新用户 | E32: 119961581 | F32: 宋增辉 | G32: 2025-07-20 21:50:35 | H32: 渠道录入来源：老带新系统 老生userid：5ca3317f-17b9-4f57-8d22-44258bf085dd 老生学号：BJWY3417879227 老生姓名：黄俊宇 产品类型：1 活动所属学校名称：北京大学事业部 老带新活动名称：邀好友，大家一起来省钱（班课专用）新 老带新活动id：2366032 推广邮箱：songzenghui@xdf.cn | I32: 2026财年第2财月老带新系统 | K32: 宋增辉 | L32: 转介绍 | M32: 老带新系统顾问 | N32: 宋增辉songzenghui@xdf.cn | Q32: 邬昊锴 | R32: 宋增辉 | S32: 29246422 | T32: 正常工单 | U32: 2025-07-20 23:34 | V32: A（六个月内有报课意向工单） | W32: 六级,大学预科 | X32: 大一 | Y32: 人大附中本部 | Z32: 新大一 | AA32: 新大一 | AB32: 邬昊锴 | AC32: 5487035 | AD32: 宋增辉 | AF32: 2025-07-21 11:26 | AG32: 宋增辉 | AH32: 2025-07-21 11:27 | AI32: YKSJ25001 | AJ32: 六级无忧计划（线上优享/新大一专属） | AK32: 国内考试 | AM32: 5480 | AO32: 宋增辉 | AP32: 新签 | AQ32: 已交接 | AR32: WebReg | AS32: BJWY1541459125 | AT32: YKSJ250010047 | AU32: 2025-07-21 | AW32: 回访人：宋增辉，回访时间：2025-07-20 23:34，回访内容：决定报名，老学员推荐，明天缴费 邬昊锴是新东方增辉老师，负责多种国内考试咨询，包括四六级、考研等。他提供线上和线下课程，线上课程已开课，错过课程可看回放。邬老师建议邬昊锴学习六级课程，尽管词汇基础较弱，但课程难度适合。费用和报名流程将在明天处理。 下次回访建议：确认邬昊锴是否已完成报名流程，了解他对课程的初步反馈，并提供词汇学习建议，帮助他更好地准备六级考试。同时，询问是否有其他学习需求或问题，确保他对课程安排满意。；|回访人：宋增辉，回访时间：2025-07-21 11:26，回访内容：已经报名 | BB32: 82077035 | BC32: 否 | BD32: 25下考季 | BE32: 六级无忧计划 | BH32: 国内高校-双非 | BI32: 是 | BL32: 报名 | BN32: 本地人本地大学(常规) | BO32: 老带新系统
A33: 33 | B33: 北京大学部 | C33: 国内大学部 | D33: 同学 | E33: 120001681 | F33: 段同飞 | G33: 2025-07-21 11:55:18 | H33: 刘晓娟老师顾问转介绍工单 | J33: 大一 | K33: 刘晓娟 | L33: 转介绍 | M33: 顾问转介绍-老带新 | N33: 刘晓娟liuxiaojuan@xdf.cn | Q33: 汪瑞涵 | R33: 刘晓娟 | S33: 29230669 | T33: 正常工单 | U33: 2025-07-21 12:00 | V33: A（六个月内有报课意向工单） | W33: 四级,大学预科 | X33: 高三 | Y33: 北京市大兴七中 | Z33: 新大一 | AA33: 新大一 | AB33: 汪瑞涵 | AC33: 5417140 | AD33: 刘晓娟 | AF33: 2025-07-21 19:20 | AG33: 刘晓娟 | AH33: 2025-07-21 19:20 | AI33: WYFJ25033 | AJ33: 四级无忧计划 | AK33: 国内考试 | AM33: 5480 | AO33: 刘晓娟 | AP33: 新签 | AQ33: 已交接 | AR33: BJWY24032w1g8X | AS33: BJWY8298538644 | AT33: WYFJ250330045 | AU33: 2025-07-21 | AW33: 回访人：刘晓娟，回访时间：2025-07-21 12:00，回访内容：孩子母亲咨询，高考90多，平时110-120，想咨询四级的课程，介绍；|回访人：刘晓娟，回访时间：2025-07-21 19:20，回访内容：报名 | BB33: 82096639 | BC33: 否 | BD33: 25下考季 | BE33: 四级无忧计划 | BH33: 普通学校-普高 | BI33: 是 | BL33: 报名 | BN33: 本地人本地大学(常规) | BO33: 客服
A34: 34 | B34: 北京大学部 | C34: 国内大学部 | D34: 涂昕童 | E34: 119934563 | F34: 李雪68 | G34: 2025-07-20 17:33:58 | J34: 未知 | K34: 李政(离职) | L34: 转介绍 | M34: 顾问转介绍-老带新 | N34: 张嘉会 | Q34: 涂昕童 | R34: 李政(离职) | S34: 29244653 | T34: 正常工单 | U34: 2025-07-20 17:35 | V34: A（六个月内有报课意向工单） | W34: 六级,大学预科 | X34: 高三 | Y34: 北京市第三中学 | Z34: 新大一 | AA34: 新大一 | AB34: 涂昕童 | AC34: 5488431 | AD34: 李政(离职) | AF34: 2025-07-20 17:58 | AG34: 李政(离职) | AH34: 2025-07-21 10:34 | AI34: YKSJ25001 | AJ34: 六级无忧计划（线上优享/新大一专属） | AK34: 国内考试 | AM34: 5680 | AO34: 张嘉会 | AP34: 新签 | AQ34: 已交接 | AR34: BJWY25030q8UPI | AS34: BJWY2751118744 | AT34: YKSJ250010045 | AU34: 2025-07-20 | AW34: 回访人：李政(离职)，回访时间：2025-07-20 17:35，回访内容：要签约；|回访人：李政(离职)，回访时间：2025-07-20 17:58，回访内容：签约 | BB34: 82060166 | BC34: 否 | BD34: 25下考季 | BE34: 六级无忧计划 | BH34: 普通学校-普高 | BI34: 是 | BL34: 转出 | BN34: 本地人本地大学(常规) | BO34: 客服
A35: 35 | B35: 北京大学部 | C35: 国内大学部 | D35: 老带新用户 | E35: 119762417 | F35: 房国超 | G35: 2025-07-18 15:16:48 | H35: 渠道录入来源：老带新系统 老生userid：43ef700a-2196-438f-8b58-230db97ab019 老生学号：BJWY2819580427 老生姓名：江卓霖 产品类型：1 活动所属学校名称：北京大学事业部 老带新活动名称：邀好友，大家一起来省钱（班课专用）新 老带新活动id：2366032 推广邮箱：fangguochao@xdf.cn | I35: 2026财年第2财月老带新系统 | K35: 房国超 | L35: 转介绍 | M35: 老带新系统顾问 | N35: 房国超fangguochao@xdf.cn | Q35: 魏子涵 | R35: 房国超 | S35: 29198090 | T35: 正常工单 | U35: 2025-07-18 15:28 | V35: A（六个月内有报课意向工单） | W35: 四级,大学预科 | X35: 大一 | Y35: 新大一 | Z35: 新大一 | AA35: 新大一 | AB35: 魏子涵 | AC35: 5484117 | AD35: 房国超 | AF35: 2025-07-18 15:47 | AG35: 房国超 | AH35: 2025-07-18 15:47 | AI35: ZVVB26001 | AJ35: 六级暑假集训营（24H冲刺直播） | AK35: 国内考试 | AM35: 15600 | AO35: 房国超 | AP35: 新签 | AQ35: 已交接 | AR35: WebReg | AS35: XDF072203144714089 | AT35: ZVVB260010050 | AU35: 2025-07-18 | AW35: 回访人：房国超，回访时间：2025-07-18 15:28，回访内容：jixunying；|回访人：房国超，回访时间：2025-07-18 15:47，回访内容：报名 | BB35: 82019053 | BC35: 否 | BD35: 25下考季 | BE35: 暑假六级集训营 | BH35: 普通学校-普高 | BI35: 是 | BL35: 报名 | BN35: 本地人本地大学(常规) | BO35: 老带新系统
A36: 36 | B36: 北京大学部 | C36: 国内大学部 | D36: 老带新用户 | E36: 119742685 | F36: 房国超 | G36: 2025-07-18 13:07:11 | H36: 渠道录入来源：老带新系统 老生userid：7b0ebef8-e3a5-415c-a950-5099cde87f5c 老生学号：BJWY3293832154 老生姓名：王宇 产品类型：1 活动所属学校名称：北京大学事业部 老带新活动名称：邀好友，大家一起来省钱（班课专用）新 老带新活动id：2366032 推广邮箱：fangguochao@xdf.cn | I36: 2026财年第2财月老带新系统 | K36: 房国超 | L36: 转介绍 | M36: 老带新系统顾问 | N36: 房国超fangguochao@xdf.cn | Q36: 侯欣彤 | R36: 房国超 | S36: 29195924 | T36: 正常工单 | U36: 2025-07-18 13:28 | V36: A（六个月内有报课意向工单） | W36: 六级 | X36: 大二 | Y36: 华侨大学 | Z36: 国际学院 | AA36: 会计学 | AB36: 侯欣彤 | AC36: 5455910 | AD36: 房国超 | AF36: 2025-07-18 13:50 | AG36: 房国超 | AH36: 2025-07-18 13:50 | AI36: WYSJ25033 | AJ36: 六级无忧计划 | AK36: 国内考试 | AM36: 5480 | AO36: 房国超 | AP36: 新签 | AQ36: 已交接 | AR36: WebReg | AS36: BJWY7092539589 | AT36: WYSJ250330090 | AU36: 2025-07-18 | AW36: 回访人：房国超，回访时间：2025-07-18 13:29，回访内容：直播课；|回访人：房国超，回访时间：2025-07-18 13:50，回访内容：报名，黑龙江 | BB36: 82006786 | BC36: 否 | BD36: 25下考季 | BE36: 六级无忧计划 | BH36: 国内高校-双非 | BI36: 是 | BL36: 报名 | BN36: 外地人外地大学(常规) | BO36: 老带新系统
A37: 37 | B37: 北京大学部 | C37: 国内大学部 | D37: 同学 | E37: 119683804 | F37: 杨沫 | G37: 2025-07-18 10:08:24 | H37: 微信号：bjlulu，微信建单 刘晓娟 | J37: 大一 | K37: 刘晓娟 | L37: 转介绍 | M37: 顾问转介绍-老带新 | N37: 李乐滢 | Q37: 刘淇扬 | R37: 刘晓娟 | S37: 29193330 | T37: 正常工单 | U37: 2025-07-18 10:19 | V37: A（六个月内有报课意向工单） | W37: 四级,大学预科 | X37: 高三 | Y37: 大兴区安定二中 | Z37: 新大一 | AA37: 新大一 | AB37: 刘淇扬 | AC37: 5455801 | AD37: 刘晓娟 | AF37: 2025-07-18 11:54 | AG37: 刘晓娟 | AH37: 2025-07-18 11:54 | AI37: YKF25002 | AJ37: 四级无忧计划（新大一专属） | AK37: 国内考试 | AM37: 5180 | AO37: 李乐滢 | AP37: 新签 | AQ37: 已交接 | AR37: BJWY2011wXCx1W | AS37: BJWY9246594506 | AT37: YKF250020038 | AU37: 2025-07-18 | AW37: 回访人：刘晓娟，回访时间：2025-07-18 10:19，回访内容：家长咨询，新大一，高考分124，想看看四级和六级的课程，7.21的班级，再跟孩子商量下；|回访人：刘晓娟，回访时间：2025-07-18 11:54，回访内容：报名 | BB37: 81927852 | BC37: 否 | BD37: 25下考季 | BE37: 四级无忧计划 | BH37: 普通学校-普高 | BI37: 是 | BL37: 报名 | BN37: 本地人本地大学(常规) | BO37: 客服
A38: 38 | B38: 北京大学部 | C38: 国内大学部 | D38: 平平 | E38: 117875945 | F38: 段同飞 | G38: 2025-07-06 17:24:01 | H38: 黄智超老师老带新 | J38: 大二 | K38: 黄智超 | L38: 转介绍 | M38: 顾问转介绍-老带新 | N38: 黄智超huangzhichao1@xdf.cn | Q38: 陈泽临 | R38: 黄智超 | S38: 28894555 | T38: 正常工单 | U38: 2025-07-06 20:14 | V38: A（六个月内有报课意向工单） | W38: 六级 | X38: 大二 | Y38: 中国政法大学 | Z38: 光明新闻传播学院 | AA38: 网络与新媒体 | AB38: 陈泽临 | AC38: 5481914 | AD38: 黄智超 | AF38: 2025-07-16 14:28 | AG38: 黄智超 | AH38: 2025-07-16 14:28 | AI38: WYSJ25033 | AJ38: 六级无忧计划 | AK38: 国内考试 | AM38: 5680 | AO38: 黄智超 | AP38: 新签 | AQ38: 已交接 | AR38: WebReg | AS38: BJWY6475303787 | AT38: WYSJ250330083 | AU38: 2025-07-16 | AW38: 回访人：黄智超，回访时间：2025-07-12 17:52，回访内容：家长反馈孩子去军训了，得是7月14号才能回来，预计7月15号联系。；|回访人：黄智超，回访时间：2025-07-15 19:14，回访内容：孩子刚回来 还没来得及沟通 等等家长的反馈；|回访人：黄智超，回访时间：2025-07-16 14:28，回访内容：已签约 六级线上网课 5680元WYSJ25033 | BB38: 65444803 | BC38: 否 | BD38: 25下考季 | BE38: 六级无忧计划 | BH38: 国内高校-211 | BI38: 是 | BL38: 报名 | BN38: 本地人本地大学(常规) | BO38: 客服
A39: 39 | B39: 北京大学部 | C39: 国内大学部 | D39: 张一帆 | E39: 118219708 | F39: 程远 | G39: 2025-07-08 16:57:06 | H39: 张博奥 | J39: 大二 | K39: 张博奥 | L39: 转介绍 | M39: 顾问转介绍-老带新 | N39: 张沛林 | Q39: 张一帆 | R39: 张博奥 | S39: 28934804 | T39: 正常工单 | U39: 2025-07-08 18:06 | V39: A（六个月内有报课意向工单） | W39: 六级 | X39: 大二 | Y39: 山西医科大学 | Z39: 第一临床医学院 | AA39: 临床医学（五年制）1 | AB39: 张一帆 | AC39: 5481690 | AD39: 张博奥 | AF39: 2025-07-16 11:28 | AG39: 张博奥 | AH39: 2025-07-16 11:30 | AI39: ZVVB26001 | AJ39: 六级暑假集训营（24H冲刺直播） | AK39: 国内考试 | AM39: 15600 | AO39: 张沛林 | AP39: 新签 | AQ39: 已交接 | AR39: BJWY25030q8UPI | AS39: BJWY1916743063 | AT39: ZVVB260010047 | AU39: 2025-07-16 | AW39: 回访人：张博奥，回访时间：2025-07-08 18:06，回访内容：张同学家长推荐，意向六级暑假集训营，和张沛林同学一起上课，加紧跟进；|回访人：张博奥，回访时间：2025-07-09 19:28，回访内容：张沛林家长推荐，准备上六级集训营，准备和张沛林一起上课，持续跟进；|回访人：张博奥，回访时间：2025-07-11 21:32，回访内容：改标签；|回访人：张博奥，回访时间：2025-07-12 20:54，回访内容：已出协议，待储值；|回访人：张博奥，回访时间：2025-07-16 11:28，回访内容：已报名 | BB39: 81411236 | BC39: 否 | BD39: 25下考季 | BE39: 暑假四级集训营 | BH39: 国内高校-双非 | BI39: 是 | BJ39: 请学管老师尽快联系，学生有住宿要求，请把张一帆和张沛林调到同一间房 | BL39: 报名 | BN39: 外地人外地大学(常规) | BO39: 客服
A40: 40 | B40: 北京大学部 | C40: 国内大学部 | D40: 闫士钧 | E40: 119413492 | F40: 段同飞 | G40: 2025-07-16 16:31:16 | H40: 李政老师老带新 | J40: 高三 | K40: 李政(离职) | L40: 转介绍 | M40: 顾问转介绍-老带新 | N40: 李政(离职)lizheng79_lz@xdf.cn | Q40: 闫士钧 | R40: 李政(离职) | S40: 29132506 | T40: 正常工单 | U40: 2025-07-16 16:37 | V40: A（六个月内有报课意向工单） | W40: 大学预科 | X40: 高三 | Y40: 北京市第三中学 | Z40: 新大一 | AA40: 新大一 | AB40: 闫士钧 | AC40: 5414897 | AD40: 李政(离职) | AF40: 2025-07-16 19:16 | AG40: 李政(离职) | AH40: 2025-07-16 19:16 | AI40: YKMJ25001 | AJ40: 大学预科数学（线上优享/新大一专属） | AK40: 国内考试 | AM40: 4180 | AO40: 李政 | AP40: 新签 | AQ40: 已交接 | AR40: BJWY25030q8UPI | AS40: BJWY8774395781 | AT40: YKMJ250010030 | AU40: 2025-07-16 | AW40: 回访人：李政(离职)，回访时间：2025-07-16 16:38，回访内容：确定要报名数学预科网课；|回访人：李政(离职)，回访时间：2025-07-16 18:35，回访内容：要签约了；|回访人：李政(离职)，回访时间：2025-07-16 19:16，回访内容：签约 | BB40: 81838702 | BC40: 否 | BH40: 普通学校-普高 | BI40: 是 | BL40: 报名 | BN40: 本地人本地大学(常规) | BO40: 客服
A41: 41 | B41: 北京大学部 | C41: 国内大学部 | D41: 佳禾妈 | E41: 118637697 | F41: 程远 | G41: 2025-07-11 16:21:35 | H41: 徐健坤； | J41: 大一 | K41: 徐健坤 | L41: 转介绍 | M41: 顾问转介绍-老带新 | N41: 张翊靖 | Q41: 栗佳禾 | R41: 徐健坤 | S41: 29040717 | T41: 正常工单 | U41: 2025-07-11 17:20 | V41: A（六个月内有报课意向工单） | W41: 六级,大学预科 | X41: 大一 | Y41: 首都师范大学附属玉泉学校 | Z41: 询问院系未告知 | AA41: 询问专业未告知 | AB41: 栗佳禾 | AC41: 5452860 | AD41: 徐健坤 | AF41: 2025-07-15 17:24 | AG41: 徐健坤 | AH41: 2025-07-15 17:26 | AI41: YKSJ25001 | AJ41: 六级无忧计划（线上优享/新大一专属） | AK41: 国内考试 | AM41: 5180 | AO41: 张翊靖 | AP41: 新签 | AQ41: 已交接 | AR41: BJWY24032w1g8X | AS41: BJWY5985267773 | AT41: YKSJ250010033 | AU41: 2025-07-15 | AW41: 回访人：徐健坤，回访时间：2025-07-11 17:20，回访内容：英语131 基础不错 数学禾口语不太考虑 考虑线上或小班 小班意向明显；|回访人：徐健坤，回访时间：2025-07-13 19:20，回访内容：要求周一联系；|回访人：徐健坤，回访时间：2025-07-14 20:54，回访内容：已经储值 等入团；|回访人：徐健坤，回访时间：2025-07-15 17:24，回访内容：签约 | BB41: 56616844 | BC41: 否 | BD41: 25下考季 | BE41: 六级无忧计划 | BH41: 普通学校-普高 | BI41: 是 | BL41: 报名 | BN41: 本地人本地大学(常规) | BO41: 客服
A42: 42 | B42: 北京大学部 | C42: 国内大学部 | D42: 王闯 | E42: 118808670 | F42: 吴凯龙 | G42: 2025-07-12 14:33:58 | H42: 宋增辉的顾问转介绍工单 | J42: 大一 | K42: 宋增辉 | L42: 转介绍 | M42: 顾问转介绍-老带新 | N42: 宋增辉songzenghui@xdf.cn | Q42: 陆昭坤 | R42: 宋增辉 | S42: 29047884 | T42: 正常工单 | U42: 2025-07-12 15:25 | V42: A（六个月内有报课意向工单） | W42: 六级,大学预科 | X42: 大一 | Y42: 人大附中本部 | Z42: 新大一 | AA42: 新大一 | AB42: 陆昭坤 | AC42: 5452365 | AD42: 宋增辉 | AF42: 2025-07-15 13:34 | AG42: 宋增辉 | AH42: 2025-07-15 13:34 | AI42: YKS25004 | AJ42: 六级精英计划（新大一专属） | AK42: 国内考试 | AM42: 19800 | AO42: 宋增辉 | AP42: 新签 | AQ42: 已交接 | AR42: WebReg | AS42: BJWY9563629636 | AT42: YKS250040015 | AU42: 2025-07-15 | AW42: 回访人：宋增辉，回访时间：2025-07-12 15:25，回访内容：试听课来了，看孩子上课情况；|回访人：宋增辉，回访时间：2025-07-12 18:34，回访内容：孩子学习没有问题，纠结学习四级还是六级，让孩子做一套四级真题后决定，规划的小班，或者大班搭配一对一去学；|回访人：宋增辉，回访时间：2025-07-14 14:48，回访内容：孩子做题看孩子适合四级还是六级 总结：客户确认试听课时间为下午两点，地点在西三环。客户到达后，通过刷门禁二维码进入大楼，校区位于B座五层。客户晚到五分钟，工作人员表示会下楼接应。客户到达后，孩子进入教室签到并开始试听，客户在等待期间出现头晕症状，但孩子继续听课。 下次回访建议：建议在回访时询问客户对试听课的满意度，了解孩子的学习进展，并关注客户的身体状况，确保其舒适度。同时，可提供更多关于课程和校区设施的信息，以便客户更好地了解。；|回访人：宋增辉，回访时间：2025-07-15 13:34，回访内容：已报名 | BB42: 81598181 | BC42: 否 | BD42: 25下考季 | BE42: 六级无忧计划 | BH42: 国内高校-双非 | BI42: 是 | BL42: 报名 | BN42: 本地人外地大学(归巢) | BO42: 客服
A43: 43 | B43: 北京大学部 | C43: 国内大学部 | D43: 老带新用户 | E43: 114887628 | F43: 房国超 | G43: 2025-06-17 19:56:54 | H43: 渠道录入来源：老带新系统 老生userid：4d21160f-6f3f-4236-88ae-cf24a39bca3f 老生学号：BJWY4512217138 老生姓名：戚颢严 产品类型：1 活动所属学校名称：北京大学事业部 老带新活动名称：邀好友，大家一起来省钱（班课专用）新 老带新活动id：2366032 推广邮箱：fangguochao@xdf.cn | I43: 2026财年第1财月老带新系统 | K43: 房国超 | L43: 转介绍 | M43: 老带新系统顾问 | N43: 房国超fangguochao@xdf.cn | Q43: 王艺蒙 | R43: 房国超 | S43: 28417405 | T43: 正常工单 | U43: 2025-07-14 10:16 | V43: A（六个月内有报课意向工单） | W43: 四级,大学预科 | X43: 高三 | Y43: 新大一 | Z43: 新大一 | AA43: 新大一 | AB43: 王艺蒙 | AC43: 5479587 | AD43: 房国超 | AF43: 2025-07-14 13:34 | AG43: 房国超 | AH43: 2025-07-14 13:34 | AI43: ZVVB26001 | AJ43: 六级暑假集训营（24H冲刺直播） | AK43: 国内考试 | AM43: 15600 | AO43: 房国超 | AP43: 新签 | AQ43: 已交接 | AR43: BJWY22035556hl | AS43: BJWY6541260474 | AT43: ZVVB260010043 | AU43: 2025-07-14 | AW43: 回访人：房国超，回访时间：2025-07-05 23:06，回访内容：想要之前优惠，年中优惠没了， 说孩子要报本地线下的班，预计死单；|回访人：房国超，回访时间：2025-07-09 22:00，回访内容：微信已沟通， 学生已报名当地课程，下次确认死单；|回访人：房国超，回访时间：2025-07-13 22:22，回访内容：二次确认，已报名当地课程；|回访人：杨沫，回访时间：2025-07-14 10:16，回访内容：杨沫恢复工单, 系统自动生成回访记录!；|回访人：房国超，回访时间：2025-07-14 13:34，回访内容：报名集训营 | BB43: 79927062 | BC43: 否 | BD43: 25下考季 | BE43: 暑假六级集训营 | BH43: 普通学校-普高 | BI43: 是 | BL43: 报名 | BO43: 老带新系统
